
package org.powerbot.game.api.methods.tab;

import org.powerbot.core.bot.handlers.ScriptHandler;
import org.powerbot.core.script.util.Timer;
import org.powerbot.core.script.methods.GroundItems;
import org.powerbot.game.api.wrappers.widget.WidgetChild;
import org.f;
import org.powerbot.game.api.util.node.Deque;
import org.powerbot.game.api.methods.interactive.NPCs;
import org.powerbot.game.api.wrappers.interactive.Character;
import org.powerbot.game.api.methods.interactive.Players;
import org.powerbot.game.api.util.Filter;
import org.powerbot.game.api.wrappers.interactive.NPC;
import org.powerbot.game.api.methods.Widgets;
import org.powerbot.game.api.methods.Settings;

public class Summoning
{
    public static final int WIDGET_FOLLOWER_DETAILS = 662;
    public static final int WIDGET_SUMMONING_ORB = 747;
    public static final int WIDGET_SET_LEFT = 880;
    public static final int WIDGET_INTERACT = 1188;
    private static final String[] z;
    
    public static int getPoints() {
        return Skills.getLevel(23);
    }
    
    public static int getSpecialPoints() {
        return Settings.get(1787);
    }
    
    public static boolean select(final Option option) {
        return select(option.getText());
    }
    
    public static boolean select(final String p0) {
        // 
        // This method could not be decompiled.
        // 
        // Original Bytecode:
        // 
        //     3: istore_2       
        //     4: getstatic       org/powerbot/game/api/methods/tab/Summoning.z:[Ljava/lang/String;
        //     7: bipush          12
        //     9: aaload         
        //    10: invokestatic    org/f.a:(Ljava/lang/String;)Ljava/lang/String;
        //    13: aload_0        
        //    14: invokevirtual   java/lang/String.toLowerCase:()Ljava/lang/String;
        //    17: invokevirtual   java/lang/String.contains:(Ljava/lang/CharSequence;)Z
        //    20: iload_2        
        //    21: ifne            143
        //    24: ifeq            127
        //    27: goto            31
        //    30: athrow         
        //    31: invokestatic    org/powerbot/game/api/methods/tab/Summoning.getEnum:()Lorg/powerbot/game/api/methods/tab/Summoning$Familiar;
        //    34: astore_1       
        //    35: aload_1        
        //    36: iload_2        
        //    37: ifne            48
        //    40: ifnull          125
        //    43: goto            47
        //    46: athrow         
        //    47: aload_1        
        //    48: invokevirtual   org/powerbot/game/api/methods/tab/Summoning$Familiar.getRequiredPoints:()I
        //    51: iload_2        
        //    52: ifne            84
        //    55: invokestatic    org/powerbot/game/api/methods/tab/Summoning.getPoints:()I
        //    58: if_icmpgt       125
        //    61: goto            65
        //    64: athrow         
        //    65: iconst_1       
        //    66: newarray        I
        //    68: dup            
        //    69: iconst_0       
        //    70: sipush          1831
        //    73: invokestatic    org/powerbot/game/api/methods/Settings.get:(I)I
        //    76: iastore        
        //    77: invokestatic    org/powerbot/game/api/methods/tab/Inventory.getCount:([I)I
        //    80: goto            84
        //    83: athrow         
        //    84: iload_2        
        //    85: ifne            110
        //    88: ifle            125
        //    91: goto            95
        //    94: athrow         
        //    95: sipush          747
        //    98: iconst_2       
        //    99: invokestatic    org/powerbot/game/api/methods/Widgets.get:(II)Lorg/powerbot/game/api/wrappers/widget/WidgetChild;
        //   102: aload_0        
        //   103: invokevirtual   org/powerbot/game/api/wrappers/widget/WidgetChild.interact:(Ljava/lang/String;)Z
        //   106: goto            110
        //   109: athrow         
        //   110: iload_2        
        //   111: ifne            122
        //   114: ifeq            125
        //   117: goto            121
        //   120: athrow         
        //   121: iconst_1       
        //   122: goto            126
        //   125: iconst_0       
        //   126: ireturn        
        //   127: getstatic       org/powerbot/game/api/methods/tab/Summoning.z:[Ljava/lang/String;
        //   130: bipush          13
        //   132: aaload         
        //   133: invokestatic    org/powerbot/game/api/util/node/Deque.e:(Ljava/lang/String;)Ljava/lang/String;
        //   136: aload_0        
        //   137: invokevirtual   java/lang/String.toLowerCase:()Ljava/lang/String;
        //   140: invokevirtual   java/lang/String.contains:(Ljava/lang/CharSequence;)Z
        //   143: iload_2        
        //   144: ifne            262
        //   147: ifeq            246
        //   150: goto            154
        //   153: athrow         
        //   154: sipush          747
        //   157: iconst_2       
        //   158: invokestatic    org/powerbot/game/api/methods/Widgets.get:(II)Lorg/powerbot/game/api/wrappers/widget/WidgetChild;
        //   161: aload_0        
        //   162: invokevirtual   org/powerbot/game/api/wrappers/widget/WidgetChild.interact:(Ljava/lang/String;)Z
        //   165: iload_2        
        //   166: ifne            245
        //   169: goto            173
        //   172: athrow         
        //   173: ifeq            244
        //   176: goto            180
        //   179: athrow         
        //   180: iconst_0       
        //   181: istore_1       
        //   182: iload_1        
        //   183: bipush          50
        //   185: if_icmpge       232
        //   188: sipush          1188
        //   191: invokestatic    org/powerbot/game/api/methods/Widgets.get:(I)Lorg/powerbot/game/api/wrappers/widget/Widget;
        //   194: invokevirtual   org/powerbot/game/api/wrappers/widget/Widget.validate:()Z
        //   197: iload_2        
        //   198: ifne            243
        //   201: iload_2        
        //   202: ifne            243
        //   205: goto            209
        //   208: athrow         
        //   209: ifne            232
        //   212: goto            216
        //   215: athrow         
        //   216: bipush          20
        //   218: invokestatic    org/powerbot/core/script/job/Task.sleep:(I)V
        //   221: iinc            1, 1
        //   224: iload_2        
        //   225: ifeq            182
        //   228: goto            232
        //   231: athrow         
        //   232: sipush          1188
        //   235: iconst_3       
        //   236: invokestatic    org/powerbot/game/api/methods/Widgets.get:(II)Lorg/powerbot/game/api/wrappers/widget/WidgetChild;
        //   239: iconst_1       
        //   240: invokevirtual   org/powerbot/game/api/wrappers/widget/WidgetChild.click:(Z)Z
        //   243: ireturn        
        //   244: iconst_0       
        //   245: ireturn        
        //   246: getstatic       org/powerbot/game/api/methods/tab/Summoning.z:[Ljava/lang/String;
        //   249: bipush          11
        //   251: aaload         
        //   252: invokestatic    org/f.a:(Ljava/lang/String;)Ljava/lang/String;
        //   255: aload_0        
        //   256: invokevirtual   java/lang/String.toLowerCase:()Ljava/lang/String;
        //   259: invokevirtual   java/lang/String.contains:(Ljava/lang/CharSequence;)Z
        //   262: iload_2        
        //   263: ifne            350
        //   266: ifeq            339
        //   269: goto            273
        //   272: athrow         
        //   273: invokestatic    org/powerbot/game/api/methods/tab/Summoning.getEnum:()Lorg/powerbot/game/api/methods/tab/Summoning$Familiar;
        //   276: astore_1       
        //   277: aload_1        
        //   278: iload_2        
        //   279: ifne            290
        //   282: ifnull          337
        //   285: goto            289
        //   288: athrow         
        //   289: aload_1        
        //   290: invokevirtual   org/powerbot/game/api/methods/tab/Summoning$Familiar.getRequiredSpecialPoints:()I
        //   293: invokestatic    org/powerbot/game/api/methods/tab/Summoning.getSpecialPoints:()I
        //   296: iload_2        
        //   297: ifne            315
        //   300: if_icmpgt       337
        //   303: goto            307
        //   306: athrow         
        //   307: sipush          747
        //   310: iconst_2       
        //   311: goto            315
        //   314: athrow         
        //   315: invokestatic    org/powerbot/game/api/methods/Widgets.get:(II)Lorg/powerbot/game/api/wrappers/widget/WidgetChild;
        //   318: aload_0        
        //   319: invokevirtual   org/powerbot/game/api/wrappers/widget/WidgetChild.interact:(Ljava/lang/String;)Z
        //   322: iload_2        
        //   323: ifne            334
        //   326: ifeq            337
        //   329: goto            333
        //   332: athrow         
        //   333: iconst_1       
        //   334: goto            338
        //   337: iconst_0       
        //   338: ireturn        
        //   339: sipush          747
        //   342: iconst_2       
        //   343: invokestatic    org/powerbot/game/api/methods/Widgets.get:(II)Lorg/powerbot/game/api/wrappers/widget/WidgetChild;
        //   346: aload_0        
        //   347: invokevirtual   org/powerbot/game/api/wrappers/widget/WidgetChild.interact:(Ljava/lang/String;)Z
        //   350: ireturn        
        //    StackMapTable: 00 36 FF 00 1E 00 03 07 00 69 00 01 00 01 07 00 FB 00 FF 00 0E 00 03 07 00 69 07 00 39 01 00 01 07 00 FB 00 40 07 00 39 4F 07 00 FB 00 51 07 00 FB 40 01 49 07 00 FB 00 4D 07 00 FB 40 01 49 07 00 FB 00 40 01 02 40 01 FF 00 00 00 03 07 00 69 00 01 00 00 4F 01 49 07 00 FB 00 51 07 00 FB 40 01 45 07 00 FB 00 FF 00 01 00 03 07 00 69 01 01 00 00 59 07 00 FB 40 01 45 07 00 FB 00 4E 07 00 FB 00 4A 01 FF 00 00 00 03 07 00 69 00 01 00 00 40 01 00 4F 01 49 07 00 FB 00 FF 00 0E 00 03 07 00 69 07 00 39 01 00 01 07 00 FB 00 40 07 00 39 4F 07 00 FB 00 46 07 00 FB FF 00 00 00 03 07 00 69 07 00 39 01 00 02 01 01 50 07 00 FB 00 40 01 02 40 01 FF 00 00 00 03 07 00 69 00 01 00 00 4A 01
        //    Exceptions:
        //  Try           Handler
        //  Start  End    Start  End    Type                        
        //  -----  -----  -----  -----  ----------------------------
        //  315    329    332    333    Ljava/lang/RuntimeException;
        //  300    311    314    315    Ljava/lang/RuntimeException;
        //  290    303    306    307    Ljava/lang/RuntimeException;
        //  277    285    288    289    Ljava/lang/RuntimeException;
        //  262    269    272    273    Ljava/lang/RuntimeException;
        //  209    228    231    232    Ljava/lang/RuntimeException;
        //  201    212    215    216    Ljava/lang/RuntimeException;
        //  188    205    208    209    Ljava/lang/RuntimeException;
        //  154    176    179    180    Ljava/lang/RuntimeException;
        //  147    169    172    173    Ljava/lang/RuntimeException;
        //  143    150    153    154    Ljava/lang/RuntimeException;
        //  110    117    120    121    Ljava/lang/RuntimeException;
        //  88     106    109    110    Ljava/lang/RuntimeException;
        //  84     91     94     95     Ljava/lang/RuntimeException;
        //  55     80     83     84     Ljava/lang/RuntimeException;
        //  48     61     64     65     Ljava/lang/RuntimeException;
        //  35     43     46     47     Ljava/lang/RuntimeException;
        //  4      27     30     31     Ljava/lang/RuntimeException;
        // 
        // The error that occurred was:
        // 
        // java.lang.IllegalStateException: Expression is linked from several locations: Label_0154:
        //     at com.strobel.decompiler.ast.Error.expressionLinkedFromMultipleLocations(Error.java:27)
        //     at com.strobel.decompiler.ast.AstOptimizer.mergeDisparateObjectInitializations(AstOptimizer.java:2596)
        //     at com.strobel.decompiler.ast.AstOptimizer.optimize(AstOptimizer.java:235)
        //     at com.strobel.decompiler.ast.AstOptimizer.optimize(AstOptimizer.java:42)
        //     at com.strobel.decompiler.languages.java.ast.AstMethodBodyBuilder.createMethodBody(AstMethodBodyBuilder.java:214)
        //     at com.strobel.decompiler.languages.java.ast.AstMethodBodyBuilder.createMethodBody(AstMethodBodyBuilder.java:99)
        //     at com.strobel.decompiler.languages.java.ast.AstBuilder.createMethodBody(AstBuilder.java:782)
        //     at com.strobel.decompiler.languages.java.ast.AstBuilder.createMethod(AstBuilder.java:675)
        //     at com.strobel.decompiler.languages.java.ast.AstBuilder.addTypeMembers(AstBuilder.java:552)
        //     at com.strobel.decompiler.languages.java.ast.AstBuilder.createTypeCore(AstBuilder.java:519)
        //     at com.strobel.decompiler.languages.java.ast.AstBuilder.createTypeNoCache(AstBuilder.java:161)
        //     at com.strobel.decompiler.languages.java.ast.AstBuilder.createType(AstBuilder.java:150)
        //     at com.strobel.decompiler.languages.java.ast.AstBuilder.addType(AstBuilder.java:125)
        //     at com.strobel.decompiler.languages.java.JavaLanguage.buildAst(JavaLanguage.java:71)
        //     at com.strobel.decompiler.languages.java.JavaLanguage.decompileType(JavaLanguage.java:59)
        //     at com.strobel.decompiler.DecompilerDriver.decompileType(DecompilerDriver.java:330)
        //     at com.strobel.decompiler.DecompilerDriver.decompileJar(DecompilerDriver.java:251)
        //     at com.strobel.decompiler.DecompilerDriver.main(DecompilerDriver.java:126)
        // 
        throw new IllegalStateException("An error occurred while decompiling this method.");
    }
    
    public static Option getLeftClickOption() {
        // 
        // This method could not be decompiled.
        // 
        // Original Bytecode:
        // 
        //     3: istore          4
        //     5: invokestatic    org/powerbot/game/api/methods/tab/Summoning$Option.values:()[Lorg/powerbot/game/api/methods/tab/Summoning$Option;
        //     8: astore_0       
        //     9: aload_0        
        //    10: arraylength    
        //    11: istore_1       
        //    12: iconst_0       
        //    13: istore_2       
        //    14: iload_2        
        //    15: iload_1        
        //    16: if_icmpge       59
        //    19: aload_0        
        //    20: iload_2        
        //    21: aaload         
        //    22: astore_3       
        //    23: iload           4
        //    25: ifne            54
        //    28: aload_3        
        //    29: iload           4
        //    31: ifne            62
        //    34: goto            38
        //    37: athrow         
        //    38: invokevirtual   org/powerbot/game/api/methods/tab/Summoning$Option.isSetLeft:()Z
        //    41: ifeq            51
        //    44: goto            48
        //    47: athrow         
        //    48: aload_3        
        //    49: areturn        
        //    50: athrow         
        //    51: iinc            2, 1
        //    54: iload           4
        //    56: ifeq            14
        //    59: getstatic       org/powerbot/game/api/methods/tab/Summoning$Option.FOLLOWER_DETAILS:Lorg/powerbot/game/api/methods/tab/Summoning$Option;
        //    62: areturn        
        //    StackMapTable: 00 0A FF 00 0E 00 05 07 01 0D 01 01 00 01 00 00 FF 00 16 00 05 07 01 0D 01 01 07 00 36 01 00 01 07 00 FB 40 07 00 36 48 07 00 FB 00 41 07 00 FB 00 02 FF 00 04 00 05 07 01 0D 01 01 00 01 00 00 42 07 00 36
        //    Exceptions:
        //  Try           Handler
        //  Start  End    Start  End    Type                        
        //  -----  -----  -----  -----  ----------------------------
        //  38     50     50     51     Ljava/lang/RuntimeException;
        //  28     44     47     48     Ljava/lang/RuntimeException;
        //  23     34     37     38     Ljava/lang/RuntimeException;
        // 
        // The error that occurred was:
        // 
        // java.lang.IllegalStateException: Expression is linked from several locations: Label_0038:
        //     at com.strobel.decompiler.ast.Error.expressionLinkedFromMultipleLocations(Error.java:27)
        //     at com.strobel.decompiler.ast.AstOptimizer.mergeDisparateObjectInitializations(AstOptimizer.java:2596)
        //     at com.strobel.decompiler.ast.AstOptimizer.optimize(AstOptimizer.java:235)
        //     at com.strobel.decompiler.ast.AstOptimizer.optimize(AstOptimizer.java:42)
        //     at com.strobel.decompiler.languages.java.ast.AstMethodBodyBuilder.createMethodBody(AstMethodBodyBuilder.java:214)
        //     at com.strobel.decompiler.languages.java.ast.AstMethodBodyBuilder.createMethodBody(AstMethodBodyBuilder.java:99)
        //     at com.strobel.decompiler.languages.java.ast.AstBuilder.createMethodBody(AstBuilder.java:782)
        //     at com.strobel.decompiler.languages.java.ast.AstBuilder.createMethod(AstBuilder.java:675)
        //     at com.strobel.decompiler.languages.java.ast.AstBuilder.addTypeMembers(AstBuilder.java:552)
        //     at com.strobel.decompiler.languages.java.ast.AstBuilder.createTypeCore(AstBuilder.java:519)
        //     at com.strobel.decompiler.languages.java.ast.AstBuilder.createTypeNoCache(AstBuilder.java:161)
        //     at com.strobel.decompiler.languages.java.ast.AstBuilder.createType(AstBuilder.java:150)
        //     at com.strobel.decompiler.languages.java.ast.AstBuilder.addType(AstBuilder.java:125)
        //     at com.strobel.decompiler.languages.java.JavaLanguage.buildAst(JavaLanguage.java:71)
        //     at com.strobel.decompiler.languages.java.JavaLanguage.decompileType(JavaLanguage.java:59)
        //     at com.strobel.decompiler.DecompilerDriver.decompileType(DecompilerDriver.java:330)
        //     at com.strobel.decompiler.DecompilerDriver.decompileJar(DecompilerDriver.java:251)
        //     at com.strobel.decompiler.DecompilerDriver.main(DecompilerDriver.java:126)
        // 
        throw new IllegalStateException("An error occurred while decompiling this method.");
    }
    
    public static boolean setLeftClickOption(final Option p0) {
        // 
        // This method could not be decompiled.
        // 
        // Original Bytecode:
        // 
        //     3: istore_3       
        //     4: aload_0        
        //     5: invokevirtual   org/powerbot/game/api/methods/tab/Summoning$Option.isSetLeft:()Z
        //     8: iload_3        
        //     9: ifne            41
        //    12: ifeq            22
        //    15: goto            19
        //    18: athrow         
        //    19: iconst_1       
        //    20: ireturn        
        //    21: athrow         
        //    22: sipush          747
        //    25: iconst_2       
        //    26: invokestatic    org/powerbot/game/api/methods/Widgets.get:(II)Lorg/powerbot/game/api/wrappers/widget/WidgetChild;
        //    29: getstatic       org/powerbot/game/api/methods/tab/Summoning.z:[Ljava/lang/String;
        //    32: bipush          9
        //    34: aaload         
        //    35: invokestatic    org/powerbot/game/api/util/node/Deque.e:(Ljava/lang/String;)Ljava/lang/String;
        //    38: invokevirtual   org/powerbot/game/api/wrappers/widget/WidgetChild.interact:(Ljava/lang/String;)Z
        //    41: iload_3        
        //    42: ifne            333
        //    45: ifeq            332
        //    48: goto            52
        //    51: athrow         
        //    52: invokestatic    org/powerbot/game/api/methods/tab/Summoning.isFamiliarSummoned:()Z
        //    55: ifne            140
        //    58: goto            62
        //    61: athrow         
        //    62: new             Lorg/powerbot/game/api/util/Timer;
        //    65: dup            
        //    66: ldc2_w          800
        //    69: invokespecial   org/powerbot/game/api/util/Timer.<init>:(J)V
        //    72: astore_1       
        //    73: aload_1        
        //    74: invokevirtual   org/powerbot/game/api/util/Timer.isRunning:()Z
        //    77: ifeq            115
        //    80: invokestatic    org/powerbot/game/api/methods/node/Menu.isOpen:()Z
        //    83: iload_3        
        //    84: ifne            127
        //    87: iload_3        
        //    88: ifne            127
        //    91: goto            95
        //    94: athrow         
        //    95: ifne            115
        //    98: goto            102
        //   101: athrow         
        //   102: bipush          15
        //   104: invokestatic    org/powerbot/core/script/job/Task.sleep:(I)V
        //   107: iload_3        
        //   108: ifeq            73
        //   111: goto            115
        //   114: athrow         
        //   115: getstatic       org/powerbot/game/api/methods/tab/Summoning.z:[Ljava/lang/String;
        //   118: bipush          7
        //   120: aaload         
        //   121: invokestatic    org/f.a:(Ljava/lang/String;)Ljava/lang/String;
        //   124: invokestatic    org/powerbot/game/api/methods/node/Menu.select:(Ljava/lang/String;)Z
        //   127: iload_3        
        //   128: ifne            139
        //   131: ifne            140
        //   134: goto            138
        //   137: athrow         
        //   138: iconst_0       
        //   139: ireturn        
        //   140: new             Lorg/powerbot/game/api/util/Timer;
        //   143: dup            
        //   144: ldc2_w          2000
        //   147: invokespecial   org/powerbot/game/api/util/Timer.<init>:(J)V
        //   150: astore_1       
        //   151: aload_1        
        //   152: invokevirtual   org/powerbot/game/api/util/Timer.isRunning:()Z
        //   155: ifeq            199
        //   158: sipush          880
        //   161: invokestatic    org/powerbot/game/api/methods/Widgets.get:(I)Lorg/powerbot/game/api/wrappers/widget/Widget;
        //   164: invokevirtual   org/powerbot/game/api/wrappers/widget/Widget.validate:()Z
        //   167: iload_3        
        //   168: ifne            221
        //   171: iload_3        
        //   172: ifne            221
        //   175: goto            179
        //   178: athrow         
        //   179: ifne            199
        //   182: goto            186
        //   185: athrow         
        //   186: bipush          15
        //   188: invokestatic    org/powerbot/core/script/job/Task.sleep:(I)V
        //   191: iload_3        
        //   192: ifeq            151
        //   195: goto            199
        //   198: athrow         
        //   199: sipush          200
        //   202: invokestatic    org/powerbot/core/script/job/Task.sleep:(I)V
        //   205: aload_0        
        //   206: invokevirtual   org/powerbot/game/api/methods/tab/Summoning$Option.getWidgetChild:()Lorg/powerbot/game/api/wrappers/widget/WidgetChild;
        //   209: getstatic       org/powerbot/game/api/methods/tab/Summoning.z:[Ljava/lang/String;
        //   212: bipush          9
        //   214: aaload         
        //   215: invokestatic    org/powerbot/game/api/util/node/Deque.e:(Ljava/lang/String;)Ljava/lang/String;
        //   218: invokevirtual   org/powerbot/game/api/wrappers/widget/WidgetChild.interact:(Ljava/lang/String;)Z
        //   221: iload_3        
        //   222: ifne            311
        //   225: ifeq            286
        //   228: goto            232
        //   231: athrow         
        //   232: new             Lorg/powerbot/game/api/util/Timer;
        //   235: dup            
        //   236: ldc2_w          800
        //   239: invokespecial   org/powerbot/game/api/util/Timer.<init>:(J)V
        //   242: astore_2       
        //   243: aload_2        
        //   244: invokevirtual   org/powerbot/game/api/util/Timer.isRunning:()Z
        //   247: ifeq            282
        //   250: aload_0        
        //   251: invokevirtual   org/powerbot/game/api/methods/tab/Summoning$Option.isSelected:()Z
        //   254: iload_3        
        //   255: ifne            331
        //   258: iload_3        
        //   259: ifne            275
        //   262: goto            266
        //   265: athrow         
        //   266: ifne            282
        //   269: goto            273
        //   272: athrow         
        //   273: bipush          15
        //   275: invokestatic    org/powerbot/core/script/job/Task.sleep:(I)V
        //   278: iload_3        
        //   279: ifeq            243
        //   282: iload_3        
        //   283: ifeq            312
        //   286: sipush          880
        //   289: iconst_5       
        //   290: invokestatic    org/powerbot/game/api/methods/Widgets.get:(II)Lorg/powerbot/game/api/wrappers/widget/WidgetChild;
        //   293: getstatic       org/powerbot/game/api/methods/tab/Summoning.z:[Ljava/lang/String;
        //   296: bipush          8
        //   298: aaload         
        //   299: invokestatic    org/f.a:(Ljava/lang/String;)Ljava/lang/String;
        //   302: invokevirtual   org/powerbot/game/api/wrappers/widget/WidgetChild.interact:(Ljava/lang/String;)Z
        //   305: pop            
        //   306: iconst_0       
        //   307: goto            311
        //   310: athrow         
        //   311: ireturn        
        //   312: sipush          880
        //   315: iconst_5       
        //   316: invokestatic    org/powerbot/game/api/methods/Widgets.get:(II)Lorg/powerbot/game/api/wrappers/widget/WidgetChild;
        //   319: getstatic       org/powerbot/game/api/methods/tab/Summoning.z:[Ljava/lang/String;
        //   322: bipush          6
        //   324: aaload         
        //   325: invokestatic    org/powerbot/game/api/util/node/Deque.e:(Ljava/lang/String;)Ljava/lang/String;
        //   328: invokevirtual   org/powerbot/game/api/wrappers/widget/WidgetChild.interact:(Ljava/lang/String;)Z
        //   331: ireturn        
        //   332: iconst_0       
        //   333: ireturn        
        //    StackMapTable: 00 2D FF 00 12 00 04 07 00 36 00 00 01 00 01 07 00 FB 00 41 07 00 FB 00 52 01 49 07 00 FB 00 48 07 00 FB 00 FF 00 0A 00 04 07 00 36 07 00 18 00 01 00 00 54 07 00 FB 40 01 45 07 00 FB 00 4B 07 00 FB 00 4B 01 49 07 00 FB 00 40 01 FF 00 00 00 04 07 00 36 00 00 01 00 00 FF 00 0A 00 04 07 00 36 07 00 18 00 01 00 00 5A 07 00 FB 40 01 45 07 00 FB 00 4B 07 00 FB 00 55 01 49 07 00 FB 00 FF 00 0A 00 04 07 00 36 07 00 18 07 00 18 01 00 00 55 07 00 FB 40 01 45 07 00 FB 00 41 01 06 FF 00 03 00 04 07 00 36 07 00 18 00 01 00 00 57 07 00 FB 40 01 FF 00 00 00 04 07 00 36 07 00 18 07 00 18 01 00 00 52 01 FF 00 00 00 04 07 00 36 00 00 01 00 00 40 01
        //    Exceptions:
        //  Try           Handler
        //  Start  End    Start  End    Type                        
        //  -----  -----  -----  -----  ----------------------------
        //  282    307    310    311    Ljava/lang/RuntimeException;
        //  258    269    272    273    Ljava/lang/RuntimeException;
        //  250    262    265    266    Ljava/lang/RuntimeException;
        //  221    228    231    232    Ljava/lang/RuntimeException;
        //  179    195    198    199    Ljava/lang/RuntimeException;
        //  171    182    185    186    Ljava/lang/RuntimeException;
        //  158    175    178    179    Ljava/lang/RuntimeException;
        //  127    134    137    138    Ljava/lang/RuntimeException;
        //  95     111    114    115    Ljava/lang/RuntimeException;
        //  87     98     101    102    Ljava/lang/RuntimeException;
        //  80     91     94     95     Ljava/lang/RuntimeException;
        //  45     58     61     62     Ljava/lang/RuntimeException;
        //  41     48     51     52     Ljava/lang/RuntimeException;
        //  12     21     21     22     Ljava/lang/RuntimeException;
        //  4      15     18     19     Ljava/lang/RuntimeException;
        // 
        // The error that occurred was:
        // 
        // java.lang.IllegalStateException: Expression is linked from several locations: Label_0095:
        //     at com.strobel.decompiler.ast.Error.expressionLinkedFromMultipleLocations(Error.java:27)
        //     at com.strobel.decompiler.ast.AstOptimizer.mergeDisparateObjectInitializations(AstOptimizer.java:2596)
        //     at com.strobel.decompiler.ast.AstOptimizer.optimize(AstOptimizer.java:235)
        //     at com.strobel.decompiler.ast.AstOptimizer.optimize(AstOptimizer.java:42)
        //     at com.strobel.decompiler.languages.java.ast.AstMethodBodyBuilder.createMethodBody(AstMethodBodyBuilder.java:214)
        //     at com.strobel.decompiler.languages.java.ast.AstMethodBodyBuilder.createMethodBody(AstMethodBodyBuilder.java:99)
        //     at com.strobel.decompiler.languages.java.ast.AstBuilder.createMethodBody(AstBuilder.java:782)
        //     at com.strobel.decompiler.languages.java.ast.AstBuilder.createMethod(AstBuilder.java:675)
        //     at com.strobel.decompiler.languages.java.ast.AstBuilder.addTypeMembers(AstBuilder.java:552)
        //     at com.strobel.decompiler.languages.java.ast.AstBuilder.createTypeCore(AstBuilder.java:519)
        //     at com.strobel.decompiler.languages.java.ast.AstBuilder.createTypeNoCache(AstBuilder.java:161)
        //     at com.strobel.decompiler.languages.java.ast.AstBuilder.createType(AstBuilder.java:150)
        //     at com.strobel.decompiler.languages.java.ast.AstBuilder.addType(AstBuilder.java:125)
        //     at com.strobel.decompiler.languages.java.JavaLanguage.buildAst(JavaLanguage.java:71)
        //     at com.strobel.decompiler.languages.java.JavaLanguage.decompileType(JavaLanguage.java:59)
        //     at com.strobel.decompiler.DecompilerDriver.decompileType(DecompilerDriver.java:330)
        //     at com.strobel.decompiler.DecompilerDriver.decompileJar(DecompilerDriver.java:251)
        //     at com.strobel.decompiler.DecompilerDriver.main(DecompilerDriver.java:126)
        // 
        throw new IllegalStateException("An error occurred while decompiling this method.");
    }
    
    public static boolean isCastOrAttackSelected() {
        int borderThickness = 0;
        Label_0024: {
            int n;
            try {
                n = (borderThickness = Widgets.get(747, 2).getBorderThickness());
                if (Inventory.a != 0) {
                    return borderThickness != 0;
                }
                final int n2 = 2;
                if (n == n2) {
                    break Label_0024;
                }
                return false;
            }
            catch (RuntimeException ex) {
                throw ex;
            }
            try {
                final int n2 = 2;
                if (n != n2) {
                    return false;
                }
                borderThickness = 1;
            }
            catch (RuntimeException ex2) {
                throw ex2;
            }
        }
        return borderThickness != 0;
        borderThickness = 0;
        return borderThickness != 0;
    }
    
    public static int getTimeLeft() {
        return Math.round(Settings.get(1786) / 2.1333334f);
    }
    
    public static boolean isFamiliarSummoned() {
        final int a = Inventory.a;
        Label_0028: {
            int timeLeft = 0;
            int value = 0;
            Label_0018: {
                int n;
                try {
                    n = (value = (timeLeft = getTimeLeft()));
                    if (a != 0) {
                        break Label_0028;
                    }
                    if (n > 0) {
                        break Label_0018;
                    }
                    return false;
                }
                catch (RuntimeException ex) {
                    throw ex;
                }
                try {
                    if (n <= 0) {
                        return false;
                    }
                    timeLeft = (value = Settings.get(1831));
                }
                catch (RuntimeException ex2) {
                    throw ex2;
                }
            }
            try {
                if (a != 0) {
                    return timeLeft != 0;
                }
                if (value <= 0) {
                    return false;
                }
            }
            catch (RuntimeException ex3) {
                throw ex3;
            }
        }
        int timeLeft = true ? 1 : 0;
        return timeLeft != 0;
        timeLeft = (false ? 1 : 0);
        return timeLeft != 0;
    }
    
    public static boolean summonFamiliar(final Familiar p0) {
        // 
        // This method could not be decompiled.
        // 
        // Original Bytecode:
        // 
        //     3: istore_1       
        //     4: iconst_1       
        //     5: newarray        I
        //     7: dup            
        //     8: iconst_0       
        //     9: aload_0        
        //    10: invokevirtual   org/powerbot/game/api/methods/tab/Summoning$Familiar.getPouchId:()I
        //    13: iastore        
        //    14: invokestatic    org/powerbot/game/api/methods/tab/Inventory.getCount:([I)I
        //    17: iload_1        
        //    18: ifne            37
        //    21: ifle            120
        //    24: goto            28
        //    27: athrow         
        //    28: bipush          23
        //    30: invokestatic    org/powerbot/game/api/methods/tab/Skills.getRealLevel:(I)I
        //    33: goto            37
        //    36: athrow         
        //    37: aload_0        
        //    38: invokevirtual   org/powerbot/game/api/methods/tab/Summoning$Familiar.getRequiredLevel:()I
        //    41: iload_1        
        //    42: ifne            71
        //    45: if_icmplt       120
        //    48: goto            52
        //    51: athrow         
        //    52: invokestatic    org/powerbot/game/api/methods/tab/Summoning.getPoints:()I
        //    55: iload_1        
        //    56: ifne            105
        //    59: goto            63
        //    62: athrow         
        //    63: aload_0        
        //    64: invokevirtual   org/powerbot/game/api/methods/tab/Summoning$Familiar.getRequiredPoints:()I
        //    67: goto            71
        //    70: athrow         
        //    71: if_icmplt       120
        //    74: iconst_1       
        //    75: newarray        I
        //    77: dup            
        //    78: iconst_0       
        //    79: aload_0        
        //    80: invokevirtual   org/powerbot/game/api/methods/tab/Summoning$Familiar.getPouchId:()I
        //    83: iastore        
        //    84: invokestatic    org/powerbot/game/api/methods/tab/Inventory.getItem:([I)Lorg/powerbot/game/api/wrappers/node/Item;
        //    87: invokevirtual   org/powerbot/game/api/wrappers/node/Item.getWidgetChild:()Lorg/powerbot/game/api/wrappers/widget/WidgetChild;
        //    90: getstatic       org/powerbot/game/api/methods/tab/Summoning.z:[Ljava/lang/String;
        //    93: iconst_3       
        //    94: aaload         
        //    95: invokestatic    org/f.a:(Ljava/lang/String;)Ljava/lang/String;
        //    98: invokevirtual   org/powerbot/game/api/wrappers/widget/WidgetChild.interact:(Ljava/lang/String;)Z
        //   101: goto            105
        //   104: athrow         
        //   105: iload_1        
        //   106: ifne            117
        //   109: ifeq            120
        //   112: goto            116
        //   115: athrow         
        //   116: iconst_1       
        //   117: goto            121
        //   120: iconst_0       
        //   121: ireturn        
        //    StackMapTable: 00 11 FF 00 1B 00 02 07 00 39 01 00 01 07 00 FB 00 47 07 00 FB 40 01 4D 07 00 FB 00 49 07 00 FB 40 01 46 07 00 FB FF 00 00 00 02 07 00 39 01 00 02 01 01 60 07 00 FB 40 01 49 07 00 FB 00 40 01 02 40 01
        //    Exceptions:
        //  Try           Handler
        //  Start  End    Start  End    Type                        
        //  -----  -----  -----  -----  ----------------------------
        //  105    112    115    116    Ljava/lang/RuntimeException;
        //  71     101    104    105    Ljava/lang/RuntimeException;
        //  52     67     70     71     Ljava/lang/RuntimeException;
        //  45     59     62     63     Ljava/lang/RuntimeException;
        //  37     48     51     52     Ljava/lang/RuntimeException;
        //  21     33     36     37     Ljava/lang/RuntimeException;
        //  4      24     27     28     Ljava/lang/RuntimeException;
        // 
        // The error that occurred was:
        // 
        // java.lang.IllegalStateException: Expression is linked from several locations: Label_0052:
        //     at com.strobel.decompiler.ast.Error.expressionLinkedFromMultipleLocations(Error.java:27)
        //     at com.strobel.decompiler.ast.AstOptimizer.mergeDisparateObjectInitializations(AstOptimizer.java:2596)
        //     at com.strobel.decompiler.ast.AstOptimizer.optimize(AstOptimizer.java:235)
        //     at com.strobel.decompiler.ast.AstOptimizer.optimize(AstOptimizer.java:42)
        //     at com.strobel.decompiler.languages.java.ast.AstMethodBodyBuilder.createMethodBody(AstMethodBodyBuilder.java:214)
        //     at com.strobel.decompiler.languages.java.ast.AstMethodBodyBuilder.createMethodBody(AstMethodBodyBuilder.java:99)
        //     at com.strobel.decompiler.languages.java.ast.AstBuilder.createMethodBody(AstBuilder.java:782)
        //     at com.strobel.decompiler.languages.java.ast.AstBuilder.createMethod(AstBuilder.java:675)
        //     at com.strobel.decompiler.languages.java.ast.AstBuilder.addTypeMembers(AstBuilder.java:552)
        //     at com.strobel.decompiler.languages.java.ast.AstBuilder.createTypeCore(AstBuilder.java:519)
        //     at com.strobel.decompiler.languages.java.ast.AstBuilder.createTypeNoCache(AstBuilder.java:161)
        //     at com.strobel.decompiler.languages.java.ast.AstBuilder.createType(AstBuilder.java:150)
        //     at com.strobel.decompiler.languages.java.ast.AstBuilder.addType(AstBuilder.java:125)
        //     at com.strobel.decompiler.languages.java.JavaLanguage.buildAst(JavaLanguage.java:71)
        //     at com.strobel.decompiler.languages.java.JavaLanguage.decompileType(JavaLanguage.java:59)
        //     at com.strobel.decompiler.DecompilerDriver.decompileType(DecompilerDriver.java:330)
        //     at com.strobel.decompiler.DecompilerDriver.decompileJar(DecompilerDriver.java:251)
        //     at com.strobel.decompiler.DecompilerDriver.main(DecompilerDriver.java:126)
        // 
        throw new IllegalStateException("An error occurred while decompiling this method.");
    }
    
    public static NPC getFamiliar() {
        try {
            if (!isFamiliarSummoned()) {
                return null;
            }
        }
        catch (RuntimeException ex) {
            throw ex;
        }
        return NPCs.getNearest(new Filter<NPC>() {
            @Override
            public boolean accept(final NPC npc) {
                final int a = Inventory.a;
                boolean equals = false;
                Label_0073: {
                    Label_0052: {
                        Character interacting = null;
                        Label_0044: {
                            NPC interacting2 = null;
                            Label_0033: {
                                Label_0025: {
                                    try {
                                        interacting = npc;
                                        interacting2 = npc;
                                        if (a != 0) {
                                            break Label_0033;
                                        }
                                        final int n = npc.getId();
                                        final int n2 = 1784;
                                        final int n3 = Settings.get(n2);
                                        if (n == n3) {
                                            break Label_0025;
                                        }
                                        break Label_0073;
                                    }
                                    catch (RuntimeException ex) {
                                        throw ex;
                                    }
                                    try {
                                        final int n = npc.getId();
                                        final int n2 = 1784;
                                        final int n3 = Settings.get(n2);
                                        if (n != n3) {
                                            break Label_0073;
                                        }
                                        interacting = (interacting2 = (NPC)npc.getInteracting());
                                    }
                                    catch (RuntimeException ex2) {
                                        throw ex2;
                                    }
                                }
                                try {
                                    if (a != 0) {
                                        break Label_0052;
                                    }
                                    if (interacting2 != null) {
                                        break Label_0044;
                                    }
                                    break Label_0073;
                                }
                                catch (RuntimeException ex3) {
                                    throw ex3;
                                }
                            }
                            try {
                                if (interacting2 == null) {
                                    break Label_0073;
                                }
                                interacting = npc.getInteracting();
                            }
                            catch (RuntimeException ex4) {
                                throw ex4;
                            }
                        }
                        try {
                            equals = interacting.equals(Players.getLocal());
                            if (a != 0) {
                                return equals;
                            }
                            if (!equals) {
                                break Label_0073;
                            }
                        }
                        catch (RuntimeException ex5) {
                            throw ex5;
                        }
                    }
                    return equals;
                }
                return equals;
            }
        });
    }
    
    public static Familiar getEnum() {
        final int a = Inventory.a;
        try {
            if (!isFamiliarSummoned()) {
                return null;
            }
        }
        catch (RuntimeException ex) {
            throw ex;
        }
        final Familiar[] values = Familiar.values();
        final int length = values.length;
        int i = 0;
        while (i < length) {
            final Familiar familiar = values[i];
            Label_0060: {
                Label_0057: {
                    try {
                        if (a != 0) {
                            break Label_0060;
                        }
                        final Familiar familiar2 = familiar;
                        final int n = familiar2.getPouchId();
                        final int n2 = 1831;
                        final int n3 = Settings.get(n2);
                        if (n == n3) {
                            return familiar;
                        }
                        break Label_0057;
                    }
                    catch (RuntimeException ex2) {
                        throw ex2;
                    }
                    try {
                        final Familiar familiar2 = familiar;
                        final int n = familiar2.getPouchId();
                        final int n2 = 1831;
                        final int n3 = Settings.get(n2);
                        if (n == n3) {
                            return familiar;
                        }
                    }
                    catch (RuntimeException ex3) {
                        throw ex3;
                    }
                }
                ++i;
            }
            if (a != 0) {
                break;
            }
        }
        return null;
    }
    
    public static boolean callFamiliar() {
        final int a = Inventory.a;
        Label_0067: {
            boolean b3 = false;
            boolean interact = false;
            Label_0044: {
                boolean b2 = false;
                Label_0033: {
                    Label_0018: {
                        boolean b;
                        try {
                            b = (b2 = (interact = (b3 = isFamiliarSummoned())));
                            if (a != 0) {
                                break Label_0033;
                            }
                            if (b) {
                                break Label_0018;
                            }
                            return false;
                        }
                        catch (RuntimeException ex) {
                            throw ex;
                        }
                        try {
                            if (!b) {
                                return false;
                            }
                            interact = (b2 = (b3 = Widgets.get(662, 49).visible()));
                        }
                        catch (RuntimeException ex2) {
                            throw ex2;
                        }
                    }
                    try {
                        if (a != 0) {
                            break Label_0067;
                        }
                        if (b2) {
                            break Label_0044;
                        }
                        return false;
                    }
                    catch (RuntimeException ex3) {
                        throw ex3;
                    }
                }
                try {
                    if (!b2) {
                        return false;
                    }
                    b3 = (interact = Widgets.get(662, 49).interact(Deque.e(Summoning.z[2])));
                }
                catch (RuntimeException ex4) {
                    throw ex4;
                }
            }
            try {
                if (a != 0) {
                    return b3;
                }
                if (!interact) {
                    return false;
                }
            }
            catch (RuntimeException ex5) {
                throw ex5;
            }
        }
        return true;
        b3 = false;
        return b3;
    }
    
    public static boolean dismissFamiliar() {
        // 
        // This method could not be decompiled.
        // 
        // Original Bytecode:
        // 
        //     3: istore_1       
        //     4: invokestatic    org/powerbot/game/api/methods/tab/Summoning.isFamiliarSummoned:()Z
        //     7: iload_1        
        //     8: ifne            45
        //    11: ifeq            44
        //    14: goto            18
        //    17: athrow         
        //    18: sipush          662
        //    21: bipush          51
        //    23: invokestatic    org/powerbot/game/api/methods/Widgets.get:(II)Lorg/powerbot/game/api/wrappers/widget/WidgetChild;
        //    26: invokevirtual   org/powerbot/game/api/wrappers/widget/WidgetChild.visible:()Z
        //    29: iload_1        
        //    30: ifne            65
        //    33: goto            37
        //    36: athrow         
        //    37: ifne            46
        //    40: goto            44
        //    43: athrow         
        //    44: iconst_0       
        //    45: ireturn        
        //    46: sipush          662
        //    49: bipush          51
        //    51: invokestatic    org/powerbot/game/api/methods/Widgets.get:(II)Lorg/powerbot/game/api/wrappers/widget/WidgetChild;
        //    54: getstatic       org/powerbot/game/api/methods/tab/Summoning.z:[Ljava/lang/String;
        //    57: iconst_1       
        //    58: aaload         
        //    59: invokestatic    org/f.a:(Ljava/lang/String;)Ljava/lang/String;
        //    62: invokevirtual   org/powerbot/game/api/wrappers/widget/WidgetChild.interact:(Ljava/lang/String;)Z
        //    65: iload_1        
        //    66: ifne            150
        //    69: ifeq            149
        //    72: goto            76
        //    75: athrow         
        //    76: new             Lorg/powerbot/game/api/util/Timer;
        //    79: dup            
        //    80: ldc2_w          1500
        //    83: invokespecial   org/powerbot/game/api/util/Timer.<init>:(J)V
        //    86: astore_0       
        //    87: aload_0        
        //    88: invokevirtual   org/powerbot/game/api/util/Timer.isRunning:()Z
        //    91: ifeq            137
        //    94: sipush          1188
        //    97: bipush          20
        //    99: invokestatic    org/powerbot/game/api/methods/Widgets.get:(II)Lorg/powerbot/game/api/wrappers/widget/WidgetChild;
        //   102: invokevirtual   org/powerbot/game/api/wrappers/widget/WidgetChild.validate:()Z
        //   105: iload_1        
        //   106: ifne            148
        //   109: iload_1        
        //   110: ifne            148
        //   113: goto            117
        //   116: athrow         
        //   117: ifne            137
        //   120: goto            124
        //   123: athrow         
        //   124: bipush          15
        //   126: invokestatic    org/powerbot/core/script/job/Task.sleep:(I)V
        //   129: iload_1        
        //   130: ifeq            87
        //   133: goto            137
        //   136: athrow         
        //   137: sipush          1188
        //   140: iconst_3       
        //   141: invokestatic    org/powerbot/game/api/methods/Widgets.get:(II)Lorg/powerbot/game/api/wrappers/widget/WidgetChild;
        //   144: iconst_1       
        //   145: invokevirtual   org/powerbot/game/api/wrappers/widget/WidgetChild.click:(Z)Z
        //   148: ireturn        
        //   149: iconst_0       
        //   150: ireturn        
        //    StackMapTable: 00 15 FF 00 11 00 02 00 01 00 01 07 00 FB 00 51 07 00 FB 40 01 45 07 00 FB 00 40 01 00 52 01 49 07 00 FB 00 FF 00 0A 00 02 07 00 18 01 00 00 5C 07 00 FB 40 01 45 07 00 FB 00 4B 07 00 FB 00 4A 01 FF 00 00 00 02 00 01 00 00 40 01
        //    Exceptions:
        //  Try           Handler
        //  Start  End    Start  End    Type                        
        //  -----  -----  -----  -----  ----------------------------
        //  117    133    136    137    Ljava/lang/RuntimeException;
        //  109    120    123    124    Ljava/lang/RuntimeException;
        //  94     113    116    117    Ljava/lang/RuntimeException;
        //  65     72     75     76     Ljava/lang/RuntimeException;
        //  18     40     43     44     Ljava/lang/RuntimeException;
        //  11     33     36     37     Ljava/lang/RuntimeException;
        //  4      14     17     18     Ljava/lang/RuntimeException;
        // 
        // The error that occurred was:
        // 
        // java.lang.IllegalStateException: Expression is linked from several locations: Label_0018:
        //     at com.strobel.decompiler.ast.Error.expressionLinkedFromMultipleLocations(Error.java:27)
        //     at com.strobel.decompiler.ast.AstOptimizer.mergeDisparateObjectInitializations(AstOptimizer.java:2596)
        //     at com.strobel.decompiler.ast.AstOptimizer.optimize(AstOptimizer.java:235)
        //     at com.strobel.decompiler.ast.AstOptimizer.optimize(AstOptimizer.java:42)
        //     at com.strobel.decompiler.languages.java.ast.AstMethodBodyBuilder.createMethodBody(AstMethodBodyBuilder.java:214)
        //     at com.strobel.decompiler.languages.java.ast.AstMethodBodyBuilder.createMethodBody(AstMethodBodyBuilder.java:99)
        //     at com.strobel.decompiler.languages.java.ast.AstBuilder.createMethodBody(AstBuilder.java:782)
        //     at com.strobel.decompiler.languages.java.ast.AstBuilder.createMethod(AstBuilder.java:675)
        //     at com.strobel.decompiler.languages.java.ast.AstBuilder.addTypeMembers(AstBuilder.java:552)
        //     at com.strobel.decompiler.languages.java.ast.AstBuilder.createTypeCore(AstBuilder.java:519)
        //     at com.strobel.decompiler.languages.java.ast.AstBuilder.createTypeNoCache(AstBuilder.java:161)
        //     at com.strobel.decompiler.languages.java.ast.AstBuilder.createType(AstBuilder.java:150)
        //     at com.strobel.decompiler.languages.java.ast.AstBuilder.addType(AstBuilder.java:125)
        //     at com.strobel.decompiler.languages.java.JavaLanguage.buildAst(JavaLanguage.java:71)
        //     at com.strobel.decompiler.languages.java.JavaLanguage.decompileType(JavaLanguage.java:59)
        //     at com.strobel.decompiler.DecompilerDriver.decompileType(DecompilerDriver.java:330)
        //     at com.strobel.decompiler.DecompilerDriver.decompileJar(DecompilerDriver.java:251)
        //     at com.strobel.decompiler.DecompilerDriver.main(DecompilerDriver.java:126)
        // 
        throw new IllegalStateException("An error occurred while decompiling this method.");
    }
    
    public static boolean takeBoB() {
        final int a = Inventory.a;
        Label_0067: {
            boolean b3 = false;
            boolean interact = false;
            Label_0044: {
                boolean b2 = false;
                Label_0033: {
                    Label_0018: {
                        boolean b;
                        try {
                            b = (b2 = (interact = (b3 = isFamiliarSummoned())));
                            if (a != 0) {
                                break Label_0033;
                            }
                            if (b) {
                                break Label_0018;
                            }
                            return false;
                        }
                        catch (RuntimeException ex) {
                            throw ex;
                        }
                        try {
                            if (!b) {
                                return false;
                            }
                            interact = (b2 = (b3 = Widgets.get(662, 67).visible()));
                        }
                        catch (RuntimeException ex2) {
                            throw ex2;
                        }
                    }
                    try {
                        if (a != 0) {
                            break Label_0067;
                        }
                        if (b2) {
                            break Label_0044;
                        }
                        return false;
                    }
                    catch (RuntimeException ex3) {
                        throw ex3;
                    }
                }
                try {
                    if (!b2) {
                        return false;
                    }
                    b3 = (interact = Widgets.get(662, 67).interact(Deque.e(Summoning.z[4])));
                }
                catch (RuntimeException ex4) {
                    throw ex4;
                }
            }
            try {
                if (a != 0) {
                    return b3;
                }
                if (!interact) {
                    return false;
                }
            }
            catch (RuntimeException ex5) {
                throw ex5;
            }
        }
        return true;
        b3 = false;
        return b3;
    }
    
    public static boolean renewFamiliar() {
        final int a = Inventory.a;
        Label_0067: {
            boolean b3 = false;
            boolean interact = false;
            Label_0044: {
                boolean b2 = false;
                Label_0033: {
                    Label_0018: {
                        boolean b;
                        try {
                            b = (b2 = (interact = (b3 = isFamiliarSummoned())));
                            if (a != 0) {
                                break Label_0033;
                            }
                            if (b) {
                                break Label_0018;
                            }
                            return false;
                        }
                        catch (RuntimeException ex) {
                            throw ex;
                        }
                        try {
                            if (!b) {
                                return false;
                            }
                            interact = (b2 = (b3 = Widgets.get(662, 69).visible()));
                        }
                        catch (RuntimeException ex2) {
                            throw ex2;
                        }
                    }
                    try {
                        if (a != 0) {
                            break Label_0067;
                        }
                        if (b2) {
                            break Label_0044;
                        }
                        return false;
                    }
                    catch (RuntimeException ex3) {
                        throw ex3;
                    }
                }
                try {
                    if (!b2) {
                        return false;
                    }
                    b3 = (interact = Widgets.get(662, 69).interact(f.a(Summoning.z[5])));
                }
                catch (RuntimeException ex4) {
                    throw ex4;
                }
            }
            try {
                if (a != 0) {
                    return b3;
                }
                if (!interact) {
                    return false;
                }
            }
            catch (RuntimeException ex5) {
                throw ex5;
            }
        }
        return true;
        b3 = false;
        return b3;
    }
    
    public static boolean cast() {
        final int a = Inventory.a;
        Label_0065: {
            boolean b3 = false;
            boolean interact = false;
            Label_0043: {
                boolean b2 = false;
                Label_0032: {
                    Label_0018: {
                        boolean b;
                        try {
                            b = (b2 = (interact = (b3 = isFamiliarSummoned())));
                            if (a != 0) {
                                break Label_0032;
                            }
                            if (b) {
                                break Label_0018;
                            }
                            return false;
                        }
                        catch (RuntimeException ex) {
                            throw ex;
                        }
                        try {
                            if (!b) {
                                return false;
                            }
                            interact = (b2 = (b3 = Widgets.get(662, 5).visible()));
                        }
                        catch (RuntimeException ex2) {
                            throw ex2;
                        }
                    }
                    try {
                        if (a != 0) {
                            break Label_0065;
                        }
                        if (b2) {
                            break Label_0043;
                        }
                        return false;
                    }
                    catch (RuntimeException ex3) {
                        throw ex3;
                    }
                }
                try {
                    if (!b2) {
                        return false;
                    }
                    b3 = (interact = Widgets.get(662, 5).interact(Deque.e(Summoning.z[0])));
                }
                catch (RuntimeException ex4) {
                    throw ex4;
                }
            }
            try {
                if (a != 0) {
                    return b3;
                }
                if (!interact) {
                    return false;
                }
            }
            catch (RuntimeException ex5) {
                throw ex5;
            }
        }
        return true;
        b3 = false;
        return b3;
    }
    
    public static boolean attack() {
        final int a = Inventory.a;
        Label_0068: {
            boolean b3 = false;
            boolean interact = false;
            Label_0044: {
                boolean b2 = false;
                Label_0033: {
                    Label_0018: {
                        boolean b;
                        try {
                            b = (b2 = (interact = (b3 = isFamiliarSummoned())));
                            if (a != 0) {
                                break Label_0033;
                            }
                            if (b) {
                                break Label_0018;
                            }
                            return false;
                        }
                        catch (RuntimeException ex) {
                            throw ex;
                        }
                        try {
                            if (!b) {
                                return false;
                            }
                            interact = (b2 = (b3 = Widgets.get(662, 65).visible()));
                        }
                        catch (RuntimeException ex2) {
                            throw ex2;
                        }
                    }
                    try {
                        if (a != 0) {
                            break Label_0068;
                        }
                        if (b2) {
                            break Label_0044;
                        }
                        return false;
                    }
                    catch (RuntimeException ex3) {
                        throw ex3;
                    }
                }
                try {
                    if (!b2) {
                        return false;
                    }
                    b3 = (interact = Widgets.get(662, 65).interact(f.a(Summoning.z[10])));
                }
                catch (RuntimeException ex4) {
                    throw ex4;
                }
            }
            try {
                if (a != 0) {
                    return b3;
                }
                if (!interact) {
                    return false;
                }
            }
            catch (RuntimeException ex5) {
                throw ex5;
            }
        }
        return true;
        b3 = false;
        return b3;
    }
    
    static {
        final String[] z2 = new String[14];
        int n14;
        int n13;
        int n12;
        int n11;
        int n10;
        int n9;
        int n8;
        int n7;
        int n6;
        int n5;
        int n4;
        int n3;
        int n2;
        int n = n2 = (n3 = (n4 = (n5 = (n6 = (n7 = (n8 = (n9 = (n10 = (n11 = (n12 = (n13 = (n14 = 0))))))))))));
        String s = "\u000e:%\u0004";
        int n15 = -1;
        String intern = null;
    Label_0168_Outer:
        while (true) {
            final char[] charArray = s.toCharArray();
            int length;
            int n17;
            final int n16 = n17 = (length = charArray.length);
            int n18 = 0;
            while (true) {
                Label_0242: {
                    if (n16 > 1) {
                        break Label_0242;
                    }
                    length = (n17 = n18);
                    do {
                        final char c = charArray[n17];
                        char c2 = '\0';
                        switch (n18 % 5) {
                            case 0: {
                                c2 = '\f';
                                break;
                            }
                            case 1: {
                                c2 = '1';
                                break;
                            }
                            case 2: {
                                c2 = '\u0017';
                                break;
                            }
                            case 3: {
                                c2 = '\u001a';
                                break;
                            }
                            default: {
                                c2 = '`';
                                break;
                            }
                        }
                        charArray[length] = (char)(c ^ c2);
                        ++n18;
                    } while (n16 == 0);
                }
                if (n16 > n18) {
                    continue;
                }
                break;
            }
            intern = new String(charArray).intern();
            switch (n15) {
                default: {
                    z2[n2] = intern;
                    n = (n2 = (n3 = (n4 = (n5 = (n6 = (n7 = (n8 = (n9 = (n10 = (n11 = (n12 = (n13 = (n14 = 1)))))))))))));
                    s = "\u0002f.ICA\b";
                    n15 = 0;
                    continue Label_0168_Outer;
                }
                case 0: {
                    z2[n] = intern;
                    n = (n2 = (n3 = (n4 = (n5 = (n6 = (n7 = (n8 = (n9 = (n10 = (n11 = (n12 = (n13 = (n14 = 2)))))))))))));
                    s = "\u000e::\u001c";
                    n15 = 1;
                    continue Label_0168_Outer;
                }
                case 1: {
                    z2[n3] = intern;
                    n = (n2 = (n3 = (n4 = (n5 = (n6 = (n7 = (n8 = (n9 = (n10 = (n11 = (n12 = (n13 = (n14 = 3)))))))))))));
                    s = "a\u000eD=1(";
                    n15 = 2;
                    continue Label_0168_Outer;
                }
                case 2: {
                    z2[n4] = intern;
                    n = (n2 = (n3 = (n4 = (n5 = (n6 = (n7 = (n8 = (n9 = (n10 = (n11 = (n12 = (n13 = (n14 = 4)))))))))))));
                    s = "\u0019:=\u0015";
                    n15 = 3;
                    continue Label_0168_Outer;
                }
                case 3: {
                    z2[n5] = intern;
                    n = (n2 = (n3 = (n4 = (n5 = (n6 = (n7 = (n8 = (n9 = (n10 = (n11 = (n12 = (n13 = (n14 = 5)))))))))))));
                    s = "\u0014j3A]";
                    n15 = 4;
                    continue Label_0168_Outer;
                }
                case 4: {
                    z2[n6] = intern;
                    n = (n2 = (n3 = (n4 = (n5 = (n6 = (n7 = (n8 = (n9 = (n10 = (n11 = (n12 = (n13 = (n14 = 6)))))))))))));
                    s = "%\u001f\u0013=c?6";
                    n15 = 5;
                    continue Label_0168_Outer;
                }
                case 5: {
                    z2[n7] = intern;
                    n = (n2 = (n3 = (n4 = (n5 = (n6 = (n7 = (n8 = (n9 = (n10 = (n11 = (n12 = (n13 = (n14 = 7)))))))))))));
                    s = "a\u001eE5=2";
                    n15 = 6;
                    continue Label_0168_Outer;
                }
                case 6: {
                    z2[n8] = intern;
                    n = (n2 = (n3 = (n4 = (n5 = (n6 = (n7 = (n8 = (n9 = (n10 = (n11 = (n12 = (n13 = (n14 = 8)))))))))))));
                    s = "\u0005`3BC@\u0016";
                    n15 = 7;
                    continue Label_0168_Outer;
                }
                case 7: {
                    z2[n9] = intern;
                    n = (n2 = (n3 = (n4 = (n5 = (n6 = (n7 = (n8 = (n9 = (n10 = (n11 = (n12 = (n13 = (n14 = 9)))))))))))));
                    s = "\u001e>:\u0015B\u0012";
                    n15 = 8;
                    continue Label_0168_Outer;
                }
                case 8: {
                    z2[n10] = intern;
                    n = (n2 = (n3 = (n4 = (n5 = (n6 = (n7 = (n8 = (n9 = (n10 = (n11 = (n12 = (n13 = (n14 = 10)))))))))))));
                    s = "s\u000f]1=-";
                    n15 = 9;
                    continue Label_0168_Outer;
                }
                case 9: {
                    z2[n11] = intern;
                    n = (n2 = (n3 = (n4 = (n5 = (n6 = (n7 = (n8 = (n9 = (n10 = (n11 = (n12 = (n13 = (n14 = 11)))))))))))));
                    s = "Q\u001aZ$";
                    n15 = 10;
                    continue Label_0168_Outer;
                }
                case 10: {
                    z2[n12] = intern;
                    n = (n2 = (n3 = (n4 = (n5 = (n6 = (n7 = (n8 = (n9 = (n10 = (n11 = (n12 = (n13 = (n14 = 12)))))))))))));
                    s = "@\u001eG5)fi<IC^\u0012H\"";
                    n15 = 11;
                    continue Label_0168_Outer;
                }
                case 11: {
                    z2[n13] = intern;
                    n = (n2 = (n3 = (n4 = (n5 = (n6 = (n7 = (n8 = (n9 = (n10 = (n11 = (n12 = (n13 = (n14 = 13)))))))))))));
                    s = "\u0002\u0019\u000e6c>(";
                    n15 = 12;
                    continue Label_0168_Outer;
                }
                case 12: {
                    break Label_0168_Outer;
                }
            }
        }
        z2[n14] = intern;
        z = z2;
    }
    
    public enum Option
    {
        FOLLOWER_DETAILS(Timer.e(Option.z[9]), 7, 16, 0), 
        CAST(Timer.e(Option.z[2]), 9, 17, 1), 
        ATTACK(Timer.e(Option.z[10]), 11, 18, 2), 
        CALL_FOLLOWER(Timer.e(Option.z[11]), 13, 19, 3), 
        DISMISS(Timer.e(Option.z[4]), 15, 20, 4), 
        TAKE_BOB(Timer.e(Option.z[12]), 17, 21, 5), 
        RENEW_FAMILIAR(Timer.e(Option.z[8]), 19, 22, 6), 
        INTERACT(Timer.e(Option.z[5]), 25, 23, 7);
        
        private final String text;
        private final int id;
        private final int setting;
        private final int set;
        private static final String[] z;
        
        private Option(final String text, final int id, final int setting, final int set) {
            this.text = text;
            this.id = id;
            this.setting = setting;
            this.set = set;
        }
        
        public String getText() {
            return this.text;
        }
        
        public WidgetChild getWidgetChild() {
            return Widgets.get(880, this.id);
        }
        
        public boolean isSetLeft() {
            int value = 0;
            Label_0023: {
                int n;
                try {
                    n = (value = Settings.get(1789));
                    if (Inventory.a != 0) {
                        return value != 0;
                    }
                    final Option option = this;
                    final int n2 = option.setting;
                    if (n == n2) {
                        break Label_0023;
                    }
                    return false;
                }
                catch (RuntimeException ex) {
                    throw ex;
                }
                try {
                    final Option option = this;
                    final int n2 = option.setting;
                    if (n != n2) {
                        return false;
                    }
                    value = (true ? 1 : 0);
                }
                catch (RuntimeException ex2) {
                    throw ex2;
                }
            }
            return value != 0;
            value = (false ? 1 : 0);
            return value != 0;
        }
        
        public boolean isSelected() {
            int value = 0;
            Label_0023: {
                int n;
                try {
                    n = (value = Settings.get(1790));
                    if (Inventory.a != 0) {
                        return value != 0;
                    }
                    final Option option = this;
                    final int n2 = option.set;
                    if (n == n2) {
                        break Label_0023;
                    }
                    return false;
                }
                catch (RuntimeException ex) {
                    throw ex;
                }
                try {
                    final Option option = this;
                    final int n2 = option.set;
                    if (n != n2) {
                        return false;
                    }
                    value = (true ? 1 : 0);
                }
                catch (RuntimeException ex2) {
                    throw ex2;
                }
            }
            return value != 0;
            value = (false ? 1 : 0);
            return value != 0;
        }
        
        static {
            final String[] z2 = new String[16];
            int n16;
            int n15;
            int n14;
            int n13;
            int n12;
            int n11;
            int n10;
            int n9;
            int n8;
            int n7;
            int n6;
            int n5;
            int n4;
            int n3;
            int n2;
            int n = n2 = (n3 = (n4 = (n5 = (n6 = (n7 = (n8 = (n9 = (n10 = (n11 = (n12 = (n13 = (n14 = (n15 = (n16 = 0))))))))))))));
            String s = "oT#bN\u0004'W";
            int n17 = -1;
            String intern = null;
        Label_0190_Outer:
            while (true) {
                final char[] charArray = s.toCharArray();
                int length;
                int n19;
                final int n18 = n19 = (length = charArray.length);
                int n20 = 0;
                while (true) {
                    Label_0266: {
                        if (n18 > 1) {
                            break Label_0266;
                        }
                        length = (n19 = n20);
                        do {
                            final char c = charArray[n19];
                            char c2 = '\0';
                            switch (n20 % 5) {
                                case 0: {
                                    c2 = '\u0019';
                                    break;
                                }
                                case 1: {
                                    c2 = 'J';
                                    break;
                                }
                                case 2: {
                                    c2 = 'J';
                                    break;
                                }
                                case 3: {
                                    c2 = 'x';
                                    break;
                                }
                                default: {
                                    c2 = '3';
                                    break;
                                }
                            }
                            charArray[length] = (char)(c ^ c2);
                            ++n20;
                        } while (n18 == 0);
                    }
                    if (n18 > n20) {
                        continue;
                    }
                    break;
                }
                intern = new String(charArray).intern();
                switch (n17) {
                    default: {
                        z2[n2] = intern;
                        n = (n2 = (n3 = (n4 = (n5 = (n6 = (n7 = (n8 = (n9 = (n10 = (n11 = (n12 = (n13 = (n14 = (n15 = (n16 = 1)))))))))))))));
                        s = "iP&bF\u0019.T\u0017%w\\)u";
                        n17 = 0;
                        continue Label_0190_Outer;
                    }
                    case 0: {
                        z2[n] = intern;
                        n = (n2 = (n3 = (n4 = (n5 = (n6 = (n7 = (n8 = (n9 = (n10 = (n11 = (n12 = (n13 = (n14 = (n15 = (n16 = 2)))))))))))))));
                        s = "P\b3/";
                        n17 = 1;
                        continue Label_0190_Outer;
                    }
                    case 1: {
                        z2[n3] = intern;
                        n = (n2 = (n3 = (n4 = (n5 = (n6 = (n7 = (n8 = (n9 = (n10 = (n11 = (n12 = (n13 = (n14 = (n15 = (n16 = 3)))))))))))))));
                        s = "xT;s";
                        n17 = 2;
                        continue Label_0190_Outer;
                    }
                    case 2: {
                        z2[n4] = intern;
                        n = (n2 = (n3 = (n4 = (n5 = (n6 = (n7 = (n8 = (n9 = (n10 = (n11 = (n12 = (n13 = (n14 = (n15 = (n16 = 4)))))))))))))));
                        s = "~)\u001a\u001fy`\u001a";
                        n17 = 3;
                        continue Label_0190_Outer;
                    }
                    case 3: {
                        z2[n5] = intern;
                        n = (n2 = (n3 = (n4 = (n5 = (n6 = (n7 = (n8 = (n9 = (n10 = (n11 = (n12 = (n13 = (n14 = (n15 = (n16 = 5)))))))))))))));
                        s = "Z\u00074>K[#\u001d";
                        n17 = 4;
                        continue Label_0190_Outer;
                    }
                    case 4: {
                        z2[n6] = intern;
                        n = (n2 = (n3 = (n4 = (n5 = (n6 = (n7 = (n8 = (n9 = (n10 = (n11 = (n12 = (n13 = (n14 = (n15 = (n16 = 6)))))))))))))));
                        s = "zA<fR\r";
                        n17 = 5;
                        continue Label_0190_Outer;
                    }
                    case 5: {
                        z2[n7] = intern;
                        n = (n2 = (n3 = (n4 = (n5 = (n6 = (n7 = (n8 = (n9 = (n10 = (n11 = (n12 = (n13 = (n14 = (n15 = (n16 = 7)))))))))))))));
                        s = "r[<bC\u0007+A";
                        n17 = 6;
                        continue Label_0190_Outer;
                    }
                    case 6: {
                        z2[n8] = intern;
                        n = (n2 = (n3 = (n4 = (n5 = (n6 = (n7 = (n8 = (n9 = (n10 = (n11 = (n12 = (n13 = (n14 = (n15 = (n16 = 8)))))))))))))));
                        s = "A\f.>N\u001a\u0006\b\u001fy\u007f\u0000!)";
                        n17 = 7;
                        continue Label_0190_Outer;
                    }
                    case 7: {
                        z2[n9] = intern;
                        n = (n2 = (n3 = (n4 = (n5 = (n6 = (n7 = (n8 = (n9 = (n10 = (n11 = (n12 = (n13 = (n14 = (n15 = (n16 = 9)))))))))))))));
                        s = "U\u0006,7VM%\u001bRTv\u001d!2UI";
                        n17 = 8;
                        continue Label_0190_Outer;
                    }
                    case 8: {
                        z2[n10] = intern;
                        n = (n2 = (n3 = (n4 = (n5 = (n6 = (n7 = (n8 = (n9 = (n10 = (n11 = (n12 = (n13 = (n14 = (n15 = (n16 = 10)))))))))))))));
                        s = "R\u001d4:ZQ";
                        n17 = 9;
                        continue Label_0190_Outer;
                    }
                    case 9: {
                        z2[n11] = intern;
                        n = (n2 = (n3 = (n4 = (n5 = (n6 = (n7 = (n8 = (n9 = (n10 = (n11 = (n12 = (n13 = (n14 = (n15 = (n16 = 11)))))))))))))));
                        s = "y!\u0005\u001e0U\u0006,7VM%\u001b";
                        n17 = 10;
                        continue Label_0190_Outer;
                    }
                    case 10: {
                        z2[n12] = intern;
                        n = (n2 = (n3 = (n4 = (n5 = (n6 = (n7 = (n8 = (n9 = (n10 = (n11 = (n12 = (n13 = (n14 = (n15 = (n16 = 12)))))))))))))));
                        s = "G\b+>\u0019x/+";
                        n17 = 11;
                        continue Label_0190_Outer;
                    }
                    case 11: {
                        z2[n13] = intern;
                        n = (n2 = (n3 = (n4 = (n5 = (n6 = (n7 = (n8 = (n9 = (n10 = (n11 = (n12 = (n13 = (n14 = (n15 = (n16 = 13)))))))))))))));
                        s = "\u0005)Y\u00163}Z$k^\u0011-G";
                        n17 = 12;
                        continue Label_0190_Outer;
                    }
                    case 12: {
                        z2[n14] = intern;
                        n = (n2 = (n3 = (n4 = (n5 = (n6 = (n7 = (n8 = (n9 = (n10 = (n11 = (n12 = (n13 = (n14 = (n15 = (n16 = 14)))))))))))))));
                        s = "}Z$k^\u0011-G\u0005(~A)n]\u0015";
                        n17 = 13;
                        continue Label_0190_Outer;
                    }
                    case 13: {
                        z2[n15] = intern;
                        n = (n2 = (n3 = (n4 = (n5 = (n6 = (n7 = (n8 = (n9 = (n10 = (n11 = (n12 = (n13 = (n14 = (n15 = (n16 = 15)))))))))))))));
                        s = "\u0002!F\u0017%hF";
                        n17 = 14;
                        continue Label_0190_Outer;
                    }
                    case 14: {
                        break Label_0190_Outer;
                    }
                }
            }
            z2[n16] = intern;
            z = z2;
        }
    }
    
    public enum Familiar
    {
        SPIRIT_WOLF(12047, 1, 0, 1, 12533, 3), 
        DREADFOWL(12043, 4, 0, 1, 12445, 3), 
        MEERKATS(19622, 4, 0, 1, 19621, 12), 
        SPIRIT_SPIDER(12059, 10, 0, 2, 12428, 6), 
        THORNY_SNAIL(12019, 13, 3, 2, 12459, 3), 
        GRANITE_CRAB(12009, 16, 0, 2, 12533, 12), 
        SPIRIT_MOSQUITO(12778, 17, 0, 2, 12838, 3), 
        DESERT_WYRM(12049, 18, 0, 1, 12460, 6), 
        SPIRIT_SCORPION(12055, 19, 0, 2, 12432, 6), 
        SPIRIT_TZ_KIH(12808, 22, 0, 3, 12839, 6), 
        ALBINO_RAT(12067, 23, 0, 3, 12430, 6), 
        SPIRIT_KALPHITE(12063, 25, 6, 3, 12446, 6), 
        COMPOST_MOUND(12091, 28, 0, 6, 12440, 12), 
        GIANT_CHINCHOMPA(12800, 29, 0, 1, 12834, 3), 
        VAMPYRE_BAT(12053, 31, 0, 4, 12447, 4), 
        HONEY_BADGER(12065, 32, 0, 4, 12433, 4), 
        BEAVER(12021, 33, 0, 4, 12429, 3), 
        VOID_RAVAGER(12818, 34, 0, 4, 12443, 3), 
        VOID_SPINNER(12780, 34, 0, 4, 12443, 3), 
        VOID_SHIFTER(12814, 34, 0, 4, 12443, 3), 
        VOID_TORCHER(12798, 34, 0, 4, 12443, 3), 
        BRONZE_MINOTAUR(12073, 36, 0, 9, 12462, 6), 
        BULL_ANT(12087, 40, 8, 5, 12431, 12), 
        MACAW(12071, 41, 0, 5, 12422, 12), 
        EVIL_TURNIP(12051, 42, 0, 5, 12448, 6), 
        SPIRIT_COCKATRICE(12095, 43, 0, 5, 12458, 3), 
        SPIRIT_GUTHATRICE(12097, 43, 0, 5, 12458, 3), 
        SPIRIT_SARATRICE(12099, 43, 0, 5, 12458, 3), 
        SPIRIT_ZAMATRICE(12101, 43, 0, 5, 12458, 3), 
        SPIRIT_PENGATRICE(12103, 43, 0, 5, 12458, 3), 
        SPIRIT_CORAXATRICE(12105, 43, 0, 5, 12458, 3), 
        SPIRIT_VULATRICE(12107, 43, 0, 5, 12458, 3), 
        IRON_MINOTAUR(12075, 46, 0, 9, 12463, 6), 
        PYRELORD(12816, 46, 0, 5, 12829, 6), 
        MAGPIE(12041, 47, 0, 5, 12426, 3), 
        BLOATED_LEECH(12061, 49, 0, 5, 12444, 6), 
        SPIRIT_TERRORBIRD(12007, 52, 12, 6, 12441, 8), 
        ABYSSAL_PARASITE(12035, 54, 7, 6, 12454, 6), 
        SPIRIT_JELLY(12027, 55, 0, 6, 12453, 6), 
        STEEL_MINOTAUR(12077, 56, 0, 9, 12464, 6), 
        IBIS(12531, 56, 0, 6, 12424, 12), 
        SPIRIT_GRAAHK(12810, 57, 0, 6, 12835, 3), 
        SPIRIT_KYATT(12812, 57, 0, 6, 12836, 3), 
        SPIRIT_LARUPIA(12784, 57, 0, 6, 12840, 6), 
        KARAMTHULHU_OVERLORD(12023, 58, 0, 6, 12455, 3), 
        SMOKE_DEVIL(12085, 61, 0, 7, 12468, 6), 
        ABYSSAL_LURKER(12037, 62, 7, 7, 12427, 3), 
        SPIRIT_COBRA(12015, 63, 0, 7, 12436, 3), 
        STRANGER_PLANT(12045, 64, 0, 7, 12467, 6), 
        MITHRIL_MINOTAUR(12079, 66, 0, 9, 12465, 6), 
        BARKER_TOAD(12123, 66, 0, 7, 12452, 6), 
        WAR_TORTOISE(12031, 67, 18, 7, 12439, 20), 
        BUNYIP(12029, 68, 0, 7, 12438, 3), 
        FRUIT_BAT(12033, 69, 0, 7, 12423, 6), 
        RAVENOUS_LOCTUS(12820, 70, 0, 4, 12830, 12), 
        ARTIC_BEAR(12057, 71, 0, 8, 12451, 6), 
        PHOENIX(14623, 72, 0, 8, 14622, 5), 
        OBSIDIAN_GOLEM(12792, 73, 0, 8, 12826, 12), 
        GRANITE_LOBSTER(12069, 74, 0, 8, 12449, 6), 
        PRAYING_MANTRIS(12011, 75, 0, 8, 12450, 6), 
        ADAMANT_MINOTAUR(12081, 76, 0, 9, 12466, 6), 
        FORGE_REGENT(12782, 76, 0, 9, 12841, 6), 
        TALON_BEAST(12794, 77, 0, 9, 12831, 6), 
        GIANT_ENT(12013, 78, 0, 8, 12457, 6), 
        FIRE_TITAN(12802, 79, 0, 9, 12824, 20), 
        ICE_TITAN(12806, 79, 0, 9, 12824, 20), 
        MOSS_TITAN(12804, 79, 0, 9, 12824, 20), 
        HYDRA(12025, 80, 0, 8, 12442, 6), 
        SPIRIT_DAGANNOTH(12017, 83, 0, 9, 12456, 6), 
        LAVA_TITAN(12788, 83, 0, 9, 12837, 4), 
        SWAMP_TITAN(12776, 85, 0, 9, 12832, 6), 
        RUNE_MINOTAUR(12083, 86, 0, 9, 12467, 6), 
        GHAST_FAMILIAR(21444, 87, 0, 1, 21453, 20), 
        UNICORN_STALLION(12039, 88, 0, 9, 12434, 20), 
        GEYSER_TITAN(12786, 89, 0, 10, 12833, 6), 
        WOLPERTINGER(12089, 92, 0, 10, 12437, 20), 
        ABYSSAL_TITAN(12796, 93, 7, 10, 12827, 6), 
        IRON_TITAN(12822, 95, 0, 10, 12828, 12), 
        PACK_YAK(12093, 96, 30, 10, 12435, 12), 
        STEEL_TITAN(12790, 99, 0, 10, 12825, 12);
        
        private final int pouch;
        private final int level;
        private final int space;
        private final int points;
        private final int scroll;
        private final int special;
        private static final String[] z;
        
        private Familiar(final int pouch, final int level, final int space, final int points, final int scroll, final int special) {
            this.pouch = pouch;
            this.level = level;
            this.space = space;
            this.points = points;
            this.special = special;
            this.scroll = scroll;
        }
        
        public int getPouchId() {
            return this.pouch;
        }
        
        public int getRequiredLevel() {
            return this.level;
        }
        
        public int getBoBSpace() {
            return this.space;
        }
        
        public int getRequiredPoints() {
            return this.points;
        }
        
        public int getScrollId() {
            return this.scroll;
        }
        
        public int getRequiredSpecialPoints() {
            return this.special;
        }
        
        static {
            final String[] z2 = new String[80];
            int n80;
            int n79;
            int n78;
            int n77;
            int n76;
            int n75;
            int n74;
            int n73;
            int n72;
            int n71;
            int n70;
            int n69;
            int n68;
            int n67;
            int n66;
            int n65;
            int n64;
            int n63;
            int n62;
            int n61;
            int n60;
            int n59;
            int n58;
            int n57;
            int n56;
            int n55;
            int n54;
            int n53;
            int n52;
            int n51;
            int n50;
            int n49;
            int n48;
            int n47;
            int n46;
            int n45;
            int n44;
            int n43;
            int n42;
            int n41;
            int n40;
            int n39;
            int n38;
            int n37;
            int n36;
            int n35;
            int n34;
            int n33;
            int n32;
            int n31;
            int n30;
            int n29;
            int n28;
            int n27;
            int n26;
            int n25;
            int n24;
            int n23;
            int n22;
            int n21;
            int n20;
            int n19;
            int n18;
            int n17;
            int n16;
            int n15;
            int n14;
            int n13;
            int n12;
            int n11;
            int n10;
            int n9;
            int n8;
            int n7;
            int n6;
            int n5;
            int n4;
            int n3;
            int n2;
            int n = n2 = (n3 = (n4 = (n5 = (n6 = (n7 = (n8 = (n9 = (n10 = (n11 = (n12 = (n13 = (n14 = (n15 = (n16 = (n17 = (n18 = (n19 = (n20 = (n21 = (n22 = (n23 = (n24 = (n25 = (n26 = (n27 = (n28 = (n29 = (n30 = (n31 = (n32 = (n33 = (n34 = (n35 = (n36 = (n37 = (n38 = (n39 = (n40 = (n41 = (n42 = (n43 = (n44 = (n45 = (n46 = (n47 = (n48 = (n49 = (n50 = (n51 = (n52 = (n53 = (n54 = (n55 = (n56 = (n57 = (n58 = (n59 = (n60 = (n61 = (n62 = (n63 = (n64 = (n65 = (n66 = (n67 = (n68 = (n69 = (n70 = (n71 = (n72 = (n73 = (n74 = (n75 = (n76 = (n77 = (n78 = (n79 = (n80 = 0))))))))))))))))))))))))))))))))))))))))))))))))))))))))))))))))))))))))))))));
            String s = "dg\u0019v(\u0014\u0016f\u0007Gga\u0019\u007f/\u000f";
            int n81 = -1;
            String intern = null;
        Label_0974_Outer:
            while (true) {
                final char[] charArray = s.toCharArray();
                int length;
                int n83;
                final int n82 = n83 = (length = charArray.length);
                int n84 = 0;
                while (true) {
                    Label_1050: {
                        if (n82 > 1) {
                            break Label_1050;
                        }
                        length = (n83 = n84);
                        do {
                            final char c = charArray[n83];
                            char c2 = '\0';
                            switch (n84 % 5) {
                                case 0: {
                                    c2 = '\u0017';
                                    break;
                                }
                                case 1: {
                                    c2 = 'd';
                                    break;
                                }
                                case 2: {
                                    c2 = 's';
                                    break;
                                }
                                case 3: {
                                    c2 = 't';
                                    break;
                                }
                                default: {
                                    c2 = 'D';
                                    break;
                                }
                            }
                            charArray[length] = (char)(c ^ c2);
                            ++n84;
                        } while (n82 == 0);
                    }
                    if (n82 > n84) {
                        continue;
                    }
                    break;
                }
                intern = new String(charArray).intern();
                switch (n81) {
                    default: {
                        z2[n2] = intern;
                        n = (n2 = (n3 = (n4 = (n5 = (n6 = (n7 = (n8 = (n9 = (n10 = (n11 = (n12 = (n13 = (n14 = (n15 = (n16 = (n17 = (n18 = (n19 = (n20 = (n21 = (n22 = (n23 = (n24 = (n25 = (n26 = (n27 = (n28 = (n29 = (n30 = (n31 = (n32 = (n33 = (n34 = (n35 = (n36 = (n37 = (n38 = (n39 = (n40 = (n41 = (n42 = (n43 = (n44 = (n45 = (n46 = (n47 = (n48 = (n49 = (n50 = (n51 = (n52 = (n53 = (n54 = (n55 = (n56 = (n57 = (n58 = (n59 = (n60 = (n61 = (n62 = (n63 = (n64 = (n65 = (n66 = (n67 = (n68 = (n69 = (n70 = (n71 = (n72 = (n73 = (n74 = (n75 = (n76 = (n77 = (n78 = (n79 = (n80 = 1)))))))))))))))))))))))))))))))))))))))))))))))))))))))))))))))))))))))))))))));
                        s = "h|\u0019w9\u0002\u0018|\u000b\\";
                        n81 = 0;
                        continue Label_0974_Outer;
                    }
                    case 0: {
                        z2[n] = intern;
                        n = (n2 = (n3 = (n4 = (n5 = (n6 = (n7 = (n8 = (n9 = (n10 = (n11 = (n12 = (n13 = (n14 = (n15 = (n16 = (n17 = (n18 = (n19 = (n20 = (n21 = (n22 = (n23 = (n24 = (n25 = (n26 = (n27 = (n28 = (n29 = (n30 = (n31 = (n32 = (n33 = (n34 = (n35 = (n36 = (n37 = (n38 = (n39 = (n40 = (n41 = (n42 = (n43 = (n44 = (n45 = (n46 = (n47 = (n48 = (n49 = (n50 = (n51 = (n52 = (n53 = (n54 = (n55 = (n56 = (n57 = (n58 = (n59 = (n60 = (n61 = (n62 = (n63 = (n64 = (n65 = (n66 = (n67 = (n68 = (n69 = (n70 = (n71 = (n72 = (n73 = (n74 = (n75 = (n76 = (n77 = (n78 = (n79 = (n80 = 2)))))))))))))))))))))))))))))))))))))))))))))))))))))))))))))))))))))))))))))));
                        s = "\u001f\bv\u0004Tlq\u0000w4\u0012\u000ex\u001f\\";
                        n81 = 1;
                        continue Label_0974_Outer;
                    }
                    case 1: {
                        z2[n3] = intern;
                        n = (n2 = (n3 = (n4 = (n5 = (n6 = (n7 = (n8 = (n9 = (n10 = (n11 = (n12 = (n13 = (n14 = (n15 = (n16 = (n17 = (n18 = (n19 = (n20 = (n21 = (n22 = (n23 = (n24 = (n25 = (n26 = (n27 = (n28 = (n29 = (n30 = (n31 = (n32 = (n33 = (n34 = (n35 = (n36 = (n37 = (n38 = (n39 = (n40 = (n41 = (n42 = (n43 = (n44 = (n45 = (n46 = (n47 = (n48 = (n49 = (n50 = (n51 = (n52 = (n53 = (n54 = (n55 = (n56 = (n57 = (n58 = (n59 = (n60 = (n61 = (n62 = (n63 = (n64 = (n65 = (n66 = (n67 = (n68 = (n69 = (n70 = (n71 = (n72 = (n73 = (n74 = (n75 = (n76 = (n77 = (n78 = (n79 = (n80 = 3)))))))))))))))))))))))))))))))))))))))))))))))))))))))))))))))))))))))))))))));
                        s = "\u000es~oD\u001dryjT";
                        n81 = 2;
                        continue Label_0974_Outer;
                    }
                    case 2: {
                        z2[n4] = intern;
                        n = (n2 = (n3 = (n4 = (n5 = (n6 = (n7 = (n8 = (n9 = (n10 = (n11 = (n12 = (n13 = (n14 = (n15 = (n16 = (n17 = (n18 = (n19 = (n20 = (n21 = (n22 = (n23 = (n24 = (n25 = (n26 = (n27 = (n28 = (n29 = (n30 = (n31 = (n32 = (n33 = (n34 = (n35 = (n36 = (n37 = (n38 = (n39 = (n40 = (n41 = (n42 = (n43 = (n44 = (n45 = (n46 = (n47 = (n48 = (n49 = (n50 = (n51 = (n52 = (n53 = (n54 = (n55 = (n56 = (n57 = (n58 = (n59 = (n60 = (n61 = (n62 = (n63 = (n64 = (n65 = (n66 = (n67 = (n68 = (n69 = (n70 = (n71 = (n72 = (n73 = (n74 = (n75 = (n76 = (n77 = (n78 = (n79 = (n80 = 4)))))))))))))))))))))))))))))))))))))))))))))))))))))))))))))))))))))))))))))));
                        s = "\u0019\b|\u000bJoa\u001ar";
                        n81 = 3;
                        continue Label_0974_Outer;
                    }
                    case 3: {
                        z2[n5] = intern;
                        n = (n2 = (n3 = (n4 = (n5 = (n6 = (n7 = (n8 = (n9 = (n10 = (n11 = (n12 = (n13 = (n14 = (n15 = (n16 = (n17 = (n18 = (n19 = (n20 = (n21 = (n22 = (n23 = (n24 = (n25 = (n26 = (n27 = (n28 = (n29 = (n30 = (n31 = (n32 = (n33 = (n34 = (n35 = (n36 = (n37 = (n38 = (n39 = (n40 = (n41 = (n42 = (n43 = (n44 = (n45 = (n46 = (n47 = (n48 = (n49 = (n50 = (n51 = (n52 = (n53 = (n54 = (n55 = (n56 = (n57 = (n58 = (n59 = (n60 = (n61 = (n62 = (n63 = (n64 = (n65 = (n66 = (n67 = (n68 = (n69 = (n70 = (n71 = (n72 = (n73 = (n74 = (n75 = (n76 = (n77 = (n78 = (n79 = (n80 = 5)))))))))))))))))))))))))))))))))))))))))))))))))))))))))))))))))))))))))))))));
                        s = "\bytxI\tvs~R\u001dzc";
                        n81 = 4;
                        continue Label_0974_Outer;
                    }
                    case 4: {
                        z2[n6] = intern;
                        n = (n2 = (n3 = (n4 = (n5 = (n6 = (n7 = (n8 = (n9 = (n10 = (n11 = (n12 = (n13 = (n14 = (n15 = (n16 = (n17 = (n18 = (n19 = (n20 = (n21 = (n22 = (n23 = (n24 = (n25 = (n26 = (n27 = (n28 = (n29 = (n30 = (n31 = (n32 = (n33 = (n34 = (n35 = (n36 = (n37 = (n38 = (n39 = (n40 = (n41 = (n42 = (n43 = (n44 = (n45 = (n46 = (n47 = (n48 = (n49 = (n50 = (n51 = (n52 = (n53 = (n54 = (n55 = (n56 = (n57 = (n58 = (n59 = (n60 = (n61 = (n62 = (n63 = (n64 = (n65 = (n66 = (n67 = (n68 = (n69 = (n70 = (n71 = (n72 = (n73 = (n74 = (n75 = (n76 = (n77 = (n78 = (n79 = (n80 = 6)))))))))))))))))))))))))))))))))))))))))))))))))))))))))))))))))))))))))))))));
                        s = "\u000f\u007fuy^\u001bdybN\tt";
                        n81 = 5;
                        continue Label_0974_Outer;
                    }
                    case 5: {
                        z2[n7] = intern;
                        n = (n2 = (n3 = (n4 = (n5 = (n6 = (n7 = (n8 = (n9 = (n10 = (n11 = (n12 = (n13 = (n14 = (n15 = (n16 = (n17 = (n18 = (n19 = (n20 = (n21 = (n22 = (n23 = (n24 = (n25 = (n26 = (n27 = (n28 = (n29 = (n30 = (n31 = (n32 = (n33 = (n34 = (n35 = (n36 = (n37 = (n38 = (n39 = (n40 = (n41 = (n42 = (n43 = (n44 = (n45 = (n46 = (n47 = (n48 = (n49 = (n50 = (n51 = (n52 = (n53 = (n54 = (n55 = (n56 = (n57 = (n58 = (n59 = (n60 = (n61 = (n62 = (n63 = (n64 = (n65 = (n66 = (n67 = (n68 = (n69 = (n70 = (n71 = (n72 = (n73 = (n74 = (n75 = (n76 = (n77 = (n78 = (n79 = (n80 = 7)))))))))))))))))))))))))))))))))))))))))))))))))))))))))))))))))))))))))))))));
                        s = "\nobsR\u0019";
                        n81 = 6;
                        continue Label_0974_Outer;
                    }
                    case 6: {
                        z2[n8] = intern;
                        n = (n2 = (n3 = (n4 = (n5 = (n6 = (n7 = (n8 = (n9 = (n10 = (n11 = (n12 = (n13 = (n14 = (n15 = (n16 = (n17 = (n18 = (n19 = (n20 = (n21 = (n22 = (n23 = (n24 = (n25 = (n26 = (n27 = (n28 = (n29 = (n30 = (n31 = (n32 = (n33 = (n34 = (n35 = (n36 = (n37 = (n38 = (n39 = (n40 = (n41 = (n42 = (n43 = (n44 = (n45 = (n46 = (n47 = (n48 = (n49 = (n50 = (n51 = (n52 = (n53 = (n54 = (n55 = (n56 = (n57 = (n58 = (n59 = (n60 = (n61 = (n62 = (n63 = (n64 = (n65 = (n66 = (n67 = (n68 = (n69 = (n70 = (n71 = (n72 = (n73 = (n74 = (n75 = (n76 = (n77 = (n78 = (n79 = (n80 = 8)))))))))))))))))))))))))))))))))))))))))))))))))))))))))))))))))))))))))))))));
                        s = "\u0019sbnT\u0001b";
                        n81 = 7;
                        continue Label_0974_Outer;
                    }
                    case 7: {
                        z2[n9] = intern;
                        n = (n2 = (n3 = (n4 = (n5 = (n6 = (n7 = (n8 = (n9 = (n10 = (n11 = (n12 = (n13 = (n14 = (n15 = (n16 = (n17 = (n18 = (n19 = (n20 = (n21 = (n22 = (n23 = (n24 = (n25 = (n26 = (n27 = (n28 = (n29 = (n30 = (n31 = (n32 = (n33 = (n34 = (n35 = (n36 = (n37 = (n38 = (n39 = (n40 = (n41 = (n42 = (n43 = (n44 = (n45 = (n46 = (n47 = (n48 = (n49 = (n50 = (n51 = (n52 = (n53 = (n54 = (n55 = (n56 = (n57 = (n58 = (n59 = (n60 = (n61 = (n62 = (n63 = (n64 = (n65 = (n66 = (n67 = (n68 = (n69 = (n70 = (n71 = (n72 = (n73 = (n74 = (n75 = (n76 = (n77 = (n78 = (n79 = (n80 = 9)))))))))))))))))))))))))))))))))))))))))))))))))))))))))))))))))))))))))))))));
                        s = "\u001b\bl\u0003Zvl\fj";
                        n81 = 8;
                        continue Label_0974_Outer;
                    }
                    case 8: {
                        z2[n10] = intern;
                        n = (n2 = (n3 = (n4 = (n5 = (n6 = (n7 = (n8 = (n9 = (n10 = (n11 = (n12 = (n13 = (n14 = (n15 = (n16 = (n17 = (n18 = (n19 = (n20 = (n21 = (n22 = (n23 = (n24 = (n25 = (n26 = (n27 = (n28 = (n29 = (n30 = (n31 = (n32 = (n33 = (n34 = (n35 = (n36 = (n37 = (n38 = (n39 = (n40 = (n41 = (n42 = (n43 = (n44 = (n45 = (n46 = (n47 = (n48 = (n49 = (n50 = (n51 = (n52 = (n53 = (n54 = (n55 = (n56 = (n57 = (n58 = (n59 = (n60 = (n61 = (n62 = (n63 = (n64 = (n65 = (n66 = (n67 = (n68 = (n69 = (n70 = (n71 = (n72 = (n73 = (n74 = (n75 = (n76 = (n77 = (n78 = (n79 = (n80 = 10)))))))))))))))))))))))))))))))))))))))))))))))))))))))))))))))))))))))))))))));
                        s = "\u0000ibeE\u0005sbeO\bn\u007f";
                        n81 = 9;
                        continue Label_0974_Outer;
                    }
                    case 9: {
                        z2[n11] = intern;
                        n = (n2 = (n3 = (n4 = (n5 = (n6 = (n7 = (n8 = (n9 = (n10 = (n11 = (n12 = (n13 = (n14 = (n15 = (n16 = (n17 = (n18 = (n19 = (n20 = (n21 = (n22 = (n23 = (n24 = (n25 = (n26 = (n27 = (n28 = (n29 = (n30 = (n31 = (n32 = (n33 = (n34 = (n35 = (n36 = (n37 = (n38 = (n39 = (n40 = (n41 = (n42 = (n43 = (n44 = (n45 = (n46 = (n47 = (n48 = (n49 = (n50 = (n51 = (n52 = (n53 = (n54 = (n55 = (n56 = (n57 = (n58 = (n59 = (n60 = (n61 = (n62 = (n63 = (n64 = (n65 = (n66 = (n67 = (n68 = (n69 = (n70 = (n71 = (n72 = (n73 = (n74 = (n75 = (n76 = (n77 = (n78 = (n79 = (n80 = 11)))))))))))))))))))))))))))))))))))))))))))))))))))))))))))))))))))))))))))))));
                        s = "zz\b{6\u0002\u0017p\u0004A}o\u0018l";
                        n81 = 10;
                        continue Label_0974_Outer;
                    }
                    case 10: {
                        z2[n12] = intern;
                        n = (n2 = (n3 = (n4 = (n5 = (n6 = (n7 = (n8 = (n9 = (n10 = (n11 = (n12 = (n13 = (n14 = (n15 = (n16 = (n17 = (n18 = (n19 = (n20 = (n21 = (n22 = (n23 = (n24 = (n25 = (n26 = (n27 = (n28 = (n29 = (n30 = (n31 = (n32 = (n33 = (n34 = (n35 = (n36 = (n37 = (n38 = (n39 = (n40 = (n41 = (n42 = (n43 = (n44 = (n45 = (n46 = (n47 = (n48 = (n49 = (n50 = (n51 = (n52 = (n53 = (n54 = (n55 = (n56 = (n57 = (n58 = (n59 = (n60 = (n61 = (n62 = (n63 = (n64 = (n65 = (n66 = (n67 = (n68 = (n69 = (n70 = (n71 = (n72 = (n73 = (n74 = (n75 = (n76 = (n77 = (n78 = (n79 = (n80 = 12)))))))))))))))))))))))))))))))))))))))))))))))))))))))))))))))))))))))))))))));
                        s = "\u0015\u0003}\u0018O";
                        n81 = 11;
                        continue Label_0974_Outer;
                    }
                    case 11: {
                        z2[n13] = intern;
                        n = (n2 = (n3 = (n4 = (n5 = (n6 = (n7 = (n8 = (n9 = (n10 = (n11 = (n12 = (n13 = (n14 = (n15 = (n16 = (n17 = (n18 = (n19 = (n20 = (n21 = (n22 = (n23 = (n24 = (n25 = (n26 = (n27 = (n28 = (n29 = (n30 = (n31 = (n32 = (n33 = (n34 = (n35 = (n36 = (n37 = (n38 = (n39 = (n40 = (n41 = (n42 = (n43 = (n44 = (n45 = (n46 = (n47 = (n48 = (n49 = (n50 = (n51 = (n52 = (n53 = (n54 = (n55 = (n56 = (n57 = (n58 = (n59 = (n60 = (n61 = (n62 = (n63 = (n64 = (n65 = (n66 = (n67 = (n68 = (n69 = (n70 = (n71 = (n72 = (n73 = (n74 = (n75 = (n76 = (n77 = (n78 = (n79 = (n80 = 13)))))))))))))))))))))))))))))))))))))))))))))))))))))))))))))))))))))))))))))));
                        s = "\u0005u\u007fyD\u001dryjT";
                        n81 = 12;
                        continue Label_0974_Outer;
                    }
                    case 12: {
                        z2[n14] = intern;
                        n = (n2 = (n3 = (n4 = (n5 = (n6 = (n7 = (n8 = (n9 = (n10 = (n11 = (n12 = (n13 = (n14 = (n15 = (n16 = (n17 = (n18 = (n19 = (n20 = (n21 = (n22 = (n23 = (n24 = (n25 = (n26 = (n27 = (n28 = (n29 = (n30 = (n31 = (n32 = (n33 = (n34 = (n35 = (n36 = (n37 = (n38 = (n39 = (n40 = (n41 = (n42 = (n43 = (n44 = (n45 = (n46 = (n47 = (n48 = (n49 = (n50 = (n51 = (n52 = (n53 = (n54 = (n55 = (n56 = (n57 = (n58 = (n59 = (n60 = (n61 = (n62 = (n63 = (n64 = (n65 = (n66 = (n67 = (n68 = (n69 = (n70 = (n71 = (n72 = (n73 = (n74 = (n75 = (n76 = (n77 = (n78 = (n79 = (n80 = 14)))))))))))))))))))))))))))))))))))))))))))))))))))))))))))))))))))))))))))))));
                        s = "\u001bjexR\u001ddndH\tbm~I\u0000xh";
                        n81 = 13;
                        continue Label_0974_Outer;
                    }
                    case 13: {
                        z2[n15] = intern;
                        n = (n2 = (n3 = (n4 = (n5 = (n6 = (n7 = (n8 = (n9 = (n10 = (n11 = (n12 = (n13 = (n14 = (n15 = (n16 = (n17 = (n18 = (n19 = (n20 = (n21 = (n22 = (n23 = (n24 = (n25 = (n26 = (n27 = (n28 = (n29 = (n30 = (n31 = (n32 = (n33 = (n34 = (n35 = (n36 = (n37 = (n38 = (n39 = (n40 = (n41 = (n42 = (n43 = (n44 = (n45 = (n46 = (n47 = (n48 = (n49 = (n50 = (n51 = (n52 = (n53 = (n54 = (n55 = (n56 = (n57 = (n58 = (n59 = (n60 = (n61 = (n62 = (n63 = (n64 = (n65 = (n66 = (n67 = (n68 = (n69 = (n70 = (n71 = (n72 = (n73 = (n74 = (n75 = (n76 = (n77 = (n78 = (n79 = (n80 = 15)))))))))))))))))))))))))))))))))))))))))))))))))))))))))))))))))))))))))))))));
                        s = "\u001euenD\u001dt\u007fhR\rh";
                        n81 = 14;
                        continue Label_0974_Outer;
                    }
                    case 14: {
                        z2[n16] = intern;
                        n = (n2 = (n3 = (n4 = (n5 = (n6 = (n7 = (n8 = (n9 = (n10 = (n11 = (n12 = (n13 = (n14 = (n15 = (n16 = (n17 = (n18 = (n19 = (n20 = (n21 = (n22 = (n23 = (n24 = (n25 = (n26 = (n27 = (n28 = (n29 = (n30 = (n31 = (n32 = (n33 = (n34 = (n35 = (n36 = (n37 = (n38 = (n39 = (n40 = (n41 = (n42 = (n43 = (n44 = (n45 = (n46 = (n47 = (n48 = (n49 = (n50 = (n51 = (n52 = (n53 = (n54 = (n55 = (n56 = (n57 = (n58 = (n59 = (n60 = (n61 = (n62 = (n63 = (n64 = (n65 = (n66 = (n67 = (n68 = (n69 = (n70 = (n71 = (n72 = (n73 = (n74 = (n75 = (n76 = (n77 = (n78 = (n79 = (n80 = 16)))))))))))))))))))))))))))))))))))))))))))))))))))))))))))))))))))))))))))))));
                        s = "\u000frmyO\u0016}lfS\u0004smx";
                        n81 = 15;
                        continue Label_0974_Outer;
                    }
                    case 15: {
                        z2[n17] = intern;
                        n = (n2 = (n3 = (n4 = (n5 = (n6 = (n7 = (n8 = (n9 = (n10 = (n11 = (n12 = (n13 = (n14 = (n15 = (n16 = (n17 = (n18 = (n19 = (n20 = (n21 = (n22 = (n23 = (n24 = (n25 = (n26 = (n27 = (n28 = (n29 = (n30 = (n31 = (n32 = (n33 = (n34 = (n35 = (n36 = (n37 = (n38 = (n39 = (n40 = (n41 = (n42 = (n43 = (n44 = (n45 = (n46 = (n47 = (n48 = (n49 = (n50 = (n51 = (n52 = (n53 = (n54 = (n55 = (n56 = (n57 = (n58 = (n59 = (n60 = (n61 = (n62 = (n63 = (n64 = (n65 = (n66 = (n67 = (n68 = (n69 = (n70 = (n71 = (n72 = (n73 = (n74 = (n75 = (n76 = (n77 = (n78 = (n79 = (n80 = 17)))))))))))))))))))))))))))))))))))))))))))))))))))))))))))))))))))))))))))))));
                        s = "z~\u0004l3\t\u0005j\u000b\\hz\u001fw9\u0018";
                        n81 = 16;
                        continue Label_0974_Outer;
                    }
                    case 16: {
                        z2[n18] = intern;
                        n = (n2 = (n3 = (n4 = (n5 = (n6 = (n7 = (n8 = (n9 = (n10 = (n11 = (n12 = (n13 = (n14 = (n15 = (n16 = (n17 = (n18 = (n19 = (n20 = (n21 = (n22 = (n23 = (n24 = (n25 = (n26 = (n27 = (n28 = (n29 = (n30 = (n31 = (n32 = (n33 = (n34 = (n35 = (n36 = (n37 = (n38 = (n39 = (n40 = (n41 = (n42 = (n43 = (n44 = (n45 = (n46 = (n47 = (n48 = (n49 = (n50 = (n51 = (n52 = (n53 = (n54 = (n55 = (n56 = (n57 = (n58 = (n59 = (n60 = (n61 = (n62 = (n63 = (n64 = (n65 = (n66 = (n67 = (n68 = (n69 = (n70 = (n71 = (n72 = (n73 = (n74 = (n75 = (n76 = (n77 = (n78 = (n79 = (n80 = 18)))))))))))))))))))))))))))))))))))))))))))))))))))))))))))))))))))))))))))))));
                        s = "\u001crcxU\u0010d~e[\u0001v";
                        n81 = 17;
                        continue Label_0974_Outer;
                    }
                    case 17: {
                        z2[n19] = intern;
                        n = (n2 = (n3 = (n4 = (n5 = (n6 = (n7 = (n8 = (n9 = (n10 = (n11 = (n12 = (n13 = (n14 = (n15 = (n16 = (n17 = (n18 = (n19 = (n20 = (n21 = (n22 = (n23 = (n24 = (n25 = (n26 = (n27 = (n28 = (n29 = (n30 = (n31 = (n32 = (n33 = (n34 = (n35 = (n36 = (n37 = (n38 = (n39 = (n40 = (n41 = (n42 = (n43 = (n44 = (n45 = (n46 = (n47 = (n48 = (n49 = (n50 = (n51 = (n52 = (n53 = (n54 = (n55 = (n56 = (n57 = (n58 = (n59 = (n60 = (n61 = (n62 = (n63 = (n64 = (n65 = (n66 = (n67 = (n68 = (n69 = (n70 = (n71 = (n72 = (n73 = (n74 = (n75 = (n76 = (n77 = (n78 = (n79 = (n80 = 19)))))))))))))))))))))))))))))))))))))))))))))))))))))))))))))))))))))))))))))));
                        s = "oa\u001fy?\u0002\b|\rKgz";
                        n81 = 18;
                        continue Label_0974_Outer;
                    }
                    case 18: {
                        z2[n20] = intern;
                        n = (n2 = (n3 = (n4 = (n5 = (n6 = (n7 = (n8 = (n9 = (n10 = (n11 = (n12 = (n13 = (n14 = (n15 = (n16 = (n17 = (n18 = (n19 = (n20 = (n21 = (n22 = (n23 = (n24 = (n25 = (n26 = (n27 = (n28 = (n29 = (n30 = (n31 = (n32 = (n33 = (n34 = (n35 = (n36 = (n37 = (n38 = (n39 = (n40 = (n41 = (n42 = (n43 = (n44 = (n45 = (n46 = (n47 = (n48 = (n49 = (n50 = (n51 = (n52 = (n53 = (n54 = (n55 = (n56 = (n57 = (n58 = (n59 = (n60 = (n61 = (n62 = (n63 = (n64 = (n65 = (n66 = (n67 = (n68 = (n69 = (n70 = (n71 = (n72 = (n73 = (n74 = (n75 = (n76 = (n77 = (n78 = (n79 = (n80 = 20)))))))))))))))))))))))))))))))))))))))))))))))))))))))))))))))))))))))))))))));
                        s = "\u0003{~kV\u001dsxgR\u001dec|^\u001bwby^";
                        n81 = 19;
                        continue Label_0974_Outer;
                    }
                    case 19: {
                        z2[n21] = intern;
                        n = (n2 = (n3 = (n4 = (n5 = (n6 = (n7 = (n8 = (n9 = (n10 = (n11 = (n12 = (n13 = (n14 = (n15 = (n16 = (n17 = (n18 = (n19 = (n20 = (n21 = (n22 = (n23 = (n24 = (n25 = (n26 = (n27 = (n28 = (n29 = (n30 = (n31 = (n32 = (n33 = (n34 = (n35 = (n36 = (n37 = (n38 = (n39 = (n40 = (n41 = (n42 = (n43 = (n44 = (n45 = (n46 = (n47 = (n48 = (n49 = (n50 = (n51 = (n52 = (n53 = (n54 = (n55 = (n56 = (n57 = (n58 = (n59 = (n60 = (n61 = (n62 = (n63 = (n64 = (n65 = (n66 = (n67 = (n68 = (n69 = (n70 = (n71 = (n72 = (n73 = (n74 = (n75 = (n76 = (n77 = (n78 = (n79 = (n80 = 21)))))))))))))))))))))))))))))))))))))))))))))))))))))))))))))))))))))))))))))));
                        s = "\u0005\u007fixP\bo~";
                        n81 = 20;
                        continue Label_0974_Outer;
                    }
                    case 20: {
                        z2[n22] = intern;
                        n = (n2 = (n3 = (n4 = (n5 = (n6 = (n7 = (n8 = (n9 = (n10 = (n11 = (n12 = (n13 = (n14 = (n15 = (n16 = (n17 = (n18 = (n19 = (n20 = (n21 = (n22 = (n23 = (n24 = (n25 = (n26 = (n27 = (n28 = (n29 = (n30 = (n31 = (n32 = (n33 = (n34 = (n35 = (n36 = (n37 = (n38 = (n39 = (n40 = (n41 = (n42 = (n43 = (n44 = (n45 = (n46 = (n47 = (n48 = (n49 = (n50 = (n51 = (n52 = (n53 = (n54 = (n55 = (n56 = (n57 = (n58 = (n59 = (n60 = (n61 = (n62 = (n63 = (n64 = (n65 = (n66 = (n67 = (n68 = (n69 = (n70 = (n71 = (n72 = (n73 = (n74 = (n75 = (n76 = (n77 = (n78 = (n79 = (n80 = 22)))))))))))))))))))))))))))))))))))))))))))))))))))))))))))))))))))))))))))))));
                        s = "\u0014\u0019|\u0015Z`z\fp";
                        n81 = 21;
                        continue Label_0974_Outer;
                    }
                    case 21: {
                        z2[n23] = intern;
                        n = (n2 = (n3 = (n4 = (n5 = (n6 = (n7 = (n8 = (n9 = (n10 = (n11 = (n12 = (n13 = (n14 = (n15 = (n16 = (n17 = (n18 = (n19 = (n20 = (n21 = (n22 = (n23 = (n24 = (n25 = (n26 = (n27 = (n28 = (n29 = (n30 = (n31 = (n32 = (n33 = (n34 = (n35 = (n36 = (n37 = (n38 = (n39 = (n40 = (n41 = (n42 = (n43 = (n44 = (n45 = (n46 = (n47 = (n48 = (n49 = (n50 = (n51 = (n52 = (n53 = (n54 = (n55 = (n56 = (n57 = (n58 = (n59 = (n60 = (n61 = (n62 = (n63 = (n64 = (n65 = (n66 = (n67 = (n68 = (n69 = (n70 = (n71 = (n72 = (n73 = (n74 = (n75 = (n76 = (n77 = (n78 = (n79 = (n80 = 23)))))))))))))))))))))))))))))))))))))))))))))))))))))))))))))))))))))))))))))));
                        s = "\t~mgZ\u0007orfS\u0006uxkN\u001b";
                        n81 = 22;
                        continue Label_0974_Outer;
                    }
                    case 22: {
                        z2[n24] = intern;
                        n = (n2 = (n3 = (n4 = (n5 = (n6 = (n7 = (n8 = (n9 = (n10 = (n11 = (n12 = (n13 = (n14 = (n15 = (n16 = (n17 = (n18 = (n19 = (n20 = (n21 = (n22 = (n23 = (n24 = (n25 = (n26 = (n27 = (n28 = (n29 = (n30 = (n31 = (n32 = (n33 = (n34 = (n35 = (n36 = (n37 = (n38 = (n39 = (n40 = (n41 = (n42 = (n43 = (n44 = (n45 = (n46 = (n47 = (n48 = (n49 = (n50 = (n51 = (n52 = (n53 = (n54 = (n55 = (n56 = (n57 = (n58 = (n59 = (n60 = (n61 = (n62 = (n63 = (n64 = (n65 = (n66 = (n67 = (n68 = (n69 = (n70 = (n71 = (n72 = (n73 = (n74 = (n75 = (n76 = (n77 = (n78 = (n79 = (n80 = 24)))))))))))))))))))))))))))))))))))))))))))))))))))))))))))))))))))))))))))))));
                        s = "eo\u001b\u007f%\t\u0013m\u000b@";
                        n81 = 23;
                        continue Label_0974_Outer;
                    }
                    case 23: {
                        z2[n25] = intern;
                        n = (n2 = (n3 = (n4 = (n5 = (n6 = (n7 = (n8 = (n9 = (n10 = (n11 = (n12 = (n13 = (n14 = (n15 = (n16 = (n17 = (n18 = (n19 = (n20 = (n21 = (n22 = (n23 = (n24 = (n25 = (n26 = (n27 = (n28 = (n29 = (n30 = (n31 = (n32 = (n33 = (n34 = (n35 = (n36 = (n37 = (n38 = (n39 = (n40 = (n41 = (n42 = (n43 = (n44 = (n45 = (n46 = (n47 = (n48 = (n49 = (n50 = (n51 = (n52 = (n53 = (n54 = (n55 = (n56 = (n57 = (n58 = (n59 = (n60 = (n61 = (n62 = (n63 = (n64 = (n65 = (n66 = (n67 = (n68 = (n69 = (n70 = (n71 = (n72 = (n73 = (n74 = (n75 = (n76 = (n77 = (n78 = (n79 = (n80 = 25)))))))))))))))))))))))))))))))))))))))))))))))))))))))))))))))))))))))))))))));
                        s = "\u0018{oaD\u0010zf";
                        n81 = 24;
                        continue Label_0974_Outer;
                    }
                    case 24: {
                        z2[n26] = intern;
                        n = (n2 = (n3 = (n4 = (n5 = (n6 = (n7 = (n8 = (n9 = (n10 = (n11 = (n12 = (n13 = (n14 = (n15 = (n16 = (n17 = (n18 = (n19 = (n20 = (n21 = (n22 = (n23 = (n24 = (n25 = (n26 = (n27 = (n28 = (n29 = (n30 = (n31 = (n32 = (n33 = (n34 = (n35 = (n36 = (n37 = (n38 = (n39 = (n40 = (n41 = (n42 = (n43 = (n44 = (n45 = (n46 = (n47 = (n48 = (n49 = (n50 = (n51 = (n52 = (n53 = (n54 = (n55 = (n56 = (n57 = (n58 = (n59 = (n60 = (n61 = (n62 = (n63 = (n64 = (n65 = (n66 = (n67 = (n68 = (n69 = (n70 = (n71 = (n72 = (n73 = (n74 = (n75 = (n76 = (n77 = (n78 = (n79 = (n80 = 26)))))))))))))))))))))))))))))))))))))))))))))))))))))))))))))))))))))))))))))));
                        s = "\r\bx\u0013Ggi\u0012s;\u0013\u000ek\u0003]";
                        n81 = 25;
                        continue Label_0974_Outer;
                    }
                    case 25: {
                        z2[n27] = intern;
                        n = (n2 = (n3 = (n4 = (n5 = (n6 = (n7 = (n8 = (n9 = (n10 = (n11 = (n12 = (n13 = (n14 = (n15 = (n16 = (n17 = (n18 = (n19 = (n20 = (n21 = (n22 = (n23 = (n24 = (n25 = (n26 = (n27 = (n28 = (n29 = (n30 = (n31 = (n32 = (n33 = (n34 = (n35 = (n36 = (n37 = (n38 = (n39 = (n40 = (n41 = (n42 = (n43 = (n44 = (n45 = (n46 = (n47 = (n48 = (n49 = (n50 = (n51 = (n52 = (n53 = (n54 = (n55 = (n56 = (n57 = (n58 = (n59 = (n60 = (n61 = (n62 = (n63 = (n64 = (n65 = (n66 = (n67 = (n68 = (n69 = (n70 = (n71 = (n72 = (n73 = (n74 = (n75 = (n76 = (n77 = (n78 = (n79 = (n80 = 27)))))))))))))))))))))))))))))))))))))))))))))))))))))))))))))))))))))))))))))));
                        s = "~o\u001fa.\u0012\bm\u0005Gzk";
                        n81 = 26;
                        continue Label_0974_Outer;
                    }
                    case 26: {
                        z2[n28] = intern;
                        n = (n2 = (n3 = (n4 = (n5 = (n6 = (n7 = (n8 = (n9 = (n10 = (n11 = (n12 = (n13 = (n14 = (n15 = (n16 = (n17 = (n18 = (n19 = (n20 = (n21 = (n22 = (n23 = (n24 = (n25 = (n26 = (n27 = (n28 = (n29 = (n30 = (n31 = (n32 = (n33 = (n34 = (n35 = (n36 = (n37 = (n38 = (n39 = (n40 = (n41 = (n42 = (n43 = (n44 = (n45 = (n46 = (n47 = (n48 = (n49 = (n50 = (n51 = (n52 = (n53 = (n54 = (n55 = (n56 = (n57 = (n58 = (n59 = (n60 = (n61 = (n62 = (n63 = (n64 = (n65 = (n66 = (n67 = (n68 = (n69 = (n70 = (n71 = (n72 = (n73 = (n74 = (n75 = (n76 = (n77 = (n78 = (n79 = (n80 = 28)))))))))))))))))))))))))))))))))))))))))))))))))))))))))))))))))))))))))))))));
                        s = "\u001fz`{C\u001a\u007fshZ\u001d";
                        n81 = 27;
                        continue Label_0974_Outer;
                    }
                    case 27: {
                        z2[n29] = intern;
                        n = (n2 = (n3 = (n4 = (n5 = (n6 = (n7 = (n8 = (n9 = (n10 = (n11 = (n12 = (n13 = (n14 = (n15 = (n16 = (n17 = (n18 = (n19 = (n20 = (n21 = (n22 = (n23 = (n24 = (n25 = (n26 = (n27 = (n28 = (n29 = (n30 = (n31 = (n32 = (n33 = (n34 = (n35 = (n36 = (n37 = (n38 = (n39 = (n40 = (n41 = (n42 = (n43 = (n44 = (n45 = (n46 = (n47 = (n48 = (n49 = (n50 = (n51 = (n52 = (n53 = (n54 = (n55 = (n56 = (n57 = (n58 = (n59 = (n60 = (n61 = (n62 = (n63 = (n64 = (n65 = (n66 = (n67 = (n68 = (n69 = (n70 = (n71 = (n72 = (n73 = (n74 = (n75 = (n76 = (n77 = (n78 = (n79 = (n80 = 29)))))))))))))))))))))))))))))))))))))))))))))))))))))))))))))))))))))))))))))));
                        s = "ng\fp.\u0002\u0019q\u0003@jf\u0002s*\u001c";
                        n81 = 28;
                        continue Label_0974_Outer;
                    }
                    case 28: {
                        z2[n30] = intern;
                        n = (n2 = (n3 = (n4 = (n5 = (n6 = (n7 = (n8 = (n9 = (n10 = (n11 = (n12 = (n13 = (n14 = (n15 = (n16 = (n17 = (n18 = (n19 = (n20 = (n21 = (n22 = (n23 = (n24 = (n25 = (n26 = (n27 = (n28 = (n29 = (n30 = (n31 = (n32 = (n33 = (n34 = (n35 = (n36 = (n37 = (n38 = (n39 = (n40 = (n41 = (n42 = (n43 = (n44 = (n45 = (n46 = (n47 = (n48 = (n49 = (n50 = (n51 = (n52 = (n53 = (n54 = (n55 = (n56 = (n57 = (n58 = (n59 = (n60 = (n61 = (n62 = (n63 = (n64 = (n65 = (n66 = (n67 = (n68 = (n69 = (n70 = (n71 = (n72 = (n73 = (n74 = (n75 = (n76 = (n77 = (n78 = (n79 = (n80 = 30)))))))))))))))))))))))))))))))))))))))))))))))))))))))))))))))))))))))))))))));
                        s = "\u000e\u0017v\u0001Kvj\bh3\u0011";
                        n81 = 29;
                        continue Label_0974_Outer;
                    }
                    case 29: {
                        z2[n31] = intern;
                        n = (n2 = (n3 = (n4 = (n5 = (n6 = (n7 = (n8 = (n9 = (n10 = (n11 = (n12 = (n13 = (n14 = (n15 = (n16 = (n17 = (n18 = (n19 = (n20 = (n21 = (n22 = (n23 = (n24 = (n25 = (n26 = (n27 = (n28 = (n29 = (n30 = (n31 = (n32 = (n33 = (n34 = (n35 = (n36 = (n37 = (n38 = (n39 = (n40 = (n41 = (n42 = (n43 = (n44 = (n45 = (n46 = (n47 = (n48 = (n49 = (n50 = (n51 = (n52 = (n53 = (n54 = (n55 = (n56 = (n57 = (n58 = (n59 = (n60 = (n61 = (n62 = (n63 = (n64 = (n65 = (n66 = (n67 = (n68 = (n69 = (n70 = (n71 = (n72 = (n73 = (n74 = (n75 = (n76 = (n77 = (n78 = (n79 = (n80 = 31)))))))))))))))))))))))))))))))))))))))))))))))))))))))))))))))))))))))))))))));
                        s = "\u001bjexR\u001ddwjW\tn~cX\f";
                        n81 = 30;
                        continue Label_0974_Outer;
                    }
                    case 30: {
                        z2[n32] = intern;
                        n = (n2 = (n3 = (n4 = (n5 = (n6 = (n7 = (n8 = (n9 = (n10 = (n11 = (n12 = (n13 = (n14 = (n15 = (n16 = (n17 = (n18 = (n19 = (n20 = (n21 = (n22 = (n23 = (n24 = (n25 = (n26 = (n27 = (n28 = (n29 = (n30 = (n31 = (n32 = (n33 = (n34 = (n35 = (n36 = (n37 = (n38 = (n39 = (n40 = (n41 = (n42 = (n43 = (n44 = (n45 = (n46 = (n47 = (n48 = (n49 = (n50 = (n51 = (n52 = (n53 = (n54 = (n55 = (n56 = (n57 = (n58 = (n59 = (n60 = (n61 = (n62 = (n63 = (n64 = (n65 = (n66 = (n67 = (n68 = (n69 = (n70 = (n71 = (n72 = (n73 = (n74 = (n75 = (n76 = (n77 = (n78 = (n79 = (n80 = 32)))))))))))))))))))))))))))))))))))))))))))))))))))))))))))))))))))))))))))))));
                        s = "\txuyH\bwrgO\u001aqix";
                        n81 = 31;
                        continue Label_0974_Outer;
                    }
                    case 31: {
                        z2[n33] = intern;
                        n = (n2 = (n3 = (n4 = (n5 = (n6 = (n7 = (n8 = (n9 = (n10 = (n11 = (n12 = (n13 = (n14 = (n15 = (n16 = (n17 = (n18 = (n19 = (n20 = (n21 = (n22 = (n23 = (n24 = (n25 = (n26 = (n27 = (n28 = (n29 = (n30 = (n31 = (n32 = (n33 = (n34 = (n35 = (n36 = (n37 = (n38 = (n39 = (n40 = (n41 = (n42 = (n43 = (n44 = (n45 = (n46 = (n47 = (n48 = (n49 = (n50 = (n51 = (n52 = (n53 = (n54 = (n55 = (n56 = (n57 = (n58 = (n59 = (n60 = (n61 = (n62 = (n63 = (n64 = (n65 = (n66 = (n67 = (n68 = (n69 = (n70 = (n71 = (n72 = (n73 = (n74 = (n75 = (n76 = (n77 = (n78 = (n79 = (n80 = 33)))))))))))))))))))))))))))))))))))))))))))))))))))))))))))))))))))))))))))))));
                        s = "\u000e\u000e|\u000fBvz\u0004j;\u0013";
                        n81 = 32;
                        continue Label_0974_Outer;
                    }
                    case 32: {
                        z2[n34] = intern;
                        n = (n2 = (n3 = (n4 = (n5 = (n6 = (n7 = (n8 = (n9 = (n10 = (n11 = (n12 = (n13 = (n14 = (n15 = (n16 = (n17 = (n18 = (n19 = (n20 = (n21 = (n22 = (n23 = (n24 = (n25 = (n26 = (n27 = (n28 = (n29 = (n30 = (n31 = (n32 = (n33 = (n34 = (n35 = (n36 = (n37 = (n38 = (n39 = (n40 = (n41 = (n42 = (n43 = (n44 = (n45 = (n46 = (n47 = (n48 = (n49 = (n50 = (n51 = (n52 = (n53 = (n54 = (n55 = (n56 = (n57 = (n58 = (n59 = (n60 = (n61 = (n62 = (n63 = (n64 = (n65 = (n66 = (n67 = (n68 = (n69 = (n70 = (n71 = (n72 = (n73 = (n74 = (n75 = (n76 = (n77 = (n78 = (n79 = (n80 = 34)))))))))))))))))))))))))))))))))))))))))))))))))))))))))))))))))))))))))))))));
                        s = "|`\u0004}5\u000f\u0014f\u0019Zhb\u0001w5\u0013";
                        n81 = 33;
                        continue Label_0974_Outer;
                    }
                    case 33: {
                        z2[n35] = intern;
                        n = (n2 = (n3 = (n4 = (n5 = (n6 = (n7 = (n8 = (n9 = (n10 = (n11 = (n12 = (n13 = (n14 = (n15 = (n16 = (n17 = (n18 = (n19 = (n20 = (n21 = (n22 = (n23 = (n24 = (n25 = (n26 = (n27 = (n28 = (n29 = (n30 = (n31 = (n32 = (n33 = (n34 = (n35 = (n36 = (n37 = (n38 = (n39 = (n40 = (n41 = (n42 = (n43 = (n44 = (n45 = (n46 = (n47 = (n48 = (n49 = (n50 = (n51 = (n52 = (n53 = (n54 = (n55 = (n56 = (n57 = (n58 = (n59 = (n60 = (n61 = (n62 = (n63 = (n64 = (n65 = (n66 = (n67 = (n68 = (n69 = (n70 = (n71 = (n72 = (n73 = (n74 = (n75 = (n76 = (n77 = (n78 = (n79 = (n80 = 35)))))))))))))))))))))))))))))))))))))))))))))))))))))))))))))))))))))))))))))));
                        s = "\u001allfJ\u0017ne~Z\u0007";
                        n81 = 34;
                        continue Label_0974_Outer;
                    }
                    case 34: {
                        z2[n36] = intern;
                        n = (n2 = (n3 = (n4 = (n5 = (n6 = (n7 = (n8 = (n9 = (n10 = (n11 = (n12 = (n13 = (n14 = (n15 = (n16 = (n17 = (n18 = (n19 = (n20 = (n21 = (n22 = (n23 = (n24 = (n25 = (n26 = (n27 = (n28 = (n29 = (n30 = (n31 = (n32 = (n33 = (n34 = (n35 = (n36 = (n37 = (n38 = (n39 = (n40 = (n41 = (n42 = (n43 = (n44 = (n45 = (n46 = (n47 = (n48 = (n49 = (n50 = (n51 = (n52 = (n53 = (n54 = (n55 = (n56 = (n57 = (n58 = (n59 = (n60 = (n61 = (n62 = (n63 = (n64 = (n65 = (n66 = (n67 = (n68 = (n69 = (n70 = (n71 = (n72 = (n73 = (n74 = (n75 = (n76 = (n77 = (n78 = (n79 = (n80 = 36)))))))))))))))))))))))))))))))))))))))))))))))))))))))))))))))))))))))))))))));
                        s = "\u000eileS\u001c\u007fsfT\u000bhynH";
                        n81 = 35;
                        continue Label_0974_Outer;
                    }
                    case 35: {
                        z2[n37] = intern;
                        n = (n2 = (n3 = (n4 = (n5 = (n6 = (n7 = (n8 = (n9 = (n10 = (n11 = (n12 = (n13 = (n14 = (n15 = (n16 = (n17 = (n18 = (n19 = (n20 = (n21 = (n22 = (n23 = (n24 = (n25 = (n26 = (n27 = (n28 = (n29 = (n30 = (n31 = (n32 = (n33 = (n34 = (n35 = (n36 = (n37 = (n38 = (n39 = (n40 = (n41 = (n42 = (n43 = (n44 = (n45 = (n46 = (n47 = (n48 = (n49 = (n50 = (n51 = (n52 = (n53 = (n54 = (n55 = (n56 = (n57 = (n58 = (n59 = (n60 = (n61 = (n62 = (n63 = (n64 = (n65 = (n66 = (n67 = (n68 = (n69 = (n70 = (n71 = (n72 = (n73 = (n74 = (n75 = (n76 = (n77 = (n78 = (n79 = (n80 = 37)))))))))))))))))))))))))))))))))))))))))))))))))))))))))))))))))))))))))))))));
                        s = "\fmdgE\u001co~dR\u0019";
                        n81 = 36;
                        continue Label_0974_Outer;
                    }
                    case 36: {
                        z2[n38] = intern;
                        n = (n2 = (n3 = (n4 = (n5 = (n6 = (n7 = (n8 = (n9 = (n10 = (n11 = (n12 = (n13 = (n14 = (n15 = (n16 = (n17 = (n18 = (n19 = (n20 = (n21 = (n22 = (n23 = (n24 = (n25 = (n26 = (n27 = (n28 = (n29 = (n30 = (n31 = (n32 = (n33 = (n34 = (n35 = (n36 = (n37 = (n38 = (n39 = (n40 = (n41 = (n42 = (n43 = (n44 = (n45 = (n46 = (n47 = (n48 = (n49 = (n50 = (n51 = (n52 = (n53 = (n54 = (n55 = (n56 = (n57 = (n58 = (n59 = (n60 = (n61 = (n62 = (n63 = (n64 = (n65 = (n66 = (n67 = (n68 = (n69 = (n70 = (n71 = (n72 = (n73 = (n74 = (n75 = (n76 = (n77 = (n78 = (n79 = (n80 = 38)))))))))))))))))))))))))))))))))))))))))))))))))))))))))))))))))))))))))))))));
                        s = "\u001bjexR\u001ddgnV\u0004c";
                        n81 = 37;
                        continue Label_0974_Outer;
                    }
                    case 37: {
                        z2[n39] = intern;
                        n = (n2 = (n3 = (n4 = (n5 = (n6 = (n7 = (n8 = (n9 = (n10 = (n11 = (n12 = (n13 = (n14 = (n15 = (n16 = (n17 = (n18 = (n19 = (n20 = (n21 = (n22 = (n23 = (n24 = (n25 = (n26 = (n27 = (n28 = (n29 = (n30 = (n31 = (n32 = (n33 = (n34 = (n35 = (n36 = (n37 = (n38 = (n39 = (n40 = (n41 = (n42 = (n43 = (n44 = (n45 = (n46 = (n47 = (n48 = (n49 = (n50 = (n51 = (n52 = (n53 = (n54 = (n55 = (n56 = (n57 = (n58 = (n59 = (n60 = (n61 = (n62 = (n63 = (n64 = (n65 = (n66 = (n67 = (n68 = (n69 = (n70 = (n71 = (n72 = (n73 = (n74 = (n75 = (n76 = (n77 = (n78 = (n79 = (n80 = 39)))))))))))))))))))))))))))))))))))))))))))))))))))))))))))))))))))))))))))))));
                        s = "z~\u0004l3\t\u0005o\u001fBhz\u001fw9\u0018";
                        n81 = 38;
                        continue Label_0974_Outer;
                    }
                    case 38: {
                        z2[n40] = intern;
                        n = (n2 = (n3 = (n4 = (n5 = (n6 = (n7 = (n8 = (n9 = (n10 = (n11 = (n12 = (n13 = (n14 = (n15 = (n16 = (n17 = (n18 = (n19 = (n20 = (n21 = (n22 = (n23 = (n24 = (n25 = (n26 = (n27 = (n28 = (n29 = (n30 = (n31 = (n32 = (n33 = (n34 = (n35 = (n36 = (n37 = (n38 = (n39 = (n40 = (n41 = (n42 = (n43 = (n44 = (n45 = (n46 = (n47 = (n48 = (n49 = (n50 = (n51 = (n52 = (n53 = (n54 = (n55 = (n56 = (n57 = (n58 = (n59 = (n60 = (n61 = (n62 = (n63 = (n64 = (n65 = (n66 = (n67 = (n68 = (n69 = (n70 = (n71 = (n72 = (n73 = (n74 = (n75 = (n76 = (n77 = (n78 = (n79 = (n80 = 40)))))))))))))))))))))))))))))))))))))))))))))))))))))))))))))))))))))))))))))));
                        s = "\u001bjexR\u001ddfr[\u001cn";
                        n81 = 39;
                        continue Label_0974_Outer;
                    }
                    case 39: {
                        z2[n41] = intern;
                        n = (n2 = (n3 = (n4 = (n5 = (n6 = (n7 = (n8 = (n9 = (n10 = (n11 = (n12 = (n13 = (n14 = (n15 = (n16 = (n17 = (n18 = (n19 = (n20 = (n21 = (n22 = (n23 = (n24 = (n25 = (n26 = (n27 = (n28 = (n29 = (n30 = (n31 = (n32 = (n33 = (n34 = (n35 = (n36 = (n37 = (n38 = (n39 = (n40 = (n41 = (n42 = (n43 = (n44 = (n45 = (n46 = (n47 = (n48 = (n49 = (n50 = (n51 = (n52 = (n53 = (n54 = (n55 = (n56 = (n57 = (n58 = (n59 = (n60 = (n61 = (n62 = (n63 = (n64 = (n65 = (n66 = (n67 = (n68 = (n69 = (n70 = (n71 = (n72 = (n73 = (n74 = (n75 = (n76 = (n77 = (n78 = (n79 = (n80 = 41)))))))))))))))))))))))))))))))))))))))))))))))))))))))))))))))))))))))))))))));
                        s = "hl\u0014m)\u001c\u0016f\u001aO{o\u001ew.\u0018";
                        n81 = 40;
                        continue Label_0974_Outer;
                    }
                    case 40: {
                        z2[n42] = intern;
                        n = (n2 = (n3 = (n4 = (n5 = (n6 = (n7 = (n8 = (n9 = (n10 = (n11 = (n12 = (n13 = (n14 = (n15 = (n16 = (n17 = (n18 = (n19 = (n20 = (n21 = (n22 = (n23 = (n24 = (n25 = (n26 = (n27 = (n28 = (n29 = (n30 = (n31 = (n32 = (n33 = (n34 = (n35 = (n36 = (n37 = (n38 = (n39 = (n40 = (n41 = (n42 = (n43 = (n44 = (n45 = (n46 = (n47 = (n48 = (n49 = (n50 = (n51 = (n52 = (n53 = (n54 = (n55 = (n56 = (n57 = (n58 = (n59 = (n60 = (n61 = (n62 = (n63 = (n64 = (n65 = (n66 = (n67 = (n68 = (n69 = (n70 = (n71 = (n72 = (n73 = (n74 = (n75 = (n76 = (n77 = (n78 = (n79 = (n80 = 42)))))))))))))))))))))))))))))))))))))))))))))))))))))))))))))))))))))))))))))));
                        s = "\u000e\np\u0018G}q\u0006\u007f6\r\u0012p\u001eK";
                        n81 = 41;
                        continue Label_0974_Outer;
                    }
                    case 41: {
                        z2[n43] = intern;
                        n = (n2 = (n3 = (n4 = (n5 = (n6 = (n7 = (n8 = (n9 = (n10 = (n11 = (n12 = (n13 = (n14 = (n15 = (n16 = (n17 = (n18 = (n19 = (n20 = (n21 = (n22 = (n23 = (n24 = (n25 = (n26 = (n27 = (n28 = (n29 = (n30 = (n31 = (n32 = (n33 = (n34 = (n35 = (n36 = (n37 = (n38 = (n39 = (n40 = (n41 = (n42 = (n43 = (n44 = (n45 = (n46 = (n47 = (n48 = (n49 = (n50 = (n51 = (n52 = (n53 = (n54 = (n55 = (n56 = (n57 = (n58 = (n59 = (n60 = (n61 = (n62 = (n63 = (n64 = (n65 = (n66 = (n67 = (n68 = (n69 = (n70 = (n71 = (n72 = (n73 = (n74 = (n75 = (n76 = (n77 = (n78 = (n79 = (n80 = 43)))))))))))))))))))))))))))))))))))))))))))))))))))))))))))))))))))))))))))))));
                        s = "\tvncU\u0006d\u007fjN";
                        n81 = 42;
                        continue Label_0974_Outer;
                    }
                    case 42: {
                        z2[n44] = intern;
                        n = (n2 = (n3 = (n4 = (n5 = (n6 = (n7 = (n8 = (n9 = (n10 = (n11 = (n12 = (n13 = (n14 = (n15 = (n16 = (n17 = (n18 = (n19 = (n20 = (n21 = (n22 = (n23 = (n24 = (n25 = (n26 = (n27 = (n28 = (n29 = (n30 = (n31 = (n32 = (n33 = (n34 = (n35 = (n36 = (n37 = (n38 = (n39 = (n40 = (n41 = (n42 = (n43 = (n44 = (n45 = (n46 = (n47 = (n48 = (n49 = (n50 = (n51 = (n52 = (n53 = (n54 = (n55 = (n56 = (n57 = (n58 = (n59 = (n60 = (n61 = (n62 = (n63 = (n64 = (n65 = (n66 = (n67 = (n68 = (n69 = (n70 = (n71 = (n72 = (n73 = (n74 = (n75 = (n76 = (n77 = (n78 = (n79 = (n80 = 44)))))))))))))))))))))))))))))))))))))))))))))))))))))))))))))))))))))))))))))));
                        s = "\u007fa\u0004z%\u000f\u001bo\u000bIl|";
                        n81 = 43;
                        continue Label_0974_Outer;
                    }
                    case 43: {
                        z2[n45] = intern;
                        n = (n2 = (n3 = (n4 = (n5 = (n6 = (n7 = (n8 = (n9 = (n10 = (n11 = (n12 = (n13 = (n14 = (n15 = (n16 = (n17 = (n18 = (n19 = (n20 = (n21 = (n22 = (n23 = (n24 = (n25 = (n26 = (n27 = (n28 = (n29 = (n30 = (n31 = (n32 = (n33 = (n34 = (n35 = (n36 = (n37 = (n38 = (n39 = (n40 = (n41 = (n42 = (n43 = (n44 = (n45 = (n46 = (n47 = (n48 = (n49 = (n50 = (n51 = (n52 = (n53 = (n54 = (n55 = (n56 = (n57 = (n58 = (n59 = (n60 = (n61 = (n62 = (n63 = (n64 = (n65 = (n66 = (n67 = (n68 = (n69 = (n70 = (n71 = (n72 = (n73 = (n74 = (n75 = (n76 = (n77 = (n78 = (n79 = (n80 = 45)))))))))))))))))))))))))))))))))))))))))))))))))))))))))))))))))))))))))))))));
                        s = "\u0005{kzR\f";
                        n81 = 44;
                        continue Label_0974_Outer;
                    }
                    case 44: {
                        z2[n46] = intern;
                        n = (n2 = (n3 = (n4 = (n5 = (n6 = (n7 = (n8 = (n9 = (n10 = (n11 = (n12 = (n13 = (n14 = (n15 = (n16 = (n17 = (n18 = (n19 = (n20 = (n21 = (n22 = (n23 = (n24 = (n25 = (n26 = (n27 = (n28 = (n29 = (n30 = (n31 = (n32 = (n33 = (n34 = (n35 = (n36 = (n37 = (n38 = (n39 = (n40 = (n41 = (n42 = (n43 = (n44 = (n45 = (n46 = (n47 = (n48 = (n49 = (n50 = (n51 = (n52 = (n53 = (n54 = (n55 = (n56 = (n57 = (n58 = (n59 = (n60 = (n61 = (n62 = (n63 = (n64 = (n65 = (n66 = (n67 = (n68 = (n69 = (n70 = (n71 = (n72 = (n73 = (n74 = (n75 = (n76 = (n77 = (n78 = (n79 = (n80 = 46)))))))))))))))))))))))))))))))))))))))))))))))))))))))))))))))))))))))))))))));
                        s = "~a\u0001n?\u000f\u000ep\u0004Il|";
                        n81 = 45;
                        continue Label_0974_Outer;
                    }
                    case 45: {
                        z2[n47] = intern;
                        n = (n2 = (n3 = (n4 = (n5 = (n6 = (n7 = (n8 = (n9 = (n10 = (n11 = (n12 = (n13 = (n14 = (n15 = (n16 = (n17 = (n18 = (n19 = (n20 = (n21 = (n22 = (n23 = (n24 = (n25 = (n26 = (n27 = (n28 = (n29 = (n30 = (n31 = (n32 = (n33 = (n34 = (n35 = (n36 = (n37 = (n38 = (n39 = (n40 = (n41 = (n42 = (n43 = (n44 = (n45 = (n46 = (n47 = (n48 = (n49 = (n50 = (n51 = (n52 = (n53 = (n54 = (n55 = (n56 = (n57 = (n58 = (n59 = (n60 = (n61 = (n62 = (n63 = (n64 = (n65 = (n66 = (n67 = (n68 = (n69 = (n70 = (n71 = (n72 = (n73 = (n74 = (n75 = (n76 = (n77 = (n78 = (n79 = (n80 = 47)))))))))))))))))))))))))))))))))))))))))))))))))))))))))))))))))))))))))))))));
                        s = "\u0001xey";
                        n81 = 46;
                        continue Label_0974_Outer;
                    }
                    case 46: {
                        z2[n48] = intern;
                        n = (n2 = (n3 = (n4 = (n5 = (n6 = (n7 = (n8 = (n9 = (n10 = (n11 = (n12 = (n13 = (n14 = (n15 = (n16 = (n17 = (n18 = (n19 = (n20 = (n21 = (n22 = (n23 = (n24 = (n25 = (n26 = (n27 = (n28 = (n29 = (n30 = (n31 = (n32 = (n33 = (n34 = (n35 = (n36 = (n37 = (n38 = (n39 = (n40 = (n41 = (n42 = (n43 = (n44 = (n45 = (n46 = (n47 = (n48 = (n49 = (n50 = (n51 = (n52 = (n53 = (n54 = (n55 = (n56 = (n57 = (n58 = (n59 = (n60 = (n61 = (n62 = (n63 = (n64 = (n65 = (n66 = (n67 = (n68 = (n69 = (n70 = (n71 = (n72 = (n73 = (n74 = (n75 = (n76 = (n77 = (n78 = (n79 = (n80 = 48)))))))))))))))))))))))))))))))))))))))))))))))))))))))))))))))))))))))))))))));
                        s = "\u0019\u001fj\u000f\\}q\u001ag(\u0010";
                        n81 = 47;
                        continue Label_0974_Outer;
                    }
                    case 47: {
                        z2[n49] = intern;
                        n = (n2 = (n3 = (n4 = (n5 = (n6 = (n7 = (n8 = (n9 = (n10 = (n11 = (n12 = (n13 = (n14 = (n15 = (n16 = (n17 = (n18 = (n19 = (n20 = (n21 = (n22 = (n23 = (n24 = (n25 = (n26 = (n27 = (n28 = (n29 = (n30 = (n31 = (n32 = (n33 = (n34 = (n35 = (n36 = (n37 = (n38 = (n39 = (n40 = (n41 = (n42 = (n43 = (n44 = (n45 = (n46 = (n47 = (n48 = (n49 = (n50 = (n51 = (n52 = (n53 = (n54 = (n55 = (n56 = (n57 = (n58 = (n59 = (n60 = (n61 = (n62 = (n63 = (n64 = (n65 = (n66 = (n67 = (n68 = (n69 = (n70 = (n71 = (n72 = (n73 = (n74 = (n75 = (n76 = (n77 = (n78 = (n79 = (n80 = 49)))))))))))))))))))))))))))))))))))))))))))))))))))))))))))))))))))))))))))))));
                        s = "\u001akdyS\u001cek\u007fO\u0001zyyS\u000b\u007f";
                        n81 = 48;
                        continue Label_0974_Outer;
                    }
                    case 48: {
                        z2[n50] = intern;
                        n = (n2 = (n3 = (n4 = (n5 = (n6 = (n7 = (n8 = (n9 = (n10 = (n11 = (n12 = (n13 = (n14 = (n15 = (n16 = (n17 = (n18 = (n19 = (n20 = (n21 = (n22 = (n23 = (n24 = (n25 = (n26 = (n27 = (n28 = (n29 = (n30 = (n31 = (n32 = (n33 = (n34 = (n35 = (n36 = (n37 = (n38 = (n39 = (n40 = (n41 = (n42 = (n43 = (n44 = (n45 = (n46 = (n47 = (n48 = (n49 = (n50 = (n51 = (n52 = (n53 = (n54 = (n55 = (n56 = (n57 = (n58 = (n59 = (n60 = (n61 = (n62 = (n63 = (n64 = (n65 = (n66 = (n67 = (n68 = (n69 = (n70 = (n71 = (n72 = (n73 = (n74 = (n75 = (n76 = (n77 = (n78 = (n79 = (n80 = 50)))))))))))))))))))))))))))))))))))))))))))))))))))))))))))))))))))))))))))))));
                        s = "\u001a\u0013x\u0004Zvk\u0003j";
                        n81 = 49;
                        continue Label_0974_Outer;
                    }
                    case 49: {
                        z2[n51] = intern;
                        n = (n2 = (n3 = (n4 = (n5 = (n6 = (n7 = (n8 = (n9 = (n10 = (n11 = (n12 = (n13 = (n14 = (n15 = (n16 = (n17 = (n18 = (n19 = (n20 = (n21 = (n22 = (n23 = (n24 = (n25 = (n26 = (n27 = (n28 = (n29 = (n30 = (n31 = (n32 = (n33 = (n34 = (n35 = (n36 = (n37 = (n38 = (n39 = (n40 = (n41 = (n42 = (n43 = (n44 = (n45 = (n46 = (n47 = (n48 = (n49 = (n50 = (n51 = (n52 = (n53 = (n54 = (n55 = (n56 = (n57 = (n58 = (n59 = (n60 = (n61 = (n62 = (n63 = (n64 = (n65 = (n66 = (n67 = (n68 = (n69 = (n70 = (n71 = (n72 = (n73 = (n74 = (n75 = (n76 = (n77 = (n78 = (n79 = (n80 = 51)))))))))))))))))))))))))))))))))))))))))))))))))))))))))))))))))))))))))))))));
                        s = "\u007fa\u0004z%\u000e\u0012p\fZl|";
                        n81 = 50;
                        continue Label_0974_Outer;
                    }
                    case 50: {
                        z2[n52] = intern;
                        n = (n2 = (n3 = (n4 = (n5 = (n6 = (n7 = (n8 = (n9 = (n10 = (n11 = (n12 = (n13 = (n14 = (n15 = (n16 = (n17 = (n18 = (n19 = (n20 = (n21 = (n22 = (n23 = (n24 = (n25 = (n26 = (n27 = (n28 = (n29 = (n30 = (n31 = (n32 = (n33 = (n34 = (n35 = (n36 = (n37 = (n38 = (n39 = (n40 = (n41 = (n42 = (n43 = (n44 = (n45 = (n46 = (n47 = (n48 = (n49 = (n50 = (n51 = (n52 = (n53 = (n54 = (n55 = (n56 = (n57 = (n58 = (n59 = (n60 = (n61 = (n62 = (n63 = (n64 = (n65 = (n66 = (n67 = (n68 = (n69 = (n70 = (n71 = (n72 = (n73 = (n74 = (n75 = (n76 = (n77 = (n78 = (n79 = (n80 = 52)))))))))))))))))))))))))))))))))))))))))))))))))))))))))))))))))))))))))))))));
                        s = "\no`fD\buy";
                        n81 = 51;
                        continue Label_0974_Outer;
                    }
                    case 51: {
                        z2[n53] = intern;
                        n = (n2 = (n3 = (n4 = (n5 = (n6 = (n7 = (n8 = (n9 = (n10 = (n11 = (n12 = (n13 = (n14 = (n15 = (n16 = (n17 = (n18 = (n19 = (n20 = (n21 = (n22 = (n23 = (n24 = (n25 = (n26 = (n27 = (n28 = (n29 = (n30 = (n31 = (n32 = (n33 = (n34 = (n35 = (n36 = (n37 = (n38 = (n39 = (n40 = (n41 = (n42 = (n43 = (n44 = (n45 = (n46 = (n47 = (n48 = (n49 = (n50 = (n51 = (n52 = (n53 = (n54 = (n55 = (n56 = (n57 = (n58 = (n59 = (n60 = (n61 = (n62 = (n63 = (n64 = (n65 = (n66 = (n67 = (n68 = (n69 = (n70 = (n71 = (n72 = (n73 = (n74 = (n75 = (n76 = (n77 = (n78 = (n79 = (n80 = 53)))))))))))))))))))))))))))))))))))))))))))))))))))))))))))))))))))))))))))))));
                        s = "\u000f\u000fw\u000fQdg\u0003q.\u001c\u000fk";
                        n81 = 52;
                        continue Label_0974_Outer;
                    }
                    case 52: {
                        z2[n54] = intern;
                        n = (n2 = (n3 = (n4 = (n5 = (n6 = (n7 = (n8 = (n9 = (n10 = (n11 = (n12 = (n13 = (n14 = (n15 = (n16 = (n17 = (n18 = (n19 = (n20 = (n21 = (n22 = (n23 = (n24 = (n25 = (n26 = (n27 = (n28 = (n29 = (n30 = (n31 = (n32 = (n33 = (n34 = (n35 = (n36 = (n37 = (n38 = (n39 = (n40 = (n41 = (n42 = (n43 = (n44 = (n45 = (n46 = (n47 = (n48 = (n49 = (n50 = (n51 = (n52 = (n53 = (n54 = (n55 = (n56 = (n57 = (n58 = (n59 = (n60 = (n61 = (n62 = (n63 = (n64 = (n65 = (n66 = (n67 = (n68 = (n69 = (n70 = (n71 = (n72 = (n73 = (n74 = (n75 = (n76 = (n77 = (n78 = (n79 = (n80 = 54)))))))))))))))))))))))))))))))))))))))))))))))))))))))))))))))))))))))))))))));
                        s = "\u000bz\u007f`_\u001aexeZ\r";
                        n81 = 53;
                        continue Label_0974_Outer;
                    }
                    case 53: {
                        z2[n55] = intern;
                        n = (n2 = (n3 = (n4 = (n5 = (n6 = (n7 = (n8 = (n9 = (n10 = (n11 = (n12 = (n13 = (n14 = (n15 = (n16 = (n17 = (n18 = (n19 = (n20 = (n21 = (n22 = (n23 = (n24 = (n25 = (n26 = (n27 = (n28 = (n29 = (n30 = (n31 = (n32 = (n33 = (n34 = (n35 = (n36 = (n37 = (n38 = (n39 = (n40 = (n41 = (n42 = (n43 = (n44 = (n45 = (n46 = (n47 = (n48 = (n49 = (n50 = (n51 = (n52 = (n53 = (n54 = (n55 = (n56 = (n57 = (n58 = (n59 = (n60 = (n61 = (n62 = (n63 = (n64 = (n65 = (n66 = (n67 = (n68 = (n69 = (n70 = (n71 = (n72 = (n73 = (n74 = (n75 = (n76 = (n77 = (n78 = (n79 = (n80 = 55)))))))))))))))))))))))))))))))))))))))))))))))))))))))))))))))))))))))))))))));
                        s = "\u001akdyS\u001ceaeH\u0018nd\u007fU";
                        n81 = 54;
                        continue Label_0974_Outer;
                    }
                    case 54: {
                        z2[n56] = intern;
                        n = (n2 = (n3 = (n4 = (n5 = (n6 = (n7 = (n8 = (n9 = (n10 = (n11 = (n12 = (n13 = (n14 = (n15 = (n16 = (n17 = (n18 = (n19 = (n20 = (n21 = (n22 = (n23 = (n24 = (n25 = (n26 = (n27 = (n28 = (n29 = (n30 = (n31 = (n32 = (n33 = (n34 = (n35 = (n36 = (n37 = (n38 = (n39 = (n40 = (n41 = (n42 = (n43 = (n44 = (n45 = (n46 = (n47 = (n48 = (n49 = (n50 = (n51 = (n52 = (n53 = (n54 = (n55 = (n56 = (n57 = (n58 = (n59 = (n60 = (n61 = (n62 = (n63 = (n64 = (n65 = (n66 = (n67 = (n68 = (n69 = (n70 = (n71 = (n72 = (n73 = (n74 = (n75 = (n76 = (n77 = (n78 = (n79 = (n80 = 56)))))))))))))))))))))))))))))))))))))))))))))))))))))))))))))))))))))))))))))));
                        s = "\u001dzadT\u0017xikH\u001d";
                        n81 = 55;
                        continue Label_0974_Outer;
                    }
                    case 55: {
                        z2[n57] = intern;
                        n = (n2 = (n3 = (n4 = (n5 = (n6 = (n7 = (n8 = (n9 = (n10 = (n11 = (n12 = (n13 = (n14 = (n15 = (n16 = (n17 = (n18 = (n19 = (n20 = (n21 = (n22 = (n23 = (n24 = (n25 = (n26 = (n27 = (n28 = (n29 = (n30 = (n31 = (n32 = (n33 = (n34 = (n35 = (n36 = (n37 = (n38 = (n39 = (n40 = (n41 = (n42 = (n43 = (n44 = (n45 = (n46 = (n47 = (n48 = (n49 = (n50 = (n51 = (n52 = (n53 = (n54 = (n55 = (n56 = (n57 = (n58 = (n59 = (n60 = (n61 = (n62 = (n63 = (n64 = (n65 = (n66 = (n67 = (n68 = (n69 = (n70 = (n71 = (n72 = (n73 = (n74 = (n75 = (n76 = (n77 = (n78 = (n79 = (n80 = 57)))))))))))))))))))))))))))))))))))))))))))))))))))))))))))))))))))))))))))))));
                        s = "\u001akdyS\u001ce{eW\u000f";
                        n81 = 56;
                        continue Label_0974_Outer;
                    }
                    case 56: {
                        z2[n58] = intern;
                        n = (n2 = (n3 = (n4 = (n5 = (n6 = (n7 = (n8 = (n9 = (n10 = (n11 = (n12 = (n13 = (n14 = (n15 = (n16 = (n17 = (n18 = (n19 = (n20 = (n21 = (n22 = (n23 = (n24 = (n25 = (n26 = (n27 = (n28 = (n29 = (n30 = (n31 = (n32 = (n33 = (n34 = (n35 = (n36 = (n37 = (n38 = (n39 = (n40 = (n41 = (n42 = (n43 = (n44 = (n45 = (n46 = (n47 = (n48 = (n49 = (n50 = (n51 = (n52 = (n53 = (n54 = (n55 = (n56 = (n57 = (n58 = (n59 = (n60 = (n61 = (n62 = (n63 = (n64 = (n65 = (n66 = (n67 = (n68 = (n69 = (n70 = (n71 = (n72 = (n73 = (n74 = (n75 = (n76 = (n77 = (n78 = (n79 = (n80 = 58)))))))))))))))))))))))))))))))))))))))))))))))))))))))))))))))))))))))))))))));
                        s = "\u000e\np\u0018G}q\u000eq9\u0016\u001bm\u0018Gjk";
                        n81 = 57;
                        continue Label_0974_Outer;
                    }
                    case 57: {
                        z2[n59] = intern;
                        n = (n2 = (n3 = (n4 = (n5 = (n6 = (n7 = (n8 = (n9 = (n10 = (n11 = (n12 = (n13 = (n14 = (n15 = (n16 = (n17 = (n18 = (n19 = (n20 = (n21 = (n22 = (n23 = (n24 = (n25 = (n26 = (n27 = (n28 = (n29 = (n30 = (n31 = (n32 = (n33 = (n34 = (n35 = (n36 = (n37 = (n38 = (n39 = (n40 = (n41 = (n42 = (n43 = (n44 = (n45 = (n46 = (n47 = (n48 = (n49 = (n50 = (n51 = (n52 = (n53 = (n54 = (n55 = (n56 = (n57 = (n58 = (n59 = (n60 = (n61 = (n62 = (n63 = (n64 = (n65 = (n66 = (n67 = (n68 = (n69 = (n70 = (n71 = (n72 = (n73 = (n74 = (n75 = (n76 = (n77 = (n78 = (n79 = (n80 = 59)))))))))))))))))))))))))))))))))))))))))))))))))))))))))))))))))))))))))))))));
                        s = "\u001bz{nT\u0007o\u007fuW\u0006xy~I";
                        n81 = 58;
                        continue Label_0974_Outer;
                    }
                    case 58: {
                        z2[n60] = intern;
                        n = (n2 = (n3 = (n4 = (n5 = (n6 = (n7 = (n8 = (n9 = (n10 = (n11 = (n12 = (n13 = (n14 = (n15 = (n16 = (n17 = (n18 = (n19 = (n20 = (n21 = (n22 = (n23 = (n24 = (n25 = (n26 = (n27 = (n28 = (n29 = (n30 = (n31 = (n32 = (n33 = (n34 = (n35 = (n36 = (n37 = (n38 = (n39 = (n40 = (n41 = (n42 = (n43 = (n44 = (n45 = (n46 = (n47 = (n48 = (n49 = (n50 = (n51 = (n52 = (n53 = (n54 = (n55 = (n56 = (n57 = (n58 = (n59 = (n60 = (n61 = (n62 = (n63 = (n64 = (n65 = (n66 = (n67 = (n68 = (n69 = (n70 = (n71 = (n72 = (n73 = (n74 = (n75 = (n76 = (n77 = (n78 = (n79 = (n80 = 60)))))))))))))))))))))))))))))))))))))))))))))))))))))))))))))))))))))))))))))));
                        s = "\u000e\np\u0018G}q\u0019d%\u0016\u0013q";
                        n81 = 59;
                        continue Label_0974_Outer;
                    }
                    case 59: {
                        z2[n61] = intern;
                        n = (n2 = (n3 = (n4 = (n5 = (n6 = (n7 = (n8 = (n9 = (n10 = (n11 = (n12 = (n13 = (n14 = (n15 = (n16 = (n17 = (n18 = (n19 = (n20 = (n21 = (n22 = (n23 = (n24 = (n25 = (n26 = (n27 = (n28 = (n29 = (n30 = (n31 = (n32 = (n33 = (n34 = (n35 = (n36 = (n37 = (n38 = (n39 = (n40 = (n41 = (n42 = (n43 = (n44 = (n45 = (n46 = (n47 = (n48 = (n49 = (n50 = (n51 = (n52 = (n53 = (n54 = (n55 = (n56 = (n57 = (n58 = (n59 = (n60 = (n61 = (n62 = (n63 = (n64 = (n65 = (n66 = (n67 = (n68 = (n69 = (n70 = (n71 = (n72 = (n73 = (n74 = (n75 = (n76 = (n77 = (n78 = (n79 = (n80 = 61)))))))))))))))))))))))))))))))))))))))))))))))))))))))))))))))))))))))))))))));
                        s = "\u001euenD\u001akdeT\rh";
                        n81 = 60;
                        continue Label_0974_Outer;
                    }
                    case 60: {
                        z2[n62] = intern;
                        n = (n2 = (n3 = (n4 = (n5 = (n6 = (n7 = (n8 = (n9 = (n10 = (n11 = (n12 = (n13 = (n14 = (n15 = (n16 = (n17 = (n18 = (n19 = (n20 = (n21 = (n22 = (n23 = (n24 = (n25 = (n26 = (n27 = (n28 = (n29 = (n30 = (n31 = (n32 = (n33 = (n34 = (n35 = (n36 = (n37 = (n38 = (n39 = (n40 = (n41 = (n42 = (n43 = (n44 = (n45 = (n46 = (n47 = (n48 = (n49 = (n50 = (n51 = (n52 = (n53 = (n54 = (n55 = (n56 = (n57 = (n58 = (n59 = (n60 = (n61 = (n62 = (n63 = (n64 = (n65 = (n66 = (n67 = (n68 = (n69 = (n70 = (n71 = (n72 = (n73 = (n74 = (n75 = (n76 = (n77 = (n78 = (n79 = (n80 = 62)))))))))))))))))))))))))))))))))))))))))))))))))))))))))))))))))))))))))))))));
                        s = "z~\u0004l3\t\u0005z\u0005L{o";
                        n81 = 61;
                        continue Label_0974_Outer;
                    }
                    case 61: {
                        z2[n63] = intern;
                        n = (n2 = (n3 = (n4 = (n5 = (n6 = (n7 = (n8 = (n9 = (n10 = (n11 = (n12 = (n13 = (n14 = (n15 = (n16 = (n17 = (n18 = (n19 = (n20 = (n21 = (n22 = (n23 = (n24 = (n25 = (n26 = (n27 = (n28 = (n29 = (n30 = (n31 = (n32 = (n33 = (n34 = (n35 = (n36 = (n37 = (n38 = (n39 = (n40 = (n41 = (n42 = (n43 = (n44 = (n45 = (n46 = (n47 = (n48 = (n49 = (n50 = (n51 = (n52 = (n53 = (n54 = (n55 = (n56 = (n57 = (n58 = (n59 = (n60 = (n61 = (n62 = (n63 = (n64 = (n65 = (n66 = (n67 = (n68 = (n69 = (n70 = (n71 = (n72 = (n73 = (n74 = (n75 = (n76 = (n77 = (n78 = (n79 = (n80 = 63)))))))))))))))))))))))))))))))))))))))))))))))))))))))))))))))))))))))))))))));
                        s = "\nt`{U\u001bnsgT\u001cui";
                        n81 = 62;
                        continue Label_0974_Outer;
                    }
                    case 62: {
                        z2[n64] = intern;
                        n = (n2 = (n3 = (n4 = (n5 = (n6 = (n7 = (n8 = (n9 = (n10 = (n11 = (n12 = (n13 = (n14 = (n15 = (n16 = (n17 = (n18 = (n19 = (n20 = (n21 = (n22 = (n23 = (n24 = (n25 = (n26 = (n27 = (n28 = (n29 = (n30 = (n31 = (n32 = (n33 = (n34 = (n35 = (n36 = (n37 = (n38 = (n39 = (n40 = (n41 = (n42 = (n43 = (n44 = (n45 = (n46 = (n47 = (n48 = (n49 = (n50 = (n51 = (n52 = (n53 = (n54 = (n55 = (n56 = (n57 = (n58 = (n59 = (n60 = (n61 = (n62 = (n63 = (n64 = (n65 = (n66 = (n67 = (n68 = (n69 = (n70 = (n71 = (n72 = (n73 = (n74 = (n75 = (n76 = (n77 = (n78 = (n79 = (n80 = 64)))))))))))))))))))))))))))))))))))))))))))))))))))))))))))))))))))))))))))))));
                        s = "\u001bn~kU\u000e~\u007ftJ\u0004{b~";
                        n81 = 63;
                        continue Label_0974_Outer;
                    }
                    case 63: {
                        z2[n65] = intern;
                        n = (n2 = (n3 = (n4 = (n5 = (n6 = (n7 = (n8 = (n9 = (n10 = (n11 = (n12 = (n13 = (n14 = (n15 = (n16 = (n17 = (n18 = (n19 = (n20 = (n21 = (n22 = (n23 = (n24 = (n25 = (n26 = (n27 = (n28 = (n29 = (n30 = (n31 = (n32 = (n33 = (n34 = (n35 = (n36 = (n37 = (n38 = (n39 = (n40 = (n41 = (n42 = (n43 = (n44 = (n45 = (n46 = (n47 = (n48 = (n49 = (n50 = (n51 = (n52 = (n53 = (n54 = (n55 = (n56 = (n57 = (n58 = (n59 = (n60 = (n61 = (n62 = (n63 = (n64 = (n65 = (n66 = (n67 = (n68 = (n69 = (n70 = (n71 = (n72 = (n73 = (n74 = (n75 = (n76 = (n77 = (n78 = (n79 = (n80 = 65)))))))))))))))))))))))))))))))))))))))))))))))))))))))))))))))))))))))))))))));
                        s = "\u001bjexR\u001ddij]\ttbeO\u0001";
                        n81 = 64;
                        continue Label_0974_Outer;
                    }
                    case 64: {
                        z2[n66] = intern;
                        n = (n2 = (n3 = (n4 = (n5 = (n6 = (n7 = (n8 = (n9 = (n10 = (n11 = (n12 = (n13 = (n14 = (n15 = (n16 = (n17 = (n18 = (n19 = (n20 = (n21 = (n22 = (n23 = (n24 = (n25 = (n26 = (n27 = (n28 = (n29 = (n30 = (n31 = (n32 = (n33 = (n34 = (n35 = (n36 = (n37 = (n38 = (n39 = (n40 = (n41 = (n42 = (n43 = (n44 = (n45 = (n46 = (n47 = (n48 = (n49 = (n50 = (n51 = (n52 = (n53 = (n54 = (n55 = (n56 = (n57 = (n58 = (n59 = (n60 = (n61 = (n62 = (n63 = (n64 = (n65 = (n66 = (n67 = (n68 = (n69 = (n70 = (n71 = (n72 = (n73 = (n74 = (n75 = (n76 = (n77 = (n78 = (n79 = (n80 = 66)))))))))))))))))))))))))))))))))))))))))))))))))))))))))))))))))))))))))))))));
                        s = "aa\u0003{#\u0002\u0018x\u000eIl|";
                        n81 = 65;
                        continue Label_0974_Outer;
                    }
                    case 65: {
                        z2[n67] = intern;
                        n = (n2 = (n3 = (n4 = (n5 = (n6 = (n7 = (n8 = (n9 = (n10 = (n11 = (n12 = (n13 = (n14 = (n15 = (n16 = (n17 = (n18 = (n19 = (n20 = (n21 = (n22 = (n23 = (n24 = (n25 = (n26 = (n27 = (n28 = (n29 = (n30 = (n31 = (n32 = (n33 = (n34 = (n35 = (n36 = (n37 = (n38 = (n39 = (n40 = (n41 = (n42 = (n43 = (n44 = (n45 = (n46 = (n47 = (n48 = (n49 = (n50 = (n51 = (n52 = (n53 = (n54 = (n55 = (n56 = (n57 = (n58 = (n59 = (n60 = (n61 = (n62 = (n63 = (n64 = (n65 = (n66 = (n67 = (n68 = (n69 = (n70 = (n71 = (n72 = (n73 = (n74 = (n75 = (n76 = (n77 = (n78 = (n79 = (n80 = 67)))))))))))))))))))))))))))))))))))))))))))))))))))))))))))))))))))))))))))))));
                        s = "\u001f\u0016v\u000bZlj\u0012r?\u0018\u0019q";
                        n81 = 66;
                        continue Label_0974_Outer;
                    }
                    case 66: {
                        z2[n68] = intern;
                        n = (n2 = (n3 = (n4 = (n5 = (n6 = (n7 = (n8 = (n9 = (n10 = (n11 = (n12 = (n13 = (n14 = (n15 = (n16 = (n17 = (n18 = (n19 = (n20 = (n21 = (n22 = (n23 = (n24 = (n25 = (n26 = (n27 = (n28 = (n29 = (n30 = (n31 = (n32 = (n33 = (n34 = (n35 = (n36 = (n37 = (n38 = (n39 = (n40 = (n41 = (n42 = (n43 = (n44 = (n45 = (n46 = (n47 = (n48 = (n49 = (n50 = (n51 = (n52 = (n53 = (n54 = (n55 = (n56 = (n57 = (n58 = (n59 = (n60 = (n61 = (n62 = (n63 = (n64 = (n65 = (n66 = (n67 = (n68 = (n69 = (n70 = (n71 = (n72 = (n73 = (n74 = (n75 = (n76 = (n77 = (n78 = (n79 = (n80 = 68)))))))))))))))))))))))))))))))))))))))))))))))))))))))))))))))))))))))))))))));
                        s = "`|\u0002p%\t\u0013m\u000b@";
                        n81 = 67;
                        continue Label_0974_Outer;
                    }
                    case 67: {
                        z2[n69] = intern;
                        n = (n2 = (n3 = (n4 = (n5 = (n6 = (n7 = (n8 = (n9 = (n10 = (n11 = (n12 = (n13 = (n14 = (n15 = (n16 = (n17 = (n18 = (n19 = (n20 = (n21 = (n22 = (n23 = (n24 = (n25 = (n26 = (n27 = (n28 = (n29 = (n30 = (n31 = (n32 = (n33 = (n34 = (n35 = (n36 = (n37 = (n38 = (n39 = (n40 = (n41 = (n42 = (n43 = (n44 = (n45 = (n46 = (n47 = (n48 = (n49 = (n50 = (n51 = (n52 = (n53 = (n54 = (n55 = (n56 = (n57 = (n58 = (n59 = (n60 = (n61 = (n62 = (n63 = (n64 = (n65 = (n66 = (n67 = (n68 = (n69 = (n70 = (n71 = (n72 = (n73 = (n74 = (n75 = (n76 = (n77 = (n78 = (n79 = (n80 = 69)))))))))))))))))))))))))))))))))))))))))))))))))))))))))))))))))))))))))))))));
                        s = "\u0010\u001bz\u000bY";
                        n81 = 68;
                        continue Label_0974_Outer;
                    }
                    case 68: {
                        z2[n70] = intern;
                        n = (n2 = (n3 = (n4 = (n5 = (n6 = (n7 = (n8 = (n9 = (n10 = (n11 = (n12 = (n13 = (n14 = (n15 = (n16 = (n17 = (n18 = (n19 = (n20 = (n21 = (n22 = (n23 = (n24 = (n25 = (n26 = (n27 = (n28 = (n29 = (n30 = (n31 = (n32 = (n33 = (n34 = (n35 = (n36 = (n37 = (n38 = (n39 = (n40 = (n41 = (n42 = (n43 = (n44 = (n45 = (n46 = (n47 = (n48 = (n49 = (n50 = (n51 = (n52 = (n53 = (n54 = (n55 = (n56 = (n57 = (n58 = (n59 = (n60 = (n61 = (n62 = (n63 = (n64 = (n65 = (n66 = (n67 = (n68 = (n69 = (n70 = (n71 = (n72 = (n73 = (n74 = (n75 = (n76 = (n77 = (n78 = (n79 = (n80 = 70)))))))))))))))))))))))))))))))))))))))))))))))))))))))))))))))))))))))))))))));
                        s = "n|\fp3\t\u001ff\t\\hl";
                        n81 = 69;
                        continue Label_0974_Outer;
                    }
                    case 69: {
                        z2[n71] = intern;
                        n = (n2 = (n3 = (n4 = (n5 = (n6 = (n7 = (n8 = (n9 = (n10 = (n11 = (n12 = (n13 = (n14 = (n15 = (n16 = (n17 = (n18 = (n19 = (n20 = (n21 = (n22 = (n23 = (n24 = (n25 = (n26 = (n27 = (n28 = (n29 = (n30 = (n31 = (n32 = (n33 = (n34 = (n35 = (n36 = (n37 = (n38 = (n39 = (n40 = (n41 = (n42 = (n43 = (n44 = (n45 = (n46 = (n47 = (n48 = (n49 = (n50 = (n51 = (n52 = (n53 = (n54 = (n55 = (n56 = (n57 = (n58 = (n59 = (n60 = (n61 = (n62 = (n63 = (n64 = (n65 = (n66 = (n67 = (n68 = (n69 = (n70 = (n71 = (n72 = (n73 = (n74 = (n75 = (n76 = (n77 = (n78 = (n79 = (n80 = 71)))))))))))))))))))))))))))))))))))))))))))))))))))))))))))))))))))))))))))))));
                        s = "fl\u001ew>\u0014\u001bw\u0015Ifb\bs";
                        n81 = 70;
                        continue Label_0974_Outer;
                    }
                    case 70: {
                        z2[n72] = intern;
                        n = (n2 = (n3 = (n4 = (n5 = (n6 = (n7 = (n8 = (n9 = (n10 = (n11 = (n12 = (n13 = (n14 = (n15 = (n16 = (n17 = (n18 = (n19 = (n20 = (n21 = (n22 = (n23 = (n24 = (n25 = (n26 = (n27 = (n28 = (n29 = (n30 = (n31 = (n32 = (n33 = (n34 = (n35 = (n36 = (n37 = (n38 = (n39 = (n40 = (n41 = (n42 = (n43 = (n44 = (n45 = (n46 = (n47 = (n48 = (n49 = (n50 = (n51 = (n52 = (n53 = (n54 = (n55 = (n56 = (n57 = (n58 = (n59 = (n60 = (n61 = (n62 = (n63 = (n64 = (n65 = (n66 = (n67 = (n68 = (n69 = (n70 = (n71 = (n72 = (n73 = (n74 = (n75 = (n76 = (n77 = (n78 = (n79 = (n80 = 72)))))))))))))))))))))))))))))))))))))))))))))))))))))))))))))))))))))))))))))));
                        s = "\n\u007fm|^\u001b";
                        n81 = 71;
                        continue Label_0974_Outer;
                    }
                    case 71: {
                        z2[n73] = intern;
                        n = (n2 = (n3 = (n4 = (n5 = (n6 = (n7 = (n8 = (n9 = (n10 = (n11 = (n12 = (n13 = (n14 = (n15 = (n16 = (n17 = (n18 = (n19 = (n20 = (n21 = (n22 = (n23 = (n24 = (n25 = (n26 = (n27 = (n28 = (n29 = (n30 = (n31 = (n32 = (n33 = (n34 = (n35 = (n36 = (n37 = (n38 = (n39 = (n40 = (n41 = (n42 = (n43 = (n44 = (n45 = (n46 = (n47 = (n48 = (n49 = (n50 = (n51 = (n52 = (n53 = (n54 = (n55 = (n56 = (n57 = (n58 = (n59 = (n60 = (n61 = (n62 = (n63 = (n64 = (n65 = (n66 = (n67 = (n68 = (n69 = (n70 = (n71 = (n72 = (n73 = (n74 = (n75 = (n76 = (n77 = (n78 = (n79 = (n80 = 73)))))))))))))))))))))))))))))))))))))))))))))))))))))))))))))))))))))))))))))));
                        s = "yw\u001f{6\u0012\b}";
                        n81 = 72;
                        continue Label_0974_Outer;
                    }
                    case 72: {
                        z2[n74] = intern;
                        n = (n2 = (n3 = (n4 = (n5 = (n6 = (n7 = (n8 = (n9 = (n10 = (n11 = (n12 = (n13 = (n14 = (n15 = (n16 = (n17 = (n18 = (n19 = (n20 = (n21 = (n22 = (n23 = (n24 = (n25 = (n26 = (n27 = (n28 = (n29 = (n30 = (n31 = (n32 = (n33 = (n34 = (n35 = (n36 = (n37 = (n38 = (n39 = (n40 = (n41 = (n42 = (n43 = (n44 = (n45 = (n46 = (n47 = (n48 = (n49 = (n50 = (n51 = (n52 = (n53 = (n54 = (n55 = (n56 = (n57 = (n58 = (n59 = (n60 = (n61 = (n62 = (n63 = (n64 = (n65 = (n66 = (n67 = (n68 = (n69 = (n70 = (n71 = (n72 = (n73 = (n74 = (n75 = (n76 = (n77 = (n78 = (n79 = (n80 = 74)))))))))))))))))))))))))))))))))))))))))))))))))))))))))))))))))))))))))))))));
                        s = "\u001akdyS\u001ce\u007fiT\u001bkddT";
                        n81 = 73;
                        continue Label_0974_Outer;
                    }
                    case 73: {
                        z2[n75] = intern;
                        n = (n2 = (n3 = (n4 = (n5 = (n6 = (n7 = (n8 = (n9 = (n10 = (n11 = (n12 = (n13 = (n14 = (n15 = (n16 = (n17 = (n18 = (n19 = (n20 = (n21 = (n22 = (n23 = (n24 = (n25 = (n26 = (n27 = (n28 = (n29 = (n30 = (n31 = (n32 = (n33 = (n34 = (n35 = (n36 = (n37 = (n38 = (n39 = (n40 = (n41 = (n42 = (n43 = (n44 = (n45 = (n46 = (n47 = (n48 = (n49 = (n50 = (n51 = (n52 = (n53 = (n54 = (n55 = (n56 = (n57 = (n58 = (n59 = (n60 = (n61 = (n62 = (n63 = (n64 = (n65 = (n66 = (n67 = (n68 = (n69 = (n70 = (n71 = (n72 = (n73 = (n74 = (n75 = (n76 = (n77 = (n78 = (n79 = (n80 = 75)))))))))))))))))))))))))))))))))))))))))))))))))))))))))))))))))))))))))))))));
                        s = "\u000e\np\u0018G}q\nl;\u001c\u0012r";
                        n81 = 74;
                        continue Label_0974_Outer;
                    }
                    case 74: {
                        z2[n76] = intern;
                        n = (n2 = (n3 = (n4 = (n5 = (n6 = (n7 = (n8 = (n9 = (n10 = (n11 = (n12 = (n13 = (n14 = (n15 = (n16 = (n17 = (n18 = (n19 = (n20 = (n21 = (n22 = (n23 = (n24 = (n25 = (n26 = (n27 = (n28 = (n29 = (n30 = (n31 = (n32 = (n33 = (n34 = (n35 = (n36 = (n37 = (n38 = (n39 = (n40 = (n41 = (n42 = (n43 = (n44 = (n45 = (n46 = (n47 = (n48 = (n49 = (n50 = (n51 = (n52 = (n53 = (n54 = (n55 = (n56 = (n57 = (n58 = (n59 = (n60 = (n61 = (n62 = (n63 = (n64 = (n65 = (n66 = (n67 = (n68 = (n69 = (n70 = (n71 = (n72 = (n73 = (n74 = (n75 = (n76 = (n77 = (n78 = (n79 = (n80 = 76)))))))))))))))))))))))))))))))))))))))))))))))))))))))))))))))))))))))))))))));
                        s = "z~\u0004l3\t\u0005u\u000b\\|~\u0004\u007f";
                        n81 = 75;
                        continue Label_0974_Outer;
                    }
                    case 75: {
                        z2[n77] = intern;
                        n = (n2 = (n3 = (n4 = (n5 = (n6 = (n7 = (n8 = (n9 = (n10 = (n11 = (n12 = (n13 = (n14 = (n15 = (n16 = (n17 = (n18 = (n19 = (n20 = (n21 = (n22 = (n23 = (n24 = (n25 = (n26 = (n27 = (n28 = (n29 = (n30 = (n31 = (n32 = (n33 = (n34 = (n35 = (n36 = (n37 = (n38 = (n39 = (n40 = (n41 = (n42 = (n43 = (n44 = (n45 = (n46 = (n47 = (n48 = (n49 = (n50 = (n51 = (n52 = (n53 = (n54 = (n55 = (n56 = (n57 = (n58 = (n59 = (n60 = (n61 = (n62 = (n63 = (n64 = (n65 = (n66 = (n67 = (n68 = (n69 = (n70 = (n71 = (n72 = (n73 = (n74 = (n75 = (n76 = (n77 = (n78 = (n79 = (n80 = 77)))))))))))))))))))))))))))))))))))))))))))))))))))))))))))))))))))))))))))))));
                        s = "\u001akdyS\u001cexoI\u001bt\u007fiS\u001a~";
                        n81 = 76;
                        continue Label_0974_Outer;
                    }
                    case 76: {
                        z2[n78] = intern;
                        n = (n2 = (n3 = (n4 = (n5 = (n6 = (n7 = (n8 = (n9 = (n10 = (n11 = (n12 = (n13 = (n14 = (n15 = (n16 = (n17 = (n18 = (n19 = (n20 = (n21 = (n22 = (n23 = (n24 = (n25 = (n26 = (n27 = (n28 = (n29 = (n30 = (n31 = (n32 = (n33 = (n34 = (n35 = (n36 = (n37 = (n38 = (n39 = (n40 = (n41 = (n42 = (n43 = (n44 = (n45 = (n46 = (n47 = (n48 = (n49 = (n50 = (n51 = (n52 = (n53 = (n54 = (n55 = (n56 = (n57 = (n58 = (n59 = (n60 = (n61 = (n62 = (n63 = (n64 = (n65 = (n66 = (n67 = (n68 = (n69 = (n70 = (n71 = (n72 = (n73 = (n74 = (n75 = (n76 = (n77 = (n78 = (n79 = (n80 = 78)))))))))))))))))))))))))))))))))))))))))))))))))))))))))))))))))))))))))))))));
                        s = "\u000e\np\u0018G}q\u001d{4\u001a\u001bm\u0018Gjk";
                        n81 = 77;
                        continue Label_0974_Outer;
                    }
                    case 77: {
                        z2[n79] = intern;
                        n = (n2 = (n3 = (n4 = (n5 = (n6 = (n7 = (n8 = (n9 = (n10 = (n11 = (n12 = (n13 = (n14 = (n15 = (n16 = (n17 = (n18 = (n19 = (n20 = (n21 = (n22 = (n23 = (n24 = (n25 = (n26 = (n27 = (n28 = (n29 = (n30 = (n31 = (n32 = (n33 = (n34 = (n35 = (n36 = (n37 = (n38 = (n39 = (n40 = (n41 = (n42 = (n43 = (n44 = (n45 = (n46 = (n47 = (n48 = (n49 = (n50 = (n51 = (n52 = (n53 = (n54 = (n55 = (n56 = (n57 = (n58 = (n59 = (n60 = (n61 = (n62 = (n63 = (n64 = (n65 = (n66 = (n67 = (n68 = (n69 = (n70 = (n71 = (n72 = (n73 = (n74 = (n75 = (n76 = (n77 = (n78 = (n79 = (n80 = 79)))))))))))))))))))))))))))))))))))))))))))))))))))))))))))))))))))))))))))))));
                        s = "\u000e\np\u0018G}q\u001en3\u0019\u001fk";
                        n81 = 78;
                        continue Label_0974_Outer;
                    }
                    case 78: {
                        break Label_0974_Outer;
                    }
                }
            }
            z2[n80] = intern;
            z = z2;
        }
    }
}
