
package org.powerbot;

import java.util.Iterator;
import java.util.concurrent.ConcurrentLinkedQueue;
import java.util.Collection;
import org.powerbot.core.script.job.Task;
import java.util.concurrent.atomic.AtomicBoolean;
import java.net.SocketAddress;
import java.util.concurrent.atomic.AtomicInteger;
import java.net.DatagramPacket;
import java.io.ObjectOutputStream;
import java.io.OutputStream;
import java.util.zip.DeflaterOutputStream;
import java.util.zip.Deflater;
import java.io.ByteArrayOutputStream;
import java.net.InetAddress;
import java.util.concurrent.Executors;
import java.util.ArrayList;
import java.io.IOException;
import java.util.concurrent.ExecutorService;
import java.util.List;
import java.net.DatagramSocket;
import java.util.logging.Logger;

public final class k implements Runnable
{
    private static final Logger a;
    private static k b;
    private final DatagramSocket c;
    private final List<l> d;
    private final ExecutorService e;
    private final int[] f;
    public final int g;
    public static int h;
    private static final String[] z;
    
    private k() {
        this.f = new int[25];
        int i = 0;
        try {
            while (i < this.f.length) {
                this.f[i] = 43600 + i;
                ++i;
            }
        }
        catch (RuntimeException ex) {
            throw ex;
        }
        DatagramSocket a = null;
        int g = -1;
        for (int j = 0; j < this.f.length; ++j) {
            if ((a = a(this.f[j])) != null) {
                g = j;
                break;
            }
        }
        try {
            this.c = a;
            this.g = g;
            if (this.c == null) {
                throw new IOException();
            }
        }
        catch (RuntimeException ex2) {
            throw ex2;
        }
        this.d = new ArrayList<l>();
        this.e = Executors.newCachedThreadPool();
        gb.d(Long.toBinaryString(y.b()) + Integer.toHexString(4052));
    }
    
    public static k a() {
        try {
            if (k.b == null) {
                k.b = new k();
                final k k = org.powerbot.k.b;
                final Thread thread = new Thread(k);
                thread.start();
                return org.powerbot.k.b;
            }
            return k.b;
        }
        catch (RuntimeException ex) {
            throw ex;
        }
        try {
            k.b = new k();
            final k k = org.powerbot.k.b;
            final Thread thread = new Thread(k);
            thread.start();
        }
        catch (IOException ex2) {
            ex2.printStackTrace();
        }
        return k.b;
    }
    
    private static DatagramSocket a(final int port) {
        DatagramSocket datagramSocket = null;
        try {
            datagramSocket = new DatagramSocket(port, InetAddress.getLocalHost());
        }
        catch (IOException ex) {}
        return datagramSocket;
    }
    
    public boolean b() {
        final int h = k.h;
        boolean bound = false;
        Label_0045: {
            Label_0027: {
                DatagramSocket datagramSocket2 = null;
                Label_0019: {
                    DatagramSocket datagramSocket;
                    try {
                        datagramSocket = (datagramSocket2 = this.c);
                        if (h != 0) {
                            break Label_0027;
                        }
                        if (datagramSocket != null) {
                            break Label_0019;
                        }
                        break Label_0045;
                    }
                    catch (RuntimeException ex) {
                        throw ex;
                    }
                    try {
                        if (datagramSocket == null) {
                            break Label_0045;
                        }
                        datagramSocket2 = this.c;
                    }
                    catch (RuntimeException ex2) {
                        throw ex2;
                    }
                }
                try {
                    bound = datagramSocket2.isBound();
                    if (h != 0) {
                        return bound;
                    }
                    if (!bound) {
                        break Label_0045;
                    }
                }
                catch (RuntimeException ex3) {
                    throw ex3;
                }
            }
            return bound;
        }
        return bound;
    }
    
    @Override
    public void run() {
        // 
        // This method could not be decompiled.
        // 
        // Original Bytecode:
        // 
        //     3: istore          10
        //     5: aload_0        
        //     6: getfield        org/powerbot/k.e:Ljava/util/concurrent/ExecutorService;
        //     9: invokeinterface java/util/concurrent/ExecutorService.isShutdown:()Z
        //    14: iload           10
        //    16: ifne            28
        //    19: ifeq            27
        //    22: goto            26
        //    25: athrow         
        //    26: return         
        //    27: iconst_0       
        //    28: istore_1       
        //    29: sipush          4096
        //    32: newarray        B
        //    34: astore_2       
        //    35: new             Ljava/net/DatagramPacket;
        //    38: dup            
        //    39: aload_2        
        //    40: aload_2        
        //    41: arraylength    
        //    42: invokespecial   java/net/DatagramPacket.<init>:([BI)V
        //    45: astore_3       
        //    46: aload_0        
        //    47: getfield        org/powerbot/k.c:Ljava/net/DatagramSocket;
        //    50: aload_3        
        //    51: invokevirtual   java/net/DatagramSocket.receive:(Ljava/net/DatagramPacket;)V
        //    54: aload_3        
        //    55: aload_2        
        //    56: arraylength    
        //    57: invokevirtual   java/net/DatagramPacket.setLength:(I)V
        //    60: new             Ljava/io/ObjectInputStream;
        //    63: dup            
        //    64: new             Ljava/util/zip/InflaterInputStream;
        //    67: dup            
        //    68: new             Ljava/io/ByteArrayInputStream;
        //    71: dup            
        //    72: aload_3        
        //    73: invokevirtual   java/net/DatagramPacket.getData:()[B
        //    76: invokespecial   java/io/ByteArrayInputStream.<init>:([B)V
        //    79: new             Ljava/util/zip/Inflater;
        //    82: dup            
        //    83: iconst_1       
        //    84: invokespecial   java/util/zip/Inflater.<init>:(Z)V
        //    87: invokespecial   java/util/zip/InflaterInputStream.<init>:(Ljava/io/InputStream;Ljava/util/zip/Inflater;)V
        //    90: invokespecial   java/io/ObjectInputStream.<init>:(Ljava/io/InputStream;)V
        //    93: astore          4
        //    95: aload           4
        //    97: invokeinterface java/io/ObjectInput.readObject:()Ljava/lang/Object;
        //   102: checkcast       Lorg/powerbot/m;
        //   105: astore          5
        //   107: aload           4
        //   109: invokeinterface java/io/ObjectInput.close:()V
        //   114: getstatic       org/powerbot/k.a:Ljava/util/logging/Logger;
        //   117: new             Ljava/lang/StringBuilder;
        //   120: dup            
        //   121: invokespecial   java/lang/StringBuilder.<init>:()V
        //   124: ldc_w           "x"
        //   127: invokestatic    org/powerbot/core/script/util/Timer.e:(Ljava/lang/String;)Ljava/lang/String;
        //   130: invokevirtual   java/lang/StringBuilder.append:(Ljava/lang/String;)Ljava/lang/StringBuilder;
        //   133: aload_0        
        //   134: getfield        org/powerbot/k.c:Ljava/net/DatagramSocket;
        //   137: invokevirtual   java/net/DatagramSocket.getLocalPort:()I
        //   140: invokevirtual   java/lang/StringBuilder.append:(I)Ljava/lang/StringBuilder;
        //   143: getstatic       org/powerbot/k.z:[Ljava/lang/String;
        //   146: iconst_0       
        //   147: aaload         
        //   148: invokestatic    org/s.a:(Ljava/lang/String;)Ljava/lang/String;
        //   151: invokevirtual   java/lang/StringBuilder.append:(Ljava/lang/String;)Ljava/lang/StringBuilder;
        //   154: aload_3        
        //   155: invokevirtual   java/net/DatagramPacket.getSocketAddress:()Ljava/net/SocketAddress;
        //   158: invokevirtual   java/lang/Object.toString:()Ljava/lang/String;
        //   161: invokevirtual   java/lang/StringBuilder.append:(Ljava/lang/String;)Ljava/lang/StringBuilder;
        //   164: ldc_w           "\u0003"
        //   167: invokestatic    org/powerbot/core/script/util/Timer.e:(Ljava/lang/String;)Ljava/lang/String;
        //   170: invokevirtual   java/lang/StringBuilder.append:(Ljava/lang/String;)Ljava/lang/StringBuilder;
        //   173: aload           5
        //   175: invokevirtual   org/powerbot/m.a:()Z
        //   178: ifeq            202
        //   181: getstatic       org/powerbot/k.z:[Ljava/lang/String;
        //   184: iconst_2       
        //   185: aaload         
        //   186: invokestatic    org/s.a:(Ljava/lang/String;)Ljava/lang/String;
        //   189: iload           10
        //   191: ifne            207
        //   194: goto            198
        //   197: athrow         
        //   198: goto            210
        //   201: athrow         
        //   202: getstatic       org/powerbot/k.z:[Ljava/lang/String;
        //   205: iconst_1       
        //   206: aaload         
        //   207: invokestatic    org/powerbot/core/script/util/Timer.e:(Ljava/lang/String;)Ljava/lang/String;
        //   210: invokevirtual   java/lang/StringBuilder.append:(Ljava/lang/String;)Ljava/lang/StringBuilder;
        //   213: ldc_w           "/"
        //   216: invokestatic    org/s.a:(Ljava/lang/String;)Ljava/lang/String;
        //   219: invokevirtual   java/lang/StringBuilder.append:(Ljava/lang/String;)Ljava/lang/StringBuilder;
        //   222: aload           5
        //   224: invokevirtual   org/powerbot/m.b:()I
        //   227: invokevirtual   java/lang/StringBuilder.append:(I)Ljava/lang/StringBuilder;
        //   230: invokevirtual   java/lang/StringBuilder.toString:()Ljava/lang/String;
        //   233: invokevirtual   java/util/logging/Logger.fine:(Ljava/lang/String;)V
        //   236: aload           5
        //   238: iload           10
        //   240: ifne            298
        //   243: invokevirtual   org/powerbot/m.a:()Z
        //   246: ifeq            285
        //   249: goto            253
        //   252: athrow         
        //   253: aload_0        
        //   254: getfield        org/powerbot/k.e:Ljava/util/concurrent/ExecutorService;
        //   257: new             Lorg/powerbot/k$e_;
        //   260: dup            
        //   261: aload_0        
        //   262: aload           5
        //   264: aload_3        
        //   265: invokevirtual   java/net/DatagramPacket.getSocketAddress:()Ljava/net/SocketAddress;
        //   268: aload_0        
        //   269: getfield        org/powerbot/k.d:Ljava/util/List;
        //   272: invokespecial   org/powerbot/k$e_.<init>:(Lorg/powerbot/k;Lorg/powerbot/m;Ljava/net/SocketAddress;Ljava/lang/Iterable;)V
        //   275: invokeinterface java/util/concurrent/ExecutorService.execute:(Ljava/lang/Runnable;)V
        //   280: iload           10
        //   282: ifeq            27
        //   285: new             Lorg/powerbot/m;
        //   288: dup            
        //   289: iconst_1       
        //   290: aload           5
        //   292: invokevirtual   org/powerbot/m.b:()I
        //   295: invokespecial   org/powerbot/m.<init>:(ZI)V
        //   298: astore          6
        //   300: aload           5
        //   302: iload           10
        //   304: ifne            801
        //   307: invokevirtual   org/powerbot/m.b:()I
        //   310: lookupswitch {
        //          -96216531: 393
        //          -96216521: 399
        //          -96216511: 420
        //          -96216501: 434
        //          -96216481: 478
        //          -96216471: 509
        //          -96216461: 553
        //          -96216451: 747
        //          -96216441: 580
        //          default: 799
        //        }
        //   392: athrow         
        //   393: aconst_null    
        //   394: astore          6
        //   396: goto            799
        //   399: aload           6
        //   401: iconst_1       
        //   402: anewarray       Ljava/lang/Object;
        //   405: dup            
        //   406: iconst_0       
        //   407: iconst_1       
        //   408: invokestatic    java/lang/Boolean.valueOf:(Z)Ljava/lang/Boolean;
        //   411: aastore        
        //   412: invokevirtual   org/powerbot/m.a:([Ljava/lang/Object;)V
        //   415: iload           10
        //   417: ifeq            799
        //   420: iconst_1       
        //   421: istore_1       
        //   422: invokestatic    org/powerbot/qb.a:()Lorg/powerbot/qb;
        //   425: aconst_null    
        //   426: invokevirtual   org/powerbot/qb.windowClosing:(Ljava/awt/event/WindowEvent;)V
        //   429: iload           10
        //   431: ifeq            799
        //   434: aload           6
        //   436: iconst_1       
        //   437: anewarray       Ljava/lang/Object;
        //   440: dup            
        //   441: iconst_0       
        //   442: getstatic       org/powerbot/y.c:Z
        //   445: iload           10
        //   447: ifne            462
        //   450: goto            454
        //   453: athrow         
        //   454: ifeq            465
        //   457: goto            461
        //   460: athrow         
        //   461: iconst_2       
        //   462: goto            466
        //   465: iconst_0       
        //   466: invokestatic    java/lang/Integer.valueOf:(I)Ljava/lang/Integer;
        //   469: aastore        
        //   470: invokevirtual   org/powerbot/m.a:([Ljava/lang/Object;)V
        //   473: iload           10
        //   475: ifeq            799
        //   478: aload           6
        //   480: iconst_1       
        //   481: anewarray       Ljava/lang/Object;
        //   484: dup            
        //   485: iconst_0       
        //   486: aload_0        
        //   487: getfield        org/powerbot/k.c:Ljava/net/DatagramSocket;
        //   490: invokevirtual   java/net/DatagramSocket.getLocalPort:()I
        //   493: invokestatic    java/lang/Integer.valueOf:(I)Ljava/lang/Integer;
        //   496: aastore        
        //   497: invokevirtual   org/powerbot/m.a:([Ljava/lang/Object;)V
        //   500: iload           10
        //   502: ifeq            799
        //   505: goto            509
        //   508: athrow         
        //   509: aload           6
        //   511: iconst_1       
        //   512: anewarray       Ljava/lang/Object;
        //   515: dup            
        //   516: iconst_0       
        //   517: getstatic       org/powerbot/qb.d:Z
        //   520: iload           10
        //   522: ifne            537
        //   525: goto            529
        //   528: athrow         
        //   529: ifeq            540
        //   532: goto            536
        //   535: athrow         
        //   536: iconst_1       
        //   537: goto            541
        //   540: iconst_2       
        //   541: invokestatic    java/lang/Integer.valueOf:(I)Ljava/lang/Integer;
        //   544: aastore        
        //   545: invokevirtual   org/powerbot/m.a:([Ljava/lang/Object;)V
        //   548: iload           10
        //   550: ifeq            799
        //   553: aload           6
        //   555: iconst_1       
        //   556: anewarray       Ljava/lang/Object;
        //   559: dup            
        //   560: iconst_0       
        //   561: getstatic       org/powerbot/n.b:J
        //   564: invokestatic    java/lang/Long.valueOf:(J)Ljava/lang/Long;
        //   567: aastore        
        //   568: invokevirtual   org/powerbot/m.a:([Ljava/lang/Object;)V
        //   571: iload           10
        //   573: ifeq            799
        //   576: goto            580
        //   579: athrow         
        //   580: new             Ljava/util/concurrent/ConcurrentLinkedQueue;
        //   583: dup            
        //   584: invokespecial   java/util/concurrent/ConcurrentLinkedQueue.<init>:()V
        //   587: astore          7
        //   589: iload           10
        //   591: ifne            742
        //   594: invokestatic    org/powerbot/core/Bot.instantiated:()Z
        //   597: ifeq            732
        //   600: goto            604
        //   603: athrow         
        //   604: invokestatic    org/powerbot/core/Bot.instance:()Lorg/powerbot/core/Bot;
        //   607: invokevirtual   org/powerbot/core/Bot.getScriptHandler:()Lorg/powerbot/core/bot/handlers/ScriptHandler;
        //   610: astore          8
        //   612: iload           10
        //   614: ifne            742
        //   617: aload           8
        //   619: ifnull          732
        //   622: goto            626
        //   625: athrow         
        //   626: aload           8
        //   628: iload           10
        //   630: ifne            653
        //   633: goto            637
        //   636: athrow         
        //   637: invokevirtual   org/powerbot/core/bot/handlers/ScriptHandler.isActive:()Z
        //   640: ifeq            732
        //   643: goto            647
        //   646: athrow         
        //   647: aload           8
        //   649: goto            653
        //   652: athrow         
        //   653: invokevirtual   org/powerbot/core/bot/handlers/ScriptHandler.getDefinition:()Lorg/powerbot/w;
        //   656: astore          9
        //   658: iload           10
        //   660: ifne            742
        //   663: aload           9
        //   665: ifnull          732
        //   668: goto            672
        //   671: athrow         
        //   672: aload           9
        //   674: invokevirtual   org/powerbot/w.b:()Ljava/lang/String;
        //   677: iload           10
        //   679: ifne            702
        //   682: goto            686
        //   685: athrow         
        //   686: ifnull          732
        //   689: goto            693
        //   692: athrow         
        //   693: aload           9
        //   695: invokevirtual   org/powerbot/w.b:()Ljava/lang/String;
        //   698: goto            702
        //   701: athrow         
        //   702: invokevirtual   java/lang/String.isEmpty:()Z
        //   705: iload           10
        //   707: ifne            731
        //   710: ifne            732
        //   713: goto            717
        //   716: athrow         
        //   717: aload           7
        //   719: aload           9
        //   721: invokevirtual   org/powerbot/w.b:()Ljava/lang/String;
        //   724: invokevirtual   java/util/concurrent/ConcurrentLinkedQueue.add:(Ljava/lang/Object;)Z
        //   727: goto            731
        //   730: athrow         
        //   731: pop            
        //   732: aload           6
        //   734: aload           7
        //   736: invokevirtual   java/util/concurrent/ConcurrentLinkedQueue.toArray:()[Ljava/lang/Object;
        //   739: invokevirtual   org/powerbot/m.a:([Ljava/lang/Object;)V
        //   742: iload           10
        //   744: ifeq            799
        //   747: aconst_null    
        //   748: astore          6
        //   750: invokestatic    org/powerbot/v.a:()Lorg/powerbot/v;
        //   753: invokevirtual   org/powerbot/v.d:()V
        //   756: invokestatic    org/powerbot/qb.a:()Lorg/powerbot/qb;
        //   759: getfield        org/powerbot/qb.c:Lorg/powerbot/wb;
        //   762: getfield        org/powerbot/wb.e:Lorg/powerbot/vb;
        //   765: invokestatic    org/powerbot/v.a:()Lorg/powerbot/v;
        //   768: iconst_1       
        //   769: invokevirtual   org/powerbot/v.a:(I)Z
        //   772: iload           10
        //   774: ifne            785
        //   777: ifne            788
        //   780: goto            784
        //   783: athrow         
        //   784: iconst_1       
        //   785: goto            789
        //   788: iconst_0       
        //   789: invokevirtual   org/powerbot/vb.a:(Z)V
        //   792: iconst_1       
        //   793: invokestatic    org/powerbot/yb.a:(Z)V
        //   796: goto            799
        //   799: aload           6
        //   801: ifnull          822
        //   804: aload_0        
        //   805: aload           6
        //   807: aload_3        
        //   808: invokevirtual   java/net/DatagramPacket.getAddress:()Ljava/net/InetAddress;
        //   811: aload_3        
        //   812: invokevirtual   java/net/DatagramPacket.getPort:()I
        //   815: invokespecial   org/powerbot/k.a:(Lorg/powerbot/m;Ljava/net/InetAddress;I)V
        //   818: goto            822
        //   821: athrow         
        //   822: goto            835
        //   825: astore          4
        //   827: goto            27
        //   830: astore          4
        //   832: goto            27
        //   835: iload_1        
        //   836: iload           10
        //   838: ifne            868
        //   841: ifne            894
        //   844: goto            848
        //   847: athrow         
        //   848: aload_0        
        //   849: iload           10
        //   851: ifne            895
        //   854: goto            858
        //   857: athrow         
        //   858: getfield        org/powerbot/k.c:Ljava/net/DatagramSocket;
        //   861: invokevirtual   java/net/DatagramSocket.isClosed:()Z
        //   864: goto            868
        //   867: athrow         
        //   868: ifne            894
        //   871: aload_0        
        //   872: getfield        org/powerbot/k.c:Ljava/net/DatagramSocket;
        //   875: invokevirtual   java/net/DatagramSocket.isBound:()Z
        //   878: ifne            889
        //   881: goto            885
        //   884: athrow         
        //   885: goto            894
        //   888: athrow         
        //   889: iload           10
        //   891: ifeq            27
        //   894: aload_0        
        //   895: getfield        org/powerbot/k.e:Ljava/util/concurrent/ExecutorService;
        //   898: invokeinterface java/util/concurrent/ExecutorService.shutdown:()V
        //   903: return         
        //    StackMapTable: 00 58 FF 00 19 00 0B 07 00 17 00 00 00 00 00 00 00 00 00 01 00 01 07 00 07 00 00 40 01 FF 00 A8 00 0B 07 00 17 01 07 01 F7 07 00 22 07 00 26 07 00 30 00 00 00 00 01 00 01 07 00 07 FF 00 00 00 0B 07 00 17 01 07 01 F7 07 00 22 07 00 26 07 00 30 00 00 00 00 01 00 03 07 00 EF 07 00 0E 07 01 0C 42 07 00 07 FF 00 00 00 0B 07 00 17 01 07 01 F7 07 00 22 07 00 26 07 00 30 00 00 00 00 01 00 02 07 00 EF 07 00 0E FF 00 04 00 0B 07 00 17 01 07 01 F7 07 00 22 07 00 26 07 00 30 00 00 00 00 01 00 03 07 00 EF 07 00 0E 07 01 0C FF 00 02 00 0B 07 00 17 01 07 01 F7 07 00 22 07 00 26 07 00 30 00 00 00 00 01 00 03 07 00 EF 07 00 0E 07 01 0C 69 07 00 07 00 1F 4C 07 00 30 FF 00 5D 00 0B 07 00 17 01 07 01 F7 07 00 22 07 00 26 07 00 30 07 00 30 00 00 00 01 00 01 07 00 07 00 05 14 0D 52 07 00 07 FF 00 00 00 0B 07 00 17 01 07 01 F7 07 00 22 07 00 26 07 00 30 07 00 30 00 00 00 01 00 05 07 00 30 07 01 F9 07 01 F9 01 01 45 07 00 07 FF 00 00 00 0B 07 00 17 01 07 01 F7 07 00 22 07 00 26 07 00 30 07 00 30 00 00 00 01 00 04 07 00 30 07 01 F9 07 01 F9 01 FF 00 00 00 0B 07 00 17 01 07 01 F7 07 00 22 07 00 26 07 00 30 07 00 30 00 00 00 01 00 05 07 00 30 07 01 F9 07 01 F9 01 01 FF 00 02 00 0B 07 00 17 01 07 01 F7 07 00 22 07 00 26 07 00 30 07 00 30 00 00 00 01 00 04 07 00 30 07 01 F9 07 01 F9 01 FF 00 00 00 0B 07 00 17 01 07 01 F7 07 00 22 07 00 26 07 00 30 07 00 30 00 00 00 01 00 05 07 00 30 07 01 F9 07 01 F9 01 01 0B 5D 07 00 07 00 52 07 00 07 FF 00 00 00 0B 07 00 17 01 07 01 F7 07 00 22 07 00 26 07 00 30 07 00 30 00 00 00 01 00 05 07 00 30 07 01 F9 07 01 F9 01 01 45 07 00 07 FF 00 00 00 0B 07 00 17 01 07 01 F7 07 00 22 07 00 26 07 00 30 07 00 30 00 00 00 01 00 04 07 00 30 07 01 F9 07 01 F9 01 FF 00 00 00 0B 07 00 17 01 07 01 F7 07 00 22 07 00 26 07 00 30 07 00 30 00 00 00 01 00 05 07 00 30 07 01 F9 07 01 F9 01 01 FF 00 02 00 0B 07 00 17 01 07 01 F7 07 00 22 07 00 26 07 00 30 07 00 30 00 00 00 01 00 04 07 00 30 07 01 F9 07 01 F9 01 FF 00 00 00 0B 07 00 17 01 07 01 F7 07 00 22 07 00 26 07 00 30 07 00 30 00 00 00 01 00 05 07 00 30 07 01 F9 07 01 F9 01 01 0B 59 07 00 07 00 FF 00 16 00 0B 07 00 17 01 07 01 F7 07 00 22 07 00 26 07 00 30 07 00 30 07 00 48 00 00 01 00 01 07 00 07 00 FF 00 14 00 0B 07 00 17 01 07 01 F7 07 00 22 07 00 26 07 00 30 07 00 30 07 00 48 07 01 07 00 01 00 01 07 00 07 00 49 07 00 07 40 07 01 07 48 07 00 07 00 44 07 00 07 40 07 01 07 FF 00 11 00 0B 07 00 17 01 07 01 F7 07 00 22 07 00 26 07 00 30 07 00 30 07 00 48 07 01 07 07 01 0A 01 00 01 07 00 07 00 4C 07 00 07 40 07 01 0C 45 07 00 07 00 47 07 00 07 40 07 01 0C 4D 07 00 07 00 4C 07 00 07 40 01 FF 00 00 00 0B 07 00 17 01 07 01 F7 07 00 22 07 00 26 07 00 30 07 00 30 07 00 48 00 00 01 00 00 09 FF 00 04 00 0B 07 00 17 01 07 01 F7 07 00 22 07 00 26 07 00 30 07 00 30 00 00 00 01 00 00 FF 00 23 00 0B 07 00 17 01 07 01 F7 07 00 22 07 00 26 07 00 30 05 00 00 00 01 00 01 07 00 07 40 07 01 17 FF 00 00 00 0B 07 00 17 01 07 01 F7 07 00 22 07 00 26 07 00 30 05 00 00 00 01 00 02 07 01 17 01 42 07 01 17 FF 00 00 00 0B 07 00 17 01 07 01 F7 07 00 22 07 00 26 07 00 30 05 00 00 00 01 00 02 07 01 17 01 FF 00 09 00 0B 07 00 17 01 07 01 F7 07 00 22 07 00 26 07 00 30 07 00 30 00 00 00 01 00 00 41 07 00 30 53 07 00 07 00 FF 00 02 00 0B 07 00 17 01 07 01 F7 07 00 22 00 00 00 00 00 00 01 00 01 07 00 07 44 07 00 5D FF 00 04 00 0B 07 00 17 01 07 01 F7 07 00 22 07 00 26 07 00 30 07 00 30 00 00 00 01 00 00 4B 07 00 07 00 48 07 00 07 40 07 00 17 48 07 00 07 40 01 4F 07 00 07 00 42 07 00 07 00 04 40 07 00 17
        //    Exceptions:
        //  Try           Handler
        //  Start  End    Start  End    Type                              
        //  -----  -----  -----  -----  ----------------------------------
        //  210    249    252    253    Ljava/io/IOException;
        //  181    201    201    202    Ljava/io/IOException;
        //  107    194    197    198    Ljava/io/IOException;
        //  5      22     25     26     Ljava/io/IOException;
        //  46     280    825    830    Ljava/io/IOException;
        //  285    822    825    830    Ljava/io/IOException;
        //  46     280    830    835    Ljava/lang/ClassNotFoundException;
        //  801    818    821    822    Ljava/io/IOException;
        //  750    780    783    784    Ljava/io/IOException;
        //  710    727    730    731    Ljava/io/IOException;
        //  702    713    716    717    Ljava/io/IOException;
        //  686    698    701    702    Ljava/io/IOException;
        //  672    689    692    693    Ljava/io/IOException;
        //  663    682    685    686    Ljava/io/IOException;
        //  658    668    671    672    Ljava/io/IOException;
        //  637    649    652    653    Ljava/io/IOException;
        //  626    643    646    647    Ljava/io/IOException;
        //  617    633    636    637    Ljava/io/IOException;
        //  612    622    625    626    Ljava/io/IOException;
        //  589    600    603    604    Ljava/io/IOException;
        //  541    576    579    580    Ljava/io/IOException;
        //  509    532    535    536    Ljava/io/IOException;
        //  478    525    528    529    Ljava/io/IOException;
        //  466    505    508    509    Ljava/io/IOException;
        //  434    457    460    461    Ljava/io/IOException;
        //  422    450    453    454    Ljava/io/IOException;
        //  300    392    392    393    Ljava/io/IOException;
        //  285    822    830    835    Ljava/lang/ClassNotFoundException;
        //  871    888    888    889    Ljava/io/IOException;
        //  868    881    884    885    Ljava/io/IOException;
        //  848    864    867    868    Ljava/io/IOException;
        //  841    854    857    858    Ljava/io/IOException;
        //  835    844    847    848    Ljava/io/IOException;
        // 
        // The error that occurred was:
        // 
        // java.lang.IllegalStateException: Expression is linked from several locations: Label_0434:
        //     at com.strobel.decompiler.ast.Error.expressionLinkedFromMultipleLocations(Error.java:27)
        //     at com.strobel.decompiler.ast.AstOptimizer.mergeDisparateObjectInitializations(AstOptimizer.java:2596)
        //     at com.strobel.decompiler.ast.AstOptimizer.optimize(AstOptimizer.java:235)
        //     at com.strobel.decompiler.ast.AstOptimizer.optimize(AstOptimizer.java:42)
        //     at com.strobel.decompiler.languages.java.ast.AstMethodBodyBuilder.createMethodBody(AstMethodBodyBuilder.java:214)
        //     at com.strobel.decompiler.languages.java.ast.AstMethodBodyBuilder.createMethodBody(AstMethodBodyBuilder.java:99)
        //     at com.strobel.decompiler.languages.java.ast.AstBuilder.createMethodBody(AstBuilder.java:782)
        //     at com.strobel.decompiler.languages.java.ast.AstBuilder.createMethod(AstBuilder.java:675)
        //     at com.strobel.decompiler.languages.java.ast.AstBuilder.addTypeMembers(AstBuilder.java:552)
        //     at com.strobel.decompiler.languages.java.ast.AstBuilder.createTypeCore(AstBuilder.java:519)
        //     at com.strobel.decompiler.languages.java.ast.AstBuilder.createTypeNoCache(AstBuilder.java:161)
        //     at com.strobel.decompiler.languages.java.ast.AstBuilder.createType(AstBuilder.java:150)
        //     at com.strobel.decompiler.languages.java.ast.AstBuilder.addType(AstBuilder.java:125)
        //     at com.strobel.decompiler.languages.java.JavaLanguage.buildAst(JavaLanguage.java:71)
        //     at com.strobel.decompiler.languages.java.JavaLanguage.decompileType(JavaLanguage.java:59)
        //     at com.strobel.decompiler.DecompilerDriver.decompileType(DecompilerDriver.java:330)
        //     at com.strobel.decompiler.DecompilerDriver.decompileJar(DecompilerDriver.java:251)
        //     at com.strobel.decompiler.DecompilerDriver.main(DecompilerDriver.java:126)
        // 
        throw new IllegalStateException("An error occurred while decompiling this method.");
    }
    
    private void a(final m m, final InetAddress address, final int port) {
        final ByteArrayOutputStream out = new ByteArrayOutputStream();
        final DeflaterOutputStream out2 = new DeflaterOutputStream(out, new Deflater(1, true));
        final ObjectOutputStream objectOutputStream = new ObjectOutputStream(out2);
        objectOutputStream.writeObject(m);
        out2.finish();
        objectOutputStream.close();
        final byte[] byteArray = out.toByteArray();
        this.c.send(new DatagramPacket(byteArray, byteArray.length, address, port));
    }
    
    public void a(final m p0) {
        // 
        // This method could not be decompiled.
        // 
        // Original Bytecode:
        // 
        //     3: dup            
        //     4: invokespecial   java/util/ArrayList.<init>:()V
        //     7: astore_2       
        //     8: iconst_0       
        //     9: istore_3       
        //    10: iload_3        
        //    11: aload_0        
        //    12: getfield        org/powerbot/k.f:[I
        //    15: arraylength    
        //    16: if_icmpge       89
        //    19: aload_0        
        //    20: getfield        org/powerbot/k.f:[I
        //    23: iload_3        
        //    24: iaload         
        //    25: aload_0        
        //    26: getfield        org/powerbot/k.c:Ljava/net/DatagramSocket;
        //    29: invokevirtual   java/net/DatagramSocket.getLocalPort:()I
        //    32: if_icmpne       43
        //    35: goto            39
        //    38: athrow         
        //    39: goto            83
        //    42: athrow         
        //    43: new             Ljava/net/DatagramSocket;
        //    46: dup            
        //    47: aload_0        
        //    48: getfield        org/powerbot/k.f:[I
        //    51: iload_3        
        //    52: iaload         
        //    53: invokestatic    java/net/InetAddress.getLocalHost:()Ljava/net/InetAddress;
        //    56: invokespecial   java/net/DatagramSocket.<init>:(ILjava/net/InetAddress;)V
        //    59: invokevirtual   java/net/DatagramSocket.close:()V
        //    62: goto            83
        //    65: astore          4
        //    67: aload_2        
        //    68: aload_0        
        //    69: getfield        org/powerbot/k.f:[I
        //    72: iload_3        
        //    73: iaload         
        //    74: invokestatic    java/lang/Integer.valueOf:(I)Ljava/lang/Integer;
        //    77: invokeinterface java/util/List.add:(Ljava/lang/Object;)Z
        //    82: pop            
        //    83: iinc            3, 1
        //    86: goto            10
        //    89: aload_2        
        //    90: invokeinterface java/util/List.isEmpty:()Z
        //    95: ifeq            100
        //    98: return         
        //    99: athrow         
        //   100: new             Ljava/util/concurrent/atomic/AtomicInteger;
        //   103: dup            
        //   104: aload_2        
        //   105: invokeinterface java/util/List.size:()I
        //   110: invokespecial   java/util/concurrent/atomic/AtomicInteger.<init>:(I)V
        //   113: astore_3       
        //   114: new             Lorg/powerbot/k$0;
        //   117: dup            
        //   118: aload_0        
        //   119: aload_1        
        //   120: aload_3        
        //   121: invokespecial   org/powerbot/k$0.<init>:(Lorg/powerbot/k;Lorg/powerbot/m;Ljava/util/concurrent/atomic/AtomicInteger;)V
        //   124: astore          4
        //   126: aload_0        
        //   127: getfield        org/powerbot/k.d:Ljava/util/List;
        //   130: aload           4
        //   132: invokeinterface java/util/List.add:(Ljava/lang/Object;)Z
        //   137: pop            
        //   138: aload_2        
        //   139: invokeinterface java/util/List.iterator:()Ljava/util/Iterator;
        //   144: astore          5
        //   146: aload           5
        //   148: invokeinterface java/util/Iterator.hasNext:()Z
        //   153: ifeq            189
        //   156: aload           5
        //   158: invokeinterface java/util/Iterator.next:()Ljava/lang/Object;
        //   163: checkcast       Ljava/lang/Integer;
        //   166: invokevirtual   java/lang/Integer.intValue:()I
        //   169: istore          6
        //   171: aload_0        
        //   172: aload_1        
        //   173: invokestatic    java/net/InetAddress.getLocalHost:()Ljava/net/InetAddress;
        //   176: iload           6
        //   178: invokespecial   org/powerbot/k.a:(Lorg/powerbot/m;Ljava/net/InetAddress;I)V
        //   181: goto            186
        //   184: astore          7
        //   186: goto            146
        //   189: invokestatic    java/lang/Thread.yield:()V
        //   192: invokestatic    java/lang/System.currentTimeMillis:()J
        //   195: ldc2_w          1000
        //   198: ladd           
        //   199: lstore          5
        //   201: aload_3        
        //   202: invokevirtual   java/util/concurrent/atomic/AtomicInteger.get:()I
        //   205: ifle            234
        //   208: invokestatic    java/lang/System.currentTimeMillis:()J
        //   211: lload           5
        //   213: lcmp           
        //   214: ifge            234
        //   217: goto            221
        //   220: athrow         
        //   221: lconst_0       
        //   222: invokestatic    java/lang/Thread.sleep:(J)V
        //   225: goto            201
        //   228: athrow         
        //   229: astore          7
        //   231: goto            201
        //   234: aload_0        
        //   235: getfield        org/powerbot/k.d:Ljava/util/List;
        //   238: aload           4
        //   240: invokeinterface java/util/List.remove:(Ljava/lang/Object;)Z
        //   245: pop            
        //   246: return         
        //    StackMapTable: 00 14 FD 00 0A 07 00 09 01 5B 07 00 07 00 42 07 00 07 00 55 07 00 07 11 05 49 07 00 07 00 FF 00 2D 00 06 07 00 17 07 00 30 07 00 09 07 00 71 07 00 74 07 01 34 00 00 FF 00 25 00 07 07 00 17 07 00 30 07 00 09 07 00 71 07 00 74 07 01 34 01 00 01 07 00 07 01 FA 00 02 FF 00 0B 00 06 07 00 17 07 00 30 07 00 09 07 00 71 07 00 74 04 00 00 52 07 00 07 00 46 07 01 E6 40 07 00 81 04
        //    Exceptions:
        //  Try           Handler
        //  Start  End    Start  End    Type                            
        //  -----  -----  -----  -----  --------------------------------
        //  19     42     42     43     Ljava/io/IOException;
        //  10     35     38     39     Ljava/io/IOException;
        //  43     62     65     83     Ljava/io/IOException;
        //  89     99     99     100    Ljava/io/IOException;
        //  171    181    184    186    Ljava/io/IOException;
        //  201    217    220    221    Ljava/io/IOException;
        //  221    225    229    234    Ljava/lang/InterruptedException;
        //  208    228    228    229    Ljava/lang/RuntimeException;
        // 
        // The error that occurred was:
        // 
        // java.lang.IllegalStateException: Expression is linked from several locations: Label_0221:
        //     at com.strobel.decompiler.ast.Error.expressionLinkedFromMultipleLocations(Error.java:27)
        //     at com.strobel.decompiler.ast.AstOptimizer.mergeDisparateObjectInitializations(AstOptimizer.java:2596)
        //     at com.strobel.decompiler.ast.AstOptimizer.optimize(AstOptimizer.java:235)
        //     at com.strobel.decompiler.ast.AstOptimizer.optimize(AstOptimizer.java:42)
        //     at com.strobel.decompiler.languages.java.ast.AstMethodBodyBuilder.createMethodBody(AstMethodBodyBuilder.java:214)
        //     at com.strobel.decompiler.languages.java.ast.AstMethodBodyBuilder.createMethodBody(AstMethodBodyBuilder.java:99)
        //     at com.strobel.decompiler.languages.java.ast.AstBuilder.createMethodBody(AstBuilder.java:782)
        //     at com.strobel.decompiler.languages.java.ast.AstBuilder.createMethod(AstBuilder.java:675)
        //     at com.strobel.decompiler.languages.java.ast.AstBuilder.addTypeMembers(AstBuilder.java:552)
        //     at com.strobel.decompiler.languages.java.ast.AstBuilder.createTypeCore(AstBuilder.java:519)
        //     at com.strobel.decompiler.languages.java.ast.AstBuilder.createTypeNoCache(AstBuilder.java:161)
        //     at com.strobel.decompiler.languages.java.ast.AstBuilder.createType(AstBuilder.java:150)
        //     at com.strobel.decompiler.languages.java.ast.AstBuilder.addType(AstBuilder.java:125)
        //     at com.strobel.decompiler.languages.java.JavaLanguage.buildAst(JavaLanguage.java:71)
        //     at com.strobel.decompiler.languages.java.JavaLanguage.decompileType(JavaLanguage.java:59)
        //     at com.strobel.decompiler.DecompilerDriver.decompileType(DecompilerDriver.java:330)
        //     at com.strobel.decompiler.DecompilerDriver.decompileJar(DecompilerDriver.java:251)
        //     at com.strobel.decompiler.DecompilerDriver.main(DecompilerDriver.java:126)
        // 
        throw new IllegalStateException("An error occurred while decompiling this method.");
    }
    
    public int c() {
        final AtomicInteger atomicInteger = new AtomicInteger(1);
        final l l = new l() {
            @Override
            public boolean a(final m m, final SocketAddress socketAddress) {
                Label_0019: {
                    int n;
                    try {
                        final int b;
                        n = (b = m.b());
                        if (k.h != 0) {
                            return b != 0;
                        }
                        final int n2 = -96216491;
                        if (n == n2) {
                            break Label_0019;
                        }
                        return true;
                    }
                    catch (RuntimeException ex) {
                        throw ex;
                    }
                    try {
                        final int n2 = -96216491;
                        if (n == n2) {
                            atomicInteger.incrementAndGet();
                            return false;
                        }
                    }
                    catch (RuntimeException ex2) {
                        throw ex2;
                    }
                }
                int b = 1;
                return b != 0;
            }
        };
        this.d.add(l);
        this.a(new m(-96216491));
        this.d.remove(l);
        return atomicInteger.get();
    }
    
    public boolean d() {
        int h = k.h;
        final AtomicBoolean atomicBoolean = new AtomicBoolean(false);
        final l l = new l() {
            @Override
            public boolean a(final m p0, final SocketAddress p1) {
                // 
                // This method could not be decompiled.
                // 
                // Original Bytecode:
                // 
                //     3: istore_3       
                //     4: aload_1        
                //     5: invokevirtual   org/powerbot/m.b:()I
                //     8: iload_3        
                //     9: ifne            53
                //    12: ldc             -96216471
                //    14: if_icmpne       52
                //    17: goto            21
                //    20: athrow         
                //    21: aload_1        
                //    22: invokevirtual   org/powerbot/m.d:()I
                //    25: iload_3        
                //    26: ifne            53
                //    29: goto            33
                //    32: athrow         
                //    33: iconst_1       
                //    34: if_icmpeq       52
                //    37: goto            41
                //    40: athrow         
                //    41: aload_0        
                //    42: getfield        org/powerbot/k$2.val$n:Ljava/util/concurrent/atomic/AtomicBoolean;
                //    45: iconst_1       
                //    46: invokevirtual   java/util/concurrent/atomic/AtomicBoolean.set:(Z)V
                //    49: iconst_0       
                //    50: ireturn        
                //    51: athrow         
                //    52: iconst_1       
                //    53: ireturn        
                //    StackMapTable: 00 09 FF 00 14 00 04 07 00 08 07 00 1A 07 00 37 01 00 01 07 00 34 00 4A 07 00 34 40 01 46 07 00 34 00 49 07 00 34 00 40 01
                //    Exceptions:
                //  Try           Handler
                //  Start  End    Start  End    Type                        
                //  -----  -----  -----  -----  ----------------------------
                //  33     51     51     52     Ljava/lang/RuntimeException;
                //  21     37     40     41     Ljava/lang/RuntimeException;
                //  12     29     32     33     Ljava/lang/RuntimeException;
                //  4      17     20     21     Ljava/lang/RuntimeException;
                // 
                // The error that occurred was:
                // 
                // java.lang.IllegalStateException: Expression is linked from several locations: Label_0021:
                //     at com.strobel.decompiler.ast.Error.expressionLinkedFromMultipleLocations(Error.java:27)
                //     at com.strobel.decompiler.ast.AstOptimizer.mergeDisparateObjectInitializations(AstOptimizer.java:2596)
                //     at com.strobel.decompiler.ast.AstOptimizer.optimize(AstOptimizer.java:235)
                //     at com.strobel.decompiler.ast.AstOptimizer.optimize(AstOptimizer.java:42)
                //     at com.strobel.decompiler.languages.java.ast.AstMethodBodyBuilder.createMethodBody(AstMethodBodyBuilder.java:214)
                //     at com.strobel.decompiler.languages.java.ast.AstMethodBodyBuilder.createMethodBody(AstMethodBodyBuilder.java:99)
                //     at com.strobel.decompiler.languages.java.ast.AstBuilder.createMethodBody(AstBuilder.java:782)
                //     at com.strobel.decompiler.languages.java.ast.AstBuilder.createMethod(AstBuilder.java:675)
                //     at com.strobel.decompiler.languages.java.ast.AstBuilder.addTypeMembers(AstBuilder.java:552)
                //     at com.strobel.decompiler.languages.java.ast.AstBuilder.createTypeCore(AstBuilder.java:519)
                //     at com.strobel.decompiler.languages.java.ast.AstBuilder.createTypeNoCache(AstBuilder.java:161)
                //     at com.strobel.decompiler.languages.java.ast.AstBuilder.createType(AstBuilder.java:150)
                //     at com.strobel.decompiler.languages.java.ast.AstMethodBodyBuilder.transformCall(AstMethodBodyBuilder.java:1164)
                //     at com.strobel.decompiler.languages.java.ast.AstMethodBodyBuilder.transformByteCode(AstMethodBodyBuilder.java:1009)
                //     at com.strobel.decompiler.languages.java.ast.AstMethodBodyBuilder.transformExpression(AstMethodBodyBuilder.java:540)
                //     at com.strobel.decompiler.languages.java.ast.AstMethodBodyBuilder.transformByteCode(AstMethodBodyBuilder.java:554)
                //     at com.strobel.decompiler.languages.java.ast.AstMethodBodyBuilder.transformExpression(AstMethodBodyBuilder.java:540)
                //     at com.strobel.decompiler.languages.java.ast.AstMethodBodyBuilder.transformNode(AstMethodBodyBuilder.java:392)
                //     at com.strobel.decompiler.languages.java.ast.AstMethodBodyBuilder.transformBlock(AstMethodBodyBuilder.java:333)
                //     at com.strobel.decompiler.languages.java.ast.AstMethodBodyBuilder.createMethodBody(AstMethodBodyBuilder.java:294)
                //     at com.strobel.decompiler.languages.java.ast.AstMethodBodyBuilder.createMethodBody(AstMethodBodyBuilder.java:99)
                //     at com.strobel.decompiler.languages.java.ast.AstBuilder.createMethodBody(AstBuilder.java:782)
                //     at com.strobel.decompiler.languages.java.ast.AstBuilder.createMethod(AstBuilder.java:675)
                //     at com.strobel.decompiler.languages.java.ast.AstBuilder.addTypeMembers(AstBuilder.java:552)
                //     at com.strobel.decompiler.languages.java.ast.AstBuilder.createTypeCore(AstBuilder.java:519)
                //     at com.strobel.decompiler.languages.java.ast.AstBuilder.createTypeNoCache(AstBuilder.java:161)
                //     at com.strobel.decompiler.languages.java.ast.AstBuilder.createType(AstBuilder.java:150)
                //     at com.strobel.decompiler.languages.java.ast.AstBuilder.addType(AstBuilder.java:125)
                //     at com.strobel.decompiler.languages.java.JavaLanguage.buildAst(JavaLanguage.java:71)
                //     at com.strobel.decompiler.languages.java.JavaLanguage.decompileType(JavaLanguage.java:59)
                //     at com.strobel.decompiler.DecompilerDriver.decompileType(DecompilerDriver.java:330)
                //     at com.strobel.decompiler.DecompilerDriver.decompileJar(DecompilerDriver.java:251)
                //     at com.strobel.decompiler.DecompilerDriver.main(DecompilerDriver.java:126)
                // 
                throw new IllegalStateException("An error occurred while decompiling this method.");
            }
        };
        boolean value;
        try {
            this.d.add(l);
            this.a(new m(-96216471));
            this.d.remove(l);
            value = atomicBoolean.get();
            if (Task.a != 0) {
                k.h = ++h;
            }
        }
        catch (RuntimeException ex) {
            throw ex;
        }
        return value;
    }
    
    public Collection<String> e() {
        final ConcurrentLinkedQueue<String> concurrentLinkedQueue = new ConcurrentLinkedQueue<String>();
        final l l = new l() {
            @Override
            public boolean a(final m m, final SocketAddress socketAddress) {
                final int h = k.h;
                try {
                    final int b;
                    final int n = b = m.b();
                    if (h != 0) {
                        return b != 0;
                    }
                    if (n != -96216441) {
                        return true;
                    }
                }
                catch (RuntimeException ex) {
                    throw ex;
                }
                final Object[] c = m.c();
                final int length = c.length;
                int i = 0;
                while (i < length) {
                    final Object o = c[i];
                    try {
                        final boolean add = concurrentLinkedQueue.add(o);
                        if (h != 0) {
                            return add;
                        }
                        ++i;
                        if (h == 0) {
                            continue;
                        }
                    }
                    catch (RuntimeException ex2) {
                        throw ex2;
                    }
                    break;
                }
                return false;
                int b = 1;
                return b != 0;
            }
        };
        this.d.add(l);
        this.a(new m(-96216441));
        this.d.remove(l);
        return concurrentLinkedQueue;
    }
    
    static {
        final String[] z2 = new String[3];
        int n3;
        int n2;
        int n = n2 = (n3 = 0);
        String s = "Hp2|\b\u001dT[\u0011b562v\u0006B\u001d";
        int n4 = -1;
        String intern = null;
    Label_0056_Outer:
        while (true) {
            final char[] charArray = s.toCharArray();
            int length;
            int n6;
            final int n5 = n6 = (length = charArray.length);
            int n7 = 0;
            while (true) {
                Label_0130: {
                    if (n5 > 1) {
                        break Label_0130;
                    }
                    length = (n6 = n7);
                    do {
                        final char c = charArray[n6];
                        char c2 = '\0';
                        switch (n7 % 5) {
                            case 0: {
                                c2 = '\u001a';
                                break;
                            }
                            case 1: {
                                c2 = '2';
                                break;
                            }
                            case 2: {
                                c2 = 'O';
                                break;
                            }
                            case 3: {
                                c2 = '{';
                                break;
                            }
                            default: {
                                c2 = 'd';
                                break;
                            }
                        }
                        charArray[length] = (char)(c ^ c2);
                        ++n7;
                    } while (n5 == 0);
                }
                if (n5 > n7) {
                    continue;
                }
                break;
            }
            intern = new String(charArray).intern();
            switch (n4) {
                default: {
                    z2[n2] = intern;
                    n = (n2 = (n3 = 1));
                    s = "[J\u0003\u0010#sp6,";
                    n4 = 0;
                    continue Label_0056_Outer;
                }
                case 0: {
                    z2[n] = intern;
                    n = (n2 = (n3 = 2));
                    s = "\nX^\u0004i{#%";
                    n4 = 1;
                    continue Label_0056_Outer;
                }
                case 1: {
                    break Label_0056_Outer;
                }
            }
        }
        z2[n3] = intern;
        z = z2;
        a = Logger.getLogger(k.class.getName());
    }
    
    private final class e_ implements Runnable
    {
        private final m a;
        private final SocketAddress b;
        private final Iterable<l> c;
        
        public e_(final m a, final SocketAddress b, final Iterable<l> c) {
            this.a = a;
            this.b = b;
            this.c = c;
        }
        
        @Override
        public void run() {
            final int h = k.h;
            for (final l l : this.c) {
                Label_0061: {
                    try {
                        Label_0056: {
                            if (l.a(this.a, this.b)) {
                                break Label_0056;
                            }
                            try {
                                if (h != 0) {
                                    break Label_0061;
                                }
                                break;
                            }
                            catch (Exception ex) {
                                throw ex;
                            }
                        }
                    }
                    catch (Exception ex2) {}
                }
                if (h != 0) {
                    break;
                }
            }
        }
    }
}
