
package org.powerbot;

import javax.swing.JComboBox;
import javax.swing.JTextField;
import javax.swing.JPasswordField;
import javax.swing.DefaultCellEditor;
import javax.swing.table.DefaultTableCellRenderer;
import javax.swing.event.ListSelectionEvent;
import javax.swing.event.ListSelectionListener;
import java.io.Serializable;
import javax.swing.table.AbstractTableModel;
import org.powerbot.core.script.internal.wrappers.HashTable;
import java.awt.event.WindowEvent;
import javax.swing.JButton;
import javax.swing.JTable;
import java.util.logging.Logger;
import java.awt.event.WindowListener;
import javax.swing.JDialog;

public final class mb extends JDialog implements WindowListener
{
    private final Logger a;
    private static final long serialVersionUID = 1L;
    private final JTable b;
    private final JButton c;
    private static final String[] d;
    private static final String[] z;
    
    public mb(final qb p0) {
        // 
        // This method could not be decompiled.
        // 
        // Original Bytecode:
        // 
        //     3: istore          7
        //     5: aload_0        
        //     6: aload_1        
        //     7: getstatic       org/powerbot/mb.z:[Ljava/lang/String;
        //    10: iconst_4       
        //    11: aaload         
        //    12: invokestatic    org/powerbot/s.a:(Ljava/lang/String;)Ljava/lang/String;
        //    15: iconst_1       
        //    16: invokespecial   javax/swing/JDialog.<init>:(Ljava/awt/Frame;Ljava/lang/String;Z)V
        //    19: aload_0        
        //    20: ldc             Lorg/powerbot/mb;.class
        //    22: invokevirtual   java/lang/Class.getName:()Ljava/lang/String;
        //    25: invokestatic    java/util/logging/Logger.getLogger:(Ljava/lang/String;)Ljava/util/logging/Logger;
        //    28: putfield        org/powerbot/mb.a:Ljava/util/logging/Logger;
        //    31: aload_0        
        //    32: getstatic       org/powerbot/mb.z:[Ljava/lang/String;
        //    35: iconst_5       
        //    36: aaload         
        //    37: invokestatic    org/powerbot/core/script/internal/wrappers/HashTable.e:(Ljava/lang/String;)Ljava/lang/String;
        //    40: invokestatic    org/powerbot/db.b:(Ljava/lang/String;)Ljava/awt/Image;
        //    43: invokevirtual   org/powerbot/mb.setIconImage:(Ljava/awt/Image;)V
        //    46: new             Ljavax/swing/JScrollPane;
        //    49: dup            
        //    50: invokespecial   javax/swing/JScrollPane.<init>:()V
        //    53: astore_2       
        //    54: aload_0        
        //    55: new             Ljavax/swing/JTable;
        //    58: dup            
        //    59: new             Lorg/powerbot/mb$a_;
        //    62: dup            
        //    63: aload_0        
        //    64: aconst_null    
        //    65: invokespecial   org/powerbot/mb$a_.<init>:(Lorg/powerbot/mb;Lorg/powerbot/mb$6;)V
        //    68: invokespecial   javax/swing/JTable.<init>:(Ljavax/swing/table/TableModel;)V
        //    71: putfield        org/powerbot/mb.b:Ljavax/swing/JTable;
        //    74: aload_0        
        //    75: getfield        org/powerbot/mb.b:Ljavax/swing/JTable;
        //    78: iconst_0       
        //    79: invokevirtual   javax/swing/JTable.setSelectionMode:(I)V
        //    82: aload_0        
        //    83: getfield        org/powerbot/mb.b:Ljavax/swing/JTable;
        //    86: invokevirtual   javax/swing/JTable.getSelectionModel:()Ljavax/swing/ListSelectionModel;
        //    89: new             Lorg/powerbot/mb$e_;
        //    92: dup            
        //    93: aload_0        
        //    94: aconst_null    
        //    95: invokespecial   org/powerbot/mb$e_.<init>:(Lorg/powerbot/mb;Lorg/powerbot/mb$6;)V
        //    98: invokeinterface javax/swing/ListSelectionModel.addListSelectionListener:(Ljavax/swing/event/ListSelectionListener;)V
        //   103: aload_0        
        //   104: getfield        org/powerbot/mb.b:Ljavax/swing/JTable;
        //   107: iconst_0       
        //   108: invokevirtual   javax/swing/JTable.setShowGrid:(Z)V
        //   111: aload_0        
        //   112: getfield        org/powerbot/mb.b:Ljavax/swing/JTable;
        //   115: invokevirtual   javax/swing/JTable.getColumnModel:()Ljavax/swing/table/TableColumnModel;
        //   118: astore_3       
        //   119: iconst_1       
        //   120: istore          4
        //   122: iload           4
        //   124: iconst_3       
        //   125: if_icmpge       182
        //   128: aload_3        
        //   129: iload           4
        //   131: invokeinterface javax/swing/table/TableColumnModel.getColumn:(I)Ljavax/swing/table/TableColumn;
        //   136: new             Lorg/powerbot/mb$b_;
        //   139: dup            
        //   140: aconst_null    
        //   141: invokespecial   org/powerbot/mb$b_.<init>:(Lorg/powerbot/mb$6;)V
        //   144: invokevirtual   javax/swing/table/TableColumn.setCellRenderer:(Ljavax/swing/table/TableCellRenderer;)V
        //   147: aload_3        
        //   148: iload           4
        //   150: invokeinterface javax/swing/table/TableColumnModel.getColumn:(I)Ljavax/swing/table/TableColumn;
        //   155: new             Lorg/powerbot/mb$c_;
        //   158: dup            
        //   159: invokespecial   org/powerbot/mb$c_.<init>:()V
        //   162: invokevirtual   javax/swing/table/TableColumn.setCellEditor:(Ljavax/swing/table/TableCellEditor;)V
        //   165: iinc            4, 1
        //   168: iload           7
        //   170: ifne            244
        //   173: iload           7
        //   175: ifeq            122
        //   178: goto            182
        //   181: athrow         
        //   182: aload_3        
        //   183: iconst_4       
        //   184: invokeinterface javax/swing/table/TableColumnModel.getColumn:(I)Ljavax/swing/table/TableColumn;
        //   189: new             Lorg/powerbot/mb$d_;
        //   192: dup            
        //   193: invokespecial   org/powerbot/mb$d_.<init>:()V
        //   196: invokevirtual   javax/swing/table/TableColumn.setCellEditor:(Ljavax/swing/table/TableCellEditor;)V
        //   199: aload_2        
        //   200: bipush          31
        //   202: invokevirtual   javax/swing/JScrollPane.setHorizontalScrollBarPolicy:(I)V
        //   205: aload_2        
        //   206: aload_0        
        //   207: getfield        org/powerbot/mb.b:Ljavax/swing/JTable;
        //   210: invokevirtual   javax/swing/JScrollPane.setViewportView:(Ljava/awt/Component;)V
        //   213: aload_2        
        //   214: new             Ljava/awt/Dimension;
        //   217: dup            
        //   218: sipush          400
        //   221: sipush          150
        //   224: invokespecial   java/awt/Dimension.<init>:(II)V
        //   227: invokevirtual   javax/swing/JScrollPane.setPreferredSize:(Ljava/awt/Dimension;)V
        //   230: aload_0        
        //   231: aload_2        
        //   232: getstatic       org/powerbot/mb.z:[Ljava/lang/String;
        //   235: bipush          8
        //   237: aaload         
        //   238: invokestatic    org/powerbot/s.a:(Ljava/lang/String;)Ljava/lang/String;
        //   241: invokevirtual   org/powerbot/mb.add:(Ljava/awt/Component;Ljava/lang/Object;)V
        //   244: new             Ljavax/swing/JToolBar;
        //   247: dup            
        //   248: invokespecial   javax/swing/JToolBar.<init>:()V
        //   251: astore          4
        //   253: aload           4
        //   255: iconst_0       
        //   256: invokevirtual   javax/swing/JToolBar.setFloatable:(Z)V
        //   259: new             Ljavax/swing/JButton;
        //   262: dup            
        //   263: new             Ljavax/swing/ImageIcon;
        //   266: dup            
        //   267: getstatic       org/powerbot/mb.z:[Ljava/lang/String;
        //   270: iconst_3       
        //   271: aaload         
        //   272: invokestatic    org/powerbot/core/script/internal/wrappers/HashTable.e:(Ljava/lang/String;)Ljava/lang/String;
        //   275: invokestatic    org/powerbot/db.b:(Ljava/lang/String;)Ljava/awt/Image;
        //   278: invokespecial   javax/swing/ImageIcon.<init>:(Ljava/awt/Image;)V
        //   281: invokespecial   javax/swing/JButton.<init>:(Ljavax/swing/Icon;)V
        //   284: astore          5
        //   286: aload           5
        //   288: iconst_0       
        //   289: invokevirtual   javax/swing/JButton.setFocusable:(Z)V
        //   292: aload           5
        //   294: new             Lorg/powerbot/mb$6;
        //   297: dup            
        //   298: aload_0        
        //   299: invokespecial   org/powerbot/mb$6.<init>:(Lorg/powerbot/mb;)V
        //   302: invokevirtual   javax/swing/JButton.addActionListener:(Ljava/awt/event/ActionListener;)V
        //   305: aload_0        
        //   306: new             Ljavax/swing/JButton;
        //   309: dup            
        //   310: new             Ljavax/swing/ImageIcon;
        //   313: dup            
        //   314: getstatic       org/powerbot/mb.z:[Ljava/lang/String;
        //   317: iconst_2       
        //   318: aaload         
        //   319: invokestatic    org/powerbot/s.a:(Ljava/lang/String;)Ljava/lang/String;
        //   322: invokestatic    org/powerbot/db.b:(Ljava/lang/String;)Ljava/awt/Image;
        //   325: invokespecial   javax/swing/ImageIcon.<init>:(Ljava/awt/Image;)V
        //   328: invokespecial   javax/swing/JButton.<init>:(Ljavax/swing/Icon;)V
        //   331: putfield        org/powerbot/mb.c:Ljavax/swing/JButton;
        //   334: aload_0        
        //   335: getfield        org/powerbot/mb.c:Ljavax/swing/JButton;
        //   338: iconst_0       
        //   339: invokevirtual   javax/swing/JButton.setFocusable:(Z)V
        //   342: aload_0        
        //   343: getfield        org/powerbot/mb.c:Ljavax/swing/JButton;
        //   346: new             Lorg/powerbot/mb$5;
        //   349: dup            
        //   350: aload_0        
        //   351: invokespecial   org/powerbot/mb$5.<init>:(Lorg/powerbot/mb;)V
        //   354: invokevirtual   javax/swing/JButton.addActionListener:(Ljava/awt/event/ActionListener;)V
        //   357: aload           4
        //   359: aload           5
        //   361: invokevirtual   javax/swing/JToolBar.add:(Ljava/awt/Component;)Ljava/awt/Component;
        //   364: pop            
        //   365: aload           4
        //   367: aload_0        
        //   368: getfield        org/powerbot/mb.c:Ljavax/swing/JButton;
        //   371: invokevirtual   javax/swing/JToolBar.add:(Ljava/awt/Component;)Ljava/awt/Component;
        //   374: pop            
        //   375: aload_0        
        //   376: aload           4
        //   378: getstatic       org/powerbot/mb.z:[Ljava/lang/String;
        //   381: bipush          7
        //   383: aaload         
        //   384: invokestatic    org/powerbot/core/script/internal/wrappers/HashTable.e:(Ljava/lang/String;)Ljava/lang/String;
        //   387: invokevirtual   org/powerbot/mb.add:(Ljava/awt/Component;Ljava/lang/Object;)V
        //   390: aload_0        
        //   391: getfield        org/powerbot/mb.b:Ljavax/swing/JTable;
        //   394: invokevirtual   javax/swing/JTable.getSelectedRow:()I
        //   397: istore          6
        //   399: aload_0        
        //   400: getfield        org/powerbot/mb.c:Ljavax/swing/JButton;
        //   403: iload           6
        //   405: iconst_m1      
        //   406: iload           7
        //   408: ifne            440
        //   411: if_icmple       447
        //   414: goto            418
        //   417: athrow         
        //   418: iload           6
        //   420: iload           7
        //   422: ifne            444
        //   425: goto            429
        //   428: athrow         
        //   429: aload_0        
        //   430: getfield        org/powerbot/mb.b:Ljavax/swing/JTable;
        //   433: invokevirtual   javax/swing/JTable.getRowCount:()I
        //   436: goto            440
        //   439: athrow         
        //   440: if_icmpge       447
        //   443: iconst_1       
        //   444: goto            448
        //   447: iconst_0       
        //   448: invokevirtual   javax/swing/JButton.setEnabled:(Z)V
        //   451: aload_0        
        //   452: aload_0        
        //   453: invokevirtual   org/powerbot/mb.addWindowListener:(Ljava/awt/event/WindowListener;)V
        //   456: aload_0        
        //   457: invokevirtual   org/powerbot/mb.pack:()V
        //   460: aload_0        
        //   461: aload_0        
        //   462: invokevirtual   org/powerbot/mb.getSize:()Ljava/awt/Dimension;
        //   465: invokevirtual   org/powerbot/mb.setMinimumSize:(Ljava/awt/Dimension;)V
        //   468: aload_0        
        //   469: iconst_0       
        //   470: invokevirtual   org/powerbot/mb.setResizable:(Z)V
        //   473: aload_0        
        //   474: aload_0        
        //   475: invokevirtual   org/powerbot/mb.getParent:()Ljava/awt/Container;
        //   478: invokevirtual   org/powerbot/mb.setLocationRelativeTo:(Ljava/awt/Component;)V
        //   481: aload_0        
        //   482: iconst_1       
        //   483: invokevirtual   org/powerbot/mb.setVisible:(Z)V
        //   486: invokestatic    org/powerbot/hb.a:()Lorg/powerbot/hb;
        //   489: getstatic       org/powerbot/mb.z:[Ljava/lang/String;
        //   492: bipush          6
        //   494: aaload         
        //   495: invokestatic    org/powerbot/s.a:(Ljava/lang/String;)Ljava/lang/String;
        //   498: aload_0        
        //   499: invokevirtual   org/powerbot/mb.getTitle:()Ljava/lang/String;
        //   502: invokevirtual   org/powerbot/hb.b:(Ljava/lang/String;Ljava/lang/String;)V
        //   505: return         
        //    StackMapTable: 00 0D FF 00 7A 00 08 07 00 05 07 01 80 07 00 0B 07 00 92 01 00 00 01 00 00 7A 07 01 86 00 3D FF 00 AC 00 08 07 00 05 07 01 80 07 00 0B 07 00 92 07 00 27 07 00 2A 01 01 00 01 07 01 86 40 07 00 2A 49 07 01 86 FF 00 00 00 08 07 00 05 07 01 80 07 00 0B 07 00 92 07 00 27 07 00 2A 01 01 00 02 07 00 2A 01 49 07 01 86 FF 00 00 00 08 07 00 05 07 01 80 07 00 0B 07 00 92 07 00 27 07 00 2A 01 01 00 03 07 00 2A 01 01 FF 00 03 00 08 07 00 05 07 01 80 07 00 0B 07 00 92 07 00 27 07 00 2A 01 01 00 02 07 00 2A 01 42 07 00 2A FF 00 00 00 08 07 00 05 07 01 80 07 00 0B 07 00 92 07 00 27 07 00 2A 01 01 00 02 07 00 2A 01
        //    Exceptions:
        //  Try           Handler
        //  Start  End    Start  End    Type                        
        //  -----  -----  -----  -----  ----------------------------
        //  418    436    439    440    Ljava/lang/RuntimeException;
        //  411    425    428    429    Ljava/lang/RuntimeException;
        //  399    414    417    418    Ljava/lang/RuntimeException;
        //  128    178    181    182    Ljava/lang/RuntimeException;
        // 
        // The error that occurred was:
        // 
        // java.lang.IllegalStateException: Expression is linked from several locations: Label_0418:
        //     at com.strobel.decompiler.ast.Error.expressionLinkedFromMultipleLocations(Error.java:27)
        //     at com.strobel.decompiler.ast.AstOptimizer.mergeDisparateObjectInitializations(AstOptimizer.java:2596)
        //     at com.strobel.decompiler.ast.AstOptimizer.optimize(AstOptimizer.java:235)
        //     at com.strobel.decompiler.ast.AstOptimizer.optimize(AstOptimizer.java:42)
        //     at com.strobel.decompiler.languages.java.ast.AstMethodBodyBuilder.createMethodBody(AstMethodBodyBuilder.java:214)
        //     at com.strobel.decompiler.languages.java.ast.AstMethodBodyBuilder.createMethodBody(AstMethodBodyBuilder.java:99)
        //     at com.strobel.decompiler.languages.java.ast.AstBuilder.createMethodBody(AstBuilder.java:782)
        //     at com.strobel.decompiler.languages.java.ast.AstBuilder.createConstructor(AstBuilder.java:713)
        //     at com.strobel.decompiler.languages.java.ast.AstBuilder.addTypeMembers(AstBuilder.java:549)
        //     at com.strobel.decompiler.languages.java.ast.AstBuilder.createTypeCore(AstBuilder.java:519)
        //     at com.strobel.decompiler.languages.java.ast.AstBuilder.createTypeNoCache(AstBuilder.java:161)
        //     at com.strobel.decompiler.languages.java.ast.AstBuilder.createType(AstBuilder.java:150)
        //     at com.strobel.decompiler.languages.java.ast.AstBuilder.addType(AstBuilder.java:125)
        //     at com.strobel.decompiler.languages.java.JavaLanguage.buildAst(JavaLanguage.java:71)
        //     at com.strobel.decompiler.languages.java.JavaLanguage.decompileType(JavaLanguage.java:59)
        //     at com.strobel.decompiler.DecompilerDriver.decompileType(DecompilerDriver.java:330)
        //     at com.strobel.decompiler.DecompilerDriver.decompileJar(DecompilerDriver.java:251)
        //     at com.strobel.decompiler.DecompilerDriver.main(DecompilerDriver.java:126)
        // 
        throw new IllegalStateException("An error occurred while decompiling this method.");
    }
    
    @Override
    public void windowActivated(final WindowEvent windowEvent) {
    }
    
    @Override
    public void windowClosed(final WindowEvent windowEvent) {
    }
    
    @Override
    public void windowClosing(final WindowEvent windowEvent) {
        this.setVisible(false);
        try {
            this.a.info(HashTable.e(mb.z[1]) + jb.a().size() + s.a(mb.z[0]));
            jb.a().c();
        }
        catch (Exception ex) {
            ex.printStackTrace();
        }
    }
    
    @Override
    public void windowDeactivated(final WindowEvent windowEvent) {
    }
    
    @Override
    public void windowDeiconified(final WindowEvent windowEvent) {
    }
    
    @Override
    public void windowIconified(final WindowEvent windowEvent) {
    }
    
    @Override
    public void windowOpened(final WindowEvent windowEvent) {
    }
    
    static {
        String[] d2;
        String[] array47;
        String[] array46;
        String[] array45;
        String[] array44;
        String[] array43;
        String[] array42;
        String[] array41;
        String[] array40;
        String[] array39;
        String[] array38;
        String[] array37;
        String[] array36;
        String[] array35;
        String[] array34;
        String[] array33;
        String[] array32;
        String[] array31;
        String[] array30;
        String[] array29;
        String[] array28;
        String[] array27;
        String[] array26;
        String[] array25;
        String[] array24;
        String[] array23;
        String[] array22;
        String[] array21;
        String[] array20;
        String[] array19;
        String[] array18;
        String[] array17;
        String[] array16;
        String[] array15;
        String[] array14;
        String[] array13;
        String[] array12;
        String[] array11;
        String[] array10;
        String[] z2;
        String[] array9;
        String[] array8;
        String[] array7;
        String[] array6;
        String[] array5;
        String[] array4;
        String[] array3;
        String[] array2;
        String[] array = array2 = (array3 = (array4 = (array5 = (array6 = (array7 = (array8 = (array9 = (z2 = (array10 = (array11 = (array12 = (array13 = (array14 = (array15 = (array16 = (array17 = (array18 = (array19 = (array20 = (array21 = (array22 = (array23 = (array24 = (array25 = (array26 = (array27 = (array28 = (array29 = (array30 = (array31 = (array32 = (array33 = (array34 = (array35 = (array36 = (array37 = (array38 = (array39 = (array40 = (array41 = (array42 = (array43 = (array44 = (array45 = (array46 = (array47 = (d2 = new String[9])))))))))))))))))))))))))))))))))))))))))))))));
        int n47;
        int n46;
        int n45;
        int n44;
        int n43;
        int n42;
        int n41;
        int n40;
        int n39;
        int n38;
        int n37;
        int n36;
        int n35;
        int n34;
        int n33;
        int n32;
        int n31;
        int n30;
        int n29;
        int n28;
        int n27;
        int n26;
        int n25;
        int n24;
        int n23;
        int n22;
        int n21;
        int n20;
        int n19;
        int n18;
        int n17;
        int n16;
        int n15;
        int n14;
        int n13;
        int n12;
        int n11;
        int n10;
        int n9;
        int n8;
        int n7;
        int n6;
        int n5;
        int n4;
        int n3;
        int n2;
        int n = n2 = (n3 = (n4 = (n5 = (n6 = (n7 = (n8 = (n9 = (n10 = (n11 = (n12 = (n13 = (n14 = (n15 = (n16 = (n17 = (n18 = (n19 = (n20 = (n21 = (n22 = (n23 = (n24 = (n25 = (n26 = (n27 = (n28 = (n29 = (n30 = (n31 = (n32 = (n33 = (n34 = (n35 = (n36 = (n37 = (n38 = (n39 = (n40 = (n41 = (n42 = (n43 = (n44 = (n45 = (n46 = (n47 = 0)))))))))))))))))))))))))))))))))))))))))))));
        String s = "\rcvU[9\r\u0000$";
        int n48 = -1;
        String intern = null;
    Label_0122_Outer:
        while (true) {
            final char[] charArray = s.toCharArray();
            int length;
            int n50;
            final int n49 = n50 = (length = charArray.length);
            int n51 = 0;
            while (true) {
                Label_0198: {
                    if (n49 > 1) {
                        break Label_0198;
                    }
                    length = (n50 = n51);
                    do {
                        final char c = charArray[n50];
                        char c2 = '\0';
                        switch (n51 % 5) {
                            case 0: {
                                c2 = 'C';
                                break;
                            }
                            case 1: {
                                c2 = '\r';
                                break;
                            }
                            case 2: {
                                c2 = '{';
                                break;
                            }
                            case 3: {
                                c2 = '9';
                                break;
                            }
                            default: {
                                c2 = 'Z';
                                break;
                            }
                        }
                        charArray[length] = (char)(c ^ c2);
                        ++n51;
                    } while (n49 == 0);
                }
                if (n49 > n51) {
                    continue;
                }
                break;
            }
            intern = new String(charArray).intern();
            switch (n48) {
                default: {
                    array2[n2] = intern;
                    n = (n2 = (n3 = (n4 = (n5 = (n6 = (n7 = (n8 = (n9 = (n10 = (n11 = (n12 = (n13 = (n14 = (n15 = (n16 = (n17 = (n18 = (n19 = (n20 = (n21 = (n22 = (n23 = (n24 = (n25 = (n26 = (n27 = (n28 = (n29 = (n30 = (n31 = (n32 = (n33 = (n34 = (n35 = (n36 = (n37 = (n38 = (n39 = (n40 = (n41 = (n42 = (n43 = (n44 = (n45 = (n46 = (n47 = 1))))))))))))))))))))))))))))))))))))))))))))));
                    s = ",\\1`\b\u0014\u0011";
                    n48 = 0;
                    continue Label_0122_Outer;
                }
                case 0: {
                    array[n] = intern;
                    n = (n2 = (n3 = (n4 = (n5 = (n6 = (n7 = (n8 = (n9 = (n10 = (n11 = (n12 = (n13 = (n14 = (n15 = (n16 = (n17 = (n18 = (n19 = (n20 = (n21 = (n22 = (n23 = (n24 = (n25 = (n26 = (n27 = (n28 = (n29 = (n30 = (n31 = (n32 = (n33 = (n34 = (n35 = (n36 = (n37 = (n38 = (n39 = (n40 = (n41 = (n42 = (n43 = (n44 = (n45 = (n46 = (n47 = 2))))))))))))))))))))))))))))))))))))))))))))));
                    s = ">\u0006\u00078 _apE\u001b%\u000e\u001500^-rZM<\u000b\u001d4:CqJ\u0007\r{<\u000628Btp\u0018D\"\u0004";
                    n48 = 1;
                    continue Label_0122_Outer;
                }
                case 1: {
                    array3[n3] = intern;
                    n = (n2 = (n3 = (n4 = (n5 = (n6 = (n7 = (n8 = (n9 = (n10 = (n11 = (n12 = (n13 = (n14 = (n15 = (n16 = (n17 = (n18 = (n19 = (n20 = (n21 = (n22 = (n23 = (n24 = (n25 = (n26 = (n27 = (n28 = (n29 = (n30 = (n31 = (n32 = (n33 = (n34 = (n35 = (n36 = (n37 = (n38 = (n39 = (n40 = (n41 = (n42 = (n43 = (n44 = (n45 = (n46 = (n47 = 3))))))))))))))))))))))))))))))))))))))))))))));
                    s = "\rX4f\u0013\u0001R.vE\u0016P&n\u0003\u0000\u001e,i\u0013\u000fU.j\t\u001dB\u00144SOb$`\u0014\u0010].Z\u001a\u0013H4'\u0016\u001dV";
                    n48 = 2;
                    continue Label_0122_Outer;
                }
                case 2: {
                    array4[n4] = intern;
                    n = (n2 = (n3 = (n4 = (n5 = (n6 = (n7 = (n8 = (n9 = (n10 = (n11 = (n12 = (n13 = (n14 = (n15 = (n16 = (n17 = (n18 = (n19 = (n20 = (n21 = (n22 = (n23 = (n24 = (n25 = (n26 = (n27 = (n28 = (n29 = (n30 = (n31 = (n32 = (n33 = (n34 = (n35 = (n36 = (n37 = (n38 = (n39 = (n40 = (n41 = (n42 = (n43 = (n44 = (n45 = (n46 = (n47 = 4))))))))))))))))))))))))))))))))))))))))))))));
                    s = "\r\u0000\u00178 Cvf";
                    n48 = 3;
                    continue Label_0122_Outer;
                }
                case 3: {
                    array5[n5] = intern;
                    n = (n2 = (n3 = (n4 = (n5 = (n6 = (n7 = (n8 = (n9 = (n10 = (n11 = (n12 = (n13 = (n14 = (n15 = (n16 = (n17 = (n18 = (n19 = (n20 = (n21 = (n22 = (n23 = (n24 = (n25 = (n26 = (n27 = (n28 = (n29 = (n30 = (n31 = (n32 = (n33 = (n34 = (n35 = (n36 = (n37 = (n38 = (n39 = (n40 = (n41 = (n42 = (n43 = (n44 = (n45 = (n46 = (n47 = 5))))))))))))))))))))))))))))))))))))))))))))));
                    s = "\rX4f\u0013\u0001R.vE\u0016P&n\u0003\u0000\u001e,i\u0013\u000fU.j\t\u001dB\u00145RGb&m\u0014\u0016B8Z\b\u0010R,'\u0016\u001dV";
                    n48 = 4;
                    continue Label_0122_Outer;
                }
                case 4: {
                    array6[n6] = intern;
                    n = (n2 = (n3 = (n4 = (n5 = (n6 = (n7 = (n8 = (n9 = (n10 = (n11 = (n12 = (n13 = (n14 = (n15 = (n16 = (n17 = (n18 = (n19 = (n20 = (n21 = (n22 = (n23 = (n24 = (n25 = (n26 = (n27 = (n28 = (n29 = (n30 = (n31 = (n32 = (n33 = (n34 = (n35 = (n36 = (n37 = (n38 = (n39 = (n40 = (n41 = (n42 = (n43 = (n44 = (n45 = (n46 = (n47 = 6))))))))))))))))))))))))))))))))))))))))))))));
                    s = "LavYA\"\u0017\u0007x";
                    n48 = 5;
                    continue Label_0122_Outer;
                }
                case 5: {
                    array7[n7] = intern;
                    n = (n2 = (n3 = (n4 = (n5 = (n6 = (n7 = (n8 = (n9 = (n10 = (n11 = (n12 = (n13 = (n14 = (n15 = (n16 = (n17 = (n18 = (n19 = (n20 = (n21 = (n22 = (n23 = (n24 = (n25 = (n26 = (n27 = (n28 = (n29 = (n30 = (n31 = (n32 = (n33 = (n34 = (n35 = (n36 = (n37 = (n38 = (n39 = (n40 = (n41 = (n42 = (n43 = (n44 = (n45 = (n46 = (n47 = 7))))))))))))))))))))))))))))))))))))))))))))));
                    s = ",R2}\u000e";
                    n48 = 6;
                    continue Label_0122_Outer;
                }
                case 6: {
                    array8[n8] = intern;
                    n = (n2 = (n3 = (n4 = (n5 = (n6 = (n7 = (n8 = (n9 = (n10 = (n11 = (n12 = (n13 = (n14 = (n15 = (n16 = (n17 = (n18 = (n19 = (n20 = (n21 = (n22 = (n23 = (n24 = (n25 = (n26 = (n27 = (n28 = (n29 = (n30 = (n31 = (n32 = (n33 = (n34 = (n35 = (n36 = (n37 = (n38 = (n39 = (n40 = (n41 = (n42 = (n43 = (n44 = (n45 = (n46 = (n47 = 8))))))))))))))))))))))))))))))))))))))))))))));
                    s = "\u000f\u0006\u001a#0_";
                    n48 = 7;
                    continue Label_0122_Outer;
                }
                case 7: {
                    array9[n9] = intern;
                    z = z2;
                    array = (array2 = (array3 = (array4 = (array5 = (array6 = (array7 = (array8 = (array9 = (z2 = (array10 = (array11 = (array12 = (array13 = (array14 = (array15 = (array16 = (array17 = (array18 = (array19 = (array20 = (array21 = (array22 = (array23 = (array24 = (array25 = (array26 = (array27 = (array28 = (array29 = (array30 = (array31 = (array32 = (array33 = (array34 = (array35 = (array36 = (array37 = (array38 = (array39 = (array40 = (array41 = (array42 = (array43 = (array44 = (array45 = (array46 = (array47 = (d2 = new String[38]))))))))))))))))))))))))))))))))))))))))))))))));
                    n = (n2 = (n3 = (n4 = (n5 = (n6 = (n7 = (n8 = (n9 = (n10 = (n11 = (n12 = (n13 = (n14 = (n15 = (n16 = (n17 = (n18 = (n19 = (n20 = (n21 = (n22 = (n23 = (n24 = (n25 = (n26 = (n27 = (n28 = (n29 = (n30 = (n31 = (n32 = (n33 = (n34 = (n35 = (n36 = (n37 = (n38 = (n39 = (n40 = (n41 = (n42 = (n43 = (n44 = (n45 = (n46 = (n47 = 0))))))))))))))))))))))))))))))))))))))))))))));
                    s = "0P8m";
                    n48 = 8;
                    continue Label_0122_Outer;
                }
                case 8: {
                    array10[n10] = HashTable.e(intern);
                    n = (n2 = (n3 = (n4 = (n5 = (n6 = (n7 = (n8 = (n9 = (n10 = (n11 = (n12 = (n13 = (n14 = (n15 = (n16 = (n17 = (n18 = (n19 = (n20 = (n21 = (n22 = (n23 = (n24 = (n25 = (n26 = (n27 = (n28 = (n29 = (n30 = (n31 = (n32 = (n33 = (n34 = (n35 = (n36 = (n37 = (n38 = (n39 = (n40 = (n41 = (n42 = (n43 = (n44 = (n45 = (n46 = (n47 = 1))))))))))))))))))))))))))))))))))))))))))))));
                    s = "\u007fw{SG";
                    n48 = 9;
                    continue Label_0122_Outer;
                }
                case 9: {
                    array11[n11] = org.powerbot.s.a(intern);
                    n = (n2 = (n3 = (n4 = (n5 = (n6 = (n7 = (n8 = (n9 = (n10 = (n11 = (n12 = (n13 = (n14 = (n15 = (n16 = (n17 = (n18 = (n19 = (n20 = (n21 = (n22 = (n23 = (n24 = (n25 = (n26 = (n27 = (n28 = (n29 = (n30 = (n31 = (n32 = (n33 = (n34 = (n35 = (n36 = (n37 = (n38 = (n39 = (n40 = (n41 = (n42 = (n43 = (n44 = (n45 = (n46 = (n47 = 2))))))))))))))))))))))))))))))))))))))))))))));
                    s = "0^*i";
                    n48 = 10;
                    continue Label_0122_Outer;
                }
                case 10: {
                    array12[n12] = HashTable.e(intern);
                    n = (n2 = (n3 = (n4 = (n5 = (n6 = (n7 = (n8 = (n9 = (n10 = (n11 = (n12 = (n13 = (n14 = (n15 = (n16 = (n17 = (n18 = (n19 = (n20 = (n21 = (n22 = (n23 = (n24 = (n25 = (n26 = (n27 = (n28 = (n29 = (n30 = (n31 = (n32 = (n33 = (n34 = (n35 = (n36 = (n37 = (n38 = (n39 = (n40 = (n41 = (n42 = (n43 = (n44 = (n45 = (n46 = (n47 = 3))))))))))))))))))))))))))))))))))))))))))))));
                    s = "hqfSZ/\u0006";
                    n48 = 11;
                    continue Label_0122_Outer;
                }
                case 11: {
                    array13[n13] = org.powerbot.s.a(intern);
                    n = (n2 = (n3 = (n4 = (n5 = (n6 = (n7 = (n8 = (n9 = (n10 = (n11 = (n12 = (n13 = (n14 = (n15 = (n16 = (n17 = (n18 = (n19 = (n20 = (n21 = (n22 = (n23 = (n24 = (n25 = (n26 = (n27 = (n28 = (n29 = (n30 = (n31 = (n32 = (n33 = (n34 = (n35 = (n36 = (n37 = (n38 = (n39 = (n40 = (n41 = (n42 = (n43 = (n44 = (n45 = (n46 = (n47 = 4))))))))))))))))))))))))))))))))))))))))))))));
                    s = "0O\"";
                    n48 = 12;
                    continue Label_0122_Outer;
                }
                case 12: {
                    array14[n14] = HashTable.e(intern);
                    n = (n2 = (n3 = (n4 = (n5 = (n6 = (n7 = (n8 = (n9 = (n10 = (n11 = (n12 = (n13 = (n14 = (n15 = (n16 = (n17 = (n18 = (n19 = (n20 = (n21 = (n22 = (n23 = (n24 = (n25 = (n26 = (n27 = (n28 = (n29 = (n30 = (n31 = (n32 = (n33 = (n34 = (n35 = (n36 = (n37 = (n38 = (n39 = (n40 = (n41 = (n42 = (n43 = (n44 = (n45 = (n46 = (n47 = 5))))))))))))))))))))))))))))))))))))))))))))));
                    s = "\u000e\u0002\u0006$";
                    n48 = 13;
                    continue Label_0122_Outer;
                }
                case 13: {
                    array15[n15] = org.powerbot.s.a(intern);
                    n = (n2 = (n3 = (n4 = (n5 = (n6 = (n7 = (n8 = (n9 = (n10 = (n11 = (n12 = (n13 = (n14 = (n15 = (n16 = (n17 = (n18 = (n19 = (n20 = (n21 = (n22 = (n23 = (n24 = (n25 = (n26 = (n27 = (n28 = (n29 = (n30 = (n31 = (n32 = (n33 = (n34 = (n35 = (n36 = (n37 = (n38 = (n39 = (n40 = (n41 = (n42 = (n43 = (n44 = (n45 = (n46 = (n47 = 6))))))))))))))))))))))))))))))))))))))))))))));
                    s = "4T&v";
                    n48 = 14;
                    continue Label_0122_Outer;
                }
                case 14: {
                    array16[n16] = HashTable.e(intern);
                    n = (n2 = (n3 = (n4 = (n5 = (n6 = (n7 = (n8 = (n9 = (n10 = (n11 = (n12 = (n13 = (n14 = (n15 = (n16 = (n17 = (n18 = (n19 = (n20 = (n21 = (n22 = (n23 = (n24 = (n25 = (n26 = (n27 = (n28 = (n29 = (n30 = (n31 = (n32 = (n33 = (n34 = (n35 = (n36 = (n37 = (n38 = (n39 = (n40 = (n41 = (n42 = (n43 = (n44 = (n45 = (n46 = (n47 = 7))))))))))))))))))))))))))))))))))))))))))))));
                    s = "eggTG";
                    n48 = 15;
                    continue Label_0122_Outer;
                }
                case 15: {
                    array17[n17] = org.powerbot.s.a(intern);
                    n = (n2 = (n3 = (n4 = (n5 = (n6 = (n7 = (n8 = (n9 = (n10 = (n11 = (n12 = (n13 = (n14 = (n15 = (n16 = (n17 = (n18 = (n19 = (n20 = (n21 = (n22 = (n23 = (n24 = (n25 = (n26 = (n27 = (n28 = (n29 = (n30 = (n31 = (n32 = (n33 = (n34 = (n35 = (n36 = (n37 = (n38 = (n39 = (n40 = (n41 = (n42 = (n43 = (n44 = (n45 = (n46 = (n47 = 8))))))))))))))))))))))))))))))))))))))))))))));
                    s = ",X\"m\u0015";
                    n48 = 16;
                    continue Label_0122_Outer;
                }
                case 16: {
                    array18[n18] = HashTable.e(intern);
                    n = (n2 = (n3 = (n4 = (n5 = (n6 = (n7 = (n8 = (n9 = (n10 = (n11 = (n12 = (n13 = (n14 = (n15 = (n16 = (n17 = (n18 = (n19 = (n20 = (n21 = (n22 = (n23 = (n24 = (n25 = (n26 = (n27 = (n28 = (n29 = (n30 = (n31 = (n32 = (n33 = (n34 = (n35 = (n36 = (n37 = (n38 = (n39 = (n40 = (n41 = (n42 = (n43 = (n44 = (n45 = (n46 = (n47 = 9))))))))))))))))))))))))))))))))))))))))))))));
                    s = "\u000f\u000b\u0015%8^";
                    n48 = 17;
                    continue Label_0122_Outer;
                }
                case 17: {
                    array19[n19] = org.powerbot.s.a(intern);
                    n = (n2 = (n3 = (n4 = (n5 = (n6 = (n7 = (n8 = (n9 = (n10 = (n11 = (n12 = (n13 = (n14 = (n15 = (n16 = (n17 = (n18 = (n19 = (n20 = (n21 = (n22 = (n23 = (n24 = (n25 = (n26 = (n27 = (n28 = (n29 = (n30 = (n31 = (n32 = (n33 = (n34 = (n35 = (n36 = (n37 = (n38 = (n39 = (n40 = (n41 = (n42 = (n43 = (n44 = (n45 = (n46 = (n47 = 10))))))))))))))))))))))))))))))))))))))))))))));
                    s = " D9u\u0018\u0016N\"";
                    n48 = 18;
                    continue Label_0122_Outer;
                }
                case 18: {
                    array20[n20] = HashTable.e(intern);
                    n = (n2 = (n3 = (n4 = (n5 = (n6 = (n7 = (n8 = (n9 = (n10 = (n11 = (n12 = (n13 = (n14 = (n15 = (n16 = (n17 = (n18 = (n19 = (n20 = (n21 = (n22 = (n23 = (n24 = (n25 = (n26 = (n27 = (n28 = (n29 = (n30 = (n31 = (n32 = (n33 = (n34 = (n35 = (n36 = (n37 = (n38 = (n39 = (n40 = (n41 = (n42 = (n43 = (n44 = (n45 = (n46 = (n47 = 11))))))))))))))))))))))))))))))))))))))))))))));
                    s = "hozBQ";
                    n48 = 19;
                    continue Label_0122_Outer;
                }
                case 19: {
                    array21[n21] = org.powerbot.s.a(intern);
                    n = (n2 = (n3 = (n4 = (n5 = (n6 = (n7 = (n8 = (n9 = (n10 = (n11 = (n12 = (n13 = (n14 = (n15 = (n16 = (n17 = (n18 = (n19 = (n20 = (n21 = (n22 = (n23 = (n24 = (n25 = (n26 = (n27 = (n28 = (n29 = (n30 = (n31 = (n32 = (n33 = (n34 = (n35 = (n36 = (n37 = (n38 = (n39 = (n40 = (n41 = (n42 = (n43 = (n44 = (n45 = (n46 = (n47 = 12))))))))))))))))))))))))))))))))))))))))))))));
                    s = "<R4}\u0013\u001eT";
                    n48 = 20;
                    continue Label_0122_Outer;
                }
                case 20: {
                    array22[n22] = HashTable.e(intern);
                    n = (n2 = (n3 = (n4 = (n5 = (n6 = (n7 = (n8 = (n9 = (n10 = (n11 = (n12 = (n13 = (n14 = (n15 = (n16 = (n17 = (n18 = (n19 = (n20 = (n21 = (n22 = (n23 = (n24 = (n25 = (n26 = (n27 = (n28 = (n29 = (n30 = (n31 = (n32 = (n33 = (n34 = (n35 = (n36 = (n37 = (n38 = (n39 = (n40 = (n41 = (n42 = (n43 = (n44 = (n45 = (n46 = (n47 = 13))))))))))))))))))))))))))))))))))))))))))))));
                    s = "\r\u0017\u000066F";
                    n48 = 21;
                    continue Label_0122_Outer;
                }
                case 21: {
                    array23[n23] = org.powerbot.s.a(intern);
                    n = (n2 = (n3 = (n4 = (n5 = (n6 = (n7 = (n8 = (n9 = (n10 = (n11 = (n12 = (n13 = (n14 = (n15 = (n16 = (n17 = (n18 = (n19 = (n20 = (n21 = (n22 = (n23 = (n24 = (n25 = (n26 = (n27 = (n28 = (n29 = (n30 = (n31 = (n32 = (n33 = (n34 = (n35 = (n36 = (n37 = (n38 = (n39 = (n40 = (n41 = (n42 = (n43 = (n44 = (n45 = (n46 = (n47 = 14))))))))))))))))))))))))))))))))))))))))))))));
                    s = ";X!l\b\u0010T";
                    n48 = 22;
                    continue Label_0122_Outer;
                }
                case 22: {
                    array24[n24] = HashTable.e(intern);
                    n = (n2 = (n3 = (n4 = (n5 = (n6 = (n7 = (n8 = (n9 = (n10 = (n11 = (n12 = (n13 = (n14 = (n15 = (n16 = (n17 = (n18 = (n19 = (n20 = (n21 = (n22 = (n23 = (n24 = (n25 = (n26 = (n27 = (n28 = (n29 = (n30 = (n31 = (n32 = (n33 = (n34 = (n35 = (n36 = (n37 = (n38 = (n39 = (n40 = (n41 = (n42 = (n43 = (n44 = (n45 = (n46 = (n47 = 15))))))))))))))))))))))))))))))))))))))))))))));
                    s = "\u001f\u0017\u00062;Jv}";
                    n48 = 23;
                    continue Label_0122_Outer;
                }
                case 23: {
                    array25[n25] = org.powerbot.s.a(intern);
                    n = (n2 = (n3 = (n4 = (n5 = (n6 = (n7 = (n8 = (n9 = (n10 = (n11 = (n12 = (n13 = (n14 = (n15 = (n16 = (n17 = (n18 = (n19 = (n20 = (n21 = (n22 = (n23 = (n24 = (n25 = (n26 = (n27 = (n28 = (n29 = (n30 = (n31 = (n32 = (n33 = (n34 = (n35 = (n36 = (n37 = (n38 = (n39 = (n40 = (n41 = (n42 = (n43 = (n44 = (n45 = (n46 = (n47 = 16))))))))))))))))))))))))))))))))))))))))))))));
                    s = "0^%v\u001e\u0016I2}\u000f\u001c_";
                    n48 = 24;
                    continue Label_0122_Outer;
                }
                case 24: {
                    array26[n26] = HashTable.e(intern);
                    n = (n2 = (n3 = (n4 = (n5 = (n6 = (n7 = (n8 = (n9 = (n10 = (n11 = (n12 = (n13 = (n14 = (n15 = (n16 = (n17 = (n18 = (n19 = (n20 = (n21 = (n22 = (n23 = (n24 = (n25 = (n26 = (n27 = (n28 = (n29 = (n30 = (n31 = (n32 = (n33 = (n34 = (n35 = (n36 = (n37 = (n38 = (n39 = (n40 = (n41 = (n42 = (n43 = (n44 = (n45 = (n46 = (n47 = 17))))))))))))))))))))))))))))))))))))))))))))));
                    s = "\u007fc{QQ";
                    n48 = 25;
                    continue Label_0122_Outer;
                }
                case 25: {
                    array27[n27] = org.powerbot.s.a(intern);
                    n = (n2 = (n3 = (n4 = (n5 = (n6 = (n7 = (n8 = (n9 = (n10 = (n11 = (n12 = (n13 = (n14 = (n15 = (n16 = (n17 = (n18 = (n19 = (n20 = (n21 = (n22 = (n23 = (n24 = (n25 = (n26 = (n27 = (n28 = (n29 = (n30 = (n31 = (n32 = (n33 = (n34 = (n35 = (n36 = (n37 = (n38 = (n39 = (n40 = (n41 = (n42 = (n43 = (n44 = (n45 = (n46 = (n47 = 18))))))))))))))))))))))))))))))))))))))))))))));
                    s = "#C*|\u000f\r";
                    n48 = 26;
                    continue Label_0122_Outer;
                }
                case 26: {
                    array28[n28] = HashTable.e(intern);
                    n = (n2 = (n3 = (n4 = (n5 = (n6 = (n7 = (n8 = (n9 = (n10 = (n11 = (n12 = (n13 = (n14 = (n15 = (n16 = (n17 = (n18 = (n19 = (n20 = (n21 = (n22 = (n23 = (n24 = (n25 = (n26 = (n27 = (n28 = (n29 = (n30 = (n31 = (n32 = (n33 = (n34 = (n35 = (n36 = (n37 = (n38 = (n39 = (n40 = (n41 = (n42 = (n43 = (n44 = (n45 = (n46 = (n47 = 19))))))))))))))))))))))))))))))))))))))))))))));
                    s = "`cr_W";
                    n48 = 27;
                    continue Label_0122_Outer;
                }
                case 27: {
                    array29[n29] = org.powerbot.s.a(intern);
                    n = (n2 = (n3 = (n4 = (n5 = (n6 = (n7 = (n8 = (n9 = (n10 = (n11 = (n12 = (n13 = (n14 = (n15 = (n16 = (n17 = (n18 = (n19 = (n20 = (n21 = (n22 = (n23 = (n24 = (n25 = (n26 = (n27 = (n28 = (n29 = (n30 = (n31 = (n32 = (n33 = (n34 = (n35 = (n36 = (n37 = (n38 = (n39 = (n40 = (n41 = (n42 = (n43 = (n44 = (n45 = (n46 = (n47 = 20))))))))))))))))))))))))))))))))))))))))))))));
                    s = "<R(b\u000f\u001dV";
                    n48 = 28;
                    continue Label_0122_Outer;
                }
                case 28: {
                    array30[n30] = HashTable.e(intern);
                    n = (n2 = (n3 = (n4 = (n5 = (n6 = (n7 = (n8 = (n9 = (n10 = (n11 = (n12 = (n13 = (n14 = (n15 = (n16 = (n17 = (n18 = (n19 = (n20 = (n21 = (n22 = (n23 = (n24 = (n25 = (n26 = (n27 = (n28 = (n29 = (n30 = (n31 = (n32 = (n33 = (n34 = (n35 = (n36 = (n37 = (n38 = (n39 = (n40 = (n41 = (n42 = (n43 = (n44 = (n45 = (n46 = (n47 = 21))))))))))))))))))))))))))))))))))))))))))))));
                    s = "zmzRW9\u0017\u0000>;J";
                    n48 = 29;
                    continue Label_0122_Outer;
                }
                case 29: {
                    array31[n31] = org.powerbot.s.a(intern);
                    n = (n2 = (n3 = (n4 = (n5 = (n6 = (n7 = (n8 = (n9 = (n10 = (n11 = (n12 = (n13 = (n14 = (n15 = (n16 = (n17 = (n18 = (n19 = (n20 = (n21 = (n22 = (n23 = (n24 = (n25 = (n26 = (n27 = (n28 = (n29 = (n30 = (n31 = (n32 = (n33 = (n34 = (n35 = (n36 = (n37 = (n38 = (n39 = (n40 = (n41 = (n42 = (n43 = (n44 = (n45 = (n46 = (n47 = 22))))))))))))))))))))))))))))))))))))))))))))));
                    s = "9Q\"}\u0005\u001bX%b";
                    n48 = 30;
                    continue Label_0122_Outer;
                }
                case 30: {
                    array32[n32] = HashTable.e(intern);
                    n = (n2 = (n3 = (n4 = (n5 = (n6 = (n7 = (n8 = (n9 = (n10 = (n11 = (n12 = (n13 = (n14 = (n15 = (n16 = (n17 = (n18 = (n19 = (n20 = (n21 = (n22 = (n23 = (n24 = (n25 = (n26 = (n27 = (n28 = (n29 = (n30 = (n31 = (n32 = (n33 = (n34 = (n35 = (n36 = (n37 = (n38 = (n39 = (n40 = (n41 = (n42 = (n43 = (n44 = (n45 = (n46 = (n47 = 23))))))))))))))))))))))))))))))))))))))))))))));
                    s = "kkf^]\"\u0004";
                    n48 = 31;
                    continue Label_0122_Outer;
                }
                case 31: {
                    array33[n33] = org.powerbot.s.a(intern);
                    n = (n2 = (n3 = (n4 = (n5 = (n6 = (n7 = (n8 = (n9 = (n10 = (n11 = (n12 = (n13 = (n14 = (n15 = (n16 = (n17 = (n18 = (n19 = (n20 = (n21 = (n22 = (n23 = (n24 = (n25 = (n26 = (n27 = (n28 = (n29 = (n30 = (n31 = (n32 = (n33 = (n34 = (n35 = (n36 = (n37 = (n38 = (n39 = (n40 = (n41 = (n42 = (n43 = (n44 = (n45 = (n46 = (n47 = 24))))))))))))))))))))))))))))))))))))))))))))));
                    s = "5X9`\u0007\u001eV.g\u0001";
                    n48 = 32;
                    continue Label_0122_Outer;
                }
                case 32: {
                    array34[n34] = HashTable.e(intern);
                    n = (n2 = (n3 = (n4 = (n5 = (n6 = (n7 = (n8 = (n9 = (n10 = (n11 = (n12 = (n13 = (n14 = (n15 = (n16 = (n17 = (n18 = (n19 = (n20 = (n21 = (n22 = (n23 = (n24 = (n25 = (n26 = (n27 = (n28 = (n29 = (n30 = (n31 = (n32 = (n33 = (n34 = (n35 = (n36 = (n37 = (n38 = (n39 = (n40 = (n41 = (n42 = (n43 = (n44 = (n45 = (n46 = (n47 = 25))))))))))))))))))))))))))))))))))))))))))))));
                    s = "\u000f\u0011\u00151!Dlr";
                    n48 = 33;
                    continue Label_0122_Outer;
                }
                case 33: {
                    array35[n35] = org.powerbot.s.a(intern);
                    n = (n2 = (n3 = (n4 = (n5 = (n6 = (n7 = (n8 = (n9 = (n10 = (n11 = (n12 = (n13 = (n14 = (n15 = (n16 = (n17 = (n18 = (n19 = (n20 = (n21 = (n22 = (n23 = (n24 = (n25 = (n26 = (n27 = (n28 = (n29 = (n30 = (n31 = (n32 = (n33 = (n34 = (n35 = (n36 = (n37 = (n38 = (n39 = (n40 = (n41 = (n42 = (n43 = (n44 = (n45 = (n46 = (n47 = 26))))))))))))))))))))))))))))))))))))))))))))));
                    s = " \\\"q\u0002\u0016S ";
                    n48 = 34;
                    continue Label_0122_Outer;
                }
                case 34: {
                    array36[n36] = HashTable.e(intern);
                    n = (n2 = (n3 = (n4 = (n5 = (n6 = (n7 = (n8 = (n9 = (n10 = (n11 = (n12 = (n13 = (n14 = (n15 = (n16 = (n17 = (n18 = (n19 = (n20 = (n21 = (n22 = (n23 = (n24 = (n25 = (n26 = (n27 = (n28 = (n29 = (n30 = (n31 = (n32 = (n33 = (n34 = (n35 = (n36 = (n37 = (n38 = (n39 = (n40 = (n41 = (n42 = (n43 = (n44 = (n45 = (n46 = (n47 = 27))))))))))))))))))))))))))))))))))))))))))))));
                    s = "\u0001\n\u001a>;J";
                    n48 = 35;
                    continue Label_0122_Outer;
                }
                case 35: {
                    array37[n37] = org.powerbot.s.a(intern);
                    n = (n2 = (n3 = (n4 = (n5 = (n6 = (n7 = (n8 = (n9 = (n10 = (n11 = (n12 = (n13 = (n14 = (n15 = (n16 = (n17 = (n18 = (n19 = (n20 = (n21 = (n22 = (n23 = (n24 = (n25 = (n26 = (n27 = (n28 = (n29 = (n30 = (n31 = (n32 = (n33 = (n34 = (n35 = (n36 = (n37 = (n38 = (n39 = (n40 = (n41 = (n42 = (n43 = (n44 = (n45 = (n46 = (n47 = 28))))))))))))))))))))))))))))))))))))))))))))));
                    s = ";T9g\u0006\u0010O\"";
                    n48 = 36;
                    continue Label_0122_Outer;
                }
                case 36: {
                    array38[n38] = HashTable.e(intern);
                    n = (n2 = (n3 = (n4 = (n5 = (n6 = (n7 = (n8 = (n9 = (n10 = (n11 = (n12 = (n13 = (n14 = (n15 = (n16 = (n17 = (n18 = (n19 = (n20 = (n21 = (n22 = (n23 = (n24 = (n25 = (n26 = (n27 = (n28 = (n29 = (n30 = (n31 = (n32 = (n33 = (n34 = (n35 = (n36 = (n37 = (n38 = (n39 = (n40 = (n41 = (n42 = (n43 = (n44 = (n45 = (n46 = (n47 = 29))))))))))))))))))))))))))))))))))))))))))))));
                    s = "le|Z]8\u001a";
                    n48 = 37;
                    continue Label_0122_Outer;
                }
                case 37: {
                    array39[n39] = org.powerbot.s.a(intern);
                    n = (n2 = (n3 = (n4 = (n5 = (n6 = (n7 = (n8 = (n9 = (n10 = (n11 = (n12 = (n13 = (n14 = (n15 = (n16 = (n17 = (n18 = (n19 = (n20 = (n21 = (n22 = (n23 = (n24 = (n25 = (n26 = (n27 = (n28 = (n29 = (n30 = (n31 = (n32 = (n33 = (n34 = (n35 = (n36 = (n37 = (n38 = (n39 = (n40 = (n41 = (n42 = (n43 = (n44 = (n45 = (n46 = (n47 = 30))))))))))))))))))))))))))))))))))))))))))))));
                    s = "'Y\"`\u001c\u0016S ";
                    n48 = 38;
                    continue Label_0122_Outer;
                }
                case 38: {
                    array40[n40] = HashTable.e(intern);
                    n = (n2 = (n3 = (n4 = (n5 = (n6 = (n7 = (n8 = (n9 = (n10 = (n11 = (n12 = (n13 = (n14 = (n15 = (n16 = (n17 = (n18 = (n19 = (n20 = (n21 = (n22 = (n23 = (n24 = (n25 = (n26 = (n27 = (n28 = (n29 = (n30 = (n31 = (n32 = (n33 = (n34 = (n35 = (n36 = (n37 = (n38 = (n39 = (n40 = (n41 = (n42 = (n43 = (n44 = (n45 = (n46 = (n47 = 31))))))))))))))))))))))))))))))))))))))))))))));
                    s = "\u001f\u000f\u0015.0_";
                    n48 = 39;
                    continue Label_0122_Outer;
                }
                case 39: {
                    array41[n41] = org.powerbot.s.a(intern);
                    n = (n2 = (n3 = (n4 = (n5 = (n6 = (n7 = (n8 = (n9 = (n10 = (n11 = (n12 = (n13 = (n14 = (n15 = (n16 = (n17 = (n18 = (n19 = (n20 = (n21 = (n22 = (n23 = (n24 = (n25 = (n26 = (n27 = (n28 = (n29 = (n30 = (n31 = (n32 = (n33 = (n34 = (n35 = (n36 = (n37 = (n38 = (n39 = (n40 = (n41 = (n42 = (n43 = (n44 = (n45 = (n46 = (n47 = 32))))))))))))))))))))))))))))))))))))))))))))));
                    s = "9\\5d\u000f\u001dV";
                    n48 = 40;
                    continue Label_0122_Outer;
                }
                case 40: {
                    array42[n42] = HashTable.e(intern);
                    n = (n2 = (n3 = (n4 = (n5 = (n6 = (n7 = (n8 = (n9 = (n10 = (n11 = (n12 = (n13 = (n14 = (n15 = (n16 = (n17 = (n18 = (n19 = (n20 = (n21 = (n22 = (n23 = (n24 = (n25 = (n26 = (n27 = (n28 = (n29 = (n30 = (n31 = (n32 = (n33 = (n34 = (n35 = (n36 = (n37 = (n38 = (n39 = (n40 = (n41 = (n42 = (n43 = (n44 = (n45 = (n46 = (n47 = 33))))))))))))))))))))))))))))))))))))))))))))));
                    s = "\u001e\u0016\u001a26_csB]\"\u0004";
                    n48 = 41;
                    continue Label_0122_Outer;
                }
                case 41: {
                    array43[n43] = org.powerbot.s.a(intern);
                    n = (n2 = (n3 = (n4 = (n5 = (n6 = (n7 = (n8 = (n9 = (n10 = (n11 = (n12 = (n13 = (n14 = (n15 = (n16 = (n17 = (n18 = (n19 = (n20 = (n21 = (n22 = (n23 = (n24 = (n25 = (n26 = (n27 = (n28 = (n29 = (n30 = (n31 = (n32 = (n33 = (n34 = (n35 = (n36 = (n37 = (n38 = (n39 = (n40 = (n41 = (n42 = (n43 = (n44 = (n45 = (n46 = (n47 = 34))))))))))))))))))))))))))))))))))))))))))))));
                    s = ";D%q\u000f\r";
                    n48 = 42;
                    continue Label_0122_Outer;
                }
                case 42: {
                    array44[n44] = HashTable.e(intern);
                    n = (n2 = (n3 = (n4 = (n5 = (n6 = (n7 = (n8 = (n9 = (n10 = (n11 = (n12 = (n13 = (n14 = (n15 = (n16 = (n17 = (n18 = (n19 = (n20 = (n21 = (n22 = (n23 = (n24 = (n25 = (n26 = (n27 = (n28 = (n29 = (n30 = (n31 = (n32 = (n33 = (n34 = (n35 = (n36 = (n37 = (n38 = (n39 = (n40 = (n41 = (n42 = (n43 = (n44 = (n45 = (n46 = (n47 = 35))))))))))))))))))))))))))))))))))))))))))))));
                    s = "\u000f\f\u001a$!_wvB]#\r";
                    n48 = 43;
                    continue Label_0122_Outer;
                }
                case 43: {
                    array45[n45] = org.powerbot.s.a(intern);
                    n = (n2 = (n3 = (n4 = (n5 = (n6 = (n7 = (n8 = (n9 = (n10 = (n11 = (n12 = (n13 = (n14 = (n15 = (n16 = (n17 = (n18 = (n19 = (n20 = (n21 = (n22 = (n23 = (n24 = (n25 = (n26 = (n27 = (n28 = (n29 = (n30 = (n31 = (n32 = (n33 = (n34 = (n35 = (n36 = (n37 = (n38 = (n39 = (n40 = (n41 = (n42 = (n43 = (n44 = (n45 = (n46 = (n47 = 36))))))))))))))))))))))))))))))))))))))))))))));
                    s = ",H*d\t\u001dX%b";
                    n48 = 44;
                    continue Label_0122_Outer;
                }
                case 44: {
                    array46[n46] = HashTable.e(intern);
                    n = (n2 = (n3 = (n4 = (n5 = (n6 = (n7 = (n8 = (n9 = (n10 = (n11 = (n12 = (n13 = (n14 = (n15 = (n16 = (n17 = (n18 = (n19 = (n20 = (n21 = (n22 = (n23 = (n24 = (n25 = (n26 = (n27 = (n28 = (n29 = (n30 = (n31 = (n32 = (n33 = (n34 = (n35 = (n36 = (n37 = (n38 = (n39 = (n40 = (n41 = (n42 = (n43 = (n44 = (n45 = (n46 = (n47 = 37))))))))))))))))))))))))))))))))))))))))))))));
                    s = "iw{QQ#\r\u00112'Dlr";
                    n48 = 45;
                    continue Label_0122_Outer;
                }
                case 45: {
                    break Label_0122_Outer;
                }
            }
        }
        array47[n47] = org.powerbot.s.a(intern);
        d = d2;
    }
    
    private class a_ extends AbstractTableModel
    {
        private static final long serialVersionUID = 1L;
        private static final String[] z;
        
        @Override
        public int getRowCount() {
            return jb.a().size();
        }
        
        @Override
        public int getColumnCount() {
            return 5;
        }
        
        @Override
        public Object getValueAt(final int n, final int n2) {
            final jb.a_ a = jb.a().a(this.a(n));
            Label_0077: {
                jb.a_ a_ = null;
                Label_0059: {
                    try {
                        switch (n2) {
                            case 0: {
                                return a.toString();
                            }
                            case 1: {
                                break;
                            }
                            case 2: {
                                break Label_0059;
                            }
                            case 3: {
                                return a.d;
                            }
                            case 4: {
                                return a.e;
                            }
                            default: {
                                return null;
                            }
                        }
                    }
                    catch (NumberFormatException ex) {
                        throw ex;
                    }
                    return a.a();
                    try {
                        final jb.a_ a_2;
                        a_ = (a_2 = a);
                        if (qb.f) {
                            return a_2.b();
                        }
                        final int n3 = a_.c;
                        final int n4 = -1;
                        if (n3 == n4) {
                            break Label_0077;
                        }
                        break Label_0077;
                    }
                    catch (NumberFormatException ex2) {
                        throw ex2;
                    }
                }
                try {
                    final int n3 = a_.c;
                    final int n4 = -1;
                    if (n3 == n4) {
                        return "";
                    }
                }
                catch (NumberFormatException ex3) {
                    throw ex3;
                }
            }
            jb.a_ a_2 = a;
            return a_2.b();
        }
        
        @Override
        public String getColumnName(final int n) {
            try {
                switch (n) {
                    case 0: {
                        return org.s.a(a_.z[2]);
                    }
                    case 1: {
                        break;
                    }
                    case 2: {
                        return org.s.a(a_.z[4]);
                    }
                    case 3: {
                        return kb.a(a_.z[1]);
                    }
                    case 4: {
                        return org.s.a(a_.z[3]);
                    }
                    default: {
                        return null;
                    }
                }
            }
            catch (NumberFormatException ex) {
                throw ex;
            }
            return kb.a(a_.z[5]);
        }
        
        @Override
        public Class<?> getColumnClass(final int n) {
            try {
                if (n == 3) {
                    final Serializable s = Boolean.class;
                    return (Class<?>)s;
                }
            }
            catch (NumberFormatException ex) {
                throw ex;
            }
            final Serializable s = Object.class;
            return (Class<?>)s;
        }
        
        @Override
        public boolean isCellEditable(final int n, final int n2) {
            try {
                final int n3 = n2;
                if (qb.f) {
                    return n3 != 0;
                }
                if (n2 <= 0) {
                    return false;
                }
            }
            catch (NumberFormatException ex) {
                throw ex;
            }
            int n3 = 1;
            return n3 != 0;
            n3 = 0;
            return n3 != 0;
        }
        
        @Override
        public void setValueAt(final Object p0, final int p1, final int p2) {
            // 
            // This method could not be decompiled.
            // 
            // Original Bytecode:
            // 
            //     3: istore          7
            //     5: invokestatic    org/powerbot/jb.a:()Lorg/powerbot/jb;
            //     8: aload_0        
            //     9: iload_2        
            //    10: invokevirtual   org/powerbot/mb$a_.a:(I)Ljava/lang/String;
            //    13: invokevirtual   org/powerbot/jb.a:(Ljava/lang/String;)Lorg/powerbot/jb$a_;
            //    16: astore          4
            //    18: aload           4
            //    20: iload           7
            //    22: ifne            34
            //    25: ifnonnull       33
            //    28: goto            32
            //    31: athrow         
            //    32: return         
            //    33: aload_1        
            //    34: invokestatic    java/lang/String.valueOf:(Ljava/lang/Object;)Ljava/lang/String;
            //    37: astore          5
            //    39: iload           7
            //    41: ifne            216
            //    44: iload_3        
            //    45: tableswitch {
            //                2: 77
            //                3: 93
            //                4: 172
            //                5: 199
            //          default: 210
            //        }
            //    76: athrow         
            //    77: aload           4
            //    79: aload           5
            //    81: invokevirtual   org/powerbot/jb$a_.a:(Ljava/lang/String;)V
            //    84: iload           7
            //    86: ifeq            210
            //    89: goto            93
            //    92: athrow         
            //    93: aload           4
            //    95: aload           5
            //    97: invokestatic    java/lang/Integer.parseInt:(Ljava/lang/String;)I
            //   100: putfield        org/powerbot/jb$a_.c:I
            //   103: goto            115
            //   106: athrow         
            //   107: astore          6
            //   109: aload           4
            //   111: iconst_m1      
            //   112: putfield        org/powerbot/jb$a_.c:I
            //   115: aload           4
            //   117: iload           7
            //   119: ifne            163
            //   122: getfield        org/powerbot/jb$a_.c:I
            //   125: iconst_1       
            //   126: if_icmplt       157
            //   129: goto            133
            //   132: athrow         
            //   133: aload           4
            //   135: iload           7
            //   137: ifne            163
            //   140: goto            144
            //   143: athrow         
            //   144: getfield        org/powerbot/jb$a_.c:I
            //   147: sipush          9999
            //   150: if_icmple       210
            //   153: goto            157
            //   156: athrow         
            //   157: aload           4
            //   159: goto            163
            //   162: athrow         
            //   163: iconst_m1      
            //   164: putfield        org/powerbot/jb$a_.c:I
            //   167: iload           7
            //   169: ifeq            210
            //   172: aload           4
            //   174: aload           5
            //   176: getstatic       org/powerbot/mb$a_.z:[Ljava/lang/String;
            //   179: iconst_0       
            //   180: aaload         
            //   181: invokestatic    org/powerbot/kb.a:(Ljava/lang/String;)Ljava/lang/String;
            //   184: invokevirtual   java/lang/String.equals:(Ljava/lang/Object;)Z
            //   187: putfield        org/powerbot/jb$a_.d:Z
            //   190: iload           7
            //   192: ifeq            210
            //   195: goto            199
            //   198: athrow         
            //   199: aload           4
            //   201: aload           5
            //   203: putfield        org/powerbot/jb$a_.e:Ljava/lang/String;
            //   206: goto            210
            //   209: athrow         
            //   210: aload_0        
            //   211: iload_2        
            //   212: iload_3        
            //   213: invokevirtual   org/powerbot/mb$a_.fireTableCellUpdated:(II)V
            //   216: return         
            //    StackMapTable: 00 19 FF 00 1F 00 08 07 00 1C 07 00 11 01 01 07 00 1B 00 00 01 00 01 07 00 15 00 00 40 07 00 11 FF 00 29 00 08 07 00 1C 07 00 11 01 01 07 00 1B 07 00 4D 00 01 00 01 07 00 15 00 4E 07 00 15 00 4C 07 00 9B 40 07 00 15 07 50 07 00 15 00 49 07 00 15 40 07 00 1B 4B 07 00 15 00 44 07 00 15 40 07 00 1B 08 59 07 00 15 00 49 07 00 15 00 05
            //    Exceptions:
            //  Try           Handler
            //  Start  End    Start  End    Type                             
            //  -----  -----  -----  -----  ---------------------------------
            //  44     89     92     93     Ljava/lang/NumberFormatException;
            //  39     76     76     77     Ljava/lang/NumberFormatException;
            //  18     28     31     32     Ljava/lang/NumberFormatException;
            //  93     103    107    115    Ljava/lang/NumberFormatException;
            //  172    206    209    210    Ljava/lang/NumberFormatException;
            //  163    195    198    199    Ljava/lang/NumberFormatException;
            //  144    159    162    163    Ljava/lang/NumberFormatException;
            //  133    153    156    157    Ljava/lang/NumberFormatException;
            //  122    140    143    144    Ljava/lang/NumberFormatException;
            //  115    129    132    133    Ljava/lang/NumberFormatException;
            //  77     106    106    107    Ljava/lang/SecurityException;
            // 
            // The error that occurred was:
            // 
            // java.lang.IllegalStateException: Expression is linked from several locations: Label_0077:
            //     at com.strobel.decompiler.ast.Error.expressionLinkedFromMultipleLocations(Error.java:27)
            //     at com.strobel.decompiler.ast.AstOptimizer.mergeDisparateObjectInitializations(AstOptimizer.java:2596)
            //     at com.strobel.decompiler.ast.AstOptimizer.optimize(AstOptimizer.java:235)
            //     at com.strobel.decompiler.ast.AstOptimizer.optimize(AstOptimizer.java:42)
            //     at com.strobel.decompiler.languages.java.ast.AstMethodBodyBuilder.createMethodBody(AstMethodBodyBuilder.java:214)
            //     at com.strobel.decompiler.languages.java.ast.AstMethodBodyBuilder.createMethodBody(AstMethodBodyBuilder.java:99)
            //     at com.strobel.decompiler.languages.java.ast.AstBuilder.createMethodBody(AstBuilder.java:782)
            //     at com.strobel.decompiler.languages.java.ast.AstBuilder.createMethod(AstBuilder.java:675)
            //     at com.strobel.decompiler.languages.java.ast.AstBuilder.addTypeMembers(AstBuilder.java:552)
            //     at com.strobel.decompiler.languages.java.ast.AstBuilder.createTypeCore(AstBuilder.java:519)
            //     at com.strobel.decompiler.languages.java.ast.AstBuilder.createTypeNoCache(AstBuilder.java:161)
            //     at com.strobel.decompiler.languages.java.ast.AstBuilder.addTypeMembers(AstBuilder.java:576)
            //     at com.strobel.decompiler.languages.java.ast.AstBuilder.createTypeCore(AstBuilder.java:519)
            //     at com.strobel.decompiler.languages.java.ast.AstBuilder.createTypeNoCache(AstBuilder.java:161)
            //     at com.strobel.decompiler.languages.java.ast.AstBuilder.createType(AstBuilder.java:150)
            //     at com.strobel.decompiler.languages.java.ast.AstBuilder.addType(AstBuilder.java:125)
            //     at com.strobel.decompiler.languages.java.JavaLanguage.buildAst(JavaLanguage.java:71)
            //     at com.strobel.decompiler.languages.java.JavaLanguage.decompileType(JavaLanguage.java:59)
            //     at com.strobel.decompiler.DecompilerDriver.decompileType(DecompilerDriver.java:330)
            //     at com.strobel.decompiler.DecompilerDriver.decompileJar(DecompilerDriver.java:251)
            //     at com.strobel.decompiler.DecompilerDriver.main(DecompilerDriver.java:126)
            // 
            throw new IllegalStateException("An error occurred while decompiling this method.");
        }
        
        public String a(final int p0) {
            // 
            // This method could not be decompiled.
            // 
            // Original Bytecode:
            // 
            //     3: istore          4
            //     5: invokestatic    org/powerbot/jb.a:()Lorg/powerbot/jb;
            //     8: invokevirtual   org/powerbot/jb.iterator:()Ljava/util/Iterator;
            //    11: astore_2       
            //    12: iconst_0       
            //    13: istore_3       
            //    14: aload_2        
            //    15: invokeinterface java/util/Iterator.hasNext:()Z
            //    20: ifeq            65
            //    23: iload_3        
            //    24: iload           4
            //    26: ifne            80
            //    29: iload           4
            //    31: ifne            80
            //    34: goto            38
            //    37: athrow         
            //    38: iload_1        
            //    39: if_icmpge       65
            //    42: goto            46
            //    45: athrow         
            //    46: aload_2        
            //    47: invokeinterface java/util/Iterator.next:()Ljava/lang/Object;
            //    52: pop            
            //    53: iinc            3, 1
            //    56: iload           4
            //    58: ifeq            14
            //    61: goto            65
            //    64: athrow         
            //    65: aload_2        
            //    66: iload           4
            //    68: ifne            93
            //    71: invokeinterface java/util/Iterator.hasNext:()Z
            //    76: goto            80
            //    79: athrow         
            //    80: ifeq            100
            //    83: aload_2        
            //    84: invokeinterface java/util/Iterator.next:()Ljava/lang/Object;
            //    89: goto            93
            //    92: athrow         
            //    93: checkcast       Lorg/powerbot/jb$a_;
            //    96: invokevirtual   org/powerbot/jb$a_.toString:()Ljava/lang/String;
            //    99: areturn        
            //   100: aconst_null    
            //   101: areturn        
            //    StackMapTable: 00 0C FE 00 0E 07 00 56 01 01 56 07 00 15 40 01 46 07 00 15 00 51 07 00 15 00 4D 07 00 15 40 01 4B 07 00 15 40 07 00 11 06
            //    Exceptions:
            //  Try           Handler
            //  Start  End    Start  End    Type                             
            //  -----  -----  -----  -----  ---------------------------------
            //  80     89     92     93     Ljava/lang/NumberFormatException;
            //  65     76     79     80     Ljava/lang/NumberFormatException;
            //  38     61     64     65     Ljava/lang/NumberFormatException;
            //  29     42     45     46     Ljava/lang/NumberFormatException;
            //  23     34     37     38     Ljava/lang/NumberFormatException;
            // 
            // The error that occurred was:
            // 
            // java.lang.IllegalStateException: Expression is linked from several locations: Label_0038:
            //     at com.strobel.decompiler.ast.Error.expressionLinkedFromMultipleLocations(Error.java:27)
            //     at com.strobel.decompiler.ast.AstOptimizer.mergeDisparateObjectInitializations(AstOptimizer.java:2596)
            //     at com.strobel.decompiler.ast.AstOptimizer.optimize(AstOptimizer.java:235)
            //     at com.strobel.decompiler.ast.AstOptimizer.optimize(AstOptimizer.java:42)
            //     at com.strobel.decompiler.languages.java.ast.AstMethodBodyBuilder.createMethodBody(AstMethodBodyBuilder.java:214)
            //     at com.strobel.decompiler.languages.java.ast.AstMethodBodyBuilder.createMethodBody(AstMethodBodyBuilder.java:99)
            //     at com.strobel.decompiler.languages.java.ast.AstBuilder.createMethodBody(AstBuilder.java:782)
            //     at com.strobel.decompiler.languages.java.ast.AstBuilder.createMethod(AstBuilder.java:675)
            //     at com.strobel.decompiler.languages.java.ast.AstBuilder.addTypeMembers(AstBuilder.java:552)
            //     at com.strobel.decompiler.languages.java.ast.AstBuilder.createTypeCore(AstBuilder.java:519)
            //     at com.strobel.decompiler.languages.java.ast.AstBuilder.createTypeNoCache(AstBuilder.java:161)
            //     at com.strobel.decompiler.languages.java.ast.AstBuilder.addTypeMembers(AstBuilder.java:576)
            //     at com.strobel.decompiler.languages.java.ast.AstBuilder.createTypeCore(AstBuilder.java:519)
            //     at com.strobel.decompiler.languages.java.ast.AstBuilder.createTypeNoCache(AstBuilder.java:161)
            //     at com.strobel.decompiler.languages.java.ast.AstBuilder.createType(AstBuilder.java:150)
            //     at com.strobel.decompiler.languages.java.ast.AstBuilder.addType(AstBuilder.java:125)
            //     at com.strobel.decompiler.languages.java.JavaLanguage.buildAst(JavaLanguage.java:71)
            //     at com.strobel.decompiler.languages.java.JavaLanguage.decompileType(JavaLanguage.java:59)
            //     at com.strobel.decompiler.DecompilerDriver.decompileType(DecompilerDriver.java:330)
            //     at com.strobel.decompiler.DecompilerDriver.decompileJar(DecompilerDriver.java:251)
            //     at com.strobel.decompiler.DecompilerDriver.main(DecompilerDriver.java:126)
            // 
            throw new IllegalStateException("An error occurred while decompiling this method.");
        }
        
        static {
            final String[] z2 = new String[6];
            int n6;
            int n5;
            int n4;
            int n3;
            int n2;
            int n = n2 = (n3 = (n4 = (n5 = (n6 = 0))));
            String s = "\u0005q\\\u0011";
            int n7 = -1;
            String intern = null;
        Label_0081_Outer:
            while (true) {
                final char[] charArray = s.toCharArray();
                int length;
                int n9;
                final int n8 = n9 = (length = charArray.length);
                int n10 = 0;
                while (true) {
                    Label_0158: {
                        if (n8 > 1) {
                            break Label_0158;
                        }
                        length = (n9 = n10);
                        do {
                            final char c = charArray[n9];
                            char c2 = '\0';
                            switch (n10 % 5) {
                                case 0: {
                                    c2 = 'f';
                                    break;
                                }
                                case 1: {
                                    c2 = 'U';
                                    break;
                                }
                                case 2: {
                                    c2 = '>';
                                    break;
                                }
                                case 3: {
                                    c2 = '\"';
                                    break;
                                }
                                default: {
                                    c2 = '8';
                                    break;
                                }
                            }
                            charArray[length] = (char)(c ^ c2);
                            ++n10;
                        } while (n8 == 0);
                    }
                    if (n8 > n10) {
                        continue;
                    }
                    break;
                }
                intern = new String(charArray).intern();
                switch (n7) {
                    default: {
                        z2[n2] = intern;
                        n = (n2 = (n3 = (n4 = (n5 = (n6 = 1)))));
                        s = "<fD\u0016JB";
                        n7 = 0;
                        continue Label_0081_Outer;
                    }
                    case 0: {
                        z2[n] = intern;
                        n = (n2 = (n3 = (n4 = (n5 = (n6 = 2)))));
                        s = "Q)9_4\bZT";
                        n7 = 1;
                        continue Label_0081_Outer;
                    }
                    case 1: {
                        z2[n3] = intern;
                        n = (n2 = (n3 = (n4 = (n5 = (n6 = 3)))));
                        s = "V?+L(\r";
                        n7 = 2;
                        continue Label_0081_Outer;
                    }
                    case 2: {
                        z2[n4] = intern;
                        n = (n2 = (n3 = (n4 = (n5 = (n6 = 4)))));
                        s = "9~\u007f";
                        n7 = 3;
                        continue Label_0081_Outer;
                    }
                    case 3: {
                        z2[n5] = intern;
                        n = (n2 = (n3 = (n4 = (n5 = (n6 = 5)))));
                        s = "!bZ\u0007X_0\f";
                        n7 = 4;
                        continue Label_0081_Outer;
                    }
                    case 4: {
                        break Label_0081_Outer;
                    }
                }
            }
            z2[n6] = intern;
            z = z2;
        }
    }
    
    private class e_ implements ListSelectionListener
    {
        @Override
        public void valueChanged(final ListSelectionEvent p0) {
            // 
            // This method could not be decompiled.
            // 
            // Original Bytecode:
            // 
            //     3: istore_3       
            //     4: aload_0        
            //     5: getfield        org/powerbot/mb$e_.this$0:Lorg/powerbot/mb;
            //     8: invokestatic    org/powerbot/mb.access$400:(Lorg/powerbot/mb;)Ljavax/swing/JTable;
            //    11: invokevirtual   javax/swing/JTable.getSelectedRow:()I
            //    14: istore_2       
            //    15: aload_1        
            //    16: invokevirtual   javax/swing/event/ListSelectionEvent.getValueIsAdjusting:()Z
            //    19: ifne            80
            //    22: aload_0        
            //    23: getfield        org/powerbot/mb$e_.this$0:Lorg/powerbot/mb;
            //    26: invokestatic    org/powerbot/mb.access$500:(Lorg/powerbot/mb;)Ljavax/swing/JButton;
            //    29: iload_2        
            //    30: iconst_m1      
            //    31: iload_3        
            //    32: ifne            69
            //    35: goto            39
            //    38: athrow         
            //    39: if_icmple       76
            //    42: goto            46
            //    45: athrow         
            //    46: iload_2        
            //    47: iload_3        
            //    48: ifne            73
            //    51: goto            55
            //    54: athrow         
            //    55: aload_0        
            //    56: getfield        org/powerbot/mb$e_.this$0:Lorg/powerbot/mb;
            //    59: invokestatic    org/powerbot/mb.access$400:(Lorg/powerbot/mb;)Ljavax/swing/JTable;
            //    62: invokevirtual   javax/swing/JTable.getRowCount:()I
            //    65: goto            69
            //    68: athrow         
            //    69: if_icmpge       76
            //    72: iconst_1       
            //    73: goto            77
            //    76: iconst_0       
            //    77: invokevirtual   javax/swing/JButton.setEnabled:(Z)V
            //    80: return         
            //    StackMapTable: 00 0C FF 00 26 00 04 07 00 0A 07 00 1F 01 01 00 01 07 00 41 FF 00 00 00 04 07 00 0A 07 00 1F 01 01 00 03 07 00 23 01 01 45 07 00 41 40 07 00 23 47 07 00 41 FF 00 00 00 04 07 00 0A 07 00 1F 01 01 00 02 07 00 23 01 4C 07 00 41 FF 00 00 00 04 07 00 0A 07 00 1F 01 01 00 03 07 00 23 01 01 FF 00 03 00 04 07 00 0A 07 00 1F 01 01 00 02 07 00 23 01 42 07 00 23 FF 00 00 00 04 07 00 0A 07 00 1F 01 01 00 02 07 00 23 01 02
            //    Exceptions:
            //  Try           Handler
            //  Start  End    Start  End    Type                        
            //  -----  -----  -----  -----  ----------------------------
            //  46     65     68     69     Ljava/lang/RuntimeException;
            //  39     51     54     55     Ljava/lang/RuntimeException;
            //  22     42     45     46     Ljava/lang/RuntimeException;
            //  15     35     38     39     Ljava/lang/RuntimeException;
            // 
            // The error that occurred was:
            // 
            // java.lang.IllegalStateException: Expression is linked from several locations: Label_0039:
            //     at com.strobel.decompiler.ast.Error.expressionLinkedFromMultipleLocations(Error.java:27)
            //     at com.strobel.decompiler.ast.AstOptimizer.mergeDisparateObjectInitializations(AstOptimizer.java:2596)
            //     at com.strobel.decompiler.ast.AstOptimizer.optimize(AstOptimizer.java:235)
            //     at com.strobel.decompiler.ast.AstOptimizer.optimize(AstOptimizer.java:42)
            //     at com.strobel.decompiler.languages.java.ast.AstMethodBodyBuilder.createMethodBody(AstMethodBodyBuilder.java:214)
            //     at com.strobel.decompiler.languages.java.ast.AstMethodBodyBuilder.createMethodBody(AstMethodBodyBuilder.java:99)
            //     at com.strobel.decompiler.languages.java.ast.AstBuilder.createMethodBody(AstBuilder.java:782)
            //     at com.strobel.decompiler.languages.java.ast.AstBuilder.createMethod(AstBuilder.java:675)
            //     at com.strobel.decompiler.languages.java.ast.AstBuilder.addTypeMembers(AstBuilder.java:552)
            //     at com.strobel.decompiler.languages.java.ast.AstBuilder.createTypeCore(AstBuilder.java:519)
            //     at com.strobel.decompiler.languages.java.ast.AstBuilder.createTypeNoCache(AstBuilder.java:161)
            //     at com.strobel.decompiler.languages.java.ast.AstBuilder.addTypeMembers(AstBuilder.java:576)
            //     at com.strobel.decompiler.languages.java.ast.AstBuilder.createTypeCore(AstBuilder.java:519)
            //     at com.strobel.decompiler.languages.java.ast.AstBuilder.createTypeNoCache(AstBuilder.java:161)
            //     at com.strobel.decompiler.languages.java.ast.AstBuilder.createType(AstBuilder.java:150)
            //     at com.strobel.decompiler.languages.java.ast.AstBuilder.addType(AstBuilder.java:125)
            //     at com.strobel.decompiler.languages.java.JavaLanguage.buildAst(JavaLanguage.java:71)
            //     at com.strobel.decompiler.languages.java.JavaLanguage.decompileType(JavaLanguage.java:59)
            //     at com.strobel.decompiler.DecompilerDriver.decompileType(DecompilerDriver.java:330)
            //     at com.strobel.decompiler.DecompilerDriver.decompileJar(DecompilerDriver.java:251)
            //     at com.strobel.decompiler.DecompilerDriver.main(DecompilerDriver.java:126)
            // 
            throw new IllegalStateException("An error occurred while decompiling this method.");
        }
    }
    
    private static class b_ extends DefaultTableCellRenderer
    {
        private static final long serialVersionUID = 1L;
        
        @Override
        protected void setValue(final Object p0) {
            // 
            // This method could not be decompiled.
            // 
            // Original Bytecode:
            // 
            //     3: istore          5
            //     5: aload_1        
            //     6: iload           5
            //     8: ifne            38
            //    11: ifnonnull       33
            //    14: goto            18
            //    17: athrow         
            //    18: aload_0        
            //    19: ldc             ""
            //    21: invokevirtual   org/powerbot/mb$b_.setText:(Ljava/lang/String;)V
            //    24: iload           5
            //    26: ifeq            97
            //    29: goto            33
            //    32: athrow         
            //    33: aload_1        
            //    34: goto            38
            //    37: athrow         
            //    38: invokevirtual   java/lang/Object.toString:()Ljava/lang/String;
            //    41: astore_2       
            //    42: new             Ljava/lang/StringBuilder;
            //    45: dup            
            //    46: invokespecial   java/lang/StringBuilder.<init>:()V
            //    49: astore_3       
            //    50: iconst_0       
            //    51: istore          4
            //    53: iload           4
            //    55: aload_2        
            //    56: invokevirtual   java/lang/String.length:()I
            //    59: if_icmpge       89
            //    62: aload_3        
            //    63: ldc             "\u25b6"
            //    65: invokestatic    org/powerbot/core/script/wrappers/Component.e:(Ljava/lang/String;)Ljava/lang/String;
            //    68: invokevirtual   java/lang/StringBuilder.append:(Ljava/lang/String;)Ljava/lang/StringBuilder;
            //    71: pop            
            //    72: iinc            4, 1
            //    75: iload           5
            //    77: ifne            97
            //    80: iload           5
            //    82: ifeq            53
            //    85: goto            89
            //    88: athrow         
            //    89: aload_0        
            //    90: aload_3        
            //    91: invokevirtual   java/lang/StringBuilder.toString:()Ljava/lang/String;
            //    94: invokevirtual   org/powerbot/mb$b_.setText:(Ljava/lang/String;)V
            //    97: return         
            //    StackMapTable: 00 0A FF 00 11 00 06 07 00 0B 07 00 1D 00 00 00 01 00 01 07 00 42 00 4D 07 00 42 00 43 07 00 42 40 07 00 1D FF 00 0E 00 06 07 00 0B 07 00 1D 07 00 20 07 00 06 01 01 00 00 62 07 00 42 00 FF 00 07 00 06 07 00 0B 07 00 1D 00 00 00 01 00 00
            //    Exceptions:
            //  Try           Handler
            //  Start  End    Start  End    Type                        
            //  -----  -----  -----  -----  ----------------------------
            //  62     85     88     89     Ljava/lang/RuntimeException;
            //  18     34     37     38     Ljava/lang/RuntimeException;
            //  11     29     32     33     Ljava/lang/RuntimeException;
            //  5      14     17     18     Ljava/lang/RuntimeException;
            // 
            // The error that occurred was:
            // 
            // java.lang.IllegalStateException: Expression is linked from several locations: Label_0018:
            //     at com.strobel.decompiler.ast.Error.expressionLinkedFromMultipleLocations(Error.java:27)
            //     at com.strobel.decompiler.ast.AstOptimizer.mergeDisparateObjectInitializations(AstOptimizer.java:2596)
            //     at com.strobel.decompiler.ast.AstOptimizer.optimize(AstOptimizer.java:235)
            //     at com.strobel.decompiler.ast.AstOptimizer.optimize(AstOptimizer.java:42)
            //     at com.strobel.decompiler.languages.java.ast.AstMethodBodyBuilder.createMethodBody(AstMethodBodyBuilder.java:214)
            //     at com.strobel.decompiler.languages.java.ast.AstMethodBodyBuilder.createMethodBody(AstMethodBodyBuilder.java:99)
            //     at com.strobel.decompiler.languages.java.ast.AstBuilder.createMethodBody(AstBuilder.java:782)
            //     at com.strobel.decompiler.languages.java.ast.AstBuilder.createMethod(AstBuilder.java:675)
            //     at com.strobel.decompiler.languages.java.ast.AstBuilder.addTypeMembers(AstBuilder.java:552)
            //     at com.strobel.decompiler.languages.java.ast.AstBuilder.createTypeCore(AstBuilder.java:519)
            //     at com.strobel.decompiler.languages.java.ast.AstBuilder.createTypeNoCache(AstBuilder.java:161)
            //     at com.strobel.decompiler.languages.java.ast.AstBuilder.addTypeMembers(AstBuilder.java:576)
            //     at com.strobel.decompiler.languages.java.ast.AstBuilder.createTypeCore(AstBuilder.java:519)
            //     at com.strobel.decompiler.languages.java.ast.AstBuilder.createTypeNoCache(AstBuilder.java:161)
            //     at com.strobel.decompiler.languages.java.ast.AstBuilder.createType(AstBuilder.java:150)
            //     at com.strobel.decompiler.languages.java.ast.AstBuilder.addType(AstBuilder.java:125)
            //     at com.strobel.decompiler.languages.java.JavaLanguage.buildAst(JavaLanguage.java:71)
            //     at com.strobel.decompiler.languages.java.JavaLanguage.decompileType(JavaLanguage.java:59)
            //     at com.strobel.decompiler.DecompilerDriver.decompileType(DecompilerDriver.java:330)
            //     at com.strobel.decompiler.DecompilerDriver.decompileJar(DecompilerDriver.java:251)
            //     at com.strobel.decompiler.DecompilerDriver.main(DecompilerDriver.java:126)
            // 
            throw new IllegalStateException("An error occurred while decompiling this method.");
        }
    }
    
    private static class c_ extends DefaultCellEditor
    {
        private static final long serialVersionUID = 1L;
        
        public c_() {
            super(new JPasswordField());
        }
    }
    
    private static class d_ extends DefaultCellEditor
    {
        private static final long serialVersionUID = 1L;
        
        public d_() {
            super(new JComboBox<Object>((Object[])mb.d));
        }
    }
}
