
package org.powerbot;

import org.p;

public class s
{
    private final u a;
    
    public s(final byte[] array) {
        this.a = new u(array);
    }
    
    public void a(final p p0) {
        // 
        // This method could not be decompiled.
        // 
        // Original Bytecode:
        // 
        //     3: istore          12
        //     5: aload_0        
        //     6: getfield        org/powerbot/s.a:Lorg/powerbot/u;
        //     9: invokevirtual   org/powerbot/u.b:()I
        //    12: istore_2       
        //    13: aload_0        
        //    14: getfield        org/powerbot/s.a:Lorg/powerbot/u;
        //    17: invokevirtual   org/powerbot/u.a:()I
        //    20: anewarray       Lorg/o;
        //    23: astore_3       
        //    24: iconst_0       
        //    25: istore          4
        //    27: aload_3        
        //    28: arraylength    
        //    29: istore          5
        //    31: iload           4
        //    33: iload           5
        //    35: if_icmpge       66
        //    38: aload_3        
        //    39: iload           4
        //    41: new             Lorg/o;
        //    44: dup            
        //    45: invokespecial   org/o.<init>:()V
        //    48: aastore        
        //    49: iinc            4, 1
        //    52: iload           12
        //    54: ifne            1045
        //    57: iload           12
        //    59: ifeq            31
        //    62: goto            66
        //    65: athrow         
        //    66: iload_2        
        //    67: iinc            2, -1
        //    70: ifle            1045
        //    73: iconst_0       
        //    74: istore          7
        //    76: iload           12
        //    78: ifne            180
        //    81: aload_0        
        //    82: getfield        org/powerbot/s.a:Lorg/powerbot/u;
        //    85: invokevirtual   org/powerbot/u.a:()I
        //    88: tableswitch {
        //                2: 165
        //                3: 185
        //                4: 212
        //                5: 239
        //                6: 266
        //                7: 307
        //                8: 348
        //                9: 377
        //               10: 629
        //               11: 656
        //               12: 756
        //               13: 890
        //               14: 917
        //               15: 964
        //               16: 1023
        //          default: 1040
        //        }
        //   164: athrow         
        //   165: aload_1        
        //   166: aload_0        
        //   167: getfield        org/powerbot/s.a:Lorg/powerbot/u;
        //   170: invokevirtual   org/powerbot/u.a:()I
        //   173: invokevirtual   org/p.a:(I)V
        //   176: goto            180
        //   179: athrow         
        //   180: iload           12
        //   182: ifeq            1040
        //   185: aload_1        
        //   186: aload_0        
        //   187: getfield        org/powerbot/s.a:Lorg/powerbot/u;
        //   190: invokevirtual   org/powerbot/u.a:()I
        //   193: aload_0        
        //   194: getfield        org/powerbot/s.a:Lorg/powerbot/u;
        //   197: invokevirtual   org/powerbot/u.b:()I
        //   200: invokevirtual   org/p.a:(II)V
        //   203: iload           12
        //   205: ifeq            1040
        //   208: goto            212
        //   211: athrow         
        //   212: aload_1        
        //   213: aload_0        
        //   214: getfield        org/powerbot/s.a:Lorg/powerbot/u;
        //   217: invokevirtual   org/powerbot/u.a:()I
        //   220: aload_0        
        //   221: getfield        org/powerbot/s.a:Lorg/powerbot/u;
        //   224: invokevirtual   org/powerbot/u.a:()I
        //   227: invokevirtual   org/p.b:(II)V
        //   230: iload           12
        //   232: ifeq            1040
        //   235: goto            239
        //   238: athrow         
        //   239: aload_1        
        //   240: aload_0        
        //   241: getfield        org/powerbot/s.a:Lorg/powerbot/u;
        //   244: invokevirtual   org/powerbot/u.a:()I
        //   247: aload_0        
        //   248: getfield        org/powerbot/s.a:Lorg/powerbot/u;
        //   251: invokevirtual   org/powerbot/u.e:()Ljava/lang/String;
        //   254: invokevirtual   org/p.a:(ILjava/lang/String;)V
        //   257: iload           12
        //   259: ifeq            1040
        //   262: goto            266
        //   265: athrow         
        //   266: aload_1        
        //   267: aload_0        
        //   268: getfield        org/powerbot/s.a:Lorg/powerbot/u;
        //   271: invokevirtual   org/powerbot/u.a:()I
        //   274: aload_0        
        //   275: getfield        org/powerbot/s.a:Lorg/powerbot/u;
        //   278: invokevirtual   org/powerbot/u.e:()Ljava/lang/String;
        //   281: aload_0        
        //   282: getfield        org/powerbot/s.a:Lorg/powerbot/u;
        //   285: invokevirtual   org/powerbot/u.e:()Ljava/lang/String;
        //   288: aload_0        
        //   289: getfield        org/powerbot/s.a:Lorg/powerbot/u;
        //   292: invokevirtual   org/powerbot/u.e:()Ljava/lang/String;
        //   295: invokevirtual   org/p.a:(ILjava/lang/String;Ljava/lang/String;Ljava/lang/String;)V
        //   298: iload           12
        //   300: ifeq            1040
        //   303: goto            307
        //   306: athrow         
        //   307: aload_1        
        //   308: aload_0        
        //   309: getfield        org/powerbot/s.a:Lorg/powerbot/u;
        //   312: invokevirtual   org/powerbot/u.a:()I
        //   315: aload_0        
        //   316: getfield        org/powerbot/s.a:Lorg/powerbot/u;
        //   319: invokevirtual   org/powerbot/u.e:()Ljava/lang/String;
        //   322: aload_0        
        //   323: getfield        org/powerbot/s.a:Lorg/powerbot/u;
        //   326: invokevirtual   org/powerbot/u.e:()Ljava/lang/String;
        //   329: aload_0        
        //   330: getfield        org/powerbot/s.a:Lorg/powerbot/u;
        //   333: invokevirtual   org/powerbot/u.e:()Ljava/lang/String;
        //   336: invokevirtual   org/p.b:(ILjava/lang/String;Ljava/lang/String;Ljava/lang/String;)V
        //   339: iload           12
        //   341: ifeq            1040
        //   344: goto            348
        //   347: athrow         
        //   348: aload_1        
        //   349: aload_0        
        //   350: getfield        org/powerbot/s.a:Lorg/powerbot/u;
        //   353: invokevirtual   org/powerbot/u.a:()I
        //   356: aload_3        
        //   357: aload_0        
        //   358: getfield        org/powerbot/s.a:Lorg/powerbot/u;
        //   361: invokevirtual   org/powerbot/u.a:()I
        //   364: aaload         
        //   365: invokevirtual   org/p.a:(ILorg/o;)V
        //   368: iload           12
        //   370: ifeq            1040
        //   373: goto            377
        //   376: athrow         
        //   377: aload_0        
        //   378: getfield        org/powerbot/s.a:Lorg/powerbot/u;
        //   381: invokevirtual   org/powerbot/u.a:()I
        //   384: istore          8
        //   386: iload           8
        //   388: iconst_1       
        //   389: iload           12
        //   391: ifne            431
        //   394: if_icmpne       424
        //   397: goto            401
        //   400: athrow         
        //   401: aload_1        
        //   402: aload_0        
        //   403: getfield        org/powerbot/s.a:Lorg/powerbot/u;
        //   406: invokevirtual   org/powerbot/u.c:()I
        //   409: invokestatic    java/lang/Integer.valueOf:(I)Ljava/lang/Integer;
        //   412: invokevirtual   org/p.a:(Ljava/lang/Object;)V
        //   415: iload           12
        //   417: ifeq            1040
        //   420: goto            424
        //   423: athrow         
        //   424: iload           8
        //   426: iconst_2       
        //   427: goto            431
        //   430: athrow         
        //   431: iload           12
        //   433: ifne            476
        //   436: if_icmpne       469
        //   439: goto            443
        //   442: athrow         
        //   443: aload_1        
        //   444: aload_0        
        //   445: getfield        org/powerbot/s.a:Lorg/powerbot/u;
        //   448: invokevirtual   org/powerbot/u.e:()Ljava/lang/String;
        //   451: invokestatic    java/lang/Float.parseFloat:(Ljava/lang/String;)F
        //   454: invokestatic    java/lang/Float.valueOf:(F)Ljava/lang/Float;
        //   457: invokevirtual   org/p.a:(Ljava/lang/Object;)V
        //   460: iload           12
        //   462: ifeq            1040
        //   465: goto            469
        //   468: athrow         
        //   469: iload           8
        //   471: iconst_3       
        //   472: goto            476
        //   475: athrow         
        //   476: iload           12
        //   478: ifne            518
        //   481: if_icmpne       511
        //   484: goto            488
        //   487: athrow         
        //   488: aload_1        
        //   489: aload_0        
        //   490: getfield        org/powerbot/s.a:Lorg/powerbot/u;
        //   493: invokevirtual   org/powerbot/u.d:()J
        //   496: invokestatic    java/lang/Long.valueOf:(J)Ljava/lang/Long;
        //   499: invokevirtual   org/p.a:(Ljava/lang/Object;)V
        //   502: iload           12
        //   504: ifeq            1040
        //   507: goto            511
        //   510: athrow         
        //   511: iload           8
        //   513: iconst_4       
        //   514: goto            518
        //   517: athrow         
        //   518: iload           12
        //   520: ifne            563
        //   523: if_icmpne       556
        //   526: goto            530
        //   529: athrow         
        //   530: aload_1        
        //   531: aload_0        
        //   532: getfield        org/powerbot/s.a:Lorg/powerbot/u;
        //   535: invokevirtual   org/powerbot/u.e:()Ljava/lang/String;
        //   538: invokestatic    java/lang/Double.parseDouble:(Ljava/lang/String;)D
        //   541: invokestatic    java/lang/Double.valueOf:(D)Ljava/lang/Double;
        //   544: invokevirtual   org/p.a:(Ljava/lang/Object;)V
        //   547: iload           12
        //   549: ifeq            1040
        //   552: goto            556
        //   555: athrow         
        //   556: iload           8
        //   558: iconst_5       
        //   559: goto            563
        //   562: athrow         
        //   563: iload           12
        //   565: ifne            603
        //   568: if_icmpne       595
        //   571: goto            575
        //   574: athrow         
        //   575: aload_1        
        //   576: aload_0        
        //   577: getfield        org/powerbot/s.a:Lorg/powerbot/u;
        //   580: invokevirtual   org/powerbot/u.e:()Ljava/lang/String;
        //   583: invokevirtual   org/p.a:(Ljava/lang/Object;)V
        //   586: iload           12
        //   588: ifeq            1040
        //   591: goto            595
        //   594: athrow         
        //   595: iload           8
        //   597: bipush          6
        //   599: goto            603
        //   602: athrow         
        //   603: if_icmpne       1040
        //   606: aload_1        
        //   607: aload_0        
        //   608: getfield        org/powerbot/s.a:Lorg/powerbot/u;
        //   611: invokevirtual   org/powerbot/u.e:()Ljava/lang/String;
        //   614: invokestatic    org/u.a:(Ljava/lang/String;)Lorg/u;
        //   617: invokevirtual   org/p.a:(Ljava/lang/Object;)V
        //   620: iload           12
        //   622: ifeq            1040
        //   625: goto            629
        //   628: athrow         
        //   629: aload_1        
        //   630: aload_0        
        //   631: getfield        org/powerbot/s.a:Lorg/powerbot/u;
        //   634: invokevirtual   org/powerbot/u.a:()I
        //   637: aload_0        
        //   638: getfield        org/powerbot/s.a:Lorg/powerbot/u;
        //   641: invokevirtual   org/powerbot/u.a:()I
        //   644: invokevirtual   org/p.c:(II)V
        //   647: iload           12
        //   649: ifeq            1040
        //   652: goto            656
        //   655: athrow         
        //   656: aload_0        
        //   657: getfield        org/powerbot/s.a:Lorg/powerbot/u;
        //   660: invokevirtual   org/powerbot/u.b:()I
        //   663: istore          9
        //   665: aload_0        
        //   666: getfield        org/powerbot/s.a:Lorg/powerbot/u;
        //   669: invokevirtual   org/powerbot/u.b:()I
        //   672: istore          10
        //   674: aload_3        
        //   675: aload_0        
        //   676: getfield        org/powerbot/s.a:Lorg/powerbot/u;
        //   679: invokevirtual   org/powerbot/u.a:()I
        //   682: aaload         
        //   683: astore          4
        //   685: aload_0        
        //   686: getfield        org/powerbot/s.a:Lorg/powerbot/u;
        //   689: invokevirtual   org/powerbot/u.a:()I
        //   692: istore          6
        //   694: iload           6
        //   696: anewarray       Lorg/o;
        //   699: astore          5
        //   701: iload           7
        //   703: iload           6
        //   705: if_icmpge       739
        //   708: aload           5
        //   710: iload           7
        //   712: iinc            7, 1
        //   715: aload_3        
        //   716: aload_0        
        //   717: getfield        org/powerbot/s.a:Lorg/powerbot/u;
        //   720: invokevirtual   org/powerbot/u.a:()I
        //   723: aaload         
        //   724: aastore        
        //   725: iload           12
        //   727: ifne            751
        //   730: iload           12
        //   732: ifeq            701
        //   735: goto            739
        //   738: athrow         
        //   739: aload_1        
        //   740: iload           9
        //   742: iload           10
        //   744: aload           4
        //   746: aload           5
        //   748: invokevirtual   org/p.a:(IILorg/o;[Lorg/o;)V
        //   751: iload           12
        //   753: ifeq            1040
        //   756: aload_3        
        //   757: aload_0        
        //   758: getfield        org/powerbot/s.a:Lorg/powerbot/u;
        //   761: invokevirtual   org/powerbot/u.a:()I
        //   764: aaload         
        //   765: astore          4
        //   767: aload_0        
        //   768: getfield        org/powerbot/s.a:Lorg/powerbot/u;
        //   771: invokevirtual   org/powerbot/u.a:()I
        //   774: istore          6
        //   776: iload           6
        //   778: newarray        I
        //   780: astore          11
        //   782: iload           7
        //   784: iload           6
        //   786: if_icmpge       818
        //   789: aload           11
        //   791: iload           7
        //   793: iinc            7, 1
        //   796: aload_0        
        //   797: getfield        org/powerbot/s.a:Lorg/powerbot/u;
        //   800: invokevirtual   org/powerbot/u.b:()I
        //   803: iastore        
        //   804: iload           12
        //   806: ifne            830
        //   809: iload           12
        //   811: ifeq            782
        //   814: goto            818
        //   817: athrow         
        //   818: aload_0        
        //   819: getfield        org/powerbot/s.a:Lorg/powerbot/u;
        //   822: invokevirtual   org/powerbot/u.a:()I
        //   825: istore          6
        //   827: iconst_0       
        //   828: istore          7
        //   830: iload           6
        //   832: anewarray       Lorg/o;
        //   835: astore          5
        //   837: iload           7
        //   839: iload           6
        //   841: if_icmpge       875
        //   844: aload           5
        //   846: iload           7
        //   848: iinc            7, 1
        //   851: aload_3        
        //   852: aload_0        
        //   853: getfield        org/powerbot/s.a:Lorg/powerbot/u;
        //   856: invokevirtual   org/powerbot/u.a:()I
        //   859: aaload         
        //   860: aastore        
        //   861: iload           12
        //   863: ifne            885
        //   866: iload           12
        //   868: ifeq            837
        //   871: goto            875
        //   874: athrow         
        //   875: aload_1        
        //   876: aload           4
        //   878: aload           11
        //   880: aload           5
        //   882: invokevirtual   org/p.a:(Lorg/o;[I[Lorg/o;)V
        //   885: iload           12
        //   887: ifeq            1040
        //   890: aload_1        
        //   891: aload_0        
        //   892: getfield        org/powerbot/s.a:Lorg/powerbot/u;
        //   895: invokevirtual   org/powerbot/u.e:()Ljava/lang/String;
        //   898: aload_0        
        //   899: getfield        org/powerbot/s.a:Lorg/powerbot/u;
        //   902: invokevirtual   org/powerbot/u.a:()I
        //   905: invokevirtual   org/p.a:(Ljava/lang/String;I)V
        //   908: iload           12
        //   910: ifeq            1040
        //   913: goto            917
        //   916: athrow         
        //   917: aload_1        
        //   918: aload_3        
        //   919: aload_0        
        //   920: getfield        org/powerbot/s.a:Lorg/powerbot/u;
        //   923: invokevirtual   org/powerbot/u.a:()I
        //   926: aaload         
        //   927: aload_3        
        //   928: aload_0        
        //   929: getfield        org/powerbot/s.a:Lorg/powerbot/u;
        //   932: invokevirtual   org/powerbot/u.a:()I
        //   935: aaload         
        //   936: aload_3        
        //   937: aload_0        
        //   938: getfield        org/powerbot/s.a:Lorg/powerbot/u;
        //   941: invokevirtual   org/powerbot/u.a:()I
        //   944: aaload         
        //   945: aload_0        
        //   946: getfield        org/powerbot/s.a:Lorg/powerbot/u;
        //   949: invokevirtual   org/powerbot/u.e:()Ljava/lang/String;
        //   952: invokevirtual   org/p.a:(Lorg/o;Lorg/o;Lorg/o;Ljava/lang/String;)V
        //   955: iload           12
        //   957: ifeq            1040
        //   960: goto            964
        //   963: athrow         
        //   964: aload_1        
        //   965: aload_0        
        //   966: getfield        org/powerbot/s.a:Lorg/powerbot/u;
        //   969: invokevirtual   org/powerbot/u.e:()Ljava/lang/String;
        //   972: aload_0        
        //   973: getfield        org/powerbot/s.a:Lorg/powerbot/u;
        //   976: invokevirtual   org/powerbot/u.e:()Ljava/lang/String;
        //   979: aload_0        
        //   980: getfield        org/powerbot/s.a:Lorg/powerbot/u;
        //   983: invokevirtual   org/powerbot/u.e:()Ljava/lang/String;
        //   986: aload_3        
        //   987: aload_0        
        //   988: getfield        org/powerbot/s.a:Lorg/powerbot/u;
        //   991: invokevirtual   org/powerbot/u.a:()I
        //   994: aaload         
        //   995: aload_3        
        //   996: aload_0        
        //   997: getfield        org/powerbot/s.a:Lorg/powerbot/u;
        //  1000: invokevirtual   org/powerbot/u.a:()I
        //  1003: aaload         
        //  1004: aload_0        
        //  1005: getfield        org/powerbot/s.a:Lorg/powerbot/u;
        //  1008: invokevirtual   org/powerbot/u.a:()I
        //  1011: invokevirtual   org/p.a:(Ljava/lang/String;Ljava/lang/String;Ljava/lang/String;Lorg/o;Lorg/o;I)V
        //  1014: iload           12
        //  1016: ifeq            1040
        //  1019: goto            1023
        //  1022: athrow         
        //  1023: aload_1        
        //  1024: aload_3        
        //  1025: aload_0        
        //  1026: getfield        org/powerbot/s.a:Lorg/powerbot/u;
        //  1029: invokevirtual   org/powerbot/u.a:()I
        //  1032: aaload         
        //  1033: invokevirtual   org/p.a:(Lorg/o;)V
        //  1036: goto            1040
        //  1039: athrow         
        //  1040: iload           12
        //  1042: ifeq            66
        //  1045: return         
        //    StackMapTable: 00 4D FF 00 1F 00 0D 07 00 22 07 00 32 01 07 00 8F 01 01 00 00 00 00 00 00 01 00 00 61 07 00 8A FF 00 00 00 0D 07 00 22 07 00 32 01 07 00 8F 00 00 00 00 00 00 00 00 01 00 00 FF 00 61 00 0D 07 00 22 07 00 32 01 07 00 8F 00 00 00 01 00 00 00 00 01 00 01 07 00 8A 00 4D 07 00 8A 00 04 59 07 00 8A 00 59 07 00 8A 00 59 07 00 8A 00 67 07 00 8A 00 67 07 00 8A 00 5B 07 00 8A 00 FF 00 16 00 0D 07 00 22 07 00 32 01 07 00 8F 00 00 00 01 01 00 00 00 01 00 01 07 00 8A 00 55 07 00 8A 00 45 07 00 8A FF 00 00 00 0D 07 00 22 07 00 32 01 07 00 8F 00 00 00 01 01 00 00 00 01 00 02 01 01 4A 07 00 8A 00 58 07 00 8A 00 45 07 00 8A FF 00 00 00 0D 07 00 22 07 00 32 01 07 00 8F 00 00 00 01 01 00 00 00 01 00 02 01 01 4A 07 00 8A 00 55 07 00 8A 00 45 07 00 8A FF 00 00 00 0D 07 00 22 07 00 32 01 07 00 8F 00 00 00 01 01 00 00 00 01 00 02 01 01 4A 07 00 8A 00 58 07 00 8A 00 45 07 00 8A FF 00 00 00 0D 07 00 22 07 00 32 01 07 00 8F 00 00 00 01 01 00 00 00 01 00 02 01 01 4A 07 00 8A 00 52 07 00 8A 00 46 07 00 8A FF 00 00 00 0D 07 00 22 07 00 32 01 07 00 8F 00 00 00 01 01 00 00 00 01 00 02 01 01 58 07 00 8A FF 00 00 00 0D 07 00 22 07 00 32 01 07 00 8F 00 00 00 01 00 00 00 00 01 00 00 59 07 00 8A 00 FF 00 2C 00 0D 07 00 22 07 00 32 01 07 00 8F 07 00 07 07 00 8F 01 01 00 01 01 00 01 00 00 64 07 00 8A 00 0B FF 00 04 00 0D 07 00 22 07 00 32 01 07 00 8F 00 00 00 01 00 00 00 00 01 00 00 FF 00 19 00 0D 07 00 22 07 00 32 01 07 00 8F 07 00 07 00 01 01 00 00 00 07 00 91 01 00 00 62 07 00 8A 00 0B FF 00 06 00 0D 07 00 22 07 00 32 01 07 00 8F 07 00 07 07 00 8F 01 01 00 00 00 07 00 91 01 00 00 64 07 00 8A 00 09 FF 00 04 00 0D 07 00 22 07 00 32 01 07 00 8F 00 00 00 01 00 00 00 00 01 00 00 59 07 00 8A 00 6D 07 00 8A 00 79 07 00 8A 00 4F 07 00 8A 00 FF 00 04 00 0D 07 00 22 07 00 32 01 07 00 8F 00 00 00 00 00 00 00 00 01 00 00
        //    Exceptions:
        //  Try           Handler
        //  Start  End    Start  End    Type                        
        //  -----  -----  -----  -----  ----------------------------
        //  964    1036   1039   1040   Ljava/lang/RuntimeException;
        //  917    1019   1022   1023   Ljava/lang/RuntimeException;
        //  890    960    963    964    Ljava/lang/RuntimeException;
        //  885    913    916    917    Ljava/lang/RuntimeException;
        //  844    871    874    875    Ljava/lang/RuntimeException;
        //  789    814    817    818    Ljava/lang/RuntimeException;
        //  708    735    738    739    Ljava/lang/RuntimeException;
        //  606    652    655    656    Ljava/lang/RuntimeException;
        //  603    625    628    629    Ljava/lang/RuntimeException;
        //  575    599    602    603    Ljava/lang/RuntimeException;
        //  568    591    594    595    Ljava/lang/RuntimeException;
        //  563    571    574    575    Ljava/lang/RuntimeException;
        //  530    559    562    563    Ljava/lang/RuntimeException;
        //  523    552    555    556    Ljava/lang/RuntimeException;
        //  518    526    529    530    Ljava/lang/RuntimeException;
        //  488    514    517    518    Ljava/lang/RuntimeException;
        //  481    507    510    511    Ljava/lang/RuntimeException;
        //  476    484    487    488    Ljava/lang/RuntimeException;
        //  443    472    475    476    Ljava/lang/RuntimeException;
        //  436    465    468    469    Ljava/lang/RuntimeException;
        //  431    439    442    443    Ljava/lang/RuntimeException;
        //  401    427    430    431    Ljava/lang/RuntimeException;
        //  394    420    423    424    Ljava/lang/RuntimeException;
        //  386    397    400    401    Ljava/lang/RuntimeException;
        //  307    373    376    377    Ljava/lang/RuntimeException;
        //  266    344    347    348    Ljava/lang/RuntimeException;
        //  239    303    306    307    Ljava/lang/RuntimeException;
        //  212    262    265    266    Ljava/lang/RuntimeException;
        //  185    235    238    239    Ljava/lang/RuntimeException;
        //  180    208    211    212    Ljava/lang/RuntimeException;
        //  81     176    179    180    Ljava/lang/RuntimeException;
        //  76     164    164    165    Ljava/lang/RuntimeException;
        //  38     62     65     66     Ljava/lang/RuntimeException;
        // 
        // The error that occurred was:
        // 
        // java.lang.IllegalStateException: Expression is linked from several locations: Label_0185:
        //     at com.strobel.decompiler.ast.Error.expressionLinkedFromMultipleLocations(Error.java:27)
        //     at com.strobel.decompiler.ast.AstOptimizer.mergeDisparateObjectInitializations(AstOptimizer.java:2596)
        //     at com.strobel.decompiler.ast.AstOptimizer.optimize(AstOptimizer.java:235)
        //     at com.strobel.decompiler.ast.AstOptimizer.optimize(AstOptimizer.java:42)
        //     at com.strobel.decompiler.languages.java.ast.AstMethodBodyBuilder.createMethodBody(AstMethodBodyBuilder.java:214)
        //     at com.strobel.decompiler.languages.java.ast.AstMethodBodyBuilder.createMethodBody(AstMethodBodyBuilder.java:99)
        //     at com.strobel.decompiler.languages.java.ast.AstBuilder.createMethodBody(AstBuilder.java:782)
        //     at com.strobel.decompiler.languages.java.ast.AstBuilder.createMethod(AstBuilder.java:675)
        //     at com.strobel.decompiler.languages.java.ast.AstBuilder.addTypeMembers(AstBuilder.java:552)
        //     at com.strobel.decompiler.languages.java.ast.AstBuilder.createTypeCore(AstBuilder.java:519)
        //     at com.strobel.decompiler.languages.java.ast.AstBuilder.createTypeNoCache(AstBuilder.java:161)
        //     at com.strobel.decompiler.languages.java.ast.AstBuilder.createType(AstBuilder.java:150)
        //     at com.strobel.decompiler.languages.java.ast.AstBuilder.addType(AstBuilder.java:125)
        //     at com.strobel.decompiler.languages.java.JavaLanguage.buildAst(JavaLanguage.java:71)
        //     at com.strobel.decompiler.languages.java.JavaLanguage.decompileType(JavaLanguage.java:59)
        //     at com.strobel.decompiler.DecompilerDriver.decompileType(DecompilerDriver.java:330)
        //     at com.strobel.decompiler.DecompilerDriver.decompileJar(DecompilerDriver.java:251)
        //     at com.strobel.decompiler.DecompilerDriver.main(DecompilerDriver.java:126)
        // 
        throw new IllegalStateException("An error occurred while decompiling this method.");
    }
    
    public static String a(final String s) {
        final int n = (0x3 ^ 0x5) << 4 ^ (0x2 ^ 0x5) << 1;
        final int n2 = 1 << 3 ^ (0x2 ^ 0x5);
        final int length = s.length();
        final char[] array = new char[length];
        int n3;
        int i = n3 = length - 1;
        final char[] value = array;
        final char c = (char)n2;
        final int n4 = n;
        while (i >= 0) {
            final char[] array2 = value;
            final int index = n3;
            final char char1 = s.charAt(index);
            --n3;
            array2[index] = (char)(char1 ^ n4);
            if (n3 < 0) {
                break;
            }
            final char[] array3 = value;
            final int index2 = n3;
            final char c2 = (char)(s.charAt(index2) ^ c);
            --n3;
            array3[index2] = c2;
            i = n3;
        }
        return new String(value);
    }
}
