
package org.powerbot;

import org.powerbot.core.script.methods.GroundItems;
import java.util.Map;
import org.o;
import org.powerbot.core.script.job.Task;
import org.powerbot.game.api.Manifest;
import java.io.Serializable;

public final class w implements Comparable<w>, Serializable
{
    private static final long serialVersionUID = 7424073911663414957L;
    private final String a;
    private final String b;
    private final String c;
    private final String d;
    private final double e;
    private final String[] f;
    public String g;
    public byte[] h;
    public String i;
    public boolean j;
    private a_ k;
    private static final String[] z;
    
    public w(final Manifest manifest) {
        final boolean a = org.powerbot.a.a;
        this.j = false;
        this.k = null;
        this.a = manifest.name();
        this.b = null;
        this.c = manifest.description();
        this.e = manifest.version();
        this.f = manifest.authors();
        this.d = manifest.website();
        if (a) {
            int a2 = Task.a;
            Task.a = ++a2;
        }
    }
    
    public w(final String a, final String b, final String c, final double e, final String[] f, final String d) {
        this.j = false;
        this.k = null;
        this.a = a;
        this.b = b;
        this.c = c;
        this.e = e;
        this.f = f;
        this.d = d;
    }
    
    private String a(final String p0) {
        // 
        // This method could not be decompiled.
        // 
        // Original Bytecode:
        // 
        //     3: istore_2       
        //     4: aload_1        
        //     5: iload_2        
        //     6: ifne            41
        //     9: ifnull          35
        //    12: goto            16
        //    15: athrow         
        //    16: aload_1        
        //    17: iload_2        
        //    18: ifne            48
        //    21: goto            25
        //    24: athrow         
        //    25: invokevirtual   java/lang/String.isEmpty:()Z
        //    28: ifeq            44
        //    31: goto            35
        //    34: athrow         
        //    35: ldc             ""
        //    37: goto            41
        //    40: athrow         
        //    41: goto            51
        //    44: aload_1        
        //    45: invokevirtual   java/lang/String.trim:()Ljava/lang/String;
        //    48: invokestatic    org/powerbot/gb.a:(Ljava/lang/String;)Ljava/lang/String;
        //    51: areturn        
        //    StackMapTable: 00 0B FF 00 0F 00 03 07 00 34 07 00 30 01 00 01 07 00 33 00 47 07 00 33 40 07 00 30 48 07 00 33 00 44 07 00 33 40 07 00 30 02 43 07 00 30 42 07 00 30
        //    Exceptions:
        //  Try           Handler
        //  Start  End    Start  End    Type                             
        //  -----  -----  -----  -----  ---------------------------------
        //  25     37     40     41     Ljava/lang/NumberFormatException;
        //  16     31     34     35     Ljava/lang/NumberFormatException;
        //  9      21     24     25     Ljava/lang/NumberFormatException;
        //  4      12     15     16     Ljava/lang/NumberFormatException;
        // 
        // The error that occurred was:
        // 
        // java.lang.IllegalStateException: Expression is linked from several locations: Label_0016:
        //     at com.strobel.decompiler.ast.Error.expressionLinkedFromMultipleLocations(Error.java:27)
        //     at com.strobel.decompiler.ast.AstOptimizer.mergeDisparateObjectInitializations(AstOptimizer.java:2596)
        //     at com.strobel.decompiler.ast.AstOptimizer.optimize(AstOptimizer.java:235)
        //     at com.strobel.decompiler.ast.AstOptimizer.optimize(AstOptimizer.java:42)
        //     at com.strobel.decompiler.languages.java.ast.AstMethodBodyBuilder.createMethodBody(AstMethodBodyBuilder.java:214)
        //     at com.strobel.decompiler.languages.java.ast.AstMethodBodyBuilder.createMethodBody(AstMethodBodyBuilder.java:99)
        //     at com.strobel.decompiler.languages.java.ast.AstBuilder.createMethodBody(AstBuilder.java:782)
        //     at com.strobel.decompiler.languages.java.ast.AstBuilder.createMethod(AstBuilder.java:675)
        //     at com.strobel.decompiler.languages.java.ast.AstBuilder.addTypeMembers(AstBuilder.java:552)
        //     at com.strobel.decompiler.languages.java.ast.AstBuilder.createTypeCore(AstBuilder.java:519)
        //     at com.strobel.decompiler.languages.java.ast.AstBuilder.createTypeNoCache(AstBuilder.java:161)
        //     at com.strobel.decompiler.languages.java.ast.AstBuilder.createType(AstBuilder.java:150)
        //     at com.strobel.decompiler.languages.java.ast.AstBuilder.addType(AstBuilder.java:125)
        //     at com.strobel.decompiler.languages.java.JavaLanguage.buildAst(JavaLanguage.java:71)
        //     at com.strobel.decompiler.languages.java.JavaLanguage.decompileType(JavaLanguage.java:59)
        //     at com.strobel.decompiler.DecompilerDriver.decompileType(DecompilerDriver.java:330)
        //     at com.strobel.decompiler.DecompilerDriver.decompileJar(DecompilerDriver.java:251)
        //     at com.strobel.decompiler.DecompilerDriver.main(DecompilerDriver.java:126)
        // 
        throw new IllegalStateException("An error occurred while decompiling this method.");
    }
    
    public String a() {
        return this.a(this.a);
    }
    
    public String b() {
        Label_0017: {
            try {
                final w w = this;
                if (org.powerbot.a.a) {
                    return w.b;
                }
                final String s = this.b;
                if (s == null) {
                    break Label_0017;
                }
                break Label_0017;
            }
            catch (NumberFormatException ex) {
                throw ex;
            }
            try {
                final String s = this.b;
                if (s == null) {
                    return "";
                }
            }
            catch (NumberFormatException ex2) {
                throw ex2;
            }
        }
        final w w = this;
        return w.b;
    }
    
    public String c() {
        return this.a(this.c);
    }
    
    public double d() {
        return this.e;
    }
    
    public String[] e() {
        return this.f;
    }
    
    public String f() {
        final boolean a = org.powerbot.a.a;
        Label_0029: {
            String[] array2 = null;
            Label_0021: {
                String[] array;
                try {
                    array = (array2 = this.f);
                    if (a) {
                        break Label_0029;
                    }
                    if (array != null) {
                        break Label_0021;
                    }
                    return "";
                }
                catch (NumberFormatException ex) {
                    throw ex;
                }
                try {
                    if (array == null) {
                        return "";
                    }
                    array2 = this.f;
                }
                catch (NumberFormatException ex2) {
                    throw ex2;
                }
            }
            try {
                if (array2.length == 0) {
                    return "";
                }
            }
            catch (NumberFormatException ex3) {
                throw ex3;
            }
        }
        final StringBuilder sb = new StringBuilder();
        final String[] e = this.e();
        int i = 0;
        while (i < e.length) {
            try {
                if (i != 0) {
                    sb.append(o.a(w.z[0]));
                }
            }
            catch (NumberFormatException ex4) {
                throw ex4;
            }
            sb.append(gb.a(e[i].trim()));
            ++i;
            if (a) {
                break;
            }
        }
        return sb.toString();
    }
    
    public String g() {
        // 
        // This method could not be decompiled.
        // 
        // Original Bytecode:
        // 
        //     3: istore_2       
        //     4: aload_0        
        //     5: getfield        org/powerbot/w.d:Ljava/lang/String;
        //     8: astore_1       
        //     9: aload_1        
        //    10: iload_2        
        //    11: ifne            22
        //    14: ifnull          98
        //    17: goto            21
        //    20: athrow         
        //    21: aload_1        
        //    22: invokevirtual   java/lang/String.isEmpty:()Z
        //    25: iload_2        
        //    26: ifne            60
        //    29: ifne            98
        //    32: goto            36
        //    35: athrow         
        //    36: aload_1        
        //    37: iload_2        
        //    38: ifne            95
        //    41: goto            45
        //    44: athrow         
        //    45: getstatic       org/powerbot/w.z:[Ljava/lang/String;
        //    48: iconst_2       
        //    49: aaload         
        //    50: invokestatic    org/powerbot/kb.a:(Ljava/lang/String;)Ljava/lang/String;
        //    53: invokevirtual   java/lang/String.startsWith:(Ljava/lang/String;)Z
        //    56: goto            60
        //    59: athrow         
        //    60: ifne            90
        //    63: aload_1        
        //    64: iload_2        
        //    65: ifne            95
        //    68: goto            72
        //    71: athrow         
        //    72: getstatic       org/powerbot/w.z:[Ljava/lang/String;
        //    75: iconst_3       
        //    76: aaload         
        //    77: invokestatic    org/o.a:(Ljava/lang/String;)Ljava/lang/String;
        //    80: invokevirtual   java/lang/String.startsWith:(Ljava/lang/String;)Z
        //    83: ifeq            98
        //    86: goto            90
        //    89: athrow         
        //    90: aload_1        
        //    91: goto            95
        //    94: athrow         
        //    95: goto            99
        //    98: aconst_null    
        //    99: areturn        
        //    StackMapTable: 00 11 FF 00 14 00 03 07 00 34 07 00 30 01 00 01 07 00 33 00 40 07 00 30 4C 07 00 33 00 47 07 00 33 40 07 00 30 4D 07 00 33 40 01 4A 07 00 33 40 07 00 30 50 07 00 33 00 43 07 00 33 40 07 00 30 02 40 07 00 30
        //    Exceptions:
        //  Try           Handler
        //  Start  End    Start  End    Type                             
        //  -----  -----  -----  -----  ---------------------------------
        //  72     91     94     95     Ljava/lang/NumberFormatException;
        //  63     86     89     90     Ljava/lang/NumberFormatException;
        //  60     68     71     72     Ljava/lang/NumberFormatException;
        //  36     56     59     60     Ljava/lang/NumberFormatException;
        //  29     41     44     45     Ljava/lang/NumberFormatException;
        //  22     32     35     36     Ljava/lang/NumberFormatException;
        //  9      17     20     21     Ljava/lang/NumberFormatException;
        // 
        // The error that occurred was:
        // 
        // java.lang.IllegalStateException: Expression is linked from several locations: Label_0036:
        //     at com.strobel.decompiler.ast.Error.expressionLinkedFromMultipleLocations(Error.java:27)
        //     at com.strobel.decompiler.ast.AstOptimizer.mergeDisparateObjectInitializations(AstOptimizer.java:2596)
        //     at com.strobel.decompiler.ast.AstOptimizer.optimize(AstOptimizer.java:235)
        //     at com.strobel.decompiler.ast.AstOptimizer.optimize(AstOptimizer.java:42)
        //     at com.strobel.decompiler.languages.java.ast.AstMethodBodyBuilder.createMethodBody(AstMethodBodyBuilder.java:214)
        //     at com.strobel.decompiler.languages.java.ast.AstMethodBodyBuilder.createMethodBody(AstMethodBodyBuilder.java:99)
        //     at com.strobel.decompiler.languages.java.ast.AstBuilder.createMethodBody(AstBuilder.java:782)
        //     at com.strobel.decompiler.languages.java.ast.AstBuilder.createMethod(AstBuilder.java:675)
        //     at com.strobel.decompiler.languages.java.ast.AstBuilder.addTypeMembers(AstBuilder.java:552)
        //     at com.strobel.decompiler.languages.java.ast.AstBuilder.createTypeCore(AstBuilder.java:519)
        //     at com.strobel.decompiler.languages.java.ast.AstBuilder.createTypeNoCache(AstBuilder.java:161)
        //     at com.strobel.decompiler.languages.java.ast.AstBuilder.createType(AstBuilder.java:150)
        //     at com.strobel.decompiler.languages.java.ast.AstBuilder.addType(AstBuilder.java:125)
        //     at com.strobel.decompiler.languages.java.JavaLanguage.buildAst(JavaLanguage.java:71)
        //     at com.strobel.decompiler.languages.java.JavaLanguage.decompileType(JavaLanguage.java:59)
        //     at com.strobel.decompiler.DecompilerDriver.decompileType(DecompilerDriver.java:330)
        //     at com.strobel.decompiler.DecompilerDriver.decompileJar(DecompilerDriver.java:251)
        //     at com.strobel.decompiler.DecompilerDriver.main(DecompilerDriver.java:126)
        // 
        throw new IllegalStateException("An error occurred while decompiling this method.");
    }
    
    public a_ h() {
        // 
        // This method could not be decompiled.
        // 
        // Original Bytecode:
        // 
        //     3: istore          9
        //     5: aload_0        
        //     6: iload           9
        //     8: ifne            28
        //    11: getfield        org/powerbot/w.k:Lorg/powerbot/w$a_;
        //    14: ifnull          27
        //    17: goto            21
        //    20: athrow         
        //    21: aload_0        
        //    22: getfield        org/powerbot/w.k:Lorg/powerbot/w$a_;
        //    25: areturn        
        //    26: athrow         
        //    27: aload_0        
        //    28: getstatic       org/powerbot/w$a_.AIO:Lorg/powerbot/w$a_;
        //    31: putfield        org/powerbot/w.k:Lorg/powerbot/w$a_;
        //    34: new             Ljava/lang/StringBuilder;
        //    37: dup            
        //    38: invokespecial   java/lang/StringBuilder.<init>:()V
        //    41: aload_0        
        //    42: invokevirtual   org/powerbot/w.a:()Ljava/lang/String;
        //    45: invokevirtual   java/lang/StringBuilder.append:(Ljava/lang/String;)Ljava/lang/StringBuilder;
        //    48: ldc             "v"
        //    50: invokestatic    org/powerbot/kb.a:(Ljava/lang/String;)Ljava/lang/String;
        //    53: invokevirtual   java/lang/StringBuilder.append:(Ljava/lang/String;)Ljava/lang/StringBuilder;
        //    56: aload_0        
        //    57: invokevirtual   org/powerbot/w.c:()Ljava/lang/String;
        //    60: invokevirtual   java/lang/StringBuilder.append:(Ljava/lang/String;)Ljava/lang/StringBuilder;
        //    63: invokevirtual   java/lang/StringBuilder.toString:()Ljava/lang/String;
        //    66: invokevirtual   java/lang/String.toLowerCase:()Ljava/lang/String;
        //    69: astore_1       
        //    70: sipush          4095
        //    73: istore_2       
        //    74: ldc             Lorg/powerbot/w$a_;.class
        //    76: invokevirtual   java/lang/Class.getEnumConstants:()[Ljava/lang/Object;
        //    79: checkcast       [Lorg/powerbot/w$a_;
        //    82: astore_3       
        //    83: aload_3        
        //    84: arraylength    
        //    85: istore          4
        //    87: iconst_0       
        //    88: istore          5
        //    90: iload           5
        //    92: iload           4
        //    94: if_icmpge       282
        //    97: aload_3        
        //    98: iload           5
        //   100: aaload         
        //   101: iload           9
        //   103: ifne            286
        //   106: astore          6
        //   108: aload_1        
        //   109: aload           6
        //   111: invokevirtual   org/powerbot/w$a_.name:()Ljava/lang/String;
        //   114: invokevirtual   java/lang/String.toLowerCase:()Ljava/lang/String;
        //   117: invokevirtual   java/lang/String.indexOf:(Ljava/lang/String;)I
        //   120: istore          7
        //   122: iload           7
        //   124: iload           9
        //   126: ifne            182
        //   129: iconst_m1      
        //   130: if_icmpeq       165
        //   133: goto            137
        //   136: athrow         
        //   137: iload           7
        //   139: iload           9
        //   141: ifne            182
        //   144: goto            148
        //   147: athrow         
        //   148: iload_2        
        //   149: if_icmpge       165
        //   152: goto            156
        //   155: athrow         
        //   156: iload           7
        //   158: istore_2       
        //   159: aload_0        
        //   160: aload           6
        //   162: putfield        org/powerbot/w.k:Lorg/powerbot/w$a_;
        //   165: aload           6
        //   167: getfield        org/powerbot/w$a_.regex:Ljava/lang/String;
        //   170: iload           9
        //   172: ifne            193
        //   175: invokevirtual   java/lang/String.length:()I
        //   178: goto            182
        //   181: athrow         
        //   182: ifne            188
        //   185: goto            274
        //   188: aload           6
        //   190: getfield        org/powerbot/w$a_.regex:Ljava/lang/String;
        //   193: invokestatic    java/util/regex/Pattern.compile:(Ljava/lang/String;)Ljava/util/regex/Pattern;
        //   196: aload_1        
        //   197: invokevirtual   java/util/regex/Pattern.matcher:(Ljava/lang/CharSequence;)Ljava/util/regex/Matcher;
        //   200: astore          8
        //   202: iload           9
        //   204: ifne            277
        //   207: aload           8
        //   209: iconst_0       
        //   210: invokevirtual   java/util/regex/Matcher.find:(I)Z
        //   213: ifeq            274
        //   216: goto            220
        //   219: athrow         
        //   220: aload           8
        //   222: invokevirtual   java/util/regex/Matcher.start:()I
        //   225: istore          7
        //   227: iload           9
        //   229: ifne            277
        //   232: iload           7
        //   234: iconst_m1      
        //   235: if_icmpeq       274
        //   238: goto            242
        //   241: athrow         
        //   242: iload           7
        //   244: iload           9
        //   246: ifne            267
        //   249: goto            253
        //   252: athrow         
        //   253: iload_2        
        //   254: if_icmpge       274
        //   257: goto            261
        //   260: athrow         
        //   261: iload           7
        //   263: goto            267
        //   266: athrow         
        //   267: istore_2       
        //   268: aload_0        
        //   269: aload           6
        //   271: putfield        org/powerbot/w.k:Lorg/powerbot/w$a_;
        //   274: iinc            5, 1
        //   277: iload           9
        //   279: ifeq            90
        //   282: aload_0        
        //   283: getfield        org/powerbot/w.k:Lorg/powerbot/w$a_;
        //   286: areturn        
        //    StackMapTable: 00 1F FF 00 14 00 0A 07 00 34 00 00 00 00 00 00 00 00 01 00 01 07 00 33 00 44 07 00 33 00 40 07 00 34 FF 00 3D 00 0A 07 00 34 07 00 30 01 07 00 21 01 01 00 00 00 01 00 00 FF 00 2D 00 0A 07 00 34 07 00 30 01 07 00 21 01 01 07 00 1F 01 00 01 00 01 07 00 33 00 49 07 00 33 40 01 46 07 00 33 00 08 4F 07 00 33 40 01 05 44 07 00 30 FF 00 19 00 0A 07 00 34 07 00 30 01 07 00 21 01 01 07 00 1F 01 07 00 8F 01 00 01 07 00 33 00 54 07 00 33 00 49 07 00 33 40 01 46 07 00 33 00 44 07 00 33 40 01 FF 00 06 00 0A 07 00 34 07 00 30 01 07 00 21 01 01 07 00 1F 01 00 01 00 00 02 FF 00 04 00 0A 07 00 34 07 00 30 01 07 00 21 01 01 00 00 00 01 00 00 43 07 00 1F
        //    Exceptions:
        //  Try           Handler
        //  Start  End    Start  End    Type                             
        //  -----  -----  -----  -----  ---------------------------------
        //  253    263    266    267    Ljava/lang/NumberFormatException;
        //  242    257    260    261    Ljava/lang/NumberFormatException;
        //  232    249    252    253    Ljava/lang/NumberFormatException;
        //  227    238    241    242    Ljava/lang/NumberFormatException;
        //  202    216    219    220    Ljava/lang/NumberFormatException;
        //  165    178    181    182    Ljava/lang/NumberFormatException;
        //  137    152    155    156    Ljava/lang/NumberFormatException;
        //  129    144    147    148    Ljava/lang/NumberFormatException;
        //  122    133    136    137    Ljava/lang/NumberFormatException;
        //  11     26     26     27     Ljava/lang/NumberFormatException;
        //  5      17     20     21     Ljava/lang/NumberFormatException;
        // 
        // The error that occurred was:
        // 
        // java.lang.IllegalStateException: Expression is linked from several locations: Label_0137:
        //     at com.strobel.decompiler.ast.Error.expressionLinkedFromMultipleLocations(Error.java:27)
        //     at com.strobel.decompiler.ast.AstOptimizer.mergeDisparateObjectInitializations(AstOptimizer.java:2596)
        //     at com.strobel.decompiler.ast.AstOptimizer.optimize(AstOptimizer.java:235)
        //     at com.strobel.decompiler.ast.AstOptimizer.optimize(AstOptimizer.java:42)
        //     at com.strobel.decompiler.languages.java.ast.AstMethodBodyBuilder.createMethodBody(AstMethodBodyBuilder.java:214)
        //     at com.strobel.decompiler.languages.java.ast.AstMethodBodyBuilder.createMethodBody(AstMethodBodyBuilder.java:99)
        //     at com.strobel.decompiler.languages.java.ast.AstBuilder.createMethodBody(AstBuilder.java:782)
        //     at com.strobel.decompiler.languages.java.ast.AstBuilder.createMethod(AstBuilder.java:675)
        //     at com.strobel.decompiler.languages.java.ast.AstBuilder.addTypeMembers(AstBuilder.java:552)
        //     at com.strobel.decompiler.languages.java.ast.AstBuilder.createTypeCore(AstBuilder.java:519)
        //     at com.strobel.decompiler.languages.java.ast.AstBuilder.createTypeNoCache(AstBuilder.java:161)
        //     at com.strobel.decompiler.languages.java.ast.AstBuilder.createType(AstBuilder.java:150)
        //     at com.strobel.decompiler.languages.java.ast.AstBuilder.addType(AstBuilder.java:125)
        //     at com.strobel.decompiler.languages.java.JavaLanguage.buildAst(JavaLanguage.java:71)
        //     at com.strobel.decompiler.languages.java.JavaLanguage.decompileType(JavaLanguage.java:59)
        //     at com.strobel.decompiler.DecompilerDriver.decompileType(DecompilerDriver.java:330)
        //     at com.strobel.decompiler.DecompilerDriver.decompileJar(DecompilerDriver.java:251)
        //     at com.strobel.decompiler.DecompilerDriver.main(DecompilerDriver.java:126)
        // 
        throw new IllegalStateException("An error occurred while decompiling this method.");
    }
    
    public boolean b(final String s) {
        return String.format(o.a(w.z[1]), this.a(), this.c(), this.f()).toLowerCase().contains(s.toLowerCase());
    }
    
    @Override
    public String toString() {
        return this.a().toLowerCase();
    }
    
    public static w a(final Map<String, String> map) {
        final boolean a = org.powerbot.a.a;
        String s3 = null;
        Label_0057: {
            Label_0056: {
                Map<String, String> map2 = null;
                String s2 = null;
                Label_0031: {
                    String s;
                    try {
                        map2 = map;
                        s = (s2 = kb.a(w.z[5]));
                        if (a) {
                            break Label_0031;
                        }
                        final boolean b = map.containsKey(s);
                        if (b) {
                            break Label_0031;
                        }
                        break Label_0056;
                    }
                    catch (NumberFormatException ex) {
                        throw ex;
                    }
                    try {
                        final boolean b = map.containsKey(s);
                        if (!b) {
                            break Label_0056;
                        }
                        map2 = map;
                        s2 = o.a(w.z[9]);
                    }
                    catch (NumberFormatException ex2) {
                        throw ex2;
                    }
                }
                s3 = map2.get(s2);
                break Label_0057;
            }
            s3 = null;
        }
        final String s4 = s3;
        String s7 = null;
        Label_0111: {
            Label_0110: {
                Map<String, String> map3 = null;
                String s6 = null;
                Label_0085: {
                    String s5;
                    try {
                        map3 = map;
                        s5 = (s6 = kb.a(w.z[10]));
                        if (a) {
                            break Label_0085;
                        }
                        final boolean b2 = map.containsKey(s5);
                        if (b2) {
                            break Label_0085;
                        }
                        break Label_0110;
                    }
                    catch (NumberFormatException ex3) {
                        throw ex3;
                    }
                    try {
                        final boolean b2 = map.containsKey(s5);
                        if (!b2) {
                            break Label_0110;
                        }
                        map3 = map;
                        s6 = o.a(w.z[15]);
                    }
                    catch (NumberFormatException ex4) {
                        throw ex4;
                    }
                }
                s7 = map3.get(s6);
                break Label_0111;
            }
            s7 = null;
        }
        final String s8 = s7;
        String s11 = null;
        Label_0165: {
            Label_0164: {
                Map<String, String> map4 = null;
                String s10 = null;
                Label_0139: {
                    String s9;
                    try {
                        map4 = map;
                        s9 = (s10 = kb.a(w.z[8]));
                        if (a) {
                            break Label_0139;
                        }
                        final boolean b3 = map.containsKey(s9);
                        if (b3) {
                            break Label_0139;
                        }
                        break Label_0164;
                    }
                    catch (NumberFormatException ex5) {
                        throw ex5;
                    }
                    try {
                        final boolean b3 = map.containsKey(s9);
                        if (!b3) {
                            break Label_0164;
                        }
                        map4 = map;
                        s10 = o.a(w.z[7]);
                    }
                    catch (NumberFormatException ex6) {
                        throw ex6;
                    }
                }
                s11 = map4.get(s10);
                break Label_0165;
            }
            s11 = null;
        }
        final String s12 = s11;
        String s15 = null;
        Label_0219: {
            Label_0218: {
                Map<String, String> map5 = null;
                String s14 = null;
                Label_0193: {
                    String s13;
                    try {
                        map5 = map;
                        s13 = (s14 = kb.a(w.z[14]));
                        if (a) {
                            break Label_0193;
                        }
                        final boolean b4 = map.containsKey(s13);
                        if (b4) {
                            break Label_0193;
                        }
                        break Label_0218;
                    }
                    catch (NumberFormatException ex7) {
                        throw ex7;
                    }
                    try {
                        final boolean b4 = map.containsKey(s13);
                        if (!b4) {
                            break Label_0218;
                        }
                        map5 = map;
                        s14 = o.a(w.z[11]);
                    }
                    catch (NumberFormatException ex8) {
                        throw ex8;
                    }
                }
                s15 = map5.get(s14);
                break Label_0219;
            }
            s15 = null;
        }
        final String s16 = s15;
        String[] split = null;
        Label_0282: {
            int containsKey = 0;
            Label_0279: {
                Label_0248: {
                    int n;
                    try {
                        n = (containsKey = (map.containsKey(kb.a(w.z[13])) ? 1 : 0));
                        if (a) {
                            break Label_0279;
                        }
                        if (n != 0) {
                            break Label_0248;
                        }
                        break Label_0248;
                    }
                    catch (NumberFormatException ex9) {
                        throw ex9;
                    }
                    try {
                        if (n != 0) {
                            split = map.get(o.a(w.z[6])).split(kb.a("z"));
                            break Label_0282;
                        }
                    }
                    catch (NumberFormatException ex10) {
                        throw ex10;
                    }
                }
                containsKey = 0;
            }
            split = new String[containsKey];
        }
        final String[] array = split;
        double double1 = 1.0;
        Label_0361: {
            String s17 = null;
            Label_0341: {
                Label_0323: {
                    String a2;
                    try {
                        final Map<String, String> map6 = map;
                        a2 = o.a(w.z[12]);
                        if (a) {
                            break Label_0323;
                        }
                        if (!map.containsKey(a2)) {
                            break Label_0341;
                        }
                    }
                    catch (NumberFormatException ex11) {
                        throw ex11;
                    }
                    try {
                        final Map<String, String> map6 = map;
                        kb.a(w.z[4]);
                        double1 = Double.parseDouble(map6.get(a2));
                    }
                    catch (NumberFormatException ex14) {}
                }
                try {
                    s17 = s4;
                    if (a) {
                        break Label_0361;
                    }
                    if (s17 == null) {
                        break Label_0361;
                    }
                }
                catch (NumberFormatException ex12) {
                    throw ex12;
                }
            }
            try {
                if (s17.isEmpty()) {
                    return null;
                }
            }
            catch (NumberFormatException ex13) {
                throw ex13;
            }
        }
        return new w(s4, s8, s12, double1, array, s16);
    }
    
    public int a(final w w) {
        final boolean a = org.powerbot.a.a;
        final String b = this.b();
        final String b2 = w.b();
        Label_0041: {
            String s2 = null;
            Label_0029: {
                try {
                    final String s3;
                    final String s = s2 = (s3 = b);
                    if (a) {
                        break Label_0029;
                    }
                    if (s == null) {
                        break Label_0041;
                    }
                }
                catch (NumberFormatException ex) {
                    throw ex;
                }
                String s3 = s2 = b2;
                try {
                    if (a) {
                        return s3.compareTo(b2);
                    }
                    if (s2 == null) {
                        break Label_0041;
                    }
                    break Label_0041;
                }
                catch (NumberFormatException ex2) {
                    throw ex2;
                }
            }
            try {
                if (s2 == null) {
                    return 0;
                }
            }
            catch (NumberFormatException ex3) {
                throw ex3;
            }
        }
        String s3 = b;
        return s3.compareTo(b2);
    }
    
    static {
        final String[] z2 = new String[16];
        int n16;
        int n15;
        int n14;
        int n13;
        int n12;
        int n11;
        int n10;
        int n9;
        int n8;
        int n7;
        int n6;
        int n5;
        int n4;
        int n3;
        int n2;
        int n = n2 = (n3 = (n4 = (n5 = (n6 = (n7 = (n8 = (n9 = (n10 = (n11 = (n12 = (n13 = (n14 = (n15 = (n16 = 0))))))))))))));
        String s = "\fB";
        int n17 = -1;
        String intern = null;
    Label_0190_Outer:
        while (true) {
            final char[] charArray = s.toCharArray();
            int length;
            int n19;
            final int n18 = n19 = (length = charArray.length);
            int n20 = 0;
            while (true) {
                Label_0265: {
                    if (n18 > 1) {
                        break Label_0265;
                    }
                    length = (n19 = n20);
                    do {
                        final char c = charArray[n19];
                        char c2 = '\0';
                        switch (n20 % 5) {
                            case 0: {
                                c2 = '`';
                                break;
                            }
                            case 1: {
                                c2 = '1';
                                break;
                            }
                            case 2: {
                                c2 = '0';
                                break;
                            }
                            case 3: {
                                c2 = '~';
                                break;
                            }
                            default: {
                                c2 = '\u0002';
                                break;
                            }
                        }
                        charArray[length] = (char)(c ^ c2);
                        ++n20;
                    } while (n18 == 0);
                }
                if (n18 > n20) {
                    continue;
                }
                break;
            }
            intern = new String(charArray).intern();
            switch (n17) {
                default: {
                    z2[n2] = intern;
                    n = (n2 = (n3 = (n4 = (n5 = (n6 = (n7 = (n8 = (n9 = (n10 = (n11 = (n12 = (n13 = (n14 = (n15 = (n16 = 1)))))))))))))));
                    s = "\u0005\u0011P\b1\u0013T\u0010";
                    n17 = 0;
                    continue Label_0190_Outer;
                }
                case 0: {
                    z2[n] = intern;
                    n = (n2 = (n3 = (n4 = (n5 = (n6 = (n7 = (n8 = (n9 = (n10 = (n11 = (n12 = (n13 = (n14 = (n15 = (n16 = 2)))))))))))))));
                    s = "^R\u0012\u0019nXH";
                    n17 = 1;
                    continue Label_0190_Outer;
                }
                case 1: {
                    z2[n3] = intern;
                    n = (n2 = (n3 = (n4 = (n5 = (n6 = (n7 = (n8 = (n9 = (n10 = (n11 = (n12 = (n13 = (n14 = (n15 = (n16 = 3)))))))))))))));
                    s = "H\u0016\u0004]1\t^L";
                    n17 = 2;
                    continue Label_0190_Outer;
                }
                case 2: {
                    z2[n4] = intern;
                    n = (n2 = (n3 = (n4 = (n5 = (n6 = (n7 = (n8 = (n9 = (n10 = (n11 = (n12 = (n13 = (n14 = (n15 = (n16 = 4)))))))))))))));
                    s = "@C\u0014\u001a=\u0018\t";
                    n17 = 3;
                    continue Label_0190_Outer;
                }
                case 3: {
                    z2[n5] = intern;
                    n = (n2 = (n3 = (n4 = (n5 = (n6 = (n7 = (n8 = (n9 = (n10 = (n11 = (n12 = (n13 = (n14 = (n15 = (n16 = 5)))))))))))))));
                    s = "\u0019\u0006JM";
                    n17 = 4;
                    continue Label_0190_Outer;
                }
                case 4: {
                    z2[n6] = intern;
                    n = (n2 = (n3 = (n4 = (n5 = (n6 = (n7 = (n8 = (n9 = (n10 = (n11 = (n12 = (n13 = (n14 = (n15 = (n16 = 6)))))))))))))));
                    s = "R\u0004\u0017V>R\u0011";
                    n17 = 5;
                    continue Label_0190_Outer;
                }
                case 5: {
                    z2[n7] = intern;
                    n = (n2 = (n3 = (n4 = (n5 = (n6 = (n7 = (n8 = (n9 = (n10 = (n11 = (n12 = (n13 = (n14 = (n15 = (n16 = 7)))))))))))))));
                    s = "W\u0014\u0010]#I\u0012\u0004D-]";
                    n17 = 6;
                    continue Label_0190_Outer;
                }
                case 6: {
                    z2[n8] = intern;
                    n = (n2 = (n3 = (n4 = (n5 = (n6 = (n7 = (n8 = (n9 = (n10 = (n11 = (n12 = (n13 = (n14 = (n15 = (n16 = 8)))))))))))))));
                    s = "RC\u0015\n&\u001e\u0017SAzX";
                    n17 = 7;
                    continue Label_0190_Outer;
                }
                case 7: {
                    z2[n9] = intern;
                    n = (n2 = (n3 = (n4 = (n5 = (n6 = (n7 = (n8 = (n9 = (n10 = (n11 = (n12 = (n13 = (n14 = (n15 = (n16 = 9)))))))))))))));
                    s = "N\u0003\u001dH";
                    n17 = 8;
                    continue Label_0190_Outer;
                }
                case 8: {
                    z2[n10] = intern;
                    n = (n2 = (n3 = (n4 = (n5 = (n6 = (n7 = (n8 = (n9 = (n10 = (n11 = (n12 = (n13 = (n14 = (n15 = (n16 = 10)))))))))))))));
                    s = "\u001e\u0003";
                    n17 = 9;
                    continue Label_0190_Outer;
                }
                case 9: {
                    z2[n11] = intern;
                    n = (n2 = (n3 = (n4 = (n5 = (n6 = (n7 = (n8 = (n9 = (n10 = (n11 = (n12 = (n13 = (n14 = (n15 = (n16 = 11)))))))))))))));
                    s = "D\u0014\u0001M8T\u0007";
                    n17 = 10;
                    continue Label_0190_Outer;
                }
                case 10: {
                    z2[n12] = intern;
                    n = (n2 = (n3 = (n4 = (n5 = (n6 = (n7 = (n8 = (n9 = (n10 = (n11 = (n12 = (n13 = (n14 = (n15 = (n16 = 12)))))))))))))));
                    s = "E\u0014\u0011M8O\f";
                    n17 = 11;
                    continue Label_0190_Outer;
                }
                case 11: {
                    z2[n13] = intern;
                    n = (n2 = (n3 = (n4 = (n5 = (n6 = (n7 = (n8 = (n9 = (n10 = (n11 = (n12 = (n13 = (n14 = (n15 = (n16 = 13)))))))))))))));
                    s = "WS\u0012\u0001;\u0005\u0014";
                    n17 = 12;
                    continue Label_0190_Outer;
                }
                case 12: {
                    z2[n14] = intern;
                    n = (n2 = (n3 = (n4 = (n5 = (n6 = (n7 = (n8 = (n9 = (n10 = (n11 = (n12 = (n13 = (n14 = (n15 = (n16 = 14)))))))))))))));
                    s = "AC\u0004\u001a=\u0003\u0002";
                    n17 = 13;
                    continue Label_0190_Outer;
                }
                case 13: {
                    z2[n15] = intern;
                    n = (n2 = (n3 = (n4 = (n5 = (n6 = (n7 = (n8 = (n9 = (n10 = (n11 = (n12 = (n13 = (n14 = (n15 = (n16 = 15)))))))))))))));
                    s = "I\u0006";
                    n17 = 14;
                    continue Label_0190_Outer;
                }
                case 14: {
                    break Label_0190_Outer;
                }
            }
        }
        z2[n16] = intern;
        z = z2;
    }
    
    public enum a_
    {
        AGILITY(0, GroundItems.e(a_.z[18])), 
        AIO(1, ""), 
        COMBAT(2, o.a(a_.z[37])), 
        CONSTRUCTION(3, o.a(a_.z[29])), 
        COOKING(4, o.a(a_.z[28])), 
        CRAFTING(5, o.a(a_.z[25])), 
        DUNGEONEERING(6, o.a(a_.z[13])), 
        FARMING(7, o.a(a_.z[3])), 
        FIREMAKING(8, o.a(a_.z[38])), 
        FISHING(9, o.a(a_.z[39])), 
        FLETCHING(10, o.a(a_.z[46])), 
        HERBLORE(11, o.a(a_.z[40])), 
        HUNTER(12, o.a(a_.z[14])), 
        MAGIC(13, o.a(a_.z[36])), 
        MINIGAME(14, o.a(a_.z[15])), 
        MINING(15, o.a(a_.z[10])), 
        MONEY(16, o.a(a_.z[24])), 
        PRAYER(17, o.a(a_.z[17])), 
        QUEST(18, o.a(a_.z[21])), 
        RANGED(19, o.a(a_.z[35])), 
        RUNECRAFTING(20, o.a(a_.z[20])), 
        SMITHING(21, o.a(a_.z[34])), 
        SUMMONING(22, o.a(a_.z[1])), 
        THIEVING(23, o.a(a_.z[9])), 
        WOODCUTTING(24, o.a(a_.z[16]));
        
        public final int index;
        public final String regex;
        private static final String[] z;
        
        private a_(final int index, final String regex) {
            this.index = index;
            this.regex = regex;
        }
        
        static {
            final String[] z2 = new String[49];
            int n49;
            int n48;
            int n47;
            int n46;
            int n45;
            int n44;
            int n43;
            int n42;
            int n41;
            int n40;
            int n39;
            int n38;
            int n37;
            int n36;
            int n35;
            int n34;
            int n33;
            int n32;
            int n31;
            int n30;
            int n29;
            int n28;
            int n27;
            int n26;
            int n25;
            int n24;
            int n23;
            int n22;
            int n21;
            int n20;
            int n19;
            int n18;
            int n17;
            int n16;
            int n15;
            int n14;
            int n13;
            int n12;
            int n11;
            int n10;
            int n9;
            int n8;
            int n7;
            int n6;
            int n5;
            int n4;
            int n3;
            int n2;
            int n = n2 = (n3 = (n4 = (n5 = (n6 = (n7 = (n8 = (n9 = (n10 = (n11 = (n12 = (n13 = (n14 = (n15 = (n16 = (n17 = (n18 = (n19 = (n20 = (n21 = (n22 = (n23 = (n24 = (n25 = (n26 = (n27 = (n28 = (n29 = (n30 = (n31 = (n32 = (n33 = (n34 = (n35 = (n36 = (n37 = (n38 = (n39 = (n40 = (n41 = (n42 = (n43 = (n44 = (n45 = (n46 = (n47 = (n48 = (n49 = 0)))))))))))))))))))))))))))))))))))))))))))))));
            String s = "\rsV\u0002j";
            int n50 = -1;
            String intern = null;
        Label_0553_Outer:
            while (true) {
                final char[] charArray = s.toCharArray();
                int length;
                int n52;
                final int n51 = n52 = (length = charArray.length);
                int n53 = 0;
                while (true) {
                    Label_0630: {
                        if (n51 > 1) {
                            break Label_0630;
                        }
                        length = (n52 = n53);
                        do {
                            final char c = charArray[n52];
                            char c2 = '\0';
                            switch (n53 % 5) {
                                case 0: {
                                    c2 = '\u001f';
                                    break;
                                }
                                case 1: {
                                    c2 = '\u001e';
                                    break;
                                }
                                case 2: {
                                    c2 = 'G';
                                    break;
                                }
                                case 3: {
                                    c2 = 'e';
                                    break;
                                }
                                default: {
                                    c2 = 'l';
                                    break;
                                }
                            }
                            charArray[length] = (char)(c ^ c2);
                            ++n53;
                        } while (n51 == 0);
                    }
                    if (n51 > n53) {
                        continue;
                    }
                    break;
                }
                intern = new String(charArray).intern();
                switch (n50) {
                    default: {
                        z2[n2] = intern;
                        n = (n2 = (n3 = (n4 = (n5 = (n6 = (n7 = (n8 = (n9 = (n10 = (n11 = (n12 = (n13 = (n14 = (n15 = (n16 = (n17 = (n18 = (n19 = (n20 = (n21 = (n22 = (n23 = (n24 = (n25 = (n26 = (n27 = (n28 = (n29 = (n30 = (n31 = (n32 = (n33 = (n34 = (n35 = (n36 = (n37 = (n38 = (n39 = (n40 = (n41 = (n42 = (n43 = (n44 = (n45 = (n46 = (n47 = (n48 = (n49 = 1))))))))))))))))))))))))))))))))))))))))))))))));
                        s = ",8j[";
                        n50 = 0;
                        continue Label_0553_Outer;
                    }
                    case 0: {
                        z2[n] = intern;
                        n = (n2 = (n3 = (n4 = (n5 = (n6 = (n7 = (n8 = (n9 = (n10 = (n11 = (n12 = (n13 = (n14 = (n15 = (n16 = (n17 = (n18 = (n19 = (n20 = (n21 = (n22 = (n23 = (n24 = (n25 = (n26 = (n27 = (n28 = (n29 = (n30 = (n31 = (n32 = (n33 = (n34 = (n35 = (n36 = (n37 = (n38 = (n39 = (n40 = (n41 = (n42 = (n43 = (n44 = (n45 = (n46 = (n47 = (n48 = (n49 = 2))))))))))))))))))))))))))))))))))))))))))))))));
                        s = "\u0017sW\u0003ph\u00151s\u0000\u0007";
                        n50 = 1;
                        continue Label_0553_Outer;
                    }
                    case 1: {
                        z2[n3] = intern;
                        n = (n2 = (n3 = (n4 = (n5 = (n6 = (n7 = (n8 = (n9 = (n10 = (n11 = (n12 = (n13 = (n14 = (n15 = (n16 = (n17 = (n18 = (n19 = (n20 = (n21 = (n22 = (n23 = (n24 = (n25 = (n26 = (n27 = (n28 = (n29 = (n30 = (n31 = (n32 = (n33 = (n34 = (n35 = (n36 = (n37 = (n38 = (n39 = (n40 = (n41 = (n42 = (n43 = (n44 = (n45 = (n46 = (n47 = (n48 = (n49 = 3))))))))))))))))))))))))))))))))))))))))))))))));
                        s = "9,u[";
                        n50 = 2;
                        continue Label_0553_Outer;
                    }
                    case 2: {
                        z2[n4] = intern;
                        n = (n2 = (n3 = (n4 = (n5 = (n6 = (n7 = (n8 = (n9 = (n10 = (n11 = (n12 = (n13 = (n14 = (n15 = (n16 = (n17 = (n18 = (n19 = (n20 = (n21 = (n22 = (n23 = (n24 = (n25 = (n26 = (n27 = (n28 = (n29 = (n30 = (n31 = (n32 = (n33 = (n34 = (n35 = (n36 = (n37 = (n38 = (n39 = (n40 = (n41 = (n42 = (n43 = (n44 = (n45 = (n46 = (n47 = (n48 = (n49 = 4))))))))))))))))))))))))))))))))))))))))))))))));
                        s = "~\u000e(x\u000f\u0014";
                        n50 = 3;
                        continue Label_0553_Outer;
                    }
                    case 3: {
                        z2[n5] = intern;
                        n = (n2 = (n3 = (n4 = (n5 = (n6 = (n7 = (n8 = (n9 = (n10 = (n11 = (n12 = (n13 = (n14 = (n15 = (n16 = (n17 = (n18 = (n19 = (n20 = (n21 = (n22 = (n23 = (n24 = (n25 = (n26 = (n27 = (n28 = (n29 = (n30 = (n31 = (n32 = (n33 = (n34 = (n35 = (n36 = (n37 = (n38 = (n39 = (n40 = (n41 = (n42 = (n43 = (n44 = (n45 = (n46 = (n47 = (n48 = (n49 = 5))))))))))))))))))))))))))))))))))))))))))))))));
                        s = "o\u0014+\u007f\r\u0012}^\u0013zs\u0006";
                        n50 = 4;
                        continue Label_0553_Outer;
                    }
                    case 4: {
                        z2[n6] = intern;
                        n = (n2 = (n3 = (n4 = (n5 = (n6 = (n7 = (n8 = (n9 = (n10 = (n11 = (n12 = (n13 = (n14 = (n15 = (n16 = (n17 = (n18 = (n19 = (n20 = (n21 = (n22 = (n23 = (n24 = (n25 = (n26 = (n27 = (n28 = (n29 = (n30 = (n31 = (n32 = (n33 = (n34 = (n35 = (n36 = (n37 = (n38 = (n39 = (n40 = (n41 = (n42 = (n43 = (n44 = (n45 = (n46 = (n47 = (n48 = (n49 = 6))))))))))))))))))))))))))))))))))))))))))))))));
                        s = "\u0011i]\u0014g";
                        n50 = 5;
                        continue Label_0553_Outer;
                    }
                    case 5: {
                        z2[n7] = intern;
                        n = (n2 = (n3 = (n4 = (n5 = (n6 = (n7 = (n8 = (n9 = (n10 = (n11 = (n12 = (n13 = (n14 = (n15 = (n16 = (n17 = (n18 = (n19 = (n20 = (n21 = (n22 = (n23 = (n24 = (n25 = (n26 = (n27 = (n28 = (n29 = (n30 = (n31 = (n32 = (n33 = (n34 = (n35 = (n36 = (n37 = (n38 = (n39 = (n40 = (n41 = (n42 = (n43 = (n44 = (n45 = (n46 = (n47 = (n48 = (n49 = 7))))))))))))))))))))))))))))))))))))))))))))))));
                        s = "\r\u0019]iv\u000b\u0014";
                        n50 = 6;
                        continue Label_0553_Outer;
                    }
                    case 6: {
                        z2[n8] = intern;
                        n = (n2 = (n3 = (n4 = (n5 = (n6 = (n7 = (n8 = (n9 = (n10 = (n11 = (n12 = (n13 = (n14 = (n15 = (n16 = (n17 = (n18 = (n19 = (n20 = (n21 = (n22 = (n23 = (n24 = (n25 = (n26 = (n27 = (n28 = (n29 = (n30 = (n31 = (n32 = (n33 = (n34 = (n35 = (n36 = (n37 = (n38 = (n39 = (n40 = (n41 = (n42 = (n43 = (n44 = (n45 = (n46 = (n47 = (n48 = (n49 = 8))))))))))))))))))))))))))))))))))))))))))))))));
                        s = "\u0006}J\nzs\u0006";
                        n50 = 7;
                        continue Label_0553_Outer;
                    }
                    case 7: {
                        z2[n9] = intern;
                        n = (n2 = (n3 = (n4 = (n5 = (n6 = (n7 = (n8 = (n9 = (n10 = (n11 = (n12 = (n13 = (n14 = (n15 = (n16 = (n17 = (n18 = (n19 = (n20 = (n21 = (n22 = (n23 = (n24 = (n25 = (n26 = (n27 = (n28 = (n29 = (n30 = (n31 = (n32 = (n33 = (n34 = (n35 = (n36 = (n37 = (n38 = (n39 = (n40 = (n41 = (n42 = (n43 = (n44 = (n45 = (n46 = (n47 = (n48 = (n49 = 9))))))))))))))))))))))))))))))))))))))))))))))));
                        s = "86}@Y#>sSM \"`MV:;";
                        n50 = 8;
                        continue Label_0553_Outer;
                    }
                    case 8: {
                        z2[n10] = intern;
                        n = (n2 = (n3 = (n4 = (n5 = (n6 = (n7 = (n8 = (n9 = (n10 = (n11 = (n12 = (n13 = (n14 = (n15 = (n16 = (n17 = (n18 = (n19 = (n20 = (n21 = (n22 = (n23 = (n24 = (n25 = (n26 = (n27 = (n28 = (n29 = (n30 = (n31 = (n32 = (n33 = (n34 = (n35 = (n36 = (n37 = (n38 = (n39 = (n40 = (n41 = (n42 = (n43 = (n44 = (n45 = (n46 = (n47 = (n48 = (n49 = 10))))))))))))))))))))))))))))))))))))))))))))))));
                        s = "2$iSP#,q";
                        n50 = 9;
                        continue Label_0553_Outer;
                    }
                    case 9: {
                        z2[n11] = intern;
                        n = (n2 = (n3 = (n4 = (n5 = (n6 = (n7 = (n8 = (n9 = (n10 = (n11 = (n12 = (n13 = (n14 = (n15 = (n16 = (n17 = (n18 = (n19 = (n20 = (n21 = (n22 = (n23 = (n24 = (n25 = (n26 = (n27 = (n28 = (n29 = (n30 = (n31 = (n32 = (n33 = (n34 = (n35 = (n36 = (n37 = (n38 = (n39 = (n40 = (n41 = (n42 = (n43 = (n44 = (n45 = (n46 = (n47 = (n48 = (n49 = 11))))))))))))))))))))))))))))))))))))))))))))))));
                        s = "\u0004iV\u0000vr\u000f \u007f\u001c\tr_";
                        n50 = 10;
                        continue Label_0553_Outer;
                    }
                    case 10: {
                        z2[n12] = intern;
                        n = (n2 = (n3 = (n4 = (n5 = (n6 = (n7 = (n8 = (n9 = (n10 = (n11 = (n12 = (n13 = (n14 = (n15 = (n16 = (n17 = (n18 = (n19 = (n20 = (n21 = (n22 = (n23 = (n24 = (n25 = (n26 = (n27 = (n28 = (n29 = (n30 = (n31 = (n32 = (n33 = (n34 = (n35 = (n36 = (n37 = (n38 = (n39 = (n40 = (n41 = (n42 = (n43 = (n44 = (n45 = (n46 = (n47 = (n48 = (n49 = 12))))))))))))))))))))))))))))))))))))))))))))))));
                        s = "p\b+s\t\u0001q]";
                        n50 = 11;
                        continue Label_0553_Outer;
                    }
                    case 11: {
                        z2[n13] = intern;
                        n = (n2 = (n3 = (n4 = (n5 = (n6 = (n7 = (n8 = (n9 = (n10 = (n11 = (n12 = (n13 = (n14 = (n15 = (n16 = (n17 = (n18 = (n19 = (n20 = (n21 = (n22 = (n23 = (n24 = (n25 = (n26 = (n27 = (n28 = (n29 = (n30 = (n31 = (n32 = (n33 = (n34 = (n35 = (n36 = (n37 = (n38 = (n39 = (n40 = (n41 = (n42 = (n43 = (n44 = (n45 = (n46 = (n47 = (n48 = (n49 = 13))))))))))))))))))))))))))))))))))))))))))))))));
                        s = ";8iQ";
                        n50 = 12;
                        continue Label_0553_Outer;
                    }
                    case 12: {
                        z2[n14] = intern;
                        n = (n2 = (n3 = (n4 = (n5 = (n6 = (n7 = (n8 = (n9 = (n10 = (n11 = (n12 = (n13 = (n14 = (n15 = (n16 = (n17 = (n18 = (n19 = (n20 = (n21 = (n22 = (n23 = (n24 = (n25 = (n26 = (n27 = (n28 = (n29 = (n30 = (n31 = (n32 = (n33 = (n34 = (n35 = (n36 = (n37 = (n38 = (n39 = (n40 = (n41 = (n42 = (n43 = (n44 = (n45 = (n46 = (n47 = (n48 = (n49 = 14))))))))))))))))))))))))))))))))))))))))))))))));
                        s = "78iBP/?`FW";
                        n50 = 13;
                        continue Label_0553_Outer;
                    }
                    case 13: {
                        z2[n15] = intern;
                        n = (n2 = (n3 = (n4 = (n5 = (n6 = (n7 = (n8 = (n9 = (n10 = (n11 = (n12 = (n13 = (n14 = (n15 = (n16 = (n17 = (n18 = (n19 = (n20 = (n21 = (n22 = (n23 = (n24 = (n25 = (n26 = (n27 = (n28 = (n29 = (n30 = (n31 = (n32 = (n33 = (n34 = (n35 = (n36 = (n37 = (n38 = (n39 = (n40 = (n41 = (n42 = (n43 = (n44 = (n45 = (n46 = (n47 = (n48 = (n49 = 15))))))))))))))))))))))))))))))))))))))))))))))));
                        s = ",\"uUP<+n_S:1j_B%9uHZ#=bEX0=uUZ";
                        n50 = 14;
                        continue Label_0553_Outer;
                    }
                    case 14: {
                        z2[n16] = intern;
                        n = (n2 = (n3 = (n4 = (n5 = (n6 = (n7 = (n8 = (n9 = (n10 = (n11 = (n12 = (n13 = (n14 = (n15 = (n16 = (n17 = (n18 = (n19 = (n20 = (n21 = (n22 = (n23 = (n24 = (n25 = (n26 = (n27 = (n28 = (n29 = (n30 = (n31 = (n32 = (n33 = (n34 = (n35 = (n36 = (n37 = (n38 = (n39 = (n40 = (n41 = (n42 = (n43 = (n44 = (n45 = (n46 = (n47 = (n48 = (n49 = 16))))))))))))))))))))))))))))))))))))))))))))))));
                        s = ";1{AC<%hF";
                        n50 = 15;
                        continue Label_0553_Outer;
                    }
                    case 15: {
                        z2[n17] = intern;
                        n = (n2 = (n3 = (n4 = (n5 = (n6 = (n7 = (n8 = (n9 = (n10 = (n11 = (n12 = (n13 = (n14 = (n15 = (n16 = (n17 = (n18 = (n19 = (n20 = (n21 = (n22 = (n23 = (n24 = (n25 = (n26 = (n27 = (n28 = (n29 = (n30 = (n31 = (n32 = (n33 = (n34 = (n35 = (n36 = (n37 = (n38 = (n39 = (n40 = (n41 = (n42 = (n43 = (n44 = (n45 = (n46 = (n47 = (n48 = (n49 = 17))))))))))))))))))))))))))))))))))))))))))))))));
                        s = "/?fOP.1z@L";
                        n50 = 16;
                        continue Label_0553_Outer;
                    }
                    case 16: {
                        z2[n18] = intern;
                        n = (n2 = (n3 = (n4 = (n5 = (n6 = (n7 = (n8 = (n9 = (n10 = (n11 = (n12 = (n13 = (n14 = (n15 = (n16 = (n17 = (n18 = (n19 = (n20 = (n21 = (n22 = (n23 = (n24 = (n25 = (n26 = (n27 = (n28 = (n29 = (n30 = (n31 = (n32 = (n33 = (n34 = (n35 = (n36 = (n37 = (n38 = (n39 = (n40 = (n41 = (n42 = (n43 = (n44 = (n45 = (n46 = (n47 = (n48 = (n49 = 18))))))))))))))))))))))))))))))))))))))))))))))));
                        s = "^.\u0010H=%";
                        n50 = 17;
                        continue Label_0553_Outer;
                    }
                    case 17: {
                        z2[n19] = intern;
                        n = (n2 = (n3 = (n4 = (n5 = (n6 = (n7 = (n8 = (n9 = (n10 = (n11 = (n12 = (n13 = (n14 = (n15 = (n16 = (n17 = (n18 = (n19 = (n20 = (n21 = (n22 = (n23 = (n24 = (n25 = (n26 = (n27 = (n28 = (n29 = (n30 = (n31 = (n32 = (n33 = (n34 = (n35 = (n36 = (n37 = (n38 = (n39 = (n40 = (n41 = (n42 = (n43 = (n44 = (n45 = (n46 = (n47 = (n48 = (n49 = 19))))))))))))))))))))))))))))))))))))))))))))))));
                        s = "i\t,\u007f\u0018\tr_";
                        n50 = 18;
                        continue Label_0553_Outer;
                    }
                    case 18: {
                        z2[n20] = intern;
                        n = (n2 = (n3 = (n4 = (n5 = (n6 = (n7 = (n8 = (n9 = (n10 = (n11 = (n12 = (n13 = (n14 = (n15 = (n16 = (n17 = (n18 = (n19 = (n20 = (n21 = (n22 = (n23 = (n24 = (n25 = (n26 = (n27 = (n28 = (n29 = (n30 = (n31 = (n32 = (n33 = (n34 = (n35 = (n36 = (n37 = (n38 = (n39 = (n40 = (n41 = (n42 = (n43 = (n44 = (n45 = (n46 = (n47 = (n48 = (n49 = 20))))))))))))))))))))))))))))))))))))))))))))))));
                        s = "-8iSP)-g";
                        n50 = 19;
                        continue Label_0553_Outer;
                    }
                    case 19: {
                        z2[n21] = intern;
                        n = (n2 = (n3 = (n4 = (n5 = (n6 = (n7 = (n8 = (n9 = (n10 = (n11 = (n12 = (n13 = (n14 = (n15 = (n16 = (n17 = (n18 = (n19 = (n20 = (n21 = (n22 = (n23 = (n24 = (n25 = (n26 = (n27 = (n28 = (n29 = (n30 = (n31 = (n32 = (n33 = (n34 = (n35 = (n36 = (n37 = (n38 = (n39 = (n40 = (n41 = (n42 = (n43 = (n44 = (n45 = (n46 = (n47 = (n48 = (n49 = 21))))))))))))))))))))))))))))))))))))))))))))))));
                        s = "=+qVK";
                        n50 = 20;
                        continue Label_0553_Outer;
                    }
                    case 20: {
                        z2[n22] = intern;
                        n = (n2 = (n3 = (n4 = (n5 = (n6 = (n7 = (n8 = (n9 = (n10 = (n11 = (n12 = (n13 = (n14 = (n15 = (n16 = (n17 = (n18 = (n19 = (n20 = (n21 = (n22 = (n23 = (n24 = (n25 = (n26 = (n27 = (n28 = (n29 = (n30 = (n31 = (n32 = (n33 = (n34 = (n35 = (n36 = (n37 = (n38 = (n39 = (n40 = (n41 = (n42 = (n43 = (n44 = (n45 = (n46 = (n47 = (n48 = (n49 = 22))))))))))))))))))))))))))))))))))))))))))))))));
                        s = "n\f,n\u0006\tr_";
                        n50 = 21;
                        continue Label_0553_Outer;
                    }
                    case 21: {
                        z2[n23] = intern;
                        n = (n2 = (n3 = (n4 = (n5 = (n6 = (n7 = (n8 = (n9 = (n10 = (n11 = (n12 = (n13 = (n14 = (n15 = (n16 = (n17 = (n18 = (n19 = (n20 = (n21 = (n22 = (n23 = (n24 = (n25 = (n26 = (n27 = (n28 = (n29 = (n30 = (n31 = (n32 = (n33 = (n34 = (n35 = (n36 = (n37 = (n38 = (n39 = (n40 = (n41 = (n42 = (n43 = (n44 = (n45 = (n46 = (n47 = (n48 = (n49 = 23))))))))))))))))))))))))))))))))))))))))))))))));
                        s = "\r\u0017[";
                        n50 = 22;
                        continue Label_0553_Outer;
                    }
                    case 22: {
                        z2[n24] = intern;
                        n = (n2 = (n3 = (n4 = (n5 = (n6 = (n7 = (n8 = (n9 = (n10 = (n11 = (n12 = (n13 = (n14 = (n15 = (n16 = (n17 = (n18 = (n19 = (n20 = (n21 = (n22 = (n23 = (n24 = (n25 = (n26 = (n27 = (n28 = (n29 = (n30 = (n31 = (n32 = (n33 = (n34 = (n35 = (n36 = (n37 = (n38 = (n39 = (n40 = (n41 = (n42 = (n43 = (n44 = (n45 = (n46 = (n47 = (n48 = (n49 = 24))))))))))))))))))))))))))))))))))))))))))))))));
                        s = "+.hBP3)";
                        n50 = 23;
                        continue Label_0553_Outer;
                    }
                    case 23: {
                        z2[n25] = intern;
                        n = (n2 = (n3 = (n4 = (n5 = (n6 = (n7 = (n8 = (n9 = (n10 = (n11 = (n12 = (n13 = (n14 = (n15 = (n16 = (n17 = (n18 = (n19 = (n20 = (n21 = (n22 = (n23 = (n24 = (n25 = (n26 = (n27 = (n28 = (n29 = (n30 = (n31 = (n32 = (n33 = (n34 = (n35 = (n36 = (n37 = (n38 = (n39 = (n40 = (n41 = (n42 = (n43 = (n44 = (n45 = (n46 = (n47 = (n48 = (n49 = 25))))))))))))))))))))))))))))))))))))))))))))))));
                        s = "<?fPX0-dLQ#.uC_$\"sWV1){P@-&hSV>!";
                        n50 = 24;
                        continue Label_0553_Outer;
                    }
                    case 24: {
                        z2[n26] = intern;
                        n = (n2 = (n3 = (n4 = (n5 = (n6 = (n7 = (n8 = (n9 = (n10 = (n11 = (n12 = (n13 = (n14 = (n15 = (n16 = (n17 = (n18 = (n19 = (n20 = (n21 = (n22 = (n23 = (n24 = (n25 = (n26 = (n27 = (n28 = (n29 = (n30 = (n31 = (n32 = (n33 = (n34 = (n35 = (n36 = (n37 = (n38 = (n39 = (n40 = (n41 = (n42 = (n43 = (n44 = (n45 = (n46 = (n47 = (n48 = (n49 = 26))))))))))))))))))))))))))))))))))))))))))))))));
                        s = "p\b+s\u0000\u0007";
                        n50 = 25;
                        continue Label_0553_Outer;
                    }
                    case 25: {
                        z2[n27] = intern;
                        n = (n2 = (n3 = (n4 = (n5 = (n6 = (n7 = (n8 = (n9 = (n10 = (n11 = (n12 = (n13 = (n14 = (n15 = (n16 = (n17 = (n18 = (n19 = (n20 = (n21 = (n22 = (n23 = (n24 = (n25 = (n26 = (n27 = (n28 = (n29 = (n30 = (n31 = (n32 = (n33 = (n34 = (n35 = (n36 = (n37 = (n38 = (n39 = (n40 = (n41 = (n42 = (n43 = (n44 = (n45 = (n46 = (n47 = (n48 = (n49 = 27))))))))))))))))))))))))))))))))))))))))))))))));
                        s = "m\u0013$c\u000b\u0012";
                        n50 = 26;
                        continue Label_0553_Outer;
                    }
                    case 26: {
                        z2[n28] = intern;
                        n = (n2 = (n3 = (n4 = (n5 = (n6 = (n7 = (n8 = (n9 = (n10 = (n11 = (n12 = (n13 = (n14 = (n15 = (n16 = (n17 = (n18 = (n19 = (n20 = (n21 = (n22 = (n23 = (n24 = (n25 = (n26 = (n27 = (n28 = (n29 = (n30 = (n31 = (n32 = (n33 = (n34 = (n35 = (n36 = (n37 = (n38 = (n39 = (n40 = (n41 = (n42 = (n43 = (n44 = (n45 = (n46 = (n47 = (n48 = (n49 = 28))))))))))))))))))))))))))))))))))))))))))))))));
                        s = "<\"h]";
                        n50 = 27;
                        continue Label_0553_Outer;
                    }
                    case 27: {
                        z2[n29] = intern;
                        n = (n2 = (n3 = (n4 = (n5 = (n6 = (n7 = (n8 = (n9 = (n10 = (n11 = (n12 = (n13 = (n14 = (n15 = (n16 = (n17 = (n18 = (n19 = (n20 = (n21 = (n22 = (n23 = (n24 = (n25 = (n26 = (n27 = (n28 = (n29 = (n30 = (n31 = (n32 = (n33 = (n34 = (n35 = (n36 = (n37 = (n38 = (n39 = (n40 = (n41 = (n42 = (n43 = (n44 = (n45 = (n46 = (n47 = (n48 = (n49 = 29))))))))))))))))))))))))))))))))))))))))))))))));
                        s = "<\"iEX>";
                        n50 = 28;
                        continue Label_0553_Outer;
                    }
                    case 28: {
                        z2[n30] = intern;
                        n = (n2 = (n3 = (n4 = (n5 = (n6 = (n7 = (n8 = (n9 = (n10 = (n11 = (n12 = (n13 = (n14 = (n15 = (n16 = (n17 = (n18 = (n19 = (n20 = (n21 = (n22 = (n23 = (n24 = (n25 = (n26 = (n27 = (n28 = (n29 = (n30 = (n31 = (n32 = (n33 = (n34 = (n35 = (n36 = (n37 = (n38 = (n39 = (n40 = (n41 = (n42 = (n43 = (n44 = (n45 = (n46 = (n47 = (n48 = (n49 = 30))))))))))))))))))))))))))))))))))))))))))))))));
                        s = "\u0006p]\u0013pu\b+}";
                        n50 = 29;
                        continue Label_0553_Outer;
                    }
                    case 29: {
                        z2[n31] = intern;
                        n = (n2 = (n3 = (n4 = (n5 = (n6 = (n7 = (n8 = (n9 = (n10 = (n11 = (n12 = (n13 = (n14 = (n15 = (n16 = (n17 = (n18 = (n19 = (n20 = (n21 = (n22 = (n23 = (n24 = (n25 = (n26 = (n27 = (n28 = (n29 = (n30 = (n31 = (n32 = (n33 = (n34 = (n35 = (n36 = (n37 = (n38 = (n39 = (n40 = (n41 = (n42 = (n43 = (n44 = (n45 = (n46 = (n47 = (n48 = (n49 = 31))))))))))))))))))))))))))))))))))))))))))))))));
                        s = "~\u0013$|\u001a\tr_";
                        n50 = 30;
                        continue Label_0553_Outer;
                    }
                    case 30: {
                        z2[n32] = intern;
                        n = (n2 = (n3 = (n4 = (n5 = (n6 = (n7 = (n8 = (n9 = (n10 = (n11 = (n12 = (n13 = (n14 = (n15 = (n16 = (n17 = (n18 = (n19 = (n20 = (n21 = (n22 = (n23 = (n24 = (n25 = (n26 = (n27 = (n28 = (n29 = (n30 = (n31 = (n32 = (n33 = (n34 = (n35 = (n36 = (n37 = (n38 = (n39 = (n40 = (n41 = (n42 = (n43 = (n44 = (n45 = (n46 = (n47 = (n48 = (n49 = 32))))))))))))))))))))))))))))))))))))))))))))))));
                        s = "\u0013iU\n|s\b+}";
                        n50 = 31;
                        continue Label_0553_Outer;
                    }
                    case 31: {
                        z2[n33] = intern;
                        n = (n2 = (n3 = (n4 = (n5 = (n6 = (n7 = (n8 = (n9 = (n10 = (n11 = (n12 = (n13 = (n14 = (n15 = (n16 = (n17 = (n18 = (n19 = (n20 = (n21 = (n22 = (n23 = (n24 = (n25 = (n26 = (n27 = (n28 = (n29 = (n30 = (n31 = (n32 = (n33 = (n34 = (n35 = (n36 = (n37 = (n38 = (n39 = (n40 = (n41 = (n42 = (n43 = (n44 = (n45 = (n46 = (n47 = (n48 = (n49 = 33))))))))))))))))))))))))))))))))))))))))))))))));
                        s = "u\u0014+n\u000b\u0012";
                        n50 = 32;
                        continue Label_0553_Outer;
                    }
                    case 32: {
                        z2[n34] = intern;
                        n = (n2 = (n3 = (n4 = (n5 = (n6 = (n7 = (n8 = (n9 = (n10 = (n11 = (n12 = (n13 = (n14 = (n15 = (n16 = (n17 = (n18 = (n19 = (n20 = (n21 = (n22 = (n23 = (n24 = (n25 = (n26 = (n27 = (n28 = (n29 = (n30 = (n31 = (n32 = (n33 = (n34 = (n35 = (n36 = (n37 = (n38 = (n39 = (n40 = (n41 = (n42 = (n43 = (n44 = (n45 = (n46 = (n47 = (n48 = (n49 = 34))))))))))))))))))))))))))))))))))))))))))))))));
                        s = ", nBD0<uWL";
                        n50 = 33;
                        continue Label_0553_Outer;
                    }
                    case 33: {
                        z2[n35] = intern;
                        n = (n2 = (n3 = (n4 = (n5 = (n6 = (n7 = (n8 = (n9 = (n10 = (n11 = (n12 = (n13 = (n14 = (n15 = (n16 = (n17 = (n18 = (n19 = (n20 = (n21 = (n22 = (n23 = (n24 = (n25 = (n26 = (n27 = (n28 = (n29 = (n30 = (n31 = (n32 = (n33 = (n34 = (n35 = (n36 = (n37 = (n38 = (n39 = (n40 = (n41 = (n42 = (n43 = (n44 = (n45 = (n46 = (n47 = (n48 = (n49 = 35))))))))))))))))))))))))))))))))))))))))))))))));
                        s = ">?zBZ#,uDC;";
                        n50 = 34;
                        continue Label_0553_Outer;
                    }
                    case 34: {
                        z2[n36] = intern;
                        n = (n2 = (n3 = (n4 = (n5 = (n6 = (n7 = (n8 = (n9 = (n10 = (n11 = (n12 = (n13 = (n14 = (n15 = (n16 = (n17 = (n18 = (n19 = (n20 = (n21 = (n22 = (n23 = (n24 = (n25 = (n26 = (n27 = (n28 = (n29 = (n30 = (n31 = (n32 = (n33 = (n34 = (n35 = (n36 = (n37 = (n38 = (n39 = (n40 = (n41 = (n42 = (n43 = (n44 = (n45 = (n46 = (n47 = (n48 = (n49 = 36))))))))))))))))))))))))))))))))))))))))))))))));
                        s = "2,`S";
                        n50 = 35;
                        continue Label_0553_Outer;
                    }
                    case 35: {
                        z2[n37] = intern;
                        n = (n2 = (n3 = (n4 = (n5 = (n6 = (n7 = (n8 = (n9 = (n10 = (n11 = (n12 = (n13 = (n14 = (n15 = (n16 = (n17 = (n18 = (n19 = (n20 = (n21 = (n22 = (n23 = (n24 = (n25 = (n26 = (n27 = (n28 = (n29 = (n30 = (n31 = (n32 = (n33 = (n34 = (n35 = (n36 = (n37 = (n38 = (n39 = (n40 = (n41 = (n42 = (n43 = (n44 = (n45 = (n46 = (n47 = (n48 = (n49 = 37))))))))))))))))))))))))))))))))))))))))))))))));
                        s = "9$`^X05}IS#)rS@0-{PS";
                        n50 = 36;
                        continue Label_0553_Outer;
                    }
                    case 36: {
                        z2[n38] = intern;
                        n = (n2 = (n3 = (n4 = (n5 = (n6 = (n7 = (n8 = (n9 = (n10 = (n11 = (n12 = (n13 = (n14 = (n15 = (n16 = (n17 = (n18 = (n19 = (n20 = (n21 = (n22 = (n23 = (n24 = (n25 = (n26 = (n27 = (n28 = (n29 = (n30 = (n31 = (n32 = (n33 = (n34 = (n35 = (n36 = (n37 = (n38 = (n39 = (n40 = (n41 = (n42 = (n43 = (n44 = (n45 = (n46 = (n47 = (n48 = (n49 = 38))))))))))))))))))))))))))))))))))))))))))))))));
                        s = "9$uS";
                        n50 = 37;
                        continue Label_0553_Outer;
                    }
                    case 37: {
                        z2[n39] = intern;
                        n = (n2 = (n3 = (n4 = (n5 = (n6 = (n7 = (n8 = (n9 = (n10 = (n11 = (n12 = (n13 = (n14 = (n15 = (n16 = (n17 = (n18 = (n19 = (n20 = (n21 = (n22 = (n23 = (n24 = (n25 = (n26 = (n27 = (n28 = (n29 = (n30 = (n31 = (n32 = (n33 = (n34 = (n35 = (n36 = (n37 = (n38 = (n39 = (n40 = (n41 = (n42 = (n43 = (n44 = (n45 = (n46 = (n47 = (n48 = (n49 = 39))))))))))))))))))))))))))))))))))))))))))))))));
                        s = "9$t^";
                        n50 = 38;
                        continue Label_0553_Outer;
                    }
                    case 38: {
                        z2[n40] = intern;
                        n = (n2 = (n3 = (n4 = (n5 = (n6 = (n7 = (n8 = (n9 = (n10 = (n11 = (n12 = (n13 = (n14 = (n15 = (n16 = (n17 = (n18 = (n19 = (n20 = (n21 = (n22 = (n23 = (n24 = (n25 = (n26 = (n27 = (n28 = (n29 = (n30 = (n31 = (n32 = (n33 = (n34 = (n35 = (n36 = (n37 = (n38 = (n39 = (n40 = (n41 = (n42 = (n43 = (n44 = (n45 = (n46 = (n47 = (n48 = (n49 = 40))))))))))))))))))))))))))))))))))))))))))))))));
                        s = "7(uTP/2qDQ# nN";
                        n50 = 39;
                        continue Label_0553_Outer;
                    }
                    case 39: {
                        z2[n41] = intern;
                        n = (n2 = (n3 = (n4 = (n5 = (n6 = (n7 = (n8 = (n9 = (n10 = (n11 = (n12 = (n13 = (n14 = (n15 = (n16 = (n17 = (n18 = (n19 = (n20 = (n21 = (n22 = (n23 = (n24 = (n25 = (n26 = (n27 = (n28 = (n29 = (n30 = (n31 = (n32 = (n33 = (n34 = (n35 = (n36 = (n37 = (n38 = (n39 = (n40 = (n41 = (n42 = (n43 = (n44 = (n45 = (n46 = (n47 = (n48 = (n49 = 41))))))))))))))))))))))))))))))))))))))))))))))));
                        s = "~\u000e+i\u001a\u0012i[\u0013zr\u000f";
                        n50 = 40;
                        continue Label_0553_Outer;
                    }
                    case 40: {
                        z2[n42] = intern;
                        n = (n2 = (n3 = (n4 = (n5 = (n6 = (n7 = (n8 = (n9 = (n10 = (n11 = (n12 = (n13 = (n14 = (n15 = (n16 = (n17 = (n18 = (n19 = (n20 = (n21 = (n22 = (n23 = (n24 = (n25 = (n26 = (n27 = (n28 = (n29 = (n30 = (n31 = (n32 = (n33 = (n34 = (n35 = (n36 = (n37 = (n38 = (n39 = (n40 = (n41 = (n42 = (n43 = (n44 = (n45 = (n46 = (n47 = (n48 = (n49 = 42))))))))))))))))))))))))))))))))))))))))))))))));
                        s = "\u0006uK\u000fzs\u0006";
                        n50 = 41;
                        continue Label_0553_Outer;
                    }
                    case 41: {
                        z2[n43] = intern;
                        n = (n2 = (n3 = (n4 = (n5 = (n6 = (n7 = (n8 = (n9 = (n10 = (n11 = (n12 = (n13 = (n14 = (n15 = (n16 = (n17 = (n18 = (n19 = (n20 = (n21 = (n22 = (n23 = (n24 = (n25 = (n26 = (n27 = (n28 = (n29 = (n30 = (n31 = (n32 = (n33 = (n34 = (n35 = (n36 = (n37 = (n38 = (n39 = (n40 = (n41 = (n42 = (n43 = (n44 = (n45 = (n46 = (n47 = (n48 = (n49 = 43))))))))))))))))))))))))))))))))))))))))))))))));
                        s = "\u0003sW\fzs\u0006";
                        n50 = 42;
                        continue Label_0553_Outer;
                    }
                    case 42: {
                        z2[n44] = intern;
                        n = (n2 = (n3 = (n4 = (n5 = (n6 = (n7 = (n8 = (n9 = (n10 = (n11 = (n12 = (n13 = (n14 = (n15 = (n16 = (n17 = (n18 = (n19 = (n20 = (n21 = (n22 = (n23 = (n24 = (n25 = (n26 = (n27 = (n28 = (n29 = (n30 = (n31 = (n32 = (n33 = (n34 = (n35 = (n36 = (n37 = (n38 = (n39 = (n40 = (n41 = (n42 = (n43 = (n44 = (n45 = (n46 = (n47 = (n48 = (n49 = 44))))))))))))))))))))))))))))))))))))))))))))))));
                        s = "o\u0000+}\u000b\u0004";
                        n50 = 43;
                        continue Label_0553_Outer;
                    }
                    case 43: {
                        z2[n45] = intern;
                        n = (n2 = (n3 = (n4 = (n5 = (n6 = (n7 = (n8 = (n9 = (n10 = (n11 = (n12 = (n13 = (n14 = (n15 = (n16 = (n17 = (n18 = (n19 = (n20 = (n21 = (n22 = (n23 = (n24 = (n25 = (n26 = (n27 = (n28 = (n29 = (n30 = (n31 = (n32 = (n33 = (n34 = (n35 = (n36 = (n37 = (n38 = (n39 = (n40 = (n41 = (n42 = (n43 = (n44 = (n45 = (n46 = (n47 = (n48 = (n49 = 45))))))))))))))))))))))))))))))))))))))))))))))));
                        s = "{\b7\u007f\u0003\u0001wQ\tt";
                        n50 = 44;
                        continue Label_0553_Outer;
                    }
                    case 44: {
                        z2[n46] = intern;
                        n = (n2 = (n3 = (n4 = (n5 = (n6 = (n7 = (n8 = (n9 = (n10 = (n11 = (n12 = (n13 = (n14 = (n15 = (n16 = (n17 = (n18 = (n19 = (n20 = (n21 = (n22 = (n23 = (n24 = (n25 = (n26 = (n27 = (n28 = (n29 = (n30 = (n31 = (n32 = (n33 = (n34 = (n35 = (n36 = (n37 = (n38 = (n39 = (n40 = (n41 = (n42 = (n43 = (n44 = (n45 = (n46 = (n47 = (n48 = (n49 = 46))))))))))))))))))))))))))))))))))))))))))))))));
                        s = "9!bBO$";
                        n50 = 45;
                        continue Label_0553_Outer;
                    }
                    case 45: {
                        z2[n47] = intern;
                        n = (n2 = (n3 = (n4 = (n5 = (n6 = (n7 = (n8 = (n9 = (n10 = (n11 = (n12 = (n13 = (n14 = (n15 = (n16 = (n17 = (n18 = (n19 = (n20 = (n21 = (n22 = (n23 = (n24 = (n25 = (n26 = (n27 = (n28 = (n29 = (n30 = (n31 = (n32 = (n33 = (n34 = (n35 = (n36 = (n37 = (n38 = (n39 = (n40 = (n41 = (n42 = (n43 = (n44 = (n45 = (n46 = (n47 = (n48 = (n49 = 47))))))))))))))))))))))))))))))))))))))))))))))));
                        s = "\r}_\u000ep";
                        n50 = 46;
                        continue Label_0553_Outer;
                    }
                    case 46: {
                        z2[n48] = intern;
                        n = (n2 = (n3 = (n4 = (n5 = (n6 = (n7 = (n8 = (n9 = (n10 = (n11 = (n12 = (n13 = (n14 = (n15 = (n16 = (n17 = (n18 = (n19 = (n20 = (n21 = (n22 = (n23 = (n24 = (n25 = (n26 = (n27 = (n28 = (n29 = (n30 = (n31 = (n32 = (n33 = (n34 = (n35 = (n36 = (n37 = (n38 = (n39 = (n40 = (n41 = (n42 = (n43 = (n44 = (n45 = (n46 = (n47 = (n48 = (n49 = 48))))))))))))))))))))))))))))))))))))))))))))))));
                        s = "u\u00047x\u0002\u000fn]";
                        n50 = 47;
                        continue Label_0553_Outer;
                    }
                    case 47: {
                        break Label_0553_Outer;
                    }
                }
            }
            z2[n49] = intern;
            z = z2;
        }
    }
}
