
package org.powerbot;

import java.awt.AWTEvent;
import java.awt.Window;
import java.awt.event.WindowEvent;
import java.util.logging.Level;
import java.util.logging.Logger;
import java.awt.Component;
import javax.swing.JOptionPane;
import org.powerbot.core.script.methods.Game;
import org.powerbot.core.Bot;
import javax.swing.SwingUtilities;
import java.awt.event.ActionEvent;
import javax.swing.JMenuItem;
import java.awt.event.ActionListener;
import javax.swing.JPopupMenu;

public final class yb extends JPopupMenu implements ActionListener
{
    private static final long serialVersionUID = 1L;
    private final JMenuItem a;
    private static final String[] z;
    
    public yb() {
        // 
        // This method could not be decompiled.
        // 
        // Original Bytecode:
        // 
        //     3: istore          11
        //     5: aload_0        
        //     6: invokespecial   javax/swing/JPopupMenu.<init>:()V
        //     9: invokestatic    org/powerbot/core/Bot.instantiated:()Z
        //    12: iload           11
        //    14: ifne            21
        //    17: ifeq            24
        //    20: iconst_1       
        //    21: goto            25
        //    24: iconst_0       
        //    25: istore_1       
        //    26: invokestatic    org/powerbot/k.a:()Lorg/powerbot/k;
        //    29: invokevirtual   org/powerbot/k.c:()I
        //    32: istore_2       
        //    33: new             Ljavax/swing/JMenuItem;
        //    36: dup            
        //    37: getstatic       org/powerbot/yb.z:[Ljava/lang/String;
        //    40: bipush          13
        //    42: aaload         
        //    43: invokestatic    org/powerbot/game/api/util/Time.e:(Ljava/lang/String;)Ljava/lang/String;
        //    46: invokespecial   javax/swing/JMenuItem.<init>:(Ljava/lang/String;)V
        //    49: astore_3       
        //    50: aload_3        
        //    51: getstatic       org/powerbot/j$b_.TAB_ADD:Lorg/powerbot/j$b_;
        //    54: invokestatic    org/powerbot/j.a:(Ljavax/swing/JMenuItem;Lorg/powerbot/j$b_;)V
        //    57: aload_3        
        //    58: new             Ljavax/swing/ImageIcon;
        //    61: dup            
        //    62: getstatic       org/powerbot/yb.z:[Ljava/lang/String;
        //    65: bipush          22
        //    67: aaload         
        //    68: invokestatic    org/powerbot/core/script/wrappers/Item.e:(Ljava/lang/String;)Ljava/lang/String;
        //    71: invokestatic    org/powerbot/db.b:(Ljava/lang/String;)Ljava/awt/Image;
        //    74: invokespecial   javax/swing/ImageIcon.<init>:(Ljava/awt/Image;)V
        //    77: invokevirtual   javax/swing/JMenuItem.setIcon:(Ljavax/swing/Icon;)V
        //    80: aload_3        
        //    81: aload_0        
        //    82: invokevirtual   javax/swing/JMenuItem.addActionListener:(Ljava/awt/event/ActionListener;)V
        //    85: new             Ljavax/swing/JMenuItem;
        //    88: dup            
        //    89: getstatic       org/powerbot/yb.z:[Ljava/lang/String;
        //    92: bipush          6
        //    94: aaload         
        //    95: invokestatic    org/powerbot/game/api/util/Time.e:(Ljava/lang/String;)Ljava/lang/String;
        //    98: invokespecial   javax/swing/JMenuItem.<init>:(Ljava/lang/String;)V
        //   101: astore          4
        //   103: aload           4
        //   105: getstatic       org/powerbot/j$b_.TAB_CLOSE:Lorg/powerbot/j$b_;
        //   108: invokestatic    org/powerbot/j.a:(Ljavax/swing/JMenuItem;Lorg/powerbot/j$b_;)V
        //   111: aload           4
        //   113: new             Ljavax/swing/ImageIcon;
        //   116: dup            
        //   117: getstatic       org/powerbot/yb.z:[Ljava/lang/String;
        //   120: bipush          15
        //   122: aaload         
        //   123: invokestatic    org/powerbot/core/script/wrappers/Item.e:(Ljava/lang/String;)Ljava/lang/String;
        //   126: invokestatic    org/powerbot/db.b:(Ljava/lang/String;)Ljava/awt/Image;
        //   129: invokespecial   javax/swing/ImageIcon.<init>:(Ljava/awt/Image;)V
        //   132: invokevirtual   javax/swing/JMenuItem.setIcon:(Ljavax/swing/Icon;)V
        //   135: aload           4
        //   137: iload_1        
        //   138: iload           11
        //   140: ifne            173
        //   143: ifgt            168
        //   146: goto            150
        //   149: athrow         
        //   150: iload_2        
        //   151: iload           11
        //   153: ifne            173
        //   156: goto            160
        //   159: athrow         
        //   160: iconst_1       
        //   161: if_icmple       176
        //   164: goto            168
        //   167: athrow         
        //   168: iconst_1       
        //   169: goto            173
        //   172: athrow         
        //   173: goto            177
        //   176: iconst_0       
        //   177: invokevirtual   javax/swing/JMenuItem.setEnabled:(Z)V
        //   180: aload           4
        //   182: aload_0        
        //   183: invokevirtual   javax/swing/JMenuItem.addActionListener:(Ljava/awt/event/ActionListener;)V
        //   186: aload_0        
        //   187: aload_3        
        //   188: invokevirtual   org/powerbot/yb.add:(Ljavax/swing/JMenuItem;)Ljavax/swing/JMenuItem;
        //   191: pop            
        //   192: aload_0        
        //   193: aload           4
        //   195: invokevirtual   org/powerbot/yb.add:(Ljavax/swing/JMenuItem;)Ljavax/swing/JMenuItem;
        //   198: pop            
        //   199: aload_0        
        //   200: invokevirtual   org/powerbot/yb.addSeparator:()V
        //   203: new             Ljavax/swing/JMenuItem;
        //   206: dup            
        //   207: getstatic       org/powerbot/yb.z:[Ljava/lang/String;
        //   210: bipush          17
        //   212: aaload         
        //   213: invokestatic    org/powerbot/game/api/util/Time.e:(Ljava/lang/String;)Ljava/lang/String;
        //   216: invokespecial   javax/swing/JMenuItem.<init>:(Ljava/lang/String;)V
        //   219: astore          5
        //   221: aload           5
        //   223: getstatic       org/powerbot/j$b_.ACCOUNTS:Lorg/powerbot/j$b_;
        //   226: invokestatic    org/powerbot/j.a:(Ljavax/swing/JMenuItem;Lorg/powerbot/j$b_;)V
        //   229: aload           5
        //   231: new             Ljavax/swing/ImageIcon;
        //   234: dup            
        //   235: getstatic       org/powerbot/yb.z:[Ljava/lang/String;
        //   238: bipush          25
        //   240: aaload         
        //   241: invokestatic    org/powerbot/core/script/wrappers/Item.e:(Ljava/lang/String;)Ljava/lang/String;
        //   244: invokestatic    org/powerbot/db.b:(Ljava/lang/String;)Ljava/awt/Image;
        //   247: invokespecial   javax/swing/ImageIcon.<init>:(Ljava/awt/Image;)V
        //   250: invokevirtual   javax/swing/JMenuItem.setIcon:(Ljavax/swing/Icon;)V
        //   253: aload           5
        //   255: aload_0        
        //   256: invokevirtual   javax/swing/JMenuItem.addActionListener:(Ljava/awt/event/ActionListener;)V
        //   259: aload_0        
        //   260: aload           5
        //   262: invokevirtual   org/powerbot/yb.add:(Ljavax/swing/JMenuItem;)Ljavax/swing/JMenuItem;
        //   265: pop            
        //   266: aload_0        
        //   267: new             Ljavax/swing/JMenuItem;
        //   270: dup            
        //   271: getstatic       org/powerbot/yb.z:[Ljava/lang/String;
        //   274: bipush          24
        //   276: aaload         
        //   277: invokestatic    org/powerbot/game/api/util/Time.e:(Ljava/lang/String;)Ljava/lang/String;
        //   280: invokespecial   javax/swing/JMenuItem.<init>:(Ljava/lang/String;)V
        //   283: putfield        org/powerbot/yb.a:Ljavax/swing/JMenuItem;
        //   286: aload_0        
        //   287: getfield        org/powerbot/yb.a:Ljavax/swing/JMenuItem;
        //   290: getstatic       org/powerbot/j$b_.SIGNIN:Lorg/powerbot/j$b_;
        //   293: invokestatic    org/powerbot/j.a:(Ljavax/swing/JMenuItem;Lorg/powerbot/j$b_;)V
        //   296: aload_0        
        //   297: getfield        org/powerbot/yb.a:Ljavax/swing/JMenuItem;
        //   300: new             Ljavax/swing/ImageIcon;
        //   303: dup            
        //   304: getstatic       org/powerbot/yb.z:[Ljava/lang/String;
        //   307: bipush          16
        //   309: aaload         
        //   310: invokestatic    org/powerbot/core/script/wrappers/Item.e:(Ljava/lang/String;)Ljava/lang/String;
        //   313: invokestatic    org/powerbot/db.b:(Ljava/lang/String;)Ljava/awt/Image;
        //   316: invokespecial   javax/swing/ImageIcon.<init>:(Ljava/awt/Image;)V
        //   319: invokevirtual   javax/swing/JMenuItem.setIcon:(Ljavax/swing/Icon;)V
        //   322: invokestatic    org/powerbot/v.a:()Lorg/powerbot/v;
        //   325: invokevirtual   org/powerbot/v.b:()Z
        //   328: iload           11
        //   330: ifne            382
        //   333: ifeq            360
        //   336: goto            340
        //   339: athrow         
        //   340: aload_0        
        //   341: getfield        org/powerbot/yb.a:Ljavax/swing/JMenuItem;
        //   344: invokestatic    org/powerbot/v.a:()Lorg/powerbot/v;
        //   347: invokevirtual   org/powerbot/v.c:()Lorg/powerbot/v$a_;
        //   350: invokevirtual   org/powerbot/v$a_.e:()Ljava/lang/String;
        //   353: invokevirtual   javax/swing/JMenuItem.setText:(Ljava/lang/String;)V
        //   356: goto            360
        //   359: athrow         
        //   360: aload_0        
        //   361: aload_0        
        //   362: getfield        org/powerbot/yb.a:Ljavax/swing/JMenuItem;
        //   365: invokevirtual   org/powerbot/yb.add:(Ljavax/swing/JMenuItem;)Ljavax/swing/JMenuItem;
        //   368: pop            
        //   369: aload_0        
        //   370: getfield        org/powerbot/yb.a:Ljavax/swing/JMenuItem;
        //   373: aload_0        
        //   374: invokevirtual   javax/swing/JMenuItem.addActionListener:(Ljava/awt/event/ActionListener;)V
        //   377: aload_0        
        //   378: invokevirtual   org/powerbot/yb.addSeparator:()V
        //   381: iconst_0       
        //   382: istore          6
        //   384: invokestatic    org/powerbot/core/Bot.instantiated:()Z
        //   387: ifeq            461
        //   390: invokestatic    org/powerbot/core/Bot.instance:()Lorg/powerbot/core/Bot;
        //   393: astore          7
        //   395: aload           7
        //   397: invokevirtual   org/powerbot/core/Bot.getScriptHandler:()Lorg/powerbot/core/bot/handlers/ScriptHandler;
        //   400: astore          8
        //   402: aload           8
        //   404: iload           11
        //   406: ifne            418
        //   409: ifnull          458
        //   412: goto            416
        //   415: athrow         
        //   416: aload           8
        //   418: invokevirtual   org/powerbot/core/bot/handlers/ScriptHandler.isActive:()Z
        //   421: iload           11
        //   423: ifne            442
        //   426: ifeq            458
        //   429: goto            433
        //   432: athrow         
        //   433: aload           8
        //   435: invokevirtual   org/powerbot/core/bot/handlers/ScriptHandler.isPaused:()Z
        //   438: goto            442
        //   441: athrow         
        //   442: iload           11
        //   444: ifne            455
        //   447: ifne            458
        //   450: goto            454
        //   453: athrow         
        //   454: iconst_1       
        //   455: goto            459
        //   458: iconst_0       
        //   459: istore          6
        //   461: new             Ljavax/swing/JMenuItem;
        //   464: dup            
        //   465: iload           6
        //   467: ifeq            483
        //   470: getstatic       org/powerbot/yb.z:[Ljava/lang/String;
        //   473: bipush          20
        //   475: aaload         
        //   476: invokestatic    org/powerbot/game/api/util/Time.e:(Ljava/lang/String;)Ljava/lang/String;
        //   479: goto            492
        //   482: athrow         
        //   483: getstatic       org/powerbot/yb.z:[Ljava/lang/String;
        //   486: bipush          19
        //   488: aaload         
        //   489: invokestatic    org/powerbot/core/script/wrappers/Item.e:(Ljava/lang/String;)Ljava/lang/String;
        //   492: invokespecial   javax/swing/JMenuItem.<init>:(Ljava/lang/String;)V
        //   495: astore          7
        //   497: aload           7
        //   499: invokestatic    org/powerbot/core/Bot.instantiated:()Z
        //   502: invokevirtual   javax/swing/JMenuItem.setEnabled:(Z)V
        //   505: aload           7
        //   507: getstatic       org/powerbot/j$b_.SCRIPT_PLAYPAUSE:Lorg/powerbot/j$b_;
        //   510: invokestatic    org/powerbot/j.a:(Ljavax/swing/JMenuItem;Lorg/powerbot/j$b_;)V
        //   513: aload           7
        //   515: new             Ljavax/swing/ImageIcon;
        //   518: dup            
        //   519: iload           6
        //   521: ifeq            537
        //   524: getstatic       org/powerbot/yb.z:[Ljava/lang/String;
        //   527: bipush          10
        //   529: aaload         
        //   530: invokestatic    org/powerbot/game/api/util/Time.e:(Ljava/lang/String;)Ljava/lang/String;
        //   533: goto            546
        //   536: athrow         
        //   537: getstatic       org/powerbot/yb.z:[Ljava/lang/String;
        //   540: bipush          12
        //   542: aaload         
        //   543: invokestatic    org/powerbot/core/script/wrappers/Item.e:(Ljava/lang/String;)Ljava/lang/String;
        //   546: invokestatic    org/powerbot/db.b:(Ljava/lang/String;)Ljava/awt/Image;
        //   549: invokespecial   javax/swing/ImageIcon.<init>:(Ljava/awt/Image;)V
        //   552: invokevirtual   javax/swing/JMenuItem.setIcon:(Ljavax/swing/Icon;)V
        //   555: aload_0        
        //   556: aload           7
        //   558: invokevirtual   org/powerbot/yb.add:(Ljavax/swing/JMenuItem;)Ljavax/swing/JMenuItem;
        //   561: pop            
        //   562: new             Ljavax/swing/JMenuItem;
        //   565: dup            
        //   566: getstatic       org/powerbot/yb.z:[Ljava/lang/String;
        //   569: bipush          21
        //   571: aaload         
        //   572: invokestatic    org/powerbot/game/api/util/Time.e:(Ljava/lang/String;)Ljava/lang/String;
        //   575: invokespecial   javax/swing/JMenuItem.<init>:(Ljava/lang/String;)V
        //   578: astore          8
        //   580: aload           8
        //   582: invokestatic    org/powerbot/core/Bot.instantiated:()Z
        //   585: invokevirtual   javax/swing/JMenuItem.setEnabled:(Z)V
        //   588: aload           8
        //   590: getstatic       org/powerbot/j$b_.SCRIPT_STOP:Lorg/powerbot/j$b_;
        //   593: invokestatic    org/powerbot/j.a:(Ljavax/swing/JMenuItem;Lorg/powerbot/j$b_;)V
        //   596: aload           8
        //   598: new             Ljavax/swing/ImageIcon;
        //   601: dup            
        //   602: getstatic       org/powerbot/yb.z:[Ljava/lang/String;
        //   605: bipush          23
        //   607: aaload         
        //   608: invokestatic    org/powerbot/core/script/wrappers/Item.e:(Ljava/lang/String;)Ljava/lang/String;
        //   611: invokestatic    org/powerbot/db.b:(Ljava/lang/String;)Ljava/awt/Image;
        //   614: invokespecial   javax/swing/ImageIcon.<init>:(Ljava/awt/Image;)V
        //   617: invokevirtual   javax/swing/JMenuItem.setIcon:(Ljavax/swing/Icon;)V
        //   620: aload_0        
        //   621: aload           8
        //   623: invokevirtual   org/powerbot/yb.add:(Ljavax/swing/JMenuItem;)Ljavax/swing/JMenuItem;
        //   626: pop            
        //   627: new             Ljavax/swing/JMenuItem;
        //   630: dup            
        //   631: getstatic       org/powerbot/yb.z:[Ljava/lang/String;
        //   634: bipush          11
        //   636: aaload         
        //   637: invokestatic    org/powerbot/game/api/util/Time.e:(Ljava/lang/String;)Ljava/lang/String;
        //   640: invokespecial   javax/swing/JMenuItem.<init>:(Ljava/lang/String;)V
        //   643: astore          9
        //   645: aload           9
        //   647: iconst_0       
        //   648: invokevirtual   javax/swing/JMenuItem.setVisible:(Z)V
        //   651: aload           9
        //   653: iload           6
        //   655: invokevirtual   javax/swing/JMenuItem.setEnabled:(Z)V
        //   658: aload           9
        //   660: new             Ljavax/swing/ImageIcon;
        //   663: dup            
        //   664: getstatic       org/powerbot/yb.z:[Ljava/lang/String;
        //   667: bipush          18
        //   669: aaload         
        //   670: invokestatic    org/powerbot/core/script/wrappers/Item.e:(Ljava/lang/String;)Ljava/lang/String;
        //   673: invokestatic    org/powerbot/db.b:(Ljava/lang/String;)Ljava/awt/Image;
        //   676: invokespecial   javax/swing/ImageIcon.<init>:(Ljava/awt/Image;)V
        //   679: invokevirtual   javax/swing/JMenuItem.setIcon:(Ljavax/swing/Icon;)V
        //   682: aload_0        
        //   683: aload           9
        //   685: invokevirtual   org/powerbot/yb.add:(Ljavax/swing/JMenuItem;)Ljavax/swing/JMenuItem;
        //   688: pop            
        //   689: aload_0        
        //   690: invokevirtual   org/powerbot/yb.addSeparator:()V
        //   693: aload_0        
        //   694: new             Lorg/powerbot/ub;
        //   697: dup            
        //   698: invokespecial   org/powerbot/ub.<init>:()V
        //   701: invokevirtual   org/powerbot/yb.add:(Ljavax/swing/JMenuItem;)Ljavax/swing/JMenuItem;
        //   704: pop            
        //   705: aload_0        
        //   706: new             Lorg/powerbot/tb;
        //   709: dup            
        //   710: invokespecial   org/powerbot/tb.<init>:()V
        //   713: invokevirtual   org/powerbot/yb.add:(Ljavax/swing/JMenuItem;)Ljavax/swing/JMenuItem;
        //   716: pop            
        //   717: aload_0        
        //   718: invokevirtual   org/powerbot/yb.addSeparator:()V
        //   721: new             Ljavax/swing/JMenuItem;
        //   724: dup            
        //   725: getstatic       org/powerbot/yb.z:[Ljava/lang/String;
        //   728: iconst_0       
        //   729: aaload         
        //   730: invokestatic    org/powerbot/game/api/util/Time.e:(Ljava/lang/String;)Ljava/lang/String;
        //   733: invokespecial   javax/swing/JMenuItem.<init>:(Ljava/lang/String;)V
        //   736: astore          10
        //   738: aload           10
        //   740: getstatic       org/powerbot/j$b_.ABOUT:Lorg/powerbot/j$b_;
        //   743: invokestatic    org/powerbot/j.a:(Ljavax/swing/JMenuItem;Lorg/powerbot/j$b_;)V
        //   746: aload           10
        //   748: new             Ljavax/swing/ImageIcon;
        //   751: dup            
        //   752: getstatic       org/powerbot/yb.z:[Ljava/lang/String;
        //   755: bipush          14
        //   757: aaload         
        //   758: invokestatic    org/powerbot/core/script/wrappers/Item.e:(Ljava/lang/String;)Ljava/lang/String;
        //   761: invokestatic    org/powerbot/db.b:(Ljava/lang/String;)Ljava/awt/Image;
        //   764: invokespecial   javax/swing/ImageIcon.<init>:(Ljava/awt/Image;)V
        //   767: invokevirtual   javax/swing/JMenuItem.setIcon:(Ljavax/swing/Icon;)V
        //   770: aload           10
        //   772: aload_0        
        //   773: invokevirtual   javax/swing/JMenuItem.addActionListener:(Ljava/awt/event/ActionListener;)V
        //   776: aload_0        
        //   777: aload           10
        //   779: invokevirtual   org/powerbot/yb.add:(Ljavax/swing/JMenuItem;)Ljavax/swing/JMenuItem;
        //   782: pop            
        //   783: iload           11
        //   785: ifeq            801
        //   788: getstatic       org/powerbot/core/script/job/Task.a:I
        //   791: istore          12
        //   793: iinc            12, 1
        //   796: iload           12
        //   798: putstatic       org/powerbot/core/script/job/Task.a:I
        //   801: return         
        //    StackMapTable: 00 26 FF 00 15 00 0C 07 00 4B 00 00 00 00 00 00 00 00 00 00 01 00 01 01 02 40 01 FF 00 7B 00 0C 07 00 4B 01 01 07 00 05 07 00 05 00 00 00 00 00 00 01 00 01 07 01 5D 40 07 00 05 48 07 01 5D FF 00 00 00 0C 07 00 4B 01 01 07 00 05 07 00 05 00 00 00 00 00 00 01 00 02 07 00 05 01 46 07 01 5D 40 07 00 05 43 07 01 5D FF 00 00 00 0C 07 00 4B 01 01 07 00 05 07 00 05 00 00 00 00 00 00 01 00 02 07 00 05 01 42 07 00 05 FF 00 00 00 0C 07 00 4B 01 01 07 00 05 07 00 05 00 00 00 00 00 00 01 00 02 07 00 05 01 FF 00 A1 00 0C 07 00 4B 01 01 07 00 05 07 00 05 07 00 05 00 00 00 00 00 01 00 01 07 01 5D 00 52 07 01 5D 00 55 01 FF 00 20 00 0C 07 00 4B 01 01 07 00 05 07 00 05 07 00 05 01 07 00 65 07 00 85 00 00 01 00 01 07 01 5D 00 41 07 00 85 4D 07 01 5D 00 47 07 01 5D 40 01 4A 07 01 5D 00 40 01 02 40 01 FF 00 01 00 0C 07 00 4B 01 01 07 00 05 07 00 05 07 00 05 01 00 00 00 00 01 00 00 54 07 01 5D FF 00 00 00 0C 07 00 4B 01 01 07 00 05 07 00 05 07 00 05 01 00 00 00 00 01 00 02 08 01 CD 08 01 CD FF 00 08 00 0C 07 00 4B 01 01 07 00 05 07 00 05 07 00 05 01 00 00 00 00 01 00 03 08 01 CD 08 01 CD 07 00 93 FF 00 2B 00 0C 07 00 4B 01 01 07 00 05 07 00 05 07 00 05 01 07 00 05 00 00 00 01 00 01 07 01 5D FF 00 00 00 0C 07 00 4B 01 01 07 00 05 07 00 05 07 00 05 01 07 00 05 00 00 00 01 00 03 07 00 05 08 02 03 08 02 03 FF 00 08 00 0C 07 00 4B 01 01 07 00 05 07 00 05 07 00 05 01 07 00 05 00 00 00 01 00 04 07 00 05 08 02 03 08 02 03 07 00 93 FF 00 FE 00 0C 07 00 4B 01 01 07 00 05 07 00 05 07 00 05 01 07 00 05 07 00 05 07 00 05 07 00 05 01 00 00
        //    Exceptions:
        //  Try           Handler
        //  Start  End    Start  End    Type                        
        //  -----  -----  -----  -----  ----------------------------
        //  497    536    536    537    Ljava/lang/RuntimeException;
        //  461    482    482    483    Ljava/lang/RuntimeException;
        //  442    450    453    454    Ljava/lang/RuntimeException;
        //  426    438    441    442    Ljava/lang/RuntimeException;
        //  418    429    432    433    Ljava/lang/RuntimeException;
        //  402    412    415    416    Ljava/lang/RuntimeException;
        //  333    356    359    360    Ljava/lang/RuntimeException;
        //  221    336    339    340    Ljava/lang/RuntimeException;
        //  160    169    172    173    Ljava/lang/RuntimeException;
        //  150    164    167    168    Ljava/lang/RuntimeException;
        //  143    156    159    160    Ljava/lang/RuntimeException;
        //  103    146    149    150    Ljava/lang/RuntimeException;
        // 
        // The error that occurred was:
        // 
        // java.lang.IllegalStateException: Expression is linked from several locations: Label_0150:
        //     at com.strobel.decompiler.ast.Error.expressionLinkedFromMultipleLocations(Error.java:27)
        //     at com.strobel.decompiler.ast.AstOptimizer.mergeDisparateObjectInitializations(AstOptimizer.java:2596)
        //     at com.strobel.decompiler.ast.AstOptimizer.optimize(AstOptimizer.java:235)
        //     at com.strobel.decompiler.ast.AstOptimizer.optimize(AstOptimizer.java:42)
        //     at com.strobel.decompiler.languages.java.ast.AstMethodBodyBuilder.createMethodBody(AstMethodBodyBuilder.java:214)
        //     at com.strobel.decompiler.languages.java.ast.AstMethodBodyBuilder.createMethodBody(AstMethodBodyBuilder.java:99)
        //     at com.strobel.decompiler.languages.java.ast.AstBuilder.createMethodBody(AstBuilder.java:782)
        //     at com.strobel.decompiler.languages.java.ast.AstBuilder.createConstructor(AstBuilder.java:713)
        //     at com.strobel.decompiler.languages.java.ast.AstBuilder.addTypeMembers(AstBuilder.java:549)
        //     at com.strobel.decompiler.languages.java.ast.AstBuilder.createTypeCore(AstBuilder.java:519)
        //     at com.strobel.decompiler.languages.java.ast.AstBuilder.createTypeNoCache(AstBuilder.java:161)
        //     at com.strobel.decompiler.languages.java.ast.AstBuilder.createType(AstBuilder.java:150)
        //     at com.strobel.decompiler.languages.java.ast.AstBuilder.addType(AstBuilder.java:125)
        //     at com.strobel.decompiler.languages.java.JavaLanguage.buildAst(JavaLanguage.java:71)
        //     at com.strobel.decompiler.languages.java.JavaLanguage.decompileType(JavaLanguage.java:59)
        //     at com.strobel.decompiler.DecompilerDriver.decompileType(DecompilerDriver.java:330)
        //     at com.strobel.decompiler.DecompilerDriver.decompileJar(DecompilerDriver.java:251)
        //     at com.strobel.decompiler.DecompilerDriver.main(DecompilerDriver.java:126)
        // 
        throw new IllegalStateException("An error occurred while decompiling this method.");
    }
    
    @Override
    public void actionPerformed(final ActionEvent p0) {
        // 
        // This method could not be decompiled.
        // 
        // Original Bytecode:
        // 
        //     3: istore          4
        //     5: invokestatic    org/powerbot/hb.a:()Lorg/powerbot/hb;
        //     8: getstatic       org/powerbot/yb.z:[Ljava/lang/String;
        //    11: iconst_2       
        //    12: aaload         
        //    13: invokestatic    org/powerbot/game/api/util/Time.e:(Ljava/lang/String;)Ljava/lang/String;
        //    16: aload_1        
        //    17: invokevirtual   java/awt/event/ActionEvent.getActionCommand:()Ljava/lang/String;
        //    20: invokevirtual   org/powerbot/hb.b:(Ljava/lang/String;Ljava/lang/String;)V
        //    23: aload_1        
        //    24: invokevirtual   java/awt/event/ActionEvent.getActionCommand:()Ljava/lang/String;
        //    27: astore_2       
        //    28: iconst_m1      
        //    29: istore_3       
        //    30: aload_2        
        //    31: invokevirtual   java/lang/String.hashCode:()I
        //    34: iload           4
        //    36: ifne            304
        //    39: lookupswitch {
        //          -2072502266: 168
        //            78208: 97
        //          2490196: 203
        //          2587682: 238
        //          63058797: 273
        //          65203672: 132
        //          default: 303
        //        }
        //    96: athrow         
        //    97: aload_2        
        //    98: getstatic       org/powerbot/yb.z:[Ljava/lang/String;
        //   101: iconst_5       
        //   102: aaload         
        //   103: invokestatic    org/powerbot/core/script/wrappers/Item.e:(Ljava/lang/String;)Ljava/lang/String;
        //   106: invokevirtual   java/lang/String.equals:(Ljava/lang/Object;)Z
        //   109: iload           4
        //   111: ifne            304
        //   114: goto            118
        //   117: athrow         
        //   118: ifeq            303
        //   121: goto            125
        //   124: athrow         
        //   125: iconst_0       
        //   126: istore_3       
        //   127: iload           4
        //   129: ifeq            303
        //   132: aload_2        
        //   133: getstatic       org/powerbot/yb.z:[Ljava/lang/String;
        //   136: bipush          6
        //   138: aaload         
        //   139: invokestatic    org/powerbot/game/api/util/Time.e:(Ljava/lang/String;)Ljava/lang/String;
        //   142: invokevirtual   java/lang/String.equals:(Ljava/lang/Object;)Z
        //   145: iload           4
        //   147: ifne            304
        //   150: goto            154
        //   153: athrow         
        //   154: ifeq            303
        //   157: goto            161
        //   160: athrow         
        //   161: iconst_1       
        //   162: istore_3       
        //   163: iload           4
        //   165: ifeq            303
        //   168: aload_2        
        //   169: getstatic       org/powerbot/yb.z:[Ljava/lang/String;
        //   172: iconst_4       
        //   173: aaload         
        //   174: invokestatic    org/powerbot/core/script/wrappers/Item.e:(Ljava/lang/String;)Ljava/lang/String;
        //   177: invokevirtual   java/lang/String.equals:(Ljava/lang/Object;)Z
        //   180: iload           4
        //   182: ifne            304
        //   185: goto            189
        //   188: athrow         
        //   189: ifeq            303
        //   192: goto            196
        //   195: athrow         
        //   196: iconst_2       
        //   197: istore_3       
        //   198: iload           4
        //   200: ifeq            303
        //   203: aload_2        
        //   204: getstatic       org/powerbot/yb.z:[Ljava/lang/String;
        //   207: iconst_3       
        //   208: aaload         
        //   209: invokestatic    org/powerbot/game/api/util/Time.e:(Ljava/lang/String;)Ljava/lang/String;
        //   212: invokevirtual   java/lang/String.equals:(Ljava/lang/Object;)Z
        //   215: iload           4
        //   217: ifne            304
        //   220: goto            224
        //   223: athrow         
        //   224: ifeq            303
        //   227: goto            231
        //   230: athrow         
        //   231: iconst_3       
        //   232: istore_3       
        //   233: iload           4
        //   235: ifeq            303
        //   238: aload_2        
        //   239: getstatic       org/powerbot/yb.z:[Ljava/lang/String;
        //   242: iconst_1       
        //   243: aaload         
        //   244: invokestatic    org/powerbot/core/script/wrappers/Item.e:(Ljava/lang/String;)Ljava/lang/String;
        //   247: invokevirtual   java/lang/String.equals:(Ljava/lang/Object;)Z
        //   250: iload           4
        //   252: ifne            304
        //   255: goto            259
        //   258: athrow         
        //   259: ifeq            303
        //   262: goto            266
        //   265: athrow         
        //   266: iconst_4       
        //   267: istore_3       
        //   268: iload           4
        //   270: ifeq            303
        //   273: aload_2        
        //   274: getstatic       org/powerbot/yb.z:[Ljava/lang/String;
        //   277: iconst_0       
        //   278: aaload         
        //   279: invokestatic    org/powerbot/game/api/util/Time.e:(Ljava/lang/String;)Ljava/lang/String;
        //   282: invokevirtual   java/lang/String.equals:(Ljava/lang/Object;)Z
        //   285: iload           4
        //   287: ifne            304
        //   290: goto            294
        //   293: athrow         
        //   294: ifeq            303
        //   297: goto            301
        //   300: athrow         
        //   301: iconst_5       
        //   302: istore_3       
        //   303: iload_3        
        //   304: tableswitch {
        //                0: 344
        //                1: 356
        //                2: 369
        //                3: 384
        //                4: 396
        //                5: 408
        //          default: 423
        //        }
        //   344: invokestatic    org/powerbot/yb.a:()V
        //   347: iload           4
        //   349: ifeq            448
        //   352: goto            356
        //   355: athrow         
        //   356: iconst_0       
        //   357: invokestatic    org/powerbot/yb.a:(Z)V
        //   360: iload           4
        //   362: ifeq            448
        //   365: goto            369
        //   368: athrow         
        //   369: getstatic       org/powerbot/j$b_.ACCOUNTS:Lorg/powerbot/j$b_;
        //   372: invokestatic    org/powerbot/yb.a:(Lorg/powerbot/j$b_;)V
        //   375: iload           4
        //   377: ifeq            448
        //   380: goto            384
        //   383: athrow         
        //   384: invokestatic    org/powerbot/yb.b:()V
        //   387: iload           4
        //   389: ifeq            448
        //   392: goto            396
        //   395: athrow         
        //   396: invokestatic    org/powerbot/yb.c:()V
        //   399: iload           4
        //   401: ifeq            448
        //   404: goto            408
        //   407: athrow         
        //   408: getstatic       org/powerbot/j$b_.ABOUT:Lorg/powerbot/j$b_;
        //   411: invokestatic    org/powerbot/yb.a:(Lorg/powerbot/j$b_;)V
        //   414: iload           4
        //   416: ifeq            448
        //   419: goto            423
        //   422: athrow         
        //   423: aload_1        
        //   424: invokevirtual   java/awt/event/ActionEvent.getSource:()Ljava/lang/Object;
        //   427: aload_0        
        //   428: getfield        org/powerbot/yb.a:Ljavax/swing/JMenuItem;
        //   431: if_acmpne       448
        //   434: goto            438
        //   437: athrow         
        //   438: getstatic       org/powerbot/j$b_.SIGNIN:Lorg/powerbot/j$b_;
        //   441: invokestatic    org/powerbot/yb.a:(Lorg/powerbot/j$b_;)V
        //   444: goto            448
        //   447: athrow         
        //   448: return         
        //    StackMapTable: 00 32 FF 00 60 00 05 07 00 4B 07 00 90 07 00 93 01 01 00 01 07 01 5D 00 53 07 01 5D 40 01 45 07 01 5D 00 06 54 07 01 5D 40 01 45 07 01 5D 00 06 53 07 01 5D 40 01 45 07 01 5D 00 06 53 07 01 5D 40 01 45 07 01 5D 00 06 53 07 01 5D 40 01 45 07 01 5D 00 06 53 07 01 5D 40 01 45 07 01 5D 00 01 40 01 27 4A 07 01 5D 00 4B 07 01 5D 00 4D 07 01 5D 00 4A 07 01 5D 00 4A 07 01 5D 00 4D 07 01 5D 00 4D 07 01 5D 00 48 07 01 5D 00
        //    Exceptions:
        //  Try           Handler
        //  Start  End    Start  End    Type                        
        //  -----  -----  -----  -----  ----------------------------
        //  423    444    447    448    Ljava/lang/RuntimeException;
        //  408    434    437    438    Ljava/lang/RuntimeException;
        //  396    419    422    423    Ljava/lang/RuntimeException;
        //  384    404    407    408    Ljava/lang/RuntimeException;
        //  369    392    395    396    Ljava/lang/RuntimeException;
        //  356    380    383    384    Ljava/lang/RuntimeException;
        //  344    365    368    369    Ljava/lang/RuntimeException;
        //  304    352    355    356    Ljava/lang/RuntimeException;
        //  273    297    300    301    Ljava/lang/RuntimeException;
        //  268    290    293    294    Ljava/lang/RuntimeException;
        //  238    262    265    266    Ljava/lang/RuntimeException;
        //  233    255    258    259    Ljava/lang/RuntimeException;
        //  203    227    230    231    Ljava/lang/RuntimeException;
        //  198    220    223    224    Ljava/lang/RuntimeException;
        //  168    192    195    196    Ljava/lang/RuntimeException;
        //  163    185    188    189    Ljava/lang/RuntimeException;
        //  132    157    160    161    Ljava/lang/RuntimeException;
        //  127    150    153    154    Ljava/lang/RuntimeException;
        //  97     121    124    125    Ljava/lang/RuntimeException;
        //  39     114    117    118    Ljava/lang/RuntimeException;
        //  30     96     96     97     Ljava/lang/RuntimeException;
        // 
        // The error that occurred was:
        // 
        // java.lang.IllegalStateException: Expression is linked from several locations: Label_0097:
        //     at com.strobel.decompiler.ast.Error.expressionLinkedFromMultipleLocations(Error.java:27)
        //     at com.strobel.decompiler.ast.AstOptimizer.mergeDisparateObjectInitializations(AstOptimizer.java:2596)
        //     at com.strobel.decompiler.ast.AstOptimizer.optimize(AstOptimizer.java:235)
        //     at com.strobel.decompiler.ast.AstOptimizer.optimize(AstOptimizer.java:42)
        //     at com.strobel.decompiler.languages.java.ast.AstMethodBodyBuilder.createMethodBody(AstMethodBodyBuilder.java:214)
        //     at com.strobel.decompiler.languages.java.ast.AstMethodBodyBuilder.createMethodBody(AstMethodBodyBuilder.java:99)
        //     at com.strobel.decompiler.languages.java.ast.AstBuilder.createMethodBody(AstBuilder.java:782)
        //     at com.strobel.decompiler.languages.java.ast.AstBuilder.createMethod(AstBuilder.java:675)
        //     at com.strobel.decompiler.languages.java.ast.AstBuilder.addTypeMembers(AstBuilder.java:552)
        //     at com.strobel.decompiler.languages.java.ast.AstBuilder.createTypeCore(AstBuilder.java:519)
        //     at com.strobel.decompiler.languages.java.ast.AstBuilder.createTypeNoCache(AstBuilder.java:161)
        //     at com.strobel.decompiler.languages.java.ast.AstBuilder.createType(AstBuilder.java:150)
        //     at com.strobel.decompiler.languages.java.ast.AstBuilder.addType(AstBuilder.java:125)
        //     at com.strobel.decompiler.languages.java.JavaLanguage.buildAst(JavaLanguage.java:71)
        //     at com.strobel.decompiler.languages.java.JavaLanguage.decompileType(JavaLanguage.java:59)
        //     at com.strobel.decompiler.DecompilerDriver.decompileType(DecompilerDriver.java:330)
        //     at com.strobel.decompiler.DecompilerDriver.decompileJar(DecompilerDriver.java:251)
        //     at com.strobel.decompiler.DecompilerDriver.main(DecompilerDriver.java:126)
        // 
        throw new IllegalStateException("An error occurred while decompiling this method.");
    }
    
    public static void a(final j.b_ b_) {
        SwingUtilities.invokeLater(new Runnable() {
            final /* synthetic */ qb val$chrome = qb.a();
            
            @Override
            public void run() {
                // 
                // This method could not be decompiled.
                // 
                // Original Bytecode:
                // 
                //     3: istore_1       
                //     4: iload_1        
                //     5: ifne            61
                //     8: getstatic       org/powerbot/yb$2.a:[I
                //    11: aload_0        
                //    12: getfield        org/powerbot/yb$4.val$action:Lorg/powerbot/j$b_;
                //    15: invokevirtual   org/powerbot/j$b_.ordinal:()I
                //    18: iaload         
                //    19: tableswitch {
                //                2: 45
                //                3: 65
                //                4: 85
                //          default: 101
                //        }
                //    44: athrow         
                //    45: new             Lorg/powerbot/mb;
                //    48: dup            
                //    49: aload_0        
                //    50: getfield        org/powerbot/yb$4.val$chrome:Lorg/powerbot/qb;
                //    53: invokespecial   org/powerbot/mb.<init>:(Lorg/powerbot/qb;)V
                //    56: pop            
                //    57: goto            61
                //    60: athrow         
                //    61: iload_1        
                //    62: ifeq            101
                //    65: new             Lorg/powerbot/pb;
                //    68: dup            
                //    69: aload_0        
                //    70: getfield        org/powerbot/yb$4.val$chrome:Lorg/powerbot/qb;
                //    73: invokespecial   org/powerbot/pb.<init>:(Lorg/powerbot/qb;)V
                //    76: pop            
                //    77: iload_1        
                //    78: ifeq            101
                //    81: goto            85
                //    84: athrow         
                //    85: new             Lorg/powerbot/lb;
                //    88: dup            
                //    89: aload_0        
                //    90: getfield        org/powerbot/yb$4.val$chrome:Lorg/powerbot/qb;
                //    93: invokespecial   org/powerbot/lb.<init>:(Ljava/awt/Frame;)V
                //    96: pop            
                //    97: goto            101
                //   100: athrow         
                //   101: return         
                //    StackMapTable: 00 09 FF 00 2C 00 02 07 00 0C 01 00 01 07 00 41 00 4E 07 00 41 00 03 52 07 00 41 00 4E 07 00 41 00
                //    Exceptions:
                //  Try           Handler
                //  Start  End    Start  End    Type                        
                //  -----  -----  -----  -----  ----------------------------
                //  65     100    100    101    Ljava/lang/RuntimeException;
                //  61     81     84     85     Ljava/lang/RuntimeException;
                //  8      57     60     61     Ljava/lang/RuntimeException;
                //  4      44     44     45     Ljava/lang/RuntimeException;
                // 
                // The error that occurred was:
                // 
                // java.lang.IllegalStateException: Expression is linked from several locations: Label_0065:
                //     at com.strobel.decompiler.ast.Error.expressionLinkedFromMultipleLocations(Error.java:27)
                //     at com.strobel.decompiler.ast.AstOptimizer.mergeDisparateObjectInitializations(AstOptimizer.java:2596)
                //     at com.strobel.decompiler.ast.AstOptimizer.optimize(AstOptimizer.java:235)
                //     at com.strobel.decompiler.ast.AstOptimizer.optimize(AstOptimizer.java:42)
                //     at com.strobel.decompiler.languages.java.ast.AstMethodBodyBuilder.createMethodBody(AstMethodBodyBuilder.java:214)
                //     at com.strobel.decompiler.languages.java.ast.AstMethodBodyBuilder.createMethodBody(AstMethodBodyBuilder.java:99)
                //     at com.strobel.decompiler.languages.java.ast.AstBuilder.createMethodBody(AstBuilder.java:782)
                //     at com.strobel.decompiler.languages.java.ast.AstBuilder.createMethod(AstBuilder.java:675)
                //     at com.strobel.decompiler.languages.java.ast.AstBuilder.addTypeMembers(AstBuilder.java:552)
                //     at com.strobel.decompiler.languages.java.ast.AstBuilder.createTypeCore(AstBuilder.java:519)
                //     at com.strobel.decompiler.languages.java.ast.AstBuilder.createTypeNoCache(AstBuilder.java:161)
                //     at com.strobel.decompiler.languages.java.ast.AstBuilder.createType(AstBuilder.java:150)
                //     at com.strobel.decompiler.languages.java.ast.AstMethodBodyBuilder.transformCall(AstMethodBodyBuilder.java:1164)
                //     at com.strobel.decompiler.languages.java.ast.AstMethodBodyBuilder.transformByteCode(AstMethodBodyBuilder.java:1009)
                //     at com.strobel.decompiler.languages.java.ast.AstMethodBodyBuilder.transformExpression(AstMethodBodyBuilder.java:540)
                //     at com.strobel.decompiler.languages.java.ast.AstMethodBodyBuilder.transformByteCode(AstMethodBodyBuilder.java:554)
                //     at com.strobel.decompiler.languages.java.ast.AstMethodBodyBuilder.transformExpression(AstMethodBodyBuilder.java:540)
                //     at com.strobel.decompiler.languages.java.ast.AstMethodBodyBuilder.transformNode(AstMethodBodyBuilder.java:392)
                //     at com.strobel.decompiler.languages.java.ast.AstMethodBodyBuilder.transformBlock(AstMethodBodyBuilder.java:333)
                //     at com.strobel.decompiler.languages.java.ast.AstMethodBodyBuilder.createMethodBody(AstMethodBodyBuilder.java:294)
                //     at com.strobel.decompiler.languages.java.ast.AstMethodBodyBuilder.createMethodBody(AstMethodBodyBuilder.java:99)
                //     at com.strobel.decompiler.languages.java.ast.AstBuilder.createMethodBody(AstBuilder.java:782)
                //     at com.strobel.decompiler.languages.java.ast.AstBuilder.createMethod(AstBuilder.java:675)
                //     at com.strobel.decompiler.languages.java.ast.AstBuilder.addTypeMembers(AstBuilder.java:552)
                //     at com.strobel.decompiler.languages.java.ast.AstBuilder.createTypeCore(AstBuilder.java:519)
                //     at com.strobel.decompiler.languages.java.ast.AstBuilder.createTypeNoCache(AstBuilder.java:161)
                //     at com.strobel.decompiler.languages.java.ast.AstBuilder.createType(AstBuilder.java:150)
                //     at com.strobel.decompiler.languages.java.ast.AstBuilder.addType(AstBuilder.java:125)
                //     at com.strobel.decompiler.languages.java.JavaLanguage.buildAst(JavaLanguage.java:71)
                //     at com.strobel.decompiler.languages.java.JavaLanguage.decompileType(JavaLanguage.java:59)
                //     at com.strobel.decompiler.DecompilerDriver.decompileType(DecompilerDriver.java:330)
                //     at com.strobel.decompiler.DecompilerDriver.decompileJar(DecompilerDriver.java:251)
                //     at com.strobel.decompiler.DecompilerDriver.main(DecompilerDriver.java:126)
                // 
                throw new IllegalStateException("An error occurred while decompiling this method.");
            }
        });
    }
    
    public static synchronized void a() {
        SwingUtilities.invokeLater(new Runnable() {
            private static final String[] z;
            
            @Override
            public void run() {
                // 
                // This method could not be decompiled.
                // 
                // Original Bytecode:
                // 
                //     3: istore          5
                //     5: invokestatic    org/powerbot/core/Bot.instantiated:()Z
                //     8: iload           5
                //    10: ifne            21
                //    13: ifeq            24
                //    16: goto            20
                //    19: athrow         
                //    20: iconst_1       
                //    21: goto            25
                //    24: iconst_0       
                //    25: istore_1       
                //    26: invokestatic    org/powerbot/k.a:()Lorg/powerbot/k;
                //    29: invokevirtual   org/powerbot/k.c:()I
                //    32: istore_2       
                //    33: ldc             Lorg/powerbot/qb;.class
                //    35: invokevirtual   java/lang/Class.getName:()Ljava/lang/String;
                //    38: invokestatic    java/util/logging/Logger.getLogger:(Ljava/lang/String;)Ljava/util/logging/Logger;
                //    41: astore_3       
                //    42: aload_3        
                //    43: getstatic       org/powerbot/yb$1.z:[Ljava/lang/String;
                //    46: iconst_3       
                //    47: aaload         
                //    48: invokestatic    org/powerbot/game/api/util/SkillData.e:(Ljava/lang/String;)Ljava/lang/String;
                //    51: invokevirtual   java/util/logging/Logger.info:(Ljava/lang/String;)V
                //    54: invokestatic    org/powerbot/v.a:()Lorg/powerbot/v;
                //    57: iconst_1       
                //    58: invokevirtual   org/powerbot/v.a:(I)Z
                //    61: iload           5
                //    63: ifne            118
                //    66: ifne            113
                //    69: goto            73
                //    72: athrow         
                //    73: invokestatic    org/powerbot/y.a:()Z
                //    76: iload           5
                //    78: ifne            118
                //    81: goto            85
                //    84: athrow         
                //    85: ifeq            113
                //    88: goto            92
                //    91: athrow         
                //    92: aload_3        
                //    93: getstatic       org/powerbot/yb$1.z:[Ljava/lang/String;
                //    96: iconst_4       
                //    97: aaload         
                //    98: invokestatic    org/powerbot/t.b:(Ljava/lang/String;)Ljava/lang/String;
                //   101: invokevirtual   java/util/logging/Logger.info:(Ljava/lang/String;)V
                //   104: iload           5
                //   106: ifeq            315
                //   109: goto            113
                //   112: athrow         
                //   113: iload_2        
                //   114: goto            118
                //   117: athrow         
                //   118: iload           5
                //   120: ifne            178
                //   123: ifle            173
                //   126: goto            130
                //   129: athrow         
                //   130: invokestatic    org/powerbot/v.a:()Lorg/powerbot/v;
                //   133: invokevirtual   org/powerbot/v.b:()Z
                //   136: iload           5
                //   138: ifne            178
                //   141: goto            145
                //   144: athrow         
                //   145: ifne            173
                //   148: goto            152
                //   151: athrow         
                //   152: aload_3        
                //   153: getstatic       org/powerbot/yb$1.z:[Ljava/lang/String;
                //   156: iconst_2       
                //   157: aaload         
                //   158: invokestatic    org/powerbot/game/api/util/SkillData.e:(Ljava/lang/String;)Ljava/lang/String;
                //   161: invokevirtual   java/util/logging/Logger.severe:(Ljava/lang/String;)V
                //   164: iload           5
                //   166: ifeq            315
                //   169: goto            173
                //   172: athrow         
                //   173: iload_2        
                //   174: goto            178
                //   177: athrow         
                //   178: iload           5
                //   180: ifne            271
                //   183: iconst_2       
                //   184: if_icmple       235
                //   187: goto            191
                //   190: athrow         
                //   191: invokestatic    org/powerbot/v.a:()Lorg/powerbot/v;
                //   194: iconst_1       
                //   195: invokevirtual   org/powerbot/v.a:(I)Z
                //   198: iload           5
                //   200: ifne            271
                //   203: goto            207
                //   206: athrow         
                //   207: ifne            235
                //   210: goto            214
                //   213: athrow         
                //   214: aload_3        
                //   215: getstatic       org/powerbot/yb$1.z:[Ljava/lang/String;
                //   218: iconst_0       
                //   219: aaload         
                //   220: invokestatic    org/powerbot/t.b:(Ljava/lang/String;)Ljava/lang/String;
                //   223: invokevirtual   java/util/logging/Logger.severe:(Ljava/lang/String;)V
                //   226: iload           5
                //   228: ifeq            315
                //   231: goto            235
                //   234: athrow         
                //   235: invokestatic    org/powerbot/hb.a:()Lorg/powerbot/hb;
                //   238: getstatic       org/powerbot/yb$1.z:[Ljava/lang/String;
                //   241: iconst_1       
                //   242: aaload         
                //   243: invokestatic    org/powerbot/game/api/util/SkillData.e:(Ljava/lang/String;)Ljava/lang/String;
                //   246: getstatic       org/powerbot/yb$1.z:[Ljava/lang/String;
                //   249: iconst_5       
                //   250: aaload         
                //   251: invokestatic    org/powerbot/t.b:(Ljava/lang/String;)Ljava/lang/String;
                //   254: invokevirtual   org/powerbot/hb.a:(Ljava/lang/String;Ljava/lang/String;)V
                //   257: iload           5
                //   259: ifne            277
                //   262: goto            266
                //   265: athrow         
                //   266: iload_1        
                //   267: goto            271
                //   270: athrow         
                //   271: ifle            282
                //   274: invokestatic    org/powerbot/Boot.a:()V
                //   277: iload           5
                //   279: ifeq            315
                //   282: invokestatic    org/powerbot/core/Bot.instance:()Lorg/powerbot/core/Bot;
                //   285: astore          4
                //   287: new             Ljava/lang/Thread;
                //   290: dup            
                //   291: aload           4
                //   293: getfield        org/powerbot/core/Bot.threadGroup:Ljava/lang/ThreadGroup;
                //   296: aload           4
                //   298: invokespecial   java/lang/Thread.<init>:(Ljava/lang/ThreadGroup;Ljava/lang/Runnable;)V
                //   301: invokevirtual   java/lang/Thread.start:()V
                //   304: invokestatic    org/powerbot/qb.a:()Lorg/powerbot/qb;
                //   307: getfield        org/powerbot/qb.c:Lorg/powerbot/wb;
                //   310: aload           4
                //   312: invokevirtual   org/powerbot/wb.a:(Lorg/powerbot/core/Bot;)V
                //   315: return         
                //    StackMapTable: 00 28 FF 00 13 00 06 07 00 19 00 00 00 00 01 00 01 07 00 8A 00 40 01 02 40 01 FF 00 2E 00 06 07 00 19 01 01 07 00 2C 00 01 00 01 07 00 8A 00 4A 07 00 8A 40 01 45 07 00 8A 00 53 07 00 8A 00 43 07 00 8A 40 01 4A 07 00 8A 00 4D 07 00 8A 40 01 45 07 00 8A 00 53 07 00 8A 00 43 07 00 8A 40 01 4B 07 00 8A 00 4E 07 00 8A 40 01 45 07 00 8A 00 53 07 00 8A 00 5D 07 00 8A 00 43 07 00 8A 40 01 05 04 20
                //    Exceptions:
                //  Try           Handler
                //  Start  End    Start  End    Type                        
                //  -----  -----  -----  -----  ----------------------------
                //  235    267    270    271    Ljava/lang/RuntimeException;
                //  214    262    265    266    Ljava/lang/RuntimeException;
                //  207    231    234    235    Ljava/lang/RuntimeException;
                //  191    210    213    214    Ljava/lang/RuntimeException;
                //  183    203    206    207    Ljava/lang/RuntimeException;
                //  178    187    190    191    Ljava/lang/RuntimeException;
                //  152    174    177    178    Ljava/lang/RuntimeException;
                //  145    169    172    173    Ljava/lang/RuntimeException;
                //  130    148    151    152    Ljava/lang/RuntimeException;
                //  123    141    144    145    Ljava/lang/RuntimeException;
                //  118    126    129    130    Ljava/lang/RuntimeException;
                //  92     114    117    118    Ljava/lang/RuntimeException;
                //  85     109    112    113    Ljava/lang/RuntimeException;
                //  73     88     91     92     Ljava/lang/RuntimeException;
                //  66     81     84     85     Ljava/lang/RuntimeException;
                //  42     69     72     73     Ljava/lang/RuntimeException;
                //  5      16     19     20     Ljava/lang/RuntimeException;
                // 
                // The error that occurred was:
                // 
                // java.lang.IllegalStateException: Expression is linked from several locations: Label_0073:
                //     at com.strobel.decompiler.ast.Error.expressionLinkedFromMultipleLocations(Error.java:27)
                //     at com.strobel.decompiler.ast.AstOptimizer.mergeDisparateObjectInitializations(AstOptimizer.java:2596)
                //     at com.strobel.decompiler.ast.AstOptimizer.optimize(AstOptimizer.java:235)
                //     at com.strobel.decompiler.ast.AstOptimizer.optimize(AstOptimizer.java:42)
                //     at com.strobel.decompiler.languages.java.ast.AstMethodBodyBuilder.createMethodBody(AstMethodBodyBuilder.java:214)
                //     at com.strobel.decompiler.languages.java.ast.AstMethodBodyBuilder.createMethodBody(AstMethodBodyBuilder.java:99)
                //     at com.strobel.decompiler.languages.java.ast.AstBuilder.createMethodBody(AstBuilder.java:782)
                //     at com.strobel.decompiler.languages.java.ast.AstBuilder.createMethod(AstBuilder.java:675)
                //     at com.strobel.decompiler.languages.java.ast.AstBuilder.addTypeMembers(AstBuilder.java:552)
                //     at com.strobel.decompiler.languages.java.ast.AstBuilder.createTypeCore(AstBuilder.java:519)
                //     at com.strobel.decompiler.languages.java.ast.AstBuilder.createTypeNoCache(AstBuilder.java:161)
                //     at com.strobel.decompiler.languages.java.ast.AstBuilder.createType(AstBuilder.java:150)
                //     at com.strobel.decompiler.languages.java.ast.AstMethodBodyBuilder.transformCall(AstMethodBodyBuilder.java:1164)
                //     at com.strobel.decompiler.languages.java.ast.AstMethodBodyBuilder.transformByteCode(AstMethodBodyBuilder.java:1009)
                //     at com.strobel.decompiler.languages.java.ast.AstMethodBodyBuilder.transformExpression(AstMethodBodyBuilder.java:540)
                //     at com.strobel.decompiler.languages.java.ast.AstMethodBodyBuilder.transformByteCode(AstMethodBodyBuilder.java:554)
                //     at com.strobel.decompiler.languages.java.ast.AstMethodBodyBuilder.transformExpression(AstMethodBodyBuilder.java:540)
                //     at com.strobel.decompiler.languages.java.ast.AstMethodBodyBuilder.transformNode(AstMethodBodyBuilder.java:392)
                //     at com.strobel.decompiler.languages.java.ast.AstMethodBodyBuilder.transformBlock(AstMethodBodyBuilder.java:333)
                //     at com.strobel.decompiler.languages.java.ast.AstMethodBodyBuilder.createMethodBody(AstMethodBodyBuilder.java:294)
                //     at com.strobel.decompiler.languages.java.ast.AstMethodBodyBuilder.createMethodBody(AstMethodBodyBuilder.java:99)
                //     at com.strobel.decompiler.languages.java.ast.AstBuilder.createMethodBody(AstBuilder.java:782)
                //     at com.strobel.decompiler.languages.java.ast.AstBuilder.createMethod(AstBuilder.java:675)
                //     at com.strobel.decompiler.languages.java.ast.AstBuilder.addTypeMembers(AstBuilder.java:552)
                //     at com.strobel.decompiler.languages.java.ast.AstBuilder.createTypeCore(AstBuilder.java:519)
                //     at com.strobel.decompiler.languages.java.ast.AstBuilder.createTypeNoCache(AstBuilder.java:161)
                //     at com.strobel.decompiler.languages.java.ast.AstBuilder.createType(AstBuilder.java:150)
                //     at com.strobel.decompiler.languages.java.ast.AstBuilder.addType(AstBuilder.java:125)
                //     at com.strobel.decompiler.languages.java.JavaLanguage.buildAst(JavaLanguage.java:71)
                //     at com.strobel.decompiler.languages.java.JavaLanguage.decompileType(JavaLanguage.java:59)
                //     at com.strobel.decompiler.DecompilerDriver.decompileType(DecompilerDriver.java:330)
                //     at com.strobel.decompiler.DecompilerDriver.decompileJar(DecompilerDriver.java:251)
                //     at com.strobel.decompiler.DecompilerDriver.main(DecompilerDriver.java:126)
                // 
                throw new IllegalStateException("An error occurred while decompiling this method.");
            }
            
            static {
                final String[] z2 = new String[6];
                int n6;
                int n5;
                int n4;
                int n3;
                int n2;
                int n = n2 = (n3 = (n4 = (n5 = (n6 = 0))));
                String s = "~h\u007f\u0006~\u00180<s\u0001Rg}_1>\u001c\u0002 L^tv_*/\u001b\u001f.";
                int n7 = -1;
                String intern = null;
            Label_0081_Outer:
                while (true) {
                    final char[] charArray = s.toCharArray();
                    int length;
                    int n9;
                    final int n8 = n9 = (length = charArray.length);
                    int n10 = 0;
                    while (true) {
                        Label_0157: {
                            if (n8 > 1) {
                                break Label_0157;
                            }
                            length = (n9 = n10);
                            do {
                                final char c = charArray[n9];
                                char c2 = '\0';
                                switch (n10 % 5) {
                                    case 0: {
                                        c2 = '&';
                                        break;
                                    }
                                    case 1: {
                                        c2 = 'n';
                                        break;
                                    }
                                    case 2: {
                                        c2 = '\u0004';
                                        break;
                                    }
                                    case 3: {
                                        c2 = '\u0017';
                                        break;
                                    }
                                    default: {
                                        c2 = 'I';
                                        break;
                                    }
                                }
                                charArray[length] = (char)(c ^ c2);
                                ++n10;
                            } while (n8 == 0);
                        }
                        if (n8 > n10) {
                            continue;
                        }
                        break;
                    }
                    intern = new String(charArray).intern();
                    switch (n7) {
                        default: {
                            z2[n2] = intern;
                            n = (n2 = (n3 = (n4 = (n5 = (n6 = 1)))));
                            s = "oU[";
                            n7 = 0;
                            continue Label_0081_Outer;
                        }
                        case 0: {
                            z2[n] = intern;
                            n = (n2 = (n3 = (n4 = (n5 = (n6 = 2)))));
                            s = "KX\\,\u0007\u0019s-Ctu\u0014P#T\b<~Ec~Z\u0019 \u001b\u000e6~^ryG\u0017";
                            n7 = 1;
                            continue Label_0081_Outer;
                        }
                        case 1: {
                            z2[n3] = intern;
                            n = (n2 = (n3 = (n4 = (n5 = (n6 = 3)))));
                            s = "W[X)\u001d\u00124~K3uQNm\u0016\u0013'";
                            n7 = 2;
                            continue Label_0081_Outer;
                        }
                        case 2: {
                            z2[n4] = intern;
                            n = (n2 = (n3 = (n4 = (n5 = (n6 = 4)))));
                            s = "\u0001\u0017\u0000y\u0001gOC\f~-\u0018\u0002 SDh3\u000b6+Y\u000eoU\u0011i}_?n/<S\u000ebca\t;<W";
                            n7 = 3;
                            continue Label_0081_Outer;
                        }
                        case 3: {
                            z2[n5] = intern;
                            n = (n2 = (n3 = (n4 = (n5 = (n6 = 5)))));
                            s = "Pbw";
                            n7 = 4;
                            continue Label_0081_Outer;
                        }
                        case 4: {
                            break Label_0081_Outer;
                        }
                    }
                }
                z2[n6] = intern;
                z = z2;
            }
        });
    }
    
    public static synchronized void a(final boolean b) {
        SwingUtilities.invokeLater(new Runnable() {
            private static final String[] z;
            
            @Override
            public void run() {
                final boolean f = wb.f;
                final qb a = qb.a();
                Label_0187: {
                    if (!Bot.instantiated()) {
                        break Label_0187;
                    }
                    final qb a2 = qb.a();
                    Label_0125: {
                        hb a3 = null;
                        String a4 = null;
                        String a5 = null;
                        Label_0085: {
                            Label_0038: {
                                try {
                                    final int n;
                                    final boolean loggedIn;
                                    final boolean b = loggedIn = ((n = (b ? 1 : 0)) != 0);
                                    if (f) {
                                        break Label_0038;
                                    }
                                    if (b) {
                                        break Label_0085;
                                    }
                                }
                                catch (RuntimeException ex) {
                                    throw ex;
                                }
                                try {
                                    final boolean loggedIn;
                                    int n = (loggedIn = Game.isLoggedIn()) ? 1 : 0;
                                    Label_0081: {
                                        Label_0050: {
                                            try {
                                                if (f) {
                                                    break Label_0050;
                                                }
                                                if (loggedIn) {
                                                    break Label_0050;
                                                }
                                                break Label_0081;
                                            }
                                            catch (RuntimeException ex2) {
                                                throw ex2;
                                            }
                                            try {
                                                if (!loggedIn) {
                                                    break Label_0081;
                                                }
                                                n = JOptionPane.showConfirmDialog(a2, s.a(yb$0.z[6]), org.powerbot.a.a(yb$0.z[4]), 0, 3);
                                            }
                                            catch (RuntimeException ex3) {
                                                throw ex3;
                                            }
                                        }
                                        if (n != 0) {
                                            return;
                                        }
                                    }
                                }
                                catch (RuntimeException ex6) {}
                            }
                            try {
                                a3 = hb.a();
                                a4 = s.a(yb$0.z[1]);
                                a5 = org.powerbot.a.a(yb$0.z[0]);
                                if (b) {
                                    final String a6 = s.a(yb$0.z[3]);
                                    break Label_0125;
                                }
                            }
                            catch (RuntimeException ex4) {
                                throw ex4;
                            }
                        }
                        final String a6 = "";
                        try {
                            a3.a(a4, a5, a6);
                            a2.c.a((Bot)null);
                            Bot.instance().stop();
                            a2.c.repaint();
                            Logger.getLogger(Bot.class.getName()).log(Level.INFO, org.powerbot.a.a(yb$0.z[5]), s.a(yb$0.z[2]));
                            System.gc();
                            if (f) {
                                a.dispatchEvent(new WindowEvent(a, 201));
                            }
                        }
                        catch (RuntimeException ex5) {
                            throw ex5;
                        }
                    }
                }
            }
            
            static {
                final String[] z2 = new String[7];
                int n7;
                int n6;
                int n5;
                int n4;
                int n3;
                int n2;
                int n = n2 = (n3 = (n4 = (n5 = (n6 = (n7 = 0)))));
                String s = "\u0005R5";
                int n8 = -1;
                String intern = null;
            Label_0091_Outer:
                while (true) {
                    final char[] charArray = s.toCharArray();
                    int length;
                    int n10;
                    final int n9 = n10 = (length = charArray.length);
                    int n11 = 0;
                    while (true) {
                        Label_0166: {
                            if (n9 > 1) {
                                break Label_0166;
                            }
                            length = (n10 = n11);
                            do {
                                final char c = charArray[n10];
                                char c2 = '\0';
                                switch (n11 % 5) {
                                    case 0: {
                                        c2 = 'G';
                                        break;
                                    }
                                    case 1: {
                                        c2 = '{';
                                        break;
                                    }
                                    case 2: {
                                        c2 = 'r';
                                        break;
                                    }
                                    case 3: {
                                        c2 = 'B';
                                        break;
                                    }
                                    default: {
                                        c2 = '\f';
                                        break;
                                    }
                                }
                                charArray[length] = (char)(c ^ c2);
                                ++n11;
                            } while (n9 == 0);
                        }
                        if (n9 > n11) {
                            continue;
                        }
                        break;
                    }
                    intern = new String(charArray).intern();
                    switch (n8) {
                        default: {
                            z2[n2] = intern;
                            n = (n2 = (n3 = (n4 = (n5 = (n6 = (n7 = 1))))));
                            s = "]\u0015~";
                            n8 = 0;
                            continue Label_0091_Outer;
                        }
                        case 0: {
                            z2[n] = intern;
                            n = (n2 = (n3 = (n4 = (n5 = (n6 = (n7 = 2))))));
                            s = "\u000by\u0012_fM";
                            n8 = 1;
                            continue Label_0091_Outer;
                        }
                        case 1: {
                            z2[n3] = intern;
                            n = (n2 = (n3 = (n4 = (n5 = (n6 = (n7 = 3))))));
                            s = ";|\u0011Im]";
                            n8 = 2;
                            continue Label_0091_Outer;
                        }
                        case 2: {
                            z2[n4] = intern;
                            n = (n2 = (n3 = (n4 = (n5 = (n6 = (n7 = 4))))));
                            s = "'Z>|J";
                            n8 = 3;
                            continue Label_0091_Outer;
                        }
                        case 3: {
                            z2[n5] = intern;
                            n = (n2 = (n3 = (n4 = (n5 = (n6 = (n7 = 5))))));
                            s = "K<[A DB0m\u000f~7\u001f\u00125\u0005D%/Nd7K\t$\u0016\u00163`[";
                            n8 = 4;
                            continue Label_0091_Outer;
                        }
                        case 4: {
                            z2[n6] = intern;
                            n = (n2 = (n3 = (n4 = (n5 = (n6 = (n7 = 6))))));
                            s = "\tg\u0018\fzF\u0001<>\u0017:p]Ul\\Tk,\f<5\tC#J\u0018s>\u0007ha\u0015Ep\t\u0000}/]";
                            n8 = 5;
                            continue Label_0091_Outer;
                        }
                        case 5: {
                            break Label_0091_Outer;
                        }
                    }
                }
                z2[n7] = intern;
                z = z2;
            }
        });
    }
    
    public static synchronized void b() {
        // 
        // This method could not be decompiled.
        // 
        // Original Bytecode:
        // 
        //     3: istore_2       
        //     4: invokestatic    org/powerbot/core/Bot.instance:()Lorg/powerbot/core/Bot;
        //     7: astore_0       
        //     8: aload_0        
        //     9: invokevirtual   org/powerbot/core/Bot.getScriptHandler:()Lorg/powerbot/core/bot/handlers/ScriptHandler;
        //    12: astore_1       
        //    13: aload_1        
        //    14: iload_2        
        //    15: ifne            26
        //    18: ifnull          128
        //    21: goto            25
        //    24: athrow         
        //    25: aload_1        
        //    26: invokevirtual   org/powerbot/core/bot/handlers/ScriptHandler.isActive:()Z
        //    29: iload_2        
        //    30: ifne            56
        //    33: ifeq            128
        //    36: goto            40
        //    39: athrow         
        //    40: aload_1        
        //    41: iload_2        
        //    42: ifne            124
        //    45: goto            49
        //    48: athrow         
        //    49: invokevirtual   org/powerbot/core/bot/handlers/ScriptHandler.isPaused:()Z
        //    52: goto            56
        //    55: athrow         
        //    56: ifeq            95
        //    59: invokestatic    org/powerbot/hb.a:()Lorg/powerbot/hb;
        //    62: getstatic       org/powerbot/yb.z:[Ljava/lang/String;
        //    65: bipush          9
        //    67: aaload         
        //    68: invokestatic    org/powerbot/core/script/wrappers/Item.e:(Ljava/lang/String;)Ljava/lang/String;
        //    71: getstatic       org/powerbot/yb.z:[Ljava/lang/String;
        //    74: bipush          8
        //    76: aaload         
        //    77: invokestatic    org/powerbot/game/api/util/Time.e:(Ljava/lang/String;)Ljava/lang/String;
        //    80: invokevirtual   org/powerbot/hb.a:(Ljava/lang/String;Ljava/lang/String;)V
        //    83: aload_1        
        //    84: invokevirtual   org/powerbot/core/bot/handlers/ScriptHandler.resume:()V
        //    87: iload_2        
        //    88: ifeq            127
        //    91: goto            95
        //    94: athrow         
        //    95: invokestatic    org/powerbot/hb.a:()Lorg/powerbot/hb;
        //    98: getstatic       org/powerbot/yb.z:[Ljava/lang/String;
        //   101: bipush          9
        //   103: aaload         
        //   104: invokestatic    org/powerbot/core/script/wrappers/Item.e:(Ljava/lang/String;)Ljava/lang/String;
        //   107: getstatic       org/powerbot/yb.z:[Ljava/lang/String;
        //   110: bipush          7
        //   112: aaload         
        //   113: invokestatic    org/powerbot/game/api/util/Time.e:(Ljava/lang/String;)Ljava/lang/String;
        //   116: invokevirtual   org/powerbot/hb.a:(Ljava/lang/String;Ljava/lang/String;)V
        //   119: aload_1        
        //   120: goto            124
        //   123: athrow         
        //   124: invokevirtual   org/powerbot/core/bot/handlers/ScriptHandler.pause:()V
        //   127: return         
        //   128: invokestatic    org/powerbot/core/Bot.client:()Lorg/powerbot/game/client/Client;
        //   131: ifnull          149
        //   134: new             Lorg/powerbot/ob;
        //   137: dup            
        //   138: invokestatic    org/powerbot/qb.a:()Lorg/powerbot/qb;
        //   141: invokespecial   org/powerbot/ob.<init>:(Lorg/powerbot/qb;)V
        //   144: pop            
        //   145: goto            149
        //   148: athrow         
        //   149: return         
        //    StackMapTable: 00 11 FF 00 18 00 03 07 00 65 07 00 85 01 00 01 07 01 5D 00 40 07 00 85 4C 07 01 5D 00 47 07 01 5D 40 07 00 85 45 07 01 5D 40 01 65 07 01 5D 00 5B 07 01 5D 40 07 00 85 02 00 53 07 01 5D 00
        //    Exceptions:
        //  Try           Handler
        //  Start  End    Start  End    Type                        
        //  -----  -----  -----  -----  ----------------------------
        //  128    145    148    149    Ljava/lang/RuntimeException;
        //  59     120    123    124    Ljava/lang/RuntimeException;
        //  56     91     94     95     Ljava/lang/RuntimeException;
        //  40     52     55     56     Ljava/lang/RuntimeException;
        //  33     45     48     49     Ljava/lang/RuntimeException;
        //  26     36     39     40     Ljava/lang/RuntimeException;
        //  13     21     24     25     Ljava/lang/RuntimeException;
        // 
        // The error that occurred was:
        // 
        // java.lang.IllegalStateException: Expression is linked from several locations: Label_0040:
        //     at com.strobel.decompiler.ast.Error.expressionLinkedFromMultipleLocations(Error.java:27)
        //     at com.strobel.decompiler.ast.AstOptimizer.mergeDisparateObjectInitializations(AstOptimizer.java:2596)
        //     at com.strobel.decompiler.ast.AstOptimizer.optimize(AstOptimizer.java:235)
        //     at com.strobel.decompiler.ast.AstOptimizer.optimize(AstOptimizer.java:42)
        //     at com.strobel.decompiler.languages.java.ast.AstMethodBodyBuilder.createMethodBody(AstMethodBodyBuilder.java:214)
        //     at com.strobel.decompiler.languages.java.ast.AstMethodBodyBuilder.createMethodBody(AstMethodBodyBuilder.java:99)
        //     at com.strobel.decompiler.languages.java.ast.AstBuilder.createMethodBody(AstBuilder.java:782)
        //     at com.strobel.decompiler.languages.java.ast.AstBuilder.createMethod(AstBuilder.java:675)
        //     at com.strobel.decompiler.languages.java.ast.AstBuilder.addTypeMembers(AstBuilder.java:552)
        //     at com.strobel.decompiler.languages.java.ast.AstBuilder.createTypeCore(AstBuilder.java:519)
        //     at com.strobel.decompiler.languages.java.ast.AstBuilder.createTypeNoCache(AstBuilder.java:161)
        //     at com.strobel.decompiler.languages.java.ast.AstBuilder.createType(AstBuilder.java:150)
        //     at com.strobel.decompiler.languages.java.ast.AstBuilder.addType(AstBuilder.java:125)
        //     at com.strobel.decompiler.languages.java.JavaLanguage.buildAst(JavaLanguage.java:71)
        //     at com.strobel.decompiler.languages.java.JavaLanguage.decompileType(JavaLanguage.java:59)
        //     at com.strobel.decompiler.DecompilerDriver.decompileType(DecompilerDriver.java:330)
        //     at com.strobel.decompiler.DecompilerDriver.decompileJar(DecompilerDriver.java:251)
        //     at com.strobel.decompiler.DecompilerDriver.main(DecompilerDriver.java:126)
        // 
        throw new IllegalStateException("An error occurred while decompiling this method.");
    }
    
    public static synchronized void c() {
        // 
        // This method could not be decompiled.
        // 
        // Original Bytecode:
        // 
        //     3: istore_2       
        //     4: invokestatic    org/powerbot/core/Bot.instantiated:()Z
        //     7: ifne            12
        //    10: return         
        //    11: athrow         
        //    12: invokestatic    org/powerbot/core/Bot.instance:()Lorg/powerbot/core/Bot;
        //    15: astore_0       
        //    16: aload_0        
        //    17: invokevirtual   org/powerbot/core/Bot.getScriptHandler:()Lorg/powerbot/core/bot/handlers/ScriptHandler;
        //    20: astore_1       
        //    21: aload_1        
        //    22: iload_2        
        //    23: ifne            34
        //    26: ifnull          182
        //    29: goto            33
        //    32: athrow         
        //    33: aload_1        
        //    34: invokevirtual   org/powerbot/core/bot/handlers/ScriptHandler.isShutdown:()Z
        //    37: iload_2        
        //    38: ifne            122
        //    41: ifne            106
        //    44: goto            48
        //    47: athrow         
        //    48: invokestatic    org/powerbot/hb.a:()Lorg/powerbot/hb;
        //    51: getstatic       org/powerbot/yb.z:[Ljava/lang/String;
        //    54: bipush          9
        //    56: aaload         
        //    57: invokestatic    org/powerbot/core/script/wrappers/Item.e:(Ljava/lang/String;)Ljava/lang/String;
        //    60: getstatic       org/powerbot/yb.z:[Ljava/lang/String;
        //    63: bipush          27
        //    65: aaload         
        //    66: invokestatic    org/powerbot/game/api/util/Time.e:(Ljava/lang/String;)Ljava/lang/String;
        //    69: invokevirtual   org/powerbot/hb.a:(Ljava/lang/String;Ljava/lang/String;)V
        //    72: aload_0        
        //    73: invokevirtual   org/powerbot/core/Bot.stopScript:()V
        //    76: new             Ljava/lang/Thread;
        //    79: dup            
        //    80: aload_0        
        //    81: getfield        org/powerbot/core/Bot.threadGroup:Ljava/lang/ThreadGroup;
        //    84: new             Lorg/powerbot/yb$3;
        //    87: dup            
        //    88: aload_1        
        //    89: invokespecial   org/powerbot/yb$3.<init>:(Lorg/powerbot/core/bot/handlers/ScriptHandler;)V
        //    92: invokespecial   java/lang/Thread.<init>:(Ljava/lang/ThreadGroup;Ljava/lang/Runnable;)V
        //    95: invokevirtual   java/lang/Thread.start:()V
        //    98: iload_2        
        //    99: ifeq            182
        //   102: goto            106
        //   105: athrow         
        //   106: aload_1        
        //   107: iload_2        
        //   108: ifne            179
        //   111: goto            115
        //   114: athrow         
        //   115: invokevirtual   org/powerbot/core/bot/handlers/ScriptHandler.isActive:()Z
        //   118: goto            122
        //   121: athrow         
        //   122: ifeq            182
        //   125: aload_1        
        //   126: getfield        org/powerbot/core/bot/handlers/ScriptHandler.log:Ljava/util/logging/Logger;
        //   129: getstatic       org/powerbot/yb.z:[Ljava/lang/String;
        //   132: bipush          30
        //   134: aaload         
        //   135: invokestatic    org/powerbot/core/script/wrappers/Item.e:(Ljava/lang/String;)Ljava/lang/String;
        //   138: invokevirtual   java/util/logging/Logger.info:(Ljava/lang/String;)V
        //   141: invokestatic    org/powerbot/hb.a:()Lorg/powerbot/hb;
        //   144: getstatic       org/powerbot/yb.z:[Ljava/lang/String;
        //   147: bipush          26
        //   149: aaload         
        //   150: invokestatic    org/powerbot/game/api/util/Time.e:(Ljava/lang/String;)Ljava/lang/String;
        //   153: getstatic       org/powerbot/yb.z:[Ljava/lang/String;
        //   156: bipush          29
        //   158: aaload         
        //   159: invokestatic    org/powerbot/core/script/wrappers/Item.e:(Ljava/lang/String;)Ljava/lang/String;
        //   162: getstatic       org/powerbot/yb.z:[Ljava/lang/String;
        //   165: bipush          28
        //   167: aaload         
        //   168: invokestatic    org/powerbot/game/api/util/Time.e:(Ljava/lang/String;)Ljava/lang/String;
        //   171: invokevirtual   org/powerbot/hb.a:(Ljava/lang/String;Ljava/lang/String;Ljava/lang/String;)V
        //   174: aload_1        
        //   175: goto            179
        //   178: athrow         
        //   179: invokevirtual   org/powerbot/core/bot/handlers/ScriptHandler.stop:()V
        //   182: return         
        //    StackMapTable: 00 10 FF 00 0B 00 03 00 00 01 00 01 07 01 5D 00 FF 00 13 00 03 07 00 65 07 00 85 01 00 01 07 01 5D 00 40 07 00 85 4C 07 01 5D 00 78 07 01 5D 00 47 07 01 5D 40 07 00 85 45 07 01 5D 40 01 77 07 01 5D 40 07 00 85 02
        //    Exceptions:
        //  Try           Handler
        //  Start  End    Start  End    Type                        
        //  -----  -----  -----  -----  ----------------------------
        //  122    175    178    179    Ljava/lang/RuntimeException;
        //  106    118    121    122    Ljava/lang/RuntimeException;
        //  48     111    114    115    Ljava/lang/RuntimeException;
        //  41     102    105    106    Ljava/lang/RuntimeException;
        //  34     44     47     48     Ljava/lang/RuntimeException;
        //  21     29     32     33     Ljava/lang/RuntimeException;
        //  4      11     11     12     Ljava/lang/RuntimeException;
        // 
        // The error that occurred was:
        // 
        // java.lang.IllegalStateException: Expression is linked from several locations: Label_0048:
        //     at com.strobel.decompiler.ast.Error.expressionLinkedFromMultipleLocations(Error.java:27)
        //     at com.strobel.decompiler.ast.AstOptimizer.mergeDisparateObjectInitializations(AstOptimizer.java:2596)
        //     at com.strobel.decompiler.ast.AstOptimizer.optimize(AstOptimizer.java:235)
        //     at com.strobel.decompiler.ast.AstOptimizer.optimize(AstOptimizer.java:42)
        //     at com.strobel.decompiler.languages.java.ast.AstMethodBodyBuilder.createMethodBody(AstMethodBodyBuilder.java:214)
        //     at com.strobel.decompiler.languages.java.ast.AstMethodBodyBuilder.createMethodBody(AstMethodBodyBuilder.java:99)
        //     at com.strobel.decompiler.languages.java.ast.AstBuilder.createMethodBody(AstBuilder.java:782)
        //     at com.strobel.decompiler.languages.java.ast.AstBuilder.createMethod(AstBuilder.java:675)
        //     at com.strobel.decompiler.languages.java.ast.AstBuilder.addTypeMembers(AstBuilder.java:552)
        //     at com.strobel.decompiler.languages.java.ast.AstBuilder.createTypeCore(AstBuilder.java:519)
        //     at com.strobel.decompiler.languages.java.ast.AstBuilder.createTypeNoCache(AstBuilder.java:161)
        //     at com.strobel.decompiler.languages.java.ast.AstBuilder.createType(AstBuilder.java:150)
        //     at com.strobel.decompiler.languages.java.ast.AstBuilder.addType(AstBuilder.java:125)
        //     at com.strobel.decompiler.languages.java.JavaLanguage.buildAst(JavaLanguage.java:71)
        //     at com.strobel.decompiler.languages.java.JavaLanguage.decompileType(JavaLanguage.java:59)
        //     at com.strobel.decompiler.DecompilerDriver.decompileType(DecompilerDriver.java:330)
        //     at com.strobel.decompiler.DecompilerDriver.decompileJar(DecompilerDriver.java:251)
        //     at com.strobel.decompiler.DecompilerDriver.main(DecompilerDriver.java:126)
        // 
        throw new IllegalStateException("An error occurred while decompiling this method.");
    }
    
    static {
        final String[] z2 = new String[31];
        int n31;
        int n30;
        int n29;
        int n28;
        int n27;
        int n26;
        int n25;
        int n24;
        int n23;
        int n22;
        int n21;
        int n20;
        int n19;
        int n18;
        int n17;
        int n16;
        int n15;
        int n14;
        int n13;
        int n12;
        int n11;
        int n10;
        int n9;
        int n8;
        int n7;
        int n6;
        int n5;
        int n4;
        int n3;
        int n2;
        int n = n2 = (n3 = (n4 = (n5 = (n6 = (n7 = (n8 = (n9 = (n10 = (n11 = (n12 = (n13 = (n14 = (n15 = (n16 = (n17 = (n18 = (n19 = (n20 = (n21 = (n22 = (n23 = (n24 = (n25 = (n26 = (n27 = (n28 = (n29 = (n30 = (n31 = 0)))))))))))))))))))))))))))));
        String s = "fsY\u0006\u001e";
        int n32 = -1;
        String intern = null;
    Label_0386_Outer:
        while (true) {
            final char[] charArray = s.toCharArray();
            int length;
            int n34;
            final int n33 = n34 = (length = charArray.length);
            int n35 = 0;
            while (true) {
                Label_0462: {
                    if (n33 > 1) {
                        break Label_0462;
                    }
                    length = (n34 = n35);
                    do {
                        final char c = charArray[n34];
                        char c2 = '\0';
                        switch (n35 % 5) {
                            case 0: {
                                c2 = ':';
                                break;
                            }
                            case 1: {
                                c2 = '%';
                                break;
                            }
                            case 2: {
                                c2 = '+';
                                break;
                            }
                            case 3: {
                                c2 = 'G';
                                break;
                            }
                            default: {
                                c2 = 'w';
                                break;
                            }
                        }
                        charArray[length] = (char)(c ^ c2);
                        ++n35;
                    } while (n33 == 0);
                }
                if (n33 > n35) {
                    continue;
                }
                break;
            }
            intern = new String(charArray).intern();
            switch (n32) {
                default: {
                    z2[n2] = intern;
                    n = (n2 = (n3 = (n4 = (n5 = (n6 = (n7 = (n8 = (n9 = (n10 = (n11 = (n12 = (n13 = (n14 = (n15 = (n16 = (n17 = (n18 = (n19 = (n20 = (n21 = (n22 = (n23 = (n24 = (n25 = (n26 = (n27 = (n28 = (n29 = (n30 = (n31 = 1))))))))))))))))))))))))))))));
                    s = "^\bsn";
                    n32 = 0;
                    continue Label_0386_Outer;
                }
                case 0: {
                    z2[n] = intern;
                    n = (n2 = (n3 = (n4 = (n5 = (n6 = (n7 = (n8 = (n9 = (n10 = (n11 = (n12 = (n13 = (n14 = (n15 = (n16 = (n17 = (n18 = (n19 = (n20 = (n21 = (n22 = (n23 = (n24 = (n25 = (n26 = (n27 = (n28 = (n29 = (n30 = (n31 = 2))))))))))))))))))))))))))))));
                    s = "\b|S\u001d\u001f";
                    n32 = 1;
                    continue Label_0386_Outer;
                }
                case 1: {
                    z2[n3] = intern;
                    n = (n2 = (n3 = (n4 = (n5 = (n6 = (n7 = (n8 = (n9 = (n10 = (n11 = (n12 = (n13 = (n14 = (n15 = (n16 = (n17 = (n18 = (n19 = (n20 = (n21 = (n22 = (n23 = (n24 = (n25 = (n26 = (n27 = (n28 = (n29 = (n30 = (n31 = 3))))))))))))))))))))))))))))));
                    s = "^T~#";
                    n32 = 2;
                    continue Label_0386_Outer;
                }
                case 2: {
                    z2[n4] = intern;
                    n = (n2 = (n3 = (n4 = (n5 = (n6 = (n7 = (n8 = (n9 = (n10 = (n11 = (n12 = (n13 = (n14 = (n15 = (n16 = (n17 = (n18 = (n19 = (n20 = (n21 = (n22 = (n23 = (n24 = (n25 = (n26 = (n27 = (n28 = (n29 = (n30 = (n31 = 4))))))))))))))))))))))))))))));
                    s = "L\u001f\u007fq5\rf\u0001";
                    n32 = 3;
                    continue Label_0386_Outer;
                }
                case 3: {
                    z2[n5] = intern;
                    n = (n2 = (n3 = (n4 = (n5 = (n6 = (n7 = (n8 = (n9 = (n10 = (n11 = (n12 = (n13 = (n14 = (n15 = (n16 = (n17 = (n18 = (n19 = (n20 = (n21 = (n22 = (n23 = (n24 = (n25 = (n26 = (n27 = (n28 = (n29 = (n30 = (n31 = 5))))))))))))))))))))))))))))));
                    s = "-w\u0005";
                    n32 = 4;
                    continue Label_0386_Outer;
                }
                case 4: {
                    z2[n6] = intern;
                    n = (n2 = (n3 = (n4 = (n5 = (n6 = (n7 = (n8 = (n9 = (n10 = (n11 = (n12 = (n13 = (n14 = (n15 = (n16 = (n17 = (n18 = (n19 = (n20 = (n21 = (n22 = (n23 = (n24 = (n25 = (n26 = (n27 = (n28 = (n29 = (n30 = (n31 = 6))))))))))))))))))))))))))))));
                    s = "d}Y\u0000\u000f";
                    n32 = 5;
                    continue Label_0386_Outer;
                }
                case 5: {
                    z2[n7] = intern;
                    n = (n2 = (n3 = (n4 = (n5 = (n6 = (n7 = (n8 = (n9 = (n10 = (n11 = (n12 = (n13 = (n14 = (n15 = (n16 = (n17 = (n18 = (n19 = (n20 = (n21 = (n22 = (n23 = (n24 = (n25 = (n26 = (n27 = (n28 = (n29 = (n30 = (n31 = 7))))))))))))))))))))))))))))));
                    s = "WpC\u0000\u000f";
                    n32 = 6;
                    continue Label_0386_Outer;
                }
                case 6: {
                    z2[n8] = intern;
                    n = (n2 = (n3 = (n4 = (n5 = (n6 = (n7 = (n8 = (n9 = (n10 = (n11 = (n12 = (n13 = (n14 = (n15 = (n16 = (n17 = (n18 = (n19 = (n20 = (n21 = (n22 = (n23 = (n24 = (n25 = (n26 = (n27 = (n28 = (n29 = (n30 = (n31 = 8))))))))))))))))))))))))))))));
                    s = "|]l/.B";
                    n32 = 7;
                    continue Label_0386_Outer;
                }
                case 7: {
                    z2[n9] = intern;
                    n = (n2 = (n3 = (n4 = (n5 = (n6 = (n7 = (n8 = (n9 = (n10 = (n11 = (n12 = (n13 = (n14 = (n15 = (n16 = (n17 = (n18 = (n19 = (n20 = (n21 = (n22 = (n23 = (n24 = (n25 = (n26 = (n27 = (n28 = (n29 = (n30 = (n31 = 9))))))))))))))))))))))))))))));
                    s = "~\u001fnw0\u0017";
                    n32 = 8;
                    continue Label_0386_Outer;
                }
                case 8: {
                    z2[n10] = intern;
                    n = (n2 = (n3 = (n4 = (n5 = (n6 = (n7 = (n8 = (n9 = (n10 = (n11 = (n12 = (n13 = (n14 = (n15 = (n16 = (n17 = (n18 = (n19 = (n20 = (n21 = (n22 = (n23 = (n24 = (n25 = (n26 = (n27 = (n28 = (n29 = (n30 = (n31 = 10))))))))))))))))))))))))))))));
                    s = "UtE\u001c\u001f|[z)lN|W\u0014\u000f}\u0017x6:Wy_\u0010\u0005`K@kt\u0013NF\u0012\u001f}]1*-@";
                    n32 = 9;
                    continue Label_0386_Outer;
                }
                case 9: {
                    z2[n11] = intern;
                    n = (n2 = (n3 = (n4 = (n5 = (n6 = (n7 = (n8 = (n9 = (n10 = (n11 = (n12 = (n13 = (n14 = (n15 = (n16 = (n17 = (n18 = (n19 = (n20 = (n21 = (n22 = (n23 = (n24 = (n25 = (n26 = (n27 = (n28 = (n29 = (n30 = (n31 = 11))))))))))))))))))))))))))))));
                    s = "H]z>!Fr]";
                    n32 = 10;
                    continue Label_0386_Outer;
                }
                case 10: {
                    z2[n12] = intern;
                    n = (n2 = (n3 = (n4 = (n5 = (n6 = (n7 = (n8 = (n9 = (n10 = (n11 = (n12 = (n13 = (n14 = (n15 = (n16 = (n17 = (n18 = (n19 = (n20 = (n21 = (n22 = (n23 = (n24 = (n25 = (n26 = (n27 = (n28 = (n29 = (n30 = (n31 = 12))))))))))))))))))))))))))))));
                    s = "\u007f\u0019oq5\u0011q\u0017\u0003\u0001d\u0011}y%\u0010=\u0015\u001cW}\u0014u}/\ra-A\u0019>#lr!\u001a<\u0002\u001eI";
                    n32 = 11;
                    continue Label_0386_Outer;
                }
                case 11: {
                    z2[n13] = intern;
                    n = (n2 = (n3 = (n4 = (n5 = (n6 = (n7 = (n8 = (n9 = (n10 = (n11 = (n12 = (n13 = (n14 = (n15 = (n16 = (n17 = (n18 = (n19 = (n20 = (n21 = (n22 = (n23 = (n24 = (n25 = (n26 = (n27 = (n28 = (n29 = (n30 = (n31 = 13))))))))))))))))))))))))))))));
                    s = "itA";
                    n32 = 12;
                    continue Label_0386_Outer;
                }
                case 12: {
                    z2[n14] = intern;
                    n = (n2 = (n3 = (n4 = (n5 = (n6 = (n7 = (n8 = (n9 = (n10 = (n11 = (n12 = (n13 = (n14 = (n15 = (n16 = (n17 = (n18 = (n19 = (n20 = (n21 = (n22 = (n23 = (n24 = (n25 = (n26 = (n27 = (n28 = (n29 = (n30 = (n31 = 14))))))))))))))))))))))))))))));
                    s = "\u0011w\u0001\u001f[\u007f\u001fymo\n\u007f\u0013\u0017K~S{r9\u0013z\u001b\u0013Ac\u000fC/yVM\u0011\u0019\\n\u0010yA)\rt\u001d^^c\u001b";
                    n32 = 13;
                    continue Label_0386_Outer;
                }
                case 13: {
                    z2[n15] = intern;
                    n = (n2 = (n3 = (n4 = (n5 = (n6 = (n7 = (n8 = (n9 = (n10 = (n11 = (n12 = (n13 = (n14 = (n15 = (n16 = (n17 = (n18 = (n19 = (n20 = (n21 = (n22 = (n23 = (n24 = (n25 = (n26 = (n27 = (n28 = (n29 = (n30 = (n31 = 15))))))))))))))))))))))))))))));
                    s = "\u007f\u0019oq5\u0011q\u0017\u0003\u0001d\u0011}y%\u0010=\u0015\u001cW}\u0014u}/\ra-A\u0017:#n{-\fd\u0017^^c\u001b";
                    n32 = 14;
                    continue Label_0386_Outer;
                }
                case 14: {
                    z2[n16] = intern;
                    n = (n2 = (n3 = (n4 = (n5 = (n6 = (n7 = (n8 = (n9 = (n10 = (n11 = (n12 = (n13 = (n14 = (n15 = (n16 = (n17 = (n18 = (n19 = (n20 = (n21 = (n22 = (n23 = (n24 = (n25 = (n26 = (n27 = (n28 = (n29 = (n30 = (n31 = 16))))))))))))))))))))))))))))));
                    s = "\u007f\u0019oq5\u0011q\u0017\u0003\u0001d\u0011}y%\u0010=\u0015\u001cW}\u0014u}/\ra-@\u001a9#w{9\u0010<\u0002\u001eI";
                    n32 = 15;
                    continue Label_0386_Outer;
                }
                case 15: {
                    z2[n17] = intern;
                    n = (n2 = (n3 = (n4 = (n5 = (n6 = (n7 = (n8 = (n9 = (n10 = (n11 = (n12 = (n13 = (n14 = (n15 = (n16 = (n17 = (n18 = (n19 = (n20 = (n21 = (n22 = (n23 = (n24 = (n25 = (n26 = (n27 = (n28 = (n29 = (n30 = (n31 = 17))))))))))))))))))))))))))))));
                    s = "O[|56IeE";
                    n32 = 16;
                    continue Label_0386_Outer;
                }
                case 16: {
                    z2[n18] = intern;
                    n = (n2 = (n3 = (n4 = (n5 = (n6 = (n7 = (n8 = (n9 = (n10 = (n11 = (n12 = (n13 = (n14 = (n15 = (n16 = (n17 = (n18 = (n19 = (n20 = (n21 = (n22 = (n23 = (n24 = (n25 = (n26 = (n27 = (n28 = (n29 = (n30 = (n31 = 18))))))))))))))))))))))))))))));
                    s = "\u007f\u0019oq5\u0011q\u0017\u0003\u0001d\u0011}y%\u0010=\u0015\u001cW}\u0014u}/\ra-B\u001a9#\u007fq.\u0015w\u0000\u0003Oy\u0015spn\u0013|\u0015";
                    n32 = 17;
                    continue Label_0386_Outer;
                }
                case 17: {
                    z2[n19] = intern;
                    n = (n2 = (n3 = (n4 = (n5 = (n6 = (n7 = (n8 = (n9 = (n10 = (n11 = (n12 = (n13 = (n14 = (n15 = (n16 = (n17 = (n18 = (n19 = (n20 = (n21 = (n22 = (n23 = (n24 = (n25 = (n26 = (n27 = (n28 = (n29 = (n30 = (n31 = 19))))))))))))))))))))))))))))));
                    s = "]\u0010}g";
                    n32 = 18;
                    continue Label_0386_Outer;
                }
                case 18: {
                    z2[n20] = intern;
                    n = (n2 = (n3 = (n4 = (n5 = (n6 = (n7 = (n8 = (n9 = (n10 = (n11 = (n12 = (n13 = (n14 = (n15 = (n16 = (n17 = (n18 = (n19 = (n20 = (n21 = (n22 = (n23 = (n24 = (n25 = (n26 = (n27 = (n28 = (n29 = (n30 = (n31 = 20))))))))))))))))))))))))))))));
                    s = "wpC\u0000\u000f";
                    n32 = 19;
                    continue Label_0386_Outer;
                }
                case 19: {
                    z2[n21] = intern;
                    n = (n2 = (n3 = (n4 = (n5 = (n6 = (n7 = (n8 = (n9 = (n10 = (n11 = (n12 = (n13 = (n14 = (n15 = (n16 = (n17 = (n18 = (n19 = (n20 = (n21 = (n22 = (n23 = (n24 = (n25 = (n26 = (n27 = (n28 = (n29 = (n30 = (n31 = 21))))))))))))))))))))))))))))));
                    s = "]Lp*";
                    n32 = 20;
                    continue Label_0386_Outer;
                }
                case 20: {
                    z2[n22] = intern;
                    n = (n2 = (n3 = (n4 = (n5 = (n6 = (n7 = (n8 = (n9 = (n10 = (n11 = (n12 = (n13 = (n14 = (n15 = (n16 = (n17 = (n18 = (n19 = (n20 = (n21 = (n22 = (n23 = (n24 = (n25 = (n26 = (n27 = (n28 = (n29 = (n30 = (n31 = 22))))))))))))))))))))))))))))));
                    s = "\u0011w\u0001\u001f[\u007f\u001fymo\n\u007f\u0013\u0017K~S{r9\u0013z\u001b\u0013Ac\u000fC/ySM\u0011\u0019\\n\u0010yA0\u000fg\u0001^^c\u001b";
                    n32 = 21;
                    continue Label_0386_Outer;
                }
                case 21: {
                    z2[n23] = intern;
                    n = (n2 = (n3 = (n4 = (n5 = (n6 = (n7 = (n8 = (n9 = (n10 = (n11 = (n12 = (n13 = (n14 = (n15 = (n16 = (n17 = (n18 = (n19 = (n20 = (n21 = (n22 = (n23 = (n24 = (n25 = (n26 = (n27 = (n28 = (n29 = (n30 = (n31 = 23))))))))))))))))))))))))))))));
                    s = "\u007f\u0019oq5\u0011q\u0017\u0003\u0001d\u0011}y%\u0010=\u0015\u001cW}\u0014u}/\ra-A\u00198#oj/\u0013<\u0002\u001eI";
                    n32 = 22;
                    continue Label_0386_Outer;
                }
                case 22: {
                    z2[n24] = intern;
                    n = (n2 = (n3 = (n4 = (n5 = (n6 = (n7 = (n8 = (n9 = (n10 = (n11 = (n12 = (n13 = (n14 = (n15 = (n16 = (n17 = (n18 = (n19 = (n20 = (n21 = (n22 = (n23 = (n24 = (n25 = (n26 = (n27 = (n28 = (n29 = (n30 = (n31 = 24))))))))))))))))))))))))))))));
                    s = "]Qx4cN\u007f\u0018]D";
                    n32 = 23;
                    continue Label_0386_Outer;
                }
                case 23: {
                    z2[n25] = intern;
                    n = (n2 = (n3 = (n4 = (n5 = (n6 = (n7 = (n8 = (n9 = (n10 = (n11 = (n12 = (n13 = (n14 = (n15 = (n16 = (n17 = (n18 = (n19 = (n20 = (n21 = (n22 = (n23 = (n24 = (n25 = (n26 = (n27 = (n28 = (n29 = (n30 = (n31 = 25))))))))))))))))))))))))))))));
                    s = "\u0011w\u0001\u001f[\u007f\u001fymo\n\u007f\u0013\u0017K~S{r9\u0013z\u001b\u0013Ac\u000fC.x[M\u0013\u0014\\h\u000foA\"\f}\u0019^^c\u001b";
                    n32 = 24;
                    continue Label_0386_Outer;
                }
                case 24: {
                    z2[n26] = intern;
                    n = (n2 = (n3 = (n4 = (n5 = (n6 = (n7 = (n8 = (n9 = (n10 = (n11 = (n12 = (n13 = (n14 = (n15 = (n16 = (n17 = (n18 = (n19 = (n20 = (n21 = (n22 = (n23 = (n24 = (n25 = (n26 = (n27 = (n28 = (n29 = (n30 = (n31 = 26))))))))))))))))))))))))))))));
                    s = "}[m33S";
                    n32 = 25;
                    continue Label_0386_Outer;
                }
                case 25: {
                    z2[n27] = intern;
                    n = (n2 = (n3 = (n4 = (n5 = (n6 = (n7 = (n8 = (n9 = (n10 = (n11 = (n12 = (n13 = (n14 = (n15 = (n16 = (n17 = (n18 = (n19 = (n20 = (n21 = (n22 = (n23 = (n24 = (n25 = (n26 = (n27 = (n28 = (n29 = (n30 = (n31 = 27))))))))))))))))))))))))))))));
                    s = "}Lp*";
                    n32 = 26;
                    continue Label_0386_Outer;
                }
                case 26: {
                    z2[n28] = intern;
                    n = (n2 = (n3 = (n4 = (n5 = (n6 = (n7 = (n8 = (n9 = (n10 = (n11 = (n12 = (n13 = (n14 = (n15 = (n16 = (n17 = (n18 = (n19 = (n20 = (n21 = (n22 = (n23 = (n24 = (n25 = (n26 = (n27 = (n28 = (n29 = (n30 = (n31 = 28))))))))))))))))))))))))))))));
                    s = "A~D\u0010\u000f";
                    n32 = 27;
                    continue Label_0386_Outer;
                }
                case 27: {
                    z2[n29] = intern;
                    n = (n2 = (n3 = (n4 = (n5 = (n6 = (n7 = (n8 = (n9 = (n10 = (n11 = (n12 = (n13 = (n14 = (n15 = (n16 = (n17 = (n18 = (n19 = (n20 = (n21 = (n22 = (n23 = (n24 = (n25 = (n26 = (n27 = (n28 = (n29 = (n30 = (n31 = 29))))))))))))))))))))))))))))));
                    s = "~\bsn";
                    n32 = 28;
                    continue Label_0386_Outer;
                }
                case 28: {
                    z2[n30] = intern;
                    n = (n2 = (n3 = (n4 = (n5 = (n6 = (n7 = (n8 = (n9 = (n10 = (n11 = (n12 = (n13 = (n14 = (n15 = (n16 = (n17 = (n18 = (n19 = (n20 = (n21 = (n22 = (n23 = (n24 = (n25 = (n26 = (n27 = (n28 = (n29 = (n30 = (n31 = 30))))))))))))))))))))))))))))));
                    s = "%}\u0000\u0013Gc\u001b<m#\u0011{\u0002\u0004\u000e~\bsn";
                    n32 = 29;
                    continue Label_0386_Outer;
                }
                case 29: {
                    break Label_0386_Outer;
                }
            }
        }
        z2[n31] = intern;
        z = z2;
    }
}
