
package org.powerbot.game.api.util.net;

import org.powerbot.core.script.job.Task;
import java.util.Scanner;
import java.net.URLEncoder;
import java.io.IOException;
import java.net.MalformedURLException;
import java.net.URL;
import java.util.HashMap;
import org.powerbot.core.script.internal.Constants;
import org.powerbot.core.script.wrappers.Component;
import java.util.Map;

public final class GeItem
{
    public static final String HOST;
    public static final String[] QUERIES;
    private final Map<String, String> map;
    private static final String[] z;
    
    private GeItem(final Map<String, String> map) {
        Map<String, String> map2 = map;
        Label_0023: {
            if (Highscores.a == 0) {
                if (map == null) {
                    break Label_0023;
                }
                map2 = map;
            }
            try {
                if (map2.isEmpty()) {
                    throw new IllegalArgumentException(Component.e(GeItem.z[41]));
                }
            }
            catch (IllegalArgumentException ex) {
                throw ex;
            }
        }
        this.map = map;
    }
    
    public double get180DayChange() {
        return Double.parseDouble(this.map.get(Constants.e(GeItem.z[47])));
    }
    
    public double get30DayChange() {
        return Double.parseDouble(this.map.get(Component.e(GeItem.z[43])));
    }
    
    public double get90DayChange() {
        return Double.parseDouble(this.map.get(Constants.e(GeItem.z[19])));
    }
    
    public String getCategory() {
        return this.map.get(Component.e(GeItem.z[51]));
    }
    
    public String getDescription() {
        return this.map.get(Constants.e(GeItem.z[50]));
    }
    
    public int getId() {
        return Integer.parseInt(this.map.get(Component.e(GeItem.z[33])));
    }
    
    public Map<String, String> getMap() {
        return new HashMap<String, String>(this.map);
    }
    
    public String getName() {
        return this.map.get(Constants.e(GeItem.z[49]));
    }
    
    public int getPrice() {
        return this.parseNumber(this.map.get(Component.e(GeItem.z[34])));
    }
    
    public URL getSpriteURL() {
        return this.getSpriteURL(false);
    }
    
    public URL getSpriteURL(final boolean b) {
        try {
            Map<String, String> map;
            StringBuilder append;
            try {
                map = this.map;
                append = new StringBuilder().append(Constants.e(GeItem.z[17]));
                if (b) {
                    final String e = Component.e(GeItem.z[18]);
                    return new URL(map.get(append.append(e).toString()));
                }
            }
            catch (MalformedURLException ex) {
                throw ex;
            }
            final String e = "";
            return new URL(map.get(append.append(e).toString()));
        }
        catch (MalformedURLException ex3) {
            try {
                StringBuilder append2;
                String[] queries;
                try {
                    append2 = new StringBuilder().append(Constants.e(GeItem.z[16]));
                    queries = GeItem.QUERIES;
                    if (b) {
                        final int n = 3;
                        return new URL(append2.append(queries[n]).append(this.getId()).toString());
                    }
                }
                catch (MalformedURLException ex2) {
                    throw ex2;
                }
                final int n = 2;
                return new URL(append2.append(queries[n]).append(this.getId()).toString());
            }
            catch (MalformedURLException ex4) {
                return null;
            }
        }
    }
    
    public int getTodayChange() {
        return this.parseNumber(this.map.get(Component.e(GeItem.z[42])));
    }
    
    public boolean isMember() {
        return Boolean.parseBoolean(this.map.get(Constants.e(GeItem.z[48])));
    }
    
    public static GeItem lookup(final int p0) {
        // 
        // This method could not be decompiled.
        // 
        // Original Bytecode:
        // 
        //     3: istore          9
        //     5: iload_0        
        //     6: ifgt            27
        //     9: new             Ljava/lang/IllegalArgumentException;
        //    12: dup            
        //    13: getstatic       org/powerbot/game/api/util/net/GeItem.z:[Ljava/lang/String;
        //    16: bipush          24
        //    18: aaload         
        //    19: invokestatic    org/powerbot/core/script/wrappers/Component.e:(Ljava/lang/String;)Ljava/lang/String;
        //    22: invokespecial   java/lang/IllegalArgumentException.<init>:(Ljava/lang/String;)V
        //    25: athrow         
        //    26: athrow         
        //    27: new             Ljava/net/URL;
        //    30: dup            
        //    31: new             Ljava/lang/StringBuilder;
        //    34: dup            
        //    35: invokespecial   java/lang/StringBuilder.<init>:()V
        //    38: getstatic       org/powerbot/game/api/util/net/GeItem.z:[Ljava/lang/String;
        //    41: bipush          16
        //    43: aaload         
        //    44: invokestatic    org/powerbot/core/script/internal/Constants.e:(Ljava/lang/String;)Ljava/lang/String;
        //    47: invokevirtual   java/lang/StringBuilder.append:(Ljava/lang/String;)Ljava/lang/StringBuilder;
        //    50: getstatic       org/powerbot/game/api/util/net/GeItem.QUERIES:[Ljava/lang/String;
        //    53: iconst_0       
        //    54: aaload         
        //    55: invokevirtual   java/lang/StringBuilder.append:(Ljava/lang/String;)Ljava/lang/StringBuilder;
        //    58: iload_0        
        //    59: invokevirtual   java/lang/StringBuilder.append:(I)Ljava/lang/StringBuilder;
        //    62: invokevirtual   java/lang/StringBuilder.toString:()Ljava/lang/String;
        //    65: invokespecial   java/net/URL.<init>:(Ljava/lang/String;)V
        //    68: astore_1       
        //    69: new             Ljava/util/Scanner;
        //    72: dup            
        //    73: aload_1        
        //    74: invokevirtual   java/net/URL.openStream:()Ljava/io/InputStream;
        //    77: invokespecial   java/util/Scanner.<init>:(Ljava/io/InputStream;)V
        //    80: astore_2       
        //    81: aload_2        
        //    82: getstatic       org/powerbot/game/api/util/net/GeItem.z:[Ljava/lang/String;
        //    85: bipush          31
        //    87: aaload         
        //    88: invokestatic    org/powerbot/core/script/wrappers/Component.e:(Ljava/lang/String;)Ljava/lang/String;
        //    91: invokevirtual   java/util/Scanner.useDelimiter:(Ljava/lang/String;)Ljava/util/Scanner;
        //    94: invokevirtual   java/util/Scanner.next:()Ljava/lang/String;
        //    97: astore_3       
        //    98: aload_2        
        //    99: invokevirtual   java/util/Scanner.close:()V
        //   102: aload_3        
        //   103: getstatic       org/powerbot/game/api/util/net/GeItem.z:[Ljava/lang/String;
        //   106: bipush          23
        //   108: aaload         
        //   109: invokestatic    org/powerbot/core/script/internal/Constants.e:(Ljava/lang/String;)Ljava/lang/String;
        //   112: getstatic       org/powerbot/game/api/util/net/GeItem.z:[Ljava/lang/String;
        //   115: bipush          25
        //   117: aaload         
        //   118: invokestatic    org/powerbot/core/script/wrappers/Component.e:(Ljava/lang/String;)Ljava/lang/String;
        //   121: invokevirtual   java/lang/String.replaceAll:(Ljava/lang/String;Ljava/lang/String;)Ljava/lang/String;
        //   124: getstatic       org/powerbot/game/api/util/net/GeItem.z:[Ljava/lang/String;
        //   127: bipush          20
        //   129: aaload         
        //   130: invokestatic    org/powerbot/core/script/internal/Constants.e:(Ljava/lang/String;)Ljava/lang/String;
        //   133: getstatic       org/powerbot/game/api/util/net/GeItem.z:[Ljava/lang/String;
        //   136: bipush          26
        //   138: aaload         
        //   139: invokestatic    org/powerbot/core/script/wrappers/Component.e:(Ljava/lang/String;)Ljava/lang/String;
        //   142: invokevirtual   java/lang/String.replaceAll:(Ljava/lang/String;Ljava/lang/String;)Ljava/lang/String;
        //   145: getstatic       org/powerbot/game/api/util/net/GeItem.z:[Ljava/lang/String;
        //   148: bipush          22
        //   150: aaload         
        //   151: invokestatic    org/powerbot/core/script/internal/Constants.e:(Ljava/lang/String;)Ljava/lang/String;
        //   154: getstatic       org/powerbot/game/api/util/net/GeItem.z:[Ljava/lang/String;
        //   157: bipush          27
        //   159: aaload         
        //   160: invokestatic    org/powerbot/core/script/wrappers/Component.e:(Ljava/lang/String;)Ljava/lang/String;
        //   163: invokevirtual   java/lang/String.replaceFirst:(Ljava/lang/String;Ljava/lang/String;)Ljava/lang/String;
        //   166: astore_3       
        //   167: aload_3        
        //   168: ldc_w           "u"
        //   171: invokestatic    org/powerbot/core/script/internal/Constants.e:(Ljava/lang/String;)Ljava/lang/String;
        //   174: ldc             ""
        //   176: invokevirtual   java/lang/String.replace:(Ljava/lang/CharSequence;Ljava/lang/CharSequence;)Ljava/lang/String;
        //   179: ldc_w           "\u0007"
        //   182: invokestatic    org/powerbot/core/script/wrappers/Component.e:(Ljava/lang/String;)Ljava/lang/String;
        //   185: invokevirtual   java/lang/String.split:(Ljava/lang/String;)[Ljava/lang/String;
        //   188: astore          4
        //   190: new             Ljava/util/HashMap;
        //   193: dup            
        //   194: invokespecial   java/util/HashMap.<init>:()V
        //   197: astore          5
        //   199: iconst_0       
        //   200: istore          6
        //   202: iload           6
        //   204: aload           4
        //   206: arraylength    
        //   207: if_icmpge       495
        //   210: aload           4
        //   212: iload           6
        //   214: aaload         
        //   215: ldc_w           "m"
        //   218: invokestatic    org/powerbot/core/script/internal/Constants.e:(Ljava/lang/String;)Ljava/lang/String;
        //   221: iconst_2       
        //   222: invokevirtual   java/lang/String.split:(Ljava/lang/String;I)[Ljava/lang/String;
        //   225: astore          7
        //   227: aload           7
        //   229: iconst_0       
        //   230: aaload         
        //   231: getstatic       org/powerbot/game/api/util/net/GeItem.z:[Ljava/lang/String;
        //   234: bipush          32
        //   236: aaload         
        //   237: invokestatic    org/powerbot/core/script/wrappers/Component.e:(Ljava/lang/String;)Ljava/lang/String;
        //   240: invokevirtual   java/lang/String.equals:(Ljava/lang/Object;)Z
        //   243: iload           9
        //   245: ifne            310
        //   248: ifeq            290
        //   251: goto            255
        //   254: athrow         
        //   255: aload           7
        //   257: iconst_0       
        //   258: getstatic       org/powerbot/game/api/util/net/GeItem.z:[Ljava/lang/String;
        //   261: bipush          17
        //   263: aaload         
        //   264: invokestatic    org/powerbot/core/script/internal/Constants.e:(Ljava/lang/String;)Ljava/lang/String;
        //   267: aastore        
        //   268: aload           7
        //   270: iconst_1       
        //   271: aload           7
        //   273: iconst_1       
        //   274: aaload         
        //   275: bipush          6
        //   277: invokevirtual   java/lang/String.substring:(I)Ljava/lang/String;
        //   280: aastore        
        //   281: iload           9
        //   283: ifeq            454
        //   286: goto            290
        //   289: athrow         
        //   290: aload           7
        //   292: iconst_0       
        //   293: aaload         
        //   294: getstatic       org/powerbot/game/api/util/net/GeItem.z:[Ljava/lang/String;
        //   297: bipush          21
        //   299: aaload         
        //   300: invokestatic    org/powerbot/core/script/wrappers/Component.e:(Ljava/lang/String;)Ljava/lang/String;
        //   303: invokevirtual   java/lang/String.equals:(Ljava/lang/Object;)Z
        //   306: goto            310
        //   309: athrow         
        //   310: iload           9
        //   312: ifne            350
        //   315: ifeq            325
        //   318: goto            322
        //   321: athrow         
        //   322: goto            487
        //   325: aload           7
        //   327: iconst_0       
        //   328: aaload         
        //   329: iload           9
        //   331: ifne            486
        //   334: getstatic       org/powerbot/game/api/util/net/GeItem.z:[Ljava/lang/String;
        //   337: bipush          30
        //   339: aaload         
        //   340: invokestatic    org/powerbot/core/script/internal/Constants.e:(Ljava/lang/String;)Ljava/lang/String;
        //   343: invokevirtual   java/lang/String.matches:(Ljava/lang/String;)Z
        //   346: goto            350
        //   349: athrow         
        //   350: ifeq            454
        //   353: aload           4
        //   355: iload           6
        //   357: iconst_1       
        //   358: isub           
        //   359: aaload         
        //   360: ldc_w           "C"
        //   363: invokestatic    org/powerbot/core/script/wrappers/Component.e:(Ljava/lang/String;)Ljava/lang/String;
        //   366: iconst_2       
        //   367: invokevirtual   java/lang/String.split:(Ljava/lang/String;I)[Ljava/lang/String;
        //   370: iconst_0       
        //   371: aaload         
        //   372: astore          8
        //   374: aload           7
        //   376: iconst_0       
        //   377: iload           9
        //   379: ifne            451
        //   382: aaload         
        //   383: getstatic       org/powerbot/game/api/util/net/GeItem.z:[Ljava/lang/String;
        //   386: bipush          29
        //   388: aaload         
        //   389: invokestatic    org/powerbot/core/script/internal/Constants.e:(Ljava/lang/String;)Ljava/lang/String;
        //   392: invokevirtual   java/lang/String.equals:(Ljava/lang/Object;)Z
        //   395: ifeq            444
        //   398: goto            402
        //   401: athrow         
        //   402: aload           5
        //   404: aload           7
        //   406: iconst_0       
        //   407: aaload         
        //   408: iload           9
        //   410: ifne            460
        //   413: goto            417
        //   416: athrow         
        //   417: invokeinterface java/util/Map.containsKey:(Ljava/lang/Object;)Z
        //   422: ifeq            454
        //   425: goto            429
        //   428: athrow         
        //   429: aload           7
        //   431: iconst_0       
        //   432: aload           8
        //   434: aastore        
        //   435: iload           9
        //   437: ifeq            454
        //   440: goto            444
        //   443: athrow         
        //   444: aload           7
        //   446: iconst_0       
        //   447: goto            451
        //   450: athrow         
        //   451: aload           8
        //   453: aastore        
        //   454: aload           5
        //   456: aload           7
        //   458: iconst_0       
        //   459: aaload         
        //   460: aload           7
        //   462: iconst_1       
        //   463: aaload         
        //   464: getstatic       org/powerbot/game/api/util/net/GeItem.z:[Ljava/lang/String;
        //   467: bipush          28
        //   469: aaload         
        //   470: invokestatic    org/powerbot/core/script/wrappers/Component.e:(Ljava/lang/String;)Ljava/lang/String;
        //   473: ldc             ""
        //   475: invokevirtual   java/lang/String.replaceAll:(Ljava/lang/String;Ljava/lang/String;)Ljava/lang/String;
        //   478: invokevirtual   java/lang/String.trim:()Ljava/lang/String;
        //   481: invokeinterface java/util/Map.put:(Ljava/lang/Object;Ljava/lang/Object;)Ljava/lang/Object;
        //   486: pop            
        //   487: iinc            6, 1
        //   490: iload           9
        //   492: ifeq            202
        //   495: new             Lorg/powerbot/game/api/util/net/GeItem;
        //   498: dup            
        //   499: aload           5
        //   501: invokespecial   org/powerbot/game/api/util/net/GeItem.<init>:(Ljava/util/Map;)V
        //   504: areturn        
        //   505: astore_1       
        //   506: aconst_null    
        //   507: areturn        
        //    StackMapTable: 00 1E FF 00 1A 00 0A 01 00 00 00 00 00 00 00 00 01 00 01 07 00 2E 00 FF 00 AE 00 0A 01 07 00 0E 07 00 1A 07 00 07 07 01 A1 07 00 0A 01 00 00 01 00 00 FF 00 33 00 0A 01 07 00 0E 07 00 1A 07 00 07 07 01 A1 07 00 0A 01 07 01 A1 00 01 00 01 07 00 2E 00 61 07 00 2E 00 52 07 00 2E 40 01 4A 07 00 2E 00 02 57 07 00 2E 40 01 FF 00 32 00 0A 01 07 00 0E 07 00 1A 07 00 07 07 01 A1 07 00 0A 01 07 01 A1 07 00 07 01 00 01 07 00 2E 00 4D 07 00 2E FF 00 00 00 0A 01 07 00 0E 07 00 1A 07 00 07 07 01 A1 07 00 0A 01 07 01 A1 07 00 07 01 00 02 07 00 0A 07 00 07 4A 07 00 2E 00 4D 07 00 2E 00 45 07 00 2E FF 00 00 00 0A 01 07 00 0E 07 00 1A 07 00 07 07 01 A1 07 00 0A 01 07 01 A1 07 00 07 01 00 02 07 01 A1 01 FF 00 02 00 0A 01 07 00 0E 07 00 1A 07 00 07 07 01 A1 07 00 0A 01 07 01 A1 00 01 00 00 FF 00 05 00 0A 01 07 00 0E 07 00 1A 07 00 07 07 01 A1 07 00 0A 01 07 01 A1 00 01 00 02 07 00 0A 07 00 07 59 07 00 51 00 FF 00 07 00 0A 01 07 00 0E 07 00 1A 07 00 07 07 01 A1 07 00 0A 01 00 00 01 00 00 FF 00 09 00 0A 01 00 00 00 00 00 00 00 00 01 00 01 07 00 2E
        //    Exceptions:
        //  Try           Handler
        //  Start  End    Start  End    Type                 
        //  -----  -----  -----  -----  ---------------------
        //  429    447    450    451    Ljava/io/IOException;
        //  417    440    443    444    Ljava/io/IOException;
        //  402    425    428    429    Ljava/io/IOException;
        //  382    413    416    417    Ljava/io/IOException;
        //  374    398    401    402    Ljava/io/IOException;
        //  325    346    349    350    Ljava/io/IOException;
        //  310    318    321    322    Ljava/io/IOException;
        //  255    306    309    310    Ljava/io/IOException;
        //  248    286    289    290    Ljava/io/IOException;
        //  227    251    254    255    Ljava/io/IOException;
        //  5      26     26     27     Ljava/io/IOException;
        //  27     504    505    508    Ljava/io/IOException;
        // 
        // The error that occurred was:
        // 
        // java.lang.IllegalStateException: Expression is linked from several locations: Label_0255:
        //     at com.strobel.decompiler.ast.Error.expressionLinkedFromMultipleLocations(Error.java:27)
        //     at com.strobel.decompiler.ast.AstOptimizer.mergeDisparateObjectInitializations(AstOptimizer.java:2596)
        //     at com.strobel.decompiler.ast.AstOptimizer.optimize(AstOptimizer.java:235)
        //     at com.strobel.decompiler.ast.AstOptimizer.optimize(AstOptimizer.java:42)
        //     at com.strobel.decompiler.languages.java.ast.AstMethodBodyBuilder.createMethodBody(AstMethodBodyBuilder.java:214)
        //     at com.strobel.decompiler.languages.java.ast.AstMethodBodyBuilder.createMethodBody(AstMethodBodyBuilder.java:99)
        //     at com.strobel.decompiler.languages.java.ast.AstBuilder.createMethodBody(AstBuilder.java:782)
        //     at com.strobel.decompiler.languages.java.ast.AstBuilder.createMethod(AstBuilder.java:675)
        //     at com.strobel.decompiler.languages.java.ast.AstBuilder.addTypeMembers(AstBuilder.java:552)
        //     at com.strobel.decompiler.languages.java.ast.AstBuilder.createTypeCore(AstBuilder.java:519)
        //     at com.strobel.decompiler.languages.java.ast.AstBuilder.createTypeNoCache(AstBuilder.java:161)
        //     at com.strobel.decompiler.languages.java.ast.AstBuilder.createType(AstBuilder.java:150)
        //     at com.strobel.decompiler.languages.java.ast.AstBuilder.addType(AstBuilder.java:125)
        //     at com.strobel.decompiler.languages.java.JavaLanguage.buildAst(JavaLanguage.java:71)
        //     at com.strobel.decompiler.languages.java.JavaLanguage.decompileType(JavaLanguage.java:59)
        //     at com.strobel.decompiler.DecompilerDriver.decompileType(DecompilerDriver.java:330)
        //     at com.strobel.decompiler.DecompilerDriver.decompileJar(DecompilerDriver.java:251)
        //     at com.strobel.decompiler.DecompilerDriver.main(DecompilerDriver.java:126)
        // 
        throw new IllegalStateException("An error occurred while decompiling this method.");
    }
    
    public static GeItem lookup(final String s) {
        final int a = Highscores.a;
        Label_0025: {
            try {
                final String s2 = s;
                if (a != 0) {
                    break Label_0025;
                }
                if (s == null) {
                    break Label_0025;
                }
            }
            catch (IOException ex) {
                throw ex;
            }
            final String s2 = s;
            try {
                if (s2.isEmpty()) {
                    throw new IllegalArgumentException(Constants.e(GeItem.z[39]));
                }
            }
            catch (IOException ex2) {
                throw ex2;
            }
        }
        try {
            final Scanner scanner = new Scanner(new URL(Component.e(GeItem.z[38]) + GeItem.QUERIES[1] + URLEncoder.encode(s, Constants.e(GeItem.z[37]))).openStream());
            int n = -1;
            while (true) {
                while (scanner.hasNextLine()) {
                    String nextLine = scanner.nextLine();
                    int contains = 0;
                    Label_0313: {
                        int n3 = 0;
                        Label_0300: {
                            Label_0286: {
                                String s3 = null;
                                String e = null;
                                Label_0215: {
                                    int n2 = 0;
                                    Label_0162: {
                                        Label_0152: {
                                            try {
                                                n2 = (n3 = (contains = (nextLine.contains(Component.e(GeItem.z[40])) ? 1 : 0)));
                                                if (a != 0) {
                                                    break Label_0300;
                                                }
                                                final int n4 = a;
                                                if (n4 == 0) {
                                                    break Label_0152;
                                                }
                                                break Label_0162;
                                            }
                                            catch (IOException ex3) {
                                                throw ex3;
                                            }
                                            try {
                                                final int n4 = a;
                                                if (n4 != 0) {
                                                    break Label_0162;
                                                }
                                                if (n2 == 0) {
                                                    break Label_0162;
                                                }
                                            }
                                            catch (IOException ex4) {
                                                throw ex4;
                                            }
                                        }
                                        break;
                                        try {
                                            s3 = nextLine;
                                            e = Constants.e(GeItem.z[35]);
                                            if (a != 0) {
                                                break Label_0215;
                                            }
                                            s3.contains(e);
                                        }
                                        catch (IOException ex5) {
                                            throw ex5;
                                        }
                                    }
                                    if (n2 == 0) {
                                        break Label_0286;
                                    }
                                    final String substring;
                                    final String s4;
                                    nextLine = (s4 = (substring = nextLine.substring(nextLine.indexOf(Component.e(GeItem.z[36])) + 4)));
                                }
                                final String substring2 = s3.substring(e.indexOf(Constants.e("j")) + 2, nextLine.length() - 2);
                                int n6 = 0;
                                Label_0256: {
                                    int n5;
                                    try {
                                        n5 = (n6 = (substring2.equalsIgnoreCase(s) ? 1 : 0));
                                        if (a != 0) {
                                            break Label_0256;
                                        }
                                        if (n5 != 0) {
                                            break Label_0256;
                                        }
                                        break Label_0286;
                                    }
                                    catch (IOException ex6) {
                                        throw ex6;
                                    }
                                    try {
                                        if (n5 == 0) {
                                            break Label_0286;
                                        }
                                        n6 = Integer.parseInt(nextLine.substring(0, nextLine.indexOf(Component.e("["))));
                                    }
                                    catch (IOException ex7) {
                                        throw ex7;
                                    }
                                }
                                n = n6;
                                try {
                                    if (a != 0) {
                                        if (a == 0) {
                                            continue;
                                        }
                                    }
                                }
                                catch (IOException ex8) {
                                    throw ex8;
                                }
                            }
                            break;
                            try {
                                if (a != 0) {
                                    return lookup(contains);
                                }
                                final int n7 = -1;
                                if (n3 != n7) {
                                    break Label_0313;
                                }
                                return null;
                            }
                            catch (IOException ex9) {
                                throw ex9;
                            }
                        }
                        try {
                            final int n7 = -1;
                            if (n3 == n7) {
                                return null;
                            }
                            contains = n;
                        }
                        catch (IOException ex10) {
                            throw ex10;
                        }
                    }
                    return lookup(contains);
                }
                scanner.close();
                int n3;
                int contains = n3 = n;
                continue;
            }
        }
        catch (IOException ex11) {}
        return null;
    }
    
    private int parseNumber(final String str) {
        final int a = Highscores.a;
        Label_0129: {
            try {
                final int n;
                final boolean b = (n = (str.matches(Constants.e(GeItem.z[44])) ? 1 : 0)) != 0;
                if (a != 0) {
                    return n;
                }
                if (!b) {
                    break Label_0129;
                }
            }
            catch (NumberFormatException ex) {
                throw ex;
            }
            final double double1 = Double.parseDouble(str.substring(0, str.length() - 1));
            Label_0108: {
                switch (str.charAt(str.length() - 1)) {
                    case 'b': {
                        final double n2 = 1.0E9;
                        if (a != 0) {
                            break Label_0108;
                        }
                        return (int)(double1 * n2);
                    }
                    case 'm': {
                        final double n2 = 1000000.0;
                        if (a != 0) {
                            break Label_0108;
                        }
                        return (int)(double1 * n2);
                    }
                    case 'k': {
                        final double n2 = 1000.0;
                        if (a != 0) {
                            break;
                        }
                        return (int)(double1 * n2);
                    }
                }
            }
            final double n2 = 1.0;
            return (int)(double1 * n2);
            try {
                return Integer.parseInt(str.replace(Component.e("U"), ""));
            }
            catch (NumberFormatException ex2) {
                System.out.println(Constants.e(GeItem.z[45]) + str);
                return Integer.parseInt(str.replaceAll(Component.e(GeItem.z[46]), ""));
            }
        }
    }
    
    @Override
    public String toString() {
        final int a = Highscores.a;
        final StringBuilder sb = new StringBuilder(Constants.e(GeItem.z[1]));
        sb.append(Component.e(GeItem.z[9])).append(this.getName()).append(Constants.e(GeItem.z[7]));
        sb.append(Component.e(GeItem.z[4])).append(this.getId()).append(Constants.e(GeItem.z[7]));
        sb.append(Component.e(GeItem.z[10])).append(this.getDescription()).append(Constants.e(GeItem.z[7]));
        sb.append(Component.e(GeItem.z[3])).append(this.getCategory()).append(Constants.e(GeItem.z[7]));
        sb.append(Component.e(GeItem.z[5])).append(this.isMember()).append(Constants.e(GeItem.z[7]));
        sb.append(Component.e(GeItem.z[2])).append(this.getPrice()).append(Constants.e(GeItem.z[7]));
        sb.append(Component.e(GeItem.z[8])).append(this.getTodayChange()).append(Constants.e(GeItem.z[7]));
        sb.append(Component.e(GeItem.z[6])).append(this.get30DayChange()).append(Constants.e(GeItem.z[7]));
        sb.append(Component.e(GeItem.z[15])).append(this.get90DayChange()).append(Constants.e(GeItem.z[7]));
        sb.append(Component.e(GeItem.z[14])).append(this.get180DayChange()).append(Constants.e(GeItem.z[0]));
        sb.append(Component.e(GeItem.z[11])).append(this.getSpriteURL().toString()).append(Constants.e(GeItem.z[7]));
        sb.append(Component.e(GeItem.z[13])).append(this.getSpriteURL(true).toString()).append(Constants.e(GeItem.z[12]));
        final String string = sb.toString();
        if (a != 0) {
            int a2 = Task.a;
            Task.a = ++a2;
        }
        return string;
    }
    
    static {
        String[] queries;
        String[] array56;
        String[] array55;
        String[] array54;
        String[] array53;
        String[] z2;
        String[] array52;
        String[] array51;
        String[] array50;
        String[] array49;
        String[] array48;
        String[] array47;
        String[] array46;
        String[] array45;
        String[] array44;
        String[] array43;
        String[] array42;
        String[] array41;
        String[] array40;
        String[] array39;
        String[] array38;
        String[] array37;
        String[] array36;
        String[] array35;
        String[] array34;
        String[] array33;
        String[] array32;
        String[] array31;
        String[] array30;
        String[] array29;
        String[] array28;
        String[] array27;
        String[] array26;
        String[] array25;
        String[] array24;
        String[] array23;
        String[] array22;
        String[] array21;
        String[] array20;
        String[] array19;
        String[] array18;
        String[] array17;
        String[] array16;
        String[] array15;
        String[] array14;
        String[] array13;
        String[] array12;
        String[] array11;
        String[] array10;
        String[] array9;
        String[] array8;
        String[] array7;
        String[] array6;
        String[] array5;
        String[] array4;
        String[] array3;
        String[] array2;
        String[] array = array2 = (array3 = (array4 = (array5 = (array6 = (array7 = (array8 = (array9 = (array10 = (array11 = (array12 = (array13 = (array14 = (array15 = (array16 = (array17 = (array18 = (array19 = (array20 = (array21 = (array22 = (array23 = (array24 = (array25 = (array26 = (array27 = (array28 = (array29 = (array30 = (array31 = (array32 = (array33 = (array34 = (array35 = (array36 = (array37 = (array38 = (array39 = (array40 = (array41 = (array42 = (array43 = (array44 = (array45 = (array46 = (array47 = (array48 = (array49 = (array50 = (array51 = (array52 = (z2 = (array53 = (array54 = (array55 = (array56 = (queries = new String[52]))))))))))))))))))))))))))))))))))))))))))))))))))))))));
        int n56;
        int n55;
        int n54;
        int n53;
        int n52;
        int n51;
        int n50;
        int n49;
        int n48;
        int n47;
        int n46;
        int n45;
        int n44;
        int n43;
        int n42;
        int n41;
        int n40;
        int n39;
        int n38;
        int n37;
        int n36;
        int n35;
        int n34;
        int n33;
        int n32;
        int n31;
        int n30;
        int n29;
        int n28;
        int n27;
        int n26;
        int n25;
        int n24;
        int n23;
        int n22;
        int n21;
        int n20;
        int n19;
        int n18;
        int n17;
        int n16;
        int n15;
        int n14;
        int n13;
        int n12;
        int n11;
        int n10;
        int n9;
        int n8;
        int n7;
        int n6;
        int n5;
        int n4;
        int n3;
        int n2;
        int n = n2 = (n3 = (n4 = (n5 = (n6 = (n7 = (n8 = (n9 = (n10 = (n11 = (n12 = (n13 = (n14 = (n15 = (n16 = (n17 = (n18 = (n19 = (n20 = (n21 = (n22 = (n23 = (n24 = (n25 = (n26 = (n27 = (n28 = (n29 = (n30 = (n31 = (n32 = (n33 = (n34 = (n35 = (n36 = (n37 = (n38 = (n39 = (n40 = (n41 = (n42 = (n43 = (n44 = (n45 = (n46 = (n47 = (n48 = (n49 = (n50 = (n51 = (n52 = (n53 = (n54 = (n55 = (n56 = 0))))))))))))))))))))))))))))))))))))))))))))))))))))));
        String s = "\u000e)%V";
        int n57 = -1;
        String intern = null;
    Label_0638_Outer:
        while (true) {
            final char[] charArray = s.toCharArray();
            int length;
            int n59;
            final int n58 = n59 = (length = charArray.length);
            int n60 = 0;
            while (true) {
                Label_0714: {
                    if (n58 > 1) {
                        break Label_0714;
                    }
                    length = (n59 = n60);
                    do {
                        final char c = charArray[n59];
                        char c2 = '\0';
                        switch (n60 % 5) {
                            case 0: {
                                c2 = 'V';
                                break;
                            }
                            case 1: {
                                c2 = '^';
                                break;
                            }
                            case 2: {
                                c2 = '\\';
                                break;
                            }
                            case 3: {
                                c2 = '!';
                                break;
                            }
                            default: {
                                c2 = '?';
                                break;
                            }
                        }
                        charArray[length] = (char)(c ^ c2);
                        ++n60;
                    } while (n58 == 0);
                }
                if (n58 > n60) {
                    continue;
                }
                break;
            }
            intern = new String(charArray).intern();
            switch (n57) {
                default: {
                    array2[n2] = intern;
                    n = (n2 = (n3 = (n4 = (n5 = (n6 = (n7 = (n8 = (n9 = (n10 = (n11 = (n12 = (n13 = (n14 = (n15 = (n16 = (n17 = (n18 = (n19 = (n20 = (n21 = (n22 = (n23 = (n24 = (n25 = (n26 = (n27 = (n28 = (n29 = (n30 = (n31 = (n32 = (n33 = (n34 = (n35 = (n36 = (n37 = (n38 = (n39 = (n40 = (n41 = (n42 = (n43 = (n44 = (n45 = (n46 = (n47 = (n48 = (n49 = (n50 = (n51 = (n52 = (n53 = (n54 = (n55 = (n56 = 1)))))))))))))))))))))))))))))))))))))))))))))))))))))));
                    s = "F>BP\r>R";
                    n57 = 0;
                    continue Label_0638_Outer;
                }
                case 0: {
                    array[n] = intern;
                    n = (n2 = (n3 = (n4 = (n5 = (n6 = (n7 = (n8 = (n9 = (n10 = (n11 = (n12 = (n13 = (n14 = (n15 = (n16 = (n17 = (n18 = (n19 = (n20 = (n21 = (n22 = (n23 = (n24 = (n25 = (n26 = (n27 = (n28 = (n29 = (n30 = (n31 = (n32 = (n33 = (n34 = (n35 = (n36 = (n37 = (n38 = (n39 = (n40 = (n41 = (n42 = (n43 = (n44 = (n45 = (n46 = (n47 = (n48 = (n49 = (n50 = (n51 = (n52 = (n53 = (n54 = (n55 = (n56 = 2)))))))))))))))))))))))))))))))))))))))))))))))))))))));
                    s = "_\u001cLr#\\\u0007";
                    n57 = 1;
                    continue Label_0638_Outer;
                }
                case 1: {
                    array3[n3] = intern;
                    n = (n2 = (n3 = (n4 = (n5 = (n6 = (n7 = (n8 = (n9 = (n10 = (n11 = (n12 = (n13 = (n14 = (n15 = (n16 = (n17 = (n18 = (n19 = (n20 = (n21 = (n22 = (n23 = (n24 = (n25 = (n26 = (n27 = (n28 = (n29 = (n30 = (n31 = (n32 = (n33 = (n34 = (n35 = (n36 = (n37 = (n38 = (n39 = (n40 = (n41 = (n42 = (n43 = (n44 = (n45 = (n46 = (n47 = (n48 = (n49 = (n50 = (n51 = (n52 = (n53 = (n54 = (n55 = (n56 = 3)))))))))))))))))))))))))))))))))))))))))))))))))))))));
                    s = "\u0005F\u0018=h@\u001c\\+f";
                    n57 = 2;
                    continue Label_0638_Outer;
                }
                case 2: {
                    array4[n4] = intern;
                    n = (n2 = (n3 = (n4 = (n5 = (n6 = (n7 = (n8 = (n9 = (n10 = (n11 = (n12 = (n13 = (n14 = (n15 = (n16 = (n17 = (n18 = (n19 = (n20 = (n21 = (n22 = (n23 = (n24 = (n25 = (n26 = (n27 = (n28 = (n29 = (n30 = (n31 = (n32 = (n33 = (n34 = (n35 = (n36 = (n37 = (n38 = (n39 = (n40 = (n41 = (n42 = (n43 = (n44 = (n45 = (n46 = (n47 = (n48 = (n49 = (n50 = (n51 = (n52 = (n53 = (n54 = (n55 = (n56 = 4)))))))))))))))))))))))))))))))))))))))))))))))))))))));
                    s = "F\u001a@|f\u000fCVx";
                    n57 = 3;
                    continue Label_0638_Outer;
                }
                case 3: {
                    array5[n5] = intern;
                    n = (n2 = (n3 = (n4 = (n5 = (n6 = (n7 = (n8 = (n9 = (n10 = (n11 = (n12 = (n13 = (n14 = (n15 = (n16 = (n17 = (n18 = (n19 = (n20 = (n21 = (n22 = (n23 = (n24 = (n25 = (n26 = (n27 = (n28 = (n29 = (n30 = (n31 = (n32 = (n33 = (n34 = (n35 = (n36 = (n37 = (n38 = (n39 = (n40 = (n41 = (n42 = (n43 = (n44 = (n45 = (n46 = (n47 = (n48 = (n49 = (n50 = (n51 = (n52 = (n53 = (n54 = (n55 = (n56 = 5)))))))))))))))))))))))))))))))))))))))))))))))))))))));
                    s = "\u000bB\u0001:j]T\u0005";
                    n57 = 4;
                    continue Label_0638_Outer;
                }
                case 4: {
                    array6[n6] = intern;
                    n = (n2 = (n3 = (n4 = (n5 = (n6 = (n7 = (n8 = (n9 = (n10 = (n11 = (n12 = (n13 = (n14 = (n15 = (n16 = (n17 = (n18 = (n19 = (n20 = (n21 = (n22 = (n23 = (n24 = (n25 = (n26 = (n27 = (n28 = (n29 = (n30 = (n31 = (n32 = (n33 = (n34 = (n35 = (n36 = (n37 = (n38 = (n39 = (n40 = (n41 = (n42 = (n43 = (n44 = (n45 = (n46 = (n47 = (n48 = (n49 = (n50 = (n51 = (n52 = (n53 = (n54 = (n55 = (n56 = 6)))))))))))))))))))))))))))))))))))))))))))))))))))))));
                    s = "U\u0017A<nVT\u0005";
                    n57 = 5;
                    continue Label_0638_Outer;
                }
                case 5: {
                    array7[n7] = intern;
                    n = (n2 = (n3 = (n4 = (n5 = (n6 = (n7 = (n8 = (n9 = (n10 = (n11 = (n12 = (n13 = (n14 = (n15 = (n16 = (n17 = (n18 = (n19 = (n20 = (n21 = (n22 = (n23 = (n24 = (n25 = (n26 = (n27 = (n28 = (n29 = (n30 = (n31 = (n32 = (n33 = (n34 = (n35 = (n36 = (n37 = (n38 = (n39 = (n40 = (n41 = (n42 = (n43 = (n44 = (n45 = (n46 = (n47 = (n48 = (n49 = (n50 = (n51 = (n52 = (n53 = (n54 = (n55 = (n56 = 7)))))))))))))))))))))))))))))))))))))))))))))))))))))));
                    s = "!'+";
                    n57 = 6;
                    continue Label_0638_Outer;
                }
                case 6: {
                    array8[n8] = intern;
                    n = (n2 = (n3 = (n4 = (n5 = (n6 = (n7 = (n8 = (n9 = (n10 = (n11 = (n12 = (n13 = (n14 = (n15 = (n16 = (n17 = (n18 = (n19 = (n20 = (n21 = (n22 = (n23 = (n24 = (n25 = (n26 = (n27 = (n28 = (n29 = (n30 = (n31 = (n32 = (n33 = (n34 = (n35 = (n36 = (n37 = (n38 = (n39 = (n40 = (n41 = (n42 = (n43 = (n44 = (n45 = (n46 = (n47 = (n48 = (n49 = (n50 = (n51 = (n52 = (n53 = (n54 = (n55 = (n56 = 8)))))))))))))))))))))))))))))))))))))))))))))))))))))));
                    s = "\u0005O\r6hJ5Q~\"\u0007^Vx";
                    n57 = 7;
                    continue Label_0638_Outer;
                }
                case 7: {
                    array9[n9] = intern;
                    n = (n2 = (n3 = (n4 = (n5 = (n6 = (n7 = (n8 = (n9 = (n10 = (n11 = (n12 = (n13 = (n14 = (n15 = (n16 = (n17 = (n18 = (n19 = (n20 = (n21 = (n22 = (n23 = (n24 = (n25 = (n26 = (n27 = (n28 = (n29 = (n30 = (n31 = (n32 = (n33 = (n34 = (n35 = (n36 = (n37 = (n38 = (n39 = (n40 = (n41 = (n42 = (n43 = (n44 = (n45 = (n46 = (n47 = (n48 = (n49 = (n50 = (n51 = (n52 = (n53 = (n54 = (n55 = (n56 = 9)))))))))))))))))))))))))))))))))))))))))))))))))))))));
                    s = "F\u001a@|f\bF\u0001=5\u000f";
                    n57 = 8;
                    continue Label_0638_Outer;
                }
                case 8: {
                    array10[n10] = intern;
                    n = (n2 = (n3 = (n4 = (n5 = (n6 = (n7 = (n8 = (n9 = (n10 = (n11 = (n12 = (n13 = (n14 = (n15 = (n16 = (n17 = (n18 = (n19 = (n20 = (n21 = (n22 = (n23 = (n24 = (n25 = (n26 = (n27 = (n28 = (n29 = (n30 = (n31 = (n32 = (n33 = (n34 = (n35 = (n36 = (n37 = (n38 = (n39 = (n40 = (n41 = (n42 = (n43 = (n44 = (n45 = (n46 = (n47 = (n48 = (n49 = (n50 = (n51 = (n52 = (n53 = (n54 = (n55 = (n56 = 10)))))))))))))))))))))))))))))))))))))))))))))))))))))));
                    s = "K\u000bVr4\u000fW\u00181`AT\u0005";
                    n57 = 9;
                    continue Label_0638_Outer;
                }
                case 9: {
                    array11[n11] = intern;
                    n = (n2 = (n3 = (n4 = (n5 = (n6 = (n7 = (n8 = (n9 = (n10 = (n11 = (n12 = (n13 = (n14 = (n15 = (n16 = (n17 = (n18 = (n19 = (n20 = (n21 = (n22 = (n23 = (n24 = (n25 = (n26 = (n27 = (n28 = (n29 = (n30 = (n31 = (n32 = (n33 = (n34 = (n35 = (n36 = (n37 = (n38 = (n39 = (n40 = (n41 = (n42 = (n43 = (n44 = (n45 = (n46 = (n47 = (n48 = (n49 = (n50 = (n51 = (n52 = (n53 = (n54 = (n55 = (n56 = 11)))))))))))))))))))))))))))))))))))))))))))))))))))))));
                    s = "\\\u001eWx2\u0003|\u00027}B\u000fI+f";
                    n57 = 10;
                    continue Label_0638_Outer;
                }
                case 10: {
                    array12[n12] = intern;
                    n = (n2 = (n3 = (n4 = (n5 = (n6 = (n7 = (n8 = (n9 = (n10 = (n11 = (n12 = (n13 = (n14 = (n15 = (n16 = (n17 = (n18 = (n19 = (n20 = (n21 = (n22 = (n23 = (n24 = (n25 = (n26 = (n27 = (n28 = (n29 = (n30 = (n31 = (n32 = (n33 = (n34 = (n35 = (n36 = (n37 = (n38 = (n39 = (n40 = (n41 = (n42 = (n43 = (n44 = (n45 = (n46 = (n47 = (n48 = (n49 = (n50 = (n51 = (n52 = (n53 = (n54 = (n55 = (n56 = 12)))))))))))))))))))))))))))))))))))))))))))))))))))))));
                    s = "\u000eT";
                    n57 = 11;
                    continue Label_0638_Outer;
                }
                case 11: {
                    array13[n13] = intern;
                    n = (n2 = (n3 = (n4 = (n5 = (n6 = (n7 = (n8 = (n9 = (n10 = (n11 = (n12 = (n13 = (n14 = (n15 = (n16 = (n17 = (n18 = (n19 = (n20 = (n21 = (n22 = (n23 = (n24 = (n25 = (n26 = (n27 = (n28 = (n29 = (n30 = (n31 = (n32 = (n33 = (n34 = (n35 = (n36 = (n37 = (n38 = (n39 = (n40 = (n41 = (n42 = (n43 = (n44 = (n45 = (n46 = (n47 = (n48 = (n49 = (n50 = (n51 = (n52 = (n53 = (n54 = (n55 = (n56 = 13)))))))))))))))))))))))))))))))))))))))))))))))))))))));
                    s = "C\u000fWv#\\\u0007";
                    n57 = 12;
                    continue Label_0638_Outer;
                }
                case 12: {
                    array14[n14] = intern;
                    n = (n2 = (n3 = (n4 = (n5 = (n6 = (n7 = (n8 = (n9 = (n10 = (n11 = (n12 = (n13 = (n14 = (n15 = (n16 = (n17 = (n18 = (n19 = (n20 = (n21 = (n22 = (n23 = (n24 = (n25 = (n26 = (n27 = (n28 = (n29 = (n30 = (n31 = (n32 = (n33 = (n34 = (n35 = (n36 = (n37 = (n38 = (n39 = (n40 = (n41 = (n42 = (n43 = (n44 = (n45 = (n46 = (n47 = (n48 = (n49 = (n50 = (n51 = (n52 = (n53 = (n54 = (n55 = (n56 = 14)))))))))))))))))))))))))))))))))))))))))))))))))))))));
                    s = "\u001eV\u0015<\"\u0007^Vx";
                    n57 = 13;
                    continue Label_0638_Outer;
                }
                case 13: {
                    array15[n15] = intern;
                    n = (n2 = (n3 = (n4 = (n5 = (n6 = (n7 = (n8 = (n9 = (n10 = (n11 = (n12 = (n13 = (n14 = (n15 = (n16 = (n17 = (n18 = (n19 = (n20 = (n21 = (n22 = (n23 = (n24 = (n25 = (n26 = (n27 = (n28 = (n29 = (n30 = (n31 = (n32 = (n33 = (n34 = (n35 = (n36 = (n37 = (n38 = (n39 = (n40 = (n41 = (n42 = (n43 = (n44 = (n45 = (n46 = (n47 = (n48 = (n49 = (n50 = (n51 = (n52 = (n53 = (n54 = (n55 = (n56 = 15)))))))))))))))))))))))))))))))))))))))))))))))))))))));
                    s = "_\u0017A<nVT\u0005";
                    n57 = 14;
                    continue Label_0638_Outer;
                }
                case 14: {
                    array16[n16] = intern;
                    n = (n2 = (n3 = (n4 = (n5 = (n6 = (n7 = (n8 = (n9 = (n10 = (n11 = (n12 = (n13 = (n14 = (n15 = (n16 = (n17 = (n18 = (n19 = (n20 = (n21 = (n22 = (n23 = (n24 = (n25 = (n26 = (n27 = (n28 = (n29 = (n30 = (n31 = (n32 = (n33 = (n34 = (n35 = (n36 = (n37 = (n38 = (n39 = (n40 = (n41 = (n42 = (n43 = (n44 = (n45 = (n46 = (n47 = (n48 = (n49 = (n50 = (n51 = (n52 = (n53 = (n54 = (n55 = (n56 = 16)))))))))))))))))))))))))))))))))))))))))))))))))))))));
                    s = "i/\u007fTR|&*\u0013Hw2hA\u001b}{,\u0018_r8jT\r}j6\u001b";
                    n57 = 15;
                    continue Label_0638_Outer;
                }
                case 15: {
                    array17[n17] = intern;
                    n = (n2 = (n3 = (n4 = (n5 = (n6 = (n7 = (n8 = (n9 = (n10 = (n11 = (n12 = (n13 = (n14 = (n15 = (n16 = (n17 = (n18 = (n19 = (n20 = (n21 = (n22 = (n23 = (n24 = (n25 = (n26 = (n27 = (n28 = (n29 = (n30 = (n31 = (n32 = (n33 = (n34 = (n35 = (n36 = (n37 = (n38 = (n39 = (n40 = (n41 = (n42 = (n43 = (n44 = (n45 = (n46 = (n47 = (n48 = (n49 = (n50 = (n51 = (n52 = (n53 = (n54 = (n55 = (n56 = 17)))))))))))))))))))))))))))))))))))))))))))))))))))))));
                    s = ":j6\u0018";
                    n57 = 16;
                    continue Label_0638_Outer;
                }
                case 16: {
                    array18[n18] = intern;
                    n = (n2 = (n3 = (n4 = (n5 = (n6 = (n7 = (n8 = (n9 = (n10 = (n11 = (n12 = (n13 = (n14 = (n15 = (n16 = (n17 = (n18 = (n19 = (n20 = (n21 = (n22 = (n23 = (n24 = (n25 = (n26 = (n27 = (n28 = (n29 = (n30 = (n31 = (n32 = (n33 = (n34 = (n35 = (n36 = (n37 = (n38 = (n39 = (n40 = (n41 = (n42 = (n43 = (n44 = (n45 = (n46 = (n47 = (n48 = (n49 = (n50 = (n51 = (n52 = (n53 = (n54 = (n55 = (n56 = 18)))))))))))))))))))))))))))))))))))))))))))))))))))))));
                    s = "9K\r*hJ";
                    n57 = 17;
                    continue Label_0638_Outer;
                }
                case 17: {
                    array19[n19] = intern;
                    n = (n2 = (n3 = (n4 = (n5 = (n6 = (n7 = (n8 = (n9 = (n10 = (n11 = (n12 = (n13 = (n14 = (n15 = (n16 = (n17 = (n18 = (n19 = (n20 = (n21 = (n22 = (n23 = (n24 = (n25 = (n26 = (n27 = (n28 = (n29 = (n30 = (n31 = (n32 = (n33 = (n34 = (n35 = (n36 = (n37 = (n38 = (n39 = (n40 = (n41 = (n42 = (n43 = (n44 = (n45 = (n46 = (n47 = (n48 = (n49 = (n50 = (n51 = (n52 = (n53 = (n54 = (n55 = (n56 = 19)))))))))))))))))))))))))))))))))))))))))))))))))))))));
                    s = "e:r\u001dX";
                    n57 = 18;
                    continue Label_0638_Outer;
                }
                case 18: {
                    array20[n20] = intern;
                    n = (n2 = (n3 = (n4 = (n5 = (n6 = (n7 = (n8 = (n9 = (n10 = (n11 = (n12 = (n13 = (n14 = (n15 = (n16 = (n17 = (n18 = (n19 = (n20 = (n21 = (n22 = (n23 = (n24 = (n25 = (n26 = (n27 = (n28 = (n29 = (n30 = (n31 = (n32 = (n33 = (n34 = (n35 = (n36 = (n37 = (n38 = (n39 = (n40 = (n41 = (n42 = (n43 = (n44 = (n45 = (n46 = (n47 = (n48 = (n49 = (n50 = (n51 = (n52 = (n53 = (n54 = (n55 = (n56 = 20)))))))))))))))))))))))))))))))))))))))))))))))))))))));
                    s = "#w)";
                    n57 = 19;
                    continue Label_0638_Outer;
                }
                case 19: {
                    array21[n21] = intern;
                    n = (n2 = (n3 = (n4 = (n5 = (n6 = (n7 = (n8 = (n9 = (n10 = (n11 = (n12 = (n13 = (n14 = (n15 = (n16 = (n17 = (n18 = (n19 = (n20 = (n21 = (n22 = (n23 = (n24 = (n25 = (n26 = (n27 = (n28 = (n29 = (n30 = (n31 = (n32 = (n33 = (n34 = (n35 = (n36 = (n37 = (n38 = (n39 = (n40 = (n41 = (n42 = (n43 = (n44 = (n45 = (n46 = (n47 = (n48 = (n49 = (n50 = (n51 = (n52 = (n53 = (n54 = (n55 = (n56 = 21)))))))))))))))))))))))))))))))))))))))))))))))))))))));
                    s = "L\u001bWc#\bS";
                    n57 = 20;
                    continue Label_0638_Outer;
                }
                case 20: {
                    array22[n22] = intern;
                    n = (n2 = (n3 = (n4 = (n5 = (n6 = (n7 = (n8 = (n9 = (n10 = (n11 = (n12 = (n13 = (n14 = (n15 = (n16 = (n17 = (n18 = (n19 = (n20 = (n21 = (n22 = (n23 = (n24 = (n25 = (n26 = (n27 = (n28 = (n29 = (n30 = (n31 = (n32 = (n33 = (n34 = (n35 = (n36 = (n37 = (n38 = (n39 = (n40 = (n41 = (n42 = (n43 = (n44 = (n45 = (n46 = (n47 = (n48 = (n49 = (n50 = (n51 = (n52 = (n53 = (n54 = (n55 = (n56 = 22)))))))))))))))))))))))))))))))))))))))))))))))))))))));
                    s = "\u007f+-\u000fJd";
                    n57 = 21;
                    continue Label_0638_Outer;
                }
                case 21: {
                    array23[n23] = intern;
                    n = (n2 = (n3 = (n4 = (n5 = (n6 = (n7 = (n8 = (n9 = (n10 = (n11 = (n12 = (n13 = (n14 = (n15 = (n16 = (n17 = (n18 = (n19 = (n20 = (n21 = (n22 = (n23 = (n24 = (n25 = (n26 = (n27 = (n28 = (n29 = (n30 = (n31 = (n32 = (n33 = (n34 = (n35 = (n36 = (n37 = (n38 = (n39 = (n40 = (n41 = (n42 = (n43 = (n44 = (n45 = (n46 = (n47 = (n48 = (n49 = (n50 = (n51 = (n52 = (n53 = (n54 = (n55 = (n56 = 23)))))))))))))))))))))))))))))))))))))))))))))))))))))));
                    s = ".%";
                    n57 = 22;
                    continue Label_0638_Outer;
                }
                case 22: {
                    array24[n24] = intern;
                    n = (n2 = (n3 = (n4 = (n5 = (n6 = (n7 = (n8 = (n9 = (n10 = (n11 = (n12 = (n13 = (n14 = (n15 = (n16 = (n17 = (n18 = (n19 = (n20 = (n21 = (n22 = (n23 = (n24 = (n25 = (n26 = (n27 = (n28 = (n29 = (n30 = (n31 = (n32 = (n33 = (n34 = (n35 = (n36 = (n37 = (n38 = (n39 = (n40 = (n41 = (n42 = (n43 = (n44 = (n45 = (n46 = (n47 = (n48 = (n49 = (n50 = (n51 = (n52 = (n53 = (n54 = (n55 = (n56 = 24)))))))))))))))))))))))))))))))))))))))))))))))))))))));
                    s = "\u000fS\t5/F\n\u0005r'\bI\u0003,/M\u000b\u0005}#\u0015TL,gN\u0000\u0005~4FB\u001d-nCNQ~fV\t";
                    n57 = 23;
                    continue Label_0638_Outer;
                }
                case 23: {
                    array25[n25] = intern;
                    n = (n2 = (n3 = (n4 = (n5 = (n6 = (n7 = (n8 = (n9 = (n10 = (n11 = (n12 = (n13 = (n14 = (n15 = (n16 = (n17 = (n18 = (n19 = (n20 = (n21 = (n22 = (n23 = (n24 = (n25 = (n26 = (n27 = (n28 = (n29 = (n30 = (n31 = (n32 = (n33 = (n34 = (n35 = (n36 = (n37 = (n38 = (n39 = (n40 = (n41 = (n42 = (n43 = (n44 = (n45 = (n46 = (n47 = (n48 = (n49 = (n50 = (n51 = (n52 = (n53 = (n54 = (n55 = (n56 = 25)))))))))))))))))))))))))))))))))))))))))))))))))))))));
                    s = "\u001bY";
                    n57 = 24;
                    continue Label_0638_Outer;
                }
                case 24: {
                    array26[n26] = intern;
                    n = (n2 = (n3 = (n4 = (n5 = (n6 = (n7 = (n8 = (n9 = (n10 = (n11 = (n12 = (n13 = (n14 = (n15 = (n16 = (n17 = (n18 = (n19 = (n20 = (n21 = (n22 = (n23 = (n24 = (n25 = (n26 = (n27 = (n28 = (n29 = (n30 = (n31 = (n32 = (n33 = (n34 = (n35 = (n36 = (n37 = (n38 = (n39 = (n40 = (n41 = (n42 = (n43 = (n44 = (n45 = (n46 = (n47 = (n48 = (n49 = (n50 = (n51 = (n52 = (n53 = (n54 = (n55 = (n56 = 26)))))))))))))))))))))))))))))))))))))))))))))))))))))));
                    s = "\r\u0010\u0007";
                    n57 = 25;
                    continue Label_0638_Outer;
                }
                case 25: {
                    array27[n27] = intern;
                    n = (n2 = (n3 = (n4 = (n5 = (n6 = (n7 = (n8 = (n9 = (n10 = (n11 = (n12 = (n13 = (n14 = (n15 = (n16 = (n17 = (n18 = (n19 = (n20 = (n21 = (n22 = (n23 = (n24 = (n25 = (n26 = (n27 = (n28 = (n29 = (n30 = (n31 = (n32 = (n33 = (n34 = (n35 = (n36 = (n37 = (n38 = (n39 = (n40 = (n41 = (n42 = (n43 = (n44 = (n45 = (n46 = (n47 = (n48 = (n49 = (n50 = (n51 = (n52 = (n53 = (n54 = (n55 = (n56 = 27)))))))))))))))))))))))))))))))))))))))))))))))))))))));
                    s = "\u0018\u0005\u0018!\u007fJ";
                    n57 = 26;
                    continue Label_0638_Outer;
                }
                case 26: {
                    array28[n28] = intern;
                    n = (n2 = (n3 = (n4 = (n5 = (n6 = (n7 = (n8 = (n9 = (n10 = (n11 = (n12 = (n13 = (n14 = (n15 = (n16 = (n17 = (n18 = (n19 = (n20 = (n21 = (n22 = (n23 = (n24 = (n25 = (n26 = (n27 = (n28 = (n29 = (n30 = (n31 = (n32 = (n33 = (n34 = (n35 = (n36 = (n37 = (n38 = (n39 = (n40 = (n41 = (n42 = (n43 = (n44 = (n45 = (n46 = (n47 = (n48 = (n49 = (n50 = (n51 = (n52 = (n53 = (n54 = (n55 = (n56 = 28)))))))))))))))))))))))))))))))))))))))))))))))))))))));
                    s = "tE\u0000l\u001b";
                    n57 = 27;
                    continue Label_0638_Outer;
                }
                case 27: {
                    array29[n29] = intern;
                    n = (n2 = (n3 = (n4 = (n5 = (n6 = (n7 = (n8 = (n9 = (n10 = (n11 = (n12 = (n13 = (n14 = (n15 = (n16 = (n17 = (n18 = (n19 = (n20 = (n21 = (n22 = (n23 = (n24 = (n25 = (n26 = (n27 = (n28 = (n29 = (n30 = (n31 = (n32 = (n33 = (n34 = (n35 = (n36 = (n37 = (n38 = (n39 = (n40 = (n41 = (n42 = (n43 = (n44 = (n45 = (n46 = (n47 = (n48 = (n49 = (n50 = (n51 = (n52 = (n53 = (n54 = (n55 = (n56 = 29)))))))))))))))))))))))))))))))))))))))))))))))))))))));
                    s = "q)bG\r";
                    n57 = 28;
                    continue Label_0638_Outer;
                }
                case 28: {
                    array30[n30] = intern;
                    n = (n2 = (n3 = (n4 = (n5 = (n6 = (n7 = (n8 = (n9 = (n10 = (n11 = (n12 = (n13 = (n14 = (n15 = (n16 = (n17 = (n18 = (n19 = (n20 = (n21 = (n22 = (n23 = (n24 = (n25 = (n26 = (n27 = (n28 = (n29 = (n30 = (n31 = (n32 = (n33 = (n34 = (n35 = (n36 = (n37 = (n38 = (n39 = (n40 = (n41 = (n42 = (n43 = (n44 = (n45 = (n46 = (n47 = (n48 = (n49 = (n50 = (n51 = (n52 = (n53 = (n54 = (n55 = (n56 = 30)))))))))))))))))))))))))))))))))))))))))))))))))))))));
                    s = "{y+\u001fYd'hL\t=n<_";
                    n57 = 29;
                    continue Label_0638_Outer;
                }
                case 29: {
                    array31[n31] = intern;
                    n = (n2 = (n3 = (n4 = (n5 = (n6 = (n7 = (n8 = (n9 = (n10 = (n11 = (n12 = (n13 = (n14 = (n15 = (n16 = (n17 = (n18 = (n19 = (n20 = (n21 = (n22 = (n23 = (n24 = (n25 = (n26 = (n27 = (n28 = (n29 = (n30 = (n31 = (n32 = (n33 = (n34 = (n35 = (n36 = (n37 = (n38 = (n39 = (n40 = (n41 = (n42 = (n43 = (n44 = (n45 = (n46 = (n47 = (n48 = (n49 = (n50 = (n51 = (n52 = (n53 = (n54 = (n55 = (n56 = 31)))))))))))))))))))))))))))))))))))))))))))))))))))))));
                    s = ":f";
                    n57 = 30;
                    continue Label_0638_Outer;
                }
                case 30: {
                    array32[n32] = intern;
                    n = (n2 = (n3 = (n4 = (n5 = (n6 = (n7 = (n8 = (n9 = (n10 = (n11 = (n12 = (n13 = (n14 = (n15 = (n16 = (n17 = (n18 = (n19 = (n20 = (n21 = (n22 = (n23 = (n24 = (n25 = (n26 = (n27 = (n28 = (n29 = (n30 = (n31 = (n32 = (n33 = (n34 = (n35 = (n36 = (n37 = (n38 = (n39 = (n40 = (n41 = (n42 = (n43 = (n44 = (n45 = (n46 = (n47 = (n48 = (n49 = (n50 = (n51 = (n52 = (n53 = (n54 = (n55 = (n56 = 32)))))))))))))))))))))))))))))))))))))))))))))))))))))));
                    s = "T\u0007Qt+";
                    n57 = 31;
                    continue Label_0638_Outer;
                }
                case 31: {
                    array33[n33] = intern;
                    n = (n2 = (n3 = (n4 = (n5 = (n6 = (n7 = (n8 = (n9 = (n10 = (n11 = (n12 = (n13 = (n14 = (n15 = (n16 = (n17 = (n18 = (n19 = (n20 = (n21 = (n22 = (n23 = (n24 = (n25 = (n26 = (n27 = (n28 = (n29 = (n30 = (n31 = (n32 = (n33 = (n34 = (n35 = (n36 = (n37 = (n38 = (n39 = (n40 = (n41 = (n42 = (n43 = (n44 = (n45 = (n46 = (n47 = (n48 = (n49 = (n50 = (n51 = (n52 = (n53 = (n54 = (n55 = (n56 = 33)))))))))))))))))))))))))))))))))))))))))))))))))))))));
                    s = "\u000fC";
                    n57 = 32;
                    continue Label_0638_Outer;
                }
                case 32: {
                    array34[n34] = intern;
                    n = (n2 = (n3 = (n4 = (n5 = (n6 = (n7 = (n8 = (n9 = (n10 = (n11 = (n12 = (n13 = (n14 = (n15 = (n16 = (n17 = (n18 = (n19 = (n20 = (n21 = (n22 = (n23 = (n24 = (n25 = (n26 = (n27 = (n28 = (n29 = (n30 = (n31 = (n32 = (n33 = (n34 = (n35 = (n36 = (n37 = (n38 = (n39 = (n40 = (n41 = (n42 = (n43 = (n44 = (n45 = (n46 = (n47 = (n48 = (n49 = (n50 = (n51 = (n52 = (n53 = (n54 = (n55 = (n56 = 34)))))))))))))))))))))))))))))))))))))))))))))))))))))));
                    s = "_\u001cLr#";
                    n57 = 33;
                    continue Label_0638_Outer;
                }
                case 33: {
                    array35[n35] = intern;
                    n = (n2 = (n3 = (n4 = (n5 = (n6 = (n7 = (n8 = (n9 = (n10 = (n11 = (n12 = (n13 = (n14 = (n15 = (n16 = (n17 = (n18 = (n19 = (n20 = (n21 = (n22 = (n23 = (n24 = (n25 = (n26 = (n27 = (n28 = (n29 = (n30 = (n31 = (n32 = (n33 = (n34 = (n35 = (n36 = (n37 = (n38 = (n39 = (n40 = (n41 = (n42 = (n43 = (n44 = (n45 = (n46 = (n47 = (n48 = (n49 = (n50 = (n51 = (n52 = (n53 = (n54 = (n55 = (n56 = 35)))))))))))))))))))))))))))))))))))))))))))))))))))))));
                    s = "^4iN7 y+\u001fNdulM\u000el`=K";
                    n57 = 34;
                    continue Label_0638_Outer;
                }
                case 34: {
                    array36[n36] = intern;
                    n = (n2 = (n3 = (n4 = (n5 = (n6 = (n7 = (n8 = (n9 = (n10 = (n11 = (n12 = (n13 = (n14 = (n15 = (n16 = (n17 = (n18 = (n19 = (n20 = (n21 = (n22 = (n23 = (n24 = (n25 = (n26 = (n27 = (n28 = (n29 = (n30 = (n31 = (n32 = (n33 = (n34 = (n35 = (n36 = (n37 = (n38 = (n39 = (n40 = (n41 = (n42 = (n43 = (n44 = (n45 = (n46 = (n47 = (n48 = (n49 = (n50 = (n51 = (n52 = (n53 = (n54 = (n55 = (n56 = 36)))))))))))))))))))))))))))))))))))))))))))))))))))))));
                    s = "\u0010\u0007A";
                    n57 = 35;
                    continue Label_0638_Outer;
                }
                case 35: {
                    array37[n37] = intern;
                    n = (n2 = (n3 = (n4 = (n5 = (n6 = (n7 = (n8 = (n9 = (n10 = (n11 = (n12 = (n13 = (n14 = (n15 = (n16 = (n17 = (n18 = (n19 = (n20 = (n21 = (n22 = (n23 = (n24 = (n25 = (n26 = (n27 = (n28 = (n29 = (n30 = (n31 = (n32 = (n33 = (n34 = (n35 = (n36 = (n37 = (n38 = (n39 = (n40 = (n41 = (n42 = (n43 = (n44 = (n45 = (n46 = (n47 = (n48 = (n49 = (n50 = (n51 = (n52 = (n53 = (n54 = (n55 = (n56 = 37)))))))))))))))))))))))))))))))))))))))))))))))))))))));
                    s = "T\u000fM\tP";
                    n57 = 36;
                    continue Label_0638_Outer;
                }
                case 36: {
                    array38[n38] = intern;
                    n = (n2 = (n3 = (n4 = (n5 = (n6 = (n7 = (n8 = (n9 = (n10 = (n11 = (n12 = (n13 = (n14 = (n15 = (n16 = (n17 = (n18 = (n19 = (n20 = (n21 = (n22 = (n23 = (n24 = (n25 = (n26 = (n27 = (n28 = (n29 = (n30 = (n31 = (n32 = (n33 = (n34 = (n35 = (n36 = (n37 = (n38 = (n39 = (n40 = (n41 = (n42 = (n43 = (n44 = (n45 = (n46 = (n47 = (n48 = (n49 = (n50 = (n51 = (n52 = (n53 = (n54 = (n55 = (n56 = 38)))))))))))))))))))))))))))))))))))))))))))))))))))))));
                    s = "G\u001aQa|I\b\u001f=}Y\u0007Ft5HU\u00196j\\\rDa#HD\u00035";
                    n57 = 37;
                    continue Label_0638_Outer;
                }
                case 37: {
                    array39[n39] = intern;
                    n = (n2 = (n3 = (n4 = (n5 = (n6 = (n7 = (n8 = (n9 = (n10 = (n11 = (n12 = (n13 = (n14 = (n15 = (n16 = (n17 = (n18 = (n19 = (n20 = (n21 = (n22 = (n23 = (n24 = (n25 = (n26 = (n27 = (n28 = (n29 = (n30 = (n31 = (n32 = (n33 = (n34 = (n35 = (n36 = (n37 = (n38 = (n39 = (n40 = (n41 = (n42 = (n43 = (n44 = (n45 = (n46 = (n47 = (n48 = (n49 = (n50 = (n51 = (n52 = (n53 = (n54 = (n55 = (n56 = 39)))))))))))))))))))))))))))))))))))))))))))))))))))))));
                    s = "@)lQ\u00056g-VY`5eK\u001csk<VTt7g\u0004\u0007!)<\u001bJu\"%";
                    n57 = 38;
                    continue Label_0638_Outer;
                }
                case 38: {
                    array40[n40] = intern;
                    n = (n2 = (n3 = (n4 = (n5 = (n6 = (n7 = (n8 = (n9 = (n10 = (n11 = (n12 = (n13 = (n14 = (n15 = (n16 = (n17 = (n18 = (n19 = (n20 = (n21 = (n22 = (n23 = (n24 = (n25 = (n26 = (n27 = (n28 = (n29 = (n30 = (n31 = (n32 = (n33 = (n34 = (n35 = (n36 = (n37 = (n38 = (n39 = (n40 = (n41 = (n42 = (n43 = (n44 = (n45 = (n46 = (n47 = (n48 = (n49 = (n50 = (n51 = (n52 = (n53 = (n54 = (n55 = (n56 = 40)))))))))))))))))))))))))))))))))))))))))))))))))))))));
                    s = "K\u0007A1(\tSL*j[\u001bW\u007ff\u0007I\u0015x}J\u001dP}2\u0015\tPwkF\u0018\u001b";
                    n57 = 39;
                    continue Label_0638_Outer;
                }
                case 39: {
                    array41[n41] = intern;
                    n = (n2 = (n3 = (n4 = (n5 = (n6 = (n7 = (n8 = (n9 = (n10 = (n11 = (n12 = (n13 = (n14 = (n15 = (n16 = (n17 = (n18 = (n19 = (n20 = (n21 = (n22 = (n23 = (n24 = (n25 = (n26 = (n27 = (n28 = (n29 = (n30 = (n31 = (n32 = (n33 = (n34 = (n35 = (n36 = (n37 = (n38 = (n39 = (n40 = (n41 = (n42 = (n43 = (n44 = (n45 = (n46 = (n47 = (n48 = (n49 = (n50 = (n51 = (n52 = (n53 = (n54 = (n55 = (n56 = 41)))))))))))))))))))))))))))))))))))))))))))))))))))))));
                    s = "n\u001cBd+\u0003I\u0018xlN\u0000K~2FE\txaZ\u0002I1)\u0014\u0007\t5\u007f[\u0017\u000b";
                    n57 = 40;
                    continue Label_0638_Outer;
                }
                case 40: {
                    array42[n42] = intern;
                    n = (n2 = (n3 = (n4 = (n5 = (n6 = (n7 = (n8 = (n9 = (n10 = (n11 = (n12 = (n13 = (n14 = (n15 = (n16 = (n17 = (n18 = (n19 = (n20 = (n21 = (n22 = (n23 = (n24 = (n25 = (n26 = (n27 = (n28 = (n29 = (n30 = (n31 = (n32 = (n33 = (n34 = (n35 = (n36 = (n37 = (n38 = (n39 = (n40 = (n41 = (n42 = (n43 = (n44 = (n45 = (n46 = (n47 = (n48 = (n49 = (n50 = (n51 = (n52 = (n53 = (n54 = (n55 = (n56 = 42)))))))))))))))))))))))))))))))))))))))))))))))))))))));
                    s = "[\u0001Ap?";
                    n57 = 41;
                    continue Label_0638_Outer;
                }
                case 41: {
                    array43[n43] = intern;
                    n = (n2 = (n3 = (n4 = (n5 = (n6 = (n7 = (n8 = (n9 = (n10 = (n11 = (n12 = (n13 = (n14 = (n15 = (n16 = (n17 = (n18 = (n19 = (n20 = (n21 = (n22 = (n23 = (n24 = (n25 = (n26 = (n27 = (n28 = (n29 = (n30 = (n31 = (n32 = (n33 = (n34 = (n35 = (n36 = (n37 = (n38 = (n39 = (n40 = (n41 = (n42 = (n43 = (n44 = (n45 = (n46 = (n47 = (n48 = (n49 = (n50 = (n51 = (n52 = (n53 = (n54 = (n55 = (n56 = 43)))))))))))))))))))))))))))))))))))))))))))))))))))))));
                    s = "K\u000f\\\"v";
                    n57 = 42;
                    continue Label_0638_Outer;
                }
                case 42: {
                    array44[n44] = intern;
                    n = (n2 = (n3 = (n4 = (n5 = (n6 = (n7 = (n8 = (n9 = (n10 = (n11 = (n12 = (n13 = (n14 = (n15 = (n16 = (n17 = (n18 = (n19 = (n20 = (n21 = (n22 = (n23 = (n24 = (n25 = (n26 = (n27 = (n28 = (n29 = (n30 = (n31 = (n32 = (n33 = (n34 = (n35 = (n36 = (n37 = (n38 = (n39 = (n40 = (n41 = (n42 = (n43 = (n44 = (n45 = (n46 = (n47 = (n48 = (n49 = (n50 = (n51 = (n52 = (n53 = (n54 = (n55 = (n56 = 44)))))))))))))))))))))))))))))))))))))))))))))))))))))));
                    s = "\r$f-\n,b%yC{6eWf/rPO\u00051TrR";
                    n57 = 43;
                    continue Label_0638_Outer;
                }
                case 43: {
                    array45[n45] = intern;
                    n = (n2 = (n3 = (n4 = (n5 = (n6 = (n7 = (n8 = (n9 = (n10 = (n11 = (n12 = (n13 = (n14 = (n15 = (n16 = (n17 = (n18 = (n19 = (n20 = (n21 = (n22 = (n23 = (n24 = (n25 = (n26 = (n27 = (n28 = (n29 = (n30 = (n31 = (n32 = (n33 = (n34 = (n35 = (n36 = (n37 = (n38 = (n39 = (n40 = (n41 = (n42 = (n43 = (n44 = (n45 = (n46 = (n47 = (n48 = (n49 = (n50 = (n51 = (n52 = (n53 = (n54 = (n55 = (n56 = 45)))))))))))))))))))))))))))))))))))))))))))))))))))))));
                    s = "T5n\\\u00186j-\u0013^!5~I\n6{cV";
                    n57 = 44;
                    continue Label_0638_Outer;
                }
                case 44: {
                    array46[n46] = intern;
                    n = (n2 = (n3 = (n4 = (n5 = (n6 = (n7 = (n8 = (n9 = (n10 = (n11 = (n12 = (n13 = (n14 = (n15 = (n16 = (n17 = (n18 = (n19 = (n20 = (n21 = (n22 = (n23 = (n24 = (n25 = (n26 = (n27 = (n28 = (n29 = (n30 = (n31 = (n32 = (n33 = (n34 = (n35 = (n36 = (n37 = (n38 = (n39 = (n40 = (n41 = (n42 = (n43 = (n44 = (n45 = (n46 = (n47 = (n48 = (n49 = (n50 = (n51 = (n52 = (n53 = (n54 = (n55 = (n56 = 46)))))))))))))))))))))))))))))))))))))))))))))))))))))));
                    s = "t\u0005HshJz";
                    n57 = 45;
                    continue Label_0638_Outer;
                }
                case 45: {
                    array47[n47] = intern;
                    n = (n2 = (n3 = (n4 = (n5 = (n6 = (n7 = (n8 = (n9 = (n10 = (n11 = (n12 = (n13 = (n14 = (n15 = (n16 = (n17 = (n18 = (n19 = (n20 = (n21 = (n22 = (n23 = (n24 = (n25 = (n26 = (n27 = (n28 = (n29 = (n30 = (n31 = (n32 = (n33 = (n34 = (n35 = (n36 = (n37 = (n38 = (n39 = (n40 = (n41 = (n42 = (n43 = (n44 = (n45 = (n46 = (n47 = (n48 = (n49 = (n50 = (n51 = (n52 = (n53 = (n54 = (n55 = (n56 = 47)))))))))))))))))))))))))))))))))))))))))))))))))))))));
                    s = "7h G\u00021";
                    n57 = 46;
                    continue Label_0638_Outer;
                }
                case 46: {
                    array48[n48] = intern;
                    n = (n2 = (n3 = (n4 = (n5 = (n6 = (n7 = (n8 = (n9 = (n10 = (n11 = (n12 = (n13 = (n14 = (n15 = (n16 = (n17 = (n18 = (n19 = (n20 = (n21 = (n22 = (n23 = (n24 = (n25 = (n26 = (n27 = (n28 = (n29 = (n30 = (n31 = (n32 = (n33 = (n34 = (n35 = (n36 = (n37 = (n38 = (n39 = (n40 = (n41 = (n42 = (n43 = (n44 = (n45 = (n46 = (n47 = (n48 = (n49 = (n50 = (n51 = (n52 = (n53 = (n54 = (n55 = (n56 = 48)))))))))))))))))))))))))))))))))))))))))))))))))))))));
                    s = "l>fF\r!z";
                    n57 = 47;
                    continue Label_0638_Outer;
                }
                case 47: {
                    array49[n49] = intern;
                    n = (n2 = (n3 = (n4 = (n5 = (n6 = (n7 = (n8 = (n9 = (n10 = (n11 = (n12 = (n13 = (n14 = (n15 = (n16 = (n17 = (n18 = (n19 = (n20 = (n21 = (n22 = (n23 = (n24 = (n25 = (n26 = (n27 = (n28 = (n29 = (n30 = (n31 = (n32 = (n33 = (n34 = (n35 = (n36 = (n37 = (n38 = (n39 = (n40 = (n41 = (n42 = (n43 = (n44 = (n45 = (n46 = (n47 = (n48 = (n49 = (n50 = (n51 = (n52 = (n53 = (n54 = (n55 = (n56 = 49)))))))))))))))))))))))))))))))))))))))))))))))))))))));
                    s = "=h4\u0013";
                    n57 = 48;
                    continue Label_0638_Outer;
                }
                case 48: {
                    array50[n50] = intern;
                    n = (n2 = (n3 = (n4 = (n5 = (n6 = (n7 = (n8 = (n9 = (n10 = (n11 = (n12 = (n13 = (n14 = (n15 = (n16 = (n17 = (n18 = (n19 = (n20 = (n21 = (n22 = (n23 = (n24 = (n25 = (n26 = (n27 = (n28 = (n29 = (n30 = (n31 = (n32 = (n33 = (n34 = (n35 = (n36 = (n37 = (n38 = (n39 = (n40 = (n41 = (n42 = (n43 = (n44 = (n45 = (n46 = (n47 = (n48 = (n49 = (n50 = (n51 = (n52 = (n53 = (n54 = (n55 = (n56 = 50)))))))))))))))))))))))))))))))))))))))))))))))))))))));
                    s = "e>xG\u001a:y-\u001fUo";
                    n57 = 49;
                    continue Label_0638_Outer;
                }
                case 49: {
                    array51[n51] = intern;
                    n = (n2 = (n3 = (n4 = (n5 = (n6 = (n7 = (n8 = (n9 = (n10 = (n11 = (n12 = (n13 = (n14 = (n15 = (n16 = (n17 = (n18 = (n19 = (n20 = (n21 = (n22 = (n23 = (n24 = (n25 = (n26 = (n27 = (n28 = (n29 = (n30 = (n31 = (n32 = (n33 = (n34 = (n35 = (n36 = (n37 = (n38 = (n39 = (n40 = (n41 = (n42 = (n43 = (n44 = (n45 = (n46 = (n47 = (n48 = (n49 = (n50 = (n51 = (n52 = (n53 = (n54 = (n55 = (n56 = 51)))))))))))))))))))))))))))))))))))))))))))))))))))))));
                    s = "\u0012^\u001c=";
                    n57 = 50;
                    continue Label_0638_Outer;
                }
                case 50: {
                    array52[n52] = intern;
                    z = z2;
                    HOST = Component.e(GeItem.z[38]);
                    array = (array2 = (array3 = (array4 = (array5 = (array6 = (array7 = (array8 = (array9 = (array10 = (array11 = (array12 = (array13 = (array14 = (array15 = (array16 = (array17 = (array18 = (array19 = (array20 = (array21 = (array22 = (array23 = (array24 = (array25 = (array26 = (array27 = (array28 = (array29 = (array30 = (array31 = (array32 = (array33 = (array34 = (array35 = (array36 = (array37 = (array38 = (array39 = (array40 = (array41 = (array42 = (array43 = (array44 = (array45 = (array46 = (array47 = (array48 = (array49 = (array50 = (array51 = (array52 = (z2 = (array53 = (array54 = (array55 = (array56 = (queries = new String[4])))))))))))))))))))))))))))))))))))))))))))))))))))))))));
                    n = (n2 = (n3 = (n4 = (n5 = (n6 = (n7 = (n8 = (n9 = (n10 = (n11 = (n12 = (n13 = (n14 = (n15 = (n16 = (n17 = (n18 = (n19 = (n20 = (n21 = (n22 = (n23 = (n24 = (n25 = (n26 = (n27 = (n28 = (n29 = (n30 = (n31 = (n32 = (n33 = (n34 = (n35 = (n36 = (n37 = (n38 = (n39 = (n40 = (n41 = (n42 = (n43 = (n44 = (n45 = (n46 = (n47 = (n48 = (n49 = (n50 = (n51 = (n52 = (n53 = (n54 = (n55 = (n56 = 0)))))))))))))))))))))))))))))))))))))))))))))))))))))));
                    s = "|dd\u001fNd6oF7!zv\u0017JhthE\u001c2e6\u0011OdtoA\u001c2`5XPr4e\u001b\u0001'l4K";
                    n57 = 51;
                    continue Label_0638_Outer;
                }
                case 51: {
                    array53[n53] = Constants.e(intern);
                    n = (n2 = (n3 = (n4 = (n5 = (n6 = (n7 = (n8 = (n9 = (n10 = (n11 = (n12 = (n13 = (n14 = (n15 = (n16 = (n17 = (n18 = (n19 = (n20 = (n21 = (n22 = (n23 = (n24 = (n25 = (n26 = (n27 = (n28 = (n29 = (n30 = (n31 = (n32 = (n33 = (n34 = (n35 = (n36 = (n37 = (n38 = (n39 = (n40 = (n41 = (n42 = (n43 = (n44 = (n45 = (n46 = (n47 = (n48 = (n49 = (n50 = (n51 = (n52 = (n53 = (n54 = (n55 = (n56 = 1)))))))))))))))))))))))))))))))))))))))))))))))))))))));
                    s = "IJQ1{J\u0003As\u0019\u0014TC*j\\\u001bIe5HP\u001fg~Z\u000bWh{";
                    n57 = 52;
                    continue Label_0638_Outer;
                }
                case 52: {
                    array54[n54] = Component.e(intern);
                    n = (n2 = (n3 = (n4 = (n5 = (n6 = (n7 = (n8 = (n9 = (n10 = (n11 = (n12 = (n13 = (n14 = (n15 = (n16 = (n17 = (n18 = (n19 = (n20 = (n21 = (n22 = (n23 = (n24 = (n25 = (n26 = (n27 = (n28 = (n29 = (n30 = (n31 = (n32 = (n33 = (n34 = (n35 = (n36 = (n37 = (n38 = (n39 = (n40 = (n41 = (n42 = (n43 = (n44 = (n45 = (n46 = (n47 = (n48 = (n49 = (n50 = (n51 = (n52 = (n53 = (n54 = (n55 = (n56 = 2)))))))))))))))))))))))))))))))))))))))))))))))))))))));
                    s = "|dd\u001fNd6oF7!zvE\u00020mTK\n9V*\u0006Hh/n\n\u000f:of\u001f^<";
                    n57 = 53;
                    continue Label_0638_Outer;
                }
                case 53: {
                    array55[n55] = Constants.e(intern);
                    n = (n2 = (n3 = (n4 = (n5 = (n6 = (n7 = (n8 = (n9 = (n10 = (n11 = (n12 = (n13 = (n14 = (n15 = (n16 = (n17 = (n18 = (n19 = (n20 = (n21 = (n22 = (n23 = (n24 = (n25 = (n26 = (n27 = (n28 = (n29 = (n30 = (n31 = (n32 = (n33 = (n34 = (n35 = (n36 = (n37 = (n38 = (n39 = (n40 = (n41 = (n42 = (n43 = (n44 = (n45 = (n46 = (n47 = (n48 = (n49 = (n50 = (n51 = (n52 = (n53 = (n54 = (n55 = (n56 = 3)))))))))))))))))))))))))))))))))))))))))))))))))))))));
                    s = "\u0000\u0003\u0018x2\u0003J\b:P]\u001d\n\"~W\u001137mE1Gx!H@\u0005>0F\n\u0018";
                    n57 = 54;
                    continue Label_0638_Outer;
                }
                case 54: {
                    break Label_0638_Outer;
                }
            }
        }
        array56[n56] = Component.e(intern);
        QUERIES = queries;
    }
}
