
package org;

final class b extends a
{
    private final g c;
    private int d;
    private final boolean e;
    private final d f;
    private final d g;
    private final int h;
    b i;
    b j;
    private static final String z;
    
    b(final g c, final boolean e, final d f, final d g, final int h) {
        super(262144);
        this.c = c;
        this.e = e;
        this.f = f;
        this.g = g;
        this.h = h;
    }
    
    @Override
    public void a(final String p0, final Object p1) {
        // 
        // This method could not be decompiled.
        // 
        // Original Bytecode:
        // 
        //     3: istore          9
        //     5: aload_0        
        //     6: dup            
        //     7: getfield        org/b.d:I
        //    10: iconst_1       
        //    11: iadd           
        //    12: putfield        org/b.d:I
        //    15: aload_0        
        //    16: getfield        org/b.e:Z
        //    19: iload           9
        //    21: ifne            55
        //    24: ifeq            51
        //    27: goto            31
        //    30: athrow         
        //    31: aload_0        
        //    32: getfield        org/b.f:Lorg/d;
        //    35: aload_0        
        //    36: getfield        org/b.c:Lorg/g;
        //    39: aload_1        
        //    40: invokevirtual   org/g.a:(Ljava/lang/String;)I
        //    43: invokevirtual   org/d.b:(I)Lorg/d;
        //    46: pop            
        //    47: goto            51
        //    50: athrow         
        //    51: aload_2        
        //    52: instanceof      Ljava/lang/String;
        //    55: iload           9
        //    57: ifne            105
        //    60: ifeq            97
        //    63: goto            67
        //    66: athrow         
        //    67: aload_0        
        //    68: getfield        org/b.f:Lorg/d;
        //    71: bipush          115
        //    73: aload_0        
        //    74: getfield        org/b.c:Lorg/g;
        //    77: aload_2        
        //    78: checkcast       Ljava/lang/String;
        //    81: invokevirtual   org/g.a:(Ljava/lang/String;)I
        //    84: invokevirtual   org/d.b:(II)Lorg/d;
        //    87: pop            
        //    88: iload           9
        //    90: ifeq            1316
        //    93: goto            97
        //    96: athrow         
        //    97: aload_2        
        //    98: instanceof      Ljava/lang/Byte;
        //   101: goto            105
        //   104: athrow         
        //   105: iload           9
        //   107: ifne            161
        //   110: ifeq            153
        //   113: goto            117
        //   116: athrow         
        //   117: aload_0        
        //   118: getfield        org/b.f:Lorg/d;
        //   121: bipush          66
        //   123: aload_0        
        //   124: getfield        org/b.c:Lorg/g;
        //   127: aload_2        
        //   128: checkcast       Ljava/lang/Byte;
        //   131: invokevirtual   java/lang/Byte.byteValue:()B
        //   134: invokevirtual   org/g.a:(I)Lorg/n;
        //   137: getfield        org/n.a:I
        //   140: invokevirtual   org/d.b:(II)Lorg/d;
        //   143: pop            
        //   144: iload           9
        //   146: ifeq            1316
        //   149: goto            153
        //   152: athrow         
        //   153: aload_2        
        //   154: instanceof      Ljava/lang/Boolean;
        //   157: goto            161
        //   160: athrow         
        //   161: iload           9
        //   163: ifne            236
        //   166: ifeq            228
        //   169: goto            173
        //   172: athrow         
        //   173: aload_2        
        //   174: checkcast       Ljava/lang/Boolean;
        //   177: invokevirtual   java/lang/Boolean.booleanValue:()Z
        //   180: iload           9
        //   182: ifne            197
        //   185: goto            189
        //   188: athrow         
        //   189: ifeq            200
        //   192: goto            196
        //   195: athrow         
        //   196: iconst_1       
        //   197: goto            201
        //   200: iconst_0       
        //   201: istore_3       
        //   202: aload_0        
        //   203: getfield        org/b.f:Lorg/d;
        //   206: bipush          90
        //   208: aload_0        
        //   209: getfield        org/b.c:Lorg/g;
        //   212: iload_3        
        //   213: invokevirtual   org/g.a:(I)Lorg/n;
        //   216: getfield        org/n.a:I
        //   219: invokevirtual   org/d.b:(II)Lorg/d;
        //   222: pop            
        //   223: iload           9
        //   225: ifeq            1316
        //   228: aload_2        
        //   229: instanceof      Ljava/lang/Character;
        //   232: goto            236
        //   235: athrow         
        //   236: iload           9
        //   238: ifne            292
        //   241: ifeq            284
        //   244: goto            248
        //   247: athrow         
        //   248: aload_0        
        //   249: getfield        org/b.f:Lorg/d;
        //   252: bipush          67
        //   254: aload_0        
        //   255: getfield        org/b.c:Lorg/g;
        //   258: aload_2        
        //   259: checkcast       Ljava/lang/Character;
        //   262: invokevirtual   java/lang/Character.charValue:()C
        //   265: invokevirtual   org/g.a:(I)Lorg/n;
        //   268: getfield        org/n.a:I
        //   271: invokevirtual   org/d.b:(II)Lorg/d;
        //   274: pop            
        //   275: iload           9
        //   277: ifeq            1316
        //   280: goto            284
        //   283: athrow         
        //   284: aload_2        
        //   285: instanceof      Ljava/lang/Short;
        //   288: goto            292
        //   291: athrow         
        //   292: iload           9
        //   294: ifne            348
        //   297: ifeq            340
        //   300: goto            304
        //   303: athrow         
        //   304: aload_0        
        //   305: getfield        org/b.f:Lorg/d;
        //   308: bipush          83
        //   310: aload_0        
        //   311: getfield        org/b.c:Lorg/g;
        //   314: aload_2        
        //   315: checkcast       Ljava/lang/Short;
        //   318: invokevirtual   java/lang/Short.shortValue:()S
        //   321: invokevirtual   org/g.a:(I)Lorg/n;
        //   324: getfield        org/n.a:I
        //   327: invokevirtual   org/d.b:(II)Lorg/d;
        //   330: pop            
        //   331: iload           9
        //   333: ifeq            1316
        //   336: goto            340
        //   339: athrow         
        //   340: aload_2        
        //   341: instanceof      Lorg/u;
        //   344: goto            348
        //   347: athrow         
        //   348: iload           9
        //   350: ifne            401
        //   353: ifeq            393
        //   356: goto            360
        //   359: athrow         
        //   360: aload_0        
        //   361: getfield        org/b.f:Lorg/d;
        //   364: bipush          99
        //   366: aload_0        
        //   367: getfield        org/b.c:Lorg/g;
        //   370: aload_2        
        //   371: checkcast       Lorg/u;
        //   374: invokevirtual   org/u.c:()Ljava/lang/String;
        //   377: invokevirtual   org/g.a:(Ljava/lang/String;)I
        //   380: invokevirtual   org/d.b:(II)Lorg/d;
        //   383: pop            
        //   384: iload           9
        //   386: ifeq            1316
        //   389: goto            393
        //   392: athrow         
        //   393: aload_2        
        //   394: instanceof      [B
        //   397: goto            401
        //   400: athrow         
        //   401: iload           9
        //   403: ifne            510
        //   406: ifeq            502
        //   409: goto            413
        //   412: athrow         
        //   413: aload_2        
        //   414: checkcast       [B
        //   417: checkcast       [B
        //   420: astore_3       
        //   421: aload_0        
        //   422: getfield        org/b.f:Lorg/d;
        //   425: bipush          91
        //   427: aload_3        
        //   428: arraylength    
        //   429: invokevirtual   org/d.b:(II)Lorg/d;
        //   432: pop            
        //   433: aload_3        
        //   434: astore          4
        //   436: aload           4
        //   438: arraylength    
        //   439: istore          5
        //   441: iconst_0       
        //   442: istore          6
        //   444: iload           6
        //   446: iload           5
        //   448: if_icmpge       497
        //   451: aload           4
        //   453: iload           6
        //   455: baload         
        //   456: istore          7
        //   458: aload_0        
        //   459: getfield        org/b.f:Lorg/d;
        //   462: bipush          66
        //   464: aload_0        
        //   465: getfield        org/b.c:Lorg/g;
        //   468: iload           7
        //   470: invokevirtual   org/g.a:(I)Lorg/n;
        //   473: getfield        org/n.a:I
        //   476: invokevirtual   org/d.b:(II)Lorg/d;
        //   479: pop            
        //   480: iinc            6, 1
        //   483: iload           9
        //   485: ifne            1316
        //   488: iload           9
        //   490: ifeq            444
        //   493: goto            497
        //   496: athrow         
        //   497: iload           9
        //   499: ifeq            1316
        //   502: aload_2        
        //   503: instanceof      [Z
        //   506: goto            510
        //   509: athrow         
        //   510: iload           9
        //   512: ifne            636
        //   515: ifeq            628
        //   518: goto            522
        //   521: athrow         
        //   522: aload_2        
        //   523: checkcast       [Z
        //   526: checkcast       [Z
        //   529: astore_3       
        //   530: aload_0        
        //   531: getfield        org/b.f:Lorg/d;
        //   534: bipush          91
        //   536: aload_3        
        //   537: arraylength    
        //   538: invokevirtual   org/d.b:(II)Lorg/d;
        //   541: pop            
        //   542: aload_3        
        //   543: astore          4
        //   545: aload           4
        //   547: arraylength    
        //   548: istore          5
        //   550: iconst_0       
        //   551: istore          6
        //   553: iload           6
        //   555: iload           5
        //   557: if_icmpge       623
        //   560: aload           4
        //   562: iload           6
        //   564: baload         
        //   565: istore          7
        //   567: iload           9
        //   569: ifne            1316
        //   572: aload_0        
        //   573: getfield        org/b.f:Lorg/d;
        //   576: bipush          90
        //   578: aload_0        
        //   579: getfield        org/b.c:Lorg/g;
        //   582: iload           7
        //   584: iload           9
        //   586: ifne            601
        //   589: goto            593
        //   592: athrow         
        //   593: ifeq            604
        //   596: goto            600
        //   599: athrow         
        //   600: iconst_1       
        //   601: goto            605
        //   604: iconst_0       
        //   605: invokevirtual   org/g.a:(I)Lorg/n;
        //   608: getfield        org/n.a:I
        //   611: invokevirtual   org/d.b:(II)Lorg/d;
        //   614: pop            
        //   615: iinc            6, 1
        //   618: iload           9
        //   620: ifeq            553
        //   623: iload           9
        //   625: ifeq            1316
        //   628: aload_2        
        //   629: instanceof      [S
        //   632: goto            636
        //   635: athrow         
        //   636: iload           9
        //   638: ifne            745
        //   641: ifeq            737
        //   644: goto            648
        //   647: athrow         
        //   648: aload_2        
        //   649: checkcast       [S
        //   652: checkcast       [S
        //   655: astore_3       
        //   656: aload_0        
        //   657: getfield        org/b.f:Lorg/d;
        //   660: bipush          91
        //   662: aload_3        
        //   663: arraylength    
        //   664: invokevirtual   org/d.b:(II)Lorg/d;
        //   667: pop            
        //   668: aload_3        
        //   669: astore          4
        //   671: aload           4
        //   673: arraylength    
        //   674: istore          5
        //   676: iconst_0       
        //   677: istore          6
        //   679: iload           6
        //   681: iload           5
        //   683: if_icmpge       732
        //   686: aload           4
        //   688: iload           6
        //   690: saload         
        //   691: istore          7
        //   693: aload_0        
        //   694: getfield        org/b.f:Lorg/d;
        //   697: bipush          83
        //   699: aload_0        
        //   700: getfield        org/b.c:Lorg/g;
        //   703: iload           7
        //   705: invokevirtual   org/g.a:(I)Lorg/n;
        //   708: getfield        org/n.a:I
        //   711: invokevirtual   org/d.b:(II)Lorg/d;
        //   714: pop            
        //   715: iinc            6, 1
        //   718: iload           9
        //   720: ifne            1316
        //   723: iload           9
        //   725: ifeq            679
        //   728: goto            732
        //   731: athrow         
        //   732: iload           9
        //   734: ifeq            1316
        //   737: aload_2        
        //   738: instanceof      [C
        //   741: goto            745
        //   744: athrow         
        //   745: iload           9
        //   747: ifne            854
        //   750: ifeq            846
        //   753: goto            757
        //   756: athrow         
        //   757: aload_2        
        //   758: checkcast       [C
        //   761: checkcast       [C
        //   764: astore_3       
        //   765: aload_0        
        //   766: getfield        org/b.f:Lorg/d;
        //   769: bipush          91
        //   771: aload_3        
        //   772: arraylength    
        //   773: invokevirtual   org/d.b:(II)Lorg/d;
        //   776: pop            
        //   777: aload_3        
        //   778: astore          4
        //   780: aload           4
        //   782: arraylength    
        //   783: istore          5
        //   785: iconst_0       
        //   786: istore          6
        //   788: iload           6
        //   790: iload           5
        //   792: if_icmpge       841
        //   795: aload           4
        //   797: iload           6
        //   799: caload         
        //   800: istore          7
        //   802: aload_0        
        //   803: getfield        org/b.f:Lorg/d;
        //   806: bipush          67
        //   808: aload_0        
        //   809: getfield        org/b.c:Lorg/g;
        //   812: iload           7
        //   814: invokevirtual   org/g.a:(I)Lorg/n;
        //   817: getfield        org/n.a:I
        //   820: invokevirtual   org/d.b:(II)Lorg/d;
        //   823: pop            
        //   824: iinc            6, 1
        //   827: iload           9
        //   829: ifne            1316
        //   832: iload           9
        //   834: ifeq            788
        //   837: goto            841
        //   840: athrow         
        //   841: iload           9
        //   843: ifeq            1316
        //   846: aload_2        
        //   847: instanceof      [I
        //   850: goto            854
        //   853: athrow         
        //   854: iload           9
        //   856: ifne            963
        //   859: ifeq            955
        //   862: goto            866
        //   865: athrow         
        //   866: aload_2        
        //   867: checkcast       [I
        //   870: checkcast       [I
        //   873: astore_3       
        //   874: aload_0        
        //   875: getfield        org/b.f:Lorg/d;
        //   878: bipush          91
        //   880: aload_3        
        //   881: arraylength    
        //   882: invokevirtual   org/d.b:(II)Lorg/d;
        //   885: pop            
        //   886: aload_3        
        //   887: astore          4
        //   889: aload           4
        //   891: arraylength    
        //   892: istore          5
        //   894: iconst_0       
        //   895: istore          6
        //   897: iload           6
        //   899: iload           5
        //   901: if_icmpge       950
        //   904: aload           4
        //   906: iload           6
        //   908: iaload         
        //   909: istore          7
        //   911: aload_0        
        //   912: getfield        org/b.f:Lorg/d;
        //   915: bipush          73
        //   917: aload_0        
        //   918: getfield        org/b.c:Lorg/g;
        //   921: iload           7
        //   923: invokevirtual   org/g.a:(I)Lorg/n;
        //   926: getfield        org/n.a:I
        //   929: invokevirtual   org/d.b:(II)Lorg/d;
        //   932: pop            
        //   933: iinc            6, 1
        //   936: iload           9
        //   938: ifne            1316
        //   941: iload           9
        //   943: ifeq            897
        //   946: goto            950
        //   949: athrow         
        //   950: iload           9
        //   952: ifeq            1316
        //   955: aload_2        
        //   956: instanceof      [J
        //   959: goto            963
        //   962: athrow         
        //   963: iload           9
        //   965: ifne            1072
        //   968: ifeq            1064
        //   971: goto            975
        //   974: athrow         
        //   975: aload_2        
        //   976: checkcast       [J
        //   979: checkcast       [J
        //   982: astore_3       
        //   983: aload_0        
        //   984: getfield        org/b.f:Lorg/d;
        //   987: bipush          91
        //   989: aload_3        
        //   990: arraylength    
        //   991: invokevirtual   org/d.b:(II)Lorg/d;
        //   994: pop            
        //   995: aload_3        
        //   996: astore          4
        //   998: aload           4
        //  1000: arraylength    
        //  1001: istore          5
        //  1003: iconst_0       
        //  1004: istore          6
        //  1006: iload           6
        //  1008: iload           5
        //  1010: if_icmpge       1059
        //  1013: aload           4
        //  1015: iload           6
        //  1017: laload         
        //  1018: lstore          7
        //  1020: aload_0        
        //  1021: getfield        org/b.f:Lorg/d;
        //  1024: bipush          74
        //  1026: aload_0        
        //  1027: getfield        org/b.c:Lorg/g;
        //  1030: lload           7
        //  1032: invokevirtual   org/g.a:(J)Lorg/n;
        //  1035: getfield        org/n.a:I
        //  1038: invokevirtual   org/d.b:(II)Lorg/d;
        //  1041: pop            
        //  1042: iinc            6, 1
        //  1045: iload           9
        //  1047: ifne            1316
        //  1050: iload           9
        //  1052: ifeq            1006
        //  1055: goto            1059
        //  1058: athrow         
        //  1059: iload           9
        //  1061: ifeq            1316
        //  1064: aload_2        
        //  1065: instanceof      [F
        //  1068: goto            1072
        //  1071: athrow         
        //  1072: iload           9
        //  1074: ifne            1190
        //  1077: ifeq            1173
        //  1080: goto            1084
        //  1083: athrow         
        //  1084: aload_2        
        //  1085: checkcast       [F
        //  1088: checkcast       [F
        //  1091: astore_3       
        //  1092: aload_0        
        //  1093: getfield        org/b.f:Lorg/d;
        //  1096: bipush          91
        //  1098: aload_3        
        //  1099: arraylength    
        //  1100: invokevirtual   org/d.b:(II)Lorg/d;
        //  1103: pop            
        //  1104: aload_3        
        //  1105: astore          4
        //  1107: aload           4
        //  1109: arraylength    
        //  1110: istore          5
        //  1112: iconst_0       
        //  1113: istore          6
        //  1115: iload           6
        //  1117: iload           5
        //  1119: if_icmpge       1168
        //  1122: aload           4
        //  1124: iload           6
        //  1126: faload         
        //  1127: fstore          7
        //  1129: aload_0        
        //  1130: getfield        org/b.f:Lorg/d;
        //  1133: bipush          70
        //  1135: aload_0        
        //  1136: getfield        org/b.c:Lorg/g;
        //  1139: fload           7
        //  1141: invokevirtual   org/g.a:(F)Lorg/n;
        //  1144: getfield        org/n.a:I
        //  1147: invokevirtual   org/d.b:(II)Lorg/d;
        //  1150: pop            
        //  1151: iinc            6, 1
        //  1154: iload           9
        //  1156: ifne            1316
        //  1159: iload           9
        //  1161: ifeq            1115
        //  1164: goto            1168
        //  1167: athrow         
        //  1168: iload           9
        //  1170: ifeq            1316
        //  1173: aload_2        
        //  1174: iload           9
        //  1176: ifne            1194
        //  1179: goto            1183
        //  1182: athrow         
        //  1183: instanceof      [D
        //  1186: goto            1190
        //  1189: athrow         
        //  1190: ifeq            1282
        //  1193: aload_2        
        //  1194: checkcast       [D
        //  1197: checkcast       [D
        //  1200: astore_3       
        //  1201: aload_0        
        //  1202: getfield        org/b.f:Lorg/d;
        //  1205: bipush          91
        //  1207: aload_3        
        //  1208: arraylength    
        //  1209: invokevirtual   org/d.b:(II)Lorg/d;
        //  1212: pop            
        //  1213: aload_3        
        //  1214: astore          4
        //  1216: aload           4
        //  1218: arraylength    
        //  1219: istore          5
        //  1221: iconst_0       
        //  1222: istore          6
        //  1224: iload           6
        //  1226: iload           5
        //  1228: if_icmpge       1277
        //  1231: aload           4
        //  1233: iload           6
        //  1235: daload         
        //  1236: dstore          7
        //  1238: aload_0        
        //  1239: getfield        org/b.f:Lorg/d;
        //  1242: bipush          68
        //  1244: aload_0        
        //  1245: getfield        org/b.c:Lorg/g;
        //  1248: dload           7
        //  1250: invokevirtual   org/g.a:(D)Lorg/n;
        //  1253: getfield        org/n.a:I
        //  1256: invokevirtual   org/d.b:(II)Lorg/d;
        //  1259: pop            
        //  1260: iinc            6, 1
        //  1263: iload           9
        //  1265: ifne            1316
        //  1268: iload           9
        //  1270: ifeq            1224
        //  1273: goto            1277
        //  1276: athrow         
        //  1277: iload           9
        //  1279: ifeq            1316
        //  1282: aload_0        
        //  1283: getfield        org/b.c:Lorg/g;
        //  1286: aload_2        
        //  1287: invokevirtual   org/g.a:(Ljava/lang/Object;)Lorg/n;
        //  1290: astore_3       
        //  1291: aload_0        
        //  1292: getfield        org/b.f:Lorg/d;
        //  1295: getstatic       org/b.z:Ljava/lang/String;
        //  1298: invokestatic    org/powerbot/core/script/internal/Constants.e:(Ljava/lang/String;)Ljava/lang/String;
        //  1301: aload_3        
        //  1302: getfield        org/n.b:I
        //  1305: invokevirtual   java/lang/String.charAt:(I)C
        //  1308: aload_3        
        //  1309: getfield        org/n.a:I
        //  1312: invokevirtual   org/d.b:(II)Lorg/d;
        //  1315: pop            
        //  1316: return         
        //    StackMapTable: 00 75 FF 00 1E 00 0A 07 00 27 07 00 0B 07 00 B6 00 00 00 00 00 00 01 00 01 07 00 A4 00 52 07 00 A4 00 43 01 4A 07 00 A4 00 5C 07 00 A4 00 46 07 00 A4 40 01 4A 07 00 A4 00 62 07 00 A4 00 46 07 00 A4 40 01 4A 07 00 A4 00 4E 07 00 A4 40 01 45 07 00 A4 00 40 01 02 40 01 1A 46 07 00 A4 40 01 4A 07 00 A4 00 62 07 00 A4 00 46 07 00 A4 40 01 4A 07 00 A4 00 62 07 00 A4 00 46 07 00 A4 40 01 4A 07 00 A4 00 5F 07 00 A4 00 46 07 00 A4 40 01 4A 07 00 A4 00 FF 00 1E 00 0A 07 00 27 07 00 0B 07 00 B6 07 00 19 07 00 19 01 01 00 00 01 00 00 FF 00 33 00 0A 07 00 27 07 00 0B 07 00 B6 07 00 19 07 00 19 01 01 01 00 01 00 01 07 00 A4 FF 00 00 00 0A 07 00 27 07 00 0B 07 00 B6 07 00 19 07 00 19 01 01 00 00 01 00 00 FF 00 04 00 0A 07 00 27 07 00 0B 07 00 B6 00 00 00 00 00 00 01 00 00 46 07 00 A4 40 01 4A 07 00 A4 00 FF 00 1E 00 0A 07 00 27 07 00 0B 07 00 B6 07 00 1A 07 00 1A 01 01 00 00 01 00 00 FF 00 26 00 0A 07 00 27 07 00 0B 07 00 B6 07 00 1A 07 00 1A 01 01 01 00 01 00 01 07 00 A4 FF 00 00 00 0A 07 00 27 07 00 0B 07 00 B6 07 00 1A 07 00 1A 01 01 01 00 01 00 04 07 00 56 01 07 00 54 01 45 07 00 A4 FF 00 00 00 0A 07 00 27 07 00 0B 07 00 B6 07 00 1A 07 00 1A 01 01 01 00 01 00 03 07 00 56 01 07 00 54 FF 00 00 00 0A 07 00 27 07 00 0B 07 00 B6 07 00 1A 07 00 1A 01 01 01 00 01 00 04 07 00 56 01 07 00 54 01 FF 00 02 00 0A 07 00 27 07 00 0B 07 00 B6 07 00 1A 07 00 1A 01 01 01 00 01 00 03 07 00 56 01 07 00 54 FF 00 00 00 0A 07 00 27 07 00 0B 07 00 B6 07 00 1A 07 00 1A 01 01 01 00 01 00 04 07 00 56 01 07 00 54 01 FF 00 11 00 0A 07 00 27 07 00 0B 07 00 B6 07 00 1A 07 00 1A 01 01 00 00 01 00 00 FF 00 04 00 0A 07 00 27 07 00 0B 07 00 B6 00 00 00 00 00 00 01 00 00 46 07 00 A4 40 01 4A 07 00 A4 00 FF 00 1E 00 0A 07 00 27 07 00 0B 07 00 B6 07 00 1B 07 00 1B 01 01 00 00 01 00 00 FF 00 33 00 0A 07 00 27 07 00 0B 07 00 B6 07 00 1B 07 00 1B 01 01 01 00 01 00 01 07 00 A4 FF 00 00 00 0A 07 00 27 07 00 0B 07 00 B6 07 00 1B 07 00 1B 01 01 00 00 01 00 00 FF 00 04 00 0A 07 00 27 07 00 0B 07 00 B6 00 00 00 00 00 00 01 00 00 46 07 00 A4 40 01 4A 07 00 A4 00 FF 00 1E 00 0A 07 00 27 07 00 0B 07 00 B6 07 00 1C 07 00 1C 01 01 00 00 01 00 00 FF 00 33 00 0A 07 00 27 07 00 0B 07 00 B6 07 00 1C 07 00 1C 01 01 01 00 01 00 01 07 00 A4 FF 00 00 00 0A 07 00 27 07 00 0B 07 00 B6 07 00 1C 07 00 1C 01 01 00 00 01 00 00 FF 00 04 00 0A 07 00 27 07 00 0B 07 00 B6 00 00 00 00 00 00 01 00 00 46 07 00 A4 40 01 4A 07 00 A4 00 FF 00 1E 00 0A 07 00 27 07 00 0B 07 00 B6 07 00 1D 07 00 1D 01 01 00 00 01 00 00 FF 00 33 00 0A 07 00 27 07 00 0B 07 00 B6 07 00 1D 07 00 1D 01 01 01 00 01 00 01 07 00 A4 FF 00 00 00 0A 07 00 27 07 00 0B 07 00 B6 07 00 1D 07 00 1D 01 01 00 00 01 00 00 FF 00 04 00 0A 07 00 27 07 00 0B 07 00 B6 00 00 00 00 00 00 01 00 00 46 07 00 A4 40 01 4A 07 00 A4 00 FF 00 1E 00 0A 07 00 27 07 00 0B 07 00 B6 07 00 1E 07 00 1E 01 01 00 00 01 00 00 FF 00 33 00 09 07 00 27 07 00 0B 07 00 B6 07 00 1E 07 00 1E 01 01 04 01 00 01 07 00 A4 FF 00 00 00 0A 07 00 27 07 00 0B 07 00 B6 07 00 1E 07 00 1E 01 01 00 00 01 00 00 FF 00 04 00 0A 07 00 27 07 00 0B 07 00 B6 00 00 00 00 00 00 01 00 00 46 07 00 A4 40 01 4A 07 00 A4 00 FF 00 1E 00 0A 07 00 27 07 00 0B 07 00 B6 07 00 20 07 00 20 01 01 00 00 01 00 00 FF 00 33 00 0A 07 00 27 07 00 0B 07 00 B6 07 00 20 07 00 20 01 01 02 00 01 00 01 07 00 A4 FF 00 00 00 0A 07 00 27 07 00 0B 07 00 B6 07 00 20 07 00 20 01 01 00 00 01 00 00 FF 00 04 00 0A 07 00 27 07 00 0B 07 00 B6 00 00 00 00 00 00 01 00 00 48 07 00 A4 40 07 00 B6 45 07 00 A4 40 01 43 07 00 B6 FF 00 1D 00 0A 07 00 27 07 00 0B 07 00 B6 07 00 22 07 00 22 01 01 00 00 01 00 00 FF 00 33 00 09 07 00 27 07 00 0B 07 00 B6 07 00 22 07 00 22 01 01 03 01 00 01 07 00 A4 FF 00 00 00 0A 07 00 27 07 00 0B 07 00 B6 07 00 22 07 00 22 01 01 00 00 01 00 00 FF 00 04 00 0A 07 00 27 07 00 0B 07 00 B6 00 00 00 00 00 00 01 00 00 21
        //    Exceptions:
        //  Try           Handler
        //  Start  End    Start  End    Type                        
        //  -----  -----  -----  -----  ----------------------------
        //  1238   1273   1276   1277   Ljava/lang/RuntimeException;
        //  1173   1186   1189   1190   Ljava/lang/RuntimeException;
        //  1168   1179   1182   1183   Ljava/lang/RuntimeException;
        //  1129   1164   1167   1168   Ljava/lang/RuntimeException;
        //  1072   1080   1083   1084   Ljava/lang/RuntimeException;
        //  1059   1068   1071   1072   Ljava/lang/RuntimeException;
        //  1020   1055   1058   1059   Ljava/lang/RuntimeException;
        //  963    971    974    975    Ljava/lang/RuntimeException;
        //  950    959    962    963    Ljava/lang/RuntimeException;
        //  911    946    949    950    Ljava/lang/RuntimeException;
        //  854    862    865    866    Ljava/lang/RuntimeException;
        //  841    850    853    854    Ljava/lang/RuntimeException;
        //  802    837    840    841    Ljava/lang/RuntimeException;
        //  745    753    756    757    Ljava/lang/RuntimeException;
        //  732    741    744    745    Ljava/lang/RuntimeException;
        //  693    728    731    732    Ljava/lang/RuntimeException;
        //  636    644    647    648    Ljava/lang/RuntimeException;
        //  623    632    635    636    Ljava/lang/RuntimeException;
        //  572    596    599    600    Ljava/lang/RuntimeException;
        //  567    589    592    593    Ljava/lang/RuntimeException;
        //  510    518    521    522    Ljava/lang/RuntimeException;
        //  497    506    509    510    Ljava/lang/RuntimeException;
        //  458    493    496    497    Ljava/lang/RuntimeException;
        //  401    409    412    413    Ljava/lang/RuntimeException;
        //  360    397    400    401    Ljava/lang/RuntimeException;
        //  353    389    392    393    Ljava/lang/RuntimeException;
        //  348    356    359    360    Ljava/lang/RuntimeException;
        //  304    344    347    348    Ljava/lang/RuntimeException;
        //  297    336    339    340    Ljava/lang/RuntimeException;
        //  292    300    303    304    Ljava/lang/RuntimeException;
        //  248    288    291    292    Ljava/lang/RuntimeException;
        //  241    280    283    284    Ljava/lang/RuntimeException;
        //  236    244    247    248    Ljava/lang/RuntimeException;
        //  202    232    235    236    Ljava/lang/RuntimeException;
        //  173    192    195    196    Ljava/lang/RuntimeException;
        //  166    185    188    189    Ljava/lang/RuntimeException;
        //  161    169    172    173    Ljava/lang/RuntimeException;
        //  117    157    160    161    Ljava/lang/RuntimeException;
        //  110    149    152    153    Ljava/lang/RuntimeException;
        //  105    113    116    117    Ljava/lang/RuntimeException;
        //  67     101    104    105    Ljava/lang/RuntimeException;
        //  60     93     96     97     Ljava/lang/RuntimeException;
        //  55     63     66     67     Ljava/lang/RuntimeException;
        //  24     47     50     51     Ljava/lang/RuntimeException;
        //  5      27     30     31     Ljava/lang/RuntimeException;
        // 
        // The error that occurred was:
        // 
        // java.lang.IllegalStateException: Expression is linked from several locations: Label_0067:
        //     at com.strobel.decompiler.ast.Error.expressionLinkedFromMultipleLocations(Error.java:27)
        //     at com.strobel.decompiler.ast.AstOptimizer.mergeDisparateObjectInitializations(AstOptimizer.java:2596)
        //     at com.strobel.decompiler.ast.AstOptimizer.optimize(AstOptimizer.java:235)
        //     at com.strobel.decompiler.ast.AstOptimizer.optimize(AstOptimizer.java:42)
        //     at com.strobel.decompiler.languages.java.ast.AstMethodBodyBuilder.createMethodBody(AstMethodBodyBuilder.java:214)
        //     at com.strobel.decompiler.languages.java.ast.AstMethodBodyBuilder.createMethodBody(AstMethodBodyBuilder.java:99)
        //     at com.strobel.decompiler.languages.java.ast.AstBuilder.createMethodBody(AstBuilder.java:782)
        //     at com.strobel.decompiler.languages.java.ast.AstBuilder.createMethod(AstBuilder.java:675)
        //     at com.strobel.decompiler.languages.java.ast.AstBuilder.addTypeMembers(AstBuilder.java:552)
        //     at com.strobel.decompiler.languages.java.ast.AstBuilder.createTypeCore(AstBuilder.java:519)
        //     at com.strobel.decompiler.languages.java.ast.AstBuilder.createTypeNoCache(AstBuilder.java:161)
        //     at com.strobel.decompiler.languages.java.ast.AstBuilder.createType(AstBuilder.java:150)
        //     at com.strobel.decompiler.languages.java.ast.AstBuilder.addType(AstBuilder.java:125)
        //     at com.strobel.decompiler.languages.java.JavaLanguage.buildAst(JavaLanguage.java:71)
        //     at com.strobel.decompiler.languages.java.JavaLanguage.decompileType(JavaLanguage.java:59)
        //     at com.strobel.decompiler.DecompilerDriver.decompileType(DecompilerDriver.java:330)
        //     at com.strobel.decompiler.DecompilerDriver.decompileJar(DecompilerDriver.java:251)
        //     at com.strobel.decompiler.DecompilerDriver.main(DecompilerDriver.java:126)
        // 
        throw new IllegalStateException("An error occurred while decompiling this method.");
    }
    
    @Override
    public void a(final String s, final String s2, final String s3) {
        b b = null;
        Label_0048: {
            Label_0027: {
                try {
                    ++this.d;
                    b = this;
                    if (org.f.c) {
                        break Label_0048;
                    }
                    final boolean b2 = this.e;
                    if (b2) {
                        break Label_0027;
                    }
                    break Label_0027;
                }
                catch (RuntimeException ex) {
                    throw ex;
                }
                try {
                    final boolean b2 = this.e;
                    if (b2) {
                        this.f.b(this.c.a(s));
                    }
                }
                catch (RuntimeException ex2) {
                    throw ex2;
                }
            }
            b = this;
        }
        b.f.b(101, this.c.a(s2)).b(this.c.a(s3));
    }
    
    @Override
    public a a(final String s, final String s2) {
        Label_0027: {
            try {
                ++this.d;
                final b b = this;
                if (org.f.c) {
                    return b;
                }
                final boolean b2 = this.e;
                if (b2) {
                    break Label_0027;
                }
                break Label_0027;
            }
            catch (RuntimeException ex) {
                throw ex;
            }
            try {
                final boolean b2 = this.e;
                if (b2) {
                    this.f.b(this.c.a(s));
                }
            }
            catch (RuntimeException ex2) {
                throw ex2;
            }
        }
        this.f.b(64, this.c.a(s2)).b(0);
        return new b(this.c, true, this.f, this.f, this.f.b - 2);
    }
    
    @Override
    public a a(final String s) {
        Label_0027: {
            try {
                ++this.d;
                final b b = this;
                if (org.f.c) {
                    return b;
                }
                final boolean b2 = this.e;
                if (b2) {
                    break Label_0027;
                }
                break Label_0027;
            }
            catch (RuntimeException ex) {
                throw ex;
            }
            try {
                final boolean b2 = this.e;
                if (b2) {
                    this.f.b(this.c.a(s));
                }
            }
            catch (RuntimeException ex2) {
                throw ex2;
            }
        }
        this.f.b(91, 0);
        return new b(this.c, false, this.f, this.f, this.f.b - 2);
    }
    
    @Override
    public void a() {
        d d2 = null;
        Label_0017: {
            d d;
            try {
                d = (d2 = this.g);
                if (org.f.c) {
                    break Label_0017;
                }
                if (d != null) {
                    break Label_0017;
                }
                return;
            }
            catch (RuntimeException ex) {
                throw ex;
            }
            try {
                if (d == null) {
                    return;
                }
                d2 = this.g;
            }
            catch (RuntimeException ex2) {
                throw ex2;
            }
        }
        final byte[] a = d2.a;
        a[this.h] = (byte)(this.d >>> 8);
        a[this.h + 1] = (byte)this.d;
    }
    
    int a() {
        final boolean c = org.f.c;
        int n = 0;
        b i = this;
        int n2 = 0;
        while (i != null) {
            n2 = n + i.f.b;
            if (c) {
                return n2;
            }
            n = n2;
            i = i.i;
            if (c) {
                break;
            }
        }
        return n2;
    }
    
    void a(final d d) {
        final boolean c = org.f.c;
        int n = 0;
        int n2 = 2;
        b i = this;
        b j = null;
    Label_0083:
        while (true) {
            while (i != null) {
                ++n;
                n2 += i.f.b;
                i.a();
                i.j = j;
                j = i;
                i = i.i;
                try {
                    if (c) {
                        break Label_0083;
                    }
                    if (!c) {
                        continue;
                    }
                }
                catch (RuntimeException ex) {
                    throw ex;
                }
                break;
                b k = j;
                while (k != null) {
                    d.a(k.f.a, 0, k.f.b);
                    k = k.j;
                    if (c) {
                        break;
                    }
                }
                return;
            }
            d.c(n2);
            d.b(n);
            continue Label_0083;
        }
    }
    
    static void a(final b[] p0, final int p1, final d p2) {
        // 
        // This method could not be decompiled.
        // 
        // Original Bytecode:
        // 
        //     3: istore          8
        //     5: iconst_1       
        //     6: iconst_2       
        //     7: aload_0        
        //     8: arraylength    
        //     9: iload_1        
        //    10: isub           
        //    11: imul           
        //    12: iadd           
        //    13: istore_3       
        //    14: iload_1        
        //    15: istore          4
        //    17: iload           4
        //    19: aload_0        
        //    20: arraylength    
        //    21: if_icmpge       72
        //    24: iload_3        
        //    25: aload_0        
        //    26: iload           8
        //    28: ifne            91
        //    31: iload           4
        //    33: aaload         
        //    34: iload           8
        //    36: ifne            59
        //    39: goto            43
        //    42: athrow         
        //    43: ifnonnull       55
        //    46: goto            50
        //    49: athrow         
        //    50: iconst_0       
        //    51: goto            62
        //    54: athrow         
        //    55: aload_0        
        //    56: iload           4
        //    58: aaload         
        //    59: invokevirtual   org/b.a:()I
        //    62: iadd           
        //    63: istore_3       
        //    64: iinc            4, 1
        //    67: iload           8
        //    69: ifeq            17
        //    72: aload_2        
        //    73: iload_3        
        //    74: invokevirtual   org/d.c:(I)Lorg/d;
        //    77: aload_0        
        //    78: arraylength    
        //    79: iload_1        
        //    80: isub           
        //    81: invokevirtual   org/d.a:(I)Lorg/d;
        //    84: pop            
        //    85: iload_1        
        //    86: istore          4
        //    88: iload           4
        //    90: aload_0        
        //    91: arraylength    
        //    92: if_icmpge       219
        //    95: aload_0        
        //    96: iload           4
        //    98: aaload         
        //    99: astore          5
        //   101: aconst_null    
        //   102: astore          6
        //   104: iconst_0       
        //   105: istore          7
        //   107: aload           5
        //   109: ifnull          152
        //   112: iinc            7, 1
        //   115: aload           5
        //   117: invokevirtual   org/b.a:()V
        //   120: aload           5
        //   122: aload           6
        //   124: putfield        org/b.j:Lorg/b;
        //   127: aload           5
        //   129: astore          6
        //   131: aload           5
        //   133: getfield        org/b.i:Lorg/b;
        //   136: astore          5
        //   138: iload           8
        //   140: ifne            159
        //   143: iload           8
        //   145: ifeq            107
        //   148: goto            152
        //   151: athrow         
        //   152: aload_2        
        //   153: iload           7
        //   155: invokevirtual   org/d.b:(I)Lorg/d;
        //   158: pop            
        //   159: aload           6
        //   161: astore          5
        //   163: aload           5
        //   165: ifnull          211
        //   168: aload_2        
        //   169: aload           5
        //   171: getfield        org/b.f:Lorg/d;
        //   174: getfield        org/d.a:[B
        //   177: iconst_0       
        //   178: aload           5
        //   180: getfield        org/b.f:Lorg/d;
        //   183: getfield        org/d.b:I
        //   186: invokevirtual   org/d.a:([BII)Lorg/d;
        //   189: pop            
        //   190: aload           5
        //   192: getfield        org/b.j:Lorg/b;
        //   195: astore          5
        //   197: iload           8
        //   199: ifne            214
        //   202: iload           8
        //   204: ifeq            163
        //   207: goto            211
        //   210: athrow         
        //   211: iinc            4, 1
        //   214: iload           8
        //   216: ifeq            88
        //   219: return         
        //    StackMapTable: 00 15 FF 00 11 00 09 07 00 B8 01 07 00 56 01 01 00 00 00 01 00 00 58 07 00 A4 FF 00 00 00 09 07 00 B8 01 07 00 56 01 01 00 00 00 01 00 02 01 07 00 27 45 07 00 A4 40 01 43 07 00 A4 40 01 FF 00 03 00 09 07 00 B8 01 07 00 56 01 01 00 00 00 01 00 02 01 07 00 27 FF 00 02 00 09 07 00 B8 01 07 00 56 01 01 00 00 00 01 00 02 01 01 09 0F FF 00 02 00 09 07 00 B8 01 07 00 56 01 01 00 00 00 01 00 02 01 07 00 B8 FF 00 0F 00 09 07 00 B8 01 07 00 56 01 01 07 00 27 07 00 27 01 01 00 00 6B 07 00 A4 00 06 03 6E 07 00 A4 00 02 FF 00 04 00 09 07 00 B8 01 07 00 56 01 01 00 00 00 01 00 00
        //    Exceptions:
        //  Try           Handler
        //  Start  End    Start  End    Type                        
        //  -----  -----  -----  -----  ----------------------------
        //  197    207    210    211    Ljava/lang/RuntimeException;
        //  138    148    151    152    Ljava/lang/RuntimeException;
        //  43     54     54     55     Ljava/lang/RuntimeException;
        //  31     46     49     50     Ljava/lang/RuntimeException;
        //  24     39     42     43     Ljava/lang/RuntimeException;
        // 
        // The error that occurred was:
        // 
        // java.lang.IllegalStateException: Expression is linked from several locations: Label_0043:
        //     at com.strobel.decompiler.ast.Error.expressionLinkedFromMultipleLocations(Error.java:27)
        //     at com.strobel.decompiler.ast.AstOptimizer.mergeDisparateObjectInitializations(AstOptimizer.java:2596)
        //     at com.strobel.decompiler.ast.AstOptimizer.optimize(AstOptimizer.java:235)
        //     at com.strobel.decompiler.ast.AstOptimizer.optimize(AstOptimizer.java:42)
        //     at com.strobel.decompiler.languages.java.ast.AstMethodBodyBuilder.createMethodBody(AstMethodBodyBuilder.java:214)
        //     at com.strobel.decompiler.languages.java.ast.AstMethodBodyBuilder.createMethodBody(AstMethodBodyBuilder.java:99)
        //     at com.strobel.decompiler.languages.java.ast.AstBuilder.createMethodBody(AstBuilder.java:782)
        //     at com.strobel.decompiler.languages.java.ast.AstBuilder.createMethod(AstBuilder.java:675)
        //     at com.strobel.decompiler.languages.java.ast.AstBuilder.addTypeMembers(AstBuilder.java:552)
        //     at com.strobel.decompiler.languages.java.ast.AstBuilder.createTypeCore(AstBuilder.java:519)
        //     at com.strobel.decompiler.languages.java.ast.AstBuilder.createTypeNoCache(AstBuilder.java:161)
        //     at com.strobel.decompiler.languages.java.ast.AstBuilder.createType(AstBuilder.java:150)
        //     at com.strobel.decompiler.languages.java.ast.AstBuilder.addType(AstBuilder.java:125)
        //     at com.strobel.decompiler.languages.java.JavaLanguage.buildAst(JavaLanguage.java:71)
        //     at com.strobel.decompiler.languages.java.JavaLanguage.decompileType(JavaLanguage.java:59)
        //     at com.strobel.decompiler.DecompilerDriver.decompileType(DecompilerDriver.java:330)
        //     at com.strobel.decompiler.DecompilerDriver.decompileJar(DecompilerDriver.java:251)
        //     at com.strobel.decompiler.DecompilerDriver.main(DecompilerDriver.java:126)
        // 
        throw new IllegalStateException("An error occurred while decompiling this method.");
    }
    
    static {
        final char[] charArray = "-+Q\u0007\u0006\u001bNnO".toCharArray();
        int length;
        int n2;
        final int n = n2 = (length = charArray.length);
        int n3 = 0;
        while (true) {
            Label_0102: {
                if (n > 1) {
                    break Label_0102;
                }
                length = (n2 = n3);
                do {
                    final char c = charArray[n2];
                    char c2 = '\0';
                    switch (n3 % 5) {
                        case 0: {
                            c2 = 'T';
                            break;
                        }
                        case 1: {
                            c2 = ']';
                            break;
                        }
                        case 2: {
                            c2 = '(';
                            break;
                        }
                        case 3: {
                            c2 = 'K';
                            break;
                        }
                        default: {
                            c2 = '\u0017';
                            break;
                        }
                    }
                    charArray[length] = (char)(c ^ c2);
                    ++n3;
                } while (n == 0);
            }
            if (n <= n3) {
                z = new String(charArray).intern();
                return;
            }
            continue;
        }
    }
}
