
package org;

final class k
{
    static final int[] a;
    o b;
    int[] c;
    int[] d;
    private int[] e;
    private int[] f;
    private int g;
    private int h;
    private int[] i;
    private static final String[] z;
    
    private int a(final int p0) {
        // 
        // This method could not be decompiled.
        // 
        // Original Bytecode:
        // 
        //     3: istore_3       
        //     4: aload_0        
        //     5: getfield        org/k.e:[I
        //     8: ifnull          32
        //    11: iload_1        
        //    12: iload_3        
        //    13: ifne            44
        //    16: goto            20
        //    19: athrow         
        //    20: aload_0        
        //    21: getfield        org/k.e:[I
        //    24: arraylength    
        //    25: if_icmplt       38
        //    28: goto            32
        //    31: athrow         
        //    32: ldc             33554432
        //    34: iload_1        
        //    35: ior            
        //    36: ireturn        
        //    37: athrow         
        //    38: aload_0        
        //    39: getfield        org/k.e:[I
        //    42: iload_1        
        //    43: iaload         
        //    44: istore_2       
        //    45: iload_2        
        //    46: iload_3        
        //    47: ifne            70
        //    50: ifne            69
        //    53: goto            57
        //    56: athrow         
        //    57: aload_0        
        //    58: getfield        org/k.e:[I
        //    61: iload_1        
        //    62: ldc             33554432
        //    64: iload_1        
        //    65: ior            
        //    66: dup_x2         
        //    67: iastore        
        //    68: istore_2       
        //    69: iload_2        
        //    70: ireturn        
        //    StackMapTable: 00 0B FF 00 13 00 04 07 00 51 01 00 01 00 01 07 00 35 40 01 4A 07 00 35 00 44 07 00 35 00 45 01 FF 00 0B 00 04 07 00 51 01 01 01 00 01 07 00 35 00 0B 40 01
        //    Exceptions:
        //  Try           Handler
        //  Start  End    Start  End    Type                        
        //  -----  -----  -----  -----  ----------------------------
        //  45     53     56     57     Ljava/lang/RuntimeException;
        //  20     37     37     38     Ljava/lang/RuntimeException;
        //  11     28     31     32     Ljava/lang/RuntimeException;
        //  4      16     19     20     Ljava/lang/RuntimeException;
        // 
        // The error that occurred was:
        // 
        // java.lang.IllegalStateException: Expression is linked from several locations: Label_0020:
        //     at com.strobel.decompiler.ast.Error.expressionLinkedFromMultipleLocations(Error.java:27)
        //     at com.strobel.decompiler.ast.AstOptimizer.mergeDisparateObjectInitializations(AstOptimizer.java:2596)
        //     at com.strobel.decompiler.ast.AstOptimizer.optimize(AstOptimizer.java:235)
        //     at com.strobel.decompiler.ast.AstOptimizer.optimize(AstOptimizer.java:42)
        //     at com.strobel.decompiler.languages.java.ast.AstMethodBodyBuilder.createMethodBody(AstMethodBodyBuilder.java:214)
        //     at com.strobel.decompiler.languages.java.ast.AstMethodBodyBuilder.createMethodBody(AstMethodBodyBuilder.java:99)
        //     at com.strobel.decompiler.languages.java.ast.AstBuilder.createMethodBody(AstBuilder.java:782)
        //     at com.strobel.decompiler.languages.java.ast.AstBuilder.createMethod(AstBuilder.java:675)
        //     at com.strobel.decompiler.languages.java.ast.AstBuilder.addTypeMembers(AstBuilder.java:552)
        //     at com.strobel.decompiler.languages.java.ast.AstBuilder.createTypeCore(AstBuilder.java:519)
        //     at com.strobel.decompiler.languages.java.ast.AstBuilder.createTypeNoCache(AstBuilder.java:161)
        //     at com.strobel.decompiler.languages.java.ast.AstBuilder.createType(AstBuilder.java:150)
        //     at com.strobel.decompiler.languages.java.ast.AstBuilder.addType(AstBuilder.java:125)
        //     at com.strobel.decompiler.languages.java.JavaLanguage.buildAst(JavaLanguage.java:71)
        //     at com.strobel.decompiler.languages.java.JavaLanguage.decompileType(JavaLanguage.java:59)
        //     at com.strobel.decompiler.DecompilerDriver.decompileType(DecompilerDriver.java:330)
        //     at com.strobel.decompiler.DecompilerDriver.decompileJar(DecompilerDriver.java:251)
        //     at com.strobel.decompiler.DecompilerDriver.main(DecompilerDriver.java:126)
        // 
        throw new IllegalStateException("An error occurred while decompiling this method.");
    }
    
    private void a(final int n, final int n2) {
        final boolean c = org.f.c;
        int[] array2 = null;
        Label_0037: {
            Label_0021: {
                int[] array;
                try {
                    array = (array2 = this.e);
                    if (c) {
                        break Label_0037;
                    }
                    if (array == null) {
                        break Label_0021;
                    }
                    break Label_0021;
                }
                catch (RuntimeException ex) {
                    throw ex;
                }
                try {
                    if (array == null) {
                        this.e = new int[10];
                    }
                }
                catch (RuntimeException ex2) {
                    throw ex2;
                }
            }
            array2 = this.e;
        }
        final int length = array2.length;
        Label_0084: {
            try {
                if (c) {
                    return;
                }
                if (n < length) {
                    break Label_0084;
                }
            }
            catch (RuntimeException ex3) {
                throw ex3;
            }
            final int[] e = new int[Math.max(n + 1, 2 * length)];
            System.arraycopy(this.e, 0, e, 0, length);
            this.e = e;
        }
        this.e[n] = n2;
    }
    
    private void b(final int n) {
        final boolean c = org.f.c;
        int[] array2 = null;
        Label_0037: {
            Label_0021: {
                int[] array;
                try {
                    array = (array2 = this.f);
                    if (c) {
                        break Label_0037;
                    }
                    if (array == null) {
                        break Label_0021;
                    }
                    break Label_0021;
                }
                catch (RuntimeException ex) {
                    throw ex;
                }
                try {
                    if (array == null) {
                        this.f = new int[10];
                    }
                }
                catch (RuntimeException ex2) {
                    throw ex2;
                }
            }
            array2 = this.f;
        }
        final int length = array2.length;
        int g = 0;
        int n2 = 0;
        Label_0115: {
            Label_0087: {
                try {
                    g = this.g;
                    n2 = length;
                    if (c) {
                        break Label_0115;
                    }
                    if (g < n2) {
                        break Label_0087;
                    }
                }
                catch (RuntimeException ex3) {
                    throw ex3;
                }
                final int[] f = new int[Math.max(this.g + 1, 2 * length)];
                System.arraycopy(this.f, 0, f, 0, length);
                this.f = f;
            }
            this.f[this.g++] = n;
            final int f2 = this.b.f;
            final int g2 = this.g;
        }
        final int g3 = g + n2;
        try {
            if (g3 > this.b.g) {
                this.b.g = g3;
            }
        }
        catch (RuntimeException ex4) {
            throw ex4;
        }
    }
    
    private void a(final g p0, final String p1) {
        // 
        // This method could not be decompiled.
        // 
        // Original Bytecode:
        // 
        //     3: istore          4
        //     5: aload_1        
        //     6: aload_2        
        //     7: invokestatic    org/k.b:(Lorg/g;Ljava/lang/String;)I
        //    10: istore_3       
        //    11: iload_3        
        //    12: iload           4
        //    14: ifne            43
        //    17: ifeq            68
        //    20: goto            24
        //    23: athrow         
        //    24: aload_0        
        //    25: iload_3        
        //    26: iload           4
        //    28: ifne            65
        //    31: goto            35
        //    34: athrow         
        //    35: invokespecial   org/k.b:(I)V
        //    38: iload_3        
        //    39: goto            43
        //    42: athrow         
        //    43: ldc             16777220
        //    45: if_icmpeq       58
        //    48: iload_3        
        //    49: ldc             16777219
        //    51: if_icmpne       68
        //    54: goto            58
        //    57: athrow         
        //    58: aload_0        
        //    59: ldc             16777216
        //    61: goto            65
        //    64: athrow         
        //    65: invokespecial   org/k.b:(I)V
        //    68: return         
        //    StackMapTable: 00 0B FF 00 17 00 05 07 00 51 07 00 82 07 00 7D 01 01 00 01 07 00 35 00 49 07 00 35 FF 00 00 00 05 07 00 51 07 00 82 07 00 7D 01 01 00 02 07 00 51 01 46 07 00 35 40 01 4D 07 00 35 00 45 07 00 35 FF 00 00 00 05 07 00 51 07 00 82 07 00 7D 01 01 00 02 07 00 51 01 02
        //    Exceptions:
        //  Try           Handler
        //  Start  End    Start  End    Type                        
        //  -----  -----  -----  -----  ----------------------------
        //  48     61     64     65     Ljava/lang/RuntimeException;
        //  43     54     57     58     Ljava/lang/RuntimeException;
        //  24     39     42     43     Ljava/lang/RuntimeException;
        //  17     31     34     35     Ljava/lang/RuntimeException;
        //  11     20     23     24     Ljava/lang/RuntimeException;
        // 
        // The error that occurred was:
        // 
        // java.lang.IllegalStateException: Expression is linked from several locations: Label_0024:
        //     at com.strobel.decompiler.ast.Error.expressionLinkedFromMultipleLocations(Error.java:27)
        //     at com.strobel.decompiler.ast.AstOptimizer.mergeDisparateObjectInitializations(AstOptimizer.java:2596)
        //     at com.strobel.decompiler.ast.AstOptimizer.optimize(AstOptimizer.java:235)
        //     at com.strobel.decompiler.ast.AstOptimizer.optimize(AstOptimizer.java:42)
        //     at com.strobel.decompiler.languages.java.ast.AstMethodBodyBuilder.createMethodBody(AstMethodBodyBuilder.java:214)
        //     at com.strobel.decompiler.languages.java.ast.AstMethodBodyBuilder.createMethodBody(AstMethodBodyBuilder.java:99)
        //     at com.strobel.decompiler.languages.java.ast.AstBuilder.createMethodBody(AstBuilder.java:782)
        //     at com.strobel.decompiler.languages.java.ast.AstBuilder.createMethod(AstBuilder.java:675)
        //     at com.strobel.decompiler.languages.java.ast.AstBuilder.addTypeMembers(AstBuilder.java:552)
        //     at com.strobel.decompiler.languages.java.ast.AstBuilder.createTypeCore(AstBuilder.java:519)
        //     at com.strobel.decompiler.languages.java.ast.AstBuilder.createTypeNoCache(AstBuilder.java:161)
        //     at com.strobel.decompiler.languages.java.ast.AstBuilder.createType(AstBuilder.java:150)
        //     at com.strobel.decompiler.languages.java.ast.AstBuilder.addType(AstBuilder.java:125)
        //     at com.strobel.decompiler.languages.java.JavaLanguage.buildAst(JavaLanguage.java:71)
        //     at com.strobel.decompiler.languages.java.JavaLanguage.decompileType(JavaLanguage.java:59)
        //     at com.strobel.decompiler.DecompilerDriver.decompileType(DecompilerDriver.java:330)
        //     at com.strobel.decompiler.DecompilerDriver.decompileJar(DecompilerDriver.java:251)
        //     at com.strobel.decompiler.DecompilerDriver.main(DecompilerDriver.java:126)
        // 
        throw new IllegalStateException("An error occurred while decompiling this method.");
    }
    
    private static int b(final g g, final String s) {
        final boolean c = f.c;
        int n4 = 0;
        Label_0040: {
            Label_0039: {
                int n = 0;
                int n3 = 0;
                Label_0024: {
                    char c2;
                    int n2;
                    try {
                        c2 = (char)(n = s.charAt(0));
                        n2 = (n3 = 40);
                        if (c) {
                            break Label_0024;
                        }
                        if (c2 == n2) {
                            break Label_0024;
                        }
                        break Label_0039;
                    }
                    catch (RuntimeException ex) {
                        throw ex;
                    }
                    try {
                        if (c2 != n2) {
                            break Label_0039;
                        }
                        n = s.indexOf(41);
                        n3 = 1;
                    }
                    catch (RuntimeException ex2) {
                        throw ex2;
                    }
                }
                n4 = n + n3;
                break Label_0040;
            }
            n4 = 0;
        }
        final int index = n4;
        int char1 = 0;
        Label_0206: {
            Label_0203: {
                char c3;
                try {
                    c3 = (char)(char1 = s.charAt(index));
                    if (c) {
                        break Label_0206;
                    }
                    switch (c3) {
                        case 86: {
                            return 0;
                        }
                        case 66:
                        case 67:
                        case 73:
                        case 83:
                        case 90: {
                            return 16777217;
                        }
                        case 70: {
                            return 16777218;
                        }
                        case 74: {
                            return 16777220;
                        }
                        case 68: {
                            return 16777219;
                        }
                        case 76: {
                            return 0x1700000 | g.f(s.substring(index + 1, s.length() - 1));
                        }
                        default: {
                            break Label_0203;
                        }
                    }
                }
                catch (RuntimeException ex3) {
                    throw ex3;
                }
                try {
                    switch (c3) {
                        case 86: {
                            return 0;
                        }
                        case 66:
                        case 67:
                        case 73:
                        case 83:
                        case 90: {
                            break;
                        }
                        case 70: {
                            return 16777218;
                        }
                        case 74: {
                            return 16777220;
                        }
                        case 68: {
                            return 16777219;
                        }
                        case 76: {
                            return 0x1700000 | g.f(s.substring(index + 1, s.length() - 1));
                        }
                        default: {
                            break Label_0203;
                        }
                    }
                }
                catch (RuntimeException ex4) {
                    throw ex4;
                }
                return 16777217;
            }
            char1 = index + 1;
        }
        int index2 = char1;
        int n5 = 0;
        String s2;
        int n6;
        Label_0379:Label_0388_Outer:
        while (true) {
            Label_0370: {
            Label_0397_Outer:
                while (true) {
                Label_0406_Outer:
                    while (true) {
                    Label_0415_Outer:
                        while (true) {
                        Label_0424_Outer:
                            while (true) {
                            Label_0433_Outer:
                                while (true) {
                                Label_0442_Outer:
                                    while (true) {
                                        while (true) {
                                            while (s.charAt(index2) == '[') {
                                                try {
                                                    ++index2;
                                                    if (c) {
                                                        break Label_0379;
                                                    }
                                                    if (!c) {
                                                        continue Label_0388_Outer;
                                                    }
                                                }
                                                catch (RuntimeException ex5) {
                                                    throw ex5;
                                                }
                                                break;
                                                n5 = 16777226;
                                                if (c) {
                                                    n5 = 16777228;
                                                    if (c) {
                                                        n5 = 16777217;
                                                        if (c) {
                                                            n5 = 16777218;
                                                            if (c) {
                                                                n5 = 16777220;
                                                                if (c) {
                                                                    n5 = 16777219;
                                                                    try {
                                                                        if (!c) {
                                                                            return index2 - index << 28 | n5;
                                                                        }
                                                                        s2 = s;
                                                                    }
                                                                    catch (RuntimeException ex6) {
                                                                        throw ex6;
                                                                    }
                                                                    n5 = (0x1700000 | g.f(s2.substring(n6, s.length() - 1)));
                                                                }
                                                            }
                                                        }
                                                    }
                                                }
                                                return index2 - index << 28 | n5;
                                            }
                                            try {
                                                s2 = s;
                                                n6 = index2;
                                                if (c) {
                                                    continue;
                                                }
                                                switch (s.charAt(n6)) {
                                                    case 'Z': {
                                                        break;
                                                    }
                                                    case 'C': {
                                                        break Label_0370;
                                                    }
                                                    case 'B': {
                                                        continue Label_0379;
                                                    }
                                                    case 'S': {
                                                        continue Label_0397_Outer;
                                                    }
                                                    case 'I': {
                                                        continue Label_0406_Outer;
                                                    }
                                                    case 'F': {
                                                        continue Label_0415_Outer;
                                                    }
                                                    case 'J': {
                                                        continue Label_0424_Outer;
                                                    }
                                                    case 'D': {
                                                        continue Label_0433_Outer;
                                                    }
                                                    default: {
                                                        continue Label_0442_Outer;
                                                    }
                                                }
                                            }
                                            catch (RuntimeException ex7) {
                                                throw ex7;
                                            }
                                            break;
                                        }
                                        break;
                                    }
                                    break;
                                }
                                break;
                            }
                            break;
                        }
                        break;
                    }
                    break;
                }
                n5 = 16777225;
                if (!c) {
                    return index2 - index << 28 | n5;
                }
            }
            n5 = 16777227;
            if (c) {
                continue Label_0379;
            }
            break;
        }
        return index2 - index << 28 | n5;
    }
    
    private int a() {
        Label_0017: {
            int n;
            try {
                final int g;
                n = (g = this.g);
                if (org.f.c) {
                    return g;
                }
                if (n > 0) {
                    break Label_0017;
                }
                break Label_0017;
            }
            catch (RuntimeException ex) {
                throw ex;
            }
            try {
                if (n > 0) {
                    final int[] f = this.f;
                    final int g2 = this.g - 1;
                    this.g = g2;
                    return f[g2];
                }
            }
            catch (RuntimeException ex2) {
                throw ex2;
            }
        }
        final int n2 = 50331648;
        final o b = this.b;
        final int f2 = b.f - 1;
        b.f = f2;
        return n2 | -f2;
    }
    
    private void c(final int p0) {
        // 
        // This method could not be decompiled.
        // 
        // Original Bytecode:
        // 
        //     3: istore_2       
        //     4: aload_0        
        //     5: iload_2        
        //     6: ifne            61
        //     9: getfield        org/k.g:I
        //    12: iload_1        
        //    13: if_icmplt       38
        //    16: goto            20
        //    19: athrow         
        //    20: aload_0        
        //    21: dup            
        //    22: getfield        org/k.g:I
        //    25: iload_1        
        //    26: isub           
        //    27: putfield        org/k.g:I
        //    30: iload_2        
        //    31: ifeq            65
        //    34: goto            38
        //    37: athrow         
        //    38: aload_0        
        //    39: getfield        org/k.b:Lorg/o;
        //    42: dup            
        //    43: getfield        org/o.f:I
        //    46: iload_1        
        //    47: aload_0        
        //    48: getfield        org/k.g:I
        //    51: isub           
        //    52: isub           
        //    53: putfield        org/o.f:I
        //    56: aload_0        
        //    57: goto            61
        //    60: athrow         
        //    61: iconst_0       
        //    62: putfield        org/k.g:I
        //    65: return         
        //    StackMapTable: 00 07 FF 00 13 00 03 07 00 51 01 01 00 01 07 00 35 00 50 07 00 35 00 55 07 00 35 40 07 00 51 03
        //    Exceptions:
        //  Try           Handler
        //  Start  End    Start  End    Type                        
        //  -----  -----  -----  -----  ----------------------------
        //  20     57     60     61     Ljava/lang/RuntimeException;
        //  9      34     37     38     Ljava/lang/RuntimeException;
        //  4      16     19     20     Ljava/lang/RuntimeException;
        // 
        // The error that occurred was:
        // 
        // java.lang.IllegalStateException: Expression is linked from several locations: Label_0020:
        //     at com.strobel.decompiler.ast.Error.expressionLinkedFromMultipleLocations(Error.java:27)
        //     at com.strobel.decompiler.ast.AstOptimizer.mergeDisparateObjectInitializations(AstOptimizer.java:2596)
        //     at com.strobel.decompiler.ast.AstOptimizer.optimize(AstOptimizer.java:235)
        //     at com.strobel.decompiler.ast.AstOptimizer.optimize(AstOptimizer.java:42)
        //     at com.strobel.decompiler.languages.java.ast.AstMethodBodyBuilder.createMethodBody(AstMethodBodyBuilder.java:214)
        //     at com.strobel.decompiler.languages.java.ast.AstMethodBodyBuilder.createMethodBody(AstMethodBodyBuilder.java:99)
        //     at com.strobel.decompiler.languages.java.ast.AstBuilder.createMethodBody(AstBuilder.java:782)
        //     at com.strobel.decompiler.languages.java.ast.AstBuilder.createMethod(AstBuilder.java:675)
        //     at com.strobel.decompiler.languages.java.ast.AstBuilder.addTypeMembers(AstBuilder.java:552)
        //     at com.strobel.decompiler.languages.java.ast.AstBuilder.createTypeCore(AstBuilder.java:519)
        //     at com.strobel.decompiler.languages.java.ast.AstBuilder.createTypeNoCache(AstBuilder.java:161)
        //     at com.strobel.decompiler.languages.java.ast.AstBuilder.createType(AstBuilder.java:150)
        //     at com.strobel.decompiler.languages.java.ast.AstBuilder.addType(AstBuilder.java:125)
        //     at com.strobel.decompiler.languages.java.JavaLanguage.buildAst(JavaLanguage.java:71)
        //     at com.strobel.decompiler.languages.java.JavaLanguage.decompileType(JavaLanguage.java:59)
        //     at com.strobel.decompiler.DecompilerDriver.decompileType(DecompilerDriver.java:330)
        //     at com.strobel.decompiler.DecompilerDriver.decompileJar(DecompilerDriver.java:251)
        //     at com.strobel.decompiler.DecompilerDriver.main(DecompilerDriver.java:126)
        // 
        throw new IllegalStateException("An error occurred while decompiling this method.");
    }
    
    private void a(final String p0) {
        // 
        // This method could not be decompiled.
        // 
        // Original Bytecode:
        // 
        //     3: istore_3       
        //     4: aload_1        
        //     5: iconst_0       
        //     6: invokevirtual   java/lang/String.charAt:(I)C
        //     9: istore_2       
        //    10: iload_2        
        //    11: bipush          40
        //    13: iload_3        
        //    14: ifne            51
        //    17: if_icmpne       44
        //    20: goto            24
        //    23: athrow         
        //    24: aload_0        
        //    25: aload_1        
        //    26: invokestatic    org/u.e:(Ljava/lang/String;)I
        //    29: iconst_2       
        //    30: ishr           
        //    31: iconst_1       
        //    32: isub           
        //    33: invokespecial   org/k.c:(I)V
        //    36: iload_3        
        //    37: ifeq            94
        //    40: goto            44
        //    43: athrow         
        //    44: iload_2        
        //    45: bipush          74
        //    47: goto            51
        //    50: athrow         
        //    51: iload_3        
        //    52: ifne            69
        //    55: if_icmpeq       72
        //    58: goto            62
        //    61: athrow         
        //    62: iload_2        
        //    63: bipush          68
        //    65: goto            69
        //    68: athrow         
        //    69: if_icmpne       85
        //    72: aload_0        
        //    73: iconst_2       
        //    74: invokespecial   org/k.c:(I)V
        //    77: iload_3        
        //    78: ifeq            94
        //    81: goto            85
        //    84: athrow         
        //    85: aload_0        
        //    86: iconst_1       
        //    87: invokespecial   org/k.c:(I)V
        //    90: goto            94
        //    93: athrow         
        //    94: return         
        //    StackMapTable: 00 0F FF 00 17 00 04 07 00 51 07 00 7D 01 01 00 01 07 00 35 00 52 07 00 35 00 45 07 00 35 FF 00 00 00 04 07 00 51 07 00 7D 01 01 00 02 01 01 49 07 00 35 00 45 07 00 35 FF 00 00 00 04 07 00 51 07 00 7D 01 01 00 02 01 01 02 4B 07 00 35 00 47 07 00 35 00
        //    Exceptions:
        //  Try           Handler
        //  Start  End    Start  End    Type                        
        //  -----  -----  -----  -----  ----------------------------
        //  72     90     93     94     Ljava/lang/RuntimeException;
        //  69     81     84     85     Ljava/lang/RuntimeException;
        //  55     65     68     69     Ljava/lang/RuntimeException;
        //  51     58     61     62     Ljava/lang/RuntimeException;
        //  24     47     50     51     Ljava/lang/RuntimeException;
        //  17     40     43     44     Ljava/lang/RuntimeException;
        //  10     20     23     24     Ljava/lang/RuntimeException;
        // 
        // The error that occurred was:
        // 
        // java.lang.IllegalStateException: Expression is linked from several locations: Label_0024:
        //     at com.strobel.decompiler.ast.Error.expressionLinkedFromMultipleLocations(Error.java:27)
        //     at com.strobel.decompiler.ast.AstOptimizer.mergeDisparateObjectInitializations(AstOptimizer.java:2596)
        //     at com.strobel.decompiler.ast.AstOptimizer.optimize(AstOptimizer.java:235)
        //     at com.strobel.decompiler.ast.AstOptimizer.optimize(AstOptimizer.java:42)
        //     at com.strobel.decompiler.languages.java.ast.AstMethodBodyBuilder.createMethodBody(AstMethodBodyBuilder.java:214)
        //     at com.strobel.decompiler.languages.java.ast.AstMethodBodyBuilder.createMethodBody(AstMethodBodyBuilder.java:99)
        //     at com.strobel.decompiler.languages.java.ast.AstBuilder.createMethodBody(AstBuilder.java:782)
        //     at com.strobel.decompiler.languages.java.ast.AstBuilder.createMethod(AstBuilder.java:675)
        //     at com.strobel.decompiler.languages.java.ast.AstBuilder.addTypeMembers(AstBuilder.java:552)
        //     at com.strobel.decompiler.languages.java.ast.AstBuilder.createTypeCore(AstBuilder.java:519)
        //     at com.strobel.decompiler.languages.java.ast.AstBuilder.createTypeNoCache(AstBuilder.java:161)
        //     at com.strobel.decompiler.languages.java.ast.AstBuilder.createType(AstBuilder.java:150)
        //     at com.strobel.decompiler.languages.java.ast.AstBuilder.addType(AstBuilder.java:125)
        //     at com.strobel.decompiler.languages.java.JavaLanguage.buildAst(JavaLanguage.java:71)
        //     at com.strobel.decompiler.languages.java.JavaLanguage.decompileType(JavaLanguage.java:59)
        //     at com.strobel.decompiler.DecompilerDriver.decompileType(DecompilerDriver.java:330)
        //     at com.strobel.decompiler.DecompilerDriver.decompileJar(DecompilerDriver.java:251)
        //     at com.strobel.decompiler.DecompilerDriver.main(DecompilerDriver.java:126)
        // 
        throw new IllegalStateException("An error occurred while decompiling this method.");
    }
    
    private void d(final int n) {
        final boolean c = org.f.c;
        int[] array2 = null;
        Label_0036: {
            Label_0021: {
                int[] array;
                try {
                    array = (array2 = this.i);
                    if (c) {
                        break Label_0036;
                    }
                    if (array == null) {
                        break Label_0021;
                    }
                    break Label_0021;
                }
                catch (RuntimeException ex) {
                    throw ex;
                }
                try {
                    if (array == null) {
                        this.i = new int[2];
                    }
                }
                catch (RuntimeException ex2) {
                    throw ex2;
                }
            }
            array2 = this.i;
        }
        final int length = array2.length;
        k k = null;
        Label_0087: {
            Label_0086: {
                try {
                    k = this;
                    if (c) {
                        break Label_0087;
                    }
                    if (this.h < length) {
                        break Label_0086;
                    }
                }
                catch (RuntimeException ex3) {
                    throw ex3;
                }
                final int[] i = new int[Math.max(this.h + 1, 2 * length)];
                System.arraycopy(this.i, 0, i, 0, length);
                this.i = i;
            }
            k = this;
        }
        k.i[this.h++] = n;
    }
    
    private int a(final g p0, final int p1) {
        // 
        // This method could not be decompiled.
        // 
        // Original Bytecode:
        // 
        //     3: istore          8
        //     5: iload_2        
        //     6: ldc             16777222
        //     8: iload           8
        //    10: ifne            56
        //    13: if_icmpne       37
        //    16: goto            20
        //    19: athrow         
        //    20: ldc             24117248
        //    22: aload_1        
        //    23: aload_1        
        //    24: getfield        org/g.s:Ljava/lang/String;
        //    27: invokevirtual   org/g.f:(Ljava/lang/String;)I
        //    30: ior            
        //    31: istore_3       
        //    32: iload           8
        //    34: ifeq            94
        //    37: iload_2        
        //    38: ldc             -1048576
        //    40: iand           
        //    41: iload           8
        //    43: ifne            93
        //    46: goto            50
        //    49: athrow         
        //    50: ldc             25165824
        //    52: goto            56
        //    55: athrow         
        //    56: if_icmpne       88
        //    59: aload_1        
        //    60: getfield        org/g.o:[Lorg/n;
        //    63: iload_2        
        //    64: ldc             1048575
        //    66: iand           
        //    67: aaload         
        //    68: getfield        org/n.e:Ljava/lang/String;
        //    71: astore          4
        //    73: ldc             24117248
        //    75: aload_1        
        //    76: aload           4
        //    78: invokevirtual   org/g.f:(Ljava/lang/String;)I
        //    81: ior            
        //    82: istore_3       
        //    83: iload           8
        //    85: ifeq            94
        //    88: iload_2        
        //    89: goto            93
        //    92: athrow         
        //    93: ireturn        
        //    94: iconst_0       
        //    95: istore          4
        //    97: iload           4
        //    99: aload_0        
        //   100: getfield        org/k.h:I
        //   103: if_icmpge       240
        //   106: aload_0        
        //   107: getfield        org/k.i:[I
        //   110: iload           4
        //   112: iaload         
        //   113: istore          5
        //   115: iload           5
        //   117: ldc             -268435456
        //   119: iand           
        //   120: istore          6
        //   122: iload           5
        //   124: ldc             251658240
        //   126: iand           
        //   127: istore          7
        //   129: iload           7
        //   131: iload           8
        //   133: ifne            241
        //   136: ldc             33554432
        //   138: iload           8
        //   140: ifne            182
        //   143: goto            147
        //   146: athrow         
        //   147: if_icmpne       174
        //   150: goto            154
        //   153: athrow         
        //   154: iload           6
        //   156: aload_0        
        //   157: getfield        org/k.c:[I
        //   160: iload           5
        //   162: ldc             8388607
        //   164: iand           
        //   165: iaload         
        //   166: iadd           
        //   167: istore          5
        //   169: iload           8
        //   171: ifeq            215
        //   174: iload           7
        //   176: ldc             50331648
        //   178: goto            182
        //   181: athrow         
        //   182: iload           8
        //   184: ifne            227
        //   187: if_icmpne       215
        //   190: goto            194
        //   193: athrow         
        //   194: iload           6
        //   196: aload_0        
        //   197: getfield        org/k.d:[I
        //   200: aload_0        
        //   201: getfield        org/k.d:[I
        //   204: arraylength    
        //   205: iload           5
        //   207: ldc             8388607
        //   209: iand           
        //   210: isub           
        //   211: iaload         
        //   212: iadd           
        //   213: istore          5
        //   215: iload_2        
        //   216: iload           8
        //   218: ifne            231
        //   221: iload           5
        //   223: goto            227
        //   226: athrow         
        //   227: if_icmpne       232
        //   230: iload_3        
        //   231: ireturn        
        //   232: iinc            4, 1
        //   235: iload           8
        //   237: ifeq            97
        //   240: iload_2        
        //   241: ireturn        
        //    StackMapTable: 00 1C FF 00 13 00 09 07 00 51 07 00 82 01 00 00 00 00 00 01 00 01 07 00 35 00 10 4B 07 00 35 40 01 44 07 00 35 FF 00 00 00 09 07 00 51 07 00 82 01 00 00 00 00 00 01 00 02 01 01 1F 43 07 00 35 40 01 FF 00 00 00 09 07 00 51 07 00 82 01 01 00 00 00 00 01 00 00 FF 00 02 00 09 07 00 51 07 00 82 01 01 01 00 00 00 01 00 00 FF 00 30 00 09 07 00 51 07 00 82 01 01 01 01 01 01 01 00 01 07 00 35 FF 00 00 00 09 07 00 51 07 00 82 01 01 01 01 01 01 01 00 02 01 01 45 07 00 35 00 13 46 07 00 35 FF 00 00 00 09 07 00 51 07 00 82 01 01 01 01 01 01 01 00 02 01 01 4A 07 00 35 00 14 4A 07 00 35 FF 00 00 00 09 07 00 51 07 00 82 01 01 01 01 01 01 01 00 02 01 01 43 01 00 FF 00 07 00 09 07 00 51 07 00 82 01 01 01 00 00 00 01 00 00 40 01
        //    Exceptions:
        //  Try           Handler
        //  Start  End    Start  End    Type                        
        //  -----  -----  -----  -----  ----------------------------
        //  215    223    226    227    Ljava/lang/RuntimeException;
        //  182    190    193    194    Ljava/lang/RuntimeException;
        //  169    178    181    182    Ljava/lang/RuntimeException;
        //  136    150    153    154    Ljava/lang/RuntimeException;
        //  129    143    146    147    Ljava/lang/RuntimeException;
        //  83     89     92     93     Ljava/lang/RuntimeException;
        //  37     52     55     56     Ljava/lang/RuntimeException;
        //  32     46     49     50     Ljava/lang/RuntimeException;
        //  5      16     19     20     Ljava/lang/RuntimeException;
        // 
        // The error that occurred was:
        // 
        // java.lang.IllegalStateException: Expression is linked from several locations: Label_0037:
        //     at com.strobel.decompiler.ast.Error.expressionLinkedFromMultipleLocations(Error.java:27)
        //     at com.strobel.decompiler.ast.AstOptimizer.mergeDisparateObjectInitializations(AstOptimizer.java:2596)
        //     at com.strobel.decompiler.ast.AstOptimizer.optimize(AstOptimizer.java:235)
        //     at com.strobel.decompiler.ast.AstOptimizer.optimize(AstOptimizer.java:42)
        //     at com.strobel.decompiler.languages.java.ast.AstMethodBodyBuilder.createMethodBody(AstMethodBodyBuilder.java:214)
        //     at com.strobel.decompiler.languages.java.ast.AstMethodBodyBuilder.createMethodBody(AstMethodBodyBuilder.java:99)
        //     at com.strobel.decompiler.languages.java.ast.AstBuilder.createMethodBody(AstBuilder.java:782)
        //     at com.strobel.decompiler.languages.java.ast.AstBuilder.createMethod(AstBuilder.java:675)
        //     at com.strobel.decompiler.languages.java.ast.AstBuilder.addTypeMembers(AstBuilder.java:552)
        //     at com.strobel.decompiler.languages.java.ast.AstBuilder.createTypeCore(AstBuilder.java:519)
        //     at com.strobel.decompiler.languages.java.ast.AstBuilder.createTypeNoCache(AstBuilder.java:161)
        //     at com.strobel.decompiler.languages.java.ast.AstBuilder.createType(AstBuilder.java:150)
        //     at com.strobel.decompiler.languages.java.ast.AstBuilder.addType(AstBuilder.java:125)
        //     at com.strobel.decompiler.languages.java.JavaLanguage.buildAst(JavaLanguage.java:71)
        //     at com.strobel.decompiler.languages.java.JavaLanguage.decompileType(JavaLanguage.java:59)
        //     at com.strobel.decompiler.DecompilerDriver.decompileType(DecompilerDriver.java:330)
        //     at com.strobel.decompiler.DecompilerDriver.decompileJar(DecompilerDriver.java:251)
        //     at com.strobel.decompiler.DecompilerDriver.main(DecompilerDriver.java:126)
        // 
        throw new IllegalStateException("An error occurred while decompiling this method.");
    }
    
    void a(final g p0, final int p1, final u[] p2, final int p3) {
        // 
        // This method could not be decompiled.
        // 
        // Original Bytecode:
        // 
        //     5: aload_0        
        //     6: iload           4
        //     8: newarray        I
        //    10: putfield        org/k.c:[I
        //    13: aload_0        
        //    14: iconst_0       
        //    15: newarray        I
        //    17: putfield        org/k.d:[I
        //    20: iconst_0       
        //    21: istore          5
        //    23: iload_2        
        //    24: bipush          8
        //    26: iand           
        //    27: iload           8
        //    29: ifne            97
        //    32: ifne            96
        //    35: goto            39
        //    38: athrow         
        //    39: iload_2        
        //    40: ldc             262144
        //    42: iand           
        //    43: ifne            80
        //    46: goto            50
        //    49: athrow         
        //    50: aload_0        
        //    51: getfield        org/k.c:[I
        //    54: iload           5
        //    56: iinc            5, 1
        //    59: ldc             24117248
        //    61: aload_1        
        //    62: aload_1        
        //    63: getfield        org/g.s:Ljava/lang/String;
        //    66: invokevirtual   org/g.f:(Ljava/lang/String;)I
        //    69: ior            
        //    70: iastore        
        //    71: iload           8
        //    73: ifeq            96
        //    76: goto            80
        //    79: athrow         
        //    80: aload_0        
        //    81: getfield        org/k.c:[I
        //    84: iload           5
        //    86: iinc            5, 1
        //    89: ldc             16777222
        //    91: iastore        
        //    92: goto            96
        //    95: athrow         
        //    96: iconst_0       
        //    97: istore          6
        //    99: iload           6
        //   101: aload_3        
        //   102: arraylength    
        //   103: if_icmpge       191
        //   106: aload_1        
        //   107: aload_3        
        //   108: iload           6
        //   110: aaload         
        //   111: invokevirtual   org/u.c:()Ljava/lang/String;
        //   114: invokestatic    org/k.b:(Lorg/g;Ljava/lang/String;)I
        //   117: istore          7
        //   119: aload_0        
        //   120: getfield        org/k.c:[I
        //   123: iload           5
        //   125: iinc            5, 1
        //   128: iload           7
        //   130: iload           8
        //   132: ifne            182
        //   135: iastore        
        //   136: iload           7
        //   138: ldc             16777220
        //   140: iload           8
        //   142: ifne            195
        //   145: goto            149
        //   148: athrow         
        //   149: if_icmpeq       167
        //   152: goto            156
        //   155: athrow         
        //   156: iload           7
        //   158: ldc             16777219
        //   160: if_icmpne       183
        //   163: goto            167
        //   166: athrow         
        //   167: aload_0        
        //   168: getfield        org/k.c:[I
        //   171: iload           5
        //   173: iinc            5, 1
        //   176: ldc             16777216
        //   178: goto            182
        //   181: athrow         
        //   182: iastore        
        //   183: iinc            6, 1
        //   186: iload           8
        //   188: ifeq            99
        //   191: iload           5
        //   193: iload           4
        //   195: if_icmpge       219
        //   198: aload_0        
        //   199: getfield        org/k.c:[I
        //   202: iload           5
        //   204: iinc            5, 1
        //   207: ldc             16777216
        //   209: iastore        
        //   210: iload           8
        //   212: ifeq            191
        //   215: goto            219
        //   218: athrow         
        //   219: return         
        //    StackMapTable: 00 17 FF 00 26 00 09 07 00 51 07 00 82 01 07 00 E8 01 01 00 00 01 00 01 07 00 35 00 49 07 00 35 00 5C 07 00 35 00 4E 07 00 35 00 40 01 FF 00 01 00 09 07 00 51 07 00 82 01 07 00 E8 01 01 01 00 01 00 00 FF 00 30 00 09 07 00 51 07 00 82 01 07 00 E8 01 01 01 01 01 00 01 07 00 35 FF 00 00 00 09 07 00 51 07 00 82 01 07 00 E8 01 01 01 01 01 00 02 01 01 45 07 00 35 00 49 07 00 35 00 4D 07 00 35 FF 00 00 00 09 07 00 51 07 00 82 01 07 00 E8 01 01 01 01 01 00 03 07 00 E7 01 01 00 FF 00 07 00 09 07 00 51 07 00 82 01 07 00 E8 01 01 01 00 01 00 00 FF 00 03 00 09 07 00 51 07 00 82 01 07 00 E8 01 01 01 00 01 00 02 01 01 56 07 00 35 00
        //    Exceptions:
        //  Try           Handler
        //  Start  End    Start  End    Type                        
        //  -----  -----  -----  -----  ----------------------------
        //  195    215    218    219    Ljava/lang/RuntimeException;
        //  156    178    181    182    Ljava/lang/RuntimeException;
        //  149    163    166    167    Ljava/lang/RuntimeException;
        //  135    152    155    156    Ljava/lang/RuntimeException;
        //  119    145    148    149    Ljava/lang/RuntimeException;
        //  50     92     95     96     Ljava/lang/RuntimeException;
        //  39     76     79     80     Ljava/lang/RuntimeException;
        //  32     46     49     50     Ljava/lang/RuntimeException;
        //  23     35     38     39     Ljava/lang/RuntimeException;
        // 
        // The error that occurred was:
        // 
        // java.lang.IllegalStateException: Expression is linked from several locations: Label_0039:
        //     at com.strobel.decompiler.ast.Error.expressionLinkedFromMultipleLocations(Error.java:27)
        //     at com.strobel.decompiler.ast.AstOptimizer.mergeDisparateObjectInitializations(AstOptimizer.java:2596)
        //     at com.strobel.decompiler.ast.AstOptimizer.optimize(AstOptimizer.java:235)
        //     at com.strobel.decompiler.ast.AstOptimizer.optimize(AstOptimizer.java:42)
        //     at com.strobel.decompiler.languages.java.ast.AstMethodBodyBuilder.createMethodBody(AstMethodBodyBuilder.java:214)
        //     at com.strobel.decompiler.languages.java.ast.AstMethodBodyBuilder.createMethodBody(AstMethodBodyBuilder.java:99)
        //     at com.strobel.decompiler.languages.java.ast.AstBuilder.createMethodBody(AstBuilder.java:782)
        //     at com.strobel.decompiler.languages.java.ast.AstBuilder.createMethod(AstBuilder.java:675)
        //     at com.strobel.decompiler.languages.java.ast.AstBuilder.addTypeMembers(AstBuilder.java:552)
        //     at com.strobel.decompiler.languages.java.ast.AstBuilder.createTypeCore(AstBuilder.java:519)
        //     at com.strobel.decompiler.languages.java.ast.AstBuilder.createTypeNoCache(AstBuilder.java:161)
        //     at com.strobel.decompiler.languages.java.ast.AstBuilder.createType(AstBuilder.java:150)
        //     at com.strobel.decompiler.languages.java.ast.AstBuilder.addType(AstBuilder.java:125)
        //     at com.strobel.decompiler.languages.java.JavaLanguage.buildAst(JavaLanguage.java:71)
        //     at com.strobel.decompiler.languages.java.JavaLanguage.decompileType(JavaLanguage.java:59)
        //     at com.strobel.decompiler.DecompilerDriver.decompileType(DecompilerDriver.java:330)
        //     at com.strobel.decompiler.DecompilerDriver.decompileJar(DecompilerDriver.java:251)
        //     at com.strobel.decompiler.DecompilerDriver.main(DecompilerDriver.java:126)
        // 
        throw new IllegalStateException("An error occurred while decompiling this method.");
    }
    
    void a(final int p0, final int p1, final g p2, final n p3) {
        // 
        // This method could not be decompiled.
        // 
        // Original Bytecode:
        // 
        //     5: iload           10
        //     7: ifne            2772
        //    10: iload_1        
        //    11: tableswitch {
        //                0: 825
        //                1: 834
        //                2: 849
        //                3: 849
        //                4: 849
        //                5: 849
        //                6: 849
        //                7: 849
        //                8: 849
        //                9: 864
        //               10: 864
        //               11: 885
        //               12: 885
        //               13: 885
        //               14: 900
        //               15: 900
        //               16: 849
        //               17: 849
        //               18: 921
        //               19: 2763
        //               20: 2763
        //               21: 849
        //               22: 864
        //               23: 885
        //               24: 900
        //               25: 1181
        //               26: 2763
        //               27: 2763
        //               28: 2763
        //               29: 2763
        //               30: 2763
        //               31: 2763
        //               32: 2763
        //               33: 2763
        //               34: 2763
        //               35: 2763
        //               36: 2763
        //               37: 2763
        //               38: 2763
        //               39: 2763
        //               40: 2763
        //               41: 2763
        //               42: 2763
        //               43: 2763
        //               44: 2763
        //               45: 2763
        //               46: 1199
        //               47: 1219
        //               48: 1245
        //               49: 1265
        //               50: 1291
        //               51: 1199
        //               52: 1199
        //               53: 1199
        //               54: 1316
        //               55: 1444
        //               56: 1316
        //               57: 1444
        //               58: 1316
        //               59: 2763
        //               60: 2763
        //               61: 2763
        //               62: 2763
        //               63: 2763
        //               64: 2763
        //               65: 2763
        //               66: 2763
        //               67: 2763
        //               68: 2763
        //               69: 2763
        //               70: 2763
        //               71: 2763
        //               72: 2763
        //               73: 2763
        //               74: 2763
        //               75: 2763
        //               76: 2763
        //               77: 2763
        //               78: 2763
        //               79: 1586
        //               80: 1600
        //               81: 1586
        //               82: 1600
        //               83: 1586
        //               84: 1586
        //               85: 1586
        //               86: 1586
        //               87: 1614
        //               88: 1628
        //               89: 1642
        //               90: 1665
        //               91: 1700
        //               92: 1747
        //               93: 1788
        //               94: 1841
        //               95: 1906
        //               96: 1935
        //               97: 1955
        //               98: 1981
        //               99: 2001
        //              100: 1935
        //              101: 1955
        //              102: 1981
        //              103: 2001
        //              104: 1935
        //              105: 1955
        //              106: 1981
        //              107: 2001
        //              108: 1935
        //              109: 1955
        //              110: 1981
        //              111: 2001
        //              112: 1935
        //              113: 1955
        //              114: 1981
        //              115: 2001
        //              116: 825
        //              117: 825
        //              118: 825
        //              119: 825
        //              120: 1935
        //              121: 2027
        //              122: 1935
        //              123: 2027
        //              124: 1935
        //              125: 2027
        //              126: 1935
        //              127: 1955
        //              128: 1935
        //              129: 1955
        //              130: 1935
        //              131: 1955
        //              132: 2053
        //              133: 2069
        //              134: 2095
        //              135: 2115
        //              136: 1935
        //              137: 1981
        //              138: 1265
        //              139: 2141
        //              140: 2069
        //              141: 2115
        //              142: 1935
        //              143: 1219
        //              144: 1981
        //              145: 825
        //              146: 825
        //              147: 825
        //              148: 2161
        //              149: 1935
        //              150: 1935
        //              151: 2161
        //              152: 2161
        //              153: 1614
        //              154: 1614
        //              155: 1614
        //              156: 1614
        //              157: 1614
        //              158: 1614
        //              159: 1628
        //              160: 1628
        //              161: 1628
        //              162: 1628
        //              163: 1628
        //              164: 1628
        //              165: 1628
        //              166: 1628
        //              167: 825
        //              168: 2181
        //              169: 2181
        //              170: 1614
        //              171: 1614
        //              172: 1614
        //              173: 1628
        //              174: 1614
        //              175: 1628
        //              176: 1614
        //              177: 825
        //              178: 2198
        //              179: 2213
        //              180: 2231
        //              181: 2255
        //              182: 2278
        //              183: 2278
        //              184: 2278
        //              185: 2278
        //              186: 2372
        //              187: 2400
        //              188: 2426
        //              189: 2605
        //              190: 2141
        //              191: 1614
        //              192: 2693
        //              193: 2141
        //              194: 1614
        //              195: 1614
        //              196: 2763
        //              197: 2763
        //              198: 1614
        //              199: 1614
        //          default: 2763
        //        }
        //   824: athrow         
        //   825: iload           10
        //   827: ifeq            2782
        //   830: goto            834
        //   833: athrow         
        //   834: aload_0        
        //   835: ldc             16777221
        //   837: invokespecial   org/k.b:(I)V
        //   840: iload           10
        //   842: ifeq            2782
        //   845: goto            849
        //   848: athrow         
        //   849: aload_0        
        //   850: ldc             16777217
        //   852: invokespecial   org/k.b:(I)V
        //   855: iload           10
        //   857: ifeq            2782
        //   860: goto            864
        //   863: athrow         
        //   864: aload_0        
        //   865: ldc             16777220
        //   867: invokespecial   org/k.b:(I)V
        //   870: aload_0        
        //   871: ldc             16777216
        //   873: invokespecial   org/k.b:(I)V
        //   876: iload           10
        //   878: ifeq            2782
        //   881: goto            885
        //   884: athrow         
        //   885: aload_0        
        //   886: ldc             16777218
        //   888: invokespecial   org/k.b:(I)V
        //   891: iload           10
        //   893: ifeq            2782
        //   896: goto            900
        //   899: athrow         
        //   900: aload_0        
        //   901: ldc             16777219
        //   903: invokespecial   org/k.b:(I)V
        //   906: aload_0        
        //   907: ldc             16777216
        //   909: invokespecial   org/k.b:(I)V
        //   912: iload           10
        //   914: ifeq            2782
        //   917: goto            921
        //   920: athrow         
        //   921: aload           4
        //   923: getfield        org/n.b:I
        //   926: tableswitch {
        //                6: 997
        //                7: 1033
        //                8: 1012
        //                9: 1048
        //               10: 1069
        //               11: 1097
        //               12: 1153
        //               13: 1153
        //               14: 1153
        //               15: 1153
        //               16: 1153
        //               17: 1153
        //               18: 1153
        //               19: 1125
        //          default: 1153
        //        }
        //   996: athrow         
        //   997: aload_0        
        //   998: ldc             16777217
        //  1000: invokespecial   org/k.b:(I)V
        //  1003: iload           10
        //  1005: ifeq            2782
        //  1008: goto            1012
        //  1011: athrow         
        //  1012: aload_0        
        //  1013: ldc             16777220
        //  1015: invokespecial   org/k.b:(I)V
        //  1018: aload_0        
        //  1019: ldc             16777216
        //  1021: invokespecial   org/k.b:(I)V
        //  1024: iload           10
        //  1026: ifeq            2782
        //  1029: goto            1033
        //  1032: athrow         
        //  1033: aload_0        
        //  1034: ldc             16777218
        //  1036: invokespecial   org/k.b:(I)V
        //  1039: iload           10
        //  1041: ifeq            2782
        //  1044: goto            1048
        //  1047: athrow         
        //  1048: aload_0        
        //  1049: ldc             16777219
        //  1051: invokespecial   org/k.b:(I)V
        //  1054: aload_0        
        //  1055: ldc             16777216
        //  1057: invokespecial   org/k.b:(I)V
        //  1060: iload           10
        //  1062: ifeq            2782
        //  1065: goto            1069
        //  1068: athrow         
        //  1069: aload_0        
        //  1070: ldc             24117248
        //  1072: aload_3        
        //  1073: getstatic       org/k.z:[Ljava/lang/String;
        //  1076: iconst_5       
        //  1077: aaload         
        //  1078: invokestatic    org/f.a:(Ljava/lang/String;)Ljava/lang/String;
        //  1081: invokevirtual   org/g.f:(Ljava/lang/String;)I
        //  1084: ior            
        //  1085: invokespecial   org/k.b:(I)V
        //  1088: iload           10
        //  1090: ifeq            2782
        //  1093: goto            1097
        //  1096: athrow         
        //  1097: aload_0        
        //  1098: ldc             24117248
        //  1100: aload_3        
        //  1101: getstatic       org/k.z:[Ljava/lang/String;
        //  1104: iconst_1       
        //  1105: aaload         
        //  1106: invokestatic    org/f.a:(Ljava/lang/String;)Ljava/lang/String;
        //  1109: invokevirtual   org/g.f:(Ljava/lang/String;)I
        //  1112: ior            
        //  1113: invokespecial   org/k.b:(I)V
        //  1116: iload           10
        //  1118: ifeq            2782
        //  1121: goto            1125
        //  1124: athrow         
        //  1125: aload_0        
        //  1126: ldc             24117248
        //  1128: aload_3        
        //  1129: getstatic       org/k.z:[Ljava/lang/String;
        //  1132: iconst_4       
        //  1133: aaload         
        //  1134: invokestatic    org/f.a:(Ljava/lang/String;)Ljava/lang/String;
        //  1137: invokevirtual   org/g.f:(Ljava/lang/String;)I
        //  1140: ior            
        //  1141: invokespecial   org/k.b:(I)V
        //  1144: iload           10
        //  1146: ifeq            2782
        //  1149: goto            1153
        //  1152: athrow         
        //  1153: aload_0        
        //  1154: ldc             24117248
        //  1156: aload_3        
        //  1157: getstatic       org/k.z:[Ljava/lang/String;
        //  1160: iconst_2       
        //  1161: aaload         
        //  1162: invokestatic    org/f.a:(Ljava/lang/String;)Ljava/lang/String;
        //  1165: invokevirtual   org/g.f:(Ljava/lang/String;)I
        //  1168: ior            
        //  1169: invokespecial   org/k.b:(I)V
        //  1172: iload           10
        //  1174: ifeq            2782
        //  1177: goto            1181
        //  1180: athrow         
        //  1181: aload_0        
        //  1182: aload_0        
        //  1183: iload_2        
        //  1184: invokespecial   org/k.a:(I)I
        //  1187: invokespecial   org/k.b:(I)V
        //  1190: iload           10
        //  1192: ifeq            2782
        //  1195: goto            1199
        //  1198: athrow         
        //  1199: aload_0        
        //  1200: iconst_2       
        //  1201: invokespecial   org/k.c:(I)V
        //  1204: aload_0        
        //  1205: ldc             16777217
        //  1207: invokespecial   org/k.b:(I)V
        //  1210: iload           10
        //  1212: ifeq            2782
        //  1215: goto            1219
        //  1218: athrow         
        //  1219: aload_0        
        //  1220: iconst_2       
        //  1221: invokespecial   org/k.c:(I)V
        //  1224: aload_0        
        //  1225: ldc             16777220
        //  1227: invokespecial   org/k.b:(I)V
        //  1230: aload_0        
        //  1231: ldc             16777216
        //  1233: invokespecial   org/k.b:(I)V
        //  1236: iload           10
        //  1238: ifeq            2782
        //  1241: goto            1245
        //  1244: athrow         
        //  1245: aload_0        
        //  1246: iconst_2       
        //  1247: invokespecial   org/k.c:(I)V
        //  1250: aload_0        
        //  1251: ldc             16777218
        //  1253: invokespecial   org/k.b:(I)V
        //  1256: iload           10
        //  1258: ifeq            2782
        //  1261: goto            1265
        //  1264: athrow         
        //  1265: aload_0        
        //  1266: iconst_2       
        //  1267: invokespecial   org/k.c:(I)V
        //  1270: aload_0        
        //  1271: ldc             16777219
        //  1273: invokespecial   org/k.b:(I)V
        //  1276: aload_0        
        //  1277: ldc             16777216
        //  1279: invokespecial   org/k.b:(I)V
        //  1282: iload           10
        //  1284: ifeq            2782
        //  1287: goto            1291
        //  1290: athrow         
        //  1291: aload_0        
        //  1292: iconst_1       
        //  1293: invokespecial   org/k.c:(I)V
        //  1296: aload_0        
        //  1297: invokespecial   org/k.a:()I
        //  1300: istore          5
        //  1302: aload_0        
        //  1303: ldc             -268435456
        //  1305: iload           5
        //  1307: iadd           
        //  1308: invokespecial   org/k.b:(I)V
        //  1311: iload           10
        //  1313: ifeq            2782
        //  1316: aload_0        
        //  1317: invokespecial   org/k.a:()I
        //  1320: istore          5
        //  1322: aload_0        
        //  1323: iload_2        
        //  1324: iload           5
        //  1326: invokespecial   org/k.a:(II)V
        //  1329: iload_2        
        //  1330: iload           10
        //  1332: ifne            1353
        //  1335: ifle            2782
        //  1338: goto            1342
        //  1341: athrow         
        //  1342: aload_0        
        //  1343: iload_2        
        //  1344: iconst_1       
        //  1345: isub           
        //  1346: invokespecial   org/k.a:(I)I
        //  1349: goto            1353
        //  1352: athrow         
        //  1353: istore          6
        //  1355: iload           10
        //  1357: ifne            1404
        //  1360: iload           6
        //  1362: ldc             16777220
        //  1364: if_icmpeq       1391
        //  1367: goto            1371
        //  1370: athrow         
        //  1371: iload           6
        //  1373: ldc             16777219
        //  1375: iload           10
        //  1377: ifne            1420
        //  1380: goto            1384
        //  1383: athrow         
        //  1384: if_icmpne       1409
        //  1387: goto            1391
        //  1390: athrow         
        //  1391: aload_0        
        //  1392: iload_2        
        //  1393: iconst_1       
        //  1394: isub           
        //  1395: ldc             16777216
        //  1397: invokespecial   org/k.a:(II)V
        //  1400: goto            1404
        //  1403: athrow         
        //  1404: iload           10
        //  1406: ifeq            2782
        //  1409: iload           6
        //  1411: ldc             251658240
        //  1413: iand           
        //  1414: ldc             16777216
        //  1416: goto            1420
        //  1419: athrow         
        //  1420: if_icmpeq       2782
        //  1423: aload_0        
        //  1424: iload_2        
        //  1425: iconst_1       
        //  1426: isub           
        //  1427: iload           6
        //  1429: ldc             8388608
        //  1431: ior            
        //  1432: invokespecial   org/k.a:(II)V
        //  1435: iload           10
        //  1437: ifeq            2782
        //  1440: goto            1444
        //  1443: athrow         
        //  1444: aload_0        
        //  1445: iconst_1       
        //  1446: invokespecial   org/k.c:(I)V
        //  1449: aload_0        
        //  1450: invokespecial   org/k.a:()I
        //  1453: istore          5
        //  1455: aload_0        
        //  1456: iload_2        
        //  1457: iload           5
        //  1459: invokespecial   org/k.a:(II)V
        //  1462: aload_0        
        //  1463: iload_2        
        //  1464: iconst_1       
        //  1465: iadd           
        //  1466: ldc             16777216
        //  1468: invokespecial   org/k.a:(II)V
        //  1471: iload_2        
        //  1472: iload           10
        //  1474: ifne            1495
        //  1477: ifle            2782
        //  1480: goto            1484
        //  1483: athrow         
        //  1484: aload_0        
        //  1485: iload_2        
        //  1486: iconst_1       
        //  1487: isub           
        //  1488: invokespecial   org/k.a:(I)I
        //  1491: goto            1495
        //  1494: athrow         
        //  1495: istore          6
        //  1497: iload           10
        //  1499: ifne            1546
        //  1502: iload           6
        //  1504: ldc             16777220
        //  1506: if_icmpeq       1533
        //  1509: goto            1513
        //  1512: athrow         
        //  1513: iload           6
        //  1515: ldc             16777219
        //  1517: iload           10
        //  1519: ifne            1562
        //  1522: goto            1526
        //  1525: athrow         
        //  1526: if_icmpne       1551
        //  1529: goto            1533
        //  1532: athrow         
        //  1533: aload_0        
        //  1534: iload_2        
        //  1535: iconst_1       
        //  1536: isub           
        //  1537: ldc             16777216
        //  1539: invokespecial   org/k.a:(II)V
        //  1542: goto            1546
        //  1545: athrow         
        //  1546: iload           10
        //  1548: ifeq            2782
        //  1551: iload           6
        //  1553: ldc             251658240
        //  1555: iand           
        //  1556: ldc             16777216
        //  1558: goto            1562
        //  1561: athrow         
        //  1562: if_icmpeq       2782
        //  1565: aload_0        
        //  1566: iload_2        
        //  1567: iconst_1       
        //  1568: isub           
        //  1569: iload           6
        //  1571: ldc             8388608
        //  1573: ior            
        //  1574: invokespecial   org/k.a:(II)V
        //  1577: iload           10
        //  1579: ifeq            2782
        //  1582: goto            1586
        //  1585: athrow         
        //  1586: aload_0        
        //  1587: iconst_3       
        //  1588: invokespecial   org/k.c:(I)V
        //  1591: iload           10
        //  1593: ifeq            2782
        //  1596: goto            1600
        //  1599: athrow         
        //  1600: aload_0        
        //  1601: iconst_4       
        //  1602: invokespecial   org/k.c:(I)V
        //  1605: iload           10
        //  1607: ifeq            2782
        //  1610: goto            1614
        //  1613: athrow         
        //  1614: aload_0        
        //  1615: iconst_1       
        //  1616: invokespecial   org/k.c:(I)V
        //  1619: iload           10
        //  1621: ifeq            2782
        //  1624: goto            1628
        //  1627: athrow         
        //  1628: aload_0        
        //  1629: iconst_2       
        //  1630: invokespecial   org/k.c:(I)V
        //  1633: iload           10
        //  1635: ifeq            2782
        //  1638: goto            1642
        //  1641: athrow         
        //  1642: aload_0        
        //  1643: invokespecial   org/k.a:()I
        //  1646: istore          5
        //  1648: aload_0        
        //  1649: iload           5
        //  1651: invokespecial   org/k.b:(I)V
        //  1654: aload_0        
        //  1655: iload           5
        //  1657: invokespecial   org/k.b:(I)V
        //  1660: iload           10
        //  1662: ifeq            2782
        //  1665: aload_0        
        //  1666: invokespecial   org/k.a:()I
        //  1669: istore          5
        //  1671: aload_0        
        //  1672: invokespecial   org/k.a:()I
        //  1675: istore          6
        //  1677: aload_0        
        //  1678: iload           5
        //  1680: invokespecial   org/k.b:(I)V
        //  1683: aload_0        
        //  1684: iload           6
        //  1686: invokespecial   org/k.b:(I)V
        //  1689: aload_0        
        //  1690: iload           5
        //  1692: invokespecial   org/k.b:(I)V
        //  1695: iload           10
        //  1697: ifeq            2782
        //  1700: aload_0        
        //  1701: invokespecial   org/k.a:()I
        //  1704: istore          5
        //  1706: aload_0        
        //  1707: invokespecial   org/k.a:()I
        //  1710: istore          6
        //  1712: aload_0        
        //  1713: invokespecial   org/k.a:()I
        //  1716: istore          7
        //  1718: aload_0        
        //  1719: iload           5
        //  1721: invokespecial   org/k.b:(I)V
        //  1724: aload_0        
        //  1725: iload           7
        //  1727: invokespecial   org/k.b:(I)V
        //  1730: aload_0        
        //  1731: iload           6
        //  1733: invokespecial   org/k.b:(I)V
        //  1736: aload_0        
        //  1737: iload           5
        //  1739: invokespecial   org/k.b:(I)V
        //  1742: iload           10
        //  1744: ifeq            2782
        //  1747: aload_0        
        //  1748: invokespecial   org/k.a:()I
        //  1751: istore          5
        //  1753: aload_0        
        //  1754: invokespecial   org/k.a:()I
        //  1757: istore          6
        //  1759: aload_0        
        //  1760: iload           6
        //  1762: invokespecial   org/k.b:(I)V
        //  1765: aload_0        
        //  1766: iload           5
        //  1768: invokespecial   org/k.b:(I)V
        //  1771: aload_0        
        //  1772: iload           6
        //  1774: invokespecial   org/k.b:(I)V
        //  1777: aload_0        
        //  1778: iload           5
        //  1780: invokespecial   org/k.b:(I)V
        //  1783: iload           10
        //  1785: ifeq            2782
        //  1788: aload_0        
        //  1789: invokespecial   org/k.a:()I
        //  1792: istore          5
        //  1794: aload_0        
        //  1795: invokespecial   org/k.a:()I
        //  1798: istore          6
        //  1800: aload_0        
        //  1801: invokespecial   org/k.a:()I
        //  1804: istore          7
        //  1806: aload_0        
        //  1807: iload           6
        //  1809: invokespecial   org/k.b:(I)V
        //  1812: aload_0        
        //  1813: iload           5
        //  1815: invokespecial   org/k.b:(I)V
        //  1818: aload_0        
        //  1819: iload           7
        //  1821: invokespecial   org/k.b:(I)V
        //  1824: aload_0        
        //  1825: iload           6
        //  1827: invokespecial   org/k.b:(I)V
        //  1830: aload_0        
        //  1831: iload           5
        //  1833: invokespecial   org/k.b:(I)V
        //  1836: iload           10
        //  1838: ifeq            2782
        //  1841: aload_0        
        //  1842: invokespecial   org/k.a:()I
        //  1845: istore          5
        //  1847: aload_0        
        //  1848: invokespecial   org/k.a:()I
        //  1851: istore          6
        //  1853: aload_0        
        //  1854: invokespecial   org/k.a:()I
        //  1857: istore          7
        //  1859: aload_0        
        //  1860: invokespecial   org/k.a:()I
        //  1863: istore          8
        //  1865: aload_0        
        //  1866: iload           6
        //  1868: invokespecial   org/k.b:(I)V
        //  1871: aload_0        
        //  1872: iload           5
        //  1874: invokespecial   org/k.b:(I)V
        //  1877: aload_0        
        //  1878: iload           8
        //  1880: invokespecial   org/k.b:(I)V
        //  1883: aload_0        
        //  1884: iload           7
        //  1886: invokespecial   org/k.b:(I)V
        //  1889: aload_0        
        //  1890: iload           6
        //  1892: invokespecial   org/k.b:(I)V
        //  1895: aload_0        
        //  1896: iload           5
        //  1898: invokespecial   org/k.b:(I)V
        //  1901: iload           10
        //  1903: ifeq            2782
        //  1906: aload_0        
        //  1907: invokespecial   org/k.a:()I
        //  1910: istore          5
        //  1912: aload_0        
        //  1913: invokespecial   org/k.a:()I
        //  1916: istore          6
        //  1918: aload_0        
        //  1919: iload           5
        //  1921: invokespecial   org/k.b:(I)V
        //  1924: aload_0        
        //  1925: iload           6
        //  1927: invokespecial   org/k.b:(I)V
        //  1930: iload           10
        //  1932: ifeq            2782
        //  1935: aload_0        
        //  1936: iconst_2       
        //  1937: invokespecial   org/k.c:(I)V
        //  1940: aload_0        
        //  1941: ldc             16777217
        //  1943: invokespecial   org/k.b:(I)V
        //  1946: iload           10
        //  1948: ifeq            2782
        //  1951: goto            1955
        //  1954: athrow         
        //  1955: aload_0        
        //  1956: iconst_4       
        //  1957: invokespecial   org/k.c:(I)V
        //  1960: aload_0        
        //  1961: ldc             16777220
        //  1963: invokespecial   org/k.b:(I)V
        //  1966: aload_0        
        //  1967: ldc             16777216
        //  1969: invokespecial   org/k.b:(I)V
        //  1972: iload           10
        //  1974: ifeq            2782
        //  1977: goto            1981
        //  1980: athrow         
        //  1981: aload_0        
        //  1982: iconst_2       
        //  1983: invokespecial   org/k.c:(I)V
        //  1986: aload_0        
        //  1987: ldc             16777218
        //  1989: invokespecial   org/k.b:(I)V
        //  1992: iload           10
        //  1994: ifeq            2782
        //  1997: goto            2001
        //  2000: athrow         
        //  2001: aload_0        
        //  2002: iconst_4       
        //  2003: invokespecial   org/k.c:(I)V
        //  2006: aload_0        
        //  2007: ldc             16777219
        //  2009: invokespecial   org/k.b:(I)V
        //  2012: aload_0        
        //  2013: ldc             16777216
        //  2015: invokespecial   org/k.b:(I)V
        //  2018: iload           10
        //  2020: ifeq            2782
        //  2023: goto            2027
        //  2026: athrow         
        //  2027: aload_0        
        //  2028: iconst_3       
        //  2029: invokespecial   org/k.c:(I)V
        //  2032: aload_0        
        //  2033: ldc             16777220
        //  2035: invokespecial   org/k.b:(I)V
        //  2038: aload_0        
        //  2039: ldc             16777216
        //  2041: invokespecial   org/k.b:(I)V
        //  2044: iload           10
        //  2046: ifeq            2782
        //  2049: goto            2053
        //  2052: athrow         
        //  2053: aload_0        
        //  2054: iload_2        
        //  2055: ldc             16777217
        //  2057: invokespecial   org/k.a:(II)V
        //  2060: iload           10
        //  2062: ifeq            2782
        //  2065: goto            2069
        //  2068: athrow         
        //  2069: aload_0        
        //  2070: iconst_1       
        //  2071: invokespecial   org/k.c:(I)V
        //  2074: aload_0        
        //  2075: ldc             16777220
        //  2077: invokespecial   org/k.b:(I)V
        //  2080: aload_0        
        //  2081: ldc             16777216
        //  2083: invokespecial   org/k.b:(I)V
        //  2086: iload           10
        //  2088: ifeq            2782
        //  2091: goto            2095
        //  2094: athrow         
        //  2095: aload_0        
        //  2096: iconst_1       
        //  2097: invokespecial   org/k.c:(I)V
        //  2100: aload_0        
        //  2101: ldc             16777218
        //  2103: invokespecial   org/k.b:(I)V
        //  2106: iload           10
        //  2108: ifeq            2782
        //  2111: goto            2115
        //  2114: athrow         
        //  2115: aload_0        
        //  2116: iconst_1       
        //  2117: invokespecial   org/k.c:(I)V
        //  2120: aload_0        
        //  2121: ldc             16777219
        //  2123: invokespecial   org/k.b:(I)V
        //  2126: aload_0        
        //  2127: ldc             16777216
        //  2129: invokespecial   org/k.b:(I)V
        //  2132: iload           10
        //  2134: ifeq            2782
        //  2137: goto            2141
        //  2140: athrow         
        //  2141: aload_0        
        //  2142: iconst_1       
        //  2143: invokespecial   org/k.c:(I)V
        //  2146: aload_0        
        //  2147: ldc             16777217
        //  2149: invokespecial   org/k.b:(I)V
        //  2152: iload           10
        //  2154: ifeq            2782
        //  2157: goto            2161
        //  2160: athrow         
        //  2161: aload_0        
        //  2162: iconst_4       
        //  2163: invokespecial   org/k.c:(I)V
        //  2166: aload_0        
        //  2167: ldc             16777217
        //  2169: invokespecial   org/k.b:(I)V
        //  2172: iload           10
        //  2174: ifeq            2782
        //  2177: goto            2181
        //  2180: athrow         
        //  2181: new             Ljava/lang/RuntimeException;
        //  2184: dup            
        //  2185: getstatic       org/k.z:[Ljava/lang/String;
        //  2188: iconst_3       
        //  2189: aaload         
        //  2190: invokestatic    org/f.a:(Ljava/lang/String;)Ljava/lang/String;
        //  2193: invokespecial   java/lang/RuntimeException.<init>:(Ljava/lang/String;)V
        //  2196: athrow         
        //  2197: athrow         
        //  2198: aload_0        
        //  2199: aload_3        
        //  2200: aload           4
        //  2202: getfield        org/n.g:Ljava/lang/String;
        //  2205: invokespecial   org/k.a:(Lorg/g;Ljava/lang/String;)V
        //  2208: iload           10
        //  2210: ifeq            2782
        //  2213: aload_0        
        //  2214: aload           4
        //  2216: getfield        org/n.g:Ljava/lang/String;
        //  2219: invokespecial   org/k.a:(Ljava/lang/String;)V
        //  2222: iload           10
        //  2224: ifeq            2782
        //  2227: goto            2231
        //  2230: athrow         
        //  2231: aload_0        
        //  2232: iconst_1       
        //  2233: invokespecial   org/k.c:(I)V
        //  2236: aload_0        
        //  2237: aload_3        
        //  2238: aload           4
        //  2240: getfield        org/n.g:Ljava/lang/String;
        //  2243: invokespecial   org/k.a:(Lorg/g;Ljava/lang/String;)V
        //  2246: iload           10
        //  2248: ifeq            2782
        //  2251: goto            2255
        //  2254: athrow         
        //  2255: aload_0        
        //  2256: aload           4
        //  2258: getfield        org/n.g:Ljava/lang/String;
        //  2261: invokespecial   org/k.a:(Ljava/lang/String;)V
        //  2264: aload_0        
        //  2265: invokespecial   org/k.a:()I
        //  2268: pop            
        //  2269: iload           10
        //  2271: ifeq            2782
        //  2274: goto            2278
        //  2277: athrow         
        //  2278: aload_0        
        //  2279: aload           4
        //  2281: getfield        org/n.g:Ljava/lang/String;
        //  2284: invokespecial   org/k.a:(Ljava/lang/String;)V
        //  2287: iload           10
        //  2289: ifne            2367
        //  2292: goto            2296
        //  2295: athrow         
        //  2296: iload_1        
        //  2297: sipush          184
        //  2300: if_icmpeq       2357
        //  2303: goto            2307
        //  2306: athrow         
        //  2307: aload_0        
        //  2308: invokespecial   org/k.a:()I
        //  2311: istore          5
        //  2313: iload           10
        //  2315: ifne            2367
        //  2318: iload_1        
        //  2319: sipush          183
        //  2322: if_icmpne       2357
        //  2325: goto            2329
        //  2328: athrow         
        //  2329: aload           4
        //  2331: getfield        org/n.f:Ljava/lang/String;
        //  2334: iconst_0       
        //  2335: invokevirtual   java/lang/String.charAt:(I)C
        //  2338: bipush          60
        //  2340: if_icmpne       2357
        //  2343: goto            2347
        //  2346: athrow         
        //  2347: aload_0        
        //  2348: iload           5
        //  2350: invokespecial   org/k.d:(I)V
        //  2353: goto            2357
        //  2356: athrow         
        //  2357: aload_0        
        //  2358: aload_3        
        //  2359: aload           4
        //  2361: getfield        org/n.g:Ljava/lang/String;
        //  2364: invokespecial   org/k.a:(Lorg/g;Ljava/lang/String;)V
        //  2367: iload           10
        //  2369: ifeq            2782
        //  2372: aload_0        
        //  2373: aload           4
        //  2375: getfield        org/n.f:Ljava/lang/String;
        //  2378: invokespecial   org/k.a:(Ljava/lang/String;)V
        //  2381: aload_0        
        //  2382: aload_3        
        //  2383: aload           4
        //  2385: getfield        org/n.f:Ljava/lang/String;
        //  2388: invokespecial   org/k.a:(Lorg/g;Ljava/lang/String;)V
        //  2391: iload           10
        //  2393: ifeq            2782
        //  2396: goto            2400
        //  2399: athrow         
        //  2400: aload_0        
        //  2401: ldc             25165824
        //  2403: aload_3        
        //  2404: aload           4
        //  2406: getfield        org/n.e:Ljava/lang/String;
        //  2409: iload_2        
        //  2410: invokevirtual   org/g.a:(Ljava/lang/String;I)I
        //  2413: ior            
        //  2414: invokespecial   org/k.b:(I)V
        //  2417: iload           10
        //  2419: ifeq            2782
        //  2422: goto            2426
        //  2425: athrow         
        //  2426: aload_0        
        //  2427: invokespecial   org/k.a:()I
        //  2430: pop            
        //  2431: iload           10
        //  2433: ifne            2600
        //  2436: goto            2440
        //  2439: athrow         
        //  2440: iload_2        
        //  2441: tableswitch {
        //                8: 2485
        //                9: 2500
        //               10: 2560
        //               11: 2575
        //               12: 2515
        //               13: 2530
        //               14: 2545
        //          default: 2590
        //        }
        //  2484: athrow         
        //  2485: aload_0        
        //  2486: ldc             285212681
        //  2488: invokespecial   org/k.b:(I)V
        //  2491: iload           10
        //  2493: ifeq            2782
        //  2496: goto            2500
        //  2499: athrow         
        //  2500: aload_0        
        //  2501: ldc             285212683
        //  2503: invokespecial   org/k.b:(I)V
        //  2506: iload           10
        //  2508: ifeq            2782
        //  2511: goto            2515
        //  2514: athrow         
        //  2515: aload_0        
        //  2516: ldc             285212682
        //  2518: invokespecial   org/k.b:(I)V
        //  2521: iload           10
        //  2523: ifeq            2782
        //  2526: goto            2530
        //  2529: athrow         
        //  2530: aload_0        
        //  2531: ldc             285212684
        //  2533: invokespecial   org/k.b:(I)V
        //  2536: iload           10
        //  2538: ifeq            2782
        //  2541: goto            2545
        //  2544: athrow         
        //  2545: aload_0        
        //  2546: ldc             285212673
        //  2548: invokespecial   org/k.b:(I)V
        //  2551: iload           10
        //  2553: ifeq            2782
        //  2556: goto            2560
        //  2559: athrow         
        //  2560: aload_0        
        //  2561: ldc             285212674
        //  2563: invokespecial   org/k.b:(I)V
        //  2566: iload           10
        //  2568: ifeq            2782
        //  2571: goto            2575
        //  2574: athrow         
        //  2575: aload_0        
        //  2576: ldc             285212675
        //  2578: invokespecial   org/k.b:(I)V
        //  2581: iload           10
        //  2583: ifeq            2782
        //  2586: goto            2590
        //  2589: athrow         
        //  2590: aload_0        
        //  2591: ldc             285212676
        //  2593: invokespecial   org/k.b:(I)V
        //  2596: goto            2600
        //  2599: athrow         
        //  2600: iload           10
        //  2602: ifeq            2782
        //  2605: aload           4
        //  2607: getfield        org/n.e:Ljava/lang/String;
        //  2610: astore          9
        //  2612: aload_0        
        //  2613: invokespecial   org/k.a:()I
        //  2616: pop            
        //  2617: iload           10
        //  2619: ifne            2688
        //  2622: aload           9
        //  2624: iconst_0       
        //  2625: invokevirtual   java/lang/String.charAt:(I)C
        //  2628: bipush          91
        //  2630: if_icmpne       2671
        //  2633: goto            2637
        //  2636: athrow         
        //  2637: aload_0        
        //  2638: aload_3        
        //  2639: new             Ljava/lang/StringBuilder;
        //  2642: dup            
        //  2643: invokespecial   java/lang/StringBuilder.<init>:()V
        //  2646: bipush          91
        //  2648: invokevirtual   java/lang/StringBuilder.append:(C)Ljava/lang/StringBuilder;
        //  2651: aload           9
        //  2653: invokevirtual   java/lang/StringBuilder.append:(Ljava/lang/String;)Ljava/lang/StringBuilder;
        //  2656: invokevirtual   java/lang/StringBuilder.toString:()Ljava/lang/String;
        //  2659: invokespecial   org/k.a:(Lorg/g;Ljava/lang/String;)V
        //  2662: iload           10
        //  2664: ifeq            2782
        //  2667: goto            2671
        //  2670: athrow         
        //  2671: aload_0        
        //  2672: ldc             292552704
        //  2674: aload_3        
        //  2675: aload           9
        //  2677: invokevirtual   org/g.f:(Ljava/lang/String;)I
        //  2680: ior            
        //  2681: invokespecial   org/k.b:(I)V
        //  2684: goto            2688
        //  2687: athrow         
        //  2688: iload           10
        //  2690: ifeq            2782
        //  2693: aload           4
        //  2695: getfield        org/n.e:Ljava/lang/String;
        //  2698: astore          9
        //  2700: aload_0        
        //  2701: invokespecial   org/k.a:()I
        //  2704: pop            
        //  2705: iload           10
        //  2707: ifne            2758
        //  2710: aload           9
        //  2712: iconst_0       
        //  2713: invokevirtual   java/lang/String.charAt:(I)C
        //  2716: bipush          91
        //  2718: if_icmpne       2741
        //  2721: goto            2725
        //  2724: athrow         
        //  2725: aload_0        
        //  2726: aload_3        
        //  2727: aload           9
        //  2729: invokespecial   org/k.a:(Lorg/g;Ljava/lang/String;)V
        //  2732: iload           10
        //  2734: ifeq            2782
        //  2737: goto            2741
        //  2740: athrow         
        //  2741: aload_0        
        //  2742: ldc             24117248
        //  2744: aload_3        
        //  2745: aload           9
        //  2747: invokevirtual   org/g.f:(Ljava/lang/String;)I
        //  2750: ior            
        //  2751: invokespecial   org/k.b:(I)V
        //  2754: goto            2758
        //  2757: athrow         
        //  2758: iload           10
        //  2760: ifeq            2782
        //  2763: aload_0        
        //  2764: iload_2        
        //  2765: invokespecial   org/k.c:(I)V
        //  2768: goto            2772
        //  2771: athrow         
        //  2772: aload_0        
        //  2773: aload_3        
        //  2774: aload           4
        //  2776: getfield        org/n.e:Ljava/lang/String;
        //  2779: invokespecial   org/k.a:(Lorg/g;Ljava/lang/String;)V
        //  2782: return         
        //    StackMapTable: 00 B1 FF 03 38 00 0B 07 00 51 01 01 07 00 82 07 00 8B 00 00 00 00 00 01 00 01 07 00 35 00 47 07 00 35 00 4D 07 00 35 00 4D 07 00 35 00 53 07 00 35 00 4D 07 00 35 00 53 07 00 35 00 F7 00 4A 07 00 35 00 4D 07 00 35 00 53 07 00 35 00 4D 07 00 35 00 53 07 00 35 00 5A 07 00 35 00 5A 07 00 35 00 5A 07 00 35 00 5A 07 00 35 00 50 07 00 35 00 52 07 00 35 00 58 07 00 35 00 52 07 00 35 00 58 07 00 35 00 18 FF 00 18 00 0B 07 00 51 01 01 07 00 82 07 00 8B 01 00 00 00 00 01 00 01 07 00 35 00 49 07 00 35 40 01 FF 00 10 00 0B 07 00 51 01 01 07 00 82 07 00 8B 01 01 00 00 00 01 00 01 07 00 35 00 4B 07 00 35 FF 00 00 00 0B 07 00 51 01 01 07 00 82 07 00 8B 01 01 00 00 00 01 00 02 01 01 45 07 00 35 00 4B 07 00 35 00 04 49 07 00 35 FF 00 00 00 0B 07 00 51 01 01 07 00 82 07 00 8B 01 01 00 00 00 01 00 02 01 01 56 07 00 35 FF 00 00 00 0B 07 00 51 01 01 07 00 82 07 00 8B 00 00 00 00 00 01 00 00 FF 00 26 00 0B 07 00 51 01 01 07 00 82 07 00 8B 01 00 00 00 00 01 00 01 07 00 35 00 49 07 00 35 40 01 FF 00 10 00 0B 07 00 51 01 01 07 00 82 07 00 8B 01 01 00 00 00 01 00 01 07 00 35 00 4B 07 00 35 FF 00 00 00 0B 07 00 51 01 01 07 00 82 07 00 8B 01 01 00 00 00 01 00 02 01 01 45 07 00 35 00 4B 07 00 35 00 04 49 07 00 35 FF 00 00 00 0B 07 00 51 01 01 07 00 82 07 00 8B 01 01 00 00 00 01 00 02 01 01 56 07 00 35 FF 00 00 00 0B 07 00 51 01 01 07 00 82 07 00 8B 00 00 00 00 00 01 00 00 4C 07 00 35 00 4C 07 00 35 00 4C 07 00 35 00 4C 07 00 35 00 16 22 2E 28 34 FB 00 40 1C 52 07 00 35 00 58 07 00 35 00 52 07 00 35 00 58 07 00 35 00 58 07 00 35 00 4E 07 00 35 00 58 07 00 35 00 52 07 00 35 00 58 07 00 35 00 52 07 00 35 00 52 07 00 35 00 4F 07 00 35 00 0E 50 07 00 35 00 56 07 00 35 00 55 07 00 35 00 50 07 00 35 00 49 07 00 35 00 FF 00 14 00 0B 07 00 51 01 01 07 00 82 07 00 8B 01 00 00 00 00 01 00 01 07 00 35 00 50 07 00 35 00 48 07 00 35 FF 00 00 00 0B 07 00 51 01 01 07 00 82 07 00 8B 00 00 00 00 00 01 00 00 09 04 5A 07 00 35 00 58 07 00 35 00 4C 07 00 35 00 6B 07 00 35 00 4D 07 00 35 00 4D 07 00 35 00 4D 07 00 35 00 4D 07 00 35 00 4D 07 00 35 00 4D 07 00 35 00 4D 07 00 35 00 48 07 00 35 00 04 FF 00 1E 00 0B 07 00 51 01 01 07 00 82 07 00 8B 00 00 00 00 07 00 7D 01 00 01 07 00 35 00 60 07 00 35 00 4F 07 00 35 00 FF 00 04 00 0B 07 00 51 01 01 07 00 82 07 00 8B 00 00 00 00 00 01 00 00 FF 00 1E 00 0B 07 00 51 01 01 07 00 82 07 00 8B 00 00 00 00 07 00 7D 01 00 01 07 00 35 00 4E 07 00 35 00 4F 07 00 35 00 FF 00 04 00 0B 07 00 51 01 01 07 00 82 07 00 8B 00 00 00 00 00 01 00 00 47 07 00 35 00 09
        //    Exceptions:
        //  Try           Handler
        //  Start  End    Start  End    Type                        
        //  -----  -----  -----  -----  ----------------------------
        //  2758   2768   2771   2772   Ljava/lang/RuntimeException;
        //  2725   2754   2757   2758   Ljava/lang/RuntimeException;
        //  2710   2737   2740   2741   Ljava/lang/RuntimeException;
        //  2700   2721   2724   2725   Ljava/lang/RuntimeException;
        //  2637   2684   2687   2688   Ljava/lang/RuntimeException;
        //  2622   2667   2670   2671   Ljava/lang/RuntimeException;
        //  2612   2633   2636   2637   Ljava/lang/RuntimeException;
        //  2575   2596   2599   2600   Ljava/lang/RuntimeException;
        //  2560   2586   2589   2590   Ljava/lang/RuntimeException;
        //  2545   2571   2574   2575   Ljava/lang/RuntimeException;
        //  2530   2556   2559   2560   Ljava/lang/RuntimeException;
        //  2515   2541   2544   2545   Ljava/lang/RuntimeException;
        //  2500   2526   2529   2530   Ljava/lang/RuntimeException;
        //  2485   2511   2514   2515   Ljava/lang/RuntimeException;
        //  2440   2496   2499   2500   Ljava/lang/RuntimeException;
        //  2426   2484   2484   2485   Ljava/lang/RuntimeException;
        //  2400   2436   2439   2440   Ljava/lang/RuntimeException;
        //  2372   2422   2425   2426   Ljava/lang/RuntimeException;
        //  2367   2396   2399   2400   Ljava/lang/RuntimeException;
        //  2329   2353   2356   2357   Ljava/lang/RuntimeException;
        //  2318   2343   2346   2347   Ljava/lang/RuntimeException;
        //  2313   2325   2328   2329   Ljava/lang/RuntimeException;
        //  2278   2303   2306   2307   Ljava/lang/RuntimeException;
        //  2255   2292   2295   2296   Ljava/lang/RuntimeException;
        //  2231   2274   2277   2278   Ljava/lang/RuntimeException;
        //  2213   2251   2254   2255   Ljava/lang/RuntimeException;
        //  2198   2227   2230   2231   Ljava/lang/RuntimeException;
        //  2161   2197   2197   2198   Ljava/lang/RuntimeException;
        //  2141   2177   2180   2181   Ljava/lang/RuntimeException;
        //  2115   2157   2160   2161   Ljava/lang/RuntimeException;
        //  2095   2137   2140   2141   Ljava/lang/RuntimeException;
        //  2069   2111   2114   2115   Ljava/lang/RuntimeException;
        //  2053   2091   2094   2095   Ljava/lang/RuntimeException;
        //  2027   2065   2068   2069   Ljava/lang/RuntimeException;
        //  2001   2049   2052   2053   Ljava/lang/RuntimeException;
        //  1981   2023   2026   2027   Ljava/lang/RuntimeException;
        //  1955   1997   2000   2001   Ljava/lang/RuntimeException;
        //  1935   1977   1980   1981   Ljava/lang/RuntimeException;
        //  1918   1951   1954   1955   Ljava/lang/RuntimeException;
        //  1614   1638   1641   1642   Ljava/lang/RuntimeException;
        //  1600   1624   1627   1628   Ljava/lang/RuntimeException;
        //  1586   1610   1613   1614   Ljava/lang/RuntimeException;
        //  1565   1596   1599   1600   Ljava/lang/RuntimeException;
        //  1562   1582   1585   1586   Ljava/lang/RuntimeException;
        //  1546   1558   1561   1562   Ljava/lang/RuntimeException;
        //  1526   1542   1545   1546   Ljava/lang/RuntimeException;
        //  1513   1529   1532   1533   Ljava/lang/RuntimeException;
        //  1502   1522   1525   1526   Ljava/lang/RuntimeException;
        //  1497   1509   1512   1513   Ljava/lang/RuntimeException;
        //  1477   1491   1494   1495   Ljava/lang/RuntimeException;
        //  1455   1480   1483   1484   Ljava/lang/RuntimeException;
        //  1420   1440   1443   1444   Ljava/lang/RuntimeException;
        //  1404   1416   1419   1420   Ljava/lang/RuntimeException;
        //  1384   1400   1403   1404   Ljava/lang/RuntimeException;
        //  1371   1387   1390   1391   Ljava/lang/RuntimeException;
        //  1360   1380   1383   1384   Ljava/lang/RuntimeException;
        //  1355   1367   1370   1371   Ljava/lang/RuntimeException;
        //  1335   1349   1352   1353   Ljava/lang/RuntimeException;
        //  1322   1338   1341   1342   Ljava/lang/RuntimeException;
        //  1245   1287   1290   1291   Ljava/lang/RuntimeException;
        //  1219   1261   1264   1265   Ljava/lang/RuntimeException;
        //  1199   1241   1244   1245   Ljava/lang/RuntimeException;
        //  1181   1215   1218   1219   Ljava/lang/RuntimeException;
        //  1153   1195   1198   1199   Ljava/lang/RuntimeException;
        //  1125   1177   1180   1181   Ljava/lang/RuntimeException;
        //  1097   1149   1152   1153   Ljava/lang/RuntimeException;
        //  1069   1121   1124   1125   Ljava/lang/RuntimeException;
        //  1048   1093   1096   1097   Ljava/lang/RuntimeException;
        //  1033   1065   1068   1069   Ljava/lang/RuntimeException;
        //  1012   1044   1047   1048   Ljava/lang/RuntimeException;
        //  997    1029   1032   1033   Ljava/lang/RuntimeException;
        //  921    1008   1011   1012   Ljava/lang/RuntimeException;
        //  900    996    996    997    Ljava/lang/RuntimeException;
        //  885    917    920    921    Ljava/lang/RuntimeException;
        //  864    896    899    900    Ljava/lang/RuntimeException;
        //  849    881    884    885    Ljava/lang/RuntimeException;
        //  834    860    863    864    Ljava/lang/RuntimeException;
        //  825    845    848    849    Ljava/lang/RuntimeException;
        //  10     830    833    834    Ljava/lang/RuntimeException;
        //  5      824    824    825    Ljava/lang/RuntimeException;
        // 
        // The error that occurred was:
        // 
        // java.lang.IllegalStateException: Expression is linked from several locations: Label_0825:
        //     at com.strobel.decompiler.ast.Error.expressionLinkedFromMultipleLocations(Error.java:27)
        //     at com.strobel.decompiler.ast.AstOptimizer.mergeDisparateObjectInitializations(AstOptimizer.java:2596)
        //     at com.strobel.decompiler.ast.AstOptimizer.optimize(AstOptimizer.java:235)
        //     at com.strobel.decompiler.ast.AstOptimizer.optimize(AstOptimizer.java:42)
        //     at com.strobel.decompiler.languages.java.ast.AstMethodBodyBuilder.createMethodBody(AstMethodBodyBuilder.java:214)
        //     at com.strobel.decompiler.languages.java.ast.AstMethodBodyBuilder.createMethodBody(AstMethodBodyBuilder.java:99)
        //     at com.strobel.decompiler.languages.java.ast.AstBuilder.createMethodBody(AstBuilder.java:782)
        //     at com.strobel.decompiler.languages.java.ast.AstBuilder.createMethod(AstBuilder.java:675)
        //     at com.strobel.decompiler.languages.java.ast.AstBuilder.addTypeMembers(AstBuilder.java:552)
        //     at com.strobel.decompiler.languages.java.ast.AstBuilder.createTypeCore(AstBuilder.java:519)
        //     at com.strobel.decompiler.languages.java.ast.AstBuilder.createTypeNoCache(AstBuilder.java:161)
        //     at com.strobel.decompiler.languages.java.ast.AstBuilder.createType(AstBuilder.java:150)
        //     at com.strobel.decompiler.languages.java.ast.AstBuilder.addType(AstBuilder.java:125)
        //     at com.strobel.decompiler.languages.java.JavaLanguage.buildAst(JavaLanguage.java:71)
        //     at com.strobel.decompiler.languages.java.JavaLanguage.decompileType(JavaLanguage.java:59)
        //     at com.strobel.decompiler.DecompilerDriver.decompileType(DecompilerDriver.java:330)
        //     at com.strobel.decompiler.DecompilerDriver.decompileJar(DecompilerDriver.java:251)
        //     at com.strobel.decompiler.DecompilerDriver.main(DecompilerDriver.java:126)
        // 
        throw new IllegalStateException("An error occurred while decompiling this method.");
    }
    
    boolean a(final g p0, final k p1, final int p2) {
        // 
        // This method could not be decompiled.
        // 
        // Original Bytecode:
        // 
        //     5: iconst_0       
        //     6: istore          4
        //     8: aload_0        
        //     9: getfield        org/k.c:[I
        //    12: arraylength    
        //    13: istore          10
        //    15: aload_0        
        //    16: getfield        org/k.d:[I
        //    19: arraylength    
        //    20: istore          11
        //    22: aload_2        
        //    23: iload           13
        //    25: ifne            43
        //    28: getfield        org/k.c:[I
        //    31: ifnonnull       53
        //    34: goto            38
        //    37: athrow         
        //    38: aload_2        
        //    39: goto            43
        //    42: athrow         
        //    43: iload           10
        //    45: newarray        I
        //    47: putfield        org/k.c:[I
        //    50: iconst_1       
        //    51: istore          4
        //    53: iconst_0       
        //    54: istore          5
        //    56: iload           5
        //    58: iload           10
        //    60: if_icmpge       386
        //    63: aload_0        
        //    64: getfield        org/k.e:[I
        //    67: iload           13
        //    69: ifne            504
        //    72: iload           13
        //    74: ifne            327
        //    77: goto            81
        //    80: athrow         
        //    81: ifnull          319
        //    84: goto            88
        //    87: athrow         
        //    88: iload           5
        //    90: iload           13
        //    92: ifne            330
        //    95: goto            99
        //    98: athrow         
        //    99: aload_0        
        //   100: getfield        org/k.e:[I
        //   103: arraylength    
        //   104: if_icmpge       319
        //   107: goto            111
        //   110: athrow         
        //   111: aload_0        
        //   112: getfield        org/k.e:[I
        //   115: iload           5
        //   117: iaload         
        //   118: istore          6
        //   120: iload           6
        //   122: iload           13
        //   124: ifne            157
        //   127: ifne            148
        //   130: goto            134
        //   133: athrow         
        //   134: aload_0        
        //   135: getfield        org/k.c:[I
        //   138: iload           5
        //   140: iaload         
        //   141: istore          9
        //   143: iload           13
        //   145: ifeq            332
        //   148: iload           6
        //   150: ldc             -268435456
        //   152: iand           
        //   153: goto            157
        //   156: athrow         
        //   157: istore          7
        //   159: iload           6
        //   161: ldc             251658240
        //   163: iand           
        //   164: istore          8
        //   166: iload           8
        //   168: ldc             16777216
        //   170: iload           13
        //   172: ifne            199
        //   175: if_icmpne       191
        //   178: goto            182
        //   181: athrow         
        //   182: iload           6
        //   184: istore          9
        //   186: iload           13
        //   188: ifeq            332
        //   191: iload           8
        //   193: ldc             33554432
        //   195: goto            199
        //   198: athrow         
        //   199: iload           13
        //   201: ifne            250
        //   204: if_icmpne       231
        //   207: goto            211
        //   210: athrow         
        //   211: iload           7
        //   213: aload_0        
        //   214: getfield        org/k.c:[I
        //   217: iload           6
        //   219: ldc             8388607
        //   221: iand           
        //   222: iaload         
        //   223: iadd           
        //   224: istore          9
        //   226: iload           13
        //   228: ifeq            253
        //   231: iload           7
        //   233: aload_0        
        //   234: getfield        org/k.d:[I
        //   237: iload           11
        //   239: iload           6
        //   241: ldc             8388607
        //   243: iand           
        //   244: isub           
        //   245: iaload         
        //   246: goto            250
        //   249: athrow         
        //   250: iadd           
        //   251: istore          9
        //   253: iload           6
        //   255: ldc             8388608
        //   257: iand           
        //   258: iload           13
        //   260: ifne            272
        //   263: ifeq            332
        //   266: goto            270
        //   269: athrow         
        //   270: iload           9
        //   272: iload           13
        //   274: ifne            312
        //   277: ldc             16777220
        //   279: if_icmpeq       306
        //   282: goto            286
        //   285: athrow         
        //   286: iload           9
        //   288: iload           13
        //   290: ifne            312
        //   293: goto            297
        //   296: athrow         
        //   297: ldc             16777219
        //   299: if_icmpne       332
        //   302: goto            306
        //   305: athrow         
        //   306: ldc             16777216
        //   308: goto            312
        //   311: athrow         
        //   312: istore          9
        //   314: iload           13
        //   316: ifeq            332
        //   319: aload_0        
        //   320: getfield        org/k.c:[I
        //   323: goto            327
        //   326: athrow         
        //   327: iload           5
        //   329: iaload         
        //   330: istore          9
        //   332: aload_0        
        //   333: iload           13
        //   335: ifne            353
        //   338: getfield        org/k.i:[I
        //   341: ifnull          361
        //   344: goto            348
        //   347: athrow         
        //   348: aload_0        
        //   349: goto            353
        //   352: athrow         
        //   353: aload_1        
        //   354: iload           9
        //   356: invokespecial   org/k.a:(Lorg/g;I)I
        //   359: istore          9
        //   361: iload           4
        //   363: aload_1        
        //   364: iload           9
        //   366: aload_2        
        //   367: getfield        org/k.c:[I
        //   370: iload           5
        //   372: invokestatic    org/k.a:(Lorg/g;I[II)Z
        //   375: ior            
        //   376: istore          4
        //   378: iinc            5, 1
        //   381: iload           13
        //   383: ifeq            56
        //   386: iload_3        
        //   387: iload           13
        //   389: ifne            513
        //   392: ifle            500
        //   395: goto            399
        //   398: athrow         
        //   399: iconst_0       
        //   400: istore          5
        //   402: iload           5
        //   404: iload           10
        //   406: if_icmpge       452
        //   409: aload_0        
        //   410: getfield        org/k.c:[I
        //   413: iload           5
        //   415: iaload         
        //   416: istore          9
        //   418: iload           4
        //   420: aload_1        
        //   421: iload           9
        //   423: aload_2        
        //   424: getfield        org/k.c:[I
        //   427: iload           5
        //   429: invokestatic    org/k.a:(Lorg/g;I[II)Z
        //   432: ior            
        //   433: istore          4
        //   435: iinc            5, 1
        //   438: iload           13
        //   440: ifne            497
        //   443: iload           13
        //   445: ifeq            402
        //   448: goto            452
        //   451: athrow         
        //   452: aload_2        
        //   453: iload           13
        //   455: ifne            473
        //   458: getfield        org/k.d:[I
        //   461: ifnonnull       482
        //   464: goto            468
        //   467: athrow         
        //   468: aload_2        
        //   469: goto            473
        //   472: athrow         
        //   473: iconst_1       
        //   474: newarray        I
        //   476: putfield        org/k.d:[I
        //   479: iconst_1       
        //   480: istore          4
        //   482: iload           4
        //   484: aload_1        
        //   485: iload_3        
        //   486: aload_2        
        //   487: getfield        org/k.d:[I
        //   490: iconst_0       
        //   491: invokestatic    org/k.a:(Lorg/g;I[II)Z
        //   494: ior            
        //   495: istore          4
        //   497: iload           4
        //   499: ireturn        
        //   500: aload_0        
        //   501: getfield        org/k.d:[I
        //   504: arraylength    
        //   505: aload_0        
        //   506: getfield        org/k.b:Lorg/o;
        //   509: getfield        org/o.f:I
        //   512: iadd           
        //   513: istore          12
        //   515: aload_2        
        //   516: iload           13
        //   518: ifne            536
        //   521: getfield        org/k.d:[I
        //   524: ifnonnull       551
        //   527: goto            531
        //   530: athrow         
        //   531: aload_2        
        //   532: goto            536
        //   535: athrow         
        //   536: iload           12
        //   538: aload_0        
        //   539: getfield        org/k.g:I
        //   542: iadd           
        //   543: newarray        I
        //   545: putfield        org/k.d:[I
        //   548: iconst_1       
        //   549: istore          4
        //   551: iconst_0       
        //   552: istore          5
        //   554: iload           5
        //   556: iload           12
        //   558: if_icmpge       629
        //   561: aload_0        
        //   562: getfield        org/k.d:[I
        //   565: iload           5
        //   567: iaload         
        //   568: istore          9
        //   570: iload           13
        //   572: ifne            624
        //   575: aload_0        
        //   576: getfield        org/k.i:[I
        //   579: iload           13
        //   581: ifne            645
        //   584: goto            588
        //   587: athrow         
        //   588: ifnull          604
        //   591: goto            595
        //   594: athrow         
        //   595: aload_0        
        //   596: aload_1        
        //   597: iload           9
        //   599: invokespecial   org/k.a:(Lorg/g;I)I
        //   602: istore          9
        //   604: iload           4
        //   606: aload_1        
        //   607: iload           9
        //   609: aload_2        
        //   610: getfield        org/k.d:[I
        //   613: iload           5
        //   615: invokestatic    org/k.a:(Lorg/g;I[II)Z
        //   618: ior            
        //   619: istore          4
        //   621: iinc            5, 1
        //   624: iload           13
        //   626: ifeq            554
        //   629: iconst_0       
        //   630: istore          5
        //   632: iload           5
        //   634: aload_0        
        //   635: getfield        org/k.g:I
        //   638: if_icmpge       878
        //   641: aload_0        
        //   642: getfield        org/k.f:[I
        //   645: iload           5
        //   647: iaload         
        //   648: istore          6
        //   650: iload           6
        //   652: ldc             -268435456
        //   654: iand           
        //   655: istore          7
        //   657: iload           6
        //   659: ldc             251658240
        //   661: iand           
        //   662: istore          8
        //   664: iload           8
        //   666: iload           13
        //   668: ifne            880
        //   671: ldc             16777216
        //   673: iload           13
        //   675: ifne            706
        //   678: goto            682
        //   681: athrow         
        //   682: if_icmpne       698
        //   685: goto            689
        //   688: athrow         
        //   689: iload           6
        //   691: istore          9
        //   693: iload           13
        //   695: ifeq            821
        //   698: iload           8
        //   700: ldc             33554432
        //   702: goto            706
        //   705: athrow         
        //   706: iload           13
        //   708: ifne            757
        //   711: if_icmpne       738
        //   714: goto            718
        //   717: athrow         
        //   718: iload           7
        //   720: aload_0        
        //   721: getfield        org/k.c:[I
        //   724: iload           6
        //   726: ldc             8388607
        //   728: iand           
        //   729: iaload         
        //   730: iadd           
        //   731: istore          9
        //   733: iload           13
        //   735: ifeq            760
        //   738: iload           7
        //   740: aload_0        
        //   741: getfield        org/k.d:[I
        //   744: iload           11
        //   746: iload           6
        //   748: ldc             8388607
        //   750: iand           
        //   751: isub           
        //   752: iaload         
        //   753: goto            757
        //   756: athrow         
        //   757: iadd           
        //   758: istore          9
        //   760: iload           6
        //   762: ldc             8388608
        //   764: iand           
        //   765: iload           13
        //   767: ifne            779
        //   770: ifeq            821
        //   773: goto            777
        //   776: athrow         
        //   777: iload           9
        //   779: iload           13
        //   781: ifne            819
        //   784: ldc             16777220
        //   786: if_icmpeq       813
        //   789: goto            793
        //   792: athrow         
        //   793: iload           9
        //   795: iload           13
        //   797: ifne            819
        //   800: goto            804
        //   803: athrow         
        //   804: ldc             16777219
        //   806: if_icmpne       821
        //   809: goto            813
        //   812: athrow         
        //   813: ldc             16777216
        //   815: goto            819
        //   818: athrow         
        //   819: istore          9
        //   821: aload_0        
        //   822: iload           13
        //   824: ifne            842
        //   827: getfield        org/k.i:[I
        //   830: ifnull          850
        //   833: goto            837
        //   836: athrow         
        //   837: aload_0        
        //   838: goto            842
        //   841: athrow         
        //   842: aload_1        
        //   843: iload           9
        //   845: invokespecial   org/k.a:(Lorg/g;I)I
        //   848: istore          9
        //   850: iload           4
        //   852: aload_1        
        //   853: iload           9
        //   855: aload_2        
        //   856: getfield        org/k.d:[I
        //   859: iload           12
        //   861: iload           5
        //   863: iadd           
        //   864: invokestatic    org/k.a:(Lorg/g;I[II)Z
        //   867: ior            
        //   868: istore          4
        //   870: iinc            5, 1
        //   873: iload           13
        //   875: ifeq            632
        //   878: iload           4
        //   880: ireturn        
        //    StackMapTable: 00 71 FF 00 25 00 0E 07 00 51 07 00 82 07 00 51 01 01 00 00 00 00 00 01 01 00 01 00 01 07 00 35 00 43 07 00 35 40 07 00 51 09 FF 00 02 00 0E 07 00 51 07 00 82 07 00 51 01 01 01 00 00 00 00 01 01 00 01 00 00 57 07 00 35 40 07 00 E7 45 07 00 35 00 49 07 00 35 40 01 4A 07 00 35 00 FF 00 15 00 0E 07 00 51 07 00 82 07 00 51 01 01 01 01 00 00 00 01 01 00 01 00 01 07 00 35 00 0D 47 07 00 35 40 01 FF 00 17 00 0E 07 00 51 07 00 82 07 00 51 01 01 01 01 01 01 00 01 01 00 01 00 01 07 00 35 00 08 46 07 00 35 FF 00 00 00 0E 07 00 51 07 00 82 07 00 51 01 01 01 01 01 01 00 01 01 00 01 00 02 01 01 4A 07 00 35 00 13 51 07 00 35 FF 00 00 00 0E 07 00 51 07 00 82 07 00 51 01 01 01 01 01 01 00 01 01 00 01 00 02 01 01 FF 00 02 00 0E 07 00 51 07 00 82 07 00 51 01 01 01 01 01 01 01 01 01 00 01 00 00 4F 07 00 35 00 41 01 4C 07 00 35 00 49 07 00 35 40 01 47 07 00 35 00 44 07 00 35 40 01 FF 00 06 00 0E 07 00 51 07 00 82 07 00 51 01 01 01 00 00 00 00 01 01 00 01 00 00 46 07 00 35 40 07 00 E7 42 01 FF 00 01 00 0E 07 00 51 07 00 82 07 00 51 01 01 01 00 00 00 01 01 01 00 01 00 00 4E 07 00 35 00 43 07 00 35 40 07 00 51 07 FF 00 18 00 0E 07 00 51 07 00 82 07 00 51 01 01 01 00 00 00 00 01 01 00 01 00 00 4B 07 00 35 00 02 FF 00 30 00 0E 07 00 51 07 00 82 07 00 51 01 01 01 00 00 00 01 01 01 00 01 00 01 07 00 35 FF 00 00 00 0E 07 00 51 07 00 82 07 00 51 01 01 01 00 00 00 00 01 01 00 01 00 00 4E 07 00 35 00 43 07 00 35 40 07 00 51 08 0E 02 43 07 00 E7 48 01 FF 00 10 00 0E 07 00 51 07 00 82 07 00 51 01 01 01 00 00 00 00 01 01 01 01 00 01 07 00 35 00 43 07 00 35 40 07 00 51 0E 02 FF 00 20 00 0E 07 00 51 07 00 82 07 00 51 01 01 01 00 00 00 01 01 01 01 01 00 01 07 00 35 40 07 00 E7 45 07 00 35 00 08 13 FF 00 04 00 0E 07 00 51 07 00 82 07 00 51 01 01 01 00 00 00 00 01 01 01 01 00 00 02 4C 07 00 E7 FF 00 23 00 0E 07 00 51 07 00 82 07 00 51 01 01 01 01 01 01 00 01 01 01 01 00 01 07 00 35 FF 00 00 00 0E 07 00 51 07 00 82 07 00 51 01 01 01 01 01 01 00 01 01 01 01 00 02 01 01 45 07 00 35 00 08 46 07 00 35 FF 00 00 00 0E 07 00 51 07 00 82 07 00 51 01 01 01 01 01 01 00 01 01 01 01 00 02 01 01 4A 07 00 35 00 13 51 07 00 35 FF 00 00 00 0E 07 00 51 07 00 82 07 00 51 01 01 01 01 01 01 00 01 01 01 01 00 02 01 01 FF 00 02 00 0E 07 00 51 07 00 82 07 00 51 01 01 01 01 01 01 01 01 01 01 01 00 00 4F 07 00 35 00 41 01 4C 07 00 35 00 49 07 00 35 40 01 47 07 00 35 00 44 07 00 35 40 01 01 4E 07 00 35 00 43 07 00 35 40 07 00 51 07 FF 00 1B 00 0E 07 00 51 07 00 82 07 00 51 01 01 01 00 00 00 00 01 01 01 01 00 00 41 01
        //    Exceptions:
        //  Try           Handler
        //  Start  End    Start  End    Type                        
        //  -----  -----  -----  -----  ----------------------------
        //  827    838    841    842    Ljava/lang/RuntimeException;
        //  821    833    836    837    Ljava/lang/RuntimeException;
        //  804    815    818    819    Ljava/lang/RuntimeException;
        //  793    809    812    813    Ljava/lang/RuntimeException;
        //  784    800    803    804    Ljava/lang/RuntimeException;
        //  779    789    792    793    Ljava/lang/RuntimeException;
        //  760    773    776    777    Ljava/lang/RuntimeException;
        //  733    753    756    757    Ljava/lang/RuntimeException;
        //  706    714    717    718    Ljava/lang/RuntimeException;
        //  693    702    705    706    Ljava/lang/RuntimeException;
        //  671    685    688    689    Ljava/lang/RuntimeException;
        //  664    678    681    682    Ljava/lang/RuntimeException;
        //  575    591    594    595    Ljava/lang/RuntimeException;
        //  570    584    587    588    Ljava/lang/RuntimeException;
        //  521    532    535    536    Ljava/lang/RuntimeException;
        //  515    527    530    531    Ljava/lang/RuntimeException;
        //  458    469    472    473    Ljava/lang/RuntimeException;
        //  452    464    467    468    Ljava/lang/RuntimeException;
        //  435    448    451    452    Ljava/lang/RuntimeException;
        //  386    395    398    399    Ljava/lang/RuntimeException;
        //  338    349    352    353    Ljava/lang/RuntimeException;
        //  332    344    347    348    Ljava/lang/RuntimeException;
        //  314    323    326    327    Ljava/lang/RuntimeException;
        //  297    308    311    312    Ljava/lang/RuntimeException;
        //  286    302    305    306    Ljava/lang/RuntimeException;
        //  277    293    296    297    Ljava/lang/RuntimeException;
        //  272    282    285    286    Ljava/lang/RuntimeException;
        //  253    266    269    270    Ljava/lang/RuntimeException;
        //  226    246    249    250    Ljava/lang/RuntimeException;
        //  199    207    210    211    Ljava/lang/RuntimeException;
        //  186    195    198    199    Ljava/lang/RuntimeException;
        //  166    178    181    182    Ljava/lang/RuntimeException;
        //  143    153    156    157    Ljava/lang/RuntimeException;
        //  120    130    133    134    Ljava/lang/RuntimeException;
        //  88     107    110    111    Ljava/lang/RuntimeException;
        //  81     95     98     99     Ljava/lang/RuntimeException;
        //  72     84     87     88     Ljava/lang/RuntimeException;
        //  63     77     80     81     Ljava/lang/RuntimeException;
        //  28     39     42     43     Ljava/lang/RuntimeException;
        //  22     34     37     38     Ljava/lang/RuntimeException;
        // 
        // The error that occurred was:
        // 
        // java.lang.IllegalStateException: Expression is linked from several locations: Label_0081:
        //     at com.strobel.decompiler.ast.Error.expressionLinkedFromMultipleLocations(Error.java:27)
        //     at com.strobel.decompiler.ast.AstOptimizer.mergeDisparateObjectInitializations(AstOptimizer.java:2596)
        //     at com.strobel.decompiler.ast.AstOptimizer.optimize(AstOptimizer.java:235)
        //     at com.strobel.decompiler.ast.AstOptimizer.optimize(AstOptimizer.java:42)
        //     at com.strobel.decompiler.languages.java.ast.AstMethodBodyBuilder.createMethodBody(AstMethodBodyBuilder.java:214)
        //     at com.strobel.decompiler.languages.java.ast.AstMethodBodyBuilder.createMethodBody(AstMethodBodyBuilder.java:99)
        //     at com.strobel.decompiler.languages.java.ast.AstBuilder.createMethodBody(AstBuilder.java:782)
        //     at com.strobel.decompiler.languages.java.ast.AstBuilder.createMethod(AstBuilder.java:675)
        //     at com.strobel.decompiler.languages.java.ast.AstBuilder.addTypeMembers(AstBuilder.java:552)
        //     at com.strobel.decompiler.languages.java.ast.AstBuilder.createTypeCore(AstBuilder.java:519)
        //     at com.strobel.decompiler.languages.java.ast.AstBuilder.createTypeNoCache(AstBuilder.java:161)
        //     at com.strobel.decompiler.languages.java.ast.AstBuilder.createType(AstBuilder.java:150)
        //     at com.strobel.decompiler.languages.java.ast.AstBuilder.addType(AstBuilder.java:125)
        //     at com.strobel.decompiler.languages.java.JavaLanguage.buildAst(JavaLanguage.java:71)
        //     at com.strobel.decompiler.languages.java.JavaLanguage.decompileType(JavaLanguage.java:59)
        //     at com.strobel.decompiler.DecompilerDriver.decompileType(DecompilerDriver.java:330)
        //     at com.strobel.decompiler.DecompilerDriver.decompileJar(DecompilerDriver.java:251)
        //     at com.strobel.decompiler.DecompilerDriver.main(DecompilerDriver.java:126)
        // 
        throw new IllegalStateException("An error occurred while decompiling this method.");
    }
    
    private static boolean a(final g p0, final int p1, final int[] p2, final int p3) {
        // 
        // This method could not be decompiled.
        // 
        // Original Bytecode:
        // 
        //     3: istore          6
        //     5: aload_2        
        //     6: iload_3        
        //     7: iaload         
        //     8: istore          4
        //    10: iload           4
        //    12: iload_1        
        //    13: iload           6
        //    15: ifne            43
        //    18: if_icmpne       28
        //    21: goto            25
        //    24: athrow         
        //    25: iconst_0       
        //    26: ireturn        
        //    27: athrow         
        //    28: iload_1        
        //    29: ldc             268435455
        //    31: iand           
        //    32: iload           6
        //    34: ifne            74
        //    37: ldc             16777221
        //    39: goto            43
        //    42: athrow         
        //    43: if_icmpne       72
        //    46: iload           4
        //    48: iload           6
        //    50: ifne            71
        //    53: goto            57
        //    56: athrow         
        //    57: ldc             16777221
        //    59: if_icmpne       69
        //    62: goto            66
        //    65: athrow         
        //    66: iconst_0       
        //    67: ireturn        
        //    68: athrow         
        //    69: ldc             16777221
        //    71: istore_1       
        //    72: iload           4
        //    74: iload           6
        //    76: ifne            98
        //    79: ifne            93
        //    82: goto            86
        //    85: athrow         
        //    86: aload_2        
        //    87: iload_3        
        //    88: iload_1        
        //    89: iastore        
        //    90: iconst_1       
        //    91: ireturn        
        //    92: athrow         
        //    93: iload           4
        //    95: ldc             267386880
        //    97: iand           
        //    98: ldc             24117248
        //   100: iload           6
        //   102: ifne            140
        //   105: if_icmpeq       133
        //   108: goto            112
        //   111: athrow         
        //   112: iload           4
        //   114: ldc             -268435456
        //   116: iand           
        //   117: iload           6
        //   119: ifne            340
        //   122: goto            126
        //   125: athrow         
        //   126: ifeq            334
        //   129: goto            133
        //   132: athrow         
        //   133: iload_1        
        //   134: ldc             16777221
        //   136: goto            140
        //   139: athrow         
        //   140: iload           6
        //   142: ifne            164
        //   145: if_icmpne       155
        //   148: goto            152
        //   151: athrow         
        //   152: iconst_0       
        //   153: ireturn        
        //   154: athrow         
        //   155: iload_1        
        //   156: ldc             -1048576
        //   158: iand           
        //   159: iload           4
        //   161: ldc             -1048576
        //   163: iand           
        //   164: iload           6
        //   166: ifne            263
        //   169: if_icmpne       253
        //   172: goto            176
        //   175: athrow         
        //   176: iload           4
        //   178: ldc             267386880
        //   180: iand           
        //   181: ldc             24117248
        //   183: iload           6
        //   185: ifne            245
        //   188: goto            192
        //   191: athrow         
        //   192: if_icmpne       227
        //   195: goto            199
        //   198: athrow         
        //   199: iload_1        
        //   200: ldc             -268435456
        //   202: iand           
        //   203: ldc             24117248
        //   205: ior            
        //   206: aload_0        
        //   207: iload_1        
        //   208: ldc             1048575
        //   210: iand           
        //   211: iload           4
        //   213: ldc             1048575
        //   215: iand           
        //   216: invokevirtual   org/g.a:(II)I
        //   219: ior            
        //   220: istore          5
        //   222: iload           6
        //   224: ifeq            417
        //   227: ldc             24117248
        //   229: aload_0        
        //   230: getstatic       org/k.z:[Ljava/lang/String;
        //   233: iconst_0       
        //   234: aaload         
        //   235: invokestatic    org/f.a:(Ljava/lang/String;)Ljava/lang/String;
        //   238: invokevirtual   org/g.f:(Ljava/lang/String;)I
        //   241: goto            245
        //   244: athrow         
        //   245: ior            
        //   246: istore          5
        //   248: iload           6
        //   250: ifeq            417
        //   253: iload_1        
        //   254: ldc             267386880
        //   256: iand           
        //   257: ldc             24117248
        //   259: goto            263
        //   262: athrow         
        //   263: iload           6
        //   265: ifne            313
        //   268: if_icmpeq       295
        //   271: goto            275
        //   274: athrow         
        //   275: iload_1        
        //   276: ldc             -268435456
        //   278: iand           
        //   279: iload           6
        //   281: ifne            327
        //   284: goto            288
        //   287: athrow         
        //   288: ifeq            321
        //   291: goto            295
        //   294: athrow         
        //   295: ldc             24117248
        //   297: aload_0        
        //   298: getstatic       org/k.z:[Ljava/lang/String;
        //   301: iconst_0       
        //   302: aaload         
        //   303: invokestatic    org/f.a:(Ljava/lang/String;)Ljava/lang/String;
        //   306: invokevirtual   org/g.f:(Ljava/lang/String;)I
        //   309: goto            313
        //   312: athrow         
        //   313: ior            
        //   314: istore          5
        //   316: iload           6
        //   318: ifeq            417
        //   321: ldc             16777216
        //   323: goto            327
        //   326: athrow         
        //   327: istore          5
        //   329: iload           6
        //   331: ifeq            417
        //   334: iload           4
        //   336: goto            340
        //   339: athrow         
        //   340: iload           6
        //   342: ifne            415
        //   345: ldc             16777221
        //   347: if_icmpne       409
        //   350: goto            354
        //   353: athrow         
        //   354: iload_1        
        //   355: ldc             267386880
        //   357: iand           
        //   358: iload           6
        //   360: ifne            397
        //   363: goto            367
        //   366: athrow         
        //   367: ldc             24117248
        //   369: if_icmpeq       396
        //   372: goto            376
        //   375: athrow         
        //   376: iload_1        
        //   377: ldc             -268435456
        //   379: iand           
        //   380: iload           6
        //   382: ifne            397
        //   385: goto            389
        //   388: athrow         
        //   389: ifeq            400
        //   392: goto            396
        //   395: athrow         
        //   396: iload_1        
        //   397: goto            402
        //   400: ldc             16777216
        //   402: istore          5
        //   404: iload           6
        //   406: ifeq            417
        //   409: ldc             16777216
        //   411: goto            415
        //   414: athrow         
        //   415: istore          5
        //   417: iload           4
        //   419: iload           6
        //   421: ifne            442
        //   424: iload           5
        //   426: if_icmpeq       441
        //   429: goto            433
        //   432: athrow         
        //   433: aload_2        
        //   434: iload_3        
        //   435: iload           5
        //   437: iastore        
        //   438: iconst_1       
        //   439: ireturn        
        //   440: athrow         
        //   441: iconst_0       
        //   442: ireturn        
        //    StackMapTable: 00 51 FF 00 18 00 07 07 00 82 01 07 00 E7 01 01 00 01 00 01 07 00 35 00 41 07 00 35 00 4D 07 00 35 FF 00 00 00 07 07 00 82 01 07 00 E7 01 01 00 01 00 02 01 01 4C 07 00 35 40 01 47 07 00 35 00 41 07 00 35 00 41 01 00 41 01 4A 07 00 35 00 45 07 00 35 00 44 01 4C 07 00 35 00 4C 07 00 35 40 01 45 07 00 35 00 45 07 00 35 FF 00 00 00 07 07 00 82 01 07 00 E7 01 01 00 01 00 02 01 01 4A 07 00 35 00 41 07 00 35 00 FF 00 08 00 07 07 00 82 01 07 00 E7 01 01 00 01 00 02 01 01 4A 07 00 35 00 4E 07 00 35 FF 00 00 00 07 07 00 82 01 07 00 E7 01 01 00 01 00 02 01 01 45 07 00 35 00 1B 50 07 00 35 FF 00 00 00 07 07 00 82 01 07 00 E7 01 01 00 01 00 02 01 01 07 48 07 00 35 FF 00 00 00 07 07 00 82 01 07 00 E7 01 01 00 01 00 02 01 01 4A 07 00 35 00 4B 07 00 35 40 01 45 07 00 35 00 50 07 00 35 FF 00 00 00 07 07 00 82 01 07 00 E7 01 01 00 01 00 02 01 01 07 44 07 00 35 40 01 06 44 07 00 35 40 01 4C 07 00 35 00 4B 07 00 35 40 01 47 07 00 35 00 4B 07 00 35 40 01 45 07 00 35 00 40 01 02 41 01 06 44 07 00 35 40 01 FF 00 01 00 07 07 00 82 01 07 00 E7 01 01 01 01 00 00 4E 07 00 35 00 46 07 00 35 00 40 01
        //    Exceptions:
        //  Try           Handler
        //  Start  End    Start  End    Type                        
        //  -----  -----  -----  -----  ----------------------------
        //  424    440    440    441    Ljava/lang/RuntimeException;
        //  417    429    432    433    Ljava/lang/RuntimeException;
        //  404    411    414    415    Ljava/lang/RuntimeException;
        //  376    392    395    396    Ljava/lang/RuntimeException;
        //  367    385    388    389    Ljava/lang/RuntimeException;
        //  354    372    375    376    Ljava/lang/RuntimeException;
        //  345    363    366    367    Ljava/lang/RuntimeException;
        //  340    350    353    354    Ljava/lang/RuntimeException;
        //  329    336    339    340    Ljava/lang/RuntimeException;
        //  316    323    326    327    Ljava/lang/RuntimeException;
        //  288    309    312    313    Ljava/lang/RuntimeException;
        //  275    291    294    295    Ljava/lang/RuntimeException;
        //  268    284    287    288    Ljava/lang/RuntimeException;
        //  263    271    274    275    Ljava/lang/RuntimeException;
        //  248    259    262    263    Ljava/lang/RuntimeException;
        //  222    241    244    245    Ljava/lang/RuntimeException;
        //  176    195    198    199    Ljava/lang/RuntimeException;
        //  169    188    191    192    Ljava/lang/RuntimeException;
        //  164    172    175    176    Ljava/lang/RuntimeException;
        //  145    154    154    155    Ljava/lang/RuntimeException;
        //  140    148    151    152    Ljava/lang/RuntimeException;
        //  126    136    139    140    Ljava/lang/RuntimeException;
        //  112    129    132    133    Ljava/lang/RuntimeException;
        //  105    122    125    126    Ljava/lang/RuntimeException;
        //  98     108    111    112    Ljava/lang/RuntimeException;
        //  79     92     92     93     Ljava/lang/RuntimeException;
        //  74     82     85     86     Ljava/lang/RuntimeException;
        //  57     68     68     69     Ljava/lang/RuntimeException;
        //  46     62     65     66     Ljava/lang/RuntimeException;
        //  43     53     56     57     Ljava/lang/RuntimeException;
        //  28     39     42     43     Ljava/lang/RuntimeException;
        //  18     27     27     28     Ljava/lang/RuntimeException;
        //  10     21     24     25     Ljava/lang/RuntimeException;
        // 
        // The error that occurred was:
        // 
        // java.lang.IllegalStateException: Expression is linked from several locations: Label_0057:
        //     at com.strobel.decompiler.ast.Error.expressionLinkedFromMultipleLocations(Error.java:27)
        //     at com.strobel.decompiler.ast.AstOptimizer.mergeDisparateObjectInitializations(AstOptimizer.java:2596)
        //     at com.strobel.decompiler.ast.AstOptimizer.optimize(AstOptimizer.java:235)
        //     at com.strobel.decompiler.ast.AstOptimizer.optimize(AstOptimizer.java:42)
        //     at com.strobel.decompiler.languages.java.ast.AstMethodBodyBuilder.createMethodBody(AstMethodBodyBuilder.java:214)
        //     at com.strobel.decompiler.languages.java.ast.AstMethodBodyBuilder.createMethodBody(AstMethodBodyBuilder.java:99)
        //     at com.strobel.decompiler.languages.java.ast.AstBuilder.createMethodBody(AstBuilder.java:782)
        //     at com.strobel.decompiler.languages.java.ast.AstBuilder.createMethod(AstBuilder.java:675)
        //     at com.strobel.decompiler.languages.java.ast.AstBuilder.addTypeMembers(AstBuilder.java:552)
        //     at com.strobel.decompiler.languages.java.ast.AstBuilder.createTypeCore(AstBuilder.java:519)
        //     at com.strobel.decompiler.languages.java.ast.AstBuilder.createTypeNoCache(AstBuilder.java:161)
        //     at com.strobel.decompiler.languages.java.ast.AstBuilder.createType(AstBuilder.java:150)
        //     at com.strobel.decompiler.languages.java.ast.AstBuilder.addType(AstBuilder.java:125)
        //     at com.strobel.decompiler.languages.java.JavaLanguage.buildAst(JavaLanguage.java:71)
        //     at com.strobel.decompiler.languages.java.JavaLanguage.decompileType(JavaLanguage.java:59)
        //     at com.strobel.decompiler.DecompilerDriver.decompileType(DecompilerDriver.java:330)
        //     at com.strobel.decompiler.DecompilerDriver.decompileJar(DecompilerDriver.java:251)
        //     at com.strobel.decompiler.DecompilerDriver.main(DecompilerDriver.java:126)
        // 
        throw new IllegalStateException("An error occurred while decompiling this method.");
    }
    
    static {
        final String[] z2 = new String[6];
        int n6;
        int n5;
        int n4;
        int n3;
        int n2;
        int n = n2 = (n3 = (n4 = (n5 = (n6 = 0))));
        String s = "dh{WF\u0016\u001c\u0017%2AkgS\n\u000e";
        int n7 = -1;
        String intern = null;
    Label_0081_Outer:
        while (true) {
            final char[] charArray = s.toCharArray();
            int length;
            int n9;
            final int n8 = n9 = (length = charArray.length);
            int n10 = 0;
            while (true) {
                Label_0158: {
                    if (n8 > 1) {
                        break Label_0158;
                    }
                    length = (n9 = n10);
                    do {
                        final char c = charArray[n9];
                        char c2 = '\0';
                        switch (n10 % 5) {
                            case 0: {
                                c2 = '0';
                                break;
                            }
                            case 1: {
                                c2 = 'C';
                                break;
                            }
                            case 2: {
                                c2 = '3';
                                break;
                            }
                            case 3: {
                                c2 = '|';
                                break;
                            }
                            default: {
                                c2 = 'W';
                                break;
                            }
                        }
                        charArray[length] = (char)(c ^ c2);
                        ++n10;
                    } while (n8 == 0);
                }
                if (n8 > n10) {
                    continue;
                }
                break;
            }
            intern = new String(charArray).intern();
            switch (n7) {
                default: {
                    z2[n2] = intern;
                    n = (n2 = (n3 = (n4 = (n5 = (n6 = 1)))));
                    s = "dh{WF\u0016\u001c\u0017%2]}\u007f_\u0007\u001d";
                    n7 = 0;
                    continue Label_0081_Outer;
                }
                case 0: {
                    z2[n] = intern;
                    n = (n2 = (n3 = (n4 = (n5 = (n6 = 2)))));
                    s = "\u0010\u001c\u000f#2bhcQF\u0013\u0013\u000f-vk&@S\u001d\u0012\u0012\u001d\n|`maS";
                    n7 = 1;
                    continue Label_0081_Outer;
                }
                case 1: {
                    z2[n3] = intern;
                    n = (n2 = (n3 = (n4 = (n5 = (n6 = 3)))));
                    s = "0.+mOK]-W\u001b\u001f]\u0017-i.zxF\u0019\u0015\u000f\r'y.~dB\u0001Z\u001e\u0016/m{}hp\u001b\u001b\u0010\u001c1=ayy_\u0006\u0014";
                    n7 = 2;
                    continue Label_0081_Outer;
                }
                case 2: {
                    z2[n4] = intern;
                    n = (n2 = (n3 = (n4 = (n5 = (n6 = 4)))));
                    s = "\u0010\u001c\u000f#2bhcQF\u0013\u0013\u000f-vk&@S\u001d\u0012\u0012\u001d\u0016d~l";
                    n7 = 3;
                    continue Label_0081_Outer;
                }
                case 3: {
                    z2[n5] = intern;
                    n = (n2 = (n3 = (n4 = (n5 = (n6 = 5)))));
                    s = "\u0010\u001c\u000f#2bhcQF9\u0011\u00181n";
                    n7 = 4;
                    continue Label_0081_Outer;
                }
                case 4: {
                    break Label_0081_Outer;
                }
            }
        }
        z2[n6] = intern;
        z = z2;
        final int[] a2 = new int[202];
        int index = 0;
        int[] array;
        int n11;
        String s2 = null;
        String intern2;
        char[] charArray2;
        int length2;
        int n13;
        int n12;
        int n14;
        char c3;
        char c4 = '\0';
        Label_0353_Outer:Label_0230_Outer:
        while (true) {
            while (true) {
                while (true) {
                    Label_0215: {
                        try {
                            if (index < a2.length) {
                                array = a2;
                                n11 = index;
                                s2 = "KOKp/<;?\u0004ZIOKp.=;?\u0004XKOJp.<8<\u0007XKLHs,?8<\u0007XKLHs,?9<\u0006XJMIr-99:\u0006XKLHs,?8<\u0007XKLHs,?8<\u0007_OKLt+8?=\u0001[HOJq.?9:\u0006^JJIu-99:\u0006^JJIu-98<\u0007XJMIr->9:\u0006^JJHp,<9=\u0007XHOIs-?8<\u0000YJKOr->9=\u0006^MJNu*9><\u0004XJMIu-99<\u0007XKLHs,?8?\u0007XKLHs->8<\u0006YKL";
                                break Label_0215;
                            }
                            break;
                            array[n11] = f.a(intern2).charAt(index) - 'E';
                            ++index;
                            continue Label_0353_Outer;
                        }
                        catch (RuntimeException ex) {
                            throw ex;
                        }
                        break;
                    }
                    charArray2 = s2.toCharArray();
                    n12 = (n13 = (length2 = charArray2.length));
                    n14 = 0;
                    Label_0306: {
                        if (n12 > 1) {
                            break Label_0306;
                        }
                        length2 = (n13 = n14);
                        do {
                            c3 = charArray2[n13];
                            switch (n14 % 5) {
                                case 0: {
                                    c4 = '0';
                                    break;
                                }
                                case 1: {
                                    c4 = 'C';
                                    break;
                                }
                                case 2: {
                                    c4 = '3';
                                    break;
                                }
                                case 3: {
                                    c4 = '|';
                                    break;
                                }
                                default: {
                                    c4 = 'W';
                                    break;
                                }
                            }
                            charArray2[length2] = (char)(c3 ^ c4);
                            ++n14;
                        } while (n12 == 0);
                    }
                    if (n12 <= n14) {
                        intern2 = new String(charArray2).intern();
                        continue Label_0230_Outer;
                    }
                    break;
                }
                continue;
            }
        }
        a = a2;
    }
}
