
package org.powerbot.game.api.methods;

import org.o;
import org.powerbot.game.api.util.SkillData;

public enum Tabs
{
    NONE(-1, (String)null, -1), 
    ATTACK(0, SkillData.e(Tabs.z[5]), 116), 
    NOTICEBOARD(1, SkillData.e(Tabs.z[27]), -1), 
    STATS(2, SkillData.e(Tabs.z[9]), -1), 
    COMBAT_ACADEMY(3, SkillData.e(Tabs.z[23]), -1), 
    INVENTORY(4, SkillData.e(Tabs.z[24]), 112), 
    EQUIPMENT(5, SkillData.e(Tabs.z[32]), 113), 
    PRAYER(6, SkillData.e(Tabs.z[20]), 114), 
    ABILITY_BOOK(7, SkillData.e(Tabs.z[21]), 115), 
    EXTRAS(8, SkillData.e(Tabs.z[3]), -1), 
    FRIENDS(9, SkillData.e(Tabs.z[31]), -1), 
    FRIENDS_CHAT(10, SkillData.e(Tabs.z[12]), -1), 
    CLAN_CHAT(11, SkillData.e(Tabs.z[29]), -1), 
    OPTIONS(12, SkillData.e(Tabs.z[16]), -1), 
    EMOTES(13, SkillData.e(Tabs.z[22]), -1), 
    MUSIC(14, SkillData.e(Tabs.z[28]), -1), 
    NOTES(15, SkillData.e(Tabs.z[18]), -1), 
    LOGOUT(16, SkillData.e(Tabs.z[1]), -1);
    
    private static final int WIDGET_LOGOUT_X = 182;
    private final String description;
    private final int functionKey;
    private final int index;
    private static final String[] z;
    
    private Tabs(final int index, final String description, final int functionKey) {
        this.description = description;
        this.functionKey = functionKey;
        this.index = index;
    }
    
    public String getDescription() {
        return this.description;
    }
    
    public int getFunctionKey() {
        return this.functionKey;
    }
    
    public boolean hasFunctionKey() {
        int functionKey = 0;
        Label_0018: {
            int n;
            try {
                n = (functionKey = this.functionKey);
                if (Widgets.a != 0) {
                    return functionKey != 0;
                }
                final int n2 = -1;
                if (n != n2) {
                    break Label_0018;
                }
                return false;
            }
            catch (RuntimeException ex) {
                throw ex;
            }
            try {
                final int n2 = -1;
                if (n == n2) {
                    return false;
                }
                functionKey = 1;
            }
            catch (RuntimeException ex2) {
                throw ex2;
            }
        }
        return functionKey != 0;
        functionKey = 0;
        return functionKey != 0;
    }
    
    public int getIndex() {
        return this.index;
    }
    
    public boolean open() {
        return this.open(false);
    }
    
    public boolean open(final boolean p0) {
        // 
        // This method could not be decompiled.
        // 
        // Original Bytecode:
        // 
        //     3: istore          4
        //     5: aload_0        
        //     6: getstatic       org/powerbot/game/api/methods/Tabs.NONE:Lorg/powerbot/game/api/methods/Tabs;
        //     9: iload           4
        //    11: ifne            28
        //    14: if_acmpne       24
        //    17: goto            21
        //    20: athrow         
        //    21: iconst_0       
        //    22: ireturn        
        //    23: athrow         
        //    24: aload_0        
        //    25: invokestatic    org/powerbot/game/api/methods/Tabs.getCurrent:()Lorg/powerbot/game/api/methods/Tabs;
        //    28: if_acmpne       34
        //    31: iconst_1       
        //    32: ireturn        
        //    33: athrow         
        //    34: iload_1        
        //    35: iload           4
        //    37: ifne            64
        //    40: ifeq            93
        //    43: goto            47
        //    46: athrow         
        //    47: aload_0        
        //    48: iload           4
        //    50: ifne            98
        //    53: goto            57
        //    56: athrow         
        //    57: invokevirtual   org/powerbot/game/api/methods/Tabs.hasFunctionKey:()Z
        //    60: goto            64
        //    63: athrow         
        //    64: ifeq            93
        //    67: ldc             65535
        //    69: aload_0        
        //    70: invokevirtual   org/powerbot/game/api/methods/Tabs.getFunctionKey:()I
        //    73: bipush          100
        //    75: sipush          300
        //    78: invokestatic    org/powerbot/game/api/util/Random.nextInt:(II)I
        //    81: invokestatic    org/powerbot/game/api/methods/input/Keyboard.sendKey:(CII)V
        //    84: iload           4
        //    86: ifeq            200
        //    89: goto            93
        //    92: athrow         
        //    93: aload_0        
        //    94: goto            98
        //    97: athrow         
        //    98: iload           4
        //   100: ifne            203
        //   103: invokestatic    org/powerbot/game/api/methods/widget/WidgetCache.getTab:(Lorg/powerbot/game/api/methods/Tabs;)Lorg/powerbot/game/api/wrappers/widget/WidgetChild;
        //   106: astore_2       
        //   107: aload_2        
        //   108: ifnull          200
        //   111: aload_2        
        //   112: invokevirtual   org/powerbot/game/api/wrappers/widget/WidgetChild.validate:()Z
        //   115: iload           4
        //   117: ifne            140
        //   120: goto            124
        //   123: athrow         
        //   124: ifeq            200
        //   127: goto            131
        //   130: athrow         
        //   131: aload_2        
        //   132: iconst_1       
        //   133: invokevirtual   org/powerbot/game/api/wrappers/widget/WidgetChild.click:(Z)Z
        //   136: goto            140
        //   139: athrow         
        //   140: ifeq            200
        //   143: new             Lorg/powerbot/game/api/util/Timer;
        //   146: dup            
        //   147: ldc2_w          800
        //   150: invokespecial   org/powerbot/game/api/util/Timer.<init>:(J)V
        //   153: astore_3       
        //   154: aload_3        
        //   155: invokevirtual   org/powerbot/game/api/util/Timer.isRunning:()Z
        //   158: ifeq            200
        //   161: invokestatic    org/powerbot/game/api/methods/Tabs.getCurrent:()Lorg/powerbot/game/api/methods/Tabs;
        //   164: aload_0        
        //   165: iload           4
        //   167: ifne            204
        //   170: iload           4
        //   172: ifne            204
        //   175: goto            179
        //   178: athrow         
        //   179: if_acmpeq       200
        //   182: goto            186
        //   185: athrow         
        //   186: bipush          15
        //   188: invokestatic    org/powerbot/core/script/job/Task.sleep:(I)V
        //   191: iload           4
        //   193: ifeq            154
        //   196: goto            200
        //   199: athrow         
        //   200: invokestatic    org/powerbot/game/api/methods/Tabs.getCurrent:()Lorg/powerbot/game/api/methods/Tabs;
        //   203: aload_0        
        //   204: if_acmpne       212
        //   207: iconst_1       
        //   208: goto            213
        //   211: athrow         
        //   212: iconst_0       
        //   213: ireturn        
        //    StackMapTable: 00 23 FF 00 14 00 05 07 00 04 01 00 00 01 00 01 07 01 09 00 41 07 01 09 00 FF 00 03 00 05 07 00 04 01 00 00 01 00 02 07 00 04 07 00 04 44 07 01 09 00 4B 07 01 09 00 48 07 01 09 40 07 00 04 45 07 01 09 40 01 5B 07 01 09 00 43 07 01 09 40 07 00 04 FF 00 18 00 05 07 00 04 01 07 00 7B 00 01 00 01 07 01 09 40 01 45 07 01 09 00 47 07 01 09 40 01 FF 00 0D 00 05 07 00 04 01 07 00 7B 07 00 15 01 00 00 57 07 01 09 FF 00 00 00 05 07 00 04 01 07 00 7B 07 00 15 01 00 02 07 00 04 07 00 04 45 07 01 09 00 4C 07 01 09 FF 00 00 00 05 07 00 04 01 00 00 01 00 00 42 07 00 04 FF 00 00 00 05 07 00 04 01 00 00 01 00 02 07 00 04 07 00 04 46 07 01 09 00 40 01
        //    Exceptions:
        //  Try           Handler
        //  Start  End    Start  End    Type                        
        //  -----  -----  -----  -----  ----------------------------
        //  204    211    211    212    Ljava/lang/RuntimeException;
        //  179    196    199    200    Ljava/lang/RuntimeException;
        //  170    182    185    186    Ljava/lang/RuntimeException;
        //  161    175    178    179    Ljava/lang/RuntimeException;
        //  124    136    139    140    Ljava/lang/RuntimeException;
        //  111    127    130    131    Ljava/lang/RuntimeException;
        //  107    120    123    124    Ljava/lang/RuntimeException;
        //  67     94     97     98     Ljava/lang/RuntimeException;
        //  64     89     92     93     Ljava/lang/RuntimeException;
        //  47     60     63     64     Ljava/lang/RuntimeException;
        //  40     53     56     57     Ljava/lang/RuntimeException;
        //  34     43     46     47     Ljava/lang/RuntimeException;
        //  28     33     33     34     Ljava/lang/RuntimeException;
        //  14     23     23     24     Ljava/lang/RuntimeException;
        //  5      17     20     21     Ljava/lang/RuntimeException;
        // 
        // The error that occurred was:
        // 
        // java.lang.IllegalStateException: Expression is linked from several locations: Label_0047:
        //     at com.strobel.decompiler.ast.Error.expressionLinkedFromMultipleLocations(Error.java:27)
        //     at com.strobel.decompiler.ast.AstOptimizer.mergeDisparateObjectInitializations(AstOptimizer.java:2596)
        //     at com.strobel.decompiler.ast.AstOptimizer.optimize(AstOptimizer.java:235)
        //     at com.strobel.decompiler.ast.AstOptimizer.optimize(AstOptimizer.java:42)
        //     at com.strobel.decompiler.languages.java.ast.AstMethodBodyBuilder.createMethodBody(AstMethodBodyBuilder.java:214)
        //     at com.strobel.decompiler.languages.java.ast.AstMethodBodyBuilder.createMethodBody(AstMethodBodyBuilder.java:99)
        //     at com.strobel.decompiler.languages.java.ast.AstBuilder.createMethodBody(AstBuilder.java:782)
        //     at com.strobel.decompiler.languages.java.ast.AstBuilder.createMethod(AstBuilder.java:675)
        //     at com.strobel.decompiler.languages.java.ast.AstBuilder.addTypeMembers(AstBuilder.java:552)
        //     at com.strobel.decompiler.languages.java.ast.AstBuilder.createTypeCore(AstBuilder.java:519)
        //     at com.strobel.decompiler.languages.java.ast.AstBuilder.createTypeNoCache(AstBuilder.java:161)
        //     at com.strobel.decompiler.languages.java.ast.AstBuilder.createType(AstBuilder.java:150)
        //     at com.strobel.decompiler.languages.java.ast.AstBuilder.addType(AstBuilder.java:125)
        //     at com.strobel.decompiler.languages.java.JavaLanguage.buildAst(JavaLanguage.java:71)
        //     at com.strobel.decompiler.languages.java.JavaLanguage.decompileType(JavaLanguage.java:59)
        //     at com.strobel.decompiler.DecompilerDriver.decompileType(DecompilerDriver.java:330)
        //     at com.strobel.decompiler.DecompilerDriver.decompileJar(DecompilerDriver.java:251)
        //     at com.strobel.decompiler.DecompilerDriver.main(DecompilerDriver.java:126)
        // 
        throw new IllegalStateException("An error occurred while decompiling this method.");
    }
    
    public boolean isOpen() {
        try {
            if (getCurrent() == this) {
                return true;
            }
        }
        catch (RuntimeException ex) {
            throw ex;
        }
        return false;
    }
    
    public static Tabs getCurrent() {
        // 
        // This method could not be decompiled.
        // 
        // Original Bytecode:
        // 
        //     3: istore          5
        //     5: invokestatic    org/powerbot/game/api/methods/Tabs.values:()[Lorg/powerbot/game/api/methods/Tabs;
        //     8: astore_0       
        //     9: aload_0        
        //    10: arraylength    
        //    11: istore_1       
        //    12: iconst_0       
        //    13: istore_2       
        //    14: iload_2        
        //    15: iload_1        
        //    16: if_icmpge       76
        //    19: aload_0        
        //    20: iload_2        
        //    21: aaload         
        //    22: astore_3       
        //    23: aload_3        
        //    24: invokestatic    org/powerbot/game/api/methods/widget/WidgetCache.getTab:(Lorg/powerbot/game/api/methods/Tabs;)Lorg/powerbot/game/api/wrappers/widget/WidgetChild;
        //    27: astore          4
        //    29: iload           5
        //    31: ifne            71
        //    34: aload           4
        //    36: iload           5
        //    38: ifne            83
        //    41: goto            45
        //    44: athrow         
        //    45: ifnull          68
        //    48: goto            52
        //    51: athrow         
        //    52: aload           4
        //    54: invokevirtual   org/powerbot/game/api/wrappers/widget/WidgetChild.getTextureId:()I
        //    57: iconst_m1      
        //    58: if_icmpeq       68
        //    61: goto            65
        //    64: athrow         
        //    65: aload_3        
        //    66: areturn        
        //    67: athrow         
        //    68: iinc            2, 1
        //    71: iload           5
        //    73: ifeq            14
        //    76: sipush          182
        //    79: iconst_1       
        //    80: invokestatic    org/powerbot/game/api/methods/Widgets.get:(II)Lorg/powerbot/game/api/wrappers/widget/WidgetChild;
        //    83: astore_0       
        //    84: aload_0        
        //    85: iload           5
        //    87: ifne            98
        //    90: ifnull          131
        //    93: goto            97
        //    96: athrow         
        //    97: aload_0        
        //    98: invokevirtual   org/powerbot/game/api/wrappers/widget/WidgetChild.validate:()Z
        //   101: iload           5
        //   103: ifne            121
        //   106: ifeq            131
        //   109: goto            113
        //   112: athrow         
        //   113: aload_0        
        //   114: invokevirtual   org/powerbot/game/api/wrappers/widget/WidgetChild.visible:()Z
        //   117: goto            121
        //   120: athrow         
        //   121: ifeq            131
        //   124: getstatic       org/powerbot/game/api/methods/Tabs.LOGOUT:Lorg/powerbot/game/api/methods/Tabs;
        //   127: goto            134
        //   130: athrow         
        //   131: getstatic       org/powerbot/game/api/methods/Tabs.NONE:Lorg/powerbot/game/api/methods/Tabs;
        //   134: areturn        
        //    StackMapTable: 00 16 FF 00 0E 00 06 07 00 68 01 01 00 00 01 00 00 FF 00 1D 00 06 07 00 68 01 01 07 00 04 07 00 7B 01 00 01 07 01 09 40 07 00 7B 45 07 01 09 00 4B 07 01 09 00 41 07 01 09 00 02 FF 00 04 00 06 07 00 68 01 01 00 00 01 00 00 46 07 00 7B FF 00 0C 00 06 07 00 7B 01 01 00 00 01 00 01 07 01 09 00 40 07 00 7B 4D 07 01 09 00 46 07 01 09 40 01 48 07 01 09 00 42 07 00 04
        //    Exceptions:
        //  Try           Handler
        //  Start  End    Start  End    Type                        
        //  -----  -----  -----  -----  ----------------------------
        //  121    130    130    131    Ljava/lang/RuntimeException;
        //  106    117    120    121    Ljava/lang/RuntimeException;
        //  98     109    112    113    Ljava/lang/RuntimeException;
        //  84     93     96     97     Ljava/lang/RuntimeException;
        //  52     67     67     68     Ljava/lang/RuntimeException;
        //  45     61     64     65     Ljava/lang/RuntimeException;
        //  34     48     51     52     Ljava/lang/RuntimeException;
        //  29     41     44     45     Ljava/lang/RuntimeException;
        // 
        // The error that occurred was:
        // 
        // java.lang.IllegalStateException: Expression is linked from several locations: Label_0045:
        //     at com.strobel.decompiler.ast.Error.expressionLinkedFromMultipleLocations(Error.java:27)
        //     at com.strobel.decompiler.ast.AstOptimizer.mergeDisparateObjectInitializations(AstOptimizer.java:2596)
        //     at com.strobel.decompiler.ast.AstOptimizer.optimize(AstOptimizer.java:235)
        //     at com.strobel.decompiler.ast.AstOptimizer.optimize(AstOptimizer.java:42)
        //     at com.strobel.decompiler.languages.java.ast.AstMethodBodyBuilder.createMethodBody(AstMethodBodyBuilder.java:214)
        //     at com.strobel.decompiler.languages.java.ast.AstMethodBodyBuilder.createMethodBody(AstMethodBodyBuilder.java:99)
        //     at com.strobel.decompiler.languages.java.ast.AstBuilder.createMethodBody(AstBuilder.java:782)
        //     at com.strobel.decompiler.languages.java.ast.AstBuilder.createMethod(AstBuilder.java:675)
        //     at com.strobel.decompiler.languages.java.ast.AstBuilder.addTypeMembers(AstBuilder.java:552)
        //     at com.strobel.decompiler.languages.java.ast.AstBuilder.createTypeCore(AstBuilder.java:519)
        //     at com.strobel.decompiler.languages.java.ast.AstBuilder.createTypeNoCache(AstBuilder.java:161)
        //     at com.strobel.decompiler.languages.java.ast.AstBuilder.createType(AstBuilder.java:150)
        //     at com.strobel.decompiler.languages.java.ast.AstBuilder.addType(AstBuilder.java:125)
        //     at com.strobel.decompiler.languages.java.JavaLanguage.buildAst(JavaLanguage.java:71)
        //     at com.strobel.decompiler.languages.java.JavaLanguage.decompileType(JavaLanguage.java:59)
        //     at com.strobel.decompiler.DecompilerDriver.decompileType(DecompilerDriver.java:330)
        //     at com.strobel.decompiler.DecompilerDriver.decompileJar(DecompilerDriver.java:251)
        //     at com.strobel.decompiler.DecompilerDriver.main(DecompilerDriver.java:126)
        // 
        throw new IllegalStateException("An error occurred while decompiling this method.");
    }
    
    static {
        final String[] z2 = new String[35];
        int n35;
        int n34;
        int n33;
        int n32;
        int n31;
        int n30;
        int n29;
        int n28;
        int n27;
        int n26;
        int n25;
        int n24;
        int n23;
        int n22;
        int n21;
        int n20;
        int n19;
        int n18;
        int n17;
        int n16;
        int n15;
        int n14;
        int n13;
        int n12;
        int n11;
        int n10;
        int n9;
        int n8;
        int n7;
        int n6;
        int n5;
        int n4;
        int n3;
        int n2;
        int n = n2 = (n3 = (n4 = (n5 = (n6 = (n7 = (n8 = (n9 = (n10 = (n11 = (n12 = (n13 = (n14 = (n15 = (n16 = (n17 = (n18 = (n19 = (n20 = (n21 = (n22 = (n23 = (n24 = (n25 = (n26 = (n27 = (n28 = (n29 = (n30 = (n31 = (n32 = (n33 = (n34 = (n35 = 0)))))))))))))))))))))))))))))))));
        String s = "\u0001[zdZ\u0012Lim";
        int n36 = -1;
        String intern = null;
    Label_0401_Outer:
        while (true) {
            final char[] charArray = s.toCharArray();
            int length;
            int n38;
            final int n37 = n38 = (length = charArray.length);
            int n39 = 0;
            while (true) {
                Label_0478: {
                    if (n37 > 1) {
                        break Label_0478;
                    }
                    length = (n38 = n39);
                    do {
                        final char c = charArray[n38];
                        char c2 = '\0';
                        switch (n39 % 5) {
                            case 0: {
                                c2 = '\u0011';
                                break;
                            }
                            case 1: {
                                c2 = 'W';
                                break;
                            }
                            case 2: {
                                c2 = 'h';
                                break;
                            }
                            case 3: {
                                c2 = 'j';
                                break;
                            }
                            default: {
                                c2 = 'V';
                                break;
                            }
                        }
                        charArray[length] = (char)(c ^ c2);
                        ++n39;
                    } while (n37 == 0);
                }
                if (n37 > n39) {
                    continue;
                }
                break;
            }
            intern = new String(charArray).intern();
            switch (n36) {
                default: {
                    z2[n2] = intern;
                    n = (n2 = (n3 = (n4 = (n5 = (n6 = (n7 = (n8 = (n9 = (n10 = (n11 = (n12 = (n13 = (n14 = (n15 = (n16 = (n17 = (n18 = (n19 = (n20 = (n21 = (n22 = (n23 = (n24 = (n25 = (n26 = (n27 = (n28 = (n29 = (n30 = (n31 = (n32 = (n33 = (n34 = (n35 = 1))))))))))))))))))))))))))))))))));
                    s = "\u000e\u0012[#";
                    n36 = 0;
                    continue Label_0401_Outer;
                }
                case 0: {
                    z2[n] = intern;
                    n = (n2 = (n3 = (n4 = (n5 = (n6 = (n7 = (n8 = (n9 = (n10 = (n11 = (n12 = (n13 = (n14 = (n15 = (n16 = (n17 = (n18 = (n19 = (n20 = (n21 = (n22 = (n23 = (n24 = (n25 = (n26 = (n27 = (n28 = (n29 = (n30 = (n31 = (n32 = (n33 = (n34 = (n35 = 2))))))))))))))))))))))))))))))))));
                    s = "\u0014\\|kW\u0011";
                    n36 = 1;
                    continue Label_0401_Outer;
                }
                case 1: {
                    z2[n3] = intern;
                    n = (n2 = (n3 = (n4 = (n5 = (n6 = (n7 = (n8 = (n9 = (n10 = (n11 = (n12 = (n13 = (n14 = (n15 = (n16 = (n17 = (n18 = (n19 = (n20 = (n21 = (n22 = (n23 = (n24 = (n25 = (n26 = (n27 = (n28 = (n29 = (n30 = (n31 = (n32 = (n33 = (n34 = (n35 = 3))))))))))))))))))))))))))))))))));
                    s = "\u000e\u0012F%m_";
                    n36 = 2;
                    continue Label_0401_Outer;
                }
                case 2: {
                    z2[n4] = intern;
                    n = (n2 = (n3 = (n4 = (n5 = (n6 = (n7 = (n8 = (n9 = (n10 = (n11 = (n12 = (n13 = (n14 = (n15 = (n16 = (n17 = (n18 = (n19 = (n20 = (n21 = (n22 = (n23 = (n24 = (n25 = (n26 = (n27 = (n28 = (n29 = (n30 = (n31 = (n32 = (n33 = (n34 = (n35 = 4))))))))))))))))))))))))))))))))));
                    s = "\u001dKovC\u0016";
                    n36 = 3;
                    continue Label_0401_Outer;
                }
                case 3: {
                    z2[n5] = intern;
                    n = (n2 = (n3 = (n4 = (n5 = (n6 = (n7 = (n8 = (n9 = (n10 = (n11 = (n12 = (n13 = (n14 = (n15 = (n16 = (n17 = (n18 = (n19 = (n20 = (n21 = (n22 = (n23 = (n24 = (n25 = (n26 = (n27 = (n28 = (n29 = (n30 = (n31 = (n32 = (n33 = (n34 = (n35 = 5))))))))))))))))))))))))))))))))));
                    s = "\b\u0005_5mX";
                    n36 = 4;
                    continue Label_0401_Outer;
                }
                case 4: {
                    z2[n6] = intern;
                    n = (n2 = (n3 = (n4 = (n5 = (n6 = (n7 = (n8 = (n9 = (n10 = (n11 = (n12 = (n13 = (n14 = (n15 = (n16 = (n17 = (n18 = (n19 = (n20 = (n21 = (n22 = (n23 = (n24 = (n25 = (n26 = (n27 = (n28 = (n29 = (n30 = (n31 = (n32 = (n33 = (n34 = (n35 = 6))))))))))))))))))))))))))))))))));
                    s = "\fXocF\u0014FgxD\u0006";
                    n36 = 5;
                    continue Label_0401_Outer;
                }
                case 5: {
                    z2[n7] = intern;
                    n = (n2 = (n3 = (n4 = (n5 = (n6 = (n7 = (n8 = (n9 = (n10 = (n11 = (n12 = (n13 = (n14 = (n15 = (n16 = (n17 = (n18 = (n19 = (n20 = (n21 = (n22 = (n23 = (n24 = (n25 = (n26 = (n27 = (n28 = (n29 = (n30 = (n31 = (n32 = (n33 = (n34 = (n35 = 7))))))))))))))))))))))))))))))))));
                    s = "\u0010P|xU\t";
                    n36 = 6;
                    continue Label_0401_Outer;
                }
                case 6: {
                    z2[n8] = intern;
                    n = (n2 = (n3 = (n4 = (n5 = (n6 = (n7 = (n8 = (n9 = (n10 = (n11 = (n12 = (n13 = (n14 = (n15 = (n16 = (n17 = (n18 = (n19 = (n20 = (n21 = (n22 = (n23 = (n24 = (n25 = (n26 = (n27 = (n28 = (n29 = (n30 = (n31 = (n32 = (n33 = (n34 = (n35 = 8))))))))))))))))))))))))))))))))));
                    s = "\u0005%|\u0012";
                    n36 = 7;
                    continue Label_0401_Outer;
                }
                case 7: {
                    z2[n9] = intern;
                    n = (n2 = (n3 = (n4 = (n5 = (n6 = (n7 = (n8 = (n9 = (n10 = (n11 = (n12 = (n13 = (n14 = (n15 = (n16 = (n17 = (n18 = (n19 = (n20 = (n21 = (n22 = (n23 = (n24 = (n25 = (n26 = (n27 = (n28 = (n29 = (n30 = (n31 = (n32 = (n33 = (n34 = (n35 = 9))))))))))))))))))))))))))))))))));
                    s = "\u007fy4D\u0018";
                    n36 = 8;
                    continue Label_0401_Outer;
                }
                case 8: {
                    z2[n10] = intern;
                    n = (n2 = (n3 = (n4 = (n5 = (n6 = (n7 = (n8 = (n9 = (n10 = (n11 = (n12 = (n13 = (n14 = (n15 = (n16 = (n17 = (n18 = (n19 = (n20 = (n21 = (n22 = (n23 = (n24 = (n25 = (n26 = (n27 = (n28 = (n29 = (n30 = (n31 = (n32 = (n33 = (n34 = (n35 = 10))))))))))))))))))))))))))))))))));
                    s = "\u0012Ke{W\u0016HziD\u0015Ae`";
                    n36 = 9;
                    continue Label_0401_Outer;
                }
                case 9: {
                    z2[n11] = intern;
                    n = (n2 = (n3 = (n4 = (n5 = (n6 = (n7 = (n8 = (n9 = (n10 = (n11 = (n12 = (n13 = (n14 = (n15 = (n16 = (n17 = (n18 = (n19 = (n20 = (n21 = (n22 = (n23 = (n24 = (n25 = (n26 = (n27 = (n28 = (n29 = (n30 = (n31 = (n32 = (n33 = (n34 = (n35 = 11))))))))))))))))))))))))))))))))));
                    s = "\rGocJ\u001fW";
                    n36 = 10;
                    continue Label_0401_Outer;
                }
                case 10: {
                    z2[n12] = intern;
                    n = (n2 = (n3 = (n4 = (n5 = (n6 = (n7 = (n8 = (n9 = (n10 = (n11 = (n12 = (n13 = (n14 = (n15 = (n16 = (n17 = (n18 = (n19 = (n20 = (n21 = (n22 = (n23 = (n24 = (n25 = (n26 = (n27 = (n28 = (n29 = (n30 = (n31 = (n32 = (n33 = (n34 = (n35 = 12))))))))))))))))))))))))))))))))));
                    s = "\r\u0018[2bH~us\u0003*\u001e";
                    n36 = 11;
                    continue Label_0401_Outer;
                }
                case 11: {
                    z2[n13] = intern;
                    n = (n2 = (n3 = (n4 = (n5 = (n6 = (n7 = (n8 = (n9 = (n10 = (n11 = (n12 = (n13 = (n14 = (n15 = (n16 = (n17 = (n18 = (n19 = (n20 = (n21 = (n22 = (n23 = (n24 = (n25 = (n26 = (n27 = (n28 = (n29 = (n30 = (n31 = (n32 = (n33 = (n34 = (n35 = 13))))))))))))))))))))))))))))))))));
                    s = "\u0010Fau_\u0016NdhJ\u001eO";
                    n36 = 12;
                    continue Label_0401_Outer;
                }
                case 12: {
                    z2[n14] = intern;
                    n = (n2 = (n3 = (n4 = (n5 = (n6 = (n7 = (n8 = (n9 = (n10 = (n11 = (n12 = (n13 = (n14 = (n15 = (n16 = (n17 = (n18 = (n19 = (n20 = (n21 = (n22 = (n23 = (n24 = (n25 = (n26 = (n27 = (n28 = (n29 = (n30 = (n31 = (n32 = (n33 = (n34 = (n35 = 14))))))))))))))))))))))))))))))))));
                    s = "\u000fBhcF";
                    n36 = 13;
                    continue Label_0401_Outer;
                }
                case 13: {
                    z2[n15] = intern;
                    n = (n2 = (n3 = (n4 = (n5 = (n6 = (n7 = (n8 = (n9 = (n10 = (n11 = (n12 = (n13 = (n14 = (n15 = (n16 = (n17 = (n18 = (n19 = (n20 = (n21 = (n22 = (n23 = (n24 = (n25 = (n26 = (n27 = (n28 = (n29 = (n30 = (n31 = (n32 = (n33 = (n34 = (n35 = 15))))))))))))))))))))))))))))))))));
                    s = "\u0011Cz~V";
                    n36 = 14;
                    continue Label_0401_Outer;
                }
                case 14: {
                    z2[n16] = intern;
                    n = (n2 = (n3 = (n4 = (n5 = (n6 = (n7 = (n8 = (n9 = (n10 = (n11 = (n12 = (n13 = (n14 = (n15 = (n16 = (n17 = (n18 = (n19 = (n20 = (n21 = (n22 = (n23 = (n24 = (n25 = (n26 = (n27 = (n28 = (n29 = (n30 = (n31 = (n32 = (n33 = (n34 = (n35 = 16))))))))))))))))))))))))))))))))));
                    s = "c}!Y\u0004%\u0019";
                    n36 = 15;
                    continue Label_0401_Outer;
                }
                case 15: {
                    z2[n17] = intern;
                    n = (n2 = (n3 = (n4 = (n5 = (n6 = (n7 = (n8 = (n9 = (n10 = (n11 = (n12 = (n13 = (n14 = (n15 = (n16 = (n17 = (n18 = (n19 = (n20 = (n21 = (n22 = (n23 = (n24 = (n25 = (n26 = (n27 = (n28 = (n29 = (n30 = (n31 = (n32 = (n33 = (n34 = (n35 = 17))))))))))))))))))))))))))))))))));
                    s = "\fXooV";
                    n36 = 16;
                    continue Label_0401_Outer;
                }
                case 16: {
                    z2[n18] = intern;
                    n = (n2 = (n3 = (n4 = (n5 = (n6 = (n7 = (n8 = (n9 = (n10 = (n11 = (n12 = (n13 = (n14 = (n15 = (n16 = (n17 = (n18 = (n19 = (n20 = (n21 = (n22 = (n23 = (n24 = (n25 = (n26 = (n27 = (n28 = (n29 = (n30 = (n31 = (n32 = (n33 = (n34 = (n35 = 18))))))))))))))))))))))))))))))))));
                    s = "bb!U\u0018";
                    n36 = 17;
                    continue Label_0401_Outer;
                }
                case 17: {
                    z2[n19] = intern;
                    n = (n2 = (n3 = (n4 = (n5 = (n6 = (n7 = (n8 = (n9 = (n10 = (n11 = (n12 = (n13 = (n14 = (n15 = (n16 = (n17 = (n18 = (n19 = (n20 = (n21 = (n22 = (n23 = (n24 = (n25 = (n26 = (n27 = (n28 = (n29 = (n30 = (n31 = (n32 = (n33 = (n34 = (n35 = 19))))))))))))))))))))))))))))))))));
                    s = "\u000bYmoK\u0005Kz`";
                    n36 = 18;
                    continue Label_0401_Outer;
                }
                case 18: {
                    z2[n20] = intern;
                    n = (n2 = (n3 = (n4 = (n5 = (n6 = (n7 = (n8 = (n9 = (n10 = (n11 = (n12 = (n13 = (n14 = (n15 = (n16 = (n17 = (n18 = (n19 = (n20 = (n21 = (n22 = (n23 = (n24 = (n25 = (n26 = (n27 = (n28 = (n29 = (n30 = (n31 = (n32 = (n33 = (n34 = (n35 = 20))))))))))))))))))))))))))))))))));
                    s = "|\u007f4I\u000e9J~>\u007fX";
                    n36 = 19;
                    continue Label_0401_Outer;
                }
                case 19: {
                    z2[n21] = intern;
                    n = (n2 = (n3 = (n4 = (n5 = (n6 = (n7 = (n8 = (n9 = (n10 = (n11 = (n12 = (n13 = (n14 = (n15 = (n16 = (n17 = (n18 = (n19 = (n20 = (n21 = (n22 = (n23 = (n24 = (n25 = (n26 = (n27 = (n28 = (n29 = (n30 = (n31 = (n32 = (n33 = (n34 = (n35 = 21))))))))))))))))))))))))))))))))));
                    s = "\n\b[;eXtur\u0004$\u0001";
                    n36 = 20;
                    continue Label_0401_Outer;
                }
                case 20: {
                    z2[n22] = intern;
                    n = (n2 = (n3 = (n4 = (n5 = (n6 = (n7 = (n8 = (n9 = (n10 = (n11 = (n12 = (n13 = (n14 = (n15 = (n16 = (n17 = (n18 = (n19 = (n20 = (n21 = (n22 = (n23 = (n24 = (n25 = (n26 = (n27 = (n28 = (n29 = (n30 = (n31 = (n32 = (n33 = (n34 = (n35 = 22))))))))))))))))))))))))))))))))));
                    s = "\u000e\u0007]#i_";
                    n36 = 21;
                    continue Label_0401_Outer;
                }
                case 21: {
                    z2[n23] = intern;
                    n = (n2 = (n3 = (n4 = (n5 = (n6 = (n7 = (n8 = (n9 = (n10 = (n11 = (n12 = (n13 = (n14 = (n15 = (n16 = (n17 = (n18 = (n19 = (n20 = (n21 = (n22 = (n23 = (n24 = (n25 = (n26 = (n27 = (n28 = (n29 = (n30 = (n31 = (n32 = (n33 = (n34 = (n35 = 23))))))))))))))))))))))))))))))))));
                    s = "\b\u0005_5mX-\u0014S\n/\u000f_.";
                    n36 = 22;
                    continue Label_0401_Outer;
                }
                case 22: {
                    z2[n24] = intern;
                    n = (n2 = (n3 = (n4 = (n5 = (n6 = (n7 = (n8 = (n9 = (n10 = (n11 = (n12 = (n13 = (n14 = (n15 = (n16 = (n17 = (n18 = (n19 = (n20 = (n21 = (n22 = (n23 = (n24 = (n25 = (n26 = (n27 = (n28 = (n29 = (n30 = (n31 = (n32 = (n33 = (n34 = (n35 = 24))))))))))))))))))))))))))))))))));
                    s = "ec#U\u0005?\u0005@.";
                    n36 = 23;
                    continue Label_0401_Outer;
                }
                case 23: {
                    z2[n25] = intern;
                    n = (n2 = (n3 = (n4 = (n5 = (n6 = (n7 = (n8 = (n9 = (n10 = (n11 = (n12 = (n13 = (n14 = (n15 = (n16 = (n17 = (n18 = (n19 = (n20 = (n21 = (n22 = (n23 = (n24 = (n25 = (n26 = (n27 = (n28 = (n29 = (n30 = (n31 = (n32 = (n33 = (n34 = (n35 = 25))))))))))))))))))))))))))))))))));
                    s = "\u0007FncU\u001cAfm";
                    n36 = 24;
                    continue Label_0401_Outer;
                }
                case 24: {
                    z2[n26] = intern;
                    n = (n2 = (n3 = (n4 = (n5 = (n6 = (n7 = (n8 = (n9 = (n10 = (n11 = (n12 = (n13 = (n14 = (n15 = (n16 = (n17 = (n18 = (n19 = (n20 = (n21 = (n22 = (n23 = (n24 = (n25 = (n26 = (n27 = (n28 = (n29 = (n30 = (n31 = (n32 = (n33 = (n34 = (n35 = 26))))))))))))))))))))))))))))))))));
                    s = "\u0001Vi`S\u0010";
                    n36 = 25;
                    continue Label_0401_Outer;
                }
                case 25: {
                    z2[n27] = intern;
                    n = (n2 = (n3 = (n4 = (n5 = (n6 = (n7 = (n8 = (n9 = (n10 = (n11 = (n12 = (n13 = (n14 = (n15 = (n16 = (n17 = (n18 = (n19 = (n20 = (n21 = (n22 = (n23 = (n24 = (n25 = (n26 = (n27 = (n28 = (n29 = (n30 = (n31 = (n32 = (n33 = (n34 = (n35 = 27))))))))))))))))))))))))))))))))));
                    s = "bb!Y\b.\b]6~H";
                    n36 = 26;
                    continue Label_0401_Outer;
                }
                case 26: {
                    z2[n28] = intern;
                    n = (n2 = (n3 = (n4 = (n5 = (n6 = (n7 = (n8 = (n9 = (n10 = (n11 = (n12 = (n13 = (n14 = (n15 = (n16 = (n17 = (n18 = (n19 = (n20 = (n21 = (n22 = (n23 = (n24 = (n25 = (n26 = (n27 = (n28 = (n29 = (n30 = (n31 = (n32 = (n33 = (n34 = (n35 = 28))))))))))))))))))))))))))))))))));
                    s = "\u0006\u001fA>o\f]9Q\u0012.\u0018";
                    n36 = 27;
                    continue Label_0401_Outer;
                }
                case 27: {
                    z2[n29] = intern;
                    n = (n2 = (n3 = (n4 = (n5 = (n6 = (n7 = (n8 = (n9 = (n10 = (n11 = (n12 = (n13 = (n14 = (n15 = (n16 = (n17 = (n18 = (n19 = (n20 = (n21 = (n22 = (n23 = (n24 = (n25 = (n26 = (n27 = (n28 = (n29 = (n30 = (n31 = (n32 = (n33 = (n34 = (n35 = 29))))))))))))))))))))))))))))))))));
                    s = "oa4^K\b\u0002S#";
                    n36 = 28;
                    continue Label_0401_Outer;
                }
                case 28: {
                    z2[n30] = intern;
                    n = (n2 = (n3 = (n4 = (n5 = (n6 = (n7 = (n8 = (n9 = (n10 = (n11 = (n12 = (n13 = (n14 = (n15 = (n16 = (n17 = (n18 = (n19 = (n20 = (n21 = (n22 = (n23 = (n24 = (n25 = (n26 = (n27 = (n28 = (n29 = (n30 = (n31 = (n32 = (n33 = (n34 = (n35 = 30))))))))))))))))))))))))))))))))));
                    s = "\u0017Va|X\u0006DdiM\u0010P";
                    n36 = 29;
                    continue Label_0401_Outer;
                }
                case 29: {
                    z2[n31] = intern;
                    n = (n2 = (n3 = (n4 = (n5 = (n6 = (n7 = (n8 = (n9 = (n10 = (n11 = (n12 = (n13 = (n14 = (n15 = (n16 = (n17 = (n18 = (n19 = (n20 = (n21 = (n22 = (n23 = (n24 = (n25 = (n26 = (n27 = (n28 = (n29 = (n30 = (n31 = (n32 = (n33 = (n34 = (n35 = 31))))))))))))))))))))))))))))))))));
                    s = "\r\u0018[2bH~u|\u00028\u001e";
                    n36 = 30;
                    continue Label_0401_Outer;
                }
                case 30: {
                    z2[n32] = intern;
                    n = (n2 = (n3 = (n4 = (n5 = (n6 = (n7 = (n8 = (n9 = (n10 = (n11 = (n12 = (n13 = (n14 = (n15 = (n16 = (n17 = (n18 = (n19 = (n20 = (n21 = (n22 = (n23 = (n24 = (n25 = (n26 = (n27 = (n28 = (n29 = (n30 = (n31 = (n32 = (n33 = (n34 = (n35 = 32))))))))))))))))))))))))))))))))));
                    s = "\u001c\u0005@9,i| Y\u001b&\u000f\\#";
                    n36 = 31;
                    continue Label_0401_Outer;
                }
                case 31: {
                    z2[n33] = intern;
                    n = (n2 = (n3 = (n4 = (n5 = (n6 = (n7 = (n8 = (n9 = (n10 = (n11 = (n12 = (n13 = (n14 = (n15 = (n16 = (n17 = (n18 = (n19 = (n20 = (n21 = (n22 = (n23 = (n24 = (n25 = (n26 = (n27 = (n28 = (n29 = (n30 = (n31 = (n32 = (n33 = (n34 = (n35 = 33))))))))))))))))))))))))))))))))));
                    s = "\u0014IgmS\u0011";
                    n36 = 32;
                    continue Label_0401_Outer;
                }
                case 32: {
                    z2[n34] = intern;
                    n = (n2 = (n3 = (n4 = (n5 = (n6 = (n7 = (n8 = (n9 = (n10 = (n11 = (n12 = (n13 = (n14 = (n15 = (n16 = (n17 = (n18 = (n19 = (n20 = (n21 = (n22 = (n23 = (n24 = (n25 = (n26 = (n27 = (n28 = (n29 = (n30 = (n31 = (n32 = (n33 = (n34 = (n35 = 34))))))))))))))))))))))))))))))))));
                    s = "\u0004EroK\u0015W";
                    n36 = 33;
                    continue Label_0401_Outer;
                }
                case 33: {
                    break Label_0401_Outer;
                }
            }
        }
        z2[n35] = intern;
        z = z2;
    }
}
